Workbook
Name _ftn1: Glossary!$B$9
Name _ftnref3: Glossary!$C$6

Sheet Overview of Framework
B2: Introduction to the Equality, Diversity and Inclusion Toolkit
B4: Background | C4: Big Issue Invest, Social Value UK, and UnLtd have partnered to develop a Equality, Diversity and Inclusion (EDI) Toolkit to support social purpose organisations (SPOs). The Toolkit project aims to contribute to a society where social purpose organisations pioneer inclusive, diverse and equitable practice. By identifying barriers to inclusion, and building a framework for organisational learning and development the toolkit develops actionable steps for organisations unlock the tangible changes needed to dismantle systemic inequality.
B6: Structure | C6: The EDI Toolkit is structured by the 10 EDI factors (Sections) identified through the EDI Literature Review. The factors are then broken down into parts which form the basis for each of the criteria points. For each part, there are 3 levels that an SPO can work to progress through as their EDI practice develops. The Toolkit should therefore offer a progressive pathway for organisations to be able to follow as a guide for their next steps in developing and embedding EDI practice into their organisations.
B7: Using the Toolkit
B8: Section introductions | C8: The background and reference reading for each section are located at the top of each page.
B9: Filling in the sections | C9: After reading the background and relevant reading, please fill in Sections 1 to 10 with the answer most relevant to your organisation using the drop down options for each part. Your EDI summary is calculated in the final sheet 'EDI Score Outcomes'. There is a glossary at the end and reference links in each section to guide you through the content. For each drop down selected, fill out the 'What we have done' box on the right hand side of the selection. In this space briefly describe the evidence of this action if relevant. Evidence can come in many formats including emails, policies, or website blogs. For certain parts, guidance has been provided to the right of the 'What we have done box' to add extra context to the statement. A 'Notes' box exists in each part for organisations to track any extra information or make comments for other staff members where needed. There is no requirement to add notes.
B10: Toolkit reviews | C10: The Toolkit has been created as a live document. By evidencing the actions taken your organisation and stakeholders can track progress made over time. Suggested intervals for updating the toolkit are annual or biannual, depending on organisation preference. When used during an investment process, an annual review of progress is suggested.
B11: Developed by | C11: SVUK, UnLtd and BII
B12: Version date | C12: 44958
B13: The Diversity, Equality and Inclusion Toolkit (“DEIT”) © 2022 by The Foundation for Social Entrepreneurs trading as UnLtd (UK Company number 4180639 - unltd.org.uk) is licensed under the Creative Commons Attribution 4.0 International licence, but subject to an additional licence condition/restriction that licensees may not charge for delivery or licensing of the DEIT.

Sheet Section 1
B2: Section 1
B3: ='EDI Framework Criteria'!A2 -> Understanding EDI Concepts: Knowledge of EDI concepts and frameworks | U3: Our organisation has committed to this | V3: 2
U4: In progress | V4: 1
B5: Background information | U5: Our organisation has not yet committed to this | V5: 0
B6: This section covers your organisation's formal training on the concepts of Equality, Diversity and Inclusion (EDI) and what efforts are made to increase the understanding of these concepts. Training on these concepts provides a foundation for other areas of EDI work as it ensures all members of an organisation have a level of exposure to core EDI areas.
U7: Our organisation has implemented this | V7: 2
B8: Useful resources (select the + button on the left hand side of the screen to expand) | U8: In progress | V8: 1
B9: Resource name | D9: Description | O9: URL | U9: Our organisation has not yet implemented this | V9: 0
B10: A Phenomenological Study of “Organizational Development Targeting Diversity” in a Nonprofit Human Service OrganizationTargeting Diversity” in a Nonprofit Human Service Organization | D10: "This study explores the experiences of non-profit human service staff members engaged in “organizational development targeting diversity” (ODTD) for two years or more. This term was adapted by combining concepts in workforce diversity management (Cox, 1993; Ely & Thomas, 1996) and intra-organizational oppression (Fine, 1996; Hyde, 1998). Drawing upon Crenshaw’s (1989) theory of intersecting oppressions stemming from race, class, and gender stratification, the experiences of staff members in a nonprofit human services organization provided a window into an organization attempting to address its use of power and how to model empowerment for a disempowered clientele. This study was conducted using interviews, documents, and field notes in a phenomenological design. It was found that perceptions of power sharing within the organizational setting are shaped by participant identities. It is recommended that organizational diversity efforts openly address issues of power and strive to understand member perspectives for organizational practices and policy formation." | O10: https://fisherpub.sjfc.edu/cgi/viewcontent.cgi?article=1006&context=education_etd
B11: Ladder of Empowerment | D11: "Proposed by Elizabeth Rocha in the Journal of Planning Education and Research in 1997, the Ladder of Empowerment represents one of the first models that conceptualized individual and collective forms of empowerment. While earlier models described the dynamics of power or participation, Rocha’s Ladder addresses building power—i.e., the interrelationship of individual and collective participation and power—and the conditions that contribute to (or undermine) power building. Rocha’s Ladder of Empowerment follows several related models, including Sherry Arnstein’s Ladder of Citizen Participation and Roger Hart’s Ladder of Children’s Participation." | O11: https://organizingengagement.org/models/ladder-of-empowerment/ | U11: Our organisation has embedded this | V11: 2
B12: Ladder of Citizen Participation | D12: "Proposed by Sherry Arnstein in 1969, the Ladder of Citizen Participation is one of the most widely referenced and influential models in the field of democratic public participation. For local leaders, organizers, and facilitators who want to understand foundational theories of public engagement and participation, and the ways in which empowered public institutions and officials deny power to citizens, Arnstein’s seminal article is essential reading. The model also influenced many later models, including Elizabeth Rocha’s Ladder of Empowerment and Roger Hart’s Ladder of Children’s Participation." | O12: https://organizingengagement.org/models/ladder-of-citizen-participation/ | U12: In progress | V12: 1
B13: Home Truths: Undoing racism and delivering real diversity in the charity sector | D13: "Home Truths is not a report that asks if there is a problem with ‘race’ equity in the charity sector. It has long been known that there is an under-representation of BAME people working in the charity sector, and that under-representation is worse in senior leadership roles. Instead, in this report we have sought to reframe the ‘diversity’ debate, saying that racism is a significant and unresolved issue in the charity sector just as it is in the rest of society." | O13: https://www.acevo.org.uk/reports/home-truths/ | U13: Our organisation has not yet embedded this | V13: 0
B17: Part 1 | D17: ='EDI Framework Criteria'!B2 -> Equality, Diversity, & Inclusion Characteristics (Equality Act and beyond)
I19: Our organisation has- please select the appropriate dropdown option | J19: What we have done - please clearly state what your organisation has done | K19: Score | L19: Guidance for these statements | V19: Non commitment
B20: Level 1 | C20: ='EDI Framework Criteria'!C2 -> 1.A.1 | D20: ='EDI Framework Criteria'!D2 -> We have committed to having a training plan for staff at all levels, including board which includes material on what is meant by "EDI Characteristics". These go beyond the 9 protected characteristics in the Equalities Act (2010). It includes characteristics like class and neurodivergence too. | I20: Our organisation has not yet committed to this | K20: =INDEX($U$3:$V$13,MATCH(I20,$U$3:$U$13,0),2) -> 0 | V20: =IF(K20=0,V19,"") -> Non commitment
B22: Level 2 | C22: ='EDI Framework Criteria'!E2 -> 2.A.1 | D22: ='EDI Framework Criteria'!F2 -> We have a training plan for staff at all levels, including board. It explains EDI characteristics. These go beyond the 9 protected characteristics in the Equalities Act (2010). It includes characteristics like class and neurodivergence too. We have started to deliver training. | I22: Our organisation has not yet implemented this | K22: =INDEX($U$3:$V$13,MATCH(I22,$U$3:$U$13,0),2) -> 0
B24: Level 3 | C24: ='EDI Framework Criteria'!G2 -> 3.A.1 | D24: ='EDI Framework Criteria'!H2 -> We have a training plan for staff at all levels, including board. It explains EDI characteristics. These go beyond the 9 protected characteristics in the Equalities Act (2010). It includes characteristics like class and neurodivergence too. The training plan has been reviewed at least once. There are plans to review it as needed. Training is given to staff at all levels. | I24: Our organisation has not yet embedded this | K24: =INDEX($U$3:$V$13,MATCH(I24,$U$3:$U$13,0),2) -> 0
B27: Part 2 | D27: ='EDI Framework Criteria'!B3 -> Understanding organisational power
I29: Our organisation has- please select the appropriate dropdown option | J29: What we have done - please clearly state what your organisation has done | L29: Guidance for these statements
B30: Level 1 | C30: ='EDI Framework Criteria'!C3 -> 1.A.2 | D30: ='EDI Framework Criteria'!D3 -> We have committed to having a training plan for staff at all levels, including board. It explains what ‘organisational power’ means. | I30: Our organisation has not yet committed to this | K30: =INDEX($U$3:$V$13,MATCH(I30,$U$3:$U$13,0),2) -> 0 | V30: =IF(K30=0,V29,"") -> 0
B32: Level 2 | C32: ='EDI Framework Criteria'!E3 -> 2.A.2 | D32: ='EDI Framework Criteria'!F3 -> We have a training plan for staff at all levels, including board. It explains what ‘organisational power’ means. We’ve started some training activities. | I32: Our organisation has not yet implemented this | K32: =INDEX($U$3:$V$13,MATCH(I32,$U$3:$U$13,0),2) -> 0
B34: Level 3 | C34: ='EDI Framework Criteria'!G3 -> 3.A.2 | D34: ='EDI Framework Criteria'!H3 -> We have a training plan for staff at all levels, including board. It explains what ‘organisational power’ means. The training plan has been reviewed at least once. There are plans to review it as needed. Training is given to staff at all levels. | I34: Our organisation has not yet embedded this | K34: =INDEX($U$3:$V$13,MATCH(I34,$U$3:$U$13,0),2) -> 0
B37: Part 3 | D37: ='EDI Framework Criteria'!B4 -> Tackling organisational barriers to Equality, Diversity and Inclusion
I39: Our organisation has- please select the appropriate dropdown option | J39: What we have done - please clearly state what your organisation has done | L39: Guidance for these statements
B40: Level 1 | C40: ='EDI Framework Criteria'!C4 -> 1.A.3 | D40: ='EDI Framework Criteria'!D4 -> We have committed to having a training plan for staff at all levels, including board. It explains what ‘organisational barriers to EDI’ means. | I40: Our organisation has not yet committed to this | K40: =INDEX($U$3:$V$13,MATCH(I40,$U$3:$U$13,0),2) -> 0 | V40: =IF(K40=0,V39,"") -> 0
B42: Level 2 | C42: ='EDI Framework Criteria'!E4 -> 2.A.3 | D42: ='EDI Framework Criteria'!F4 -> We have a training plan for staff at all levels, including board. It explains what ‘organisational barriers to EDI’ means. We’ve started some training activities. | I42: Our organisation has not yet implemented this | K42: =INDEX($U$3:$V$13,MATCH(I42,$U$3:$U$13,0),2) -> 0
B44: Level 3 | C44: ='EDI Framework Criteria'!G4 -> 3.A.3 | D44: ='EDI Framework Criteria'!H4 -> We have a training plan for staff at all levels, including board. It explains what ‘organisational barriers to EDI’ means. The training plan has been reviewed at least once. There are plans to review it as needed. Training is given to staff at all levels. | I44: Our organisation has not yet embedded this | K44: =INDEX($U$3:$V$13,MATCH(I44,$U$3:$U$13,0),2) -> 0
B47: Part 4 | D47: ='EDI Framework Criteria'!B5 -> Our role in structural discrimination
I48: Our organisation has- please select the appropriate dropdown option | J48: What we have done - please clearly state what your organisation has done | L48: Guidance for these statements
B49: Level 1 | C49: ='EDI Framework Criteria'!C5 -> 1.A.4 | D49: ='EDI Framework Criteria'!D5 -> We have committed to having a training plan for staff at all levels, including board. It explains what is meant by 'structural discrimination'. | I49: Our organisation has not yet committed to this | K49: =INDEX($U$3:$V$13,MATCH(I49,$U$3:$U$13,0),2) -> 0 | V49: =IF(K49=0,V48,"") -> 0
B51: Level 2 | C51: ='EDI Framework Criteria'!E5 -> 2.A.4 | D51: ='EDI Framework Criteria'!F5 -> We have a training plan for staff at all levels, including board. It explains what is meant by 'structural discrimination'. We’ve started some training activities. | I51: Our organisation has not yet implemented this | K51: =INDEX($U$3:$V$13,MATCH(I51,$U$3:$U$13,0),2) -> 0
B53: Level 3 | C53: ='EDI Framework Criteria'!G5 -> 3.A.4 | D53: ='EDI Framework Criteria'!H5 -> We have a training plan for staff at all levels, including board. It explains what is meant by 'structural discrimination'. The training plan has been reviewed at least once. There are plans to review it as needed. Training is given to staff at all levels. | I53: Our organisation has not yet embedded this | K53: =INDEX($U$3:$V$13,MATCH(I53,$U$3:$U$13,0),2) -> 0
B56: Part 5 | D56: ='EDI Framework Criteria'!B6 -> Intersectionality
I57: Our organisation has- please select the appropriate dropdown option | J57: What we have done - please clearly state what your organisation has done | L57: Guidance for these statements
B58: Level 1 | C58: ='EDI Framework Criteria'!C6 -> 1.A.5 | D58: ='EDI Framework Criteria'!D6 -> We have a training plan for staff at all levels, including board. It explains what ‘intersectionality’ means. | I58: Our organisation has not yet committed to this | K58: =INDEX($U$3:$V$13,MATCH(I58,$U$3:$U$13,0),2) -> 0 | V58: =IF(K58=0,V57,"") -> 0
B60: Level 2 | C60: ='EDI Framework Criteria'!E6 -> 2.A.5 | D60: ='EDI Framework Criteria'!F6 -> We have a training plan for staff at all levels, including board. It explains what ‘intersectionality’ means. We’ve started some training activities. | I60: Our organisation has not yet implemented this | K60: =INDEX($U$3:$V$13,MATCH(I60,$U$3:$U$13,0),2) -> 0
B62: Level 3 | C62: ='EDI Framework Criteria'!G6 -> 3.A.5 | D62: ='EDI Framework Criteria'!H6 -> We have a training plan for staff at all levels, including board. It explains what ‘intersectionality’ means. The training plan has been reviewed at least once. There are plans to review it as needed. Training is given to staff at all levels. | I62: Our organisation has not yet embedded this | K62: =INDEX($U$3:$V$13,MATCH(I62,$U$3:$U$13,0),2) -> 0
B66: Return to overview | D66: Next section

Sheet Section 2
V1: Macro Coding
B2: Section 2 | V2: =#REF! -> #REF! | W2: =#REF! -> #REF! | X2: =#REF! -> #REF! | Y2: =#REF! -> #REF!
B3: ='EDI Framework Criteria'!A7 -> Mission and Policies | U3: Our organisation has committed to this | V3: 2
U4: In progress | V4: 1
B5: Background information | U5: Our organisation has not yet committed to this | V5: 0
B6: This section covers how your organisation outlines your commitment to Equality, Diversity and Inclusion in your mission statement. This should be created alongside people with relevant lived experiences, and where possible the mission statement should be public. Missions and policies support organisations by committing them to action in EDI both internally and externally. They also ensure all staff are aware of the EDI aims the organisation has committed to in addition to necessary resourcing and accountability for EDI work.
U7: Our organisation has implemented this | V7: 2
B8: Useful resources (select the + button on the left hand side of the screen to expand) | U8: In progress | V8: 1
B9: Resource name | D9: Description | O9: URL | U9: Our organisation has not yet implemented this | V9: 0
B10: feministkilljoys killing joy as a world making project | D10: Link provided by Anita B | O10: https://feministkilljoys.com
B11: Act Boldly - Anti-racist principles, guidance & toolkit | D11: "This guide is primarily for people with leadership responsibilities at Wellcome, including the ELT, Senior Leadership Team, Board of Governors, and funding committee chairs. While everyone at Wellcome is responsible for anti-racism in their everyday work, those in power are accountable for meeting our anti-racism commitments and for following these five anti-racist principles. Wellcome has developed this resource to help us achieve racial equity in our organisation and work. This is not legal advice, it is a framework for how to be anti-racist at Wellcome." | O11: https://cms.wellcome.org/sites/default/files/2021-06/Wellcomes-Anti-racist-principles-and-toolkit-2021.pdf | U11: Our organisation has embedded this | V11: 2
B12: The Case for Capitalizing the B in Black | D12: Link provided by Fearless Futures | O12: https://www.theatlantic.com/ideas/archive/2020/06/time-to-capitalize-blackand-white/613159/ | U12: In progress | V12: 1
B13: Diversity in Governance - NPC | D13: "This paper outlines what it means to have a truly diverse board of trustees and what it brings to an organisation. It also explores how to manage and maintain a board that is diverse." | O13: https://www.thinknpc.org/resource-hub/diversity-in-governance-the-what-why-and-how/ | U13: Our organisation has not yet embedded this | V13: 0
B18: Part 1 | D18: ='EDI Framework Criteria'!B7 -> Social mission
I20: Our organisation has- please select the appropriate dropdown option | J20: What we have done - please clearly state what your organisation has done | K20: Score | L20: Guidance for these statements | V20: Non commitment
B21: Level 1 | C21: ='EDI Framework Criteria'!C7 -> 1.B.1 | D21: ='EDI Framework Criteria'!D7 -> We have committed to producing a mission or vision statement which shows a clear organisational commitment to improving Equality, Diversity and Inclusion. | I21: Our organisation has not yet committed to this | K21: =INDEX($U$3:$V$13,MATCH(I21,$U$3:$U$13,0),2) -> 0 | V21: =IF(K21=0,V20,"") -> Non commitment
B23: Level 2 | C23: ='EDI Framework Criteria'!E7 -> 2.B.1 | D23: ='EDI Framework Criteria'!F7 -> We have a mission or vision statement which shows our commitment to improving Equality, Diversity and Inclusion. | I23: Our organisation has not yet implemented this | K23: =INDEX($U$3:$V$13,MATCH(I23,$U$3:$U$13,0),2) -> 0
B25: Level 3 | C25: ='EDI Framework Criteria'!G7 -> 3.B.1 | D25: ='EDI Framework Criteria'!H7 -> We have a mission or vision statement which shows our commitment to improving EDI. We have reviewed it at least once, and will keep making updates as our EDI work goes on. We have shared it internally and externally, and invited comments from affected people. We share this statement on a range of public materials, like terms of references and procurement materials. | I25: Our organisation has not yet embedded this | K25: =INDEX($U$3:$V$13,MATCH(I25,$U$3:$U$13,0),2) -> 0
B28: Part 2 | D28: ='EDI Framework Criteria'!B8 -> Individual responsibilities
I30: Our organisation has- please select the appropriate dropdown option | J30: What we have done - please clearly state what your organisation has done | L30: Guidance for these statements
B31: Level 1 | C31: ='EDI Framework Criteria'!C8 -> 1.B.2 | D31: ='EDI Framework Criteria'!D8 -> We are committed to creating a document that explains what people's personal responsibilities are for working towards EDI. | I31: Our organisation has not yet committed to this | K31: =INDEX($U$3:$V$13,MATCH(I31,$U$3:$U$13,0),2) -> 0 | V31: =IF(#REF!=0,V30,"") -> #REF!
B33: Level 2 | C33: ='EDI Framework Criteria'!E8 -> 2.B.2 | D33: ='EDI Framework Criteria'!F8 -> We have created a document that explains what people's personal responsibilities are for working towards EDI. | I33: Our organisation has not yet implemented this | K33: =INDEX($U$3:$V$13,MATCH(I33,$U$3:$U$13,0),2) -> 0
B35: Level 3 | C35: ='EDI Framework Criteria'!G8 -> 3.B.2 | D35: ='EDI Framework Criteria'!H8 -> We have a document that explains what everyone’s responsibilities are for working towards EDI. We have reviewed it at least once, and will keep making updates as our EDI work goes on. | I35: Our organisation has not yet embedded this | K35: =INDEX($U$3:$V$13,MATCH(I35,$U$3:$U$13,0),2) -> 0
B38: Part 3 | D38: ='EDI Framework Criteria'!B9 -> Targets for Equality, Diversity and Inclusion
I40: Our organisation has- please select the appropriate dropdown option | J40: What we have done - please clearly state what your organisation has done | L40: Guidance for these statements
B41: Level 1 | C41: ='EDI Framework Criteria'!C9 -> 1.B.3 | D41: ='EDI Framework Criteria'!D9 -> We have committed to setting relevant targets for EDI. This will include targets for outputs and outcomes. | I41: Our organisation has not yet committed to this | K41: =INDEX($U$3:$V$13,MATCH(I41,$U$3:$U$13,0),2) -> 0 | V41: =IF(K31=0,V40,"") -> 0
B43: Level 2 | C43: ='EDI Framework Criteria'!E9 -> 2.B.3 | D43: ='EDI Framework Criteria'!F9 -> We have set relevant targets for EDI. We are tracking not only outputs but also outcomes. | I43: Our organisation has not yet implemented this | K43: =INDEX($U$3:$V$13,MATCH(I43,$U$3:$U$13,0),2) -> 0
B45: Level 3 | C45: ='EDI Framework Criteria'!G9 -> 3.B.3 | D45: ='EDI Framework Criteria'!H9 -> We have set relevant targets for EDI. We are tracking not only outputs but also outcomes. Our targets have been reviewed at least once, with input from stakeholders. We have revised the targets as needed, and will keep revising them as our EDI work goes on. | I45: Our organisation has not yet embedded this | K45: =INDEX($U$3:$V$13,MATCH(I45,$U$3:$U$13,0),2) -> 0
B48: Part 4 | D48: ='EDI Framework Criteria'!B10 -> Working with marginalised groups
I50: Our organisation has- please select the appropriate dropdown option | J50: What we have done - please clearly state what your organisation has done | L50: Guidance for these statements
B51: Level 1 | C51: ='EDI Framework Criteria'!C10 -> 1.B.4 | D51: ='EDI Framework Criteria'!D10 -> We have committed to creating a policy or action plan with clear commitments to identify and support marginalised groups. | I51: Our organisation has not yet committed to this | K51: =INDEX($U$3:$V$13,MATCH(I51,$U$3:$U$13,0),2) -> 0
B53: Level 2 | C53: ='EDI Framework Criteria'!E10 -> 2.B.4 | D53: ='EDI Framework Criteria'!F10 -> We have a policy or action plan with clear commitments to identify and support marginalised groups. This has been agreed to by senior management or the board. | I53: Our organisation has not yet implemented this | K53: =INDEX($U$3:$V$13,MATCH(I53,$U$3:$U$13,0),2) -> 0
B55: Level 3 | C55: ='EDI Framework Criteria'!G10 -> 3.B.4 | D55: ='EDI Framework Criteria'!H10 -> We have a policy or action plan with clear commitments to identify and support marginalised groups. We have reviewed it at least once, and will keep making updates as our EDI work goes on. | I55: Our organisation has not yet embedded this | K55: =INDEX($U$3:$V$13,MATCH(I55,$U$3:$U$13,0),2) -> 0
B59: Previous section | D59: Next section

Sheet Section 3
B2: Section 3
B3: ='EDI Framework Criteria'!A11 -> Theory of Change | U3: Our organisation has committed to this | V3: 2
U4: In progress | V4: 1
B5: Background information | U5: Our organisation has not yet committed to this | V5: 0
B6: Developing a EDI specific theory of change allows an organisation to define how to approach EDI issues through strategic business choices and the intended and possible unintended outcomes of those choices.
U7: Our organisation has implemented this | V7: 2
B8: Useful resources (select the + button on the left hand side of the screen to expand) | U8: In progress | V8: 1
B9: Resource name | D9: Description | O9: URL | U9: Our organisation has not yet implemented this | V9: 0
B10: Theory of change in ten steps | D10: "Throughout our work and personal lives we have aims and ideas about how to achieve them, but we rarely take the time to think these through, scrutinise and articulate them. This is what a theory of change process does. It encourages us to reflect on our aims and plans, to discuss them with others and to make them explicit. We see theory of change as the foundation of charity strategy, evaluation and communication. This guide is a ten step handbook to creating a theory of change, built on many years of developing them for charities and funders. It focusses on the basics, our core approach. It gives you the information you need to do any theory of change and is directly applicable to smaller projects and charitable services." | O10: https://www.thinknpc.org/resource-hub/ten-steps/
B11: ESS Evaluation Tool: Interactive Logic Model Template | D11: A logic model tells the story of your project or programme in a diagram and a few simple words. It shows a causal connection between the need you have identified, what you do and how this makes a difference for individuals and communities. | O11: https://evaluationsupportscotland.org.uk/resources/interactive-logic-model-template/ | U11: Our organisation has embedded this | V11: 2
B12: How to Build a Theory of Change | D12: "A theory of change is a description of why a particular way of working will be effective, showing how change happens in the short, medium and long term to achieve the intended impact. It can be represented in a visual diagram, as a narrative, or both. A theory of change can be developed at the beginning of a piece of work (to help with strategic planning), or to describe an existing piece of work (so you can evaluate it). It is particularly helpful if you are planning or evaluating a complex, initiative but can also be used for more straightforward projects. See more in our summary of the uses of theory of change. It is helpful to involve a variety of stakeholders when you develop a theory of change – you could include staff, trustees, beneficiaries, partners and funders. The development process, and the thinking involved, is often as important as the diagram or narrative you produce." | O12: https://knowhow.ncvo.org.uk/how-to/how-to-build-a-theory-of-change | U12: In progress | V12: 1
U13: Our organisation has not yet embedded this | V13: 0
B16: Part 1 | D16: ='EDI Framework Criteria'!B11 -> Theory of Change
I18: Our organisation has- please select the appropriate dropdown option | J18: What we have done - please clearly state what your organisation has done | K18: Score | L18: Guidance for these statements | V18: Non commitment
B19: Level 1 | C19: ='EDI Framework Criteria'!C11 -> 1.C.1 | D19: ='EDI Framework Criteria'!D11 -> We have committed to creating a Theory of Change for how EDI outcomes are created by our activities. This will include positive and negative outcomes; cover all our stakeholder groups; and include inputs and outputs. | I19: Our organisation has not yet committed to this | K19: =INDEX($U$3:$V$13,MATCH(I19,$U$3:$U$13,0),2) -> 0 | V19: =IF(K19=0,V18,"") -> Non commitment
B21: Level 2 | C21: ='EDI Framework Criteria'!E11 -> 2.C.1 | D21: ='EDI Framework Criteria'!F11 -> We have a Theory of Change for how EDI outcomes are created by our activities. This includes positive and negative outcomes; covers all our stakeholder groups; and includes inputs and outputs. | I21: Our organisation has not yet implemented this | K21: =INDEX($U$3:$V$13,MATCH(I21,$U$3:$U$13,0),2) -> 0
B23: Level 3 | C23: ='EDI Framework Criteria'!G11 -> 3.C.1 | D23: ='EDI Framework Criteria'!H11 -> We have a Theory of Change for how EDI outcomes are created by our activities. This includes positive and negative outcomes; covers all our stakeholder groups; and includes inputs and outputs. We collect relevant EDI data and use it to update the Theory of Change. We have reviewed it at least once, and will keep making updates as our EDI work goes on. | I23: Our organisation has not yet embedded this | K23: =INDEX($U$3:$V$13,MATCH(I23,$U$3:$U$13,0),2) -> 0
B27: Previous section | D27: Next section

Sheet Section 4
B2: Section 4
B3: ='EDI Framework Criteria'!A12 -> Equality, Diversity and Inclusion Advocacy | U3: Our organisation has committed to this | V3: 2
U4: In progress | V4: 1
B5: Background information | U5: Our organisation has not yet committed to this | V5: 0
B6: EDI advocacy covers the promotion of EDI within your organisation, to both staff and a board if a board exists. This may be through training or other forms of EDI capacity building.
U7: Our organisation has implemented this | V7: 2
B8: Useful resources (select the + button on the left hand side of the screen to expand) | U8: In progress | V8: 1
B9: Resource name | D9: Description | O9: URL | U9: Our organisation has not yet implemented this | V9: 0
B10: Best practice, toolkits and resources | D10: "Our resources and toolkits are here to help you. Looking to make your policies LGBT inclusive? To learn how to empower senior leaders? Support your LGBT staff on overseas assignments? Our step-by-step resources and toolkits will guide you on your way." | O10: https://www.stonewall.org.uk/best-practice-toolkits-and-resources
B11: How to shift public attitudes on equality - A practical guide for campaigners and communicators | D11: "This guide applies a strategic communications approach to the challenge of showing inequality as structural – deeply embedded in our society and institutions, rather than the responsibility of individuals. It aims to shift thinking away from the belief that anyone can be a successful ‘self-made person’, and towards a recognition that there are still major structural barriers to equality. It is based on a six-month, qualitative and quantitative research project by ComRes for Equally Ours, which itself builds upon previous research for Equally Ours by YouGov." | O11: https://www.equallyours.org.uk/wp-content/uploads/2019/11/Talking-about-equality-guide.pdf | U11: Our organisation has embedded this | V11: 2
B12: Inclusive Language Guide - OneGSMA | D12: "Inclusive language is a form of communication that avoids using words, expressions or assumptions that would stereotype, demean or exclude people. For example, gendered language is commonly understood as language that has a biastowards a particular sex or social gender. In English, this would include using gender-specific terms referring to professions or people, such as businessman or fireman. Please note the terms used in this guide reflect the diverse identities and experiences ofBritish and American society, there might be alternative preferred terms in other regions which we look forward to capturing." | O12: https://www.gsma.com/aboutus/wp-content/uploads/2020/11/GSMA-Inclusive-Language-Guide_2020.pdf?fbclid=IwAR1DRe-CGvJqraLTEwRsVS4CucRP-M_1OOhep8ZIXa22uYA-RHasM_LgfyU | U12: In progress | V12: 1
U13: Our organisation has not yet embedded this | V13: 0
B16: Part 1 | D16: ='EDI Framework Criteria'!B12 -> Equality, Diversity and Inclusion training
I18: Our organisation has- please select the appropriate dropdown option | J18: What we have done - please clearly state what your organisation has done | K18: Score | L18: Guidance for these statements | V18: Non commitment
B19: Level 1 | C19: ='EDI Framework Criteria'!C12 -> 1.D.1 | D19: ='EDI Framework Criteria'!D12 -> We have committed to creating a training plan for staff across all levels including board level for embedding EDI practice into their organisational practice and decision making. | I19: Our organisation has not yet committed to this | K19: =INDEX($U$3:$V$13,MATCH(I19,$U$3:$U$13,0),2) -> 0 | V19: =IF(K19=0,V18,"") -> Non commitment
B21: Level 2 | C21: ='EDI Framework Criteria'!E12 -> 2.D.1 | D21: ='EDI Framework Criteria'!F12 -> A training plan for staff across all levels including board level for embedding EDI practice into organisational practice has been developed. Some training activities have started. | I21: Our organisation has not yet implemented this | K21: =INDEX($U$3:$V$13,MATCH(I21,$U$3:$U$13,0),2) -> 0
B23: Level 3 | C23: ='EDI Framework Criteria'!G12 -> 3.D.1 | D23: ='EDI Framework Criteria'!H12 -> The training plan for staff across all levels including board level for embedding EDI practice into organisational practice is in place. The plan has been reviewed at least once, with plans to continue to review as needed. Activities for all levels are underway. Training around EDI practice is included in new staff induction or training at all levels of the organisation (in line with the needs of their role). | I23: Our organisation has not yet embedded this | K23: =INDEX($U$3:$V$13,MATCH(I23,$U$3:$U$13,0),2) -> 0
B26: Part 2 | D26: ='EDI Framework Criteria'!B13 -> Equality, Diversity and Inclusion resourcing
I28: Our organisation has- please select the appropriate dropdown option | J28: What we have done - please clearly state what your organisation has done | L28: Guidance for these statements
B29: Level 1 | C29: ='EDI Framework Criteria'!C13 -> 1.D.2 | D29: ='EDI Framework Criteria'!D13 -> We have committed to creating an organisational commitment to EDI by allocating resources for EDI management and capacity building. | I29: Our organisation has not yet committed to this | K29: =INDEX($U$3:$V$13,MATCH(I29,$U$3:$U$13,0),2) -> 0 | V29: =IF(K29=0,V28,"") -> 0
B31: Level 2 | C31: ='EDI Framework Criteria'!E13 -> 2.D.2 | D31: ='EDI Framework Criteria'!F13 -> Resources have been allocated for EDI management and capacity building. | I31: Our organisation has not yet implemented this | K31: =INDEX($U$3:$V$13,MATCH(I31,$U$3:$U$13,0),2) -> 0
B33: Level 3 | C33: ='EDI Framework Criteria'!G13 -> 3.D.2 | D33: ='EDI Framework Criteria'!H13 -> Resources continue to be allocated for EDI management and capacity building, and are reviewed and revised as necessary. | I33: Our organisation has not yet embedded this | K33: =INDEX($U$3:$V$13,MATCH(I33,$U$3:$U$13,0),2) -> 0
B37: Previous section | D37: Next section

Sheet Section 5
B2: Section 5
B3: ='EDI Framework Criteria'!A14 -> Equality, Diversity and Inclusion Data Analysis and Evaluation | U3: Our organisation has committed to this | V3: 2
U4: In progress | V4: 1
B5: Background information | U5: Our organisation has not yet committed to this | V5: 0
B6: Measurement of EDI progress is an important and necessary aspect of practice. By embedding data collection in organisational activites the results of EDI strategy and activities can be analysed and assessed. Where appropriate data is also useful so areas of concern can be identified such as intersectionality of experience and unexpected outcomes.
U7: Our organisation has implemented this | V7: 2
B8: Useful resources (select the + button on the left hand side of the screen to expand) | U8: In progress | V8: 1
B9: Resource name | D9: Description | O9: URL | U9: Our organisation has not yet implemented this | V9: 0
B10: Maximise Your Impact – A Guide for Social Entrepreneurs | D10: "The Maximise Your Impact guide was developed within “Know Your Impact: Social Impact Management Tools for Young Social Entrepreneurs” by Estonian Social Enterprise Network, Koç University Social Impact Forum, Mikado Sustainable Development Consulting and Social Value UK. The “Know Your Impact: Social Impact Management Tools for Young Social Entrepreneurs” is funded by Erasmus + programme of the European Union." | O10: https://socialvalueuk.org/resource/maximise-impact/
U11: Our organisation has embedded this | V11: 2
U12: In progress | V12: 1
U13: Our organisation has not yet embedded this | V13: 0
B16: Part 1 | D16: ='EDI Framework Criteria'!B14 -> Collection of specific data, including outcomes | K16: part 1
I18: Our organisation has- please select the appropriate dropdown option | J18: What we have done - please clearly state what your organisation has done | K18: Score | L18: Guidance for these statements | V18: Non commitment
B19: Level 1 | C19: ='EDI Framework Criteria'!C14 -> 1.E.1 | D19: ='EDI Framework Criteria'!D14 -> We have committed to tracking information from all stakeholder groups to collect the following data for outcomes measurement: - Numbers of people experiencing each outcome (scale) - Extent of change for each outcome (depth) - The EDI characteristics of stakeholders | I19: Our organisation has not yet committed to this | K19: =INDEX($U$3:$V$13,MATCH(I19,$U$3:$U$13,0),2) -> 0 | V19: =IF(K19=0,V18,"") -> Non commitment
B21: Level 2 | C21: ='EDI Framework Criteria'!E14 -> 2.E.1 | D21: ='EDI Framework Criteria'!F14 -> Outcomes are starting to be measured involving all stakeholder groups. The measurement includes: - Numbers of people experiencing each outcome (scale) - Extent of change for each outcome (depth) - The EDI characteristics of stakeholders | I21: Our organisation has not yet implemented this | K21: =INDEX($U$3:$V$13,MATCH(I21,$U$3:$U$13,0),2) -> 0
B23: Level 3 | C23: ='EDI Framework Criteria'!G14 -> 3.E.1 | D23: ='EDI Framework Criteria'!H14 -> Outcomes are being measured on a regular basis. Measurement includes: - Numbers of people experiencing each outcome (scale) - Extent of change for each outcome (depth) - The EDI characteristics of stakeholders | I23: Our organisation has not yet embedded this | K23: =INDEX($U$3:$V$13,MATCH(I23,$U$3:$U$13,0),2) -> 0
B26: Part 2 | D26: ='EDI Framework Criteria'!B14 -> Collection of specific data, including outcomes | K26: part 2
I28: Our organisation has- please select the appropriate dropdown option | J28: What we have done - please clearly state what your organisation has done | L28: Guidance for these statements
B29: Level 1 | C29: ='EDI Framework Criteria'!C15 -> 1.E.7 | D29: ='EDI Framework Criteria'!D15 -> We have committed to creating a plan for which EDI characteristics to track when we are measuring outcomes. We look at all 9 protected characteristics in the Equalities Act (2010) and more, for example, socioeconomic class. | I29: Our organisation has not yet committed to this | K29: =INDEX($U$3:$V$13,MATCH(I29,$U$3:$U$13,0),2) -> 0 | V29: =IF(K29=0,V28,"") -> 0
B31: Level 2 | C31: ='EDI Framework Criteria'!E15 -> 2.E.7 | D31: ='EDI Framework Criteria'!F15 -> We identified which EDI characteristics to track when we are measuring outcomes. We look at all 9 protected characteristics in the Equalities Act (2010) and more, for example, socioeconomic class. We are integrating these into our outcomes measurement. | I31: Our organisation has not yet implemented this | K31: =INDEX($U$3:$V$13,MATCH(I31,$U$3:$U$13,0),2) -> 0
B33: Level 3 | C33: ='EDI Framework Criteria'!G15 -> 3.E.7 | D33: ='EDI Framework Criteria'!H15 -> Our stakeholders’ EDI characteristics are included in our outcomes measurement. We look at all 9 protected characteristics in the Equalities Act (2010) and more, for example, socioeconomic class. We review and revise them regularly. | I33: Our organisation has not yet embedded this | K33: =INDEX($U$3:$V$13,MATCH(I33,$U$3:$U$13,0),2) -> 0
B36: Part 3 | D36: ='EDI Framework Criteria'!B16 -> Social value verification
I38: Our organisation has- please select the appropriate dropdown option | J38: What we have done - please clearly state what your organisation has done | L38: Guidance for these statements
B39: Level 1 | C39: ='EDI Framework Criteria'!C16 -> 1.E.3 | D39: ='EDI Framework Criteria'!D16 -> We have committed to seeking feedback from a third-party on our EDI data collection and analysis. This could be through a critical friend, peer review, or through a more formal assurance provider. | I39: Our organisation has not yet committed to this | K39: =INDEX($U$3:$V$13,MATCH(I39,$U$3:$U$13,0),2) -> 0 | V39: =IF(K39=0,V38,"") -> 0
B41: Level 2 | C41: ='EDI Framework Criteria'!E16 -> 2.E.3 | D41: ='EDI Framework Criteria'!F16 -> We have had feedback from a third-party on our EDI data collection and analysis. Explanation given about choice of third party and any associated risks of choice (this could be a critical friend, peer review or a more formal assurance provider). | I41: Our organisation has not yet implemented this | K41: =INDEX($U$3:$V$13,MATCH(I41,$U$3:$U$13,0),2) -> 0
B43: Level 3 | C43: ='EDI Framework Criteria'!G16 -> 3.E.3 | D43: ='EDI Framework Criteria'!H16 -> EDI data collection and analysis are continuing to be reviewed by a third party. Any issues identified by the third party have been recorded and action taken to address the issues. Risks of choice of third party considered and addressed (this could be a critical friend, peer review or a more formal assurance provider). | I43: Our organisation has not yet embedded this | K43: =INDEX($U$3:$V$13,MATCH(I43,$U$3:$U$13,0),2) -> 0
B46: Part 4 | D46: ='EDI Framework Criteria'!B17 -> Transparency around Equality, Diversity and Inclusion practice
I48: Our organisation has- please select the appropriate dropdown option | J48: What we have done - please clearly state what your organisation has done | L48: Guidance for these statements
B49: Level 1 | C49: ='EDI Framework Criteria'!C17 -> 1.E.4 | D49: ='EDI Framework Criteria'!D17 -> We have committed to creating reports on our EDI data and practices. These will cover: - Scope of the activities, - Our audience, - Why we’re conducting analysis, - Limitations or risks of using this data, - Performance against our targets, - Recommendations for improvement. We may use different types of reporting for internal and external audiences. | I49: Our organisation has not yet committed to this | K49: =INDEX($U$3:$V$13,MATCH(I49,$U$3:$U$13,0),2) -> 0 | V49: =IF(K49=0,V48,"") -> 0
B51: Level 2 | C51: ='EDI Framework Criteria'!E17 -> 2.E.4 | D51: ='EDI Framework Criteria'!F17 -> We are starting to create reports on our EDI data and practices. These cover: - Scope of the activities, - Our audience, - Why we’re conducting analysis, - Limitations or risks of using this data, - Performance against our targets, - Recommendations for improvement. We may use different types of reporting for internal and external audiences. | I51: Our organisation has not yet implemented this | K51: =INDEX($U$3:$V$13,MATCH(I51,$U$3:$U$13,0),2) -> 0
B53: Level 3 | C53: ='EDI Framework Criteria'!G17 -> 3.E.4 | D53: ='EDI Framework Criteria'!H17 -> We regularly create reports on our EDI data and practices. These cover: - Scope of the activities, - Our audience, - Why we’re conducting analysis, - Limitations or risks of using this data, - Performance against our targets, - Recommendations for improvement. We may use different types of reporting for internal and external audiences. | I53: Our organisation has not yet embedded this | K53: =INDEX($U$3:$V$13,MATCH(I53,$U$3:$U$13,0),2) -> 0
B56: Part 5 | D56: ='EDI Framework Criteria'!B17 -> Transparency around Equality, Diversity and Inclusion practice
I58: Our organisation has- please select the appropriate dropdown option | J58: What we have done - please clearly state what your organisation has done | L58: Guidance for these statements
B59: Level 1 | C59: ='EDI Framework Criteria'!C18 -> 1.E.5 | D59: ='EDI Framework Criteria'!D18 -> We have committed to recording the limitations and risks of our EDI data collection and analysis. This will include gaps, sources of potential bias, and how far we’ve involved stakeholders. We will identify where other sources of data are needed, and how they can be compared. | I59: Our organisation has not yet committed to this | K59: =INDEX($U$3:$V$13,MATCH(I59,$U$3:$U$13,0),2) -> 0 | V59: =IF(K59=0,V58,"") -> 0
B61: Level 2 | C61: ='EDI Framework Criteria'!E18 -> 2.E.5 | D61: ='EDI Framework Criteria'!F18 -> We have recorded the limitations and risks of our EDI data collection and analysis. We have included gaps, sources of potential bias, and how far we’ve involved stakeholders. We have taken steps to identify and address limitations or risks around this data. | I61: Our organisation has not yet implemented this | K61: =INDEX($U$3:$V$13,MATCH(I61,$U$3:$U$13,0),2) -> 0
B63: Level 3 | C63: ='EDI Framework Criteria'!G18 -> 3.E.5 | D63: ='EDI Framework Criteria'!H18 -> We are continually checking for limitations and risks to our EDI data collection and analysis. We make any necessary changes to our data collection and analysis processes. | I63: Our organisation has not yet embedded this | K63: =INDEX($U$3:$V$13,MATCH(I63,$U$3:$U$13,0),2) -> 0
B66: Part 6 | D66: ='EDI Framework Criteria'!B19 -> Measuring inclusion
I68: Our organisation has- please select the appropriate dropdown option | J68: What we have done - please clearly state what your organisation has done | L68: Guidance for these statements
B69: Level 1 | C69: ='EDI Framework Criteria'!C19 -> 1.E.6 | D69: ='EDI Framework Criteria'!D19 -> We have committed to setting up a strong system for collecting and recording information on inclusion. We will collect information on inclusion. We will break that data down by relevant EDI characteristics, going beyond the 9 protected characteristics to include other areas like class or neurodivergence. | I69: Our organisation has not yet committed to this | K69: =INDEX($U$3:$V$13,MATCH(I69,$U$3:$U$13,0),2) -> 0 | V69: =IF(K69=0,V68,"") -> 0
B71: Level 2 | C71: ='EDI Framework Criteria'!E19 -> 2.E.6 | D71: ='EDI Framework Criteria'!F19 -> A system for collecting and recording information on inclusion has been established. We are starting to collect information on inclusion. We are starting to break that data down by relevant EDI characteristics, going beyond the 9 protected characteristics to include other areas like class or neurodivergence. | I71: Our organisation has not yet implemented this | K71: =INDEX($U$3:$V$13,MATCH(I71,$U$3:$U$13,0),2) -> 0
B73: Level 3 | C73: ='EDI Framework Criteria'!G19 -> 3.E.6 | D73: ='EDI Framework Criteria'!H19 -> Our system for collecting and recording information on inclusion is in place. We collect information on inclusion, and break that data down by relevant EDI characteristics, going beyond the 9 protected characteristics to include other areas like class or neurodivergence. Not all groups have the same needs, so we make changes to our systems to make them more just and equitable. | I73: Our organisation has not yet embedded this | K73: =INDEX($U$3:$V$13,MATCH(I73,$U$3:$U$13,0),2) -> 0
B77: Previous section | D77: Next section

Sheet Section 6
B2: Section 6
B3: ='EDI Framework Criteria'!A20 -> Stakeholder engagement: Understanding approach towards previously omitted groups in service provision and activities | U3: Our organisation has committed to this | V3: 2
U4: In progress | V4: 1
B5: Background information | U5: Our organisation has not yet committed to this | V5: 0
B6: For effective EDI practice stakeholders should be continually and robustly engaged as stakeholder preferences need to be incorporated into definitions of ‘success’. This section covers the identification and engagement of these stakeholders.
U7: Our organisation has implemented this | V7: 2
B8: Useful resources (select the + button on the left hand side of the screen to expand) | U8: In progress | V8: 1
B9: Resource name | D9: Description | O9: URL | U9: Our organisation has not yet implemented this | V9: 0
B10: AA1000 Stakeholder engagement standard | D10: "The AA1000 AccountAbility Stakeholder Engagement Standard (2015) – the most widely applied stakeholder engagement standard – establishes the global benchmark for conducting high-quality stakeholder engagement projects and programs." | O10: https://www.accountability.org/standards/aa1000-stakeholder-engagement-standard/
B11: Standard on applying Principle 1: Involve Stakeholders | D11: "Inform what gets measured and how this is measured and valued in an account of social value by involving stakeholders. This document sets out SVI’s Standard for applying Principle 1: Involve your stakeholders. Involving stakeholders is at the heart of accounting for value and plays a key role in how you apply the other social value principles: Understand what changes; Value the things that matter; Only include what is material; and Do not over-claim. The standard focuses on involving all stakeholders (not only intended beneficiaries) who experience change in their lives (outcomes) as a result of an activity or intervention." | O11: https://www.socialvalueint.org/principle-1-involve-stakeholders | U11: Our organisation has embedded this | V11: 2
B12: Stories for Impact - Stakeholder mapping tool | D12: "A stakeholder map helps you analyse and manage relationships with individuals and organisations who are impacted by your solution or who can influence whether your solution will be successful. " | O12: https://storiesforimpact.com/toolbox/stakeholder-map/ | U12: In progress | V12: 1
U13: Our organisation has not yet embedded this | V13: 0
B16: Part 1 | D16: ='EDI Framework Criteria'!B20 -> Stakeholder mapping
I18: Our organisation has- please select the appropriate dropdown option | J18: What we have done - please clearly state what your organisation has done | K18: Score | L18: Guidance for these statements | V18: Non commitment
B19: Level 1 | C19: ='EDI Framework Criteria'!C20 -> 1.F.1 | D19: ='EDI Framework Criteria'!D20 -> We have committed to mapping out our stakeholder groups (and identify sub groups) for the activities that we plan to include in our EDI practice. | I19: Our organisation has not yet committed to this | K19: =INDEX($U$3:$V$13,MATCH(I19,$U$3:$U$13,0),2) -> 0 | V19: =IF(K19=0,V18,"") -> Non commitment
B21: Level 2 | C21: ='EDI Framework Criteria'!E20 -> 2.F.1 | D21: ='EDI Framework Criteria'!F20 -> We have mapped out the stakeholder groups (and subgroups) affected by our EDI practice. | I21: Our organisation has not yet implemented this | K21: =INDEX($U$3:$V$13,MATCH(I21,$U$3:$U$13,0),2) -> 0
B23: Level 3 | C23: ='EDI Framework Criteria'!G20 -> 3.F.1 | D23: ='EDI Framework Criteria'!H20 -> We have mapped out the stakeholder groups (and subgroups) affected by our EDI practice. We review and revise this as needed. | I23: Our organisation has not yet embedded this | K23: =INDEX($U$3:$V$13,MATCH(I23,$U$3:$U$13,0),2) -> 0
B26: Part 2 | D26: ='EDI Framework Criteria'!B21 -> Stakeholder engagement
I28: Our organisation has- please select the appropriate dropdown option | J28: What we have done - please clearly state what your organisation has done | L28: Guidance for these statements
B29: Level 1 | C29: ='EDI Framework Criteria'!C21 -> 1.F.2 | D29: ='EDI Framework Criteria'!D21 -> We have committed to creating a plan to engage with people from all stakeholder groups. | I29: Our organisation has not yet committed to this | K29: =INDEX($U$3:$V$13,MATCH(I29,$U$3:$U$13,0),2) -> 0 | V29: =IF(K29=0,V28,"") -> 0
B31: Level 2 | C31: ='EDI Framework Criteria'!E21 -> 2.F.2 | D31: ='EDI Framework Criteria'!F21 -> We have created a plan to engage with people from all stakeholder groups. We are collecting feedback from stakeholders on how effective this plan is in practice. | I31: Our organisation has not yet implemented this | K31: =INDEX($U$3:$V$13,MATCH(I31,$U$3:$U$13,0),2) -> 0
B33: Level 3 | C33: ='EDI Framework Criteria'!G21 -> 3.F.2 | D33: ='EDI Framework Criteria'!H21 -> A plan to engage with people from all stakeholder groups has been developed. We are collecting feedback from stakeholders on how effective this plan is in practice. | I33: Our organisation has not yet embedded this | K33: =INDEX($U$3:$V$13,MATCH(I33,$U$3:$U$13,0),2) -> 0
B36: Part 3 | D36: ='EDI Framework Criteria'!B22 -> Defining outcomes
I38: Our organisation has- please select the appropriate dropdown option | J38: What we have done - please clearly state what your organisation has done | L38: Guidance for these statements
B39: Level 1 | C39: ='EDI Framework Criteria'!C22 -> 1.F.3 | D39: ='EDI Framework Criteria'!D22 -> We plan to involve stakeholder groups to understand the outcomes they are experiencing, and why. We will use open-ended questions to identify outcomes which are positive, negative, intended, and unintended. | I39: Our organisation has not yet committed to this | K39: =INDEX($U$3:$V$13,MATCH(I39,$U$3:$U$13,0),2) -> 0 | V39: =IF(K39=0,V38,"") -> 0
B41: Level 2 | C41: ='EDI Framework Criteria'!E22 -> 2.F.3 | D41: ='EDI Framework Criteria'!F22 -> We have involved stakeholder groups to understand the outcomes they are experiencing, and why. We have used use open-ended questions to identify outcomes which are positive, negative, intended, and unintended. | I41: Our organisation has not yet implemented this | K41: =INDEX($U$3:$V$13,MATCH(I41,$U$3:$U$13,0),2) -> 0
B43: Level 3 | C43: ='EDI Framework Criteria'!G22 -> 3.F.3 | D43: ='EDI Framework Criteria'!H22 -> Outcomes are reviewed and revised based on ongoing stakeholder engagement. | I43: Our organisation has not yet embedded this | K43: =INDEX($U$3:$V$13,MATCH(I43,$U$3:$U$13,0),2) -> 0
B46: Part 4 | D46: ='EDI Framework Criteria'!B23 -> General feedback on Equality, Diversity and Inclusion
I48: Our organisation has- please select the appropriate dropdown option | J48: What we have done - please clearly state what your organisation has done | L48: Guidance for these statements
B49: Level 1 | C49: ='EDI Framework Criteria'!C23 -> 1.F.4 | D49: ='EDI Framework Criteria'!D23 -> We have committed to establishing or adapting mechanisms for collecting and recording feedback on EDI. This could include surveys, focus groups or suggestion schemes. | I49: Our organisation has not yet committed to this | K49: =INDEX($U$3:$V$13,MATCH(I49,$U$3:$U$13,0),2) -> 0 | V49: =IF(K49=0,V48,"") -> 0
B51: Level 2 | C51: ='EDI Framework Criteria'!E23 -> 2.F.4 | D51: ='EDI Framework Criteria'!F23 -> We have in place mechanisms for collecting and recording feedback on EDI. This could include surveys, focus groups or suggestion schemes. | I51: Our organisation has not yet implemented this | K51: =INDEX($U$3:$V$13,MATCH(I51,$U$3:$U$13,0),2) -> 0
B53: Level 3 | C53: ='EDI Framework Criteria'!G23 -> 3.F.4 | D53: ='EDI Framework Criteria'!H23 -> We have reviewed feedback mechanisms at least once. We kept a record of how feedback has been responded to | I53: Our organisation has not yet embedded this | K53: =INDEX($U$3:$V$13,MATCH(I53,$U$3:$U$13,0),2) -> 0
B57: Previous section | D57: Next section

Sheet Section 7
B2: Section 7
B3: ='EDI Framework Criteria'!A24 -> Diversity management: EDI integrated into every part of the organisation’s work. | U3: Our organisation has committed to this | V3: 2
U4: In progress | V4: 1
B5: Background information | U5: Our organisation has not yet committed to this | V5: 0
B6: Diversity management tracks how EDI is integrated into every part of the organisation’s work through structures, such as EDI leads, EDI accountability, and whistleblowing processes.
U7: Our organisation has implemented this | V7: 2
B8: Useful resources (select the + button on the left hand side of the screen to expand) | U8: In progress | V8: 1
B9: Resource name | D9: Description | O9: URL | U9: Our organisation has not yet implemented this | V9: 0
B10: ISO 30415 2021(en), Human resource management — Diversity and inclusion | D10: "This document provides guidance on D&I for organizations, including their governance body, leaders, workforce and recognized representatives, and other stakeholders. It is intended to be scalable to the needs of all types of organizations in different sectors, whether in public, private, government or non-governmental organizations (NGO), regardless of size, type, activity, industry or sector, growth phase, external influences and country-specific requirements." | O10: https://www.iso.org/standard/71164.html
U11: Our organisation has embedded this | V11: 2
U12: In progress | V12: 1
U13: Our organisation has not yet embedded this | V13: 0
B16: Part 1 | D16: ='EDI Framework Criteria'!B24 -> Groups set up and tasked with Equality, Diversity and Inclusion
I18: Our organisation has- please select the appropriate dropdown option | J18: What we have done - please clearly state what your organisation has done | K18: Score | L18: Guidance for these statements | V18: Non commitment
B19: Level 1 | C19: ='EDI Framework Criteria'!C24 -> 1.G.1 | D19: ='EDI Framework Criteria'!D24 -> We have committed to identifying EDI lead/s and creating a working group or forum with representation from across the organisation. This should report to, and receive support from, the board or senior management. | I19: Our organisation has not yet committed to this | K19: =INDEX($U$3:$V$13,MATCH(I19,$U$3:$U$13,0),2) -> 0 | V19: =IF(K19=0,V18,"") -> Non commitment
B21: Level 2 | C21: ='EDI Framework Criteria'!E24 -> 2.G.1 | D21: ='EDI Framework Criteria'!F24 -> EDI lead/s and a working group or forum with representation from across the organisation have started work. They report to, and receive support from, the board or senior management. | I21: Our organisation has not yet implemented this | K21: =INDEX($U$3:$V$13,MATCH(I21,$U$3:$U$13,0),2) -> 0
B23: Level 3 | C23: ='EDI Framework Criteria'!G24 -> 3.G.1 | D23: ='EDI Framework Criteria'!H24 -> EDI lead/s and working group or forum meet regularly. They are given support by the board or senior management, and also report on their activities. | I23: Our organisation has not yet embedded this | K23: =INDEX($U$3:$V$13,MATCH(I23,$U$3:$U$13,0),2) -> 0
B26: Part 2 | D26: ='EDI Framework Criteria'!B25 -> Accountability mechanisms for Equality, Diversity and Inclusion issues
I28: Our organisation has- please select the appropriate dropdown option | J28: What we have done - please clearly state what your organisation has done | L28: Guidance for these statements
B29: Level 1 | C29: ='EDI Framework Criteria'!C25 -> 1.G.2 | D29: ='EDI Framework Criteria'!D25 -> We have committed to creating a policy or action plan to cover accountability mechanisms for EDI practice. This will outline the responsibilities of our governance, for example, our board. | I29: Our organisation has not yet committed to this | K29: =INDEX($U$3:$V$13,MATCH(I29,$U$3:$U$13,0),2) -> 0 | V29: =IF(K29=0,V28,"") -> 0
B31: Level 2 | C31: ='EDI Framework Criteria'!E25 -> 2.G.2 | D31: ='EDI Framework Criteria'!F25 -> We have created a policy or action plan to cover accountability mechanisms for EDI practice. This outlines the responsibilities of our governance, for example, our board. | I31: Our organisation has not yet implemented this | K31: =INDEX($U$3:$V$13,MATCH(I31,$U$3:$U$13,0),2) -> 0
B33: Level 3 | C33: ='EDI Framework Criteria'!G25 -> 3.G.2 | D33: ='EDI Framework Criteria'!H25 -> We have a policy or action plan in place to cover accountability mechanisms for EDI practice. It outlines the responsibilities of our governance, for example, our board. It has been reviewed at least once. We have plans to keep reviewing it as needed. | I33: Our organisation has not yet embedded this | K33: =INDEX($U$3:$V$13,MATCH(I33,$U$3:$U$13,0),2) -> 0
B36: Part 3 | D36: ='EDI Framework Criteria'!B26 -> Mechanisms have been set up to address Equality, Diversity and Inclusion incidents
I38: Our organisation has- please select the appropriate dropdown option | J38: What we have done - please clearly state what your organisation has done | L38: Guidance for these statements
B39: Level 1 | C39: ='EDI Framework Criteria'!C26 -> 1.G.3 | D39: ='EDI Framework Criteria'!D26 -> We are committed to creating or adapting an existing complaint or whistleblowing process. These processes will include support for people making the complaint. The processes will be accessible to internal and external stakeholders. | I39: Our organisation has not yet committed to this | K39: =INDEX($U$3:$V$13,MATCH(I39,$U$3:$U$13,0),2) -> 0 | V39: =IF(K39=0,V38,"") -> 0
B41: Level 2 | C41: ='EDI Framework Criteria'!E26 -> 2.G.3 | D41: ='EDI Framework Criteria'!F26 -> We have created or adapted an existing complaint or whistleblowing process. These processes include support for people making the complaint. The processes are accessible to internal and external stakeholders. | I41: Our organisation has not yet implemented this | K41: =INDEX($U$3:$V$13,MATCH(I41,$U$3:$U$13,0),2) -> 0
B43: Level 3 | C43: ='EDI Framework Criteria'!G26 -> 3.G.3 | D43: ='EDI Framework Criteria'!H26 -> Our complaint or whistleblowing process is in place, and has been reviewed at least once. We keep a record of how incidents or concerns have been addressed. | I43: Our organisation has not yet embedded this | K43: =INDEX($U$3:$V$13,MATCH(I43,$U$3:$U$13,0),2) -> 0
B47: Previous section | D47: Next section

Sheet Section 8
B2: Section 8
B3: ='EDI Framework Criteria'!A27 -> Work integration: Managers and governance reflect diversity of wider workforce | U3: Our organisation has committed to this
U4: In progress | V4: 1
B5: Background information | U5: Our organisation has not yet committed to this | V5: 0
B6: This section covers how the organisational management and governance reflects the diversity of the wider workforce, and promotes staff diversity.
U7: Our organisation has implemented this | V7: 2
B8: Useful resources (select the + button on the left hand side of the screen to expand) | U8: In progress | V8: 1
B9: Resource name | D9: Description | O9: URL | U9: Our organisation has not yet implemented this | V9: 0
U11: Our organisation has embedded this | V11: 2
U12: In progress | V12: 1
U13: Our organisation has not yet embedded this | V13: 0
B16: Part 1 | D16: ='EDI Framework Criteria'!B27 -> Staff diversity and hiring practices
I18: Our organisation has- please select the appropriate dropdown option | J18: What we have done - please clearly state what your organisation has done | K18: Score | L18: Guidance for these statements
B19: Level 1 | C19: ='EDI Framework Criteria'!C27 -> 1.H.1 | D19: ='EDI Framework Criteria'!D27 -> We are committed to creating a plan to improve EDI within our recruitment. This may include adapting language used in job adverts, promoting flexible and remote working, and reaching out to diverse networks. | I19: Our organisation has not yet committed to this | K19: =INDEX($U$3:$V$13,MATCH(I19,$U$3:$U$13,0),2) -> 0
B21: Level 2 | C21: ='EDI Framework Criteria'!E27 -> 2.H.1 | D21: ='EDI Framework Criteria'!F27 -> We have a plan to improve EDI within our recruitment. This can include adapting language used in job adverts, promoting flexible and remote working, and reaching out to diverse networks. | I21: Our organisation has not yet implemented this | K21: =INDEX($U$3:$V$13,MATCH(I21,$U$3:$U$13,0),2) -> 0
B23: Level 3 | C23: ='EDI Framework Criteria'!G27 -> 3.H.1 | D23: ='EDI Framework Criteria'!H27 -> A plan to improve EDI within our recruitment is in place. We have reviewed our practices at least once, and made changes. We will continue to review and make changes as needed. | I23: Our organisation has not yet embedded this | K23: =INDEX($U$3:$V$13,MATCH(I23,$U$3:$U$13,0),2) -> 0
B26: Part 2 | D26: ='EDI Framework Criteria'!B28 -> Career progression
I28: Our organisation has- please select the appropriate dropdown option | J28: What we have done - please clearly state what your organisation has done | L28: Guidance for these statements
B29: Level 1 | C29: ='EDI Framework Criteria'!C28 -> 1.H.2 | D29: ='EDI Framework Criteria'!D28 -> We are committed to creating a plan to improve EDI within career progression. This should include tracking and recording changes (including who is joining, progressing, and leaving the organisation), and possible reasons. | I29: Our organisation has not yet committed to this | K29: =INDEX($U$3:$V$13,MATCH(I29,$U$3:$U$13,0),2) -> 0 | V29: =IF(K29=0,V28,"") -> 0
B31: Level 2 | C31: ='EDI Framework Criteria'!E28 -> 2.H.2 | D31: ='EDI Framework Criteria'!F28 -> We have a plan to improve EDI within career progression. We are tracking information to understand how employees progress, and what structural barriers exist. We are making changes based on this. | I31: Our organisation has not yet implemented this | K31: =INDEX($U$3:$V$13,MATCH(I31,$U$3:$U$13,0),2) -> 0
B33: Level 3 | C33: ='EDI Framework Criteria'!G28 -> 3.H.2 | D33: ='EDI Framework Criteria'!H28 -> We have put in place our plan to improve EDI within career progression. We have recorded information on how our employees progress, and what structural barriers exist. We have made changes based on this, and will keep doing so. | I33: Our organisation has not yet embedded this | K33: =INDEX($U$3:$V$13,MATCH(I33,$U$3:$U$13,0),2) -> 0
B36: Part 3 | D36: ='EDI Framework Criteria'!B29 -> Board diversity
I38: Our organisation has- please select the appropriate dropdown option | J38: What we have done - please clearly state what your organisation has done | L38: Guidance for these statements
B39: Level 1 | C39: ='EDI Framework Criteria'!C29 -> 1.H.3 | D39: ='EDI Framework Criteria'!D29 -> We are committed to creating a plan or policy to improve EDI within our board and senior leadership team. This will include an understanding of changes (like who is joining and leaving the board and senior leadership positions), and reasons why. | I39: Our organisation has not yet committed to this | K39: =INDEX($U$3:$V$13,MATCH(I39,$U$3:$U$13,0),2) -> 0 | V39: =IF(K39=0,V38,"") -> 0
B41: Level 2 | C41: ='EDI Framework Criteria'!E29 -> 2.H.3 | D41: ='EDI Framework Criteria'!F29 -> We have created a plan or policy to improve EDI within our board and senior leadership team. This includes an understanding of changes (like who is joining and leaving the board and senior leadership positions), and reasons why. We are starting to make changes based on this. | I41: Our organisation has not yet implemented this | K41: =INDEX($U$3:$V$13,MATCH(I41,$U$3:$U$13,0),2) -> 0
B43: Level 3 | C43: ='EDI Framework Criteria'!G29 -> 3.H.3 | D43: ='EDI Framework Criteria'!H29 -> We have a plan or policy in place to improve EDI within our board and senior leadership team. We are using our understanding of changes (like who is joining and leaving the board and senior leadership positions), and reasons why to address structural barriers. | I43: Our organisation has not yet embedded this | K43: =INDEX($U$3:$V$13,MATCH(I43,$U$3:$U$13,0),2) -> 0
B46: Part 4 | D46: ='EDI Framework Criteria'!B30 -> Mentoring
I48: Our organisation has- please select the appropriate dropdown option | J48: What we have done - please clearly state what your organisation has done | L48: Guidance for these statements
B49: Level 1 | C49: ='EDI Framework Criteria'!C30 -> 1.H.4 | D49: ='EDI Framework Criteria'!D30 -> We are committed to creating a mentoring scheme to help improve EDI. We will consider who is involved in the scheme, what their EDI characteristics are, and what outcomes they experience. | I49: Our organisation has not yet committed to this | K49: =INDEX($U$3:$V$13,MATCH(I49,$U$3:$U$13,0),2) -> 0
B51: Level 2 | C51: ='EDI Framework Criteria'!E30 -> 2.H.4 | D51: ='EDI Framework Criteria'!F30 -> We have a mentoring scheme to help improve EDI. We have considered who is involved in the scheme, what their EDI characteristics are, and what outcomes they experience. We are collecting information to track this. | I51: Our organisation has not yet implemented this | K51: =INDEX($U$3:$V$13,MATCH(I51,$U$3:$U$13,0),2) -> 0
B53: Level 3 | C53: ='EDI Framework Criteria'!G30 -> 3.H.4 | D53: ='EDI Framework Criteria'!H30 -> We have put in place our plan for improving EDI through a mentoring scheme for staff. We used our understanding of who is participating and what outcomes they experience to maximise positive impact. We will continue to review and make changes. | I53: Our organisation has not yet embedded this | K53: =INDEX($U$3:$V$13,MATCH(I53,$U$3:$U$13,0),2) -> 0
B57: Previous section | D57: Next section
V59: =IF(K49=0,V58,"") -> 0

Sheet Section 9
B2: Section 9
B3: ='EDI Framework Criteria'!A31 -> Support | U3: Our organisation has committed to this | V3: 2
U4: In progress | V4: 1
B5: Background information | U5: Our organisation has not yet committed to this | V5: 0
B6: Organisations need support to progress in their EDI journey so this section supports the identification of and engagement with potential supporters.
U7: Our organisation has implemented this | V7: 2
B8: Useful resources (select the + button on the left hand side of the screen to expand) | U8: In progress | V8: 1
B9: Resource name | D9: Description | O9: URL | U9: Our organisation has not yet implemented this | V9: 0
U11: Our organisation has embedded this | V11: 2
U12: In progress | V12: 1
U13: Our organisation has not yet embedded this | V13: 0
B16: Part 1 | D16: ='EDI Framework Criteria'!B31 -> Professional support
I18: Our organisation has- please select the appropriate dropdown option | J18: What we have done - please clearly state what your organisation has done | K18: Score | L18: Guidance for these statements
B19: Level 1 | C19: ='EDI Framework Criteria'!C31 -> 1.I.1 | D19: ='EDI Framework Criteria'!D31 -> We are committed to creating a plan for identifying experts, organisations, associations, or membership bodies that can help us improve our EDI practice. | I19: Our organisation has not yet committed to this | K19: =INDEX($U$3:$V$13,MATCH(I19,$U$3:$U$13,0),2) -> 0 | L19: Professional support statements aim to identify whether an organisation has external supporters alongside their internal EDI journey. Examples of supporters include but are not limited to: peer organisations also working on their EDI practices; membership bodies that mean regularly to discuss EDI; an advisor with expertise in an area of EDI; a funder who provides grant funding to work on EDI processes. In the 'what we have done' box note down any names of supporters so far and if an organisaisation does not have any yet try to list potential supporters to reach out to.
B21: Level 2 | C21: ='EDI Framework Criteria'!E31 -> 2.I.1 | D21: ='EDI Framework Criteria'!F31 -> We have identified experts, organisations, associations, or membership bodies that can help us improve our EDI practice. We have engaged with them in some way. | I21: Our organisation has not yet implemented this | K21: =INDEX($U$3:$V$13,MATCH(I21,$U$3:$U$13,0),2) -> 0
B23: Level 3 | C23: ='EDI Framework Criteria'!G31 -> 3.I.1 | D23: ='EDI Framework Criteria'!H31 -> We’re in continuing contact with experts, organisations, associations, or membership bodies that can help us improve our EDI practice. Where possible, we are sharing our practice with other organisations. This helps create a community of practice, which we can all learn from. | I23: Our organisation has not yet embedded this | K23: =INDEX($U$3:$V$13,MATCH(I23,$U$3:$U$13,0),2) -> 0
B27: Previous section | D27: Next section

Sheet Section 10
B2: Section 10
B3: ='EDI Framework Criteria'!A32 -> Business Model | U3: Our organisation has committed to this
U4: In progress | V4: 1
B5: Background information | U5: Our organisation has not yet committed to this | V5: 0
B6: This section covers how EDI practices are embedded in business activities. The section focuses on all area of the business model canvas and can be applied to any business models.
U7: Our organisation has implemented this | V7: 2
B8: Useful resources (select the + button on the left hand side of the screen to expand) | U8: In progress | V8: 1
B9: Resource name | D9: Description | O9: URL | U9: Our organisation has not yet implemented this | V9: 0
U11: Our organisation has embedded this | V11: 2
U12: In progress | V12: 1
U13: Our organisation has not yet embedded this | V13: 0
B14: Due to the size of your organisation you do not need to complete Section 7. However, we recommend you review the content for future reference and fill in the section when you have a team of 4 or more people.
B16: Part 1 | D16: ='EDI Framework Criteria'!B32 -> Value proposition
I18: Our organisation has- please select the appropriate dropdown option | J18: What we have done - please clearly state what your organisation has done | K18: Score | L18: Guidance for these statements
B19: Level 1 | C19: ='EDI Framework Criteria'!C32 -> 1.J.1 | D19: ='EDI Framework Criteria'!D32 -> We are committed to creating a plan to assess whether products and services are designed and delivered in a way that is accessible to our stakeholders e.g. taking into account step free access to a location. | I19: Our organisation has not yet committed to this | K19: =INDEX($U$3:$V$13,MATCH(I19,$U$3:$U$13,0),2) -> 0
B21: Level 2 | C21: ='EDI Framework Criteria'!E32 -> 2.J.1 | D21: ='EDI Framework Criteria'!F32 -> We have developed a plan to assess whether products and services are designed and delivered in a way that is accessible to our stakeholders. We have a way to respond to feedback and action changes. | I21: Our organisation has not yet implemented this | K21: =INDEX($U$3:$V$13,MATCH(I21,$U$3:$U$13,0),2) -> 0
B23: Level 3 | C23: ='EDI Framework Criteria'!G32 -> 3.J.1 | D23: ='EDI Framework Criteria'!H32 -> We have in place a plan to assess whether products and services are designed and delivered in a way that is accessible to our stakeholders. Accessibility and inclusion are top considerations when we are creating products and services. | I23: Our organisation has not yet embedded this | K23: =INDEX($U$3:$V$13,MATCH(I23,$U$3:$U$13,0),2) -> 0
B26: Part 2 | D26: ='EDI Framework Criteria'!B33 -> Customer/ user preferences
I28: Our organisation has- please select the appropriate dropdown option | J28: What we have done - please clearly state what your organisation has done | L28: Guidance for these statements
B29: Level 1 | C29: ='EDI Framework Criteria'!C33 -> 1.J.2 | D29: ='EDI Framework Criteria'!D33 -> We are committed to collecting data on our users’ wants and needs regarding pricing of products and or services. | I29: Our organisation has not yet committed to this | K29: =INDEX($U$3:$V$13,MATCH(I29,$U$3:$U$13,0),2) -> 0
B31: Level 2 | C31: ='EDI Framework Criteria'!E33 -> 2.J.2 | D31: ='EDI Framework Criteria'!F33 -> We have collected data on our users’ wants and needs regarding pricing of products and or services and use this information in pricing model decisions. | I31: Our organisation has not yet implemented this | K31: =INDEX($U$3:$V$13,MATCH(I31,$U$3:$U$13,0),2) -> 0
B33: Level 3 | C33: ='EDI Framework Criteria'!G33 -> 3.J.2 | D33: ='EDI Framework Criteria'!H33 -> We have a pricing model that makes affordability a key consideration. We use this to make products and services affordable to our users e.g. using a subsidy model for low-income individuals where appropriate. Our pricing model has been reviewed at least once. | I33: Our organisation has not yet embedded this | K33: =INDEX($U$3:$V$13,MATCH(I33,$U$3:$U$13,0),2) -> 0
B36: Part 3 | D36: ='EDI Framework Criteria'!B34 -> Customer/ user data collection preferences
I38: Our organisation has- please select the appropriate dropdown option | J38: What we have done - please clearly state what your organisation has done | L38: Guidance for these statements
B39: Level 1 | C39: ='EDI Framework Criteria'!C34 -> 1.J.3 | D39: ='EDI Framework Criteria'!D34 -> We are committed to developing systems to collect user data in a regular, timely and safe way. Included in this is a plan to gather feedback from customers/ users on their data collection preferences through formats such as advisory groups or anonymous surveys. | I39: Our organisation has not yet committed to this | K39: =INDEX($U$3:$V$13,MATCH(I39,$U$3:$U$13,0),2) -> 0
B41: Level 2 | C41: ='EDI Framework Criteria'!E34 -> 2.J.3 | D41: ='EDI Framework Criteria'!F34 -> We have processes in place to collect user data in a regular, timely and safe way. This is supported by feedback from customers/ users around their data collection preferences. | I41: Our organisation has not yet implemented this | K41: =INDEX($U$3:$V$13,MATCH(I41,$U$3:$U$13,0),2) -> 0
B43: Level 3 | C43: ='EDI Framework Criteria'!G34 -> 3.J.3 | D43: ='EDI Framework Criteria'!H34 -> We have processes in place to collect user data in a regular, timely and safe way. These processes have been reviewed at least once and we continue to gather user feedback about our data collection. | I43: Our organisation has not yet embedded this | K43: =INDEX($U$3:$V$13,MATCH(I43,$U$3:$U$13,0),2) -> 0
B46: Part 4 | D46: ='EDI Framework Criteria'!B35 -> Cultural needs
I48: Our organisation has- please select the appropriate dropdown option | J48: What we have done - please clearly state what your organisation has done | L48: Guidance for these statements
B49: Level 1 | C49: ='EDI Framework Criteria'!C35 -> 1.J.4 | D49: ='EDI Framework Criteria'!D35 -> We understand that some customers/user groups have culturally specific needs. We are committed to identifying cultural needs where users consent to sharing this information and adapting processes to account for these cultural needs. | I49: Our organisation has not yet committed to this | K49: =INDEX($U$3:$V$13,MATCH(I49,$U$3:$U$13,0),2) -> 0
B51: Level 2 | C51: ='EDI Framework Criteria'!E35 -> 2.J.4 | D51: ='EDI Framework Criteria'!F35 -> We have identified cultural needs and have processes in place that prioritise cultural competency in response to these needs. For example, we make interpretation available, create our content in other languages, write in plain English. | I51: Our organisation has not yet implemented this | K51: =INDEX($U$3:$V$13,MATCH(I51,$U$3:$U$13,0),2) -> 0
B53: Level 3 | C53: ='EDI Framework Criteria'!G35 -> 3.J.4 | D53: ='EDI Framework Criteria'!H35 -> We have processes in place to make sure cultural needs are valued. We continuously update these based on information gathered around cultural needs. | I53: Our organisation has not yet embedded this | K53: =INDEX($U$3:$V$13,MATCH(I53,$U$3:$U$13,0),2) -> 0
B56: Part 5 | D56: ='EDI Framework Criteria'!B36 -> Sales EDI audits
I58: Our organisation has- please select the appropriate dropdown option | J58: What we have done - please clearly state what your organisation has done | L58: Guidance for these statements
B59: Level 1 | C59: ='EDI Framework Criteria'!C36 -> 1.J.5 | D59: ='EDI Framework Criteria'!D36 -> We are committed to auditing our sales channels for inclusive language and accessibility. We will train our staff to make sure our communication to users is up to the highest EDI standards and gather feedback on inclusive language and accessibility. | I59: Our organisation has not yet committed to this | K59: =INDEX($U$3:$V$13,MATCH(I59,$U$3:$U$13,0),2) -> 0
B61: Level 2 | C61: ='EDI Framework Criteria'!E36 -> 2.J.5 | D61: ='EDI Framework Criteria'!F36 -> We audit our sales channels for inclusive language and accessibility. We train our staff to make sure our communication to users is up to the highest EDI standards and gather feedback on inclusive language and accessibility. | I61: Our organisation has not yet implemented this | K61: =INDEX($U$3:$V$13,MATCH(I61,$U$3:$U$13,0),2) -> 0
B63: Level 3 | C63: ='EDI Framework Criteria'!G36 -> 3.J.5 | D63: ='EDI Framework Criteria'!H36 -> We regularly audit our sales channels for inclusive language and accessibility. Our staff training has been reviewed at least once to ensure our communication to users is up to the highest EDI standards and we continue to gather feedback on inclusive language and accessibility. | I63: Our organisation has not yet embedded this | K63: =INDEX($U$3:$V$13,MATCH(I63,$U$3:$U$13,0),2) -> 0
B66: Part 6 | D66: ='EDI Framework Criteria'!B37 -> Sales funnel
I68: Our organisation has- please select the appropriate dropdown option | J68: What we have done - please clearly state what your organisation has done | L68: Guidance for these statements
B69: Level 1 | C69: ='EDI Framework Criteria'!C37 -> 1.J.6 | D69: ='EDI Framework Criteria'!D37 -> We are committed to making sure our sales pipeline and/ or outreach and referral pathways target marginalised groups. This includes going beyond our existing networks to reach a diverse range of people. | I69: Our organisation has not yet committed to this | K69: =INDEX($U$3:$V$13,MATCH(I69,$U$3:$U$13,0),2) -> 0
B71: Level 2 | C71: ='EDI Framework Criteria'!E37 -> 2.J.6 | D71: ='EDI Framework Criteria'!F37 -> We have a sales funnel and/ or outreach and referral pathways that target marginalised groups. This includes going beyond our existing networks to reach a diverse range of people. | I71: Our organisation has not yet implemented this | K71: =INDEX($U$3:$V$13,MATCH(I71,$U$3:$U$13,0),2) -> 0
B73: Level 3 | C73: ='EDI Framework Criteria'!G37 -> 3.J.6 | D73: ='EDI Framework Criteria'!H37 -> Our sales funnel and/ or outreach and referral pathways target marginalised groups. We adapt them using the information we collect about the affected groups. | I73: Our organisation has not yet embedded this | K73: =INDEX($U$3:$V$13,MATCH(I73,$U$3:$U$13,0),2) -> 0
B76: Part 7 | D76: ='EDI Framework Criteria'!B38 -> Representative marketing materials
I78: Our organisation has- please select the appropriate dropdown option | J78: What we have done - please clearly state what your organisation has done | L78: Guidance for these statements
B79: Level 1 | C79: ='EDI Framework Criteria'!C38 -> 1.J.7 | D79: ='EDI Framework Criteria'!D38 -> We are committed to using representative case studies and imagery in our marketing materials and website. | I79: Our organisation has not yet committed to this | K79: =INDEX($U$3:$V$13,MATCH(I79,$U$3:$U$13,0),2) -> 0
B81: Level 2 | C81: ='EDI Framework Criteria'!E38 -> 2.J.7 | D81: ='EDI Framework Criteria'!F38 -> We are starting to use representative case studies and imagery in all our marketing and website content. | I81: Our organisation has not yet implemented this | K81: =INDEX($U$3:$V$13,MATCH(I81,$U$3:$U$13,0),2) -> 0
B83: Level 3 | C83: ='EDI Framework Criteria'!G38 -> 3.J.7 | D83: ='EDI Framework Criteria'!H38 -> We consistently use representative case studies and imagery in all our marketing and website content. We regularly review our content. | I83: Our organisation has not yet embedded this | K83: =INDEX($U$3:$V$13,MATCH(I83,$U$3:$U$13,0),2) -> 0
B86: Part 8 | D86: ='EDI Framework Criteria'!B39 -> Accessible external communications
I88: Our organisation has- please select the appropriate dropdown option | J88: What we have done - please clearly state what your organisation has done | L88: Guidance for these statements
B89: Level 1 | C89: ='EDI Framework Criteria'!C39 -> 1.J.8 | D89: ='EDI Framework Criteria'!D39 -> We are committed to assessing our external communications content (such as our website and marketing materials) for accessibility by auditing it through an accessibility checker, or an accessibility expert. | I89: Our organisation has not yet committed to this | K89: =INDEX($U$3:$V$13,MATCH(I89,$U$3:$U$13,0),2) -> 0
B91: Level 2 | C91: ='EDI Framework Criteria'!E39 -> 2.J.8 | D91: ='EDI Framework Criteria'!F39 -> We have carried out an accessibility audit of our external communications content (such as our website and marketing materials). | I91: Our organisation has not yet implemented this | K91: =INDEX($U$3:$V$13,MATCH(I91,$U$3:$U$13,0),2) -> 0
B93: Level 3 | C93: ='EDI Framework Criteria'!G39 -> 3.J.8 | D93: ='EDI Framework Criteria'!H39 -> We have actioned recommended changes from our content audit across all our content and continue to regularly audit the content. | I93: Our organisation has not yet embedded this | K93: =INDEX($U$3:$V$13,MATCH(I93,$U$3:$U$13,0),2) -> 0
B98: Part 9 | D98: ='EDI Framework Criteria'!B40 -> Supply chain(s)
I100: Our organisation has- please select the appropriate dropdown option | J100: What we have done - please clearly state what your organisation has done | L100: Guidance for these statements
B101: Level 1 | C101: ='EDI Framework Criteria'!C40 -> 1.J.9 | D101: ='EDI Framework Criteria'!D40 -> We are committed to creating a plan for improving EDI through our supply chain including any deliver partners or subcontractors. | I101: Our organisation has not yet committed to this | K101: =INDEX($U$3:$V$13,MATCH(I101,$U$3:$U$13,0),2) -> 0
B103: Level 2 | C103: ='EDI Framework Criteria'!E40 -> 2.J.11 | D103: ='EDI Framework Criteria'!F40 -> We have a plan for improving EDI throughout our supply chain and any delivery partners or subcontractors. We are making changes to where needed. | I103: Our organisation has not yet implemented this | K103: =INDEX($U$3:$V$13,MATCH(I103,$U$3:$U$13,0),2) -> 0
B105: Level 3 | C105: ='EDI Framework Criteria'!G40 -> 3.J.11 | D105: ='EDI Framework Criteria'!H40 -> We engage with supply chain organisations and any delivery partners and subcontractors where possible to improve EDI. We are improving procurement in line with EDI plans. | I105: Our organisation has not yet embedded this | K105: =INDEX($U$3:$V$13,MATCH(I105,$U$3:$U$13,0),2) -> 0
B108: Part 10 | D108: ='EDI Framework Criteria'!B41 -> EDI in product and/or service iteration and R&D
I110: Our organisation has- please select the appropriate dropdown option | J110: What we have done - please clearly state what your organisation has done | L110: Guidance for these statements
B111: Level 1 | C111: ='EDI Framework Criteria'!C41 -> 1.J.10 | D111: ='EDI Framework Criteria'!D41 -> We are committed to creating a plan for improving EDI in our products and/or services. | I111: Our organisation has not yet committed to this | K111: =INDEX($U$3:$V$13,MATCH(I111,$U$3:$U$13,0),2) -> 0
B113: Level 2 | C113: ='EDI Framework Criteria'!E41 -> 2.J.12 | D113: ='EDI Framework Criteria'!F41 -> We have in place a plan for improving EDI in our products and/or services. We have started to review and make changes to our products and services. | I113: Our organisation has not yet implemented this | K113: =INDEX($U$3:$V$13,MATCH(I113,$U$3:$U$13,0),2) -> 0
B115: Level 3 | C115: ='EDI Framework Criteria'!G41 -> 3.J.12 | D115: ='EDI Framework Criteria'!H41 -> We regularly use our understanding of EDI to make our products and/or services service affected groups better. | I115: Our organisation has not yet embedded this | K115: =INDEX($U$3:$V$13,MATCH(I115,$U$3:$U$13,0),2) -> 0
B119: Previous section

Sheet EDI Framework Criteria
A1: Factor (based on the academic and grey literature) | B1: Factor element | C1: Level 1 Criteria | D1: Level 1 Statement My organisation commits to | E1: Level 2 Criteria | F1: Level 2 Statement My organisation has implemented | G1: Level 3 Criteria | H1: Level 3 Statement My organisation is managing by embedding…
A2: Understanding EDI Concepts: Knowledge of EDI concepts and frameworks | B2: Equality, Diversity, & Inclusion Characteristics (Equality Act and beyond) | C2: 1.A.1 | D2: We have committed to having a training plan for staff at all levels, including board which includes material on what is meant by "EDI Characteristics". These go beyond the 9 protected characteristics in the Equalities Act (2010). It includes characteristics like class and neurodivergence too. | E2: 2.A.1 | F2: We have a training plan for staff at all levels, including board. It explains EDI characteristics. These go beyond the 9 protected characteristics in the Equalities Act (2010). It includes characteristics like class and neurodivergence too. We have started to deliver training. | G2: 3.A.1 | H2: We have a training plan for staff at all levels, including board. It explains EDI characteristics. These go beyond the 9 protected characteristics in the Equalities Act (2010). It includes characteristics like class and neurodivergence too. The training plan has been reviewed at least once. There are plans to review it as needed. Training is given to staff at all levels.
B3: Understanding organisational power | C3: 1.A.2 | D3: We have committed to having a training plan for staff at all levels, including board. It explains what ‘organisational power’ means. | E3: 2.A.2 | F3: We have a training plan for staff at all levels, including board. It explains what ‘organisational power’ means. We’ve started some training activities. | G3: 3.A.2 | H3: We have a training plan for staff at all levels, including board. It explains what ‘organisational power’ means. The training plan has been reviewed at least once. There are plans to review it as needed. Training is given to staff at all levels.
B4: Tackling organisational barriers to Equality, Diversity and Inclusion | C4: 1.A.3 | D4: We have committed to having a training plan for staff at all levels, including board. It explains what ‘organisational barriers to EDI’ means. | E4: 2.A.3 | F4: We have a training plan for staff at all levels, including board. It explains what ‘organisational barriers to EDI’ means. We’ve started some training activities. | G4: 3.A.3 | H4: We have a training plan for staff at all levels, including board. It explains what ‘organisational barriers to EDI’ means. The training plan has been reviewed at least once. There are plans to review it as needed. Training is given to staff at all levels.
B5: Our role in structural discrimination | C5: 1.A.4 | D5: We have committed to having a training plan for staff at all levels, including board. It explains what is meant by 'structural discrimination'. | E5: 2.A.4 | F5: We have a training plan for staff at all levels, including board. It explains what is meant by 'structural discrimination'. We’ve started some training activities. | G5: 3.A.4 | H5: We have a training plan for staff at all levels, including board. It explains what is meant by 'structural discrimination'. The training plan has been reviewed at least once. There are plans to review it as needed. Training is given to staff at all levels.
B6: Intersectionality | C6: 1.A.5 | D6: We have a training plan for staff at all levels, including board. It explains what ‘intersectionality’ means. | E6: 2.A.5 | F6: We have a training plan for staff at all levels, including board. It explains what ‘intersectionality’ means. We’ve started some training activities. | G6: 3.A.5 | H6: We have a training plan for staff at all levels, including board. It explains what ‘intersectionality’ means. The training plan has been reviewed at least once. There are plans to review it as needed. Training is given to staff at all levels.
A7: Mission and Policies | B7: Social mission | C7: 1.B.1 | D7: We have committed to producing a mission or vision statement which shows a clear organisational commitment to improving Equality, Diversity and Inclusion. | E7: 2.B.1 | F7: We have a mission or vision statement which shows our commitment to improving Equality, Diversity and Inclusion. | G7: 3.B.1 | H7: We have a mission or vision statement which shows our commitment to improving EDI. We have reviewed it at least once, and will keep making updates as our EDI work goes on. We have shared it internally and externally, and invited comments from affected people. We share this statement on a range of public materials, like terms of references and procurement materials.
B8: Individual responsibilities | C8: 1.B.2 | D8: We are committed to creating a document that explains what people's personal responsibilities are for working towards EDI. | E8: 2.B.2 | F8: We have created a document that explains what people's personal responsibilities are for working towards EDI. | G8: 3.B.2 | H8: We have a document that explains what everyone’s responsibilities are for working towards EDI. We have reviewed it at least once, and will keep making updates as our EDI work goes on.
B9: Targets for Equality, Diversity and Inclusion | C9: 1.B.3 | D9: We have committed to setting relevant targets for EDI. This will include targets for outputs and outcomes. | E9: 2.B.3 | F9: We have set relevant targets for EDI. We are tracking not only outputs but also outcomes. | G9: 3.B.3 | H9: We have set relevant targets for EDI. We are tracking not only outputs but also outcomes. Our targets have been reviewed at least once, with input from stakeholders. We have revised the targets as needed, and will keep revising them as our EDI work goes on.
B10: Working with marginalised groups | C10: 1.B.4 | D10: We have committed to creating a policy or action plan with clear commitments to identify and support marginalised groups. | E10: 2.B.4 | F10: We have a policy or action plan with clear commitments to identify and support marginalised groups. This has been agreed to by senior management or the board. | G10: 3.B.4 | H10: We have a policy or action plan with clear commitments to identify and support marginalised groups. We have reviewed it at least once, and will keep making updates as our EDI work goes on.
A11: Theory of Change | B11: Theory of Change | C11: 1.C.1 | D11: We have committed to creating a Theory of Change for how EDI outcomes are created by our activities. This will include positive and negative outcomes; cover all our stakeholder groups; and include inputs and outputs. | E11: 2.C.1 | F11: We have a Theory of Change for how EDI outcomes are created by our activities. This includes positive and negative outcomes; covers all our stakeholder groups; and includes inputs and outputs. | G11: 3.C.1 | H11: We have a Theory of Change for how EDI outcomes are created by our activities. This includes positive and negative outcomes; covers all our stakeholder groups; and includes inputs and outputs. We collect relevant EDI data and use it to update the Theory of Change. We have reviewed it at least once, and will keep making updates as our EDI work goes on.
A12: Equality, Diversity and Inclusion Advocacy | B12: Equality, Diversity and Inclusion training | C12: 1.D.1 | D12: We have committed to creating a training plan for staff across all levels including board level for embedding EDI practice into their organisational practice and decision making. | E12: 2.D.1 | F12: A training plan for staff across all levels including board level for embedding EDI practice into organisational practice has been developed. Some training activities have started. | G12: 3.D.1 | H12: The training plan for staff across all levels including board level for embedding EDI practice into organisational practice is in place. The plan has been reviewed at least once, with plans to continue to review as needed. Activities for all levels are underway. Training around EDI practice is included in new staff induction or training at all levels of the organisation (in line with the needs of their role).
B13: Equality, Diversity and Inclusion resourcing | C13: 1.D.2 | D13: We have committed to creating an organisational commitment to EDI by allocating resources for EDI management and capacity building. | E13: 2.D.2 | F13: Resources have been allocated for EDI management and capacity building. | G13: 3.D.2 | H13: Resources continue to be allocated for EDI management and capacity building, and are reviewed and revised as necessary.
A14: Equality, Diversity and Inclusion Data Analysis and Evaluation | B14: Collection of specific data, including outcomes | C14: 1.E.1 | D14: We have committed to tracking information from all stakeholder groups to collect the following data for outcomes measurement: - Numbers of people experiencing each outcome (scale) - Extent of change for each outcome (depth) - The EDI characteristics of stakeholders | E14: 2.E.1 | F14: Outcomes are starting to be measured involving all stakeholder groups. The measurement includes: - Numbers of people experiencing each outcome (scale) - Extent of change for each outcome (depth) - The EDI characteristics of stakeholders | G14: 3.E.1 | H14: Outcomes are being measured on a regular basis. Measurement includes: - Numbers of people experiencing each outcome (scale) - Extent of change for each outcome (depth) - The EDI characteristics of stakeholders
C15: 1.E.7 | D15: We have committed to creating a plan for which EDI characteristics to track when we are measuring outcomes. We look at all 9 protected characteristics in the Equalities Act (2010) and more, for example, socioeconomic class. | E15: 2.E.7 | F15: We identified which EDI characteristics to track when we are measuring outcomes. We look at all 9 protected characteristics in the Equalities Act (2010) and more, for example, socioeconomic class. We are integrating these into our outcomes measurement. | G15: 3.E.7 | H15: Our stakeholders’ EDI characteristics are included in our outcomes measurement. We look at all 9 protected characteristics in the Equalities Act (2010) and more, for example, socioeconomic class. We review and revise them regularly.
B16: Social value verification | C16: 1.E.3 | D16: We have committed to seeking feedback from a third-party on our EDI data collection and analysis. This could be through a critical friend, peer review, or through a more formal assurance provider. | E16: 2.E.3 | F16: We have had feedback from a third-party on our EDI data collection and analysis. Explanation given about choice of third party and any associated risks of choice (this could be a critical friend, peer review or a more formal assurance provider). | G16: 3.E.3 | H16: EDI data collection and analysis are continuing to be reviewed by a third party. Any issues identified by the third party have been recorded and action taken to address the issues. Risks of choice of third party considered and addressed (this could be a critical friend, peer review or a more formal assurance provider).
B17: Transparency around Equality, Diversity and Inclusion practice | C17: 1.E.4 | D17: We have committed to creating reports on our EDI data and practices. These will cover: - Scope of the activities, - Our audience, - Why we’re conducting analysis, - Limitations or risks of using this data, - Performance against our targets, - Recommendations for improvement. We may use different types of reporting for internal and external audiences. | E17: 2.E.4 | F17: We are starting to create reports on our EDI data and practices. These cover: - Scope of the activities, - Our audience, - Why we’re conducting analysis, - Limitations or risks of using this data, - Performance against our targets, - Recommendations for improvement. We may use different types of reporting for internal and external audiences. | G17: 3.E.4 | H17: We regularly create reports on our EDI data and practices. These cover: - Scope of the activities, - Our audience, - Why we’re conducting analysis, - Limitations or risks of using this data, - Performance against our targets, - Recommendations for improvement. We may use different types of reporting for internal and external audiences.
C18: 1.E.5 | D18: We have committed to recording the limitations and risks of our EDI data collection and analysis. This will include gaps, sources of potential bias, and how far we’ve involved stakeholders. We will identify where other sources of data are needed, and how they can be compared. | E18: 2.E.5 | F18: We have recorded the limitations and risks of our EDI data collection and analysis. We have included gaps, sources of potential bias, and how far we’ve involved stakeholders. We have taken steps to identify and address limitations or risks around this data. | G18: 3.E.5 | H18: We are continually checking for limitations and risks to our EDI data collection and analysis. We make any necessary changes to our data collection and analysis processes.
B19: Measuring inclusion | C19: 1.E.6 | D19: We have committed to setting up a strong system for collecting and recording information on inclusion. We will collect information on inclusion. We will break that data down by relevant EDI characteristics, going beyond the 9 protected characteristics to include other areas like class or neurodivergence. | E19: 2.E.6 | F19: A system for collecting and recording information on inclusion has been established. We are starting to collect information on inclusion. We are starting to break that data down by relevant EDI characteristics, going beyond the 9 protected characteristics to include other areas like class or neurodivergence. | G19: 3.E.6 | H19: Our system for collecting and recording information on inclusion is in place. We collect information on inclusion, and break that data down by relevant EDI characteristics, going beyond the 9 protected characteristics to include other areas like class or neurodivergence. Not all groups have the same needs, so we make changes to our systems to make them more just and equitable.
A20: Stakeholder engagement: Understanding approach towards previously omitted groups in service provision and activities | B20: Stakeholder mapping | C20: 1.F.1 | D20: We have committed to mapping out our stakeholder groups (and identify sub groups) for the activities that we plan to include in our EDI practice. | E20: 2.F.1 | F20: We have mapped out the stakeholder groups (and subgroups) affected by our EDI practice. | G20: 3.F.1 | H20: We have mapped out the stakeholder groups (and subgroups) affected by our EDI practice. We review and revise this as needed.
B21: Stakeholder engagement | C21: 1.F.2 | D21: We have committed to creating a plan to engage with people from all stakeholder groups. | E21: 2.F.2 | F21: We have created a plan to engage with people from all stakeholder groups. We are collecting feedback from stakeholders on how effective this plan is in practice. | G21: 3.F.2 | H21: A plan to engage with people from all stakeholder groups has been developed. We are collecting feedback from stakeholders on how effective this plan is in practice.
B22: Defining outcomes | C22: 1.F.3 | D22: We plan to involve stakeholder groups to understand the outcomes they are experiencing, and why. We will use open-ended questions to identify outcomes which are positive, negative, intended, and unintended. | E22: 2.F.3 | F22: We have involved stakeholder groups to understand the outcomes they are experiencing, and why. We have used use open-ended questions to identify outcomes which are positive, negative, intended, and unintended. | G22: 3.F.3 | H22: Outcomes are reviewed and revised based on ongoing stakeholder engagement.
B23: General feedback on Equality, Diversity and Inclusion | C23: 1.F.4 | D23: We have committed to establishing or adapting mechanisms for collecting and recording feedback on EDI. This could include surveys, focus groups or suggestion schemes. | E23: 2.F.4 | F23: We have in place mechanisms for collecting and recording feedback on EDI. This could include surveys, focus groups or suggestion schemes. | G23: 3.F.4 | H23: We have reviewed feedback mechanisms at least once. We kept a record of how feedback has been responded to
A24: Diversity management: EDI integrated into every part of the organisation’s work. | B24: Groups set up and tasked with Equality, Diversity and Inclusion | C24: 1.G.1 | D24: We have committed to identifying EDI lead/s and creating a working group or forum with representation from across the organisation. This should report to, and receive support from, the board or senior management. | E24: 2.G.1 | F24: EDI lead/s and a working group or forum with representation from across the organisation have started work. They report to, and receive support from, the board or senior management. | G24: 3.G.1 | H24: EDI lead/s and working group or forum meet regularly. They are given support by the board or senior management, and also report on their activities.
B25: Accountability mechanisms for Equality, Diversity and Inclusion issues | C25: 1.G.2 | D25: We have committed to creating a policy or action plan to cover accountability mechanisms for EDI practice. This will outline the responsibilities of our governance, for example, our board. | E25: 2.G.2 | F25: We have created a policy or action plan to cover accountability mechanisms for EDI practice. This outlines the responsibilities of our governance, for example, our board. | G25: 3.G.2 | H25: We have a policy or action plan in place to cover accountability mechanisms for EDI practice. It outlines the responsibilities of our governance, for example, our board. It has been reviewed at least once. We have plans to keep reviewing it as needed.
B26: Mechanisms have been set up to address Equality, Diversity and Inclusion incidents | C26: 1.G.3 | D26: We are committed to creating or adapting an existing complaint or whistleblowing process. These processes will include support for people making the complaint. The processes will be accessible to internal and external stakeholders. | E26: 2.G.3 | F26: We have created or adapted an existing complaint or whistleblowing process. These processes include support for people making the complaint. The processes are accessible to internal and external stakeholders. | G26: 3.G.3 | H26: Our complaint or whistleblowing process is in place, and has been reviewed at least once. We keep a record of how incidents or concerns have been addressed.
A27: Work integration: Managers and governance reflect diversity of wider workforce | B27: Staff diversity and hiring practices | C27: 1.H.1 | D27: We are committed to creating a plan to improve EDI within our recruitment. This may include adapting language used in job adverts, promoting flexible and remote working, and reaching out to diverse networks. | E27: 2.H.1 | F27: We have a plan to improve EDI within our recruitment. This can include adapting language used in job adverts, promoting flexible and remote working, and reaching out to diverse networks. | G27: 3.H.1 | H27: A plan to improve EDI within our recruitment is in place. We have reviewed our practices at least once, and made changes. We will continue to review and make changes as needed.
B28: Career progression | C28: 1.H.2 | D28: We are committed to creating a plan to improve EDI within career progression. This should include tracking and recording changes (including who is joining, progressing, and leaving the organisation), and possible reasons. | E28: 2.H.2 | F28: We have a plan to improve EDI within career progression. We are tracking information to understand how employees progress, and what structural barriers exist. We are making changes based on this. | G28: 3.H.2 | H28: We have put in place our plan to improve EDI within career progression. We have recorded information on how our employees progress, and what structural barriers exist. We have made changes based on this, and will keep doing so.
B29: Board diversity | C29: 1.H.3 | D29: We are committed to creating a plan or policy to improve EDI within our board and senior leadership team. This will include an understanding of changes (like who is joining and leaving the board and senior leadership positions), and reasons why. | E29: 2.H.3 | F29: We have created a plan or policy to improve EDI within our board and senior leadership team. This includes an understanding of changes (like who is joining and leaving the board and senior leadership positions), and reasons why. We are starting to make changes based on this. | G29: 3.H.3 | H29: We have a plan or policy in place to improve EDI within our board and senior leadership team. We are using our understanding of changes (like who is joining and leaving the board and senior leadership positions), and reasons why to address structural barriers.
B30: Mentoring | C30: 1.H.4 | D30: We are committed to creating a mentoring scheme to help improve EDI. We will consider who is involved in the scheme, what their EDI characteristics are, and what outcomes they experience. | E30: 2.H.4 | F30: We have a mentoring scheme to help improve EDI. We have considered who is involved in the scheme, what their EDI characteristics are, and what outcomes they experience. We are collecting information to track this. | G30: 3.H.4 | H30: We have put in place our plan for improving EDI through a mentoring scheme for staff. We used our understanding of who is participating and what outcomes they experience to maximise positive impact. We will continue to review and make changes.
A31: Support | B31: Professional support | C31: 1.I.1 | D31: We are committed to creating a plan for identifying experts, organisations, associations, or membership bodies that can help us improve our EDI practice. | E31: 2.I.1 | F31: We have identified experts, organisations, associations, or membership bodies that can help us improve our EDI practice. We have engaged with them in some way. | G31: 3.I.1 | H31: We’re in continuing contact with experts, organisations, associations, or membership bodies that can help us improve our EDI practice. Where possible, we are sharing our practice with other organisations. This helps create a community of practice, which we can all learn from.
A32: Business Model | B32: Value proposition | C32: 1.J.1 | D32: We are committed to creating a plan to assess whether products and services are designed and delivered in a way that is accessible to our stakeholders e.g. taking into account step free access to a location. | E32: 2.J.1 | F32: We have developed a plan to assess whether products and services are designed and delivered in a way that is accessible to our stakeholders. We have a way to respond to feedback and action changes. | G32: 3.J.1 | H32: We have in place a plan to assess whether products and services are designed and delivered in a way that is accessible to our stakeholders. Accessibility and inclusion are top considerations when we are creating products and services.
B33: Customer/ user preferences | C33: 1.J.2 | D33: We are committed to collecting data on our users’ wants and needs regarding pricing of products and or services. | E33: 2.J.2 | F33: We have collected data on our users’ wants and needs regarding pricing of products and or services and use this information in pricing model decisions. | G33: 3.J.2 | H33: We have a pricing model that makes affordability a key consideration. We use this to make products and services affordable to our users e.g. using a subsidy model for low-income individuals where appropriate. Our pricing model has been reviewed at least once.
B34: Customer/ user data collection preferences | C34: 1.J.3 | D34: We are committed to developing systems to collect user data in a regular, timely and safe way. Included in this is a plan to gather feedback from customers/ users on their data collection preferences through formats such as advisory groups or anonymous surveys. | E34: 2.J.3 | F34: We have processes in place to collect user data in a regular, timely and safe way. This is supported by feedback from customers/ users around their data collection preferences. | G34: 3.J.3 | H34: We have processes in place to collect user data in a regular, timely and safe way. These processes have been reviewed at least once and we continue to gather user feedback about our data collection.
B35: Cultural needs | C35: 1.J.4 | D35: We understand that some customers/user groups have culturally specific needs. We are committed to identifying cultural needs where users consent to sharing this information and adapting processes to account for these cultural needs. | E35: 2.J.4 | F35: We have identified cultural needs and have processes in place that prioritise cultural competency in response to these needs. For example, we make interpretation available, create our content in other languages, write in plain English. | G35: 3.J.4 | H35: We have processes in place to make sure cultural needs are valued. We continuously update these based on information gathered around cultural needs.
B36: Sales EDI audits | C36: 1.J.5 | D36: We are committed to auditing our sales channels for inclusive language and accessibility. We will train our staff to make sure our communication to users is up to the highest EDI standards and gather feedback on inclusive language and accessibility. | E36: 2.J.5 | F36: We audit our sales channels for inclusive language and accessibility. We train our staff to make sure our communication to users is up to the highest EDI standards and gather feedback on inclusive language and accessibility. | G36: 3.J.5 | H36: We regularly audit our sales channels for inclusive language and accessibility. Our staff training has been reviewed at least once to ensure our communication to users is up to the highest EDI standards and we continue to gather feedback on inclusive language and accessibility.
B37: Sales funnel | C37: 1.J.6 | D37: We are committed to making sure our sales pipeline and/ or outreach and referral pathways target marginalised groups. This includes going beyond our existing networks to reach a diverse range of people. | E37: 2.J.6 | F37: We have a sales funnel and/ or outreach and referral pathways that target marginalised groups. This includes going beyond our existing networks to reach a diverse range of people. | G37: 3.J.6 | H37: Our sales funnel and/ or outreach and referral pathways target marginalised groups. We adapt them using the information we collect about the affected groups.
B38: Representative marketing materials | C38: 1.J.7 | D38: We are committed to using representative case studies and imagery in our marketing materials and website. | E38: 2.J.7 | F38: We are starting to use representative case studies and imagery in all our marketing and website content. | G38: 3.J.7 | H38: We consistently use representative case studies and imagery in all our marketing and website content. We regularly review our content.
B39: Accessible external communications | C39: 1.J.8 | D39: We are committed to assessing our external communications content (such as our website and marketing materials) for accessibility by auditing it through an accessibility checker, or an accessibility expert. | E39: 2.J.8 | F39: We have carried out an accessibility audit of our external communications content (such as our website and marketing materials). | G39: 3.J.8 | H39: We have actioned recommended changes from our content audit across all our content and continue to regularly audit the content.
B40: Supply chain(s) | C40: 1.J.9 | D40: We are committed to creating a plan for improving EDI through our supply chain including any deliver partners or subcontractors. | E40: 2.J.11 | F40: We have a plan for improving EDI throughout our supply chain and any delivery partners or subcontractors. We are making changes to where needed. | G40: 3.J.11 | H40: We engage with supply chain organisations and any delivery partners and subcontractors where possible to improve EDI. We are improving procurement in line with EDI plans.
B41: EDI in product and/or service iteration and R&D | C41: 1.J.10 | D41: We are committed to creating a plan for improving EDI in our products and/or services. | E41: 2.J.12 | F41: We have in place a plan for improving EDI in our products and/or services. We have started to review and make changes to our products and services. | G41: 3.J.12 | H41: We regularly use our understanding of EDI to make our products and/or services service affected groups better.

Sheet EDI score outcomes
B2: Score outcomes
B3: Below are the scores calculated from your answers in each of the 10 sections. On the right hand side, an overall score is calculated which enables your organisation to track your progress over time. This sheet is calculated automatically from your answers and requires no edits.
E5: Understanding EDI Concepts | F5: Mission and policies | G5: Theory of Change | H5: EDI Advocacy | I5: Analysis and Evaluation | J5: Stakeholder Engagement | K5: Diversity Management | L5: Work Integration | M5: Support | N5: Business Model
B6: DEI Scorecard overview | E6: Section 1 | F6: Section 2 | G6: Section 3 | H6: Section 4 | I6: Section 5 | J6: Section 6 | K6: Section 7 | L6: Section 8 | M6: Section 9 | N6: Section 10
B8: Average score | E8: =AVERAGE(E25:E34) -> 0 | F8: =AVERAGE(F25:F34) -> 0 | G8: =AVERAGE(G25:G34) -> 0 | H8: =AVERAGE(H25:H34) -> 0 | I8: =AVERAGE(I25:I34) -> 0 | J8: =AVERAGE(J25:J34) -> 0 | K8: =AVERAGE(K25:K34) -> 0 | L8: =AVERAGE(L25:L34) -> 0 | ... N8: =AVERAGE(N25:N34) -> 0 | P8: For GIF DD process | Q8: Score | R8: Out of
B9: Modal score | E9: =_xlfn.MODE.SNGL(E25:E34) -> 0 | F9: =_xlfn.MODE.SNGL(F25:F34) -> 0 | G9: =G25 -> 0 | I9: =_xlfn.MODE.SNGL(I25:I34) -> 0 | J9: =_xlfn.MODE.SNGL(J25:J34) -> 0 | K9: =_xlfn.MODE.SNGL(K25:K34) -> 0 | L9: =_xlfn.MODE.SNGL(L25:L34) -> 0 | M9: =M25 -> 0 | N9: =_xlfn.MODE.SNGL(N25:N34) -> 0 | P9: Portfolio Scorecard | Q9: =ROUND(Q38*10,1) -> 0 | R9: 10
B10: % achieved | E10: =E35/(E23*6) -> 0 | F10: =F35/(F23*6) -> 0 | G10: =G35/(G23*6) -> 0 | H10: =H35/(H23*6) -> 0 | I10: =I35/(I23*6) -> 0 | J10: =J35/(J23*6) -> 0 | K10: =K35/(K23*6) -> 0 | L10: =L35/(L23*6) -> 0 | ... N10: =N35/(N23*6) -> 0 | P10: Impact Charter Score | Q10: =ROUND(12*(Q9/10),0) -> 0 | R10: 12
B12: Level 1 No | C12: 0 | D12: Commit | E12: =COUNTIFS('Full Score Matrix'!$A$3:$A$17,$D$12,'Full Score Matrix'!$C$3:$C$17,0) -> 5 | F12: =COUNTIFS('Full Score Matrix'!$A$3:$A$14,$D$12,'Full Score Matrix'!$D$3:$D$14,0) -> 4 | G12: =COUNTIFS('Full Score Matrix'!$A$3:$A$32,$D$12,'Full Score Matrix'!$E$3:$E$32,0) -> 1 | H12: =COUNTIFS('Full Score Matrix'!$A$3:$A$32,$D$12,'Full Score Matrix'!$F$3:$F$32,0) -> 2 | I12: =COUNTIFS('Full Score Matrix'!$A$3:$A$32,$D$12,'Full Score Matrix'!$G$3:$G$32,0) -> 6 | J12: =COUNTIFS('Full Score Matrix'!$A$3:$A$32,$D$12,'Full Score Matrix'!$H$3:$H$32,0) -> 4 | K12: =COUNTIFS('Full Score Matrix'!$A$3:$A$32,$D$12,'Full Score Matrix'!$I$3:$I$32,0) -> 3 | L12: =COUNTIFS('Full Score Matrix'!$A$3:$A$14,$D$12,'Full Score Matrix'!$J$3:$J$14,0) -> 4 | M12: =COUNTIFS('Full Score Matrix'!$A$3:$A$32,$D$12,'Full Score Matrix'!$K$3:$K$32,0) -> 1 | N12: =COUNTIFS('Full Score Matrix'!$A$3:$A$32,$D$12,'Full Score Matrix'!$L$3:$L$32,0) -> 10
B13: Level 1 In progress | C13: 1 | E13: =COUNTIFS('Full Score Matrix'!$A$3:$A$17,$D$12,'Full Score Matrix'!$C$3:$C$17,1) -> 0 | F13: =COUNTIFS('Full Score Matrix'!$A$3:$A$14,$D$12,'Full Score Matrix'!$D$3:$D$14,1) -> 0 | G13: =COUNTIFS('Full Score Matrix'!$A$3:$A$32,$D$12,'Full Score Matrix'!$E$3:$E$32,1) -> 0 | H13: =COUNTIFS('Full Score Matrix'!$A$3:$A$32,$D$12,'Full Score Matrix'!$F$3:$F$32,1) -> 0 | I13: =COUNTIFS('Full Score Matrix'!$A$3:$A$32,$D$12,'Full Score Matrix'!$G$3:$G$32,1) -> 0 | J13: =COUNTIFS('Full Score Matrix'!$A$3:$A$32,$D$12,'Full Score Matrix'!$H$3:$H$32,1) -> 0 | K13: =COUNTIFS('Full Score Matrix'!$A$3:$A$32,$D$12,'Full Score Matrix'!$I$3:$I$32,1) -> 0 | L13: =COUNTIFS('Full Score Matrix'!$A$3:$A$14,$D$12,'Full Score Matrix'!$J$3:$J$14,1) -> 0 | M13: =COUNTIFS('Full Score Matrix'!$A$3:$A$32,$D$12,'Full Score Matrix'!$K$3:$K$32,1) -> 0 | N13: =COUNTIFS('Full Score Matrix'!$A$3:$A$32,$D$12,'Full Score Matrix'!$L$3:$L$32,1) -> 0
B14: Level 1 Committed | C14: 2 | E14: =COUNTIFS('Full Score Matrix'!$A$3:$A$17,$D$12,'Full Score Matrix'!$C$3:$C$17,2) -> 0 | F14: =COUNTIFS('Full Score Matrix'!$A$3:$A$14,$D$12,'Full Score Matrix'!$D$3:$D$14,2) -> 0 | G14: =COUNTIFS('Full Score Matrix'!$A$3:$A$32,$D$12,'Full Score Matrix'!$E$3:$E$32,2) -> 0 | H14: =COUNTIFS('Full Score Matrix'!$A$3:$A$32,$D$15,'Full Score Matrix'!$F$3:$F$32,2) -> 0 | I14: =COUNTIFS('Full Score Matrix'!$A$3:$A$32,$D$15,'Full Score Matrix'!$G$3:$G$32,2) -> 0 | J14: =COUNTIFS('Full Score Matrix'!$A$3:$A$32,$D$15,'Full Score Matrix'!$H$3:$H$32,2) -> 0 | K14: =COUNTIFS('Full Score Matrix'!$A$3:$A$32,$D$15,'Full Score Matrix'!$I$3:$I$32,2) -> 0 | L14: =COUNTIFS('Full Score Matrix'!$A$3:$A$14,$D$12,'Full Score Matrix'!$J$3:$J$14,2) -> 0 | M14: =COUNTIFS('Full Score Matrix'!$A$3:$A$32,$D$15,'Full Score Matrix'!$K$3:$K$32,2) -> 0 | N14: =COUNTIFS('Full Score Matrix'!$A$3:$A$32,$D$15,'Full Score Matrix'!$L$3:$L$32,2) -> 0
B15: Level 2 No | C15: 0 | D15: Implement | E15: =COUNTIFS('Full Score Matrix'!$A$3:$A$17,$D$15,'Full Score Matrix'!$C$3:$C$17,0) -> 5 | F15: =COUNTIFS('Full Score Matrix'!$A$3:$A$14,$D$15,'Full Score Matrix'!$D$3:$D$14,0) -> 4 | G15: =COUNTIFS('Full Score Matrix'!$A$3:$A$32,$D$15,'Full Score Matrix'!$E$3:$E$32,0) -> 1 | H15: =COUNTIFS('Full Score Matrix'!$A$3:$A$32,$D$15,'Full Score Matrix'!$F$3:$F$32,0) -> 2 | I15: =COUNTIFS('Full Score Matrix'!$A$3:$A$32,$D$15,'Full Score Matrix'!$G$3:$G$32,0) -> 6 | J15: =COUNTIFS('Full Score Matrix'!$A$3:$A$32,$D$15,'Full Score Matrix'!$H$3:$H$32,0) -> 4 | K15: =COUNTIFS('Full Score Matrix'!$A$3:$A$32,$D$15,'Full Score Matrix'!$I$3:$I$32,0) -> 3 | L15: =COUNTIFS('Full Score Matrix'!$A$3:$A$14,$D$15,'Full Score Matrix'!$J$3:$J$14,0) -> 4 | M15: =COUNTIFS('Full Score Matrix'!$A$3:$A$32,$D$15,'Full Score Matrix'!$K$3:$K$32,0) -> 1 | N15: =COUNTIFS('Full Score Matrix'!$A$3:$A$32,$D$15,'Full Score Matrix'!$L$3:$L$32,0) -> 10
B16: Level 2 In progress | C16: 1 | E16: =COUNTIFS('Full Score Matrix'!$A$3:$A$17,$D$15,'Full Score Matrix'!$C$3:$C$17,1) -> 0 | F16: =COUNTIFS('Full Score Matrix'!$A$3:$A$14,$D$15,'Full Score Matrix'!$D$3:$D$14,1) -> 0 | G16: =COUNTIFS('Full Score Matrix'!$A$3:$A$32,$D$15,'Full Score Matrix'!$E$3:$E$32,1) -> 0 | H16: =COUNTIFS('Full Score Matrix'!$A$3:$A$32,$D$15,'Full Score Matrix'!$F$3:$F$32,1) -> 0 | I16: =COUNTIFS('Full Score Matrix'!$A$3:$A$32,$D$15,'Full Score Matrix'!$G$3:$G$32,1) -> 0 | J16: =COUNTIFS('Full Score Matrix'!$A$3:$A$32,$D$15,'Full Score Matrix'!$H$3:$H$32,1) -> 0 | K16: =COUNTIFS('Full Score Matrix'!$A$3:$A$32,$D$15,'Full Score Matrix'!$I$3:$I$32,1) -> 0 | L16: =COUNTIFS('Full Score Matrix'!$A$3:$A$14,$D$15,'Full Score Matrix'!$J$3:$J$14,1) -> 0 | M16: =COUNTIFS('Full Score Matrix'!$A$3:$A$32,$D$15,'Full Score Matrix'!$K$3:$K$32,1) -> 0 | N16: =COUNTIFS('Full Score Matrix'!$A$3:$A$32,$D$15,'Full Score Matrix'!$L$3:$L$32,1) -> 0
B17: Level 2 Implemented | C17: 2 | E17: =COUNTIFS('Full Score Matrix'!$A$3:$A$17,$D$15,'Full Score Matrix'!$C$3:$C$17,2) -> 0 | F17: =COUNTIFS('Full Score Matrix'!$A$3:$A$14,$D$15,'Full Score Matrix'!$D$3:$D$14,2) -> 0 | G17: =COUNTIFS('Full Score Matrix'!$A$3:$A$32,$D$15,'Full Score Matrix'!$E$3:$E$32,2) -> 0 | H17: =COUNTIFS('Full Score Matrix'!$A$3:$A$32,$D$15,'Full Score Matrix'!$F$3:$F$32,2) -> 0 | I17: =COUNTIFS('Full Score Matrix'!$A$3:$A$32,$D$15,'Full Score Matrix'!$G$3:$G$32,2) -> 0 | J17: =COUNTIFS('Full Score Matrix'!$A$3:$A$32,$D$15,'Full Score Matrix'!$H$3:$H$32,2) -> 0 | K17: =COUNTIFS('Full Score Matrix'!$A$3:$A$32,$D$15,'Full Score Matrix'!$I$3:$I$32,2) -> 0 | L17: =COUNTIFS('Full Score Matrix'!$A$3:$A$14,$D$15,'Full Score Matrix'!$J$3:$J$14,2) -> 0 | M17: =COUNTIFS('Full Score Matrix'!$A$3:$A$32,$D$15,'Full Score Matrix'!$K$3:$K$32,2) -> 0 | N17: =COUNTIFS('Full Score Matrix'!$A$3:$A$32,$D$18,'Full Score Matrix'!$L$3:$L$32,2) -> 0
B18: Level 3 No | C18: 0 | D18: Embed | E18: =COUNTIFS('Full Score Matrix'!$A$3:$A$17,$D$18,'Full Score Matrix'!$C$3:$C$17,0) -> 5 | F18: =COUNTIFS('Full Score Matrix'!$A$3:$A$14,$D$18,'Full Score Matrix'!$D$3:$D$14,0) -> 4 | G18: =COUNTIFS('Full Score Matrix'!$A$3:$A$32,$D$18,'Full Score Matrix'!$E$3:$E$32,0) -> 1 | H18: =COUNTIFS('Full Score Matrix'!$A$3:$A$32,$D$18,'Full Score Matrix'!$F$3:$F$32,0) -> 2 | I18: =COUNTIFS('Full Score Matrix'!$A$3:$A$32,$D$18,'Full Score Matrix'!$G$3:$G$32,0) -> 6 | J18: =COUNTIFS('Full Score Matrix'!$A$3:$A$32,$D$18,'Full Score Matrix'!$H$3:$H$32,0) -> 4 | K18: =COUNTIFS('Full Score Matrix'!$A$3:$A$32,$D$18,'Full Score Matrix'!$I$3:$I$32,0) -> 3 | L18: =COUNTIFS('Full Score Matrix'!$A$3:$A$14,$D$18,'Full Score Matrix'!$J$3:$J$14,0) -> 4 | M18: =COUNTIFS('Full Score Matrix'!$A$3:$A$32,$D$18,'Full Score Matrix'!$K$3:$K$32,0) -> 1 | N18: =COUNTIFS('Full Score Matrix'!$A$3:$A$32,$D$18,'Full Score Matrix'!$L$3:$L$32,0) -> 10
B19: Level 3 In progress | C19: 1 | E19: =COUNTIFS('Full Score Matrix'!$A$3:$A$17,$D$18,'Full Score Matrix'!$C$3:$C$17,1) -> 0 | F19: =COUNTIFS('Full Score Matrix'!$A$3:$A$14,$D$18,'Full Score Matrix'!$D$3:$D$14,1) -> 0 | G19: =COUNTIFS('Full Score Matrix'!$A$3:$A$32,$D$18,'Full Score Matrix'!$E$3:$E$32,1) -> 0 | H19: =COUNTIFS('Full Score Matrix'!$A$3:$A$32,$D$18,'Full Score Matrix'!$F$3:$F$32,1) -> 0 | I19: =COUNTIFS('Full Score Matrix'!$A$3:$A$32,$D$18,'Full Score Matrix'!$G$3:$G$32,1) -> 0 | J19: =COUNTIFS('Full Score Matrix'!$A$3:$A$32,$D$18,'Full Score Matrix'!$H$3:$H$32,1) -> 0 | K19: =COUNTIFS('Full Score Matrix'!$A$3:$A$32,$D$18,'Full Score Matrix'!$I$3:$I$32,1) -> 0 | L19: =COUNTIFS('Full Score Matrix'!$A$3:$A$14,$D$18,'Full Score Matrix'!$J$3:$J$14,1) -> 0 | M19: =COUNTIFS('Full Score Matrix'!$A$3:$A$32,$D$18,'Full Score Matrix'!$K$3:$K$32,1) -> 0 | N19: =COUNTIFS('Full Score Matrix'!$A$3:$A$32,$D$18,'Full Score Matrix'!$L$3:$L$32,1) -> 0
B20: Level 3 Embedded | C20: 2 | E20: =COUNTIFS('Full Score Matrix'!$A$3:$A$17,$D$18,'Full Score Matrix'!$C$3:$C$17,2) -> 0 | F20: =COUNTIFS('Full Score Matrix'!$A$3:$A$14,$D$18,'Full Score Matrix'!$D$3:$D$14,2) -> 0 | G20: =COUNTIFS('Full Score Matrix'!$A$3:$A$32,$D$18,'Full Score Matrix'!$E$3:$E$32,2) -> 0 | H20: =COUNTIFS('Full Score Matrix'!$A$3:$A$32,$D$18,'Full Score Matrix'!$F$3:$F$32,2) -> 0 | I20: =COUNTIFS('Full Score Matrix'!$A$3:$A$32,$D$18,'Full Score Matrix'!$G$3:$G$32,2) -> 0 | J20: =COUNTIFS('Full Score Matrix'!$A$3:$A$32,$D$18,'Full Score Matrix'!$H$3:$H$32,2) -> 0 | K20: =COUNTIFS('Full Score Matrix'!$A$3:$A$32,$D$18,'Full Score Matrix'!$I$3:$I$32,2) -> 0 | L20: =COUNTIFS('Full Score Matrix'!$A$3:$A$14,$D$18,'Full Score Matrix'!$J$3:$J$14,2) -> 0 | M20: =COUNTIFS('Full Score Matrix'!$A$3:$A$32,$D$18,'Full Score Matrix'!$K$3:$K$32,2) -> 0 | N20: =COUNTIFS('Full Score Matrix'!$A$3:$A$32,$D$12,'Full Score Matrix'!$L$3:$L$32,2) -> 0
B22: DEI Scorecard overview | E22: Section 1 | F22: Section 2 | G22: Section 3 | H22: Section 4 | I22: Section 5 | J22: Section 6 | K22: Section 7 | L22: Section 8 | M22: Section 9 | N22: Section 10
B23: Number of parts | E23: ='Full Score Matrix'!C2 -> 5 | F23: ='Full Score Matrix'!D2 -> 4 | G23: ='Full Score Matrix'!E2 -> 1 | H23: ='Full Score Matrix'!F2 -> 2 | I23: ='Full Score Matrix'!G2 -> 6 | J23: ='Full Score Matrix'!H2 -> 4 | K23: ='Full Score Matrix'!I2 -> 3 | L23: ='Full Score Matrix'!J2 -> 4 | ... N23: ='Full Score Matrix'!L2 -> 10
B25: Part 1 | E25: =SUM('Section 1'!$K$20:$K$24) -> 0 | F25: =SUM('Section 2'!$K$21:$K$25) -> 0 | G25: =SUM('Section 3'!$K$19:$K$23) -> 0 | H25: =SUM('Section 4'!$K$19:$K$23) -> 0 | I25: =SUM('Section 5'!$K$19:$K$23) -> 0 | J25: =SUM('Section 6'!$K$19:$K$23) -> 0 | K25: =SUM('Section 7'!$K$19:$K$23) -> 0 | L25: =SUM('Section 8'!$K$19:$K$23) -> 0 | M25: =SUM('Section 9'!$K$19:$K$23) -> 0 | N25: =SUM('Section 10'!$K$19:$K$23) -> 0
B26: Part 2 | E26: =SUM('Section 1'!$K$30:$K$34) -> 0 | F26: =SUM('Section 2'!$K$31:$K$35) -> 0 | H26: =SUM('Section 4'!$K$29:$K$33) -> 0 | I26: =SUM('Section 5'!$K$29:$K$33) -> 0 | J26: =SUM('Section 6'!$K$29:$K$33) -> 0 | K26: =SUM('Section 7'!$K$29:$K$33) -> 0 | L26: =SUM('Section 8'!$K$29:$K$33) -> 0 | N26: =SUM('Section 10'!$K$29:$K$33) -> 0
B27: Part 3 | E27: =SUM('Section 1'!$K$40:$K$44) -> 0 | F27: =SUM('Section 2'!$K$41:$K$45) -> 0 | I27: =SUM('Section 5'!$K$39:$K$43) -> 0 | J27: =SUM('Section 6'!$K$39:$K$43) -> 0 | K27: =SUM('Section 7'!$K$39:$K$43) -> 0 | L27: =SUM('Section 8'!$K$39:$K$43) -> 0 | N27: =SUM('Section 10'!$K$39:$K$43) -> 0
B28: Part 4 | E28: =SUM('Section 1'!$K$50:$K$54) -> 0 | F28: =SUM('Section 2'!$K$51:$K$55) -> 0 | I28: =SUM('Section 5'!$K$49:$K$53) -> 0 | J28: =SUM('Section 6'!$K$49:$K$53) -> 0 | L28: =SUM('Section 8'!$K$49:$K$53) -> 0 | N28: =SUM('Section 10'!$K$49:$K$53) -> 0
B29: Part 5 | E29: =SUM('Section 1'!$K$60:$K$64) -> 0 | I29: =SUM('Section 5'!$K$59:$K$63) -> 0 | N29: =SUM('Section 10'!$K$59:$K$63) -> 0
B30: Part 6 | I30: =SUM('Section 5'!$K$69:$K$73) -> 0 | N30: =SUM('Section 10'!$K$69:$K$73) -> 0
B31: Part 7 | N31: =SUM('Section 10'!$K$79:$K$83) -> 0
B32: Part 8 | N32: =SUM('Section 10'!$K$89:$K$93) -> 0
B33: Part 9 | N33: =SUM('Section 10'!$K$101:$K$105) -> 0
B34: Part 10 | N34: =SUM('Section 10'!$K$111:$K$115) -> 0
B35: Total Score | E35: =SUM(E25:E29) -> 0 | F35: =SUM(F25:F28) -> 0 | G35: =SUM(G25) -> 0 | H35: =SUM(H25:H26) -> 0 | I35: =SUM(I25:I30) -> 0 | J35: =SUM(J25:J28) -> 0 | K35: =SUM(K25:K27) -> 0 | L35: =SUM(L25:L28) -> 0 | M35: =SUM(M25:M26) -> 0 | N35: =SUM(N25:N34) -> 0
B36: Potential | E36: =E23*6 -> 30 | F36: =F23*6 -> 24 | G36: =G23*6 -> 6 | H36: =H23*6 -> 12 | I36: =I23*6 -> 36 | J36: =J23*6 -> 24 | K36: =K23*6 -> 18 | L36: =L23*6 -> 24 | ... N36: =N23*6 -> 60
B37: Version Maximum Score | E37: 30 | F37: 24 | G37: 6 | H37: 12 | I37: 36 | J37: 24 | K37: 18 | L37: 24 | M37: 6 | N37: 60 | P37: =SUM(E35:N35) -> 0
P38: =SUM(E36:N36) -> 240 | Q38: =P37/P38 -> 0
P39: =SUM(E37:N37) -> 240

Sheet Glossary
B3: Term | C3: Definition | D3: Further information
B4: Bias | C4: Bias refers to the attitudes and beliefs we hold about an individual or a group. This can be in favour of, or against that person or group. So, some people see it as favouritism while others refer to it as prejudice. Bias can be unconscious or explicit. Unconscious bias, which some legal scholars refer to as implicit bias or hidden bias, has mainly negative connotations and suggests that people act without intending to do so. Many studies have indicated that implicit biases affect individuals’ attitudes and actions, thus creating real-world implications, even though individuals may not be aware that those biases exist within themselves . Explicit bias is when individuals are aware of their attitudes and beliefs. For example, some organisations can choose to serve on certain income levels or issue statements that are deliberately racist. A key thing to note from these examples is that they can be positive or negative for different members of society. Choosing to serve a certain income group may make that group feel good, however, those excluded from the service may feel harmed. Bias and its related concepts is contested however. DEI practitioners and researchers argue that the term, and training based on it, promotes inaction and ignores the power relationship between parties . They prefer the term prejudice. | D4: Early scholarship drew on Freudian research and referred to “unconscious” bias. More recent literature relies upon scientific methodology and uses the term “implicit” to describe attitudes and beliefs that are outside of conscious control https://www.sjsu.edu/diversity/office/education/terms.php#I A practitioner view of bias is available here. https://medium.com/fearless-futures/six-reasons-why-we-are-just-not-into-unconscious-bias-9289278a96fc and in this podcast episode https://medium.com/fearless-futures/fearless-futures-podcast-episode-3-unconscious-bias-transcript-b6a762cf1913
B5: Diversity | C5: Diversity is about the variation between individuals or groups. It relates to how individuals categorise themselves into social groups and how they perceive others as in their group (sometimes called their in-group) or outside their group (sometimes called the out-group). This perception is important as it determines how they interact and cohere as a group.
B6: Equality | C6: Equality as a term on its own has limited meaning and application to an organisation; it means being equal. It’s real value as a term for organisations is when it is qualified.
B7: Equality Act (2010) | C7: The Equality Act 2010 is UK legislation to support strategic decision making that reduces socio-economic inequalities such as discrimination and harassment related to nine personal protected characteristics and to increase equality of opportunity. The characteristics protected in the Equality Act are the following: age; disability; gender reassignment; marriage and civil partnership; pregnancy and maternity; race; religion or belief; sex, and sexual orientation.
B8: Equity | C8: Equity is about being socially just, or deliberately fair, in the way people are treated. It explains the actions we take to correct the unfair distribution of resources and allocation of rights, responsibilities costs and burdens
B9: Inclusion | C9: Inclusion is concerned with how diverse members of a group are treated and how they feel. Inclusion is necessary because focusing on diversity alone may lead to awareness but not necessarily deal with the issues related to diversity. Thus, various inclusion activities, such as diversity management, are necessary. Inclusive practices seek to ensure people are respected and valued for who they are as an individual or group.
B10: Indicator | C10: Indicators are measures that provide information on how much of an outcome is expected to happen or has happened. They can be based on information provided by those experiencing the outcome or from other sources. | D10: CM alternative definition (from the Impact Management Platform): A standard of measurement. The words ‘metric’ and ‘indicator’ are typically used interchangeably. Metrics are used to measure the state of something at a point in time. Repeated measurement makes it possible to determine change over time. Source: Adapted from Meriam Webster Online Dictionary
B11: Inputs | C11: The contributions made by each stakeholder that are necessary for the activity to happen.
B12: Intersectionality | C12: Intersectionality is the complex, cumulative way in which the effects of multiple forms of discrimination (such as racism, sexism, and classism) combine, overlap, or intersect especially in the experiences of marginalized individuals or groups. It is a lens through which you can see where power comes and collides and the way in which various forms of inequality often exacerbate each other.
B13: Outcome | C13: The changes resulting from an activity. The main types of change from the perspective of stakeholders are unintended (unexpected) and intended (expected), positive and negative changes. For example, this could be an increase in someone's mental wellbeing, or a reduction in loneliness.
B14: Outputs | C14: The summary of activities in numbers. These are the easiest things to count. For example, the number of training classes attended, or the quantity of a product grown.
B15: Power | C15: There are many different notions of power. One main one power as the ability to influence others and impose one’s beliefs – or power over someone. All power is relational, and the different relationships either reinforce or disrupt one another.
B16: Social enterprises | C16: A social enterprise is an organisation which has a legal form recognised as a social purpose organisation . They are usually led by a social entrepreneur and apply entrepreneurial solutions to solve social problems. They have a strong link to charitable activities and trade extensively with the public and private sectors forming part of a broader, integrated programme for social benefit. For example, Social Value UK is a social enterprise. It is a company limited by guarantee which means it has no shareholders. All the money it makes is applied for the benefit of its membership and to further its mission. | D16: Maretich, M., & Bolton, M. (2010). Social enterprise: from definitions to developments in practice. European Venture Philanthropy Association Knowledge Centre.
B17: Social purpose organisation | C17: A social purpose organisation is a broad term used to describe an organisation that declares that it pursues a social purpose. It is not a registered legal form. This includes organisations that pursue other purposes, for example, private limited organisations that pursue profit, non-profit organisations that are less focused on profit but are required by law to focus on social purposes, and social enterprises, for example Community Interest Companies whose registered form encourages them to pursue both social purpose and profit.
B18: Social value | C18: Social value is the quantification of the relative importance that people place on the changes they experience in their lives. Some, but not all of this value is captured in market prices. It is important to consider and measure this social value from the perspective of those affected by an organisation’s work.
B19: Stakeholders | C19: People, organisations or entities that experience change, whether positive or negative, as a result of the activity that is being analysed.
B20: Structural discrimination | C20: Structural discrimination is when society collectively disadvantages one social group through benefitting other social groups. This discrimination is rooted and perpetuated through discriminatory practices that are reinforced through institutions, ideologies, representations, policies/laws and practices. For instance, when this kind of inequity is related to racial discrimination, it is referred to as structural racism.

Sheet Full Score Matrix
C1: Section 1 | D1: Section 2 | E1: Section 3 | F1: Section 4 | G1: Section 5 | H1: Section 6 | I1: Section 7 | J1: Section 8 | K1: Section 9 | L1: Section 10
A2: Number of parts | C2: 5 | D2: 4 | E2: 1 | F2: 2 | G2: 6 | H2: 4 | I2: 3 | J2: 4 | K2: 1 | L2: 10
A3: Commit | B3: Part 1 | C3: ='Section 1'!$K$20 -> 0 | D3: ='Section 2'!$K$21 -> 0 | E3: ='Section 3'!$K$19 -> 0 | F3: ='Section 4'!$K$19 -> 0 | G3: ='Section 5'!$K$19 -> 0 | H3: ='Section 6'!$K$19 -> 0 | I3: ='Section 7'!$K$19 -> 0 | J3: ='Section 8'!$K$19 -> 0 | K3: ='Section 9'!$K$19 -> 0 | L3: ='Section 10'!$K$19 -> 0
A4: Implement | B4: Part 1 | C4: ='Section 1'!$K$22 -> 0 | D4: ='Section 2'!$K$23 -> 0 | E4: ='Section 3'!$K$21 -> 0 | F4: ='Section 4'!$K$21 -> 0 | G4: ='Section 5'!$K$21 -> 0 | H4: ='Section 6'!$K$21 -> 0 | I4: ='Section 7'!$K$21 -> 0 | J4: ='Section 8'!$K$21 -> 0 | K4: ='Section 9'!$K$21 -> 0 | L4: ='Section 10'!$K$21 -> 0
A5: Embed | B5: Part 1 | C5: ='Section 1'!$K$24 -> 0 | D5: ='Section 2'!$K$25 -> 0 | E5: ='Section 3'!$K$23 -> 0 | F5: ='Section 4'!$K$23 -> 0 | G5: ='Section 5'!$K$23 -> 0 | H5: ='Section 6'!$K$23 -> 0 | I5: ='Section 7'!$K$23 -> 0 | J5: ='Section 8'!$K$23 -> 0 | K5: ='Section 9'!$K$23 -> 0 | L5: ='Section 10'!$K$23 -> 0
A6: Commit | B6: Part 2 | C6: ='Section 1'!$K$30 -> 0 | D6: ='Section 2'!$K$31 -> 0 | F6: ='Section 4'!$K$29 -> 0 | G6: ='Section 5'!$K$29 -> 0 | H6: ='Section 6'!$K$29 -> 0 | I6: ='Section 7'!$K$29 -> 0 | J6: ='Section 8'!$K$29 -> 0 | L6: ='Section 10'!$K$29 -> 0
A7: Implement | B7: Part 2 | C7: ='Section 1'!$K$32 -> 0 | D7: ='Section 2'!$K$33 -> 0 | F7: ='Section 4'!$K$31 -> 0 | G7: ='Section 5'!$K$31 -> 0 | H7: ='Section 6'!$K$31 -> 0 | I7: ='Section 7'!$K$31 -> 0 | J7: ='Section 8'!$K$31 -> 0 | L7: ='Section 10'!$K$31 -> 0
A8: Embed | B8: Part 2 | C8: ='Section 1'!$K$34 -> 0 | D8: ='Section 2'!$K$35 -> 0 | F8: ='Section 4'!$K$33 -> 0 | G8: ='Section 5'!$K$33 -> 0 | H8: ='Section 6'!$K$33 -> 0 | I8: ='Section 7'!$K$33 -> 0 | J8: ='Section 8'!$K$33 -> 0 | L8: ='Section 10'!$K$33 -> 0
A9: Commit | B9: Part 3 | C9: ='Section 1'!$K$40 -> 0 | D9: ='Section 2'!$K$41 -> 0 | G9: ='Section 5'!$K$39 -> 0 | H9: ='Section 6'!$K$39 -> 0 | I9: ='Section 7'!$K$39 -> 0 | J9: ='Section 8'!$K$39 -> 0 | L9: ='Section 10'!$K$39 -> 0
A10: Implement | B10: Part 3 | C10: ='Section 1'!$K$42 -> 0 | D10: ='Section 2'!$K$43 -> 0 | G10: ='Section 5'!$K$41 -> 0 | H10: ='Section 6'!$K$41 -> 0 | I10: ='Section 7'!$K$41 -> 0 | J10: ='Section 8'!$K$41 -> 0 | L10: ='Section 10'!$K$41 -> 0
A11: Embed | B11: Part 3 | C11: ='Section 1'!$K$44 -> 0 | D11: ='Section 2'!$K$45 -> 0 | G11: ='Section 5'!$K$43 -> 0 | H11: ='Section 6'!$K$43 -> 0 | I11: ='Section 7'!$K$43 -> 0 | J11: ='Section 8'!$K$43 -> 0 | L11: ='Section 10'!$K$43 -> 0
A12: Commit | B12: Part 4 | C12: ='Section 1'!$K$50 -> 0 | D12: ='Section 2'!$K$51 -> 0 | G12: ='Section 5'!$K$49 -> 0 | H12: ='Section 6'!$K$49 -> 0 | J12: ='Section 8'!$K$49 -> 0 | L12: ='Section 10'!$K$49 -> 0
A13: Implement | B13: Part 4 | C13: ='Section 1'!$K$52 -> 0 | D13: ='Section 2'!$K$53 -> 0 | G13: ='Section 5'!$K$51 -> 0 | H13: ='Section 6'!$K$51 -> 0 | J13: ='Section 8'!$K$51 -> 0 | L13: ='Section 10'!$K$51 -> 0
A14: Embed | B14: Part 4 | C14: ='Section 1'!$K$54 -> 0 | D14: ='Section 2'!$K$55 -> 0 | G14: ='Section 5'!$K$53 -> 0 | H14: ='Section 6'!$K$53 -> 0 | J14: ='Section 8'!$K$53 -> 0 | L14: ='Section 10'!$K$53 -> 0
A15: Commit | B15: Part 5 | C15: ='Section 1'!$K$60 -> 0 | G15: ='Section 5'!$K$59 -> 0 | L15: ='Section 10'!$K$59 -> 0
A16: Implement | B16: Part 5 | C16: ='Section 1'!$K$62 -> 0 | G16: ='Section 5'!$K$61 -> 0 | L16: ='Section 10'!$K$61 -> 0
A17: Embed | B17: Part 5 | C17: ='Section 1'!$K$64 -> 0 | G17: ='Section 5'!$K$63 -> 0 | L17: ='Section 10'!$K$63 -> 0
A18: Commit | B18: Part 6 | G18: ='Section 5'!$K$69 -> 0 | L18: ='Section 10'!$K$69 -> 0
A19: Implement | B19: Part 6 | G19: ='Section 5'!$K$71 -> 0 | L19: ='Section 10'!$K$71 -> 0
A20: Embed | B20: Part 6 | G20: ='Section 5'!$K$73 -> 0 | L20: ='Section 10'!$K$73 -> 0
A21: Commit | B21: Part 7 | L21: ='Section 10'!$K$79 -> 0
A22: Implement | B22: Part 7 | L22: ='Section 10'!$K$81 -> 0
A23: Embed | B23: Part 7 | L23: ='Section 10'!$K$83 -> 0
A24: Commit | B24: Part 8 | L24: ='Section 10'!$K$89 -> 0
A25: Implement | B25: Part 8 | L25: ='Section 10'!$K$91 -> 0
A26: Embed | B26: Part 8 | L26: ='Section 10'!$K$93 -> 0
A27: Commit | B27: Part 9 | L27: ='Section 10'!$K$101 -> 0
A28: Implement | B28: Part 9 | L28: ='Section 10'!$K$103 -> 0
A29: Embed | B29: Part 9 | L29: ='Section 10'!$K$105 -> 0
A30: Commit | B30: Part 10 | L30: ='Section 10'!$K$111 -> 0
A31: Implement | B31: Part 10 | L31: ='Section 10'!$K$113 -> 0
A32: Embed | B32: Part 10 | L32: ='Section 10'!$K$115 -> 0

Sheet Part ref table
B2: DEI Scorecard overview | E2: Section 1 | F2: Section 2 | G2: Section 3 | H2: Section 4 | I2: Section 5 | J2: Section 6 | K2: Section 7 | L2: Section 8 | M2: Section 9 | N2: Section 10
B3: Part 1 | E3: ='Section 1'!D17 -> Equality, Diversity, & Inclusion Characteristics (Equality Act and beyond) | F3: ='Section 2'!C18 -> 0 | G3: ='Section 3'!C16 -> 0 | H3: ='Section 4'!C16 -> 0 | I3: ='Section 5'!C16 -> 0 | J3: ='Section 6'!C16 -> 0 | K3: ='Section 7'!C16 -> 0 | L3: ='Section 8'!C16 -> 0 | M3: ='Section 9'!C16 -> 0 | N3: ='Section 10'!C16 -> 0
B4: Part 2 | E4: ='Section 1'!D27 -> Understanding organisational power | F4: ='Section 2'!C28 -> 0 | H4: ='Section 4'!C26 -> 0 | I4: ='Section 5'!C26 -> 0 | J4: ='Section 6'!C26 -> 0 | K4: ='Section 7'!C26 -> 0 | L4: ='Section 8'!C26 -> 0 | N4: ='Section 10'!C26 -> 0
B5: Part 3 | E5: ='Section 1'!D37 -> Tackling organisational barriers to Equality, Diversity and Inclusion | F5: ='Section 2'!C38 -> 0 | I5: ='Section 5'!C36 -> 0 | J5: ='Section 6'!C36 -> 0 | K5: ='Section 7'!C36 -> 0 | L5: ='Section 8'!C36 -> 0 | N5: ='Section 10'!C36 -> 0
B6: Part 4 | E6: ='Section 1'!D47 -> Our role in structural discrimination | F6: ='Section 2'!C48 -> 0 | I6: ='Section 5'!C46 -> 0 | J6: ='Section 6'!C46 -> 0 | L6: ='Section 8'!C46 -> 0 | N6: ='Section 10'!C46 -> 0
B7: Part 5 | E7: ='Section 1'!D56 -> Intersectionality | I7: ='Section 5'!C56 -> 0 | N7: ='Section 10'!C56 -> 0
B8: Part 6 | I8: ='Section 5'!C66 -> 0 | N8: ='Section 10'!C66 -> 0
B9: Part 7 | N9: ='Section 10'!C76 -> 0
B10: Part 8 | N10: ='Section 10'!C86 -> 0
B11: Part 9 | N11: ='Section 10'!#REF! -> #REF!
B12: Part 10 | N12: ='Section 10'!#REF! -> #REF!
B13: Part 11 | N13: ='Section 10'!C98 -> 0
B14: Part 12 | N14: ='Section 10'!C108 -> 0
B15: Part 13
B16: Part 14
B17: Part 15
B18: Part 16
B19: Part 17
B20: Part 18
B21: Part 19
B22: Part 20
B23: Part 21
