Workbook
Name BaseCaseIndicator: InpC!$J$7:$S$7
Name CASE_ACTIVE: InpC!$F$4
Name CHK_TOL: InpC!$F$49
Name InputRowTemplate: InpC!$E$66:$S$66
Name SMU: InpC!$F$52
Name TRK_TOL: InpC!$F$48

Sheet InpC
A1: =RIGHT(CELL("filename", A1), LEN(CELL("filename", A1)) - SEARCH("]", CELL("filename", A1))) & " - " & $F$3 -> InpC - Case 1
K2: =IF(K4 = $F4, "q", "") | L2: =IF(L4 = $F4, "q", "") | M2: =IF(M4 = $F4, "q", "") | O2: =IF(O4 = $F4, "q", "") -> q | P2: =IF(P4 = $F4, "q", "") | Q2: =IF(Q4 = $F4, "q", "") | R2: =IF(R4 = $F4, "q", "")
F3: =INDEX(J3:S3,MATCH(F4,J4:S4)) -> Case 1 | K3: Base case 1 | L3: Alt case 1 | M3: Alt case 2 | O3: Case 1 | P3: Case 2 | Q3: Case 3 | R3: Case 4
E4: Active scenario | F4: 5 | I4: =MATCH(F4, $J$4:$S$4) -> 6 | K4: 1 | L4: 2 | M4: 3 | O4: 5 | P4: 6 | Q4: 7 | R4: 8
E5: Comparison scenario | F5: 1 | I5: =MATCH(F5, $J$4:$S$4) -> 2
E6: Base case | F6: =INDEX(J6:S6,MATCH(F4,J4:S4,0)) -> 1 | I6: =MATCH(F6, $J$4:$S$4) -> 2 | K6: 1 | L6: 2 | M6: 3 | O6: 1 | P6: 1 | Q6: 2 | R6: 2
E7: Input differences | F7: =COUNTIF(I10:I46, "tu") -> 0 | K7: =IF(K6 = $F$6, "Base case", "") -> Base case | L7: =IF(L6 = $F$6, "Base case", "") | M7: =IF(M6 = $F$6, "Base case", "")
F9: Constant | G9: Unit | H9: Source
A11: TIMING ASSUMPTIONS
E13: First date of time rulers | F13: =IF( INDEX(J13:S13, $I$4) = "", INDEX(J13:R13, $I$6), INDEX(J13:S13, $I$4)) -> 44013 | G13: date | I13: {=IF( INDEX(J13:S13, I$5) = "", IF( INDEX(J13:S13, I$6) = F13, "vw", "tu"), IF(INDEX(J13:S13, I$5) = F13, "vw", "tu"))} -> vw | K13: 44013 | L13: 43831 | M13: 43831
E14: Annual year end date of first operating period | F14: =IF( INDEX(J14:S14, $I$4) = "", INDEX(J14:R14, $I$6), INDEX(J14:S14, $I$4)) -> 43921 | G14: date | I14: {=IF( INDEX(J14:S14, I$5) = "", IF( INDEX(J14:S14, I$6) = F14, "vw", "tu"), IF(INDEX(J14:S14, I$5) = F14, "vw", "tu"))} -> vw | K14: 43921 | L14: 43921 | M14: 43921
E15: Additional periods at start of operating timeline | F15: =IF( INDEX(J15:S15, $I$4) = "", INDEX(J15:R15, $I$6), INDEX(J15:S15, $I$4)) -> 2 | G15: periods | I15: {=IF( INDEX(J15:S15, I$5) = "", IF( INDEX(J15:S15, I$6) = F15, "vw", "tu"), IF(INDEX(J15:S15, I$5) = F15, "vw", "tu"))} -> vw | K15: 2 | L15: 2 | M15: 2
E16: Financial year end month number | F16: =IF( INDEX(J16:S16, $I$4) = "", INDEX(J16:R16, $I$6), INDEX(J16:S16, $I$4)) -> 12 | G16: month # | I16: {=IF( INDEX(J16:S16, I$5) = "", IF( INDEX(J16:S16, I$6) = F16, "vw", "tu"), IF(INDEX(J16:S16, I$5) = F16, "vw", "tu"))} -> vw | K16: 12 | L16: 12 | M16: 12
E17: Length of operating period | F17: =IF( INDEX(J17:S17, $I$4) = "", INDEX(J17:R17, $I$6), INDEX(J17:S17, $I$4)) -> 3 | G17: months | I17: {=IF( INDEX(J17:S17, I$5) = "", IF( INDEX(J17:S17, I$6) = F17, "vw", "tu"), IF(INDEX(J17:S17, I$5) = F17, "vw", "tu"))} -> vw | K17: 3 | L17: 3 | M17: 3
E19: Acquisition date | F19: =IF( INDEX(J19:S19, $I$4) = "", INDEX(J19:R19, $I$6), INDEX(J19:S19, $I$4)) -> 44286 | G19: date | I19: {=IF( INDEX(J19:S19, I$5) = "", IF( INDEX(J19:S19, I$6) = F19, "vw", "tu"), IF(INDEX(J19:S19, I$5) = F19, "vw", "tu"))} -> vw | K19: 44286 | L19: 43921 | M19: 43921
E20: Construction period length | F20: =IF( INDEX(J20:S20, $I$4) = "", INDEX(J20:R20, $I$6), INDEX(J20:S20, $I$4)) -> 12 | G20: months | I20: {=IF( INDEX(J20:S20, I$5) = "", IF( INDEX(J20:S20, I$6) = F20, "vw", "tu"), IF(INDEX(J20:S20, I$5) = F20, "vw", "tu"))} -> vw | K20: 12 | L20: 12 | M20: 12
E21: Construction delay length | F21: =IF( INDEX(J21:S21, $I$4) = "", INDEX(J21:R21, $I$6), INDEX(J21:S21, $I$4)) -> 0 | G21: months | I21: {=IF( INDEX(J21:S21, I$5) = "", IF( INDEX(J21:S21, I$6) = F21, "vw", "tu"), IF(INDEX(J21:S21, I$5) = F21, "vw", "tu"))} -> vw | K21: 0 | L21: 0 | M21: 0
E23: Operating years remaining | F23: =IF( INDEX(J23:S23, $I$4) = "", INDEX(J23:R23, $I$6), INDEX(J23:S23, $I$4)) -> 25 | G23: years | I23: {=IF( INDEX(J23:S23, I$5) = "", IF( INDEX(J23:S23, I$6) = F23, "vw", "tu"), IF(INDEX(J23:S23, I$5) = F23, "vw", "tu"))} -> vw | K23: 25 | L23: 25 | M23: 25
E24: Extend PPA in the event of delay | F24: =IF( INDEX(J24:S24, $I$4) = "", INDEX(J24:R24, $I$6), INDEX(J24:S24, $I$4)) -> 0 | G24: 1 = yes, 0 = no | I24: {=IF( INDEX(J24:S24, I$5) = "", IF( INDEX(J24:S24, I$6) = F24, "vw", "tu"), IF(INDEX(J24:S24, I$5) = F24, "vw", "tu"))} -> vw | K24: 0 | L24: 0 | M24: 0
E25: Contract extension | F25: =IF( INDEX(J25:S25, $I$4) = "", INDEX(J25:R25, $I$6), INDEX(J25:S25, $I$4)) -> 0 | G25: years | I25: {=IF( INDEX(J25:S25, I$5) = "", IF( INDEX(J25:S25, I$6) = F25, "vw", "tu"), IF(INDEX(J25:S25, I$5) = F25, "vw", "tu"))} -> vw | K25: 0 | L25: 0 | M25: 0
A27: OPERATIONS
E28: Q1 yield | F28: =IF( INDEX(J28:S28, $I$4) = "", INDEX(J28:R28, $I$6), INDEX(J28:S28, $I$4)) -> 0.33 | G28: % of annual yield | I28: {=IF( INDEX(J28:S28, I$5) = "", IF( INDEX(J28:S28, I$6) = F28, "vw", "tu"), IF(INDEX(J28:S28, I$5) = F28, "vw", "tu"))} -> vw | K28: 0.33
E29: Q2 yield | F29: =IF( INDEX(J29:S29, $I$4) = "", INDEX(J29:R29, $I$6), INDEX(J29:S29, $I$4)) -> 0.36 | G29: % of annual yield | I29: {=IF( INDEX(J29:S29, I$5) = "", IF( INDEX(J29:S29, I$6) = F29, "vw", "tu"), IF(INDEX(J29:S29, I$5) = F29, "vw", "tu"))} -> vw | K29: 0.36
E30: Q3 yield | F30: =IF( INDEX(J30:S30, $I$4) = "", INDEX(J30:R30, $I$6), INDEX(J30:S30, $I$4)) -> 0.155 | G30: % of annual yield | I30: {=IF( INDEX(J30:S30, I$5) = "", IF( INDEX(J30:S30, I$6) = F30, "vw", "tu"), IF(INDEX(J30:S30, I$5) = F30, "vw", "tu"))} -> vw | K30: 0.155
E31: Q4 yield | F31: =IF( INDEX(J31:S31, $I$4) = "", INDEX(J31:R31, $I$6), INDEX(J31:S31, $I$4)) -> 0.155 | G31: % of annual yield | I31: {=IF( INDEX(J31:S31, I$5) = "", IF( INDEX(J31:S31, I$6) = F31, "vw", "tu"), IF(INDEX(J31:S31, I$5) = F31, "vw", "tu"))} -> vw | K31: 0.155
E33: Annual degredation | F33: =IF( INDEX(J33:S33, $I$4) = "", INDEX(J33:R33, $I$6), INDEX(J33:S33, $I$4)) -> 0.005 | G33: % p.a. | H33: 0 | I33: {=IF( INDEX(J33:S33, I$5) = "", IF( INDEX(J33:S33, I$6) = F33, "vw", "tu"), IF(INDEX(J33:S33, I$5) = F33, "vw", "tu"))} -> vw | K33: 0.005
E34: Year 1 P50 yield | F34: =IF( INDEX(J34:S34, $I$4) = "", INDEX(J34:R34, $I$6), INDEX(J34:S34, $I$4)) -> 250 | G34: GWh | I34: {=IF( INDEX(J34:S34, I$5) = "", IF( INDEX(J34:S34, I$6) = F34, "vw", "tu"), IF(INDEX(J34:S34, I$5) = F34, "vw", "tu"))} -> vw | K34: 250
E35: Availability | F35: =IF( INDEX(J35:S35, $I$4) = "", INDEX(J35:R35, $I$6), INDEX(J35:S35, $I$4)) -> 0.97 | G35: % | I35: {=IF( INDEX(J35:S35, I$5) = "", IF( INDEX(J35:S35, I$6) = F35, "vw", "tu"), IF(INDEX(J35:S35, I$5) = F35, "vw", "tu"))} -> vw | K35: 0.97
E36: Power tariff | F36: =IF( INDEX(J36:S36, $I$4) = "", INDEX(J36:R36, $I$6), INDEX(J36:S36, $I$4)) -> 0.065 | G36: USD / kWh | I36: {=IF( INDEX(J36:S36, I$5) = "", IF( INDEX(J36:S36, I$6) = F36, "vw", "tu"), IF(INDEX(J36:S36, I$5) = F36, "vw", "tu"))} -> vw | K36: 0.065
E38: O&M contract cost | F38: =IF( INDEX(J38:S38, $I$4) = "", INDEX(J38:R38, $I$6), INDEX(J38:S38, $I$4)) -> 1500 | G38: USD pa | I38: {=IF( INDEX(J38:S38, I$5) = "", IF( INDEX(J38:S38, I$6) = F38, "vw", "tu"), IF(INDEX(J38:S38, I$5) = F38, "vw", "tu"))} -> vw | K38: 1500
E40: Accounts receivable days | F40: =IF( INDEX(J40:S40, $I$4) = "", INDEX(J40:R40, $I$6), INDEX(J40:S40, $I$4)) -> 45 | G40: days | I40: {=IF( INDEX(J40:S40, I$5) = "", IF( INDEX(J40:S40, I$6) = F40, "vw", "tu"), IF(INDEX(J40:S40, I$5) = F40, "vw", "tu"))} -> vw | K40: 45
E41: Accounts payable days | F41: =IF( INDEX(J41:S41, $I$4) = "", INDEX(J41:R41, $I$6), INDEX(J41:S41, $I$4)) -> 30 | G41: days | I41: {=IF( INDEX(J41:S41, I$5) = "", IF( INDEX(J41:S41, I$6) = F41, "vw", "tu"), IF(INDEX(J41:S41, I$5) = F41, "vw", "tu"))} -> vw | K41: 30
E43: Corporate income tax rate | F43: =IF( INDEX(J43:S43, $I$4) = "", INDEX(J43:R43, $I$6), INDEX(J43:S43, $I$4)) -> 0.15 | G43: % | I43: {=IF( INDEX(J43:S43, I$5) = "", IF( INDEX(J43:S43, I$6) = F43, "vw", "tu"), IF(INDEX(J43:S43, I$5) = F43, "vw", "tu"))} -> vw | K43: 0.15
A46: MODEL TECHNICAL INPUTS - DO NOT CHANGE
E48: Model track tolerance level | F48: 0.001 | G48: tolerance
E49: Model check tolerance level | F49: 0.001 | G49: tolerance
E50: Months in year | F50: 12 | G50: months
E51: Number of periods in a year | F51: 4 | G51: periods
E52: Standard Monetary Unit | F52: $ 000s | G52: named "SMU"
E53: US$c / US$ | F53: 100 | G53: US$c / US$
E54: GWh to KWh conversion | F54: 1000000 | G54: kWh / GWh
E55: Units in a thousand | F55: 1000 | G55: units
B57: Timeline label
E58: Pre-forecast period | F58: Pre-fcst | G58: label
E59: Financial Close | F59: Fin Close | G59: label
E60: Construction | F60: Construction | G60: label
E61: Constrution delay | F61: Delay | G61: label
E62: Operations | F62: Operations | G62: label
E63: PPA extension | F63: PPA ext. | G63: label
E64: Post ops | F64: Post ops | G64: label
E66: Input row template for relocation macro | F66: =IF( INDEX(J66:S66, $I$4) = "", INDEX(J66:R66, $I$6), INDEX(J66:S66, $I$4)) -> 0 | G66: unit | I66: {=IF( INDEX(J66:S66, I$5) = "", IF( INDEX(J66:S66, I$6) = F66, "vw", "tu"), IF(INDEX(J66:S66, I$5) = F66, "vw", "tu"))} -> vw
A69: END
E71: Incoming investor required IRR | F71: =IF( INDEX(J71:S71, $I$4) = "", INDEX(J71:R71, $I$6), INDEX(J71:S71, $I$4)) -> 0.14 | G71: % | I71: {=IF( INDEX(J71:S71, I$5) = "", IF( INDEX(J71:S71, I$6) = F71, "vw", "tu"), IF(INDEX(J71:S71, I$5) = F71, "vw", "tu"))} -> vw | K71: 0.14 | L71: 0.14 | M71: 0.14

Sheet Time
A1: =RIGHT(CELL("filename", A1), LEN(CELL("filename", A1)) - SEARCH("]", CELL("filename", A1))) & " - " & InpC!F3 -> Time - Case 1
E2: =Time!E$25 -> Model period ending | F2: 0 | G2: Error chks | J2: =Time!J$25 -> 44104 | K2: =Time!K$25 -> 44196 | L2: =Time!L$25 -> 44286 | M2: =Time!M$25 -> 44377 | N2: =Time!N$25 -> 44469 | O2: =Time!O$25 -> 44561 | P2: =Time!P$25 -> 44651 | Q2: =Time!Q$25 -> 44742 | ... GJ2: =Time!GJ$25 -> 60722
E3: =Time!E$188 -> Timeline label | F3: 0 | G3: Track chgs | J3: =Time!J$188 -> Pre-fcst | K3: =Time!K$188 -> Pre-fcst | L3: =Time!L$188 -> Fin Close | M3: =Time!M$188 -> Operations | N3: =Time!N$188 -> Operations | O3: =Time!O$188 -> Operations | P3: =Time!P$188 -> Operations | Q3: =Time!Q$188 -> Operations | ... GJ3: =Time!GJ$188 -> Post ops
E4: =Time!E$42 -> Contract year | F4: 0 | G4: Alerts | J4: =Time!J$42 -> 2020 | K4: =Time!K$42 -> 2020 | L4: =Time!L$42 -> 2020 | M4: =Time!M$42 -> 2021 | N4: =Time!N$42 -> 2021 | O4: =Time!O$42 -> 2021 | P4: =Time!P$42 -> 2021 | Q4: =Time!Q$42 -> 2022 | ... GJ4: =Time!GJ$42 -> 2065
E5: =Time!E$10 -> model column counter | F5: Constant | G5: Unit | H5: Total | J5: =Time!J$10 -> 1 | K5: =Time!K$10 -> 2 | L5: =Time!L$10 -> 3 | M5: =Time!M$10 -> 4 | N5: =Time!N$10 -> 5 | O5: =Time!O$10 -> 6 | P5: =Time!P$10 -> 7 | Q5: =Time!Q$10 -> 8 | ... GJ5: =Time!GJ$10 -> 183
A7: TIME RULER
B9: First model column
E10: model column counter | G10: counter | J10: =I10 + 1 -> 1 | K10: =J10 + 1 -> 2 | L10: =K10 + 1 -> 3 | M10: =L10 + 1 -> 4 | N10: =M10 + 1 -> 5 | O10: =N10 + 1 -> 6 | P10: =O10 + 1 -> 7 | Q10: =P10 + 1 -> 8 | ... GJ10: =GI10 + 1 -> 183
E11: Model column total | F11: =MAX(J10:PU10) -> 183 | G11: columns
E13: =E$10 -> model column counter | F13: =F$10 -> 0 | G13: =G$10 -> counter | H13: =H$10 -> 0 | I13: =I$10 -> 0 | J13: =J$10 -> 1 | K13: =K$10 -> 2 | L13: =L$10 -> 3 | ... GJ13: =GJ$10 -> 183
E14: First model column flag | G14: flag | H14: =SUM(J14:GJ14) -> 1 | J14: =IF(J13 = 1, 1, 0) -> 1 | K14: =IF(K13 = 1, 1, 0) -> 0 | L14: =IF(L13 = 1, 1, 0) -> 0 | M14: =IF(M13 = 1, 1, 0) -> 0 | N14: =IF(N13 = 1, 1, 0) -> 0 | O14: =IF(O13 = 1, 1, 0) -> 0 | P14: =IF(P13 = 1, 1, 0) -> 0 | Q14: =IF(Q13 = 1, 1, 0) -> 0 | ... GJ14: =IF(GJ13 = 1, 1, 0) -> 0
B16: Model period beginning
E17: =InpC!E$13 -> First date of time rulers | F17: =InpC!F$13 -> 44013 | G17: =InpC!G$13 -> date
E18: =InpC!E$17 -> Length of operating period | F18: =InpC!F$17 -> 3 | G18: =InpC!G$17 -> months
E19: =E$14 -> First model column flag | F19: =F$14 -> 0 | G19: =G$14 -> flag | H19: =H$14 -> 1 | I19: =I$14 -> 0 | J19: =J$14 -> 1 | K19: =K$14 -> 0 | L19: =L$14 -> 0 | ... GJ19: =GJ$14 -> 0
E20: Model period beginning | G20: date | J20: =IF(J19 = 1, $F17, DATE(YEAR(I20), MONTH(I20) + $F18, DAY(1))) -> 44013 | K20: =IF(K19 = 1, $F17, DATE(YEAR(J20), MONTH(J20) + $F18, DAY(1))) -> 44105 | L20: =IF(L19 = 1, $F17, DATE(YEAR(K20), MONTH(K20) + $F18, DAY(1))) -> 44197 | M20: =IF(M19 = 1, $F17, DATE(YEAR(L20), MONTH(L20) + $F18, DAY(1))) -> 44287 | N20: =IF(N19 = 1, $F17, DATE(YEAR(M20), MONTH(M20) + $F18, DAY(1))) -> 44378 | O20: =IF(O19 = 1, $F17, DATE(YEAR(N20), MONTH(N20) + $F18, DAY(1))) -> 44470 | P20: =IF(P19 = 1, $F17, DATE(YEAR(O20), MONTH(O20) + $F18, DAY(1))) -> 44562 | Q20: =IF(Q19 = 1, $F17, DATE(YEAR(P20), MONTH(P20) + $F18, DAY(1))) -> 44652 | ... GJ20: =IF(GJ19 = 1, $F17, DATE(YEAR(GI20), MONTH(GI20) + $F18, DAY(1))) -> 60633
B22: Model period ending
E23: =InpC!E$17 -> Length of operating period | F23: =InpC!F$17 -> 3 | G23: =InpC!G$17 -> months
E24: =E$20 -> Model period beginning | F24: =F$20 -> 0 | G24: =G$20 -> date | H24: =H$20 -> 0 | I24: =I$20 -> 0 | J24: =J$20 -> 44013 | K24: =K$20 -> 44105 | L24: =L$20 -> 44197 | ... GJ24: =GJ$20 -> 60633
E25: Model period ending | G25: date | J25: =DATE(YEAR(J24), MONTH(J24) + $F23, DAY(J24) -1) -> 44104 | K25: =DATE(YEAR(K24), MONTH(K24) + $F23, DAY(K24) -1) -> 44196 | L25: =DATE(YEAR(L24), MONTH(L24) + $F23, DAY(L24) -1) -> 44286 | M25: =DATE(YEAR(M24), MONTH(M24) + $F23, DAY(M24) -1) -> 44377 | N25: =DATE(YEAR(N24), MONTH(N24) + $F23, DAY(N24) -1) -> 44469 | O25: =DATE(YEAR(O24), MONTH(O24) + $F23, DAY(O24) -1) -> 44561 | P25: =DATE(YEAR(P24), MONTH(P24) + $F23, DAY(P24) -1) -> 44651 | Q25: =DATE(YEAR(Q24), MONTH(Q24) + $F23, DAY(Q24) -1) -> 44742 | ... GJ25: =DATE(YEAR(GJ24), MONTH(GJ24) + $F23, DAY(GJ24) -1) -> 60722
B27: Financial year ending
E28: =InpC!E$19 -> Acquisition date | F28: =InpC!F$19 -> 44286 | G28: =InpC!G$19 -> date
E29: Month of end of timeline | F29: =MONTH(F28) -> 3 | G29: month
E31: =E$29 -> Month of end of timeline | F31: =F$29 -> 3 | G31: =G$29 -> month
E32: =E$25 -> Model period ending | F32: =F$25 -> 0 | G32: =G$25 -> date | H32: =H$25 -> 0 | I32: =I$25 -> 0 | J32: =J$25 -> 44104 | K32: =K$25 -> 44196 | L32: =L$25 -> 44286 | ... GJ32: =GJ$25 -> 60722
E33: End of contract year flag | J33: =IF( MONTH(J32) = $F31, 1, 0) -> 0 | K33: =IF( MONTH(K32) = $F31, 1, 0) -> 0 | L33: =IF( MONTH(L32) = $F31, 1, 0) -> 1 | M33: =IF( MONTH(M32) = $F31, 1, 0) -> 0 | N33: =IF( MONTH(N32) = $F31, 1, 0) -> 0 | O33: =IF( MONTH(O32) = $F31, 1, 0) -> 0 | P33: =IF( MONTH(P32) = $F31, 1, 0) -> 1 | Q33: =IF( MONTH(Q32) = $F31, 1, 0) -> 0 | ... GJ33: =IF( MONTH(GJ32) = $F31, 1, 0) -> 1
E35: =InpC!E$14 -> Annual year end date of first operating period | F35: =InpC!F$14 -> 43921 | G35: =InpC!G$14 -> date
E36: =InpC!E$50 -> Months in year | F36: =InpC!F$50 -> 12 | G36: =InpC!G$50 -> months
E37: =E$14 -> First model column flag | F37: =F$14 -> 0 | G37: =G$14 -> flag | H37: =H$14 -> 1 | I37: =I$14 -> 0 | J37: =J$14 -> 1 | K37: =K$14 -> 0 | L37: =L$14 -> 0 | ... GJ37: =GJ$14 -> 0
E38: =E$33 -> End of contract year flag | F38: =F$33 -> 0 | G38: =G$33 -> 0 | H38: =H$33 -> 0 | I38: =I$33 -> 0 | J38: =J$33 -> 0 | K38: =K$33 -> 0 | L38: =L$33 -> 1 | ... GJ38: =GJ$33 -> 1
E39: Contract year applicable to period | G39: date | J39: =IF( J37 = 1, $F35, IF( I38 = 1, EOMONTH(I39, 12), I39)) -> 43921 | K39: =IF( K37 = 1, $F35, IF( J38 = 1, EOMONTH(J39, 12), J39)) -> 43921 | L39: =IF( L37 = 1, $F35, IF( K38 = 1, EOMONTH(K39, 12), K39)) -> 43921 | M39: =IF( M37 = 1, $F35, IF( L38 = 1, EOMONTH(L39, 12), L39)) -> 44286 | N39: =IF( N37 = 1, $F35, IF( M38 = 1, EOMONTH(M39, 12), M39)) -> 44286 | O39: =IF( O37 = 1, $F35, IF( N38 = 1, EOMONTH(N39, 12), N39)) -> 44286 | P39: =IF( P37 = 1, $F35, IF( O38 = 1, EOMONTH(O39, 12), O39)) -> 44286 | Q39: =IF( Q37 = 1, $F35, IF( P38 = 1, EOMONTH(P39, 12), P39)) -> 44651 | ... GJ39: =IF( GJ37 = 1, $F35, IF( GI38 = 1, EOMONTH(GI39, 12), GI39)) -> 60357
E41: =E$39 -> Contract year applicable to period | F41: =F$39 -> 0 | G41: =G$39 -> date | H41: =H$39 -> 0 | I41: =I$39 -> 0 | J41: =J$39 -> 43921 | K41: =K$39 -> 43921 | L41: =L$39 -> 43921 | ... GJ41: =GJ$39 -> 60357
E42: Contract year | G42: year # | J42: =YEAR(J41) -> 2020 | K42: =YEAR(K41) -> 2020 | L42: =YEAR(L41) -> 2020 | M42: =YEAR(M41) -> 2021 | N42: =YEAR(N41) -> 2021 | O42: =YEAR(O41) -> 2021 | P42: =YEAR(P41) -> 2021 | Q42: =YEAR(Q41) -> 2022 | ... GJ42: =YEAR(GJ41) -> 2065
B44: Quarterly period number
E45: =E$90 -> Operating period flag | F45: =F$90 -> 0 | G45: =G$90 -> flag | H45: =H$90 -> 100 | I45: =I$90 -> 0 | J45: =J$90 -> 0 | K45: =K$90 -> 0 | L45: =L$90 -> 0 | ... GJ45: =GJ$90 -> 0
E46: Contract period number | J46: =I46 + J45 -> 0 | K46: =J46 + K45 -> 0 | L46: =K46 + L45 -> 0 | M46: =L46 + M45 -> 1 | N46: =M46 + N45 -> 2 | O46: =N46 + O45 -> 3 | P46: =O46 + P45 -> 4 | Q46: =P46 + Q45 -> 5 | ... GJ46: =GI46 + GJ45 -> 100
E48: =InpC!E$51 -> Number of periods in a year | F48: =InpC!F$51 -> 4 | G48: =InpC!G$51 -> periods
E49: =E$46 -> Contract period number | F49: =F$46 -> 0 | G49: =G$46 -> 0 | H49: =H$46 -> 0 | I49: =I$46 -> 0 | J49: =J$46 -> 0 | K49: =K$46 -> 0 | L49: =L$46 -> 0 | ... GJ49: =GJ$46 -> 100
E50: =E$90 -> Operating period flag | F50: =F$90 -> 0 | G50: =G$90 -> flag | H50: =H$90 -> 100 | I50: =I$90 -> 0 | J50: =J$90 -> 0 | K50: =K$90 -> 0 | L50: =L$90 -> 0 | ... GJ50: =GJ$90 -> 0
E51: Contract quarter number | G51: counter | J51: =IF( I51 = $F48, 1, I51 + 1) * J50 -> 0 | K51: =IF( J51 = $F48, 1, J51 + 1) * K50 -> 0 | L51: =IF( K51 = $F48, 1, K51 + 1) * L50 -> 0 | M51: =IF( L51 = $F48, 1, L51 + 1) * M50 -> 1 | N51: =IF( M51 = $F48, 1, M51 + 1) * N50 -> 2 | O51: =IF( N51 = $F48, 1, N51 + 1) * O50 -> 3 | P51: =IF( O51 = $F48, 1, O51 + 1) * P50 -> 4 | Q51: =IF( P51 = $F48, 1, P51 + 1) * Q50 -> 1 | ... GJ51: =IF( GI51 = $F48, 1, GI51 + 1) * GJ50 -> 0
E53: =InpC!E$51 -> Number of periods in a year | F53: =InpC!F$51 -> 4 | G53: =InpC!G$51 -> periods
E54: =E$33 -> End of contract year flag | F54: =F$33 -> 0 | G54: =G$33 -> 0 | H54: =H$33 -> 0 | I54: =I$33 -> 0 | J54: =J$33 -> 0 | K54: =K$33 -> 0 | L54: =L$33 -> 1 | ... GJ54: =GJ$33 -> 1
E55: =E$90 -> Operating period flag | F55: =F$90 -> 0 | G55: =G$90 -> flag | H55: =H$90 -> 100 | I55: =I$90 -> 0 | J55: =J$90 -> 0 | K55: =K$90 -> 0 | L55: =L$90 -> 0 | ... GJ55: =GJ$90 -> 0
E56: Contract year number | G56: counter | J56: =(I56 + I54) * J55 -> 0 | K56: =(J56 + J54) * K55 -> 0 | L56: =(K56 + K54) * L55 -> 0 | M56: =(L56 + L54) * M55 -> 1 | N56: =(M56 + M54) * N55 -> 1 | O56: =(N56 + N54) * O55 -> 1 | P56: =(O56 + O54) * P55 -> 1 | Q56: =(P56 + P54) * Q55 -> 2 | ... GJ56: =(GI56 + GI54) * GJ55 -> 0
A59: DAYS IN PERIOD
E60: =E$20 -> Model period beginning | F60: =F$20 -> 0 | G60: =G$20 -> date | H60: =H$20 -> 0 | I60: =I$20 -> 0 | J60: =J$20 -> 44013 | K60: =K$20 -> 44105 | L60: =L$20 -> 44197 | ... GJ60: =GJ$20 -> 60633
E61: =E$25 -> Model period ending | F61: =F$25 -> 0 | G61: =G$25 -> date | H61: =H$25 -> 0 | I61: =I$25 -> 0 | J61: =J$25 -> 44104 | K61: =K$25 -> 44196 | L61: =L$25 -> 44286 | ... GJ61: =GJ$25 -> 60722
E62: Days in operating period | G62: days | J62: =J61 - J60 + 1 -> 92 | K62: =K61 - K60 + 1 -> 92 | L62: =L61 - L60 + 1 -> 90 | M62: =M61 - M60 + 1 -> 91 | N62: =N61 - N60 + 1 -> 92 | O62: =O61 - O60 + 1 -> 92 | P62: =P61 - P60 + 1 -> 90 | Q62: =Q61 - Q60 + 1 -> 91 | ... GJ62: =GJ61 - GJ60 + 1 -> 90
A65: FLAGS
B67: Financial close date flag
E68: =InpC!E$19 -> Acquisition date | F68: =InpC!F$19 -> 44286 | G68: =InpC!G$19 -> date
E69: =E$25 -> Model period ending | F69: =F$25 -> 0 | G69: =G$25 -> date | H69: =H$25 -> 0 | I69: =I$25 -> 0 | J69: =J$25 -> 44104 | K69: =K$25 -> 44196 | L69: =L$25 -> 44286 | ... GJ69: =GJ$25 -> 60722
E70: Financial close date flag | G70: flag | H70: =SUM(J70:GJ70) -> 1 | J70: =IF(AND(I69 < $F68, J69 >= $F68), 1, 0) -> 0 | K70: =IF(AND(J69 < $F68, K69 >= $F68), 1, 0) -> 0 | L70: =IF(AND(K69 < $F68, L69 >= $F68), 1, 0) -> 1 | M70: =IF(AND(L69 < $F68, M69 >= $F68), 1, 0) -> 0 | N70: =IF(AND(M69 < $F68, N69 >= $F68), 1, 0) -> 0 | O70: =IF(AND(N69 < $F68, O69 >= $F68), 1, 0) -> 0 | P70: =IF(AND(O69 < $F68, P69 >= $F68), 1, 0) -> 0 | Q70: =IF(AND(P69 < $F68, Q69 >= $F68), 1, 0) -> 0 | ... GJ70: =IF(AND(GI69 < $F68, GJ69 >= $F68), 1, 0) -> 0
B72: Operating period flag
E73: =InpC!E$19 -> Acquisition date | F73: =InpC!F$19 -> 44286 | G73: =InpC!G$19 -> date
E74: =InpC!E$23 -> Operating years remaining | F74: =InpC!F$23 -> 25 | G74: =InpC!G$23 -> years
E75: =InpC!E$21 -> Construction delay length | F75: =InpC!F$21 -> 0 | G75: =InpC!G$21 -> months
E76: =InpC!E$50 -> Months in year | F76: =InpC!F$50 -> 12 | G76: =InpC!G$50 -> months
E77: End of operating period | F77: =EOMONTH(F73, ((F74 + F75) * F76)) -> 53417 | G77: date
B79: First operating period flag
E80: =E$70 -> Financial close date flag | F80: =F$70 -> 0 | G80: =G$70 -> flag | H80: =H$70 -> 1 | I80: =I$70 -> 0 | J80: =J$70 -> 0 | K80: =K$70 -> 0 | L80: =L$70 -> 1 | ... GJ80: =GJ$70 -> 0
E81: First operating period flag | G81: flag | H81: =SUM(J81:GJ81) -> 1 | J81: =I80 -> 0 | K81: =J80 -> 0 | L81: =K80 -> 0 | M81: =L80 -> 1 | N81: =M80 -> 0 | O81: =N80 -> 0 | P81: =O80 -> 0 | Q81: =P80 -> 0 | ... GJ81: =GI80 -> 0
B83: Last operating period flag
E84: =E$77 -> End of operating period | F84: =F$77 -> 53417 | G84: =G$77 -> date
E85: =E$25 -> Model period ending | F85: =F$25 -> 0 | G85: =G$25 -> date | H85: =H$25 -> 0 | I85: =I$25 -> 0 | J85: =J$25 -> 44104 | K85: =K$25 -> 44196 | L85: =L$25 -> 44286 | ... GJ85: =GJ$25 -> 60722
E86: Last operating period flag | G86: flag | H86: =SUM(J86:GJ86) -> 1 | J86: =IF(J85 = $F84, 1, 0) -> 0 | K86: =IF(K85 = $F84, 1, 0) -> 0 | L86: =IF(L85 = $F84, 1, 0) -> 0 | M86: =IF(M85 = $F84, 1, 0) -> 0 | N86: =IF(N85 = $F84, 1, 0) -> 0 | O86: =IF(O85 = $F84, 1, 0) -> 0 | P86: =IF(P85 = $F84, 1, 0) -> 0 | Q86: =IF(Q85 = $F84, 1, 0) -> 0 | ... GJ86: =IF(GJ85 = $F84, 1, 0) -> 0
E88: =E$81 -> First operating period flag | F88: =F$81 -> 0 | G88: =G$81 -> flag | H88: =H$81 -> 1 | I88: =I$81 -> 0 | J88: =J$81 -> 0 | K88: =K$81 -> 0 | L88: =L$81 -> 0 | ... GJ88: =GJ$81 -> 0
E89: =E$86 -> Last operating period flag | F89: =F$86 -> 0 | G89: =G$86 -> flag | H89: =H$86 -> 1 | I89: =I$86 -> 0 | J89: =J$86 -> 0 | K89: =K$86 -> 0 | L89: =L$86 -> 0 | ... GJ89: =GJ$86 -> 0
E90: Operating period flag | G90: flag | H90: =SUM(J90:GJ90) -> 100 | J90: =J88 + I90 - I89 -> 0 | K90: =K88 + J90 - J89 -> 0 | L90: =L88 + K90 - K89 -> 0 | M90: =M88 + L90 - L89 -> 1 | N90: =N88 + M90 - M89 -> 1 | O90: =O88 + N90 - N89 -> 1 | P90: =P88 + O90 - O89 -> 1 | Q90: =Q88 + P90 - P89 -> 1 | ... GJ90: =GJ88 + GI90 - GI89 -> 0
B93: First PPA ops perod extension period flag
E94: =E$77 -> End of operating period | F94: =F$77 -> 53417 | G94: =G$77 -> date
E95: PPA ops perod extension period start date | F95: =F94 + 1 -> 53418 | G95: date
E97: =E$95 -> PPA ops perod extension period start date | F97: =F$95 -> 53418 | G97: =G$95 -> date
E98: =E$25 -> Model period ending | F98: =F$25 -> 0 | G98: =G$25 -> date | H98: =H$25 -> 0 | I98: =I$25 -> 0 | J98: =J$25 -> 44104 | K98: =K$25 -> 44196 | L98: =L$25 -> 44286 | ... GJ98: =GJ$25 -> 60722
E99: First PPA ops perod extension period flag | G99: flag | H99: =SUM(J99:GJ99) -> 1 | J99: =IF(AND(I98 < $F97, J98 >= $F97), 1, 0) -> 0 | K99: =IF(AND(J98 < $F97, K98 >= $F97), 1, 0) -> 0 | L99: =IF(AND(K98 < $F97, L98 >= $F97), 1, 0) -> 0 | M99: =IF(AND(L98 < $F97, M98 >= $F97), 1, 0) -> 0 | N99: =IF(AND(M98 < $F97, N98 >= $F97), 1, 0) -> 0 | O99: =IF(AND(N98 < $F97, O98 >= $F97), 1, 0) -> 0 | P99: =IF(AND(O98 < $F97, P98 >= $F97), 1, 0) -> 0 | Q99: =IF(AND(P98 < $F97, Q98 >= $F97), 1, 0) -> 0 | ... GJ99: =IF(AND(GI98 < $F97, GJ98 >= $F97), 1, 0) -> 0
B101: Last operating period flag
E102: =E$77 -> End of operating period | F102: =F$77 -> 53417 | G102: =G$77 -> date
E103: =E$25 -> Model period ending | F103: =F$25 -> 0 | G103: =G$25 -> date | H103: =H$25 -> 0 | I103: =I$25 -> 0 | J103: =J$25 -> 44104 | K103: =K$25 -> 44196 | L103: =L$25 -> 44286 | ... GJ103: =GJ$25 -> 60722
E104: Last operating period flag | G104: flag | H104: =SUM(J104:GJ104) -> 1 | J104: =IF(AND(I103 < $F102, J103 >= $F102), 1, 0) -> 0 | K104: =IF(AND(J103 < $F102, K103 >= $F102), 1, 0) -> 0 | L104: =IF(AND(K103 < $F102, L103 >= $F102), 1, 0) -> 0 | M104: =IF(AND(L103 < $F102, M103 >= $F102), 1, 0) -> 0 | N104: =IF(AND(M103 < $F102, N103 >= $F102), 1, 0) -> 0 | O104: =IF(AND(N103 < $F102, O103 >= $F102), 1, 0) -> 0 | P104: =IF(AND(O103 < $F102, P103 >= $F102), 1, 0) -> 0 | Q104: =IF(AND(P103 < $F102, Q103 >= $F102), 1, 0) -> 0 | ... GJ104: =IF(AND(GI103 < $F102, GJ103 >= $F102), 1, 0) -> 0
E106: =E$104 -> Last operating period flag | F106: =F$104 -> 0 | G106: =G$104 -> flag | H106: =H$104 -> 1 | I106: =I$104 -> 0 | J106: =J$104 -> 0 | K106: =K$104 -> 0 | L106: =L$104 -> 0 | ... GJ106: =GJ$104 -> 0
E107: First post operating period flag | J107: =I106 -> 0 | K107: =J106 -> 0 | L107: =K106 -> 0 | M107: =L106 -> 0 | N107: =M106 -> 0 | O107: =N106 -> 0 | P107: =O106 -> 0 | Q107: =P106 -> 0 | ... GJ107: =GI106 -> 0
B112: Useful life of plant flag
E113: =InpC!E$19 -> Acquisition date | F113: =InpC!F$19 -> 44286 | G113: =InpC!G$19 -> date
E114: =InpC!#REF! -> #REF! | F114: =InpC!#REF! -> #REF! | G114: =InpC!#REF! -> #REF!
E115: =InpC!E$50 -> Months in year | F115: =InpC!F$50 -> 12 | G115: =InpC!G$50 -> months
E116: End of useful life of asset | F116: =EOMONTH(F113, F114 * F115) -> #REF! | G116: date
E118: =InpC!E$19 -> Acquisition date | F118: =InpC!F$19 -> 44286 | G118: =InpC!G$19 -> date
E119: =E$116 -> End of useful life of asset | F119: =F$116 -> #REF! | G119: =G$116 -> date
E120: =E$25 -> Model period ending | F120: =F$25 -> 0 | G120: =G$25 -> date | H120: =H$25 -> 0 | I120: =I$25 -> 0 | J120: =J$25 -> 44104 | K120: =K$25 -> 44196 | L120: =L$25 -> 44286 | ... GJ120: =GJ$25 -> 60722
E121: Useful life of asset flag | G121: =SMU -> $ 000s | H121: =SUM(J121:GJ121) -> #REF! | J121: =IF( AND( J120 > $F118, J120 <= $F119), 1, 0) -> #REF! | K121: =IF( AND( K120 > $F118, K120 <= $F119), 1, 0) -> #REF! | L121: =IF( AND( L120 > $F118, L120 <= $F119), 1, 0) -> #REF! | M121: =IF( AND( M120 > $F118, M120 <= $F119), 1, 0) -> #REF! | N121: =IF( AND( N120 > $F118, N120 <= $F119), 1, 0) -> #REF! | O121: =IF( AND( O120 > $F118, O120 <= $F119), 1, 0) -> #REF! | P121: =IF( AND( P120 > $F118, P120 <= $F119), 1, 0) -> #REF! | Q121: =IF( AND( Q120 > $F118, Q120 <= $F119), 1, 0) -> #REF! | ... GJ121: =IF( AND( GJ120 > $F118, GJ120 <= $F119), 1, 0) -> #REF!
B124: Senior debt repayment period flag
E125: =InpC!E$19 -> Acquisition date | F125: =InpC!F$19 -> 44286 | G125: =InpC!G$19 -> date
E126: =InpC!#REF! -> #REF! | F126: =InpC!#REF! -> #REF! | G126: =InpC!#REF! -> #REF!
E127: =InpC!E$50 -> Months in year | F127: =InpC!F$50 -> 12 | G127: =InpC!G$50 -> months
E128: Last senior debt repayment period | F128: =EOMONTH(F125, F126 * F127) -> #REF! | G128: date
E130: =InpC!E$19 -> Acquisition date | F130: =InpC!F$19 -> 44286 | G130: =InpC!G$19 -> date
E131: =E$128 -> Last senior debt repayment period | F131: =F$128 -> #REF! | G131: =G$128 -> date
E132: =E$25 -> Model period ending | F132: =F$25 -> 0 | G132: =G$25 -> date | H132: =H$25 -> 0 | I132: =I$25 -> 0 | J132: =J$25 -> 44104 | K132: =K$25 -> 44196 | L132: =L$25 -> 44286 | ... GJ132: =GJ$25 -> 60722
E133: Senior debt repayment period flag | G133: =SMU -> $ 000s | H133: =SUM(J133:GJ133) -> #REF! | J133: =IF( AND( J132 > $F130, J132 <= $F131), 1, 0) -> #REF! | K133: =IF( AND( K132 > $F130, K132 <= $F131), 1, 0) -> #REF! | L133: =IF( AND( L132 > $F130, L132 <= $F131), 1, 0) -> #REF! | M133: =IF( AND( M132 > $F130, M132 <= $F131), 1, 0) -> #REF! | N133: =IF( AND( N132 > $F130, N132 <= $F131), 1, 0) -> #REF! | O133: =IF( AND( O132 > $F130, O132 <= $F131), 1, 0) -> #REF! | P133: =IF( AND( P132 > $F130, P132 <= $F131), 1, 0) -> #REF! | Q133: =IF( AND( Q132 > $F130, Q132 <= $F131), 1, 0) -> #REF! | ... GJ133: =IF( AND( GJ132 > $F130, GJ132 <= $F131), 1, 0) -> #REF!
B136: Senior debt refinancing period flag
...

Sheet Ops
A1: =RIGHT(CELL("filename", A1), LEN(CELL("filename", A1)) - SEARCH("]", CELL("filename", A1))) & " - " & InpC!F3 -> Ops - Case 1
E2: =Time!E$25 -> Model period ending | F2: 0 | G2: Error chks | J2: =Time!J$25 -> 44104 | K2: =Time!K$25 -> 44196 | L2: =Time!L$25 -> 44286 | M2: =Time!M$25 -> 44377 | N2: =Time!N$25 -> 44469 | O2: =Time!O$25 -> 44561 | P2: =Time!P$25 -> 44651 | Q2: =Time!Q$25 -> 44742 | ... GJ2: =Time!GJ$25 -> 60722
E3: =Time!E$188 -> Timeline label | F3: 0 | G3: Track chgs | J3: =Time!J$188 -> Pre-fcst | K3: =Time!K$188 -> Pre-fcst | L3: =Time!L$188 -> Fin Close | M3: =Time!M$188 -> Operations | N3: =Time!N$188 -> Operations | O3: =Time!O$188 -> Operations | P3: =Time!P$188 -> Operations | Q3: =Time!Q$188 -> Operations | ... GJ3: =Time!GJ$188 -> Post ops
E4: =Time!E$42 -> Contract year | F4: 0 | G4: Alerts | J4: =Time!J$42 -> 2020 | K4: =Time!K$42 -> 2020 | L4: =Time!L$42 -> 2020 | M4: =Time!M$42 -> 2021 | N4: =Time!N$42 -> 2021 | O4: =Time!O$42 -> 2021 | P4: =Time!P$42 -> 2021 | Q4: =Time!Q$42 -> 2022 | ... GJ4: =Time!GJ$42 -> 2065
E5: =Time!E$10 -> model column counter | F5: Constant | G5: Unit | H5: Total | J5: =Time!J$10 -> 1 | K5: =Time!K$10 -> 2 | L5: =Time!L$10 -> 3 | M5: =Time!M$10 -> 4 | N5: =Time!N$10 -> 5 | O5: =Time!O$10 -> 6 | P5: =Time!P$10 -> 7 | Q5: =Time!Q$10 -> 8 | ... GJ5: =Time!GJ$10 -> 183
E8: Electricity generation revenue | G8: =SMU -> $ 000s | H8: =SUM(J8:PY8) -> 371409.68 | J8: =InpC!$F$36 / InpC!$F$55*InpC!$F$34*InpC!$F$35*IF(Time!J$90=1,1/((1+InpC!$F$33)^(Time!J$56-1)),0) *IF(Time!J$90=1,INDEX(InpC!$F28:$F31,Time!J$51),0)*InpC!$F$54*Time!J$90 -> 0 | K8: =InpC!$F$36 / InpC!$F$55*InpC!$F$34*InpC!$F$35*IF(Time!K$90=1,1/((1+InpC!$F$33)^(Time!K$56-1)),0) *IF(Time!K$90=1,INDEX(InpC!$F28:$F31,Time!K$51),0)*InpC!$F$54*Time!K$90 -> 0 | L8: =InpC!$F$36 / InpC!$F$55*InpC!$F$34*InpC!$F$35*IF(Time!L$90=1,1/((1+InpC!$F$33)^(Time!L$56-1)),0) *IF(Time!L$90=1,INDEX(InpC!$F28:$F31,Time!L$51),0)*InpC!$F$54*Time!L$90 -> 0 | M8: =InpC!$F$36 / InpC!$F$55*InpC!$F$34*InpC!$F$35*IF(Time!M$90=1,1/((1+InpC!$F$33)^(Time!M$56-1)),0) *IF(Time!M$90=1,INDEX(InpC!$F28:$F31,Time!M$51),0)*InpC!$F$54*Time!M$90 -> 5201.625 | N8: =InpC!$F$36 / InpC!$F$55*InpC!$F$34*InpC!$F$35*IF(Time!N$90=1,1/((1+InpC!$F$33)^(Time!N$56-1)),0) *IF(Time!N$90=1,INDEX(InpC!$F28:$F31,Time!N$51),0)*InpC!$F$54*Time!N$90 -> 5674.5 | O8: =InpC!$F$36 / InpC!$F$55*InpC!$F$34*InpC!$F$35*IF(Time!O$90=1,1/((1+InpC!$F$33)^(Time!O$56-1)),0) *IF(Time!O$90=1,INDEX(InpC!$F28:$F31,Time!O$51),0)*InpC!$F$54*Time!O$90 -> 2443.1875 | P8: =InpC!$F$36 / InpC!$F$55*InpC!$F$34*InpC!$F$35*IF(Time!P$90=1,1/((1+InpC!$F$33)^(Time!P$56-1)),0) *IF(Time!P$90=1,INDEX(InpC!$F28:$F31,Time!P$51),0)*InpC!$F$54*Time!P$90 -> 2443.1875 | Q8: =InpC!$F$36 / InpC!$F$55*InpC!$F$34*InpC!$F$35*IF(Time!Q$90=1,1/((1+InpC!$F$33)^(Time!Q$56-1)),0) *IF(Time!Q$90=1,INDEX(InpC!$F28:$F31,Time!Q$51),0)*InpC!$F$54*Time!Q$90 -> 5175.7463 | ... GJ8: =InpC!$F$36 / InpC!$F$55*InpC!$F$34*InpC!$F$35*IF(Time!GJ$90=1,1/((1+InpC!$F$33)^(Time!GJ$56-1)),0) *IF(Time!GJ$90=1,INDEX(InpC!$F28:$F31,Time!GJ$51),0)*InpC!$F$54*Time!GJ$90 -> 0
A11: REVENUE
B13: Compound degredation
E14: =InpC!E$33 -> Annual degredation | F14: =InpC!F$33 -> 0.005 | G14: =InpC!G$33 -> % p.a. | I14: 0 | J14: 0
E15: =Time!E$56 -> Contract year number | F15: =Time!F$56 -> 0 | G15: =Time!G$56 -> counter | H15: =Time!H$56 -> 0 | I15: =Time!I$56 -> 0 | J15: =Time!J$56 -> 0 | K15: =Time!K$56 -> 0 | L15: =Time!L$56 -> 0 | ... GJ15: =Time!GJ$56 -> 0
E16: =Time!E$90 -> Operating period flag | F16: =Time!F$90 -> 0 | G16: =Time!G$90 -> flag | H16: =Time!H$90 -> 100 | I16: =Time!I$90 -> 0 | J16: =Time!J$90 -> 0 | K16: =Time!K$90 -> 0 | L16: =Time!L$90 -> 0 | ... GJ16: =Time!GJ$90 -> 0
E17: Compound degredation | G17: % | H17: 0 | I17: 0 | J17: =IF( J16 = 1, 1 / ((1 + $F14) ^ (J15 - 1)), 0) -> 0 | K17: =IF( K16 = 1, 1 / ((1 + $F14) ^ (K15 - 1)), 0) -> 0 | L17: =IF( L16 = 1, 1 / ((1 + $F14) ^ (L15 - 1)), 0) -> 0 | M17: =IF( M16 = 1, 1 / ((1 + $F14) ^ (M15 - 1)), 0) -> 1 | N17: =IF( N16 = 1, 1 / ((1 + $F14) ^ (N15 - 1)), 0) -> 1 | O17: =IF( O16 = 1, 1 / ((1 + $F14) ^ (O15 - 1)), 0) -> 1 | P17: =IF( P16 = 1, 1 / ((1 + $F14) ^ (P15 - 1)), 0) -> 1 | Q17: =IF( Q16 = 1, 1 / ((1 + $F14) ^ (Q15 - 1)), 0) -> 0.99502488 | ... GJ17: =IF( GJ16 = 1, 1 / ((1 + $F14) ^ (GJ15 - 1)), 0) -> 0
B19: Seasonality adjustment
E20: =InpC!E$28 -> Q1 yield | F20: =InpC!F$28 -> 0.33 | G20: =InpC!G$28 -> % of annual yield
E21: =InpC!E$29 -> Q2 yield | F21: =InpC!F$29 -> 0.36 | G21: =InpC!G$29 -> % of annual yield
E22: =InpC!E$30 -> Q3 yield | F22: =InpC!F$30 -> 0.155 | G22: =InpC!G$30 -> % of annual yield
E23: =InpC!E$31 -> Q4 yield | F23: =InpC!F$31 -> 0.155 | G23: =InpC!G$31 -> % of annual yield
E24: =Time!E$51 -> Contract quarter number | F24: =Time!F$51 -> 0 | G24: =Time!G$51 -> counter | H24: =Time!H$51 -> 0 | I24: =Time!I$51 -> 0 | J24: =Time!J$51 -> 0 | K24: =Time!K$51 -> 0 | L24: =Time!L$51 -> 0 | ... GJ24: =Time!GJ$51 -> 0
E25: =Time!E$90 -> Operating period flag | F25: =Time!F$90 -> 0 | G25: =Time!G$90 -> flag | H25: =Time!H$90 -> 100 | I25: =Time!I$90 -> 0 | J25: =Time!J$90 -> 0 | K25: =Time!K$90 -> 0 | L25: =Time!L$90 -> 0 | ... GJ25: =Time!GJ$90 -> 0
E26: Seasonality adjustment | G26: % | H26: =SUM(J26:GJ26) -> 25 | J26: =IF(J25 = 1, INDEX($F20:$F23, J24), 0) -> 0 | K26: =IF(K25 = 1, INDEX($F20:$F23, K24), 0) -> 0 | L26: =IF(L25 = 1, INDEX($F20:$F23, L24), 0) -> 0 | M26: =IF(M25 = 1, INDEX($F20:$F23, M24), 0) -> 0.33 | N26: =IF(N25 = 1, INDEX($F20:$F23, N24), 0) -> 0.36 | O26: =IF(O25 = 1, INDEX($F20:$F23, O24), 0) -> 0.155 | P26: =IF(P25 = 1, INDEX($F20:$F23, P24), 0) -> 0.155 | Q26: =IF(Q25 = 1, INDEX($F20:$F23, Q24), 0) -> 0.33 | ... GJ26: =IF(GJ25 = 1, INDEX($F20:$F23, GJ24), 0) -> 0
B28: Electricity adjustment
E29: =InpC!E$34 -> Year 1 P50 yield | F29: =InpC!F$34 -> 250 | G29: =InpC!G$34 -> GWh
E30: =InpC!E$35 -> Availability | F30: =InpC!F$35 -> 0.97 | G30: =InpC!G$35 -> %
E31: =E$17 -> Compound degredation | F31: =F$17 -> 0 | G31: =G$17 -> % | H31: =H$17 -> 0 | I31: =I$17 -> 0 | J31: =J$17 -> 0 | K31: =K$17 -> 0 | L31: =L$17 -> 0 | ... GJ31: =GJ$17 -> 0
E32: =E$26 -> Seasonality adjustment | F32: =F$26 -> 0 | G32: =G$26 -> % | H32: =H$26 -> 25 | I32: =I$26 -> 0 | J32: =J$26 -> 0 | K32: =K$26 -> 0 | L32: =L$26 -> 0 | ... GJ32: =GJ$26 -> 0
E33: Electricty generation | G33: MWh | H33: =SUM(J33:PY33) -> 5713.9951 | J33: =$F29 * $F30 * J31 * J32 -> 0 | K33: =$F29 * $F30 * K31 * K32 -> 0 | L33: =$F29 * $F30 * L31 * L32 -> 0 | M33: =$F29 * $F30 * M31 * M32 -> 80.025 | N33: =$F29 * $F30 * N31 * N32 -> 87.3 | O33: =$F29 * $F30 * O31 * O32 -> 37.5875 | P33: =$F29 * $F30 * P31 * P32 -> 37.5875 | Q33: =$F29 * $F30 * Q31 * Q32 -> 79.626866 | ... GJ33: =$F29 * $F30 * GJ31 * GJ32 -> 0
B35: Electricity generation revenue
E36: =InpC!E$36 -> Power tariff | F36: =InpC!F$36 -> 0.065 | G36: =InpC!G$36 -> USD / kWh
E37: =InpC!E$55 -> Units in a thousand | F37: =InpC!F$55 -> 1000 | G37: =InpC!G$55 -> units
E38: =InpC!E$54 -> GWh to KWh conversion | F38: =InpC!F$54 -> 1000000 | G38: =InpC!G$54 -> kWh / GWh
E39: =E$33 -> Electricty generation | F39: =F$33 -> 0 | G39: =G$33 -> MWh | H39: =H$33 -> 5713.9951 | I39: =I$33 -> 0 | J39: =J$33 -> 0 | K39: =K$33 -> 0 | L39: =L$33 -> 0 | ... GJ39: =GJ$33 -> 0
E40: =Time!E$90 -> Operating period flag | F40: =Time!F$90 -> 0 | G40: =Time!G$90 -> flag | H40: =Time!H$90 -> 100 | I40: =Time!I$90 -> 0 | J40: =Time!J$90 -> 0 | K40: =Time!K$90 -> 0 | L40: =Time!L$90 -> 0 | ... GJ40: =Time!GJ$90 -> 0
E41: Electricity generation revenue | G41: =SMU -> $ 000s | H41: =SUM(J41:PY41) -> 371409.68 | J41: =$F36 / $F37 * J39 * $F38 * J40 -> 0 | K41: =$F36 / $F37 * K39 * $F38 * K40 -> 0 | L41: =$F36 / $F37 * L39 * $F38 * L40 -> 0 | M41: =$F36 / $F37 * M39 * $F38 * M40 -> 5201.625 | N41: =$F36 / $F37 * N39 * $F38 * N40 -> 5674.5 | O41: =$F36 / $F37 * O39 * $F38 * O40 -> 2443.1875 | P41: =$F36 / $F37 * P39 * $F38 * P40 -> 2443.1875 | Q41: =$F36 / $F37 * Q39 * $F38 * Q40 -> 5175.7463 | ... GJ41: =$F36 / $F37 * GJ39 * $F38 * GJ40 -> 0
A144: END

Sheet Tmp
A1: =RIGHT(CELL("filename", A1), LEN(CELL("filename", A1)) - SEARCH("]", CELL("filename", A1))) & " - " & InpC!F3 -> Tmp - Case 1
E2: =Time!E$25 -> Model period ending | F2: 0 | G2: Error chks | J2: =Time!J$25 -> 44104 | K2: =Time!K$25 -> 44196 | L2: =Time!L$25 -> 44286 | M2: =Time!M$25 -> 44377 | N2: =Time!N$25 -> 44469 | O2: =Time!O$25 -> 44561 | P2: =Time!P$25 -> 44651 | Q2: =Time!Q$25 -> 44742 | ... GJ2: =Time!GJ$25 -> 60722
E3: =Time!E$188 -> Timeline label | F3: 0 | G3: Track chgs | J3: =Time!J$188 -> Pre-fcst | K3: =Time!K$188 -> Pre-fcst | L3: =Time!L$188 -> Fin Close | M3: =Time!M$188 -> Operations | N3: =Time!N$188 -> Operations | O3: =Time!O$188 -> Operations | P3: =Time!P$188 -> Operations | Q3: =Time!Q$188 -> Operations | ... GJ3: =Time!GJ$188 -> Post ops
E4: =Time!E$42 -> Contract year | F4: 0 | G4: Alerts | J4: =Time!J$42 -> 2020 | K4: =Time!K$42 -> 2020 | L4: =Time!L$42 -> 2020 | M4: =Time!M$42 -> 2021 | N4: =Time!N$42 -> 2021 | O4: =Time!O$42 -> 2021 | P4: =Time!P$42 -> 2021 | Q4: =Time!Q$42 -> 2022 | ... GJ4: =Time!GJ$42 -> 2065
E5: =Time!E$10 -> model column counter | F5: Constant | G5: Unit | H5: Total | J5: =Time!J$10 -> 1 | K5: =Time!K$10 -> 2 | L5: =Time!L$10 -> 3 | M5: =Time!M$10 -> 4 | N5: =Time!N$10 -> 5 | O5: =Time!O$10 -> 6 | P5: =Time!P$10 -> 7 | Q5: =Time!Q$10 -> 8 | ... GJ5: =Time!GJ$10 -> 183
E9: [xxx] - initial balance
E10: =Time!E$70 -> Financial close date flag | F10: =Time!F$70 -> 0 | G10: =Time!G$70 -> flag | H10: =Time!H$70 -> 1 | I10: =Time!I$70 -> 0 | J10: =Time!J$70 -> 0 | K10: =Time!K$70 -> 0 | L10: =Time!L$70 -> 1 | ... GJ10: =Time!GJ$70 -> 0
E12: [xxx] balance BEG | G12: =SMU -> $ 000s | J12: =I15 -> 0 | K12: =J15 -> 0 | L12: =K15 -> 0 | M12: =L15 -> 0 | N12: =M15 -> 0 | O12: =N15 -> 0 | P12: =O15 -> 0 | Q12: =P15 -> 0 | ... GJ12: =GI15 -> 0
E13: [upward flow]
E14: [downward flow]
E15: [xxx] balance | G15: =SMU -> $ 000s | J15: =IF( J10 = 1, $F9, J12 + J13 - J14) -> 0 | K15: =IF( K10 = 1, $F9, K12 + K13 - K14) -> 0 | L15: =IF( L10 = 1, $F9, L12 + L13 - L14) -> 0 | M15: =IF( M10 = 1, $F9, M12 + M13 - M14) -> 0 | N15: =IF( N10 = 1, $F9, N12 + N13 - N14) -> 0 | O15: =IF( O10 = 1, $F9, O12 + O13 - O14) -> 0 | P15: =IF( P10 = 1, $F9, P12 + P13 - P14) -> 0 | Q15: =IF( Q10 = 1, $F9, Q12 + Q13 - Q14) -> 0 | ... GJ15: =IF( GJ10 = 1, $F9, GJ12 + GJ13 - GJ14) -> 0
E18: Sign switch line item POS | G18: =SMU -> $ 000s | H18: =SUM(J18:GJ18) -> 18300 | J18: 100 | K18: 100 | L18: 100 | M18: 100 | N18: 100 | O18: 100 | P18: 100 | Q18: 100 | R18: 100 | S18: 100 | T18: 100 | U18: 100 | V18: 100 | W18: 100 | X18: 100 | Y18: 100 | Z18: 100 | AA18: 100 | AB18: 100 | AC18: 100 | AD18: 100 | AE18: 100 | AF18: 100 | AG18: 100 | AH18: 100 | AI18: 100 | AJ18: 100 | AK18: 100 | AL18: 100 | AM18: 100 | AN18: 100 | AO18: 100 | AP18: 100 | AQ18: 100 | AR18: 100 | AS18: 100 | AT18: 100 | AU18: 100 | AV18: 100 | AW18: 100 | AX18: 100 | AY18: 100 | AZ18: 100 | BA18: 100 | BB18: 100 | BC18: 100 | BD18: 100 | BE18: 100 | BF18: 100 | BG18: 100 | BH18: 100 | BI18: 100 | BJ18: 100 | BK18: 100 | BL18: 100 | BM18: 100 | BN18: 100 | BO18: 100 | BP18: 100 | BQ18: 100 | BR18: 100 | BS18: 100 | BT18: 100 | BU18: 100 | BV18: 100 | BW18: 100 | BX18: 100 | BY18: 100 | BZ18: 100 | CA18: 100 | CB18: 100 | CC18: 100 | CD18: 100 | CE18: 100 | CF18: 100 | CG18: 100 | CH18: 100 | CI18: 100 | CJ18: 100 | CK18: 100 | CL18: 100 | CM18: 100 | CN18: 100 | CO18: 100 | CP18: 100 | CQ18: 100 | CR18: 100 | CS18: 100 | CT18: 100 | CU18: 100 | CV18: 100 | CW18: 100 | CX18: 100 | CY18: 100 | CZ18: 100 | DA18: 100 | DB18: 100 | DC18: 100 | DD18: 100 | DE18: 100 | DF18: 100 | DG18: 100 | DH18: 100 | DI18: 100 | DJ18: 100 | DK18: 100 | DL18: 100 | DM18: 100 | DN18: 100 | DO18: 100 | DP18: 100 | DQ18: 100 | DR18: 100 | DS18: 100 | DT18: 100 | DU18: 100 | DV18: 100 | DW18: 100 | DX18: 100 | DY18: 100 | DZ18: 100 | EA18: 100 | EB18: 100 | EC18: 100 | ED18: 100 | EE18: 100 | EF18: 100 | EG18: 100 | EH18: 100 | EI18: 100 | EJ18: 100 | EK18: 100 | EL18: 100 | EM18: 100 | EN18: 100 | EO18: 100 | EP18: 100 | EQ18: 100 | ER18: 100 | ES18: 100 | ET18: 100 | EU18: 100 | EV18: 100 | EW18: 100 | EX18: 100 | EY18: 100 | EZ18: 100 | FA18: 100 | FB18: 100 | FC18: 100 | FD18: 100 | FE18: 100 | FF18: 100 | FG18: 100 | FH18: 100 | FI18: 100 | FJ18: 100 | FK18: 100 | FL18: 100 | FM18: 100 | FN18: 100 | FO18: 100 | FP18: 100 | FQ18: 100 | FR18: 100 | FS18: 100 | FT18: 100 | FU18: 100 | FV18: 100 | FW18: 100 | FX18: 100 | FY18: 100 | FZ18: 100 | GA18: 100 | GB18: 100 | GC18: 100 | GD18: 100 | GE18: 100 | GF18: 100 | GG18: 100 | GH18: 100 | GI18: 100 | GJ18: 100
E19: =LEFT(E18, LEN(E18) - 4) -> Sign switch line item | G19: =SMU -> $ 000s | H19: =SUM(J19:GJ19) -> -18300 | J19: =-1 * J18 -> -100 | K19: =-1 * K18 -> -100 | L19: =-1 * L18 -> -100 | M19: =-1 * M18 -> -100 | N19: =-1 * N18 -> -100 | O19: =-1 * O18 -> -100 | P19: =-1 * P18 -> -100 | Q19: =-1 * Q18 -> -100 | ... GJ19: =-1 * GJ18 -> -100
