Workbook
Name BaseCaseIndicator: InpC!$J$7:$S$7
Name CASE_ACTIVE: InpC!$F$4
Name CHK_TOL: InpC!$F$58
Name InputRowTemplate: InpC!$E$73:$S$73
Name InputStored: InpC!$J$3:$S$3
Name OutputRowTemplate: Output!$E$67:$Z$67
Name SMU: InpC!$F$61
Name TrackActive: Output!$H$5
Name TrackLiveResults: Output!$H$6:$H$74
Name TrackStoredResults: Output!$M$5:$Z$5
Name TRK_TOL: InpC!$F$57

Sheet InpC
A1: =RIGHT(CELL("filename", A1), LEN(CELL("filename", A1)) - SEARCH("]", CELL("filename", A1))) & " - " & $F$3 -> InpC - Base case 1
K2: =IF(K4 = $F4, "q", "") -> q | L2: =IF(L4 = $F4, "q", "") | M2: =IF(M4 = $F4, "q", "") | O2: =IF(O4 = $F4, "q", "") | P2: =IF(P4 = $F4, "q", "") | Q2: =IF(Q4 = $F4, "q", "") | R2: =IF(R4 = $F4, "q", "")
F3: =INDEX(J3:S3,MATCH(F4,J4:S4)) -> Base case 1 | K3: Base case 1 | L3: Base case 2 | M3: Base case 3 | O3: Scenario 1 | P3: Scenario 2 | Q3: Scenario 3 | R3: Scenario 4
E4: Active scenario | F4: 1 | I4: =MATCH(F4, $J$4:$S$4) -> 2 | K4: 1 | L4: 2 | M4: 3 | O4: 5 | P4: 6 | Q4: 7 | R4: 8
E5: Comparison scenario | F5: 1 | I5: =MATCH(F5, $J$4:$S$4) -> 2
E6: Base case | F6: =INDEX(J6:S6,MATCH(F4,J4:S4,0)) -> 1 | I6: =MATCH(F6, $J$4:$S$4) -> 2 | K6: 1 | L6: 2 | M6: 3 | O6: 1 | P6: 1 | Q6: 2 | R6: 2
E7: Input differences | F7: =COUNTIF(I10:I55, "tu") -> 0 | K7: =IF(K6 = $F$6, "Base case", "") -> Base case | L7: =IF(L6 = $F$6, "Base case", "") | M7: =IF(M6 = $F$6, "Base case", "")
F9: Constant | G9: Unit | H9: Source
A11: TIMING ASSUMPTIONS
E13: First date of time rulers | F13: =IF( INDEX(J13:S13, $I$4) = "", INDEX(J13:R13, $I$6), INDEX(J13:S13, $I$4)) -> 44013 | G13: date | I13: {=IF( INDEX(J13:S13, I$5) = "", IF( INDEX(J13:S13, I$6) = F13, "vw", "tu"), IF(INDEX(J13:S13, I$5) = F13, "vw", "tu"))} -> vw | K13: 44013
E14: Annual year end date of first operating period | F14: =IF( INDEX(J14:S14, $I$4) = "", INDEX(J14:R14, $I$6), INDEX(J14:S14, $I$4)) -> 43921 | G14: date | I14: {=IF( INDEX(J14:S14, I$5) = "", IF( INDEX(J14:S14, I$6) = F14, "vw", "tu"), IF(INDEX(J14:S14, I$5) = F14, "vw", "tu"))} -> vw | K14: 43921
E15: Financial year end month number | F15: =IF( INDEX(J15:S15, $I$4) = "", INDEX(J15:R15, $I$6), INDEX(J15:S15, $I$4)) -> 12 | G15: month # | I15: {=IF( INDEX(J15:S15, I$5) = "", IF( INDEX(J15:S15, I$6) = F15, "vw", "tu"), IF(INDEX(J15:S15, I$5) = F15, "vw", "tu"))} -> vw | K15: 12
E16: Length of operating period | F16: =IF( INDEX(J16:S16, $I$4) = "", INDEX(J16:R16, $I$6), INDEX(J16:S16, $I$4)) -> 3 | G16: months | I16: {=IF( INDEX(J16:S16, I$5) = "", IF( INDEX(J16:S16, I$6) = F16, "vw", "tu"), IF(INDEX(J16:S16, I$5) = F16, "vw", "tu"))} -> vw | K16: 3
E18: Acquisition date | F18: =IF( INDEX(J18:S18, $I$4) = "", INDEX(J18:R18, $I$6), INDEX(J18:S18, $I$4)) -> 44286 | G18: date | I18: {=IF( INDEX(J18:S18, I$5) = "", IF( INDEX(J18:S18, I$6) = F18, "vw", "tu"), IF(INDEX(J18:S18, I$5) = F18, "vw", "tu"))} -> vw | K18: 44286
E20: Operating years remaining | F20: =IF( INDEX(J20:S20, $I$4) = "", INDEX(J20:R20, $I$6), INDEX(J20:S20, $I$4)) -> 25 | G20: years | I20: {=IF( INDEX(J20:S20, I$5) = "", IF( INDEX(J20:S20, I$6) = F20, "vw", "tu"), IF(INDEX(J20:S20, I$5) = F20, "vw", "tu"))} -> vw | K20: 25
E21: Contract extension | F21: =IF( INDEX(J21:S21, $I$4) = "", INDEX(J21:R21, $I$6), INDEX(J21:S21, $I$4)) -> 0 | G21: years | I21: {=IF( INDEX(J21:S21, I$5) = "", IF( INDEX(J21:S21, I$6) = F21, "vw", "tu"), IF(INDEX(J21:S21, I$5) = F21, "vw", "tu"))} -> vw | K21: 0
A23: REVENUE
E24: Q1 seasonal adjustment | F24: =IF( INDEX(J24:S24, $I$4) = "", INDEX(J24:R24, $I$6), INDEX(J24:S24, $I$4)) -> 0.33 | G24: % of annual yield | I24: {=IF( INDEX(J24:S24, I$5) = "", IF( INDEX(J24:S24, I$6) = F24, "vw", "tu"), IF(INDEX(J24:S24, I$5) = F24, "vw", "tu"))} -> vw | K24: 0.33 | L24: 0.33 | M24: 0.33
E25: Q2 seasonal adjustment | F25: =IF( INDEX(J25:S25, $I$4) = "", INDEX(J25:R25, $I$6), INDEX(J25:S25, $I$4)) -> 0.36 | G25: % of annual yield | I25: {=IF( INDEX(J25:S25, I$5) = "", IF( INDEX(J25:S25, I$6) = F25, "vw", "tu"), IF(INDEX(J25:S25, I$5) = F25, "vw", "tu"))} -> vw | K25: 0.36 | L25: 0.36 | M25: 0.36
E26: Q3 seasonal adjustment | F26: =IF( INDEX(J26:S26, $I$4) = "", INDEX(J26:R26, $I$6), INDEX(J26:S26, $I$4)) -> 0.155 | G26: % of annual yield | I26: {=IF( INDEX(J26:S26, I$5) = "", IF( INDEX(J26:S26, I$6) = F26, "vw", "tu"), IF(INDEX(J26:S26, I$5) = F26, "vw", "tu"))} -> vw | K26: 0.155 | L26: 0.155 | M26: 0.155
E27: Q4 seasonal adjustment | F27: =IF( INDEX(J27:S27, $I$4) = "", INDEX(J27:R27, $I$6), INDEX(J27:S27, $I$4)) -> 0.155 | G27: % of annual yield | I27: {=IF( INDEX(J27:S27, I$5) = "", IF( INDEX(J27:S27, I$6) = F27, "vw", "tu"), IF(INDEX(J27:S27, I$5) = F27, "vw", "tu"))} -> vw | K27: 0.155 | L27: 0.155 | M27: 0.155
E29: Annual degradation | F29: =IF( INDEX(J29:S29, $I$4) = "", INDEX(J29:R29, $I$6), INDEX(J29:S29, $I$4)) -> 0.005 | G29: % p.a. | I29: {=IF( INDEX(J29:S29, I$5) = "", IF( INDEX(J29:S29, I$6) = F29, "vw", "tu"), IF(INDEX(J29:S29, I$5) = F29, "vw", "tu"))} -> vw | K29: 0.005 | L29: 0.005 | M29: 0.005
E30: Year 1 P50 yield | F30: =IF( INDEX(J30:S30, $I$4) = "", INDEX(J30:R30, $I$6), INDEX(J30:S30, $I$4)) -> 250 | G30: GWh | I30: {=IF( INDEX(J30:S30, I$5) = "", IF( INDEX(J30:S30, I$6) = F30, "vw", "tu"), IF(INDEX(J30:S30, I$5) = F30, "vw", "tu"))} -> vw | K30: 250 | L30: 250 | M30: 250
E31: Availability | F31: =IF( INDEX(J31:S31, $I$4) = "", INDEX(J31:R31, $I$6), INDEX(J31:S31, $I$4)) -> 0.97 | G31: % | I31: {=IF( INDEX(J31:S31, I$5) = "", IF( INDEX(J31:S31, I$6) = F31, "vw", "tu"), IF(INDEX(J31:S31, I$5) = F31, "vw", "tu"))} -> vw | K31: 0.97 | L31: 0.97 | M31: 0.97
E33: Power tariff | F33: =IF( INDEX(J33:S33, $I$4) = "", INDEX(J33:R33, $I$6), INDEX(J33:S33, $I$4)) -> 0.065 | G33: USD / kWh | I33: {=IF( INDEX(J33:S33, I$5) = "", IF( INDEX(J33:S33, I$6) = F33, "vw", "tu"), IF(INDEX(J33:S33, I$5) = F33, "vw", "tu"))} -> vw | K33: 0.065 | L33: 0.065 | M33: 0.065
A35: OPERATING COSTS
E36: Annual fixed real O&M cost | F36: =IF( INDEX(J36:S36, $I$4) = "", INDEX(J36:R36, $I$6), INDEX(J36:S36, $I$4)) -> 1500 | G36: =SMU -> $ 000s | I36: {=IF( INDEX(J36:S36, I$5) = "", IF( INDEX(J36:S36, I$6) = F36, "vw", "tu"), IF(INDEX(J36:S36, I$5) = F36, "vw", "tu"))} -> vw | K36: 1500 | L36: 1500 | M36: 1500
A38: FIXED ASSET
E39: Useful life of asset | F39: =IF( INDEX(J39:S39, $I$4) = "", INDEX(J39:R39, $I$6), INDEX(J39:S39, $I$4)) -> 25 | G39: years | I39: {=IF( INDEX(J39:S39, I$5) = "", IF( INDEX(J39:S39, I$6) = F39, "vw", "tu"), IF(INDEX(J39:S39, I$5) = F39, "vw", "tu"))} -> vw | K39: 25 | L39: 25 | M39: 25
A41: WORKING CAPITAL
E42: Accounts receivable days | F42: =IF( INDEX(J42:S42, $I$4) = "", INDEX(J42:R42, $I$6), INDEX(J42:S42, $I$4)) -> 60 | G42: days | I42: {=IF( INDEX(J42:S42, I$5) = "", IF( INDEX(J42:S42, I$6) = F42, "vw", "tu"), IF(INDEX(J42:S42, I$5) = F42, "vw", "tu"))} -> vw | K42: 60 | L42: 60 | M42: 60
E43: Accounts payable days | F43: =IF( INDEX(J43:S43, $I$4) = "", INDEX(J43:R43, $I$6), INDEX(J43:S43, $I$4)) -> 30 | G43: days | I43: {=IF( INDEX(J43:S43, I$5) = "", IF( INDEX(J43:S43, I$6) = F43, "vw", "tu"), IF(INDEX(J43:S43, I$5) = F43, "vw", "tu"))} -> vw | K43: 30 | L43: 30 | M43: 30
A45: OPENING BALANCES
E46: Retained earnings - initial balance | F46: =IF( INDEX(J46:S46, $I$4) = "", INDEX(J46:R46, $I$6), INDEX(J46:S46, $I$4)) -> 0 | G46: =SMU -> $ 000s | I46: {=IF( INDEX(J46:S46, I$5) = "", IF( INDEX(J46:S46, I$6) = F46, "vw", "tu"), IF(INDEX(J46:S46, I$5) = F46, "vw", "tu"))} -> vw | K46: 0 | L46: 0 | M46: 0
E47: Retained cash - initial balance | F47: =IF( INDEX(J47:S47, $I$4) = "", INDEX(J47:R47, $I$6), INDEX(J47:S47, $I$4)) -> 0 | G47: =SMU -> $ 000s | I47: {=IF( INDEX(J47:S47, I$5) = "", IF( INDEX(J47:S47, I$6) = F47, "vw", "tu"), IF(INDEX(J47:S47, I$5) = F47, "vw", "tu"))} -> vw | K47: 0 | L47: 0 | M47: 0
E48: Accounts receivable - initial balance | F48: =IF( INDEX(J48:S48, $I$4) = "", INDEX(J48:R48, $I$6), INDEX(J48:S48, $I$4)) -> 0 | G48: =SMU -> $ 000s | I48: {=IF( INDEX(J48:S48, I$5) = "", IF( INDEX(J48:S48, I$6) = F48, "vw", "tu"), IF(INDEX(J48:S48, I$5) = F48, "vw", "tu"))} -> vw | K48: 0 | L48: 0 | M48: 0
E49: Accounts payable - initial balance | F49: =IF( INDEX(J49:S49, $I$4) = "", INDEX(J49:R49, $I$6), INDEX(J49:S49, $I$4)) -> 0 | G49: =SMU -> $ 000s | I49: {=IF( INDEX(J49:S49, I$5) = "", IF( INDEX(J49:S49, I$6) = F49, "vw", "tu"), IF(INDEX(J49:S49, I$5) = F49, "vw", "tu"))} -> vw | K49: 0 | L49: 0 | M49: 0
E50: Fixed asset - initial balance | F50: =IF( INDEX(J50:S50, $I$4) = "", INDEX(J50:R50, $I$6), INDEX(J50:S50, $I$4)) -> 100000 | G50: =SMU -> $ 000s | I50: {=IF( INDEX(J50:S50, I$5) = "", IF( INDEX(J50:S50, I$6) = F50, "vw", "tu"), IF(INDEX(J50:S50, I$5) = F50, "vw", "tu"))} -> vw | K50: 100000 | L50: 100000 | M50: 100000
E51: Share capital - initial balance | F51: =IF( INDEX(J51:S51, $I$4) = "", INDEX(J51:R51, $I$6), INDEX(J51:S51, $I$4)) -> 100000 | G51: =SMU -> $ 000s | I51: {=IF( INDEX(J51:S51, I$5) = "", IF( INDEX(J51:S51, I$6) = F51, "vw", "tu"), IF(INDEX(J51:S51, I$5) = F51, "vw", "tu"))} -> vw | K51: 100000 | L51: 100000 | M51: 100000
A55: MODEL TECHNICAL INPUTS - DO NOT CHANGE
E57: Model track tolerance level | F57: 0.001 | G57: tolerance
E58: Model check tolerance level | F58: 0.001 | G58: tolerance
E59: Months in year | F59: 12 | G59: months
E60: Number of periods in a year | F60: 4 | G60: periods
E61: Standard Monetary Unit | F61: $ 000s | G61: named "SMU"
E62: US$c / US$ | F62: 100 | G62: US$c / US$
E63: GWh to kWh conversion | F63: 1000000 | G63: kWh / GWh
E64: Units in a thousand | F64: 1000 | G64: units
E65: Small negative value for XIRR | F65: -1e-07 | G65: $ 000s
B67: Timeline label
E68: Pre-forecast period | F68: Pre-fcst | G68: label
E69: Financial Close | F69: Fin Close | G69: label
E70: Operations | F70: Operations | G70: label
E71: Post ops | F71: Post ops | G71: label
E73: Input row template for relocation macro | F73: =IF( INDEX(J73:S73, $I$4) = "", INDEX(J73:R73, $I$6), INDEX(J73:S73, $I$4)) -> 0 | G73: unit | I73: {=IF( INDEX(J73:S73, I$5) = "", IF( INDEX(J73:S73, I$6) = F73, "vw", "tu"), IF(INDEX(J73:S73, I$5) = F73, "vw", "tu"))} -> vw
A76: END

Sheet Time
A1: =RIGHT(CELL("filename", A1), LEN(CELL("filename", A1)) - SEARCH("]", CELL("filename", A1))) & " - " & InpC!F3 -> Time - Base case 1
E2: =Time!E$25 -> Model period ending | F2: =Check!$F$9 -> 0 | G2: Error chks | J2: =Time!J$25 -> 44104 | K2: =Time!K$25 -> 44196 | L2: =Time!L$25 -> 44286 | M2: =Time!M$25 -> 44377 | N2: =Time!N$25 -> 44469 | O2: =Time!O$25 -> 44561 | P2: =Time!P$25 -> 44651 | Q2: =Time!Q$25 -> 44742 | ... EA2: =Time!EA$25 -> 55153
E3: =Time!E$67 -> Timeline label | F3: =Output!J2 -> 0 | G3: Track chgs | J3: =Time!J$67 -> Pre-fcst | K3: =Time!K$67 -> Pre-fcst | L3: =Time!L$67 -> Fin Close | M3: =Time!M$67 -> Operations | N3: =Time!N$67 -> Operations | O3: =Time!O$67 -> Operations | P3: =Time!P$67 -> Operations | Q3: =Time!Q$67 -> Operations | ... EA3: =Time!EA$67 -> Post ops
E4: =Time!E$42 -> Contract year | F4: =Check!$F$21 -> 0 | G4: Alerts | J4: =Time!J$42 -> 2020 | K4: =Time!K$42 -> 2020 | L4: =Time!L$42 -> 2020 | M4: =Time!M$42 -> 2021 | N4: =Time!N$42 -> 2021 | O4: =Time!O$42 -> 2021 | P4: =Time!P$42 -> 2021 | Q4: =Time!Q$42 -> 2022 | ... EA4: =Time!EA$42 -> 2050
E5: =Time!E$10 -> Model column counter | F5: Constant | G5: Unit | H5: Total | J5: =Time!J$10 -> 1 | K5: =Time!K$10 -> 2 | L5: =Time!L$10 -> 3 | M5: =Time!M$10 -> 4 | N5: =Time!N$10 -> 5 | O5: =Time!O$10 -> 6 | P5: =Time!P$10 -> 7 | Q5: =Time!Q$10 -> 8 | ... EA5: =Time!EA$10 -> 122
A7: TIME RULER
B9: First model column
E10: Model column counter | G10: counter | J10: =I10 + 1 -> 1 | K10: =J10 + 1 -> 2 | L10: =K10 + 1 -> 3 | M10: =L10 + 1 -> 4 | N10: =M10 + 1 -> 5 | O10: =N10 + 1 -> 6 | P10: =O10 + 1 -> 7 | Q10: =P10 + 1 -> 8 | ... EA10: =DZ10 + 1 -> 122
E11: Model column total | F11: =MAX(J10:EA10) -> 122 | G11: columns
E13: =E$10 -> Model column counter | F13: =F$10 -> 0 | G13: =G$10 -> counter | H13: =H$10 -> 0 | I13: =I$10 -> 0 | J13: =J$10 -> 1 | K13: =K$10 -> 2 | L13: =L$10 -> 3 | ... EA13: =EA$10 -> 122
E14: First model column flag | G14: flag | H14: =SUM(J14:EA14) -> 1 | J14: =IF(J13 = 1, 1, 0) -> 1 | K14: =IF(K13 = 1, 1, 0) -> 0 | L14: =IF(L13 = 1, 1, 0) -> 0 | M14: =IF(M13 = 1, 1, 0) -> 0 | N14: =IF(N13 = 1, 1, 0) -> 0 | O14: =IF(O13 = 1, 1, 0) -> 0 | P14: =IF(P13 = 1, 1, 0) -> 0 | Q14: =IF(Q13 = 1, 1, 0) -> 0 | ... EA14: =IF(EA13 = 1, 1, 0) -> 0
B16: Model period beginning
E17: =InpC!E$13 -> First date of time rulers | F17: =InpC!F$13 -> 44013 | G17: =InpC!G$13 -> date
E18: =InpC!E$16 -> Length of operating period | F18: =InpC!F$16 -> 3 | G18: =InpC!G$16 -> months
E19: =E$14 -> First model column flag | F19: =F$14 -> 0 | G19: =G$14 -> flag | H19: =H$14 -> 1 | I19: =I$14 -> 0 | J19: =J$14 -> 1 | K19: =K$14 -> 0 | L19: =L$14 -> 0 | ... EA19: =EA$14 -> 0
E20: Model period beginning | G20: date | J20: =IF(J19 = 1, $F17, DATE(YEAR(I20), MONTH(I20) + $F18, DAY(1))) -> 44013 | K20: =IF(K19 = 1, $F17, DATE(YEAR(J20), MONTH(J20) + $F18, DAY(1))) -> 44105 | L20: =IF(L19 = 1, $F17, DATE(YEAR(K20), MONTH(K20) + $F18, DAY(1))) -> 44197 | M20: =IF(M19 = 1, $F17, DATE(YEAR(L20), MONTH(L20) + $F18, DAY(1))) -> 44287 | N20: =IF(N19 = 1, $F17, DATE(YEAR(M20), MONTH(M20) + $F18, DAY(1))) -> 44378 | O20: =IF(O19 = 1, $F17, DATE(YEAR(N20), MONTH(N20) + $F18, DAY(1))) -> 44470 | P20: =IF(P19 = 1, $F17, DATE(YEAR(O20), MONTH(O20) + $F18, DAY(1))) -> 44562 | Q20: =IF(Q19 = 1, $F17, DATE(YEAR(P20), MONTH(P20) + $F18, DAY(1))) -> 44652 | ... EA20: =IF(EA19 = 1, $F17, DATE(YEAR(DZ20), MONTH(DZ20) + $F18, DAY(1))) -> 55062
B22: Model period ending
E23: =InpC!E$16 -> Length of operating period | F23: =InpC!F$16 -> 3 | G23: =InpC!G$16 -> months
E24: =E$20 -> Model period beginning | F24: =F$20 -> 0 | G24: =G$20 -> date | H24: =H$20 -> 0 | I24: =I$20 -> 0 | J24: =J$20 -> 44013 | K24: =K$20 -> 44105 | L24: =L$20 -> 44197 | ... EA24: =EA$20 -> 55062
E25: Model period ending | G25: date | J25: =DATE(YEAR(J24), MONTH(J24) + $F23, DAY(J24) -1) -> 44104 | K25: =DATE(YEAR(K24), MONTH(K24) + $F23, DAY(K24) -1) -> 44196 | L25: =DATE(YEAR(L24), MONTH(L24) + $F23, DAY(L24) -1) -> 44286 | M25: =DATE(YEAR(M24), MONTH(M24) + $F23, DAY(M24) -1) -> 44377 | N25: =DATE(YEAR(N24), MONTH(N24) + $F23, DAY(N24) -1) -> 44469 | O25: =DATE(YEAR(O24), MONTH(O24) + $F23, DAY(O24) -1) -> 44561 | P25: =DATE(YEAR(P24), MONTH(P24) + $F23, DAY(P24) -1) -> 44651 | Q25: =DATE(YEAR(Q24), MONTH(Q24) + $F23, DAY(Q24) -1) -> 44742 | ... EA25: =DATE(YEAR(EA24), MONTH(EA24) + $F23, DAY(EA24) -1) -> 55153
B27: Contract year
E28: =InpC!E$18 -> Acquisition date | F28: =InpC!F$18 -> 44286 | G28: =InpC!G$18 -> date
E29: Contract year end month | F29: =MONTH(F28) -> 3 | G29: month
E31: =E$29 -> Contract year end month | F31: =F$29 -> 3 | G31: =G$29 -> month
E32: =E$25 -> Model period ending | F32: =F$25 -> 0 | G32: =G$25 -> date | H32: =H$25 -> 0 | I32: =I$25 -> 0 | J32: =J$25 -> 44104 | K32: =K$25 -> 44196 | L32: =L$25 -> 44286 | ... EA32: =EA$25 -> 55153
E33: End of contract year flag | J33: =IF( MONTH(J32) = $F31, 1, 0) -> 0 | K33: =IF( MONTH(K32) = $F31, 1, 0) -> 0 | L33: =IF( MONTH(L32) = $F31, 1, 0) -> 1 | M33: =IF( MONTH(M32) = $F31, 1, 0) -> 0 | N33: =IF( MONTH(N32) = $F31, 1, 0) -> 0 | O33: =IF( MONTH(O32) = $F31, 1, 0) -> 0 | P33: =IF( MONTH(P32) = $F31, 1, 0) -> 1 | Q33: =IF( MONTH(Q32) = $F31, 1, 0) -> 0 | ... EA33: =IF( MONTH(EA32) = $F31, 1, 0) -> 0
E35: =InpC!E$14 -> Annual year end date of first operating period | F35: =InpC!F$14 -> 43921 | G35: =InpC!G$14 -> date
E36: =InpC!E$59 -> Months in year | F36: =InpC!F$59 -> 12 | G36: =InpC!G$59 -> months
E37: =E$14 -> First model column flag | F37: =F$14 -> 0 | G37: =G$14 -> flag | H37: =H$14 -> 1 | I37: =I$14 -> 0 | J37: =J$14 -> 1 | K37: =K$14 -> 0 | L37: =L$14 -> 0 | ... EA37: =EA$14 -> 0
E38: =E$33 -> End of contract year flag | F38: =F$33 -> 0 | G38: =G$33 -> 0 | H38: =H$33 -> 0 | I38: =I$33 -> 0 | J38: =J$33 -> 0 | K38: =K$33 -> 0 | L38: =L$33 -> 1 | ... EA38: =EA$33 -> 0
E39: Contract year applicable to period | G39: date | J39: =IF( J37 = 1, $F35, IF( I38 = 1, EOMONTH(I39, 12), I39)) -> 43921 | K39: =IF( K37 = 1, $F35, IF( J38 = 1, EOMONTH(J39, 12), J39)) -> 43921 | L39: =IF( L37 = 1, $F35, IF( K38 = 1, EOMONTH(K39, 12), K39)) -> 43921 | M39: =IF( M37 = 1, $F35, IF( L38 = 1, EOMONTH(L39, 12), L39)) -> 44286 | N39: =IF( N37 = 1, $F35, IF( M38 = 1, EOMONTH(M39, 12), M39)) -> 44286 | O39: =IF( O37 = 1, $F35, IF( N38 = 1, EOMONTH(N39, 12), N39)) -> 44286 | P39: =IF( P37 = 1, $F35, IF( O38 = 1, EOMONTH(O39, 12), O39)) -> 44286 | Q39: =IF( Q37 = 1, $F35, IF( P38 = 1, EOMONTH(P39, 12), P39)) -> 44651 | ... EA39: =IF( EA37 = 1, $F35, IF( DZ38 = 1, EOMONTH(DZ39, 12), DZ39)) -> 54878
E41: =E$39 -> Contract year applicable to period | F41: =F$39 -> 0 | G41: =G$39 -> date | H41: =H$39 -> 0 | I41: =I$39 -> 0 | J41: =J$39 -> 43921 | K41: =K$39 -> 43921 | L41: =L$39 -> 43921 | ... EA41: =EA$39 -> 54878
E42: Contract year | G42: year # | J42: =YEAR(J41) -> 2020 | K42: =YEAR(K41) -> 2020 | L42: =YEAR(L41) -> 2020 | M42: =YEAR(M41) -> 2021 | N42: =YEAR(N41) -> 2021 | O42: =YEAR(O41) -> 2021 | P42: =YEAR(P41) -> 2021 | Q42: =YEAR(Q41) -> 2022 | ... EA42: =YEAR(EA41) -> 2050
B44: Annual timeline
E45: =InpC!E$14 -> Annual year end date of first operating period | F45: =InpC!F$14 -> 43921 | G45: =InpC!G$14 -> date
E46: =InpC!E$59 -> Months in year | F46: =InpC!F$59 -> 12 | G46: =InpC!G$59 -> months
E47: =E$14 -> First model column flag | F47: =F$14 -> 0 | G47: =G$14 -> flag | H47: =H$14 -> 1 | I47: =I$14 -> 0 | J47: =J$14 -> 1 | K47: =K$14 -> 0 | L47: =L$14 -> 0 | ... EA47: =EA$14 -> 0
E48: Model period ending - annual | G48: date | J48: =IF(J47 = 1, $F45, EOMONTH(I48, $F46)) -> 43921 | K48: =IF(K47 = 1, $F45, EOMONTH(J48, $F46)) -> 44286 | L48: =IF(L47 = 1, $F45, EOMONTH(K48, $F46)) -> 44651 | M48: =IF(M47 = 1, $F45, EOMONTH(L48, $F46)) -> 45016 | N48: =IF(N47 = 1, $F45, EOMONTH(M48, $F46)) -> 45382 | O48: =IF(O47 = 1, $F45, EOMONTH(N48, $F46)) -> 45747 | P48: =IF(P47 = 1, $F45, EOMONTH(O48, $F46)) -> 46112 | Q48: =IF(Q47 = 1, $F45, EOMONTH(P48, $F46)) -> 46477 | ... EA48: =IF(EA47 = 1, $F45, EOMONTH(DZ48, $F46)) -> 88115
E50: =E$67 -> Timeline label | F50: =F$67 -> 0 | G50: =G$67 -> label | H50: =H$67 -> 0 | I50: =I$67 -> 0 | J50: =J$67 -> Pre-fcst | K50: =K$67 -> Pre-fcst | L50: =L$67 -> Fin Close | ... EA50: =EA$67 -> Post ops
E51: =E$48 -> Model period ending - annual | F51: =F$48 -> 0 | G51: =G$48 -> date | H51: =H$48 -> 0 | I51: =I$48 -> 0 | J51: =J$48 -> 43921 | K51: =K$48 -> 44286 | L51: =L$48 -> 44651 | ... EA51: =EA$48 -> 88115
E52: =E$41 -> Contract year applicable to period | F52: =F$41 -> 0 | G52: =G$41 -> date | H52: =H$41 -> 0 | I52: =I$41 -> 0 | J52: =J$41 -> 43921 | K52: =K$41 -> 43921 | L52: =L$41 -> 43921 | ... EA52: =EA$41 -> 54878
E53: Timeline label - annual | J53: =IF(ISNA(INDEX($J$50:$EA$50,MATCH(J51,$J$52:$EA$52,0))),"Pre-fcst",INDEX($J$50:$EA$50,MATCH(J51,$J$52:$EA$52,0))) -> Pre-fcst | K53: =IF(ISNA(INDEX($J$50:$EA$50,MATCH(K51,$J$52:$EA$52,0))),"Pre-fcst",INDEX($J$50:$EA$50,MATCH(K51,$J$52:$EA$52,0))) -> Operations | L53: =IF(ISNA(INDEX($J$50:$EA$50,MATCH(L51,$J$52:$EA$52,0))),"Pre-fcst",INDEX($J$50:$EA$50,MATCH(L51,$J$52:$EA$52,0))) -> Operations | M53: =IF(ISNA(INDEX($J$50:$EA$50,MATCH(M51,$J$52:$EA$52,0))),"Pre-fcst",INDEX($J$50:$EA$50,MATCH(M51,$J$52:$EA$52,0))) -> Operations | N53: =IF(ISNA(INDEX($J$50:$EA$50,MATCH(N51,$J$52:$EA$52,0))),"Pre-fcst",INDEX($J$50:$EA$50,MATCH(N51,$J$52:$EA$52,0))) -> Operations | O53: =IF(ISNA(INDEX($J$50:$EA$50,MATCH(O51,$J$52:$EA$52,0))),"Pre-fcst",INDEX($J$50:$EA$50,MATCH(O51,$J$52:$EA$52,0))) -> Operations | P53: =IF(ISNA(INDEX($J$50:$EA$50,MATCH(P51,$J$52:$EA$52,0))),"Pre-fcst",INDEX($J$50:$EA$50,MATCH(P51,$J$52:$EA$52,0))) -> Operations | Q53: =IF(ISNA(INDEX($J$50:$EA$50,MATCH(Q51,$J$52:$EA$52,0))),"Pre-fcst",INDEX($J$50:$EA$50,MATCH(Q51,$J$52:$EA$52,0))) -> Operations | ... BC53: =IF(ISNA(INDEX($J$50:$EA$50,MATCH(BC51,$J$52:$EA$52,0))),"Pre-fcst",INDEX($J$50:$EA$50,MATCH(BC51,$J$52:$EA$52,0))) -> Pre-fcst
B55: Quarterly timeline
E56: =E$14 -> First model column flag | F56: =F$14 -> 0 | G56: =G$14 -> flag | H56: =H$14 -> 1 | I56: =I$14 -> 0 | J56: =J$14 -> 1 | K56: =K$14 -> 0 | L56: =L$14 -> 0 | ... EA56: =EA$14 -> 0
E57: =E$76 -> Financial close date flag | F57: =F$76 -> 0 | G57: =G$76 -> flag | H57: =H$76 -> 1 | I57: =I$76 -> 0 | J57: =J$76 -> 0 | K57: =K$76 -> 0 | L57: =L$76 -> 1 | ... EA57: =EA$76 -> 0
E58: =E$80 -> First operating period flag | F58: =F$80 -> 0 | G58: =G$80 -> flag | H58: =H$80 -> 1 | I58: =I$80 -> 0 | J58: =J$80 -> 0 | K58: =K$80 -> 0 | L58: =L$80 -> 0 | ... EA58: =EA$80 -> 0
E59: =E$113 -> First post operating period flag | F59: =F$113 -> 0 | G59: =G$113 -> 0 | H59: =H$113 -> 0 | I59: =I$113 -> 0 | J59: =J$113 -> 0 | K59: =K$113 -> 0 | L59: =L$113 -> 0 | ... EA59: =EA$113 -> 0
E60: Timeline label counter | G60: counter | J60: =I60 + MAX(J56:J59) -> 1 | K60: =J60 + MAX(K56:K59) -> 1 | L60: =K60 + MAX(L56:L59) -> 2 | M60: =L60 + MAX(M56:M59) -> 3 | N60: =M60 + MAX(N56:N59) -> 3 | O60: =N60 + MAX(O56:O59) -> 3 | P60: =O60 + MAX(P56:P59) -> 3 | Q60: =P60 + MAX(Q56:Q59) -> 3 | ... EA60: =DZ60 + MAX(EA56:EA59) -> 4
E62: =InpC!E$68 -> Pre-forecast period | F62: =InpC!F$68 -> Pre-fcst | G62: =InpC!G$68 -> label
E63: =InpC!E$69 -> Financial Close | F63: =InpC!F$69 -> Fin Close | G63: =InpC!G$69 -> label
E64: =InpC!E$70 -> Operations | F64: =InpC!F$70 -> Operations | G64: =InpC!G$70 -> label
E65: =InpC!E$71 -> Post ops | F65: =InpC!F$71 -> Post ops | G65: =InpC!G$71 -> label
E66: =E$60 -> Timeline label counter | F66: =F$60 -> 0 | G66: =G$60 -> counter | H66: =H$60 -> 0 | I66: =I$60 -> 0 | J66: =J$60 -> 1 | K66: =K$60 -> 1 | L66: =L$60 -> 2 | ... EA66: =EA$60 -> 4
E67: Timeline label | G67: label | J67: =INDEX($F62:$F65, J66) -> Pre-fcst | K67: =INDEX($F62:$F65, K66) -> Pre-fcst | L67: =INDEX($F62:$F65, L66) -> Fin Close | M67: =INDEX($F62:$F65, M66) -> Operations | N67: =INDEX($F62:$F65, N66) -> Operations | O67: =INDEX($F62:$F65, O66) -> Operations | P67: =INDEX($F62:$F65, P66) -> Operations | Q67: =INDEX($F62:$F65, Q66) -> Operations | ... EA67: =INDEX($F62:$F65, EA66) -> Post ops
A71: FLAGS
B73: Financial close date flag
E74: =InpC!E$18 -> Acquisition date | F74: =InpC!F$18 -> 44286 | G74: =InpC!G$18 -> date
E75: =E$25 -> Model period ending | F75: =F$25 -> 0 | G75: =G$25 -> date | H75: =H$25 -> 0 | I75: =I$25 -> 0 | J75: =J$25 -> 44104 | K75: =K$25 -> 44196 | L75: =L$25 -> 44286 | ... EA75: =EA$25 -> 55153
E76: Financial close date flag | G76: flag | H76: =SUM(J76:EA76) -> 1 | J76: =IF(AND(I75 < $F74, J75 >= $F74), 1, 0) -> 0 | K76: =IF(AND(J75 < $F74, K75 >= $F74), 1, 0) -> 0 | L76: =IF(AND(K75 < $F74, L75 >= $F74), 1, 0) -> 1 | M76: =IF(AND(L75 < $F74, M75 >= $F74), 1, 0) -> 0 | N76: =IF(AND(M75 < $F74, N75 >= $F74), 1, 0) -> 0 | O76: =IF(AND(N75 < $F74, O75 >= $F74), 1, 0) -> 0 | P76: =IF(AND(O75 < $F74, P75 >= $F74), 1, 0) -> 0 | Q76: =IF(AND(P75 < $F74, Q75 >= $F74), 1, 0) -> 0 | ... EA76: =IF(AND(DZ75 < $F74, EA75 >= $F74), 1, 0) -> 0
B78: First operating period flag
E79: =E$76 -> Financial close date flag | F79: =F$76 -> 0 | G79: =G$76 -> flag | H79: =H$76 -> 1 | I79: =I$76 -> 0 | J79: =J$76 -> 0 | K79: =K$76 -> 0 | L79: =L$76 -> 1 | ... EA79: =EA$76 -> 0
E80: First operating period flag | G80: flag | H80: =SUM(J80:EA80) -> 1 | J80: =I79 -> 0 | K80: =J79 -> 0 | L80: =K79 -> 0 | M80: =L79 -> 1 | N80: =M79 -> 0 | O80: =N79 -> 0 | P80: =O79 -> 0 | Q80: =P79 -> 0 | ... EA80: =DZ79 -> 0
B82: Last operating period flag
E83: =InpC!E$18 -> Acquisition date | F83: =InpC!F$18 -> 44286 | G83: =InpC!G$18 -> date
E84: =InpC!E$20 -> Operating years remaining | F84: =InpC!F$20 -> 25 | G84: =InpC!G$20 -> years
E85: =InpC!E$21 -> Contract extension | F85: =InpC!F$21 -> 0 | G85: =InpC!G$21 -> years
E86: =InpC!E$59 -> Months in year | F86: =InpC!F$59 -> 12 | G86: =InpC!G$59 -> months
E87: End of operating period | F87: =EOMONTH(F83, ((F84 + F85) * F86)) -> 53417 | G87: date
E89: =E$87 -> End of operating period | F89: =F$87 -> 53417 | G89: =G$87 -> date
E90: =E$25 -> Model period ending | F90: =F$25 -> 0 | G90: =G$25 -> date | H90: =H$25 -> 0 | I90: =I$25 -> 0 | J90: =J$25 -> 44104 | K90: =K$25 -> 44196 | L90: =L$25 -> 44286 | ... EA90: =EA$25 -> 55153
E91: Last operating period flag | G91: flag | H91: =SUM(J91:EA91) -> 1 | J91: =IF(J90 = $F89, 1, 0) -> 0 | K91: =IF(K90 = $F89, 1, 0) -> 0 | L91: =IF(L90 = $F89, 1, 0) -> 0 | M91: =IF(M90 = $F89, 1, 0) -> 0 | N91: =IF(N90 = $F89, 1, 0) -> 0 | O91: =IF(O90 = $F89, 1, 0) -> 0 | P91: =IF(P90 = $F89, 1, 0) -> 0 | Q91: =IF(Q90 = $F89, 1, 0) -> 0 | ... EA91: =IF(EA90 = $F89, 1, 0) -> 0
B93: Operating period flag
E94: =InpC!E$18 -> Acquisition date | F94: =InpC!F$18 -> 44286 | G94: =InpC!G$18 -> date
E95: =E$87 -> End of operating period | F95: =F$87 -> 53417 | G95: =G$87 -> date
E96: =E$25 -> Model period ending | F96: =F$25 -> 0 | G96: =G$25 -> date | H96: =H$25 -> 0 | I96: =I$25 -> 0 | J96: =J$25 -> 44104 | K96: =K$25 -> 44196 | L96: =L$25 -> 44286 | ... EA96: =EA$25 -> 55153
E97: Operating period flag | G97: flag | H97: =SUM(J97:EA97) -> 100 | J97: =IF( AND(J96 > $F94, J96 <= $F95), 1, 0) -> 0 | K97: =IF( AND(K96 > $F94, K96 <= $F95), 1, 0) -> 0 | L97: =IF( AND(L96 > $F94, L96 <= $F95), 1, 0) -> 0 | M97: =IF( AND(M96 > $F94, M96 <= $F95), 1, 0) -> 1 | N97: =IF( AND(N96 > $F94, N96 <= $F95), 1, 0) -> 1 | O97: =IF( AND(O96 > $F94, O96 <= $F95), 1, 0) -> 1 | P97: =IF( AND(P96 > $F94, P96 <= $F95), 1, 0) -> 1 | Q97: =IF( AND(Q96 > $F94, Q96 <= $F95), 1, 0) -> 1 | ... EA97: =IF( AND(EA96 > $F94, EA96 <= $F95), 1, 0) -> 0
B99: Useful life of asset flag
E100: =InpC!E$18 -> Acquisition date | F100: =InpC!F$18 -> 44286 | G100: =InpC!G$18 -> date
E101: =InpC!E$39 -> Useful life of asset | F101: =InpC!F$39 -> 25 | G101: =InpC!G$39 -> years
E102: =InpC!E$21 -> Contract extension | F102: =InpC!F$21 -> 0 | G102: =InpC!G$21 -> years
E103: =InpC!E$59 -> Months in year | F103: =InpC!F$59 -> 12 | G103: =InpC!G$59 -> months
E104: End of useful life of asset | F104: =EOMONTH(F100, ((F101 + F102) * F103)) -> 53417 | G104: date
E106: =InpC!E$18 -> Acquisition date | F106: =InpC!F$18 -> 44286 | G106: =InpC!G$18 -> date
E107: =E$104 -> End of useful life of asset | F107: =F$104 -> 53417 | G107: =G$104 -> date | H107: =H$104 -> 0 | I107: =I$104 -> 0 | J107: =J$104 -> 0 | K107: =K$104 -> 0 | L107: =L$104 -> 0 | ... EA107: =EA$104 -> 0
E108: =E$25 -> Model period ending | F108: =F$25 -> 0 | G108: =G$25 -> date | H108: =H$25 -> 0 | I108: =I$25 -> 0 | J108: =J$25 -> 44104 | K108: =K$25 -> 44196 | L108: =L$25 -> 44286 | ... EA108: =EA$25 -> 55153
E109: Useful life of asset flag | G109: flag | H109: =SUM(J109:EA109) -> 100 | J109: =IF( AND(J108 > $F106, J108 <= $F107), 1, 0) -> 0 | K109: =IF( AND(K108 > $F106, K108 <= $F107), 1, 0) -> 0 | L109: =IF( AND(L108 > $F106, L108 <= $F107), 1, 0) -> 0 | M109: =IF( AND(M108 > $F106, M108 <= $F107), 1, 0) -> 1 | N109: =IF( AND(N108 > $F106, N108 <= $F107), 1, 0) -> 1 | O109: =IF( AND(O108 > $F106, O108 <= $F107), 1, 0) -> 1 | P109: =IF( AND(P108 > $F106, P108 <= $F107), 1, 0) -> 1 | Q109: =IF( AND(Q108 > $F106, Q108 <= $F107), 1, 0) -> 1 | ... EA109: =IF( AND(EA108 > $F106, EA108 <= $F107), 1, 0) -> 0
B111: First post operating period flag
E112: =E$91 -> Last operating period flag | F112: =F$91 -> 0 | G112: =G$91 -> flag | H112: =H$91 -> 1 | I112: =I$91 -> 0 | J112: =J$91 -> 0 | K112: =K$91 -> 0 | L112: =L$91 -> 0 | ... EA112: =EA$91 -> 0
E113: First post operating period flag | J113: =I112 -> 0 | K113: =J112 -> 0 | L113: =K112 -> 0 | M113: =L112 -> 0 | N113: =M112 -> 0 | O113: =N112 -> 0 | P113: =O112 -> 0 | Q113: =P112 -> 0 | ... EA113: =DZ112 -> 0
A117: COUNTERS / PERIOD NUMBERS
B119: Period number
E120: =E$97 -> Operating period flag | F120: =F$97 -> 0 | G120: =G$97 -> flag | H120: =H$97 -> 100 | I120: =I$97 -> 0 | J120: =J$97 -> 0 | K120: =K$97 -> 0 | L120: =L$97 -> 0 | ... EA120: =EA$97 -> 0
E121: Contract period number | J121: =I121 + J120 -> 0 | K121: =J121 + K120 -> 0 | L121: =K121 + L120 -> 0 | M121: =L121 + M120 -> 1 | N121: =M121 + N120 -> 2 | O121: =N121 + O120 -> 3 | P121: =O121 + P120 -> 4 | Q121: =P121 + Q120 -> 5 | ... EA121: =DZ121 + EA120 -> 100
E123: =InpC!E$60 -> Number of periods in a year | F123: =InpC!F$60 -> 4 | G123: =InpC!G$60 -> periods
E124: =E$121 -> Contract period number | F124: =F$121 -> 0 | G124: =G$121 -> 0 | H124: =H$121 -> 0 | I124: =I$121 -> 0 | J124: =J$121 -> 0 | K124: =K$121 -> 0 | L124: =L$121 -> 0 | ... EA124: =EA$121 -> 100
E125: =E$97 -> Operating period flag | F125: =F$97 -> 0 | G125: =G$97 -> flag | H125: =H$97 -> 100 | I125: =I$97 -> 0 | J125: =J$97 -> 0 | K125: =K$97 -> 0 | L125: =L$97 -> 0 | ... EA125: =EA$97 -> 0
E126: Period number | G126: counter | J126: =IF( I126 = $F123, 1, I126 + 1) * J125 -> 0 | K126: =IF( J126 = $F123, 1, J126 + 1) * K125 -> 0 | L126: =IF( K126 = $F123, 1, K126 + 1) * L125 -> 0 | M126: =IF( L126 = $F123, 1, L126 + 1) * M125 -> 1 | N126: =IF( M126 = $F123, 1, M126 + 1) * N125 -> 2 | O126: =IF( N126 = $F123, 1, N126 + 1) * O125 -> 3 | P126: =IF( O126 = $F123, 1, O126 + 1) * P125 -> 4 | Q126: =IF( P126 = $F123, 1, P126 + 1) * Q125 -> 1 | ... EA126: =IF( DZ126 = $F123, 1, DZ126 + 1) * EA125 -> 0
B128: Contract year number
E129: =InpC!E$60 -> Number of periods in a year | F129: =InpC!F$60 -> 4 | G129: =InpC!G$60 -> periods
E130: =E$33 -> End of contract year flag | F130: =F$33 -> 0 | G130: =G$33 -> 0 | H130: =H$33 -> 0 | I130: =I$33 -> 0 | J130: =J$33 -> 0 | K130: =K$33 -> 0 | L130: =L$33 -> 1 | ... EA130: =EA$33 -> 0
...

Sheet Ops
A1: =RIGHT(CELL("filename", A1), LEN(CELL("filename", A1)) - SEARCH("]", CELL("filename", A1))) & " - " & InpC!F3 -> Ops - Base case 1
E2: =Time!E$25 -> Model period ending | F2: =Check!$F$9 -> 0 | G2: Error chks | J2: =Time!J$25 -> 44104 | K2: =Time!K$25 -> 44196 | L2: =Time!L$25 -> 44286 | M2: =Time!M$25 -> 44377 | N2: =Time!N$25 -> 44469 | O2: =Time!O$25 -> 44561 | P2: =Time!P$25 -> 44651 | Q2: =Time!Q$25 -> 44742 | ... EA2: =Time!EA$25 -> 55153
E3: =Time!E$67 -> Timeline label | F3: =Output!J2 -> 0 | G3: Track chgs | J3: =Time!J$67 -> Pre-fcst | K3: =Time!K$67 -> Pre-fcst | L3: =Time!L$67 -> Fin Close | M3: =Time!M$67 -> Operations | N3: =Time!N$67 -> Operations | O3: =Time!O$67 -> Operations | P3: =Time!P$67 -> Operations | Q3: =Time!Q$67 -> Operations | ... EA3: =Time!EA$67 -> Post ops
E4: =Time!E$42 -> Contract year | F4: =Check!$F$21 -> 0 | G4: Alerts | J4: =Time!J$42 -> 2020 | K4: =Time!K$42 -> 2020 | L4: =Time!L$42 -> 2020 | M4: =Time!M$42 -> 2021 | N4: =Time!N$42 -> 2021 | O4: =Time!O$42 -> 2021 | P4: =Time!P$42 -> 2021 | Q4: =Time!Q$42 -> 2022 | ... EA4: =Time!EA$42 -> 2050
E5: =Time!E$10 -> Model column counter | F5: Constant | G5: Unit | H5: Total | J5: =Time!J$10 -> 1 | K5: =Time!K$10 -> 2 | L5: =Time!L$10 -> 3 | M5: =Time!M$10 -> 4 | N5: =Time!N$10 -> 5 | O5: =Time!O$10 -> 6 | P5: =Time!P$10 -> 7 | Q5: =Time!Q$10 -> 8 | ... EA5: =Time!EA$10 -> 122
A8: REVENUE
B10: Degradation
E11: =InpC!E$29 -> Annual degradation | F11: =InpC!F$29 -> 0.005 | G11: =InpC!G$29 -> % p.a.
E12: =Time!E$132 -> Contract year number | F12: =Time!F$132 -> 0 | G12: =Time!G$132 -> counter | H12: =Time!H$132 -> 0 | I12: =Time!I$132 -> 0 | J12: =Time!J$132 -> 0 | K12: =Time!K$132 -> 0 | L12: =Time!L$132 -> 0 | ... EA12: =Time!EA$132 -> 0
E13: =Time!E$97 -> Operating period flag | F13: =Time!F$97 -> 0 | G13: =Time!G$97 -> flag | H13: =Time!H$97 -> 100 | I13: =Time!I$97 -> 0 | J13: =Time!J$97 -> 0 | K13: =Time!K$97 -> 0 | L13: =Time!L$97 -> 0 | ... EA13: =Time!EA$97 -> 0
E14: Compound degradation | G14: % | J14: =IF( J13 = 1, 1 / ((1 + $F11) ^ (J12 - 1)), 0) -> 0 | K14: =IF( K13 = 1, 1 / ((1 + $F11) ^ (K12 - 1)), 0) -> 0 | L14: =IF( L13 = 1, 1 / ((1 + $F11) ^ (L12 - 1)), 0) -> 0 | M14: =IF( M13 = 1, 1 / ((1 + $F11) ^ (M12 - 1)), 0) -> 1 | N14: =IF( N13 = 1, 1 / ((1 + $F11) ^ (N12 - 1)), 0) -> 1 | O14: =IF( O13 = 1, 1 / ((1 + $F11) ^ (O12 - 1)), 0) -> 1 | P14: =IF( P13 = 1, 1 / ((1 + $F11) ^ (P12 - 1)), 0) -> 1 | Q14: =IF( Q13 = 1, 1 / ((1 + $F11) ^ (Q12 - 1)), 0) -> 0.99502488 | ... EA14: =IF( EA13 = 1, 1 / ((1 + $F11) ^ (EA12 - 1)), 0) -> 0
B16: Seasonality adjustment
E17: =InpC!E$24 -> Q1 seasonal adjustment | F17: =InpC!F$24 -> 0.33 | G17: =InpC!G$24 -> % of annual yield
E18: =InpC!E$25 -> Q2 seasonal adjustment | F18: =InpC!F$25 -> 0.36 | G18: =InpC!G$25 -> % of annual yield
E19: =InpC!E$26 -> Q3 seasonal adjustment | F19: =InpC!F$26 -> 0.155 | G19: =InpC!G$26 -> % of annual yield
E20: =InpC!E$27 -> Q4 seasonal adjustment | F20: =InpC!F$27 -> 0.155 | G20: =InpC!G$27 -> % of annual yield
E21: =Time!E$126 -> Period number | F21: =Time!F$126 -> 0 | G21: =Time!G$126 -> counter | H21: =Time!H$126 -> 0 | I21: =Time!I$126 -> 0 | J21: =Time!J$126 -> 0 | K21: =Time!K$126 -> 0 | L21: =Time!L$126 -> 0 | ... EA21: =Time!EA$126 -> 0
E22: =Time!E$97 -> Operating period flag | F22: =Time!F$97 -> 0 | G22: =Time!G$97 -> flag | H22: =Time!H$97 -> 100 | I22: =Time!I$97 -> 0 | J22: =Time!J$97 -> 0 | K22: =Time!K$97 -> 0 | L22: =Time!L$97 -> 0 | ... EA22: =Time!EA$97 -> 0
E23: Seasonality adjustment | G23: % | H23: =SUM(J23:GJ23) -> 25 | J23: =IF(J22 = 1, INDEX($F17:$F20, J21), 0) -> 0 | K23: =IF(K22 = 1, INDEX($F17:$F20, K21), 0) -> 0 | L23: =IF(L22 = 1, INDEX($F17:$F20, L21), 0) -> 0 | M23: =IF(M22 = 1, INDEX($F17:$F20, M21), 0) -> 0.33 | N23: =IF(N22 = 1, INDEX($F17:$F20, N21), 0) -> 0.36 | O23: =IF(O22 = 1, INDEX($F17:$F20, O21), 0) -> 0.155 | P23: =IF(P22 = 1, INDEX($F17:$F20, P21), 0) -> 0.155 | Q23: =IF(Q22 = 1, INDEX($F17:$F20, Q21), 0) -> 0.33 | ... EA23: =IF(EA22 = 1, INDEX($F17:$F20, EA21), 0) -> 0
B25: Electricity generation
E26: =InpC!E$30 -> Year 1 P50 yield | F26: =InpC!F$30 -> 250 | G26: =InpC!G$30 -> GWh
E27: =InpC!E$31 -> Availability | F27: =InpC!F$31 -> 0.97 | G27: =InpC!G$31 -> %
E28: =E$14 -> Compound degradation | F28: =F$14 -> 0 | G28: =G$14 -> % | H28: =H$14 -> 0 | I28: =I$14 -> 0 | J28: =J$14 -> 0 | K28: =K$14 -> 0 | L28: =L$14 -> 0 | ... EA28: =EA$14 -> 0
E29: =E$23 -> Seasonality adjustment | F29: =F$23 -> 0 | G29: =G$23 -> % | H29: =H$23 -> 25 | I29: =I$23 -> 0 | J29: =J$23 -> 0 | K29: =K$23 -> 0 | L29: =L$23 -> 0 | ... EA29: =EA$23 -> 0
E30: Electricity generation | G30: GWh | H30: =SUM(J30:GJ30) -> 5713.9951 | J30: =$F26 * $F27 * J28 * J29 -> 0 | K30: =$F26 * $F27 * K28 * K29 -> 0 | L30: =$F26 * $F27 * L28 * L29 -> 0 | M30: =$F26 * $F27 * M28 * M29 -> 80.025 | N30: =$F26 * $F27 * N28 * N29 -> 87.3 | O30: =$F26 * $F27 * O28 * O29 -> 37.5875 | P30: =$F26 * $F27 * P28 * P29 -> 37.5875 | Q30: =$F26 * $F27 * Q28 * Q29 -> 79.626866 | ... EA30: =$F26 * $F27 * EA28 * EA29 -> 0
B32: Electricity revenue
E33: =InpC!E$33 -> Power tariff | F33: =InpC!F$33 -> 0.065 | G33: =InpC!G$33 -> USD / kWh
E34: =InpC!E$63 -> GWh to kWh conversion | F34: =InpC!F$63 -> 1000000 | G34: =InpC!G$63 -> kWh / GWh
E35: =InpC!E$64 -> Units in a thousand | F35: =InpC!F$64 -> 1000 | G35: =InpC!G$64 -> units
E36: =E$30 -> Electricity generation | F36: =F$30 -> 0 | G36: =G$30 -> GWh | H36: =H$30 -> 5713.9951 | I36: =I$30 -> 0 | J36: =J$30 -> 0 | K36: =K$30 -> 0 | L36: =L$30 -> 0 | ... EA36: =EA$30 -> 0
E37: =Time!E$97 -> Operating period flag | F37: =Time!F$97 -> 0 | G37: =Time!G$97 -> flag | H37: =Time!H$97 -> 100 | I37: =Time!I$97 -> 0 | J37: =Time!J$97 -> 0 | K37: =Time!K$97 -> 0 | L37: =Time!L$97 -> 0 | ... EA37: =Time!EA$97 -> 0
E38: Electricity revenue | G38: =SMU -> $ 000s | H38: =SUM(J38:GJ38) -> 371409.68 | J38: =$F33 * $F34 / $F35 * J36 * J37 -> 0 | K38: =$F33 * $F34 / $F35 * K36 * K37 -> 0 | L38: =$F33 * $F34 / $F35 * L36 * L37 -> 0 | M38: =$F33 * $F34 / $F35 * M36 * M37 -> 5201.625 | N38: =$F33 * $F34 / $F35 * N36 * N37 -> 5674.5 | O38: =$F33 * $F34 / $F35 * O36 * O37 -> 2443.1875 | P38: =$F33 * $F34 / $F35 * P36 * P37 -> 2443.1875 | Q38: =$F33 * $F34 / $F35 * Q36 * Q37 -> 5175.7463 | ... EA38: =$F33 * $F34 / $F35 * EA36 * EA37 -> 0
A41: ACCOUNTS RECEIVABLE
B43: Forecast accounts receivable balance
E44: =InpC!E$42 -> Accounts receivable days | F44: =InpC!F$42 -> 60 | G44: =InpC!G$42 -> days
E45: =E$38 -> Electricity revenue | F45: =F$38 -> 0 | G45: =G$38 -> $ 000s | H45: =H$38 -> 371409.68 | I45: =I$38 -> 0 | J45: =J$38 -> 0 | K45: =K$38 -> 0 | L45: =L$38 -> 0 | ... EA45: =EA$38 -> 0
E46: =Time!E$138 -> Days in period | F46: =Time!F$138 -> 0 | G46: =Time!G$138 -> days | H46: =Time!H$138 -> 0 | I46: =Time!I$138 -> 0 | J46: =Time!J$138 -> 92 | K46: =Time!K$138 -> 92 | L46: =Time!L$138 -> 90 | ... EA46: =Time!EA$138 -> 92
E47: Forecast accounts receivable balance | G47: =SMU -> $ 000s | J47: =J45 / J46 * $F44 -> 0 | K47: =K45 / K46 * $F44 -> 0 | L47: =L45 / L46 * $F44 -> 0 | M47: =M45 / M46 * $F44 -> 3429.6429 | N47: =N45 / N46 * $F44 -> 3700.7609 | O47: =O45 / O46 * $F44 -> 1593.3832 | P47: =P45 / P46 * $F44 -> 1628.7917 | Q47: =Q45 / Q46 * $F44 -> 3412.58 | ... EA47: =EA45 / EA46 * $F44 -> 0
B49: Cash received from invoices
E50: =E$38 -> Electricity revenue | F50: =F$38 -> 0 | G50: =G$38 -> $ 000s | H50: =H$38 -> 371409.68 | I50: =I$38 -> 0 | J50: =J$38 -> 0 | K50: =K$38 -> 0 | L50: =L$38 -> 0 | ... EA50: =EA$38 -> 0
D51: Less: | E51: =E$47 -> Forecast accounts receivable balance | F51: =F$47 -> 0 | G51: =G$47 -> $ 000s | H51: =H$47 -> 0 | I51: =I$47 -> 0 | J51: =J$47 -> 0 | K51: =K$47 -> 0 | L51: =L$47 -> 0 | ... EA51: =EA$47 -> 0
D52: Plus: | E52: =E$60 -> Accounts receivable balance BEG | F52: =F$60 -> 0 | G52: =G$60 -> $ 000s | H52: =H$60 -> 0 | I52: =I$60 -> 0 | J52: =J$60 -> 0 | K52: =K$60 -> 0 | L52: =L$60 -> 0 | ... EA52: =EA$60 -> 0
E53: Cash received from invoices | G53: =SMU -> $ 000s | H53: =SUM(J53:EA53) -> 371409.68 | J53: =J50 - J51 + J52 -> 0 | K53: =K50 - K51 + K52 -> 0 | L53: =L50 - L51 + L52 -> 0 | M53: =M50 - M51 + M52 -> 1771.9821 | N53: =N50 - N51 + N52 -> 5403.382 | O53: =O50 - O51 + O52 -> 4550.5652 | P53: =P50 - P51 + P52 -> 2407.779 | Q53: =Q50 - Q51 + Q52 -> 3391.958 | ... EA53: =EA50 - EA51 + EA52 -> 0
B55: Accounts receivable balance
E57: =InpC!E$48 -> Accounts receivable - initial balance | F57: =InpC!F$48 -> 0 | G57: =InpC!G$48 -> $ 000s
E58: =Time!E$76 -> Financial close date flag | F58: =Time!F$76 -> 0 | G58: =Time!G$76 -> flag | H58: =Time!H$76 -> 1 | I58: =Time!I$76 -> 0 | J58: =Time!J$76 -> 0 | K58: =Time!K$76 -> 0 | L58: =Time!L$76 -> 1 | ... EA58: =Time!EA$76 -> 0
E60: Accounts receivable balance BEG | G60: =SMU -> $ 000s | J60: =I63 -> 0 | K60: =J63 -> 0 | L60: =K63 -> 0 | M60: =L63 -> 0 | N60: =M63 -> 3429.6429 | O60: =N63 -> 3700.7609 | P60: =O63 -> 1593.3832 | Q60: =P63 -> 1628.7917 | ... EA60: =DZ63 -> 0
E61: =E$38 -> Electricity revenue | F61: =F$38 -> 0 | G61: =G$38 -> $ 000s | H61: =H$38 -> 371409.68 | I61: =I$38 -> 0 | J61: =J$38 -> 0 | K61: =K$38 -> 0 | L61: =L$38 -> 0 | ... EA61: =EA$38 -> 0
E62: =E$53 -> Cash received from invoices | F62: =F$53 -> 0 | G62: =G$53 -> $ 000s | H62: =H$53 -> 371409.68 | I62: =I$53 -> 0 | J62: =J$53 -> 0 | K62: =K$53 -> 0 | L62: =L$53 -> 0 | ... EA62: =EA$53 -> 0
E63: Accounts receivable balance | G63: =SMU -> $ 000s | J63: =IF( J58 = 1, $F57, J60 + J61 - J62) -> 0 | K63: =IF( K58 = 1, $F57, K60 + K61 - K62) -> 0 | L63: =IF( L58 = 1, $F57, L60 + L61 - L62) -> 0 | M63: =IF( M58 = 1, $F57, M60 + M61 - M62) -> 3429.6429 | N63: =IF( N58 = 1, $F57, N60 + N61 - N62) -> 3700.7609 | O63: =IF( O58 = 1, $F57, O60 + O61 - O62) -> 1593.3832 | P63: =IF( P58 = 1, $F57, P60 + P61 - P62) -> 1628.7917 | Q63: =IF( Q58 = 1, $F57, Q60 + Q61 - Q62) -> 3412.58 | ... EA63: =IF( EA58 = 1, $F57, EA60 + EA61 - EA62) -> 0
A67: ACCOUNTS RECEIVABLE - ALTERNATIVE METHOD - NOT USED IN MODEL
B69: Forecast cash received for current period invoices
E70: =InpC!E$42 -> Accounts receivable days | F70: =InpC!F$42 -> 60 | G70: =InpC!G$42 -> days
E71: =E$38 -> Electricity revenue | F71: =F$38 -> 0 | G71: =G$38 -> $ 000s | H71: =H$38 -> 371409.68 | I71: =I$38 -> 0 | J71: =J$38 -> 0 | K71: =K$38 -> 0 | L71: =L$38 -> 0 | ... EA71: =EA$38 -> 0
E72: =Time!E$138 -> Days in period | F72: =Time!F$138 -> 0 | G72: =Time!G$138 -> days | H72: =Time!H$138 -> 0 | I72: =Time!I$138 -> 0 | J72: =Time!J$138 -> 92 | K72: =Time!K$138 -> 92 | L72: =Time!L$138 -> 90 | ... EA72: =Time!EA$138 -> 92
E73: Cash received from current period invoices | G73: =SMU -> $ 000s | J73: =J71 / J72 * (J72 - $F70) -> 0 | K73: =K71 / K72 * (K72 - $F70) -> 0 | L73: =L71 / L72 * (L72 - $F70) -> 0 | M73: =M71 / M72 * (M72 - $F70) -> 1771.9821 | N73: =N71 / N72 * (N72 - $F70) -> 1973.7391 | O73: =O71 / O72 * (O72 - $F70) -> 849.80435 | P73: =P71 / P72 * (P72 - $F70) -> 814.39583 | Q73: =Q71 / Q72 * (Q72 - $F70) -> 1763.1663 | ... EA73: =EA71 / EA72 * (EA72 - $F70) -> 0
B75: Cash received from invoices
E76: =E$83 -> Accounts receivable - balance BEG | F76: =F$83 -> 0 | G76: =G$83 -> $ 000s | H76: =H$83 -> 0 | I76: =I$83 -> 0 | J76: =J$83 -> 0 | K76: =K$83 -> 0 | L76: =L$83 -> 0 | ... EA76: =EA$83 -> 0
E77: =E$73 -> Cash received from current period invoices | F77: =F$73 -> 0 | G77: =G$73 -> $ 000s | H77: =H$73 -> 0 | I77: =I$73 -> 0 | J77: =J$73 -> 0 | K77: =K$73 -> 0 | L77: =L$73 -> 0 | ... EA77: =EA$73 -> 0
E78: Cash received from invoices | J78: =SUM(J76:J77) -> 0 | K78: =SUM(K76:K77) -> 0 | L78: =SUM(L76:L77) -> 0 | M78: =SUM(M76:M77) -> 1771.9821 | N78: =SUM(N76:N77) -> 5403.382 | O78: =SUM(O76:O77) -> 4550.5652 | P78: =SUM(P76:P77) -> 2407.779 | Q78: =SUM(Q76:Q77) -> 3391.958 | ... EA78: =SUM(EA76:EA77) -> 0
E80: =InpC!E$48 -> Accounts receivable - initial balance | F80: =InpC!F$48 -> 0 | G80: =InpC!G$48 -> $ 000s
E81: =Time!E$76 -> Financial close date flag | F81: =Time!F$76 -> 0 | G81: =Time!G$76 -> flag | H81: =Time!H$76 -> 1 | I81: =Time!I$76 -> 0 | J81: =Time!J$76 -> 0 | K81: =Time!K$76 -> 0 | L81: =Time!L$76 -> 1 | ... EA81: =Time!EA$76 -> 0
E83: Accounts receivable - balance BEG | G83: =SMU -> $ 000s | J83: =I86 -> 0 | K83: =J86 -> 0 | L83: =K86 -> 0 | M83: =L86 -> 0 | N83: =M86 -> 3429.6429 | O83: =N86 -> 3700.7609 | P83: =O86 -> 1593.3832 | Q83: =P86 -> 1628.7917 | ... EA83: =DZ86 -> 0
E84: =E$38 -> Electricity revenue | F84: =F$38 -> 0 | G84: =G$38 -> $ 000s | H84: =H$38 -> 371409.68 | I84: =I$38 -> 0 | J84: =J$38 -> 0 | K84: =K$38 -> 0 | L84: =L$38 -> 0 | ... EA84: =EA$38 -> 0
E85: =E$78 -> Cash received from invoices | F85: =F$78 -> 0 | G85: =G$78 -> 0 | H85: =H$78 -> 0 | I85: =I$78 -> 0 | J85: =J$78 -> 0 | K85: =K$78 -> 0 | L85: =L$78 -> 0 | ... EA85: =EA$78 -> 0
E86: Accounts receivable - balance | G86: =SMU -> $ 000s | J86: =IF( J81 = 1, $F80, J83 + J84 - J85) -> 0 | K86: =IF( K81 = 1, $F80, K83 + K84 - K85) -> 0 | L86: =IF( L81 = 1, $F80, L83 + L84 - L85) -> 0 | M86: =IF( M81 = 1, $F80, M83 + M84 - M85) -> 3429.6429 | N86: =IF( N81 = 1, $F80, N83 + N84 - N85) -> 3700.7609 | O86: =IF( O81 = 1, $F80, O83 + O84 - O85) -> 1593.3832 | P86: =IF( P81 = 1, $F80, P83 + P84 - P85) -> 1628.7917 | Q86: =IF( Q81 = 1, $F80, Q83 + Q84 - Q85) -> 3412.58 | ... EA86: =IF( EA81 = 1, $F80, EA83 + EA84 - EA85) -> 0
A91: OPERATING COSTS
E93: =InpC!E$36 -> Annual fixed real O&M cost | F93: =InpC!F$36 -> 1500 | G93: =InpC!G$36 -> $ 000s
E94: =InpC!E$60 -> Number of periods in a year | F94: =InpC!F$60 -> 4 | G94: =InpC!G$60 -> periods
E95: [us cpi indexation factor] | L95: 1 | M95: =L95 * 1.005 -> 1.005 | N95: =M95 * 1.005 -> 1.010025 | O95: =N95 * 1.005 -> 1.0150751 | P95: =O95 * 1.005 -> 1.0201505 | Q95: =P95 * 1.005 -> 1.0252513 | R95: =Q95 * 1.005 -> 1.0303775 | S95: =R95 * 1.005 -> 1.0355294 | T95: =S95 * 1.005 -> 1.040707 | ... EA95: =DZ95 * 1.005 -> 1.810345
E96: =Time!E$97 -> Operating period flag | F96: =Time!F$97 -> 0 | G96: =Time!G$97 -> flag | H96: =Time!H$97 -> 100 | I96: =Time!I$97 -> 0 | J96: =Time!J$97 -> 0 | K96: =Time!K$97 -> 0 | L96: =Time!L$97 -> 0 | ... EA96: =Time!EA$97 -> 0
E97: O&M cost POS | G97: =SMU -> $ 000s | H97: =SUM(J97:EA97) -> 48742.638 | J97: =$F93 / $F94 * J95 * J96 -> 0 | K97: =$F93 / $F94 * K95 * K96 -> 0 | L97: =$F93 / $F94 * L95 * L96 -> 0 | M97: =$F93 / $F94 * M95 * M96 -> 376.875 | N97: =$F93 / $F94 * N95 * N96 -> 378.75937 | O97: =$F93 / $F94 * O95 * O96 -> 380.65317 | P97: =$F93 / $F94 * P95 * P96 -> 382.55644 | Q97: =$F93 / $F94 * Q95 * Q96 -> 384.46922 | ... EA97: =$F93 / $F94 * EA95 * EA96 -> 0
E98: =LEFT(E97, LEN(E97) - 4) -> O&M cost | G98: =SMU -> $ 000s | H98: =SUM(J98:EA98) -> -48742.638 | J98: =-1 * J97 -> 0 | K98: =-1 * K97 -> 0 | L98: =-1 * L97 -> 0 | M98: =-1 * M97 -> -376.875 | N98: =-1 * N97 -> -378.75937 | O98: =-1 * O97 -> -380.65317 | P98: =-1 * P97 -> -382.55644 | Q98: =-1 * Q97 -> -384.46922 | ... EA98: =-1 * EA97 -> 0
A101: ACCOUNTS PAYABLE
B103: Forecast accounts payable balance
E104: =InpC!E$43 -> Accounts payable days | F104: =InpC!F$43 -> 30 | G104: =InpC!G$43 -> days
E105: =E$97 -> O&M cost POS | F105: =F$97 -> 0 | G105: =G$97 -> $ 000s | H105: =H$97 -> 48742.638 | I105: =I$97 -> 0 | J105: =J$97 -> 0 | K105: =K$97 -> 0 | L105: =L$97 -> 0 | ... EA105: =EA$97 -> 0
E106: =Time!E$138 -> Days in period | F106: =Time!F$138 -> 0 | G106: =Time!G$138 -> days | H106: =Time!H$138 -> 0 | I106: =Time!I$138 -> 0 | J106: =Time!J$138 -> 92 | K106: =Time!K$138 -> 92 | L106: =Time!L$138 -> 90 | ... EA106: =Time!EA$138 -> 92
E107: Forecast accounts payable balance | G107: =SMU -> $ 000s | J107: =J105 / J106 * $F104 -> 0 | K107: =K105 / K106 * $F104 -> 0 | L107: =L105 / L106 * $F104 -> 0 | M107: =M105 / M106 * $F104 -> 124.24451 | N107: =N105 / N106 * $F104 -> 123.50849 | O107: =O105 / O106 * $F104 -> 124.12603 | P107: =P105 / P106 * $F104 -> 127.51881 | Q107: =Q105 / Q106 * $F104 -> 126.74809 | ... EA107: =EA105 / EA106 * $F104 -> 0
B109: Cash received from invoices
E110: =E$97 -> O&M cost POS | F110: =F$97 -> 0 | G110: =G$97 -> $ 000s | H110: =H$97 -> 48742.638 | I110: =I$97 -> 0 | J110: =J$97 -> 0 | K110: =K$97 -> 0 | L110: =L$97 -> 0 | ... EA110: =EA$97 -> 0
D111: Less: | E111: =E$107 -> Forecast accounts payable balance | F111: =F$107 -> 0 | G111: =G$107 -> $ 000s | H111: =H$107 -> 0 | I111: =I$107 -> 0 | J111: =J$107 -> 0 | K111: =K$107 -> 0 | L111: =L$107 -> 0 | ... EA111: =EA$107 -> 0
D112: Plus: | E112: =E$121 -> Accounts payable balance BEG | F112: =F$121 -> 0 | G112: =G$121 -> $ 000s | H112: =H$121 -> 0 | I112: =I$121 -> 0 | J112: =J$121 -> 0 | K112: =K$121 -> 0 | L112: =L$121 -> 0 | ... EA112: =EA$121 -> 0
E113: Cash paid for operating costs POS | G113: =SMU -> $ 000s | H113: =SUM(J113:EA113) -> 48742.638 | J113: =J110 - J111 + J112 -> 0 | K113: =K110 - K111 + K112 -> 0 | L113: =L110 - L111 + L112 -> 0 | M113: =M110 - M111 + M112 -> 252.63049 | N113: =N110 - N111 + N112 -> 379.49539 | O113: =O110 - O111 + O112 -> 380.03563 | P113: =P110 - P111 + P112 -> 379.16366 | Q113: =Q110 - Q111 + Q112 -> 385.23994 | ... EA113: =EA110 - EA111 + EA112 -> 0
E114: =LEFT(E113, LEN(E113) - 4) -> Cash paid for operating costs | G114: =SMU -> $ 000s | H114: =SUM(J114:EA114) -> -48742.638 | J114: =-1 * J113 -> 0 | K114: =-1 * K113 -> 0 | L114: =-1 * L113 -> 0 | M114: =-1 * M113 -> -252.63049 | N114: =-1 * N113 -> -379.49539 | O114: =-1 * O113 -> -380.03563 | P114: =-1 * P113 -> -379.16366 | Q114: =-1 * Q113 -> -385.23994 | ... EA114: =-1 * EA113 -> 0
B116: Accounts payable balance
E118: =InpC!E$49 -> Accounts payable - initial balance | F118: =InpC!F$49 -> 0 | G118: =InpC!G$49 -> $ 000s
E119: =Time!E$76 -> Financial close date flag | F119: =Time!F$76 -> 0 | G119: =Time!G$76 -> flag | H119: =Time!H$76 -> 1 | I119: =Time!I$76 -> 0 | J119: =Time!J$76 -> 0 | K119: =Time!K$76 -> 0 | L119: =Time!L$76 -> 1 | ... EA119: =Time!EA$76 -> 0
E121: Accounts payable balance BEG | G121: =SMU -> $ 000s | J121: =I124 -> 0 | K121: =J124 -> 0 | L121: =K124 -> 0 | M121: =L124 -> 0 | N121: =M124 -> 124.24451 | O121: =N124 -> 123.50849 | P121: =O124 -> 124.12603 | Q121: =P124 -> 127.51881 | ... EA121: =DZ124 -> 0
E122: =E$97 -> O&M cost POS | F122: =F$97 -> 0 | G122: =G$97 -> $ 000s | H122: =H$97 -> 48742.638 | I122: =I$97 -> 0 | J122: =J$97 -> 0 | K122: =K$97 -> 0 | L122: =L$97 -> 0 | ... EA122: =EA$97 -> 0
E123: =E$113 -> Cash paid for operating costs POS | F123: =F$113 -> 0 | G123: =G$113 -> $ 000s | H123: =H$113 -> 48742.638 | I123: =I$113 -> 0 | J123: =J$113 -> 0 | K123: =K$113 -> 0 | L123: =L$113 -> 0 | ... EA123: =EA$113 -> 0
E124: Accounts payable balance | G124: =SMU -> $ 000s | J124: =IF( J119 = 1, $F118, J121 + J122 - J123) -> 0 | K124: =IF( K119 = 1, $F118, K121 + K122 - K123) -> 0 | L124: =IF( L119 = 1, $F118, L121 + L122 - L123) -> 0 | M124: =IF( M119 = 1, $F118, M121 + M122 - M123) -> 124.24451 | N124: =IF( N119 = 1, $F118, N121 + N122 - N123) -> 123.50849 | O124: =IF( O119 = 1, $F118, O121 + O122 - O123) -> 124.12603 | P124: =IF( P119 = 1, $F118, P121 + P122 - P123) -> 127.51881 | Q124: =IF( Q119 = 1, $F118, Q121 + Q122 - Q123) -> 126.74809 | ... EA124: =IF( EA119 = 1, $F118, EA121 + EA122 - EA123) -> 0
A127: END

Sheet Asset
A1: =RIGHT(CELL("filename", A1), LEN(CELL("filename", A1)) - SEARCH("]", CELL("filename", A1))) & " - " & InpC!F3 -> Asset - Base case 1
E2: =Time!E$25 -> Model period ending | F2: =Check!$F$9 -> 0 | G2: Error chks | J2: =Time!J$25 -> 44104 | K2: =Time!K$25 -> 44196 | L2: =Time!L$25 -> 44286 | M2: =Time!M$25 -> 44377 | N2: =Time!N$25 -> 44469 | O2: =Time!O$25 -> 44561 | P2: =Time!P$25 -> 44651 | Q2: =Time!Q$25 -> 44742 | ... EA2: =Time!EA$25 -> 55153
E3: =Time!E$67 -> Timeline label | F3: =Output!J2 -> 0 | G3: Track chgs | J3: =Time!J$67 -> Pre-fcst | K3: =Time!K$67 -> Pre-fcst | L3: =Time!L$67 -> Fin Close | M3: =Time!M$67 -> Operations | N3: =Time!N$67 -> Operations | O3: =Time!O$67 -> Operations | P3: =Time!P$67 -> Operations | Q3: =Time!Q$67 -> Operations | ... EA3: =Time!EA$67 -> Post ops
E4: =Time!E$42 -> Contract year | F4: =Check!$F$21 -> 0 | G4: Alerts | J4: =Time!J$42 -> 2020 | K4: =Time!K$42 -> 2020 | L4: =Time!L$42 -> 2020 | M4: =Time!M$42 -> 2021 | N4: =Time!N$42 -> 2021 | O4: =Time!O$42 -> 2021 | P4: =Time!P$42 -> 2021 | Q4: =Time!Q$42 -> 2022 | ... EA4: =Time!EA$42 -> 2050
E5: =Time!E$10 -> Model column counter | F5: Constant | G5: Unit | H5: Total | J5: =Time!J$10 -> 1 | K5: =Time!K$10 -> 2 | L5: =Time!L$10 -> 3 | M5: =Time!M$10 -> 4 | N5: =Time!N$10 -> 5 | O5: =Time!O$10 -> 6 | P5: =Time!P$10 -> 7 | Q5: =Time!Q$10 -> 8 | ... EA5: =Time!EA$10 -> 122
A8: FIXED ASSET
B10: Depreciation
E11: =InpC!E$50 -> Fixed asset - initial balance | F11: =InpC!F$50 -> 100000 | G11: =InpC!G$50 -> $ 000s
E12: =InpC!E$39 -> Useful life of asset | F12: =InpC!F$39 -> 25 | G12: =InpC!G$39 -> years
E13: =InpC!E$60 -> Number of periods in a year | F13: =InpC!F$60 -> 4 | G13: =InpC!G$60 -> periods
E14: =Time!E$109 -> Useful life of asset flag | F14: =Time!F$109 -> 0 | G14: =Time!G$109 -> flag | H14: =Time!H$109 -> 100 | I14: =Time!I$109 -> 0 | J14: =Time!J$109 -> 0 | K14: =Time!K$109 -> 0 | L14: =Time!L$109 -> 0 | ... EA14: =Time!EA$109 -> 0
E15: Depreciation of fixed asset POS | G15: =SMU -> $ 000s | H15: =SUM(J15:EA15) -> 100000 | J15: =$F11 / $F12 / $F13 * J14 -> 0 | K15: =$F11 / $F12 / $F13 * K14 -> 0 | L15: =$F11 / $F12 / $F13 * L14 -> 0 | M15: =$F11 / $F12 / $F13 * M14 -> 1000 | N15: =$F11 / $F12 / $F13 * N14 -> 1000 | O15: =$F11 / $F12 / $F13 * O14 -> 1000 | P15: =$F11 / $F12 / $F13 * P14 -> 1000 | Q15: =$F11 / $F12 / $F13 * Q14 -> 1000 | ... EA15: =$F11 / $F12 / $F13 * EA14 -> 0
E16: =LEFT(E15, LEN(E15) - 4) -> Depreciation of fixed asset | G16: =SMU -> $ 000s | H16: =SUM(J16:EA16) -> -100000 | J16: =-1 * J15 -> 0 | K16: =-1 * K15 -> 0 | L16: =-1 * L15 -> 0 | M16: =-1 * M15 -> -1000 | N16: =-1 * N15 -> -1000 | O16: =-1 * O15 -> -1000 | P16: =-1 * P15 -> -1000 | Q16: =-1 * Q15 -> -1000 | ... EA16: =-1 * EA15 -> 0
B18: Fixed asset balance
E20: =InpC!E$50 -> Fixed asset - initial balance | F20: =InpC!F$50 -> 100000 | G20: =InpC!G$50 -> $ 000s
E21: =Time!E$76 -> Financial close date flag | F21: =Time!F$76 -> 0 | G21: =Time!G$76 -> flag | H21: =Time!H$76 -> 1 | I21: =Time!I$76 -> 0 | J21: =Time!J$76 -> 0 | K21: =Time!K$76 -> 0 | L21: =Time!L$76 -> 1 | ... EA21: =Time!EA$76 -> 0
E23: Fixed asset balance BEG | G23: =SMU -> $ 000s | J23: =I26 -> 0 | K23: =J26 -> 0 | L23: =K26 -> 0 | M23: =L26 -> 100000 | N23: =M26 -> 99000 | O23: =N26 -> 98000 | P23: =O26 -> 97000 | Q23: =P26 -> 96000 | ... EA23: =DZ26 -> 0
E24: [Additional capex]
E25: =E$15 -> Depreciation of fixed asset POS | F25: =F$15 -> 0 | G25: =G$15 -> $ 000s | H25: =H$15 -> 100000 | I25: =I$15 -> 0 | J25: =J$15 -> 0 | K25: =K$15 -> 0 | L25: =L$15 -> 0 | ... EA25: =EA$15 -> 0
E26: Fixed asset balance | G26: =SMU -> $ 000s | J26: =IF( J21 = 1, $F20, J23 + J24 - J25) -> 0 | K26: =IF( K21 = 1, $F20, K23 + K24 - K25) -> 0 | L26: =IF( L21 = 1, $F20, L23 + L24 - L25) -> 100000 | M26: =IF( M21 = 1, $F20, M23 + M24 - M25) -> 99000 | N26: =IF( N21 = 1, $F20, N23 + N24 - N25) -> 98000 | O26: =IF( O21 = 1, $F20, O23 + O24 - O25) -> 97000 | P26: =IF( P21 = 1, $F20, P23 + P24 - P25) -> 96000 | Q26: =IF( Q21 = 1, $F20, Q23 + Q24 - Q25) -> 95000 | ... EA26: =IF( EA21 = 1, $F20, EA23 + EA24 - EA25) -> 0
A30: END

Sheet Debt
A1: =RIGHT(CELL("filename", A1), LEN(CELL("filename", A1)) - SEARCH("]", CELL("filename", A1))) & " - " & InpC!F3 -> Debt - Base case 1
E2: =Time!E$25 -> Model period ending | F2: =Check!$F$9 -> 0 | G2: Error chks | J2: =Time!J$25 -> 44104 | K2: =Time!K$25 -> 44196 | L2: =Time!L$25 -> 44286 | M2: =Time!M$25 -> 44377 | N2: =Time!N$25 -> 44469 | O2: =Time!O$25 -> 44561 | P2: =Time!P$25 -> 44651 | Q2: =Time!Q$25 -> 44742 | ... EA2: =Time!EA$25 -> 55153
E3: =Time!E$67 -> Timeline label | F3: =Output!J2 -> 0 | G3: Track chgs | J3: =Time!J$67 -> Pre-fcst | K3: =Time!K$67 -> Pre-fcst | L3: =Time!L$67 -> Fin Close | M3: =Time!M$67 -> Operations | N3: =Time!N$67 -> Operations | O3: =Time!O$67 -> Operations | P3: =Time!P$67 -> Operations | Q3: =Time!Q$67 -> Operations | ... EA3: =Time!EA$67 -> Post ops
E4: =Time!E$42 -> Contract year | F4: =Check!$F$21 -> 0 | G4: Alerts | J4: =Time!J$42 -> 2020 | K4: =Time!K$42 -> 2020 | L4: =Time!L$42 -> 2020 | M4: =Time!M$42 -> 2021 | N4: =Time!N$42 -> 2021 | O4: =Time!O$42 -> 2021 | P4: =Time!P$42 -> 2021 | Q4: =Time!Q$42 -> 2022 | ... EA4: =Time!EA$42 -> 2050
E5: =Time!E$10 -> Model column counter | F5: Constant | G5: Unit | H5: Total | J5: =Time!J$10 -> 1 | K5: =Time!K$10 -> 2 | L5: =Time!L$10 -> 3 | M5: =Time!M$10 -> 4 | N5: =Time!N$10 -> 5 | O5: =Time!O$10 -> 6 | P5: =Time!P$10 -> 7 | Q5: =Time!Q$10 -> 8 | ... EA5: =Time!EA$10 -> 122
A7: SENIOR DEBT
B9: Senior debt intial drawdown
E10: Senior debt leverage | F10: 0.7 | G10: %
E11: =InpC!E$50 -> Fixed asset - initial balance | F11: =InpC!F$50 -> 100000 | G11: =InpC!G$50 -> $ 000s
E12: Senior debt initial drawdown | F12: =F10 * F11 -> 70000 | G12: =SMU -> $ 000s
B14: Senior debt principal repayment
B18: Senior debt interest
B22: Senior debt balance
E24: =E$12 -> Senior debt initial drawdown | F24: =F$12 -> 70000 | G24: =G$12 -> $ 000s
E25: =Time!E$76 -> Financial close date flag | F25: =Time!F$76 -> 0 | G25: =Time!G$76 -> flag | H25: =Time!H$76 -> 1 | I25: =Time!I$76 -> 0 | J25: =Time!J$76 -> 0 | K25: =Time!K$76 -> 0 | L25: =Time!L$76 -> 1 | ... EA25: =Time!EA$76 -> 0
E27: Senior debt balance BEG | G27: =SMU -> $ 000s | J27: =I30 -> 0 | K27: =J30 -> 0 | L27: =K30 -> 0 | M27: =L30 -> 70000 | N27: =M30 -> 70000 | O27: =N30 -> 70000 | P27: =O30 -> 70000 | Q27: =P30 -> 70000 | ... EA27: =DZ30 -> 70000
E28: [senior debt drawdown]
E29: [senior debt repayment]
E30: Senior debt balance | G30: =SMU -> $ 000s | J30: =IF( J25 = 1, $F24, J27 + J28 - J29) -> 0 | K30: =IF( K25 = 1, $F24, K27 + K28 - K29) -> 0 | L30: =IF( L25 = 1, $F24, L27 + L28 - L29) -> 70000 | M30: =IF( M25 = 1, $F24, M27 + M28 - M29) -> 70000 | N30: =IF( N25 = 1, $F24, N27 + N28 - N29) -> 70000 | O30: =IF( O25 = 1, $F24, O27 + O28 - O29) -> 70000 | P30: =IF( P25 = 1, $F24, P27 + P28 - P29) -> 70000 | Q30: =IF( Q25 = 1, $F24, Q27 + Q28 - Q29) -> 70000 | ... EA30: =IF( EA25 = 1, $F24, EA27 + EA28 - EA29) -> 70000
A36: END

Sheet Equity
A1: =RIGHT(CELL("filename", A1), LEN(CELL("filename", A1)) - SEARCH("]", CELL("filename", A1))) & " - " & InpC!F3 -> Equity - Base case 1
E2: =Time!E$25 -> Model period ending | F2: =Check!$F$9 -> 0 | G2: Error chks | J2: =Time!J$25 -> 44104 | K2: =Time!K$25 -> 44196 | L2: =Time!L$25 -> 44286 | M2: =Time!M$25 -> 44377 | N2: =Time!N$25 -> 44469 | O2: =Time!O$25 -> 44561 | P2: =Time!P$25 -> 44651 | Q2: =Time!Q$25 -> 44742 | ... EA2: =Time!EA$25 -> 55153
E3: =Time!E$67 -> Timeline label | F3: =Output!J2 -> 0 | G3: Track chgs | J3: =Time!J$67 -> Pre-fcst | K3: =Time!K$67 -> Pre-fcst | L3: =Time!L$67 -> Fin Close | M3: =Time!M$67 -> Operations | N3: =Time!N$67 -> Operations | O3: =Time!O$67 -> Operations | P3: =Time!P$67 -> Operations | Q3: =Time!Q$67 -> Operations | ... EA3: =Time!EA$67 -> Post ops
E4: =Time!E$42 -> Contract year | F4: =Check!$F$21 -> 0 | G4: Alerts | J4: =Time!J$42 -> 2020 | K4: =Time!K$42 -> 2020 | L4: =Time!L$42 -> 2020 | M4: =Time!M$42 -> 2021 | N4: =Time!N$42 -> 2021 | O4: =Time!O$42 -> 2021 | P4: =Time!P$42 -> 2021 | Q4: =Time!Q$42 -> 2022 | ... EA4: =Time!EA$42 -> 2050
E5: =Time!E$10 -> Model column counter | F5: Constant | G5: Unit | H5: Total | J5: =Time!J$10 -> 1 | K5: =Time!K$10 -> 2 | L5: =Time!L$10 -> 3 | M5: =Time!M$10 -> 4 | N5: =Time!N$10 -> 5 | O5: =Time!O$10 -> 6 | P5: =Time!P$10 -> 7 | Q5: =Time!Q$10 -> 8 | ... EA5: =Time!EA$10 -> 122
A8: SHARE CAPITAL
B10: Share capital initial drawdown
E11: =InpC!E$50 -> Fixed asset - initial balance | F11: =InpC!F$50 -> 100000 | G11: =InpC!G$50 -> $ 000s
E12: =Debt!E$12 -> Senior debt initial drawdown | F12: =Debt!F$12 -> 70000 | G12: =Debt!G$12 -> $ 000s
E13: Share capital - initial drawdown | F13: =F11 - F12 -> 30000 | G13: =SMU -> $ 000s
B15: Share capital redemption
E16: =E$26 -> Share capital balance BEG | F16: =F$26 -> 0 | G16: =G$26 -> $ 000s | H16: =H$26 -> 0 | I16: =I$26 -> 0 | J16: =J$26 -> 0 | K16: =K$26 -> 0 | L16: =L$26 -> 0 | ... EA16: =EA$26 -> 0
E17: =Time!E$91 -> Last operating period flag | F17: =Time!F$91 -> 0 | G17: =Time!G$91 -> flag | H17: =Time!H$91 -> 1 | I17: =Time!I$91 -> 0 | J17: =Time!J$91 -> 0 | K17: =Time!K$91 -> 0 | L17: =Time!L$91 -> 0 | ... EA17: =Time!EA$91 -> 0
E18: Share capital redemption POS | G18: =SMU -> $ 000s | H18: =SUM(J18:EA18) -> 30000 | J18: =J16 * J17 -> 0 | K18: =K16 * K17 -> 0 | L18: =L16 * L17 -> 0 | M18: =M16 * M17 -> 0 | N18: =N16 * N17 -> 0 | O18: =O16 * O17 -> 0 | P18: =P16 * P17 -> 0 | Q18: =Q16 * Q17 -> 0 | ... EA18: =EA16 * EA17 -> 0
E19: =LEFT(E18, LEN(E18) - 4) -> Share capital redemption | G19: =SMU -> $ 000s | H19: =SUM(J19:EA19) -> -30000 | J19: =-1 * J18 -> 0 | K19: =-1 * K18 -> 0 | L19: =-1 * L18 -> 0 | M19: =-1 * M18 -> 0 | N19: =-1 * N18 -> 0 | O19: =-1 * O18 -> 0 | P19: =-1 * P18 -> 0 | Q19: =-1 * Q18 -> 0 | ... EA19: =-1 * EA18 -> 0
B21: Share capital balance
E23: =E$13 -> Share capital - initial drawdown | F23: =F$13 -> 30000 | G23: =G$13 -> $ 000s
E24: =Time!E$76 -> Financial close date flag | F24: =Time!F$76 -> 0 | G24: =Time!G$76 -> flag | H24: =Time!H$76 -> 1 | I24: =Time!I$76 -> 0 | J24: =Time!J$76 -> 0 | K24: =Time!K$76 -> 0 | L24: =Time!L$76 -> 1 | ... EA24: =Time!EA$76 -> 0
E26: Share capital balance BEG | G26: =SMU -> $ 000s | J26: =I29 -> 0 | K26: =J29 -> 0 | L26: =K29 -> 0 | M26: =L29 -> 30000 | N26: =M29 -> 30000 | O26: =N29 -> 30000 | P26: =O29 -> 30000 | Q26: =P29 -> 30000 | ... EA26: =DZ29 -> 0
E27: [Additional share capital issued]
E28: =E$18 -> Share capital redemption POS | F28: =F$18 -> 0 | G28: =G$18 -> $ 000s | H28: =H$18 -> 30000 | I28: =I$18 -> 0 | J28: =J$18 -> 0 | K28: =K$18 -> 0 | L28: =L$18 -> 0 | ... EA28: =EA$18 -> 0
E29: Share capital balance | G29: =SMU -> $ 000s | J29: =IF( J24 = 1, $F23, J26 + J27 - J28) -> 0 | K29: =IF( K24 = 1, $F23, K26 + K27 - K28) -> 0 | L29: =IF( L24 = 1, $F23, L26 + L27 - L28) -> 30000 | M29: =IF( M24 = 1, $F23, M26 + M27 - M28) -> 30000 | N29: =IF( N24 = 1, $F23, N26 + N27 - N28) -> 30000 | O29: =IF( O24 = 1, $F23, O26 + O27 - O28) -> 30000 | P29: =IF( P24 = 1, $F23, P26 + P27 - P28) -> 30000 | Q29: =IF( Q24 = 1, $F23, Q26 + Q27 - Q28) -> 30000 | ... EA29: =IF( EA24 = 1, $F23, EA26 + EA27 - EA28) -> 0
A33: RETAINED EARNINGS
E35: =InpC!E$46 -> Retained earnings - initial balance | F35: =InpC!F$46 -> 0 | G35: =InpC!G$46 -> $ 000s
E36: =Time!E$76 -> Financial close date flag | F36: =Time!F$76 -> 0 | G36: =Time!G$76 -> flag | H36: =Time!H$76 -> 1 | I36: =Time!I$76 -> 0 | J36: =Time!J$76 -> 0 | K36: =Time!K$76 -> 0 | L36: =Time!L$76 -> 1 | ... EA36: =Time!EA$76 -> 0
E38: Retained earnings balance BEG | G38: =SMU -> $ 000s | J38: =I41 -> 0 | K38: =J41 -> 0 | L38: =K41 -> 0 | M38: =L41 -> 0 | N38: =M41 -> 2305.3984 | O38: =N41 -> 1577.2524 | P38: =O41 -> 0 | Q38: =P41 -> 0 | ... EA38: =DZ41 -> 0
E39: ='FS Qtr'!E$22 -> Profit after tax | F39: ='FS Qtr'!F$22 -> 0 | G39: ='FS Qtr'!G$22 -> $ 000s | H39: ='FS Qtr'!H$22 -> 222667.04 | I39: ='FS Qtr'!I$22 -> 0 | J39: ='FS Qtr'!J$22 -> 0 | K39: ='FS Qtr'!K$22 -> 0 | L39: ='FS Qtr'!L$22 -> 0 | ... EA39: ='FS Qtr'!EA$22 -> 0
E40: =E$69 -> Dividends paid POS | F40: =F$69 -> 0 | G40: =G$69 -> $ 000s | H40: =H$69 -> 222667.04 | I40: =I$69 -> 0 | J40: =J$69 -> 0 | K40: =K$69 -> 0 | L40: =L$69 -> 0 | ... EA40: =EA$69 -> 0
E41: Retained earnings balance | G41: =SMU -> $ 000s | J41: =IF( J36 = 1, $F35, J38 + J39 - J40) -> 0 | K41: =IF( K36 = 1, $F35, K38 + K39 - K40) -> 0 | L41: =IF( L36 = 1, $F35, L38 + L39 - L40) -> 0 | M41: =IF( M36 = 1, $F35, M38 + M39 - M40) -> 2305.3984 | N41: =IF( N36 = 1, $F35, N38 + N39 - N40) -> 1577.2524 | O41: =IF( O36 = 1, $F35, O38 + O39 - O40) -> 0 | P41: =IF( P36 = 1, $F35, P38 + P39 - P40) -> 0 | Q41: =IF( Q36 = 1, $F35, Q38 + Q39 - Q40) -> 0 | ... EA41: =IF( EA36 = 1, $F35, EA38 + EA39 - EA40) -> 0
A44: RETAINED CASH
E46: =InpC!E$47 -> Retained cash - initial balance | F46: =InpC!F$47 -> 0 | G46: =InpC!G$47 -> $ 000s
E47: =Time!E$76 -> Financial close date flag | F47: =Time!F$76 -> 0 | G47: =Time!G$76 -> flag | H47: =Time!H$76 -> 1 | I47: =Time!I$76 -> 0 | J47: =Time!J$76 -> 0 | K47: =Time!K$76 -> 0 | L47: =Time!L$76 -> 1 | ... EA47: =Time!EA$76 -> 0
E49: Retained cash balance BEG | G49: =SMU -> $ 000s | J49: =I52 -> 0 | K49: =J52 -> 0 | L49: =K52 -> 0 | M49: =L52 -> 0 | N49: =M52 -> 0 | O49: =N52 -> 0 | P49: =O52 -> 1530.7429 | Q49: =P52 -> 2498.7271 | ... EA49: =DZ52 -> 70000
E50: ='FS Qtr'!E$50 -> Cash flow available for dividends | F50: ='FS Qtr'!F$50 -> 0 | G50: ='FS Qtr'!G$50 -> $ 000s | H50: ='FS Qtr'!H$50 -> 292667.04 | I50: ='FS Qtr'!I$50 -> 0 | J50: ='FS Qtr'!J$50 -> 0 | K50: ='FS Qtr'!K$50 -> 0 | L50: ='FS Qtr'!L$50 -> 0 | ... EA50: ='FS Qtr'!EA$50 -> 0
E51: =E$69 -> Dividends paid POS | F51: =F$69 -> 0 | G51: =G$69 -> $ 000s | H51: =H$69 -> 222667.04 | I51: =I$69 -> 0 | J51: =J$69 -> 0 | K51: =K$69 -> 0 | L51: =L$69 -> 0 | ... EA51: =EA$69 -> 0
E52: Retained cash balance | G52: =SMU -> $ 000s | J52: =IF( J47 = 1, $F46, J49 + J50 - J51) -> 0 | K52: =IF( K47 = 1, $F46, K49 + K50 - K51) -> 0 | L52: =IF( L47 = 1, $F46, L49 + L50 - L51) -> 0 | M52: =IF( M47 = 1, $F46, M49 + M50 - M51) -> 0 | N52: =IF( N47 = 1, $F46, N49 + N50 - N51) -> 0 | O52: =IF( O47 = 1, $F46, O49 + O50 - O51) -> 1530.7429 | P52: =IF( P47 = 1, $F46, P49 + P50 - P51) -> 2498.7271 | Q52: =IF( Q47 = 1, $F46, Q49 + Q50 - Q51) -> 1714.1681 | ... EA52: =IF( EA47 = 1, $F46, EA49 + EA50 - EA51) -> 70000
A54: DIVIDENDS
B56: Earnings available for dividend
E57: =E$38 -> Retained earnings balance BEG | F57: =F$38 -> 0 | G57: =G$38 -> $ 000s | H57: =H$38 -> 0 | I57: =I$38 -> 0 | J57: =J$38 -> 0 | K57: =K$38 -> 0 | L57: =L$38 -> 0 | ... EA57: =EA$38 -> 0
E58: ='FS Qtr'!E$22 -> Profit after tax | F58: ='FS Qtr'!F$22 -> 0 | G58: ='FS Qtr'!G$22 -> $ 000s | H58: ='FS Qtr'!H$22 -> 222667.04 | I58: ='FS Qtr'!I$22 -> 0 | J58: ='FS Qtr'!J$22 -> 0 | K58: ='FS Qtr'!K$22 -> 0 | L58: ='FS Qtr'!L$22 -> 0 | ... EA58: ='FS Qtr'!EA$22 -> 0
E59: Earnings available for dividend | G59: =SMU -> $ 000s | J59: =SUM(J57:J58) -> 0 | K59: =SUM(K57:K58) -> 0 | L59: =SUM(L57:L58) -> 0 | M59: =SUM(M57:M58) -> 3824.75 | N59: =SUM(N57:N58) -> 6601.139 | O59: =SUM(O57:O58) -> 2639.7867 | P59: =SUM(P57:P58) -> 1060.6311 | Q59: =SUM(Q57:Q58) -> 3791.277 | ... EA59: =SUM(EA57:EA58) -> 0
B61: Cash available for dividend
E62: =E$49 -> Retained cash balance BEG | F62: =F$49 -> 0 | G62: =G$49 -> $ 000s | H62: =H$49 -> 0 | I62: =I$49 -> 0 | J62: =J$49 -> 0 | K62: =K$49 -> 0 | L62: =L$49 -> 0 | ... EA62: =EA$49 -> 70000
E63: ='FS Qtr'!E$50 -> Cash flow available for dividends | F63: ='FS Qtr'!F$50 -> 0 | G63: ='FS Qtr'!G$50 -> $ 000s | H63: ='FS Qtr'!H$50 -> 292667.04 | I63: ='FS Qtr'!I$50 -> 0 | J63: ='FS Qtr'!J$50 -> 0 | K63: ='FS Qtr'!K$50 -> 0 | L63: ='FS Qtr'!L$50 -> 0 | ... EA63: ='FS Qtr'!EA$50 -> 0
E64: Cash available for dividend | G64: =SMU -> $ 000s | J64: =SUM(J62:J63) -> 0 | K64: =SUM(K62:K63) -> 0 | L64: =SUM(L62:L63) -> 0 | M64: =SUM(M62:M63) -> 1519.3516 | N64: =SUM(N62:N63) -> 5023.8866 | O64: =SUM(O62:O63) -> 4170.5296 | P64: =SUM(P62:P63) -> 3559.3582 | Q64: =SUM(Q62:Q63) -> 5505.4452 | ... EA64: =SUM(EA62:EA63) -> 70000
B66: Dividends paid
E67: =E$59 -> Earnings available for dividend | F67: =F$59 -> 0 | G67: =G$59 -> $ 000s | H67: =H$59 -> 0 | I67: =I$59 -> 0 | J67: =J$59 -> 0 | K67: =K$59 -> 0 | L67: =L$59 -> 0 | ... EA67: =EA$59 -> 0
E68: =E$64 -> Cash available for dividend | F68: =F$64 -> 0 | G68: =G$64 -> $ 000s | H68: =H$64 -> 0 | I68: =I$64 -> 0 | J68: =J$64 -> 0 | K68: =K$64 -> 0 | L68: =L$64 -> 0 | ... EA68: =EA$64 -> 70000
E69: Dividends paid POS | G69: =SMU -> $ 000s | H69: =SUM(J69:EA69) -> 222667.04 | J69: =MAX(0, MIN(J67:J68)) -> 0 | K69: =MAX(0, MIN(K67:K68)) -> 0 | L69: =MAX(0, MIN(L67:L68)) -> 0 | M69: =MAX(0, MIN(M67:M68)) -> 1519.3516 | N69: =MAX(0, MIN(N67:N68)) -> 5023.8866 | O69: =MAX(0, MIN(O67:O68)) -> 2639.7867 | P69: =MAX(0, MIN(P67:P68)) -> 1060.6311 | Q69: =MAX(0, MIN(Q67:Q68)) -> 3791.277 | ... EA69: =MAX(0, MIN(EA67:EA68)) -> 0
E70: =LEFT(E69, LEN(E69) - 4) -> Dividends paid | G70: =SMU -> $ 000s | H70: =SUM(J70:EA70) -> -222667.04 | J70: =-1 * J69 -> 0 | K70: =-1 * K69 -> 0 | L70: =-1 * L69 -> 0 | M70: =-1 * M69 -> -1519.3516 | N70: =-1 * N69 -> -5023.8866 | O70: =-1 * O69 -> -2639.7867 | P70: =-1 * P69 -> -1060.6311 | Q70: =-1 * Q69 -> -3791.277 | ... EA70: =-1 * EA69 -> 0
A72: END

Sheet Metrics
A1: =RIGHT(CELL("filename", A1), LEN(CELL("filename", A1)) - SEARCH("]", CELL("filename", A1))) & " - " & InpC!F3 -> Metrics - Base case 1
E2: =Time!E$25 -> Model period ending | F2: =Check!$F$9 -> 0 | G2: Error chks | J2: =Time!J$25 -> 44104 | K2: =Time!K$25 -> 44196 | L2: =Time!L$25 -> 44286 | M2: =Time!M$25 -> 44377 | N2: =Time!N$25 -> 44469 | O2: =Time!O$25 -> 44561 | P2: =Time!P$25 -> 44651 | Q2: =Time!Q$25 -> 44742 | ... EA2: =Time!EA$25 -> 55153
E3: =Time!E$67 -> Timeline label | F3: =Output!J2 -> 0 | G3: Track chgs | J3: =Time!J$67 -> Pre-fcst | K3: =Time!K$67 -> Pre-fcst | L3: =Time!L$67 -> Fin Close | M3: =Time!M$67 -> Operations | N3: =Time!N$67 -> Operations | O3: =Time!O$67 -> Operations | P3: =Time!P$67 -> Operations | Q3: =Time!Q$67 -> Operations | ... EA3: =Time!EA$67 -> Post ops
E4: =Time!E$42 -> Contract year | F4: =Check!$F$21 -> 0 | G4: Alerts | J4: =Time!J$42 -> 2020 | K4: =Time!K$42 -> 2020 | L4: =Time!L$42 -> 2020 | M4: =Time!M$42 -> 2021 | N4: =Time!N$42 -> 2021 | O4: =Time!O$42 -> 2021 | P4: =Time!P$42 -> 2021 | Q4: =Time!Q$42 -> 2022 | ... EA4: =Time!EA$42 -> 2050
E5: =Time!E$10 -> Model column counter | F5: Constant | G5: Unit | H5: Total | J5: =Time!J$10 -> 1 | K5: =Time!K$10 -> 2 | L5: =Time!L$10 -> 3 | M5: =Time!M$10 -> 4 | N5: =Time!N$10 -> 5 | O5: =Time!O$10 -> 6 | P5: =Time!P$10 -> 7 | Q5: =Time!Q$10 -> 8 | ... EA5: =Time!EA$10 -> 122
A7: IRR
B9: Equity IRR
E10: =InpC!E$51 -> Share capital - initial balance | F10: =InpC!F$51 -> 100000 | G10: =InpC!G$51 -> $ 000s
E11: =InpC!E$65 -> Small negative value for XIRR | F11: =InpC!F$65 -> -1e-07 | G11: =InpC!G$65 -> $ 000s
E12: =Time!E$76 -> Financial close date flag | F12: =Time!F$76 -> 0 | G12: =Time!G$76 -> flag | H12: =Time!H$76 -> 1 | I12: =Time!I$76 -> 0 | J12: =Time!J$76 -> 0 | K12: =Time!K$76 -> 0 | L12: =Time!L$76 -> 1 | ... EA12: =Time!EA$76 -> 0
E13: =Time!E$14 -> First model column flag | F13: =Time!F$14 -> 0 | G13: =Time!G$14 -> flag | H13: =Time!H$14 -> 1 | I13: =Time!I$14 -> 0 | J13: =Time!J$14 -> 1 | K13: =Time!K$14 -> 0 | L13: =Time!L$14 -> 0 | ... EA13: =Time!EA$14 -> 0
E14: =Equity!E$69 -> Dividends paid POS | F14: =Equity!F$69 -> 0 | G14: =Equity!G$69 -> $ 000s | H14: =Equity!H$69 -> 222667.04 | I14: =Equity!I$69 -> 0 | J14: =Equity!J$69 -> 0 | K14: =Equity!K$69 -> 0 | L14: =Equity!L$69 -> 0 | ... EA14: =Equity!EA$69 -> 0
E15: =Equity!E$18 -> Share capital redemption POS | F15: =Equity!F$18 -> 0 | G15: =Equity!G$18 -> $ 000s | H15: =Equity!H$18 -> 30000 | I15: =Equity!I$18 -> 0 | J15: =Equity!J$18 -> 0 | K15: =Equity!K$18 -> 0 | L15: =Equity!L$18 -> 0 | ... EA15: =Equity!EA$18 -> 0
E16: Net cashflow to / (from) equity | G16: =SMU -> $ 000s | H16: =SUM(J16:EA16) -> 152667.04 | J16: =$F11 * J13 + -1 * $F10 * J12 + J14 + J15 -> -1e-07 | K16: =$F11 * K13 + -1 * $F10 * K12 + K14 + K15 -> 0 | L16: =$F11 * L13 + -1 * $F10 * L12 + L14 + L15 -> -100000 | M16: =$F11 * M13 + -1 * $F10 * M12 + M14 + M15 -> 1519.3516 | N16: =$F11 * N13 + -1 * $F10 * N12 + N14 + N15 -> 5023.8866 | O16: =$F11 * O13 + -1 * $F10 * O12 + O14 + O15 -> 2639.7867 | P16: =$F11 * P13 + -1 * $F10 * P12 + P14 + P15 -> 1060.6311 | Q16: =$F11 * Q13 + -1 * $F10 * Q12 + Q14 + Q15 -> 3791.277 | ... EA16: =$F11 * EA13 + -1 * $F10 * EA12 + EA14 + EA15 -> 0
E18: =E$16 -> Net cashflow to / (from) equity | F18: =F$16 -> 0 | G18: =G$16 -> $ 000s | H18: =H$16 -> 152667.04 | I18: =I$16 -> 0 | J18: =J$16 -> -1e-07 | K18: =K$16 -> 0 | L18: =L$16 -> -100000 | ... EA18: =EA$16 -> 0
E19: =Time!E$25 -> Model period ending | F19: =Time!F$25 -> 0 | G19: =Time!G$25 -> date | H19: =Time!H$25 -> 0 | I19: =Time!I$25 -> 0 | J19: =Time!J$25 -> 44104 | K19: =Time!K$25 -> 44196 | L19: =Time!L$25 -> 44286 | ... EA19: =Time!EA$25 -> 55153
E20: Equity IRR | F20: =XIRR(J18:EA18, J19:EA19) -> 0.089617065 | G20: %

Sheet FS Qtr
A1: =RIGHT(CELL("filename", A1), LEN(CELL("filename", A1)) - SEARCH("]", CELL("filename", A1))) & " - " & InpC!F3 -> FS Qtr - Base case 1
E2: =Time!E$25 -> Model period ending | F2: =Check!$F$9 -> 0 | G2: Error chks | J2: =Time!J$25 -> 44104 | K2: =Time!K$25 -> 44196 | L2: =Time!L$25 -> 44286 | M2: =Time!M$25 -> 44377 | N2: =Time!N$25 -> 44469 | O2: =Time!O$25 -> 44561 | P2: =Time!P$25 -> 44651 | Q2: =Time!Q$25 -> 44742 | ... EA2: =Time!EA$25 -> 55153
E3: =Time!E$67 -> Timeline label | F3: =Output!J2 -> 0 | G3: Track chgs | J3: =Time!J$67 -> Pre-fcst | K3: =Time!K$67 -> Pre-fcst | L3: =Time!L$67 -> Fin Close | M3: =Time!M$67 -> Operations | N3: =Time!N$67 -> Operations | O3: =Time!O$67 -> Operations | P3: =Time!P$67 -> Operations | Q3: =Time!Q$67 -> Operations | ... EA3: =Time!EA$67 -> Post ops
E4: =Time!E$42 -> Contract year | F4: =Check!$F$21 -> 0 | G4: Alerts | J4: =Time!J$42 -> 2020 | K4: =Time!K$42 -> 2020 | L4: =Time!L$42 -> 2020 | M4: =Time!M$42 -> 2021 | N4: =Time!N$42 -> 2021 | O4: =Time!O$42 -> 2021 | P4: =Time!P$42 -> 2021 | Q4: =Time!Q$42 -> 2022 | ... EA4: =Time!EA$42 -> 2050
E5: =Time!E$10 -> Model column counter | F5: Constant | G5: Unit | H5: Total | J5: =Time!J$10 -> 1 | K5: =Time!K$10 -> 2 | L5: =Time!L$10 -> 3 | M5: =Time!M$10 -> 4 | N5: =Time!N$10 -> 5 | O5: =Time!O$10 -> 6 | P5: =Time!P$10 -> 7 | Q5: =Time!Q$10 -> 8 | ... EA5: =Time!EA$10 -> 122
A7: INCOME STATEMENT
E9: =Ops!E$38 -> Electricity revenue | F9: =Ops!F$38 -> 0 | G9: =Ops!G$38 -> $ 000s | H9: =Ops!H$38 -> 371409.68 | I9: =Ops!I$38 -> 0 | J9: =Ops!J$38 -> 0 | K9: =Ops!K$38 -> 0 | L9: s | M9: =Ops!M$38 -> 5201.625 | N9: =Ops!N$38 -> 5674.5 | O9: =Ops!O$38 -> 2443.1875 | P9: =Ops!P$38 -> 2443.1875 | Q9: =Ops!Q$38 -> 5175.7463 | R9: =Ops!R$38 -> 5646.2687 | S9: =Ops!S$38 -> 2431.0323 | T9: =Ops!T$38 -> 2431.0323 | ... EA9: =Ops!EA$38 -> 0
E10: =Ops!E$98 -> O&M cost | F10: =Ops!F$98 -> 0 | G10: =Ops!G$98 -> $ 000s | H10: =Ops!H$98 -> -48742.638 | I10: =Ops!I$98 -> 0 | J10: =Ops!J$98 -> 0 | K10: =Ops!K$98 -> 0 | L10: =Ops!L$98 -> 0 | ... EA10: =Ops!EA$98 -> 0
E11: EBITDA | G11: =SMU -> $ 000s | H11: =SUM(J11:EA11) -> 322667.04 | J11: =SUM(J9:J10) -> 0 | K11: =SUM(K9:K10) -> 0 | L11: =SUM(L9:L10) -> 0 | M11: =SUM(M9:M10) -> 4824.75 | N11: =SUM(N9:N10) -> 5295.7406 | O11: =SUM(O9:O10) -> 2062.5343 | P11: =SUM(P9:P10) -> 2060.6311 | Q11: =SUM(Q9:Q10) -> 4791.277 | ... EA11: =SUM(EA9:EA10) -> 0
E13: =Asset!E$16 -> Depreciation of fixed asset | F13: =Asset!F$16 -> 0 | G13: =Asset!G$16 -> $ 000s | H13: =Asset!H$16 -> -100000 | I13: =Asset!I$16 -> 0 | J13: =Asset!J$16 -> 0 | K13: =Asset!K$16 -> 0 | L13: =Asset!L$16 -> 0 | ... EA13: =Asset!EA$16 -> 0
E14: EBIT | G14: =SMU -> $ 000s | H14: =SUM(J14:EA14) -> 222667.04 | J14: =J11 + SUM(J13:J13) -> 0 | K14: =K11 + SUM(K13:K13) -> 0 | L14: =L11 + SUM(L13:L13) -> 0 | M14: =M11 + SUM(M13:M13) -> 3824.75 | N14: =N11 + SUM(N13:N13) -> 4295.7406 | O14: =O11 + SUM(O13:O13) -> 1062.5343 | P14: =P11 + SUM(P13:P13) -> 1060.6311 | Q14: =Q11 + SUM(Q13:Q13) -> 3791.277 | ... EA14: =EA11 + SUM(EA13:EA13) -> 0
E16: [Senior debt interest]
E17: [Refi facility interest]
E18: [RCF interest expense]
E19: Profit before tax | G19: =SMU -> $ 000s | H19: =SUM(J19:EA19) -> 222667.04 | J19: =J14 + SUM(J16:J18) -> 0 | K19: =K14 + SUM(K16:K18) -> 0 | L19: =L14 + SUM(L16:L18) -> 0 | M19: =M14 + SUM(M16:M18) -> 3824.75 | N19: =N14 + SUM(N16:N18) -> 4295.7406 | O19: =O14 + SUM(O16:O18) -> 1062.5343 | P19: =P14 + SUM(P16:P18) -> 1060.6311 | Q19: =Q14 + SUM(Q16:Q18) -> 3791.277 | ... EA19: =EA14 + SUM(EA16:EA18) -> 0
E21: [Corporate income tax expense]
E22: Profit after tax | G22: =SMU -> $ 000s | H22: =SUM(J22:EA22) -> 222667.04 | J22: =J19 + J21 -> 0 | K22: =K19 + K21 -> 0 | L22: =L19 + L21 -> 0 | M22: =M19 + M21 -> 3824.75 | N22: =N19 + N21 -> 4295.7406 | O22: =O19 + O21 -> 1062.5343 | P22: =P19 + P21 -> 1060.6311 | Q22: =Q19 + Q21 -> 3791.277 | ... EA22: =EA19 + EA21 -> 0
E24: =Equity!E$70 -> Dividends paid | F24: =Equity!F$70 -> 0 | G24: =Equity!G$70 -> $ 000s | H24: =Equity!H$70 -> -222667.04 | I24: =Equity!I$70 -> 0 | J24: =Equity!J$70 -> 0 | K24: =Equity!K$70 -> 0 | L24: =Equity!L$70 -> 0 | ... EA24: =Equity!EA$70 -> 0
E25: Net income after dividends | G25: =SMU -> $ 000s | H25: =SUM(J25:EA25) -> 0 | J25: =J22 + J24 -> 0 | K25: =K22 + K24 -> 0 | L25: =L22 + L24 -> 0 | M25: =M22 + M24 -> 2305.3984 | N25: =N22 + N24 -> -728.14597 | O25: =O22 + O24 -> -1577.2524 | P25: =P22 + P24 -> 0 | Q25: =Q22 + Q24 -> 0 | ... EA25: =EA22 + EA24 -> 0
A28: CASH FLOW STATEMENT
E30: =Ops!E$53 -> Cash received from invoices | F30: =Ops!F$53 -> 0 | G30: =Ops!G$53 -> $ 000s | H30: =Ops!H$53 -> 371409.68 | I30: =Ops!I$53 -> 0 | J30: =Ops!J$53 -> 0 | K30: =Ops!K$53 -> 0 | L30: =Ops!L$53 -> 0 | ... EA30: =Ops!EA$53 -> 0
E31: =Ops!E$114 -> Cash paid for operating costs | F31: =Ops!F$114 -> 0 | G31: =Ops!G$114 -> $ 000s | H31: =Ops!H$114 -> -48742.638 | I31: =Ops!I$114 -> 0 | J31: =Ops!J$114 -> 0 | K31: =Ops!K$114 -> 0 | L31: =Ops!L$114 -> 0 | ... EA31: =Ops!EA$114 -> 0
E32: [Corporate income tax expense]
E33: Cash flow available for senior debt service | G33: =SMU -> $ 000s | H33: =SUM(J33:EA33) -> 322667.04 | J33: =SUM(J30:J32) -> 0 | K33: =SUM(K30:K32) -> 0 | L33: =SUM(L30:L32) -> 0 | M33: =SUM(M30:M32) -> 1519.3516 | N33: =SUM(N30:N32) -> 5023.8866 | O33: =SUM(O30:O32) -> 4170.5296 | P33: =SUM(P30:P32) -> 2028.6153 | Q33: =SUM(Q30:Q32) -> 3006.718 | ... EA33: =SUM(EA30:EA32) -> 0
E35: [Senior debt interest]
E36: [Senior debt repayment]
E37: Cash flow available for refinancing facility | G37: =SMU -> $ 000s | H37: =SUM(J37:EA37) -> 322667.04 | J37: =J33 + SUM(J35:J36) -> 0 | K37: =K33 + SUM(K35:K36) -> 0 | L37: =L33 + SUM(L35:L36) -> 0 | M37: =M33 + SUM(M35:M36) -> 1519.3516 | N37: =N33 + SUM(N35:N36) -> 5023.8866 | O37: =O33 + SUM(O35:O36) -> 4170.5296 | P37: =P33 + SUM(P35:P36) -> 2028.6153 | Q37: =Q33 + SUM(Q35:Q36) -> 3006.718 | ... EA37: =EA33 + SUM(EA35:EA36) -> 0
E39: [Refi facility drawdown]
E40: [Refi facility repayment]
E41: [Refi facility interest]
E42: Cash flow available for revolving credit facility | G42: =SMU -> $ 000s | H42: =SUM(J42:EA42) -> 322667.04 | J42: =J37 + SUM(J39:J41) -> 0 | K42: =K37 + SUM(K39:K41) -> 0 | L42: =L37 + SUM(L39:L41) -> 0 | M42: =M37 + SUM(M39:M41) -> 1519.3516 | N42: =N37 + SUM(N39:N41) -> 5023.8866 | O42: =O37 + SUM(O39:O41) -> 4170.5296 | P42: =P37 + SUM(P39:P41) -> 2028.6153 | Q42: =Q37 + SUM(Q39:Q41) -> 3006.718 | ... EA42: =EA37 + SUM(EA39:EA41) -> 0
E44: [RCF drawdown]
E45: [RCF repayment]
E46: [RCF interest expense paid]
E47: Cash flow available for distribution | G47: =SMU -> $ 000s | H47: =SUM(J47:EA47) -> 322667.04 | J47: =J42 + SUM(J44:J46) -> 0 | K47: =K42 + SUM(K44:K46) -> 0 | L47: =L42 + SUM(L44:L46) -> 0 | M47: =M42 + SUM(M44:M46) -> 1519.3516 | N47: =N42 + SUM(N44:N46) -> 5023.8866 | O47: =O42 + SUM(O44:O46) -> 4170.5296 | P47: =P42 + SUM(P44:P46) -> 2028.6153 | Q47: =Q42 + SUM(Q44:Q46) -> 3006.718 | ... EA47: =EA42 + SUM(EA44:EA46) -> 0
E49: =Equity!E$19 -> Share capital redemption | F49: =Equity!F$19 -> 0 | G49: =Equity!G$19 -> $ 000s | H49: =Equity!H$19 -> -30000 | I49: =Equity!I$19 -> 0 | J49: =Equity!J$19 -> 0 | K49: =Equity!K$19 -> 0 | L49: =Equity!L$19 -> 0 | ... EA49: =Equity!EA$19 -> 0
E50: Cash flow available for dividends | G50: =SMU -> $ 000s | H50: =SUM(J50:EA50) -> 292667.04 | J50: =J47 + J49 -> 0 | K50: =K47 + K49 -> 0 | L50: =L47 + L49 -> 0 | M50: =M47 + M49 -> 1519.3516 | N50: =N47 + N49 -> 5023.8866 | O50: =O47 + O49 -> 4170.5296 | P50: =P47 + P49 -> 2028.6153 | Q50: =Q47 + Q49 -> 3006.718 | ... EA50: =EA47 + EA49 -> 0
E52: =Equity!E$70 -> Dividends paid | F52: =Equity!F$70 -> 0 | G52: =Equity!G$70 -> $ 000s | H52: =Equity!H$70 -> -222667.04 | I52: =Equity!I$70 -> 0 | J52: =Equity!J$70 -> 0 | K52: =Equity!K$70 -> 0 | L52: =Equity!L$70 -> 0 | ... EA52: =Equity!EA$70 -> 0
E53: Net cash flow after dividends | G53: =SMU -> $ 000s | H53: =SUM(J53:EA53) -> 70000 | J53: =J50 + J52 -> 0 | K53: =K50 + K52 -> 0 | L53: =L50 + L52 -> 0 | M53: =M50 + M52 -> 0 | N53: =N50 + N52 -> 0 | O53: =O50 + O52 -> 1530.7429 | P53: =P50 + P52 -> 967.98426 | Q53: =Q50 + Q52 -> -784.55901 | ... EA53: =EA50 + EA52 -> 0
A56: BALANCE SHEET
B58: Non current assets
E59: =Asset!E$26 -> Fixed asset balance | F59: =Asset!F$26 -> 0 | G59: =Asset!G$26 -> $ 000s | H59: =Asset!H$26 -> 0 | I59: =Asset!I$26 -> 0 | J59: =Asset!J$26 -> 0 | K59: =Asset!K$26 -> 0 | L59: =Asset!L$26 -> 100000 | ... EA59: =Asset!EA$26 -> 0
E60: Non current assets | G60: =SMU -> $ 000s | J60: =SUM(J59) -> 0 | K60: =SUM(K59) -> 0 | L60: =SUM(L59) -> 100000 | M60: =SUM(M59) -> 99000 | N60: =SUM(N59) -> 98000 | O60: =SUM(O59) -> 97000 | P60: =SUM(P59) -> 96000 | Q60: =SUM(Q59) -> 95000 | ... EA60: =SUM(EA59) -> 0
B62: Current assets
E63: =Equity!E$52 -> Retained cash balance | F63: =Equity!F$52 -> 0 | G63: =Equity!G$52 -> $ 000s | H63: =Equity!H$52 -> 0 | I63: =Equity!I$52 -> 0 | J63: =Equity!J$52 -> 0 | K63: =Equity!K$52 -> 0 | L63: =Equity!L$52 -> 0 | ... EA63: =Equity!EA$52 -> 70000
E64: =Ops!E$63 -> Accounts receivable balance | F64: =Ops!F$63 -> 0 | G64: =Ops!G$63 -> $ 000s | H64: =Ops!H$63 -> 0 | I64: =Ops!I$63 -> 0 | J64: =Ops!J$63 -> 0 | K64: =Ops!K$63 -> 0 | L64: =Ops!L$63 -> 0 | ... EA64: =Ops!EA$63 -> 0
E65: Current assets | G65: =SMU -> $ 000s | J65: =SUM(J63:J64) -> 0 | K65: =SUM(K63:K64) -> 0 | L65: =SUM(L63:L64) -> 0 | M65: =SUM(M63:M64) -> 3429.6429 | N65: =SUM(N63:N64) -> 3700.7609 | O65: =SUM(O63:O64) -> 3124.126 | P65: =SUM(P63:P64) -> 4127.5188 | Q65: =SUM(Q63:Q64) -> 5126.7481 | ... EA65: =SUM(EA63:EA64) -> 70000
E67: Total assets | G67: =SMU -> $ 000s | J67: =J65 + J60 -> 0 | K67: =K65 + K60 -> 0 | L67: =L65 + L60 -> 100000 | M67: =M65 + M60 -> 102429.64 | N67: =N65 + N60 -> 101700.76 | O67: =O65 + O60 -> 100124.13 | P67: =P65 + P60 -> 100127.52 | Q67: =Q65 + Q60 -> 100126.75 | ... EA67: =EA65 + EA60 -> 70000
E69: =Ops!E$124 -> Accounts payable balance | F69: =Ops!F$124 -> 0 | G69: =Ops!G$124 -> $ 000s | H69: =Ops!H$124 -> 0 | I69: =Ops!I$124 -> 0 | J69: =Ops!J$124 -> 0 | K69: =Ops!K$124 -> 0 | L69: =Ops!L$124 -> 0 | ... EA69: =Ops!EA$124 -> 0
E70: =Debt!E$30 -> Senior debt balance | F70: =Debt!F$30 -> 0 | G70: =Debt!G$30 -> $ 000s | H70: =Debt!H$30 -> 0 | I70: =Debt!I$30 -> 0 | J70: =Debt!J$30 -> 0 | K70: =Debt!K$30 -> 0 | L70: =Debt!L$30 -> 70000 | ... EA70: =Debt!EA$30 -> 70000
E71: [Refi facility balance]
E72: [RCF balance]
E73: =Equity!E$29 -> Share capital balance | F73: =Equity!F$29 -> 0 | G73: =Equity!G$29 -> $ 000s | H73: =Equity!H$29 -> 0 | I73: =Equity!I$29 -> 0 | J73: =Equity!J$29 -> 0 | K73: =Equity!K$29 -> 0 | L73: =Equity!L$29 -> 30000 | ... EA73: =Equity!EA$29 -> 0
E74: =Equity!E$41 -> Retained earnings balance | F74: =Equity!F$41 -> 0 | G74: =Equity!G$41 -> $ 000s | H74: =Equity!H$41 -> 0 | I74: =Equity!I$41 -> 0 | J74: =Equity!J$41 -> 0 | K74: =Equity!K$41 -> 0 | L74: =Equity!L$41 -> 0 | ... EA74: =Equity!EA$41 -> 0
E75: Total liabilities | G75: =SMU -> $ 000s | J75: =SUM(J69:J74) -> 0 | K75: =SUM(K69:K74) -> 0 | L75: =SUM(L69:L74) -> 100000 | M75: =SUM(M69:M74) -> 102429.64 | N75: =SUM(N69:N74) -> 101700.76 | O75: =SUM(O69:O74) -> 100124.13 | P75: =SUM(P69:P74) -> 100127.52 | Q75: =SUM(Q69:Q74) -> 100126.75 | ... EA75: =SUM(EA69:EA74) -> 70000
A78: BALANCE SHEET CHECK
E80: =E$67 -> Total assets | F80: =F$67 -> 0 | G80: =G$67 -> $ 000s | H80: =H$67 -> 0 | I80: =I$67 -> 0 | J80: =J$67 -> 0 | K80: =K$67 -> 0 | L80: =L$67 -> 100000 | ... EA80: =EA$67 -> 70000
E81: =E$75 -> Total liabilities | F81: =F$75 -> 0 | G81: =G$75 -> $ 000s | H81: =H$75 -> 0 | I81: =I$75 -> 0 | J81: =J$75 -> 0 | K81: =K$75 -> 0 | L81: =L$75 -> 100000 | ... EA81: =EA$75 -> 70000
E82: Balance sheet check | F82: =IF(SUM(J82:EA82) <> 0, 1, 0) -> 0 | G82: check | J82: =IF(ABS(J80 - J81) > CHK_TOL, 1, 0) -> 0 | K82: =IF(ABS(K80 - K81) > CHK_TOL, 1, 0) -> 0 | L82: =IF(ABS(L80 - L81) > CHK_TOL, 1, 0) -> 0 | M82: =IF(ABS(M80 - M81) > CHK_TOL, 1, 0) -> 0 | N82: =IF(ABS(N80 - N81) > CHK_TOL, 1, 0) -> 0 | O82: =IF(ABS(O80 - O81) > CHK_TOL, 1, 0) -> 0 | P82: =IF(ABS(P80 - P81) > CHK_TOL, 1, 0) -> 0 | Q82: =IF(ABS(Q80 - Q81) > CHK_TOL, 1, 0) -> 0 | ... EA82: =IF(ABS(EA80 - EA81) > CHK_TOL, 1, 0) -> 0
E83: Balance sheet difference | H83: =SUM(J83:EA83) -> 0 | J83: =J80 - J81 -> 0 | K83: =K80 - K81 -> 0 | L83: =L80 - L81 -> 0 | M83: =M80 - M81 -> 0 | N83: =N80 - N81 -> 0 | O83: =O80 - O81 -> 0 | P83: =P80 - P81 -> 0 | Q83: =Q80 - Q81 -> 0 | ... EA83: =EA80 - EA81 -> 0
A87: END

Sheet FS Ann
A1: =RIGHT(CELL("filename", A1), LEN(CELL("filename", A1)) - SEARCH("]", CELL("filename", A1))) & " - " & InpC!F3 -> FS Ann - Base case 1
E2: =Time!E$48 -> Model period ending - annual | F2: =Check!$F$9 -> 0 | G2: Error chks | J2: =Time!J$48 -> 43921 | K2: =Time!K$48 -> 44286 | L2: =Time!L$48 -> 44651 | M2: =Time!M$48 -> 45016 | N2: =Time!N$48 -> 45382 | O2: =Time!O$48 -> 45747 | P2: =Time!P$48 -> 46112 | Q2: =Time!Q$48 -> 46477 | ... AN2: =Time!AN$48 -> 54878
E3: =Time!E$53 -> Timeline label - annual | F3: =Output!J2 -> 0 | G3: Track chgs | J3: =Time!J$53 -> Pre-fcst | K3: =Time!K$53 -> Operations | L3: =Time!L$53 -> Operations | M3: =Time!M$53 -> Operations | N3: =Time!N$53 -> Operations | O3: =Time!O$53 -> Operations | P3: =Time!P$53 -> Operations | Q3: =Time!Q$53 -> Operations | ... AN3: =Time!AN$53 -> Post ops
E4: =Time!E$42 -> Contract year | F4: =Check!$F$21 -> 0 | G4: Alerts | J4: =YEAR(J2) -> 2020 | K4: =YEAR(K2) -> 2021 | L4: =YEAR(L2) -> 2022 | M4: =YEAR(M2) -> 2023 | N4: =YEAR(N2) -> 2024 | O4: =YEAR(O2) -> 2025 | P4: =YEAR(P2) -> 2026 | Q4: =YEAR(Q2) -> 2027 | ... AN4: =YEAR(AN2) -> 2050
E5: =Time!E$10 -> Model column counter | F5: Constant | G5: Unit | H5: Total | J5: =Time!J$10 -> 1 | K5: =Time!K$10 -> 2 | L5: =Time!L$10 -> 3 | M5: =Time!M$10 -> 4 | N5: =Time!N$10 -> 5 | O5: =Time!O$10 -> 6 | P5: =Time!P$10 -> 7 | Q5: =Time!Q$10 -> 8 | ... AN5: =Time!AN$10 -> 31
A7: INCOME STATEMENT
E9: ='FS Qtr'!E9 -> Electricity revenue | F9: ='FS Qtr'!F9 -> 0 | G9: ='FS Qtr'!G9 -> $ 000s | H9: =SUM(J9:AN9) -> 371409.68 | J9: =SUMIFS('FS Qtr'!$J9:$EA9, 'FS Qtr'!$J$4:$EA$4, 'FS Ann'!J$4) -> 0 | K9: =SUMIFS('FS Qtr'!$J9:$EA9, 'FS Qtr'!$J$4:$EA$4, 'FS Ann'!K$4) -> 15762.5 | L9: =SUMIFS('FS Qtr'!$J9:$EA9, 'FS Qtr'!$J$4:$EA$4, 'FS Ann'!L$4) -> 15684.08 | M9: =SUMIFS('FS Qtr'!$J9:$EA9, 'FS Qtr'!$J$4:$EA$4, 'FS Ann'!M$4) -> 15606.049 | N9: =SUMIFS('FS Qtr'!$J9:$EA9, 'FS Qtr'!$J$4:$EA$4, 'FS Ann'!N$4) -> 15528.407 | O9: =SUMIFS('FS Qtr'!$J9:$EA9, 'FS Qtr'!$J$4:$EA$4, 'FS Ann'!O$4) -> 15451.152 | P9: =SUMIFS('FS Qtr'!$J9:$EA9, 'FS Qtr'!$J$4:$EA$4, 'FS Ann'!P$4) -> 15374.28 | Q9: =SUMIFS('FS Qtr'!$J9:$EA9, 'FS Qtr'!$J$4:$EA$4, 'FS Ann'!Q$4) -> 15297.791 | ... AN9: =SUMIFS('FS Qtr'!$J9:$EA9, 'FS Qtr'!$J$4:$EA$4, 'FS Ann'!AN$4) -> 0
E10: ='FS Qtr'!E10 -> O&M cost | F10: ='FS Qtr'!F10 -> 0 | G10: ='FS Qtr'!G10 -> $ 000s | H10: =SUM(J10:AN10) -> -48742.638 | J10: =SUMIFS('FS Qtr'!$J10:$EA10, 'FS Qtr'!$J$4:$EA$4, 'FS Ann'!J$4) -> 0 | K10: =SUMIFS('FS Qtr'!$J10:$EA10, 'FS Qtr'!$J$4:$EA$4, 'FS Ann'!K$4) -> -1518.844 | L10: =SUMIFS('FS Qtr'!$J10:$EA10, 'FS Qtr'!$J$4:$EA$4, 'FS Ann'!L$4) -> -1549.4495 | M10: =SUMIFS('FS Qtr'!$J10:$EA10, 'FS Qtr'!$J$4:$EA$4, 'FS Ann'!M$4) -> -1580.6716 | N10: =SUMIFS('FS Qtr'!$J10:$EA10, 'FS Qtr'!$J$4:$EA$4, 'FS Ann'!N$4) -> -1612.523 | O10: =SUMIFS('FS Qtr'!$J10:$EA10, 'FS Qtr'!$J$4:$EA$4, 'FS Ann'!O$4) -> -1645.0161 | P10: =SUMIFS('FS Qtr'!$J10:$EA10, 'FS Qtr'!$J$4:$EA$4, 'FS Ann'!P$4) -> -1678.164 | Q10: =SUMIFS('FS Qtr'!$J10:$EA10, 'FS Qtr'!$J$4:$EA$4, 'FS Ann'!Q$4) -> -1711.9798 | ... AN10: =SUMIFS('FS Qtr'!$J10:$EA10, 'FS Qtr'!$J$4:$EA$4, 'FS Ann'!AN$4) -> 0
E11: EBITDA | G11: =SMU -> $ 000s | H11: =SUM(J11:AN11) -> 322667.04 | J11: =SUM(J9:J10) -> 0 | K11: =SUM(K9:K10) -> 14243.656 | L11: =SUM(L9:L10) -> 14134.63 | M11: =SUM(M9:M10) -> 14025.378 | N11: =SUM(N9:N10) -> 13915.884 | O11: =SUM(O9:O10) -> 13806.135 | P11: =SUM(P9:P10) -> 13696.116 | Q11: =SUM(Q9:Q10) -> 13585.811 | ... AN11: =SUM(AN9:AN10) -> 0
E13: ='FS Qtr'!E13 -> Depreciation of fixed asset | F13: ='FS Qtr'!F13 -> 0 | G13: ='FS Qtr'!G13 -> $ 000s | H13: =SUM(J13:AN13) -> -100000 | J13: =SUMIFS('FS Qtr'!$J13:$EA13, 'FS Qtr'!$J$4:$EA$4, 'FS Ann'!J$4) -> 0 | K13: =SUMIFS('FS Qtr'!$J13:$EA13, 'FS Qtr'!$J$4:$EA$4, 'FS Ann'!K$4) -> -4000 | L13: =SUMIFS('FS Qtr'!$J13:$EA13, 'FS Qtr'!$J$4:$EA$4, 'FS Ann'!L$4) -> -4000 | M13: =SUMIFS('FS Qtr'!$J13:$EA13, 'FS Qtr'!$J$4:$EA$4, 'FS Ann'!M$4) -> -4000 | N13: =SUMIFS('FS Qtr'!$J13:$EA13, 'FS Qtr'!$J$4:$EA$4, 'FS Ann'!N$4) -> -4000 | O13: =SUMIFS('FS Qtr'!$J13:$EA13, 'FS Qtr'!$J$4:$EA$4, 'FS Ann'!O$4) -> -4000 | P13: =SUMIFS('FS Qtr'!$J13:$EA13, 'FS Qtr'!$J$4:$EA$4, 'FS Ann'!P$4) -> -4000 | Q13: =SUMIFS('FS Qtr'!$J13:$EA13, 'FS Qtr'!$J$4:$EA$4, 'FS Ann'!Q$4) -> -4000 | ... AN13: =SUMIFS('FS Qtr'!$J13:$EA13, 'FS Qtr'!$J$4:$EA$4, 'FS Ann'!AN$4) -> 0
E14: EBIT | G14: =SMU -> $ 000s | H14: =SUM(J14:AN14) -> 222667.04 | J14: =J11 + J13 -> 0 | K14: =K11 + K13 -> 10243.656 | L14: =L11 + L13 -> 10134.63 | M14: =M11 + M13 -> 10025.378 | N14: =N11 + N13 -> 9915.8844 | O14: =O11 + O13 -> 9806.1355 | P14: =P11 + P13 -> 9696.1162 | Q14: =Q11 + Q13 -> 9585.8114 | ... AN14: =AN11 + AN13 -> 0
E16: ='FS Qtr'!E16 -> [Senior debt interest] | F16: ='FS Qtr'!F16 -> 0 | G16: ='FS Qtr'!G16 -> 0 | H16: =SUM(J16:AN16) -> 0 | J16: =SUMIFS('FS Qtr'!$J16:$EA16, 'FS Qtr'!$J$4:$EA$4, 'FS Ann'!J$4) -> 0 | K16: =SUMIFS('FS Qtr'!$J16:$EA16, 'FS Qtr'!$J$4:$EA$4, 'FS Ann'!K$4) -> 0 | L16: =SUMIFS('FS Qtr'!$J16:$EA16, 'FS Qtr'!$J$4:$EA$4, 'FS Ann'!L$4) -> 0 | M16: =SUMIFS('FS Qtr'!$J16:$EA16, 'FS Qtr'!$J$4:$EA$4, 'FS Ann'!M$4) -> 0 | N16: =SUMIFS('FS Qtr'!$J16:$EA16, 'FS Qtr'!$J$4:$EA$4, 'FS Ann'!N$4) -> 0 | O16: =SUMIFS('FS Qtr'!$J16:$EA16, 'FS Qtr'!$J$4:$EA$4, 'FS Ann'!O$4) -> 0 | P16: =SUMIFS('FS Qtr'!$J16:$EA16, 'FS Qtr'!$J$4:$EA$4, 'FS Ann'!P$4) -> 0 | Q16: =SUMIFS('FS Qtr'!$J16:$EA16, 'FS Qtr'!$J$4:$EA$4, 'FS Ann'!Q$4) -> 0 | ... AN16: =SUMIFS('FS Qtr'!$J16:$EA16, 'FS Qtr'!$J$4:$EA$4, 'FS Ann'!AN$4) -> 0
E17: ='FS Qtr'!E17 -> [Refi facility interest] | F17: ='FS Qtr'!F17 -> 0 | G17: ='FS Qtr'!G17 -> 0 | H17: =SUM(J17:AN17) -> 0 | J17: =SUMIFS('FS Qtr'!$J17:$EA17, 'FS Qtr'!$J$4:$EA$4, 'FS Ann'!J$4) -> 0 | K17: =SUMIFS('FS Qtr'!$J17:$EA17, 'FS Qtr'!$J$4:$EA$4, 'FS Ann'!K$4) -> 0 | L17: =SUMIFS('FS Qtr'!$J17:$EA17, 'FS Qtr'!$J$4:$EA$4, 'FS Ann'!L$4) -> 0 | M17: =SUMIFS('FS Qtr'!$J17:$EA17, 'FS Qtr'!$J$4:$EA$4, 'FS Ann'!M$4) -> 0 | N17: =SUMIFS('FS Qtr'!$J17:$EA17, 'FS Qtr'!$J$4:$EA$4, 'FS Ann'!N$4) -> 0 | O17: =SUMIFS('FS Qtr'!$J17:$EA17, 'FS Qtr'!$J$4:$EA$4, 'FS Ann'!O$4) -> 0 | P17: =SUMIFS('FS Qtr'!$J17:$EA17, 'FS Qtr'!$J$4:$EA$4, 'FS Ann'!P$4) -> 0 | Q17: =SUMIFS('FS Qtr'!$J17:$EA17, 'FS Qtr'!$J$4:$EA$4, 'FS Ann'!Q$4) -> 0 | ... AN17: =SUMIFS('FS Qtr'!$J17:$EA17, 'FS Qtr'!$J$4:$EA$4, 'FS Ann'!AN$4) -> 0
E18: ='FS Qtr'!E18 -> [RCF interest expense] | F18: ='FS Qtr'!F18 -> 0 | G18: ='FS Qtr'!G18 -> 0 | H18: =SUM(J18:AN18) -> 0 | J18: =SUMIFS('FS Qtr'!$J18:$EA18, 'FS Qtr'!$J$4:$EA$4, 'FS Ann'!J$4) -> 0 | K18: =SUMIFS('FS Qtr'!$J18:$EA18, 'FS Qtr'!$J$4:$EA$4, 'FS Ann'!K$4) -> 0 | L18: =SUMIFS('FS Qtr'!$J18:$EA18, 'FS Qtr'!$J$4:$EA$4, 'FS Ann'!L$4) -> 0 | M18: =SUMIFS('FS Qtr'!$J18:$EA18, 'FS Qtr'!$J$4:$EA$4, 'FS Ann'!M$4) -> 0 | N18: =SUMIFS('FS Qtr'!$J18:$EA18, 'FS Qtr'!$J$4:$EA$4, 'FS Ann'!N$4) -> 0 | O18: =SUMIFS('FS Qtr'!$J18:$EA18, 'FS Qtr'!$J$4:$EA$4, 'FS Ann'!O$4) -> 0 | P18: =SUMIFS('FS Qtr'!$J18:$EA18, 'FS Qtr'!$J$4:$EA$4, 'FS Ann'!P$4) -> 0 | Q18: =SUMIFS('FS Qtr'!$J18:$EA18, 'FS Qtr'!$J$4:$EA$4, 'FS Ann'!Q$4) -> 0 | ... AN18: =SUMIFS('FS Qtr'!$J18:$EA18, 'FS Qtr'!$J$4:$EA$4, 'FS Ann'!AN$4) -> 0
E19: EBT | G19: =SMU -> $ 000s | H19: =SUM(J19:AN19) -> 222667.04 | J19: =J14 + SUM(J16:J18) -> 0 | K19: =K14 + SUM(K16:K18) -> 10243.656 | L19: =L14 + SUM(L16:L18) -> 10134.63 | M19: =M14 + SUM(M16:M18) -> 10025.378 | N19: =N14 + SUM(N16:N18) -> 9915.8844 | O19: =O14 + SUM(O16:O18) -> 9806.1355 | P19: =P14 + SUM(P16:P18) -> 9696.1162 | Q19: =Q14 + SUM(Q16:Q18) -> 9585.8114 | ... AN19: =AN14 + SUM(AN16:AN18) -> 0
E21: ='FS Qtr'!E21 -> [Corporate income tax expense] | F21: ='FS Qtr'!F21 -> 0 | G21: ='FS Qtr'!G21 -> 0 | H21: =SUM(J21:AN21) -> 0 | J21: =SUMIFS('FS Qtr'!$J21:$EA21, 'FS Qtr'!$J$4:$EA$4, 'FS Ann'!J$4) -> 0 | K21: =SUMIFS('FS Qtr'!$J21:$EA21, 'FS Qtr'!$J$4:$EA$4, 'FS Ann'!K$4) -> 0 | L21: =SUMIFS('FS Qtr'!$J21:$EA21, 'FS Qtr'!$J$4:$EA$4, 'FS Ann'!L$4) -> 0 | M21: =SUMIFS('FS Qtr'!$J21:$EA21, 'FS Qtr'!$J$4:$EA$4, 'FS Ann'!M$4) -> 0 | N21: =SUMIFS('FS Qtr'!$J21:$EA21, 'FS Qtr'!$J$4:$EA$4, 'FS Ann'!N$4) -> 0 | O21: =SUMIFS('FS Qtr'!$J21:$EA21, 'FS Qtr'!$J$4:$EA$4, 'FS Ann'!O$4) -> 0 | P21: =SUMIFS('FS Qtr'!$J21:$EA21, 'FS Qtr'!$J$4:$EA$4, 'FS Ann'!P$4) -> 0 | Q21: =SUMIFS('FS Qtr'!$J21:$EA21, 'FS Qtr'!$J$4:$EA$4, 'FS Ann'!Q$4) -> 0 | ... AN21: =SUMIFS('FS Qtr'!$J21:$EA21, 'FS Qtr'!$J$4:$EA$4, 'FS Ann'!AN$4) -> 0
E22: EBT | G22: =SMU -> $ 000s | H22: =SUM(J22:AN22) -> 222667.04 | J22: =J19 + J21 -> 0 | K22: =K19 + K21 -> 10243.656 | L22: =L19 + L21 -> 10134.63 | M22: =M19 + M21 -> 10025.378 | N22: =N19 + N21 -> 9915.8844 | O22: =O19 + O21 -> 9806.1355 | P22: =P19 + P21 -> 9696.1162 | Q22: =Q19 + Q21 -> 9585.8114 | ... AN22: =AN19 + AN21 -> 0
E24: ='FS Qtr'!E24 -> Dividends paid | F24: ='FS Qtr'!F24 -> 0 | G24: ='FS Qtr'!G24 -> $ 000s | H24: =SUM(J24:AN24) -> -222667.04 | J24: =SUMIFS('FS Qtr'!$J24:$EA24, 'FS Qtr'!$J$4:$EA$4, 'FS Ann'!J$4) -> 0 | K24: =SUMIFS('FS Qtr'!$J24:$EA24, 'FS Qtr'!$J$4:$EA$4, 'FS Ann'!K$4) -> -10243.656 | L24: =SUMIFS('FS Qtr'!$J24:$EA24, 'FS Qtr'!$J$4:$EA$4, 'FS Ann'!L$4) -> -10134.63 | M24: =SUMIFS('FS Qtr'!$J24:$EA24, 'FS Qtr'!$J$4:$EA$4, 'FS Ann'!M$4) -> -10025.378 | N24: =SUMIFS('FS Qtr'!$J24:$EA24, 'FS Qtr'!$J$4:$EA$4, 'FS Ann'!N$4) -> -9915.8844 | O24: =SUMIFS('FS Qtr'!$J24:$EA24, 'FS Qtr'!$J$4:$EA$4, 'FS Ann'!O$4) -> -9806.1355 | P24: =SUMIFS('FS Qtr'!$J24:$EA24, 'FS Qtr'!$J$4:$EA$4, 'FS Ann'!P$4) -> -9696.1162 | Q24: =SUMIFS('FS Qtr'!$J24:$EA24, 'FS Qtr'!$J$4:$EA$4, 'FS Ann'!Q$4) -> -9585.8114 | ... AN24: =SUMIFS('FS Qtr'!$J24:$EA24, 'FS Qtr'!$J$4:$EA$4, 'FS Ann'!AN$4) -> 0
E25: Net income | G25: =SMU -> $ 000s | H25: =SUM(J25:AN25) -> 0 | J25: =J22 + J24 -> 0 | K25: =K22 + K24 -> 0 | L25: =L22 + L24 -> 0 | M25: =M22 + M24 -> 0 | N25: =N22 + N24 -> 0 | O25: =O22 + O24 -> 0 | P25: =P22 + P24 -> 0 | Q25: =Q22 + Q24 -> 0 | ... AN25: =AN22 + AN24 -> 0
A28: CASH FLOW STATEMENT
E30: ='FS Qtr'!E30 -> Cash received from invoices | F30: ='FS Qtr'!F30 -> 0 | G30: ='FS Qtr'!G30 -> $ 000s | H30: =SUM(J30:AN30) -> 371409.68 | J30: =SUMIFS('FS Qtr'!$J30:$EA30, 'FS Qtr'!$J$4:$EA$4, 'FS Ann'!J$4) -> 0 | K30: =SUMIFS('FS Qtr'!$J30:$EA30, 'FS Qtr'!$J$4:$EA$4, 'FS Ann'!K$4) -> 14133.708 | L30: =SUMIFS('FS Qtr'!$J30:$EA30, 'FS Qtr'!$J$4:$EA$4, 'FS Ann'!L$4) -> 15692.183 | M30: =SUMIFS('FS Qtr'!$J30:$EA30, 'FS Qtr'!$J$4:$EA$4, 'FS Ann'!M$4) -> 15631.834 | N30: =SUMIFS('FS Qtr'!$J30:$EA30, 'FS Qtr'!$J$4:$EA$4, 'FS Ann'!N$4) -> 15518.709 | O30: =SUMIFS('FS Qtr'!$J30:$EA30, 'FS Qtr'!$J$4:$EA$4, 'FS Ann'!O$4) -> 15459.135 | P30: =SUMIFS('FS Qtr'!$J30:$EA30, 'FS Qtr'!$J$4:$EA$4, 'FS Ann'!P$4) -> 15382.224 | Q30: =SUMIFS('FS Qtr'!$J30:$EA30, 'FS Qtr'!$J$4:$EA$4, 'FS Ann'!Q$4) -> 15323.066 | ... AN30: =SUMIFS('FS Qtr'!$J30:$EA30, 'FS Qtr'!$J$4:$EA$4, 'FS Ann'!AN$4) -> 0
E31: ='FS Qtr'!E31 -> Cash paid for operating costs | F31: ='FS Qtr'!F31 -> 0 | G31: ='FS Qtr'!G31 -> $ 000s | H31: =SUM(J31:AN31) -> -48742.638 | J31: =SUMIFS('FS Qtr'!$J31:$EA31, 'FS Qtr'!$J$4:$EA$4, 'FS Ann'!J$4) -> 0 | K31: =SUMIFS('FS Qtr'!$J31:$EA31, 'FS Qtr'!$J$4:$EA$4, 'FS Ann'!K$4) -> -1391.3252 | L31: =SUMIFS('FS Qtr'!$J31:$EA31, 'FS Qtr'!$J$4:$EA$4, 'FS Ann'!L$4) -> -1546.8799 | M31: =SUMIFS('FS Qtr'!$J31:$EA31, 'FS Qtr'!$J$4:$EA$4, 'FS Ann'!M$4) -> -1579.5086 | N31: =SUMIFS('FS Qtr'!$J31:$EA31, 'FS Qtr'!$J$4:$EA$4, 'FS Ann'!N$4) -> -1608.3904 | O31: =SUMIFS('FS Qtr'!$J31:$EA31, 'FS Qtr'!$J$4:$EA$4, 'FS Ann'!O$4) -> -1642.288 | P31: =SUMIFS('FS Qtr'!$J31:$EA31, 'FS Qtr'!$J$4:$EA$4, 'FS Ann'!P$4) -> -1675.381 | Q31: =SUMIFS('FS Qtr'!$J31:$EA31, 'FS Qtr'!$J$4:$EA$4, 'FS Ann'!Q$4) -> -1710.7202 | ... AN31: =SUMIFS('FS Qtr'!$J31:$EA31, 'FS Qtr'!$J$4:$EA$4, 'FS Ann'!AN$4) -> 0
E32: ='FS Qtr'!E32 -> [Corporate income tax expense] | F32: ='FS Qtr'!F32 -> 0 | G32: ='FS Qtr'!G32 -> 0 | H32: =SUM(J32:AN32) -> 0 | J32: =SUMIFS('FS Qtr'!$J32:$EA32, 'FS Qtr'!$J$4:$EA$4, 'FS Ann'!J$4) -> 0 | K32: =SUMIFS('FS Qtr'!$J32:$EA32, 'FS Qtr'!$J$4:$EA$4, 'FS Ann'!K$4) -> 0 | L32: =SUMIFS('FS Qtr'!$J32:$EA32, 'FS Qtr'!$J$4:$EA$4, 'FS Ann'!L$4) -> 0 | M32: =SUMIFS('FS Qtr'!$J32:$EA32, 'FS Qtr'!$J$4:$EA$4, 'FS Ann'!M$4) -> 0 | N32: =SUMIFS('FS Qtr'!$J32:$EA32, 'FS Qtr'!$J$4:$EA$4, 'FS Ann'!N$4) -> 0 | O32: =SUMIFS('FS Qtr'!$J32:$EA32, 'FS Qtr'!$J$4:$EA$4, 'FS Ann'!O$4) -> 0 | P32: =SUMIFS('FS Qtr'!$J32:$EA32, 'FS Qtr'!$J$4:$EA$4, 'FS Ann'!P$4) -> 0 | Q32: =SUMIFS('FS Qtr'!$J32:$EA32, 'FS Qtr'!$J$4:$EA$4, 'FS Ann'!Q$4) -> 0 | ... AN32: =SUMIFS('FS Qtr'!$J32:$EA32, 'FS Qtr'!$J$4:$EA$4, 'FS Ann'!AN$4) -> 0
E33: Cash flow available for debt service | G33: =SMU -> $ 000s | H33: =SUM(J33:AN33) -> 322667.04 | J33: =SUM(J30:J32) -> 0 | K33: =SUM(K30:K32) -> 12742.383 | L33: =SUM(L30:L32) -> 14145.303 | M33: =SUM(M30:M32) -> 14052.325 | N33: =SUM(N30:N32) -> 13910.319 | O33: =SUM(O30:O32) -> 13816.847 | P33: =SUM(P30:P32) -> 13706.843 | Q33: =SUM(Q30:Q32) -> 13612.346 | ... AN33: =SUM(AN30:AN32) -> 0
E35: ='FS Qtr'!E35 -> [Senior debt interest] | F35: ='FS Qtr'!F35 -> 0 | G35: ='FS Qtr'!G35 -> 0 | H35: =SUM(J35:AN35) -> 0 | J35: =SUMIFS('FS Qtr'!$J35:$EA35, 'FS Qtr'!$J$4:$EA$4, 'FS Ann'!J$4) -> 0 | K35: =SUMIFS('FS Qtr'!$J35:$EA35, 'FS Qtr'!$J$4:$EA$4, 'FS Ann'!K$4) -> 0 | L35: =SUMIFS('FS Qtr'!$J35:$EA35, 'FS Qtr'!$J$4:$EA$4, 'FS Ann'!L$4) -> 0 | M35: =SUMIFS('FS Qtr'!$J35:$EA35, 'FS Qtr'!$J$4:$EA$4, 'FS Ann'!M$4) -> 0 | N35: =SUMIFS('FS Qtr'!$J35:$EA35, 'FS Qtr'!$J$4:$EA$4, 'FS Ann'!N$4) -> 0 | O35: =SUMIFS('FS Qtr'!$J35:$EA35, 'FS Qtr'!$J$4:$EA$4, 'FS Ann'!O$4) -> 0 | P35: =SUMIFS('FS Qtr'!$J35:$EA35, 'FS Qtr'!$J$4:$EA$4, 'FS Ann'!P$4) -> 0 | Q35: =SUMIFS('FS Qtr'!$J35:$EA35, 'FS Qtr'!$J$4:$EA$4, 'FS Ann'!Q$4) -> 0 | ... AN35: =SUMIFS('FS Qtr'!$J35:$EA35, 'FS Qtr'!$J$4:$EA$4, 'FS Ann'!AN$4) -> 0
E36: ='FS Qtr'!E36 -> [Senior debt repayment] | F36: ='FS Qtr'!F36 -> 0 | G36: ='FS Qtr'!G36 -> 0 | H36: =SUM(J36:AN36) -> 0 | J36: =SUMIFS('FS Qtr'!$J36:$EA36, 'FS Qtr'!$J$4:$EA$4, 'FS Ann'!J$4) -> 0 | K36: =SUMIFS('FS Qtr'!$J36:$EA36, 'FS Qtr'!$J$4:$EA$4, 'FS Ann'!K$4) -> 0 | L36: =SUMIFS('FS Qtr'!$J36:$EA36, 'FS Qtr'!$J$4:$EA$4, 'FS Ann'!L$4) -> 0 | M36: =SUMIFS('FS Qtr'!$J36:$EA36, 'FS Qtr'!$J$4:$EA$4, 'FS Ann'!M$4) -> 0 | N36: =SUMIFS('FS Qtr'!$J36:$EA36, 'FS Qtr'!$J$4:$EA$4, 'FS Ann'!N$4) -> 0 | O36: =SUMIFS('FS Qtr'!$J36:$EA36, 'FS Qtr'!$J$4:$EA$4, 'FS Ann'!O$4) -> 0 | P36: =SUMIFS('FS Qtr'!$J36:$EA36, 'FS Qtr'!$J$4:$EA$4, 'FS Ann'!P$4) -> 0 | Q36: =SUMIFS('FS Qtr'!$J36:$EA36, 'FS Qtr'!$J$4:$EA$4, 'FS Ann'!Q$4) -> 0 | ... AN36: =SUMIFS('FS Qtr'!$J36:$EA36, 'FS Qtr'!$J$4:$EA$4, 'FS Ann'!AN$4) -> 0
E37: Cash flow available for refinancing facility | G37: =SMU -> $ 000s | H37: =SUM(J37:AN37) -> 322667.04 | J37: =J33 + SUM(J35:J36) -> 0 | K37: =K33 + SUM(K35:K36) -> 12742.383 | L37: =L33 + SUM(L35:L36) -> 14145.303 | M37: =M33 + SUM(M35:M36) -> 14052.325 | N37: =N33 + SUM(N35:N36) -> 13910.319 | O37: =O33 + SUM(O35:O36) -> 13816.847 | P37: =P33 + SUM(P35:P36) -> 13706.843 | Q37: =Q33 + SUM(Q35:Q36) -> 13612.346 | ... AN37: =AN33 + SUM(AN35:AN36) -> 0
E39: ='FS Qtr'!E40 -> [Refi facility repayment] | F39: ='FS Qtr'!F40 -> 0 | G39: ='FS Qtr'!G40 -> 0 | H39: =SUM(J39:AN39) -> 0 | J39: =SUMIFS('FS Qtr'!$J40:$EA40, 'FS Qtr'!$J$4:$EA$4, 'FS Ann'!J$4) -> 0 | K39: =SUMIFS('FS Qtr'!$J40:$EA40, 'FS Qtr'!$J$4:$EA$4, 'FS Ann'!K$4) -> 0 | L39: =SUMIFS('FS Qtr'!$J40:$EA40, 'FS Qtr'!$J$4:$EA$4, 'FS Ann'!L$4) -> 0 | M39: =SUMIFS('FS Qtr'!$J40:$EA40, 'FS Qtr'!$J$4:$EA$4, 'FS Ann'!M$4) -> 0 | N39: =SUMIFS('FS Qtr'!$J40:$EA40, 'FS Qtr'!$J$4:$EA$4, 'FS Ann'!N$4) -> 0 | O39: =SUMIFS('FS Qtr'!$J40:$EA40, 'FS Qtr'!$J$4:$EA$4, 'FS Ann'!O$4) -> 0 | P39: =SUMIFS('FS Qtr'!$J40:$EA40, 'FS Qtr'!$J$4:$EA$4, 'FS Ann'!P$4) -> 0 | Q39: =SUMIFS('FS Qtr'!$J40:$EA40, 'FS Qtr'!$J$4:$EA$4, 'FS Ann'!Q$4) -> 0 | ... AN39: =SUMIFS('FS Qtr'!$J40:$EA40, 'FS Qtr'!$J$4:$EA$4, 'FS Ann'!AN$4) -> 0
E40: ='FS Qtr'!E41 -> [Refi facility interest] | F40: ='FS Qtr'!F41 -> 0 | G40: ='FS Qtr'!G41 -> 0 | H40: =SUM(J40:AN40) -> 0 | J40: =SUMIFS('FS Qtr'!$J41:$EA41, 'FS Qtr'!$J$4:$EA$4, 'FS Ann'!J$4) -> 0 | K40: =SUMIFS('FS Qtr'!$J41:$EA41, 'FS Qtr'!$J$4:$EA$4, 'FS Ann'!K$4) -> 0 | L40: =SUMIFS('FS Qtr'!$J41:$EA41, 'FS Qtr'!$J$4:$EA$4, 'FS Ann'!L$4) -> 0 | M40: =SUMIFS('FS Qtr'!$J41:$EA41, 'FS Qtr'!$J$4:$EA$4, 'FS Ann'!M$4) -> 0 | N40: =SUMIFS('FS Qtr'!$J41:$EA41, 'FS Qtr'!$J$4:$EA$4, 'FS Ann'!N$4) -> 0 | O40: =SUMIFS('FS Qtr'!$J41:$EA41, 'FS Qtr'!$J$4:$EA$4, 'FS Ann'!O$4) -> 0 | P40: =SUMIFS('FS Qtr'!$J41:$EA41, 'FS Qtr'!$J$4:$EA$4, 'FS Ann'!P$4) -> 0 | Q40: =SUMIFS('FS Qtr'!$J41:$EA41, 'FS Qtr'!$J$4:$EA$4, 'FS Ann'!Q$4) -> 0 | ... AN40: =SUMIFS('FS Qtr'!$J41:$EA41, 'FS Qtr'!$J$4:$EA$4, 'FS Ann'!AN$4) -> 0
E41: Cash flow available for revolving credit facility | G41: =SMU -> $ 000s | H41: =SUM(J41:AN41) -> 322667.04 | J41: =J37 + SUM(J39:J40) -> 0 | K41: =K37 + SUM(K39:K40) -> 12742.383 | L41: =L37 + SUM(L39:L40) -> 14145.303 | M41: =M37 + SUM(M39:M40) -> 14052.325 | N41: =N37 + SUM(N39:N40) -> 13910.319 | O41: =O37 + SUM(O39:O40) -> 13816.847 | P41: =P37 + SUM(P39:P40) -> 13706.843 | Q41: =Q37 + SUM(Q39:Q40) -> 13612.346 | ... AN41: =AN37 + SUM(AN39:AN40) -> 0
E43: ='FS Qtr'!E44 -> [RCF drawdown] | F43: ='FS Qtr'!F44 -> 0 | G43: ='FS Qtr'!G44 -> 0 | H43: =SUM(J43:AN43) -> 0 | J43: =SUMIFS('FS Qtr'!$J44:$EA44, 'FS Qtr'!$J$4:$EA$4, 'FS Ann'!J$4) -> 0 | K43: =SUMIFS('FS Qtr'!$J44:$EA44, 'FS Qtr'!$J$4:$EA$4, 'FS Ann'!K$4) -> 0 | L43: =SUMIFS('FS Qtr'!$J44:$EA44, 'FS Qtr'!$J$4:$EA$4, 'FS Ann'!L$4) -> 0 | M43: =SUMIFS('FS Qtr'!$J44:$EA44, 'FS Qtr'!$J$4:$EA$4, 'FS Ann'!M$4) -> 0 | N43: =SUMIFS('FS Qtr'!$J44:$EA44, 'FS Qtr'!$J$4:$EA$4, 'FS Ann'!N$4) -> 0 | O43: =SUMIFS('FS Qtr'!$J44:$EA44, 'FS Qtr'!$J$4:$EA$4, 'FS Ann'!O$4) -> 0 | P43: =SUMIFS('FS Qtr'!$J44:$EA44, 'FS Qtr'!$J$4:$EA$4, 'FS Ann'!P$4) -> 0 | Q43: =SUMIFS('FS Qtr'!$J44:$EA44, 'FS Qtr'!$J$4:$EA$4, 'FS Ann'!Q$4) -> 0 | ... AN43: =SUMIFS('FS Qtr'!$J44:$EA44, 'FS Qtr'!$J$4:$EA$4, 'FS Ann'!AN$4) -> 0
E44: ='FS Qtr'!E45 -> [RCF repayment] | F44: ='FS Qtr'!F45 -> 0 | G44: ='FS Qtr'!G45 -> 0 | H44: =SUM(J44:AN44) -> 0 | J44: =SUMIFS('FS Qtr'!$J45:$EA45, 'FS Qtr'!$J$4:$EA$4, 'FS Ann'!J$4) -> 0 | K44: =SUMIFS('FS Qtr'!$J45:$EA45, 'FS Qtr'!$J$4:$EA$4, 'FS Ann'!K$4) -> 0 | L44: =SUMIFS('FS Qtr'!$J45:$EA45, 'FS Qtr'!$J$4:$EA$4, 'FS Ann'!L$4) -> 0 | M44: =SUMIFS('FS Qtr'!$J45:$EA45, 'FS Qtr'!$J$4:$EA$4, 'FS Ann'!M$4) -> 0 | N44: =SUMIFS('FS Qtr'!$J45:$EA45, 'FS Qtr'!$J$4:$EA$4, 'FS Ann'!N$4) -> 0 | O44: =SUMIFS('FS Qtr'!$J45:$EA45, 'FS Qtr'!$J$4:$EA$4, 'FS Ann'!O$4) -> 0 | P44: =SUMIFS('FS Qtr'!$J45:$EA45, 'FS Qtr'!$J$4:$EA$4, 'FS Ann'!P$4) -> 0 | Q44: =SUMIFS('FS Qtr'!$J45:$EA45, 'FS Qtr'!$J$4:$EA$4, 'FS Ann'!Q$4) -> 0 | ... AN44: =SUMIFS('FS Qtr'!$J45:$EA45, 'FS Qtr'!$J$4:$EA$4, 'FS Ann'!AN$4) -> 0
E45: ='FS Qtr'!E46 -> [RCF interest expense paid] | F45: ='FS Qtr'!F46 -> 0 | G45: ='FS Qtr'!G46 -> 0 | H45: =SUM(J45:AN45) -> 0 | J45: =SUMIFS('FS Qtr'!$J46:$EA46, 'FS Qtr'!$J$4:$EA$4, 'FS Ann'!J$4) -> 0 | K45: =SUMIFS('FS Qtr'!$J46:$EA46, 'FS Qtr'!$J$4:$EA$4, 'FS Ann'!K$4) -> 0 | L45: =SUMIFS('FS Qtr'!$J46:$EA46, 'FS Qtr'!$J$4:$EA$4, 'FS Ann'!L$4) -> 0 | M45: =SUMIFS('FS Qtr'!$J46:$EA46, 'FS Qtr'!$J$4:$EA$4, 'FS Ann'!M$4) -> 0 | N45: =SUMIFS('FS Qtr'!$J46:$EA46, 'FS Qtr'!$J$4:$EA$4, 'FS Ann'!N$4) -> 0 | O45: =SUMIFS('FS Qtr'!$J46:$EA46, 'FS Qtr'!$J$4:$EA$4, 'FS Ann'!O$4) -> 0 | P45: =SUMIFS('FS Qtr'!$J46:$EA46, 'FS Qtr'!$J$4:$EA$4, 'FS Ann'!P$4) -> 0 | Q45: =SUMIFS('FS Qtr'!$J46:$EA46, 'FS Qtr'!$J$4:$EA$4, 'FS Ann'!Q$4) -> 0 | ... AN45: =SUMIFS('FS Qtr'!$J46:$EA46, 'FS Qtr'!$J$4:$EA$4, 'FS Ann'!AN$4) -> 0
E46: Cash available for shareholders | G46: =SMU -> $ 000s | H46: =SUM(J46:AN46) -> 322667.04 | J46: =J41 + SUM(J43:J45) -> 0 | K46: =K41 + SUM(K43:K45) -> 12742.383 | L46: =L41 + SUM(L43:L45) -> 14145.303 | M46: =M41 + SUM(M43:M45) -> 14052.325 | N46: =N41 + SUM(N43:N45) -> 13910.319 | O46: =O41 + SUM(O43:O45) -> 13816.847 | P46: =P41 + SUM(P43:P45) -> 13706.843 | Q46: =Q41 + SUM(Q43:Q45) -> 13612.346 | ... AN46: =AN41 + SUM(AN43:AN45) -> 0
E48: ='FS Qtr'!E49 -> Share capital redemption | F48: ='FS Qtr'!F49 -> 0 | G48: ='FS Qtr'!G49 -> $ 000s | H48: =SUM(J48:AN48) -> -30000 | J48: =SUMIFS('FS Qtr'!$J49:$EA49, 'FS Qtr'!$J$4:$EA$4, 'FS Ann'!J$4) -> 0 | K48: =SUMIFS('FS Qtr'!$J49:$EA49, 'FS Qtr'!$J$4:$EA$4, 'FS Ann'!K$4) -> 0 | L48: =SUMIFS('FS Qtr'!$J49:$EA49, 'FS Qtr'!$J$4:$EA$4, 'FS Ann'!L$4) -> 0 | M48: =SUMIFS('FS Qtr'!$J49:$EA49, 'FS Qtr'!$J$4:$EA$4, 'FS Ann'!M$4) -> 0 | N48: =SUMIFS('FS Qtr'!$J49:$EA49, 'FS Qtr'!$J$4:$EA$4, 'FS Ann'!N$4) -> 0 | O48: =SUMIFS('FS Qtr'!$J49:$EA49, 'FS Qtr'!$J$4:$EA$4, 'FS Ann'!O$4) -> 0 | P48: =SUMIFS('FS Qtr'!$J49:$EA49, 'FS Qtr'!$J$4:$EA$4, 'FS Ann'!P$4) -> 0 | Q48: =SUMIFS('FS Qtr'!$J49:$EA49, 'FS Qtr'!$J$4:$EA$4, 'FS Ann'!Q$4) -> 0 | ... AN48: =SUMIFS('FS Qtr'!$J49:$EA49, 'FS Qtr'!$J$4:$EA$4, 'FS Ann'!AN$4) -> 0
E49: Cash flow available for dividends | G49: =SMU -> $ 000s | H49: =SUM(J49:AN49) -> 292667.04 | J49: =J46 + J48 -> 0 | K49: =K46 + K48 -> 12742.383 | L49: =L46 + L48 -> 14145.303 | M49: =M46 + M48 -> 14052.325 | N49: =N46 + N48 -> 13910.319 | O49: =O46 + O48 -> 13816.847 | P49: =P46 + P48 -> 13706.843 | Q49: =Q46 + Q48 -> 13612.346 | ... AN49: =AN46 + AN48 -> 0
E51: ='FS Qtr'!E52 -> Dividends paid | F51: ='FS Qtr'!F52 -> 0 | G51: ='FS Qtr'!G52 -> $ 000s | H51: =SUM(J51:AN51) -> -222667.04 | J51: =SUMIFS('FS Qtr'!$J52:$EA52, 'FS Qtr'!$J$4:$EA$4, 'FS Ann'!J$4) -> 0 | K51: =SUMIFS('FS Qtr'!$J52:$EA52, 'FS Qtr'!$J$4:$EA$4, 'FS Ann'!K$4) -> -10243.656 | L51: =SUMIFS('FS Qtr'!$J52:$EA52, 'FS Qtr'!$J$4:$EA$4, 'FS Ann'!L$4) -> -10134.63 | M51: =SUMIFS('FS Qtr'!$J52:$EA52, 'FS Qtr'!$J$4:$EA$4, 'FS Ann'!M$4) -> -10025.378 | N51: =SUMIFS('FS Qtr'!$J52:$EA52, 'FS Qtr'!$J$4:$EA$4, 'FS Ann'!N$4) -> -9915.8844 | O51: =SUMIFS('FS Qtr'!$J52:$EA52, 'FS Qtr'!$J$4:$EA$4, 'FS Ann'!O$4) -> -9806.1355 | P51: =SUMIFS('FS Qtr'!$J52:$EA52, 'FS Qtr'!$J$4:$EA$4, 'FS Ann'!P$4) -> -9696.1162 | Q51: =SUMIFS('FS Qtr'!$J52:$EA52, 'FS Qtr'!$J$4:$EA$4, 'FS Ann'!Q$4) -> -9585.8114 | ... AN51: =SUMIFS('FS Qtr'!$J52:$EA52, 'FS Qtr'!$J$4:$EA$4, 'FS Ann'!AN$4) -> 0
E52: Net cash flow | G52: =SMU -> $ 000s | H52: =SUM(J52:AN52) -> 70000 | J52: =J49 + J51 -> 0 | K52: =K49 + K51 -> 2498.7271 | L52: =L49 + L51 -> 4010.673 | M52: =M49 + M51 -> 4026.9473 | N52: =N49 + N51 -> 3994.4344 | O52: =O49 + O51 -> 4010.7111 | P52: =P49 + P51 -> 4010.7264 | Q52: =Q49 + Q51 -> 4026.5346 | ... AN52: =AN49 + AN51 -> 0
A56: BALANCE SHEET
B58: Non current assets
E59: ='FS Qtr'!E59 -> Fixed asset balance | F59: ='FS Qtr'!F59 -> 0 | G59: ='FS Qtr'!G59 -> $ 000s | J59: =SUMIFS( 'FS Qtr'!$J59:$EA59, 'FS Qtr'!$J$2:$EA$2, 'FS Ann'!J$2) -> 0 | K59: =SUMIFS( 'FS Qtr'!$J59:$EA59, 'FS Qtr'!$J$2:$EA$2, 'FS Ann'!K$2) -> 100000 | L59: =SUMIFS( 'FS Qtr'!$J59:$EA59, 'FS Qtr'!$J$2:$EA$2, 'FS Ann'!L$2) -> 96000 | M59: =SUMIFS( 'FS Qtr'!$J59:$EA59, 'FS Qtr'!$J$2:$EA$2, 'FS Ann'!M$2) -> 92000 | N59: =SUMIFS( 'FS Qtr'!$J59:$EA59, 'FS Qtr'!$J$2:$EA$2, 'FS Ann'!N$2) -> 88000 | O59: =SUMIFS( 'FS Qtr'!$J59:$EA59, 'FS Qtr'!$J$2:$EA$2, 'FS Ann'!O$2) -> 84000 | P59: =SUMIFS( 'FS Qtr'!$J59:$EA59, 'FS Qtr'!$J$2:$EA$2, 'FS Ann'!P$2) -> 80000 | Q59: =SUMIFS( 'FS Qtr'!$J59:$EA59, 'FS Qtr'!$J$2:$EA$2, 'FS Ann'!Q$2) -> 76000 | ... AN59: =SUMIFS( 'FS Qtr'!$J59:$EA59, 'FS Qtr'!$J$2:$EA$2, 'FS Ann'!AN$2) -> 0
E60: Non current assets | G60: =SMU -> $ 000s | J60: =SUM(J59) -> 0 | K60: =SUM(K59) -> 100000 | L60: =SUM(L59) -> 96000 | M60: =SUM(M59) -> 92000 | N60: =SUM(N59) -> 88000 | O60: =SUM(O59) -> 84000 | P60: =SUM(P59) -> 80000 | Q60: =SUM(Q59) -> 76000 | ... AN60: =SUM(AN59) -> 0
B62: Current assets
E63: ='FS Qtr'!E63 -> Retained cash balance | F63: ='FS Qtr'!F63 -> 0 | G63: ='FS Qtr'!G63 -> $ 000s | J63: =SUMIFS( 'FS Qtr'!$J63:$EA63, 'FS Qtr'!$J$2:$EA$2, 'FS Ann'!J$2) -> 0 | K63: =SUMIFS( 'FS Qtr'!$J63:$EA63, 'FS Qtr'!$J$2:$EA$2, 'FS Ann'!K$2) -> 0 | L63: =SUMIFS( 'FS Qtr'!$J63:$EA63, 'FS Qtr'!$J$2:$EA$2, 'FS Ann'!L$2) -> 2498.7271 | M63: =SUMIFS( 'FS Qtr'!$J63:$EA63, 'FS Qtr'!$J$2:$EA$2, 'FS Ann'!M$2) -> 6509.4002 | N63: =SUMIFS( 'FS Qtr'!$J63:$EA63, 'FS Qtr'!$J$2:$EA$2, 'FS Ann'!N$2) -> 10536.347 | O63: =SUMIFS( 'FS Qtr'!$J63:$EA63, 'FS Qtr'!$J$2:$EA$2, 'FS Ann'!O$2) -> 14530.782 | P63: =SUMIFS( 'FS Qtr'!$J63:$EA63, 'FS Qtr'!$J$2:$EA$2, 'FS Ann'!P$2) -> 18541.493 | Q63: =SUMIFS( 'FS Qtr'!$J63:$EA63, 'FS Qtr'!$J$2:$EA$2, 'FS Ann'!Q$2) -> 22552.219 | ... AN63: =SUMIFS( 'FS Qtr'!$J63:$EA63, 'FS Qtr'!$J$2:$EA$2, 'FS Ann'!AN$2) -> 70000
E64: ='FS Qtr'!E64 -> Accounts receivable balance | F64: ='FS Qtr'!F64 -> 0 | G64: ='FS Qtr'!G64 -> $ 000s | J64: =SUMIFS( 'FS Qtr'!$J64:$EA64, 'FS Qtr'!$J$2:$EA$2, 'FS Ann'!J$2) -> 0 | K64: =SUMIFS( 'FS Qtr'!$J64:$EA64, 'FS Qtr'!$J$2:$EA$2, 'FS Ann'!K$2) -> 0 | L64: =SUMIFS( 'FS Qtr'!$J64:$EA64, 'FS Qtr'!$J$2:$EA$2, 'FS Ann'!L$2) -> 1628.7917 | M64: =SUMIFS( 'FS Qtr'!$J64:$EA64, 'FS Qtr'!$J$2:$EA$2, 'FS Ann'!M$2) -> 1620.6882 | N64: =SUMIFS( 'FS Qtr'!$J64:$EA64, 'FS Qtr'!$J$2:$EA$2, 'FS Ann'!N$2) -> 1594.9039 | O64: =SUMIFS( 'FS Qtr'!$J64:$EA64, 'FS Qtr'!$J$2:$EA$2, 'FS Ann'!O$2) -> 1604.6021 | P64: =SUMIFS( 'FS Qtr'!$J64:$EA64, 'FS Qtr'!$J$2:$EA$2, 'FS Ann'!P$2) -> 1596.619 | Q64: =SUMIFS( 'FS Qtr'!$J64:$EA64, 'FS Qtr'!$J$2:$EA$2, 'FS Ann'!Q$2) -> 1588.6756 | ... AN64: =SUMIFS( 'FS Qtr'!$J64:$EA64, 'FS Qtr'!$J$2:$EA$2, 'FS Ann'!AN$2) -> 0
E65: Current assets | G65: =SMU -> $ 000s | J65: =SUM(J63:J64) -> 0 | K65: =SUM(K63:K64) -> 0 | L65: =SUM(L63:L64) -> 4127.5188 | M65: =SUM(M63:M64) -> 8130.0884 | N65: =SUM(N63:N64) -> 12131.251 | O65: =SUM(O63:O64) -> 16135.384 | P65: =SUM(P63:P64) -> 20138.112 | Q65: =SUM(Q63:Q64) -> 24140.895 | ... AN65: =SUM(AN63:AN64) -> 70000
E67: Total assets | G67: =SMU -> $ 000s | J67: =J65 + J60 -> 0 | K67: =K65 + K60 -> 100000 | L67: =L65 + L60 -> 100127.52 | M67: =M65 + M60 -> 100130.09 | N67: =N65 + N60 -> 100131.25 | O67: =O65 + O60 -> 100135.38 | P67: =P65 + P60 -> 100138.11 | Q67: =Q65 + Q60 -> 100140.89 | ... AN67: =AN65 + AN60 -> 70000
E69: ='FS Qtr'!E69 -> Accounts payable balance | F69: ='FS Qtr'!F69 -> 0 | G69: ='FS Qtr'!G69 -> $ 000s | J69: =SUMIFS( 'FS Qtr'!$J69:$EA69, 'FS Qtr'!$J$2:$EA$2, 'FS Ann'!J$2) -> 0 | K69: =SUMIFS( 'FS Qtr'!$J69:$EA69, 'FS Qtr'!$J$2:$EA$2, 'FS Ann'!K$2) -> 0 | L69: =SUMIFS( 'FS Qtr'!$J69:$EA69, 'FS Qtr'!$J$2:$EA$2, 'FS Ann'!L$2) -> 127.51881 | M69: =SUMIFS( 'FS Qtr'!$J69:$EA69, 'FS Qtr'!$J$2:$EA$2, 'FS Ann'!M$2) -> 130.08838 | N69: =SUMIFS( 'FS Qtr'!$J69:$EA69, 'FS Qtr'!$J$2:$EA$2, 'FS Ann'!N$2) -> 131.25138 | O69: =SUMIFS( 'FS Qtr'!$J69:$EA69, 'FS Qtr'!$J$2:$EA$2, 'FS Ann'!O$2) -> 135.38389 | P69: =SUMIFS( 'FS Qtr'!$J69:$EA69, 'FS Qtr'!$J$2:$EA$2, 'FS Ann'!P$2) -> 138.11195 | Q69: =SUMIFS( 'FS Qtr'!$J69:$EA69, 'FS Qtr'!$J$2:$EA$2, 'FS Ann'!Q$2) -> 140.89497 | ... AN69: =SUMIFS( 'FS Qtr'!$J69:$EA69, 'FS Qtr'!$J$2:$EA$2, 'FS Ann'!AN$2) -> 0
E70: ='FS Qtr'!E70 -> Senior debt balance | F70: ='FS Qtr'!F70 -> 0 | G70: ='FS Qtr'!G70 -> $ 000s | J70: =SUMIFS( 'FS Qtr'!$J70:$EA70, 'FS Qtr'!$J$2:$EA$2, 'FS Ann'!J$2) -> 0 | K70: =SUMIFS( 'FS Qtr'!$J70:$EA70, 'FS Qtr'!$J$2:$EA$2, 'FS Ann'!K$2) -> 70000 | L70: =SUMIFS( 'FS Qtr'!$J70:$EA70, 'FS Qtr'!$J$2:$EA$2, 'FS Ann'!L$2) -> 70000 | M70: =SUMIFS( 'FS Qtr'!$J70:$EA70, 'FS Qtr'!$J$2:$EA$2, 'FS Ann'!M$2) -> 70000 | N70: =SUMIFS( 'FS Qtr'!$J70:$EA70, 'FS Qtr'!$J$2:$EA$2, 'FS Ann'!N$2) -> 70000 | O70: =SUMIFS( 'FS Qtr'!$J70:$EA70, 'FS Qtr'!$J$2:$EA$2, 'FS Ann'!O$2) -> 70000 | P70: =SUMIFS( 'FS Qtr'!$J70:$EA70, 'FS Qtr'!$J$2:$EA$2, 'FS Ann'!P$2) -> 70000 | Q70: =SUMIFS( 'FS Qtr'!$J70:$EA70, 'FS Qtr'!$J$2:$EA$2, 'FS Ann'!Q$2) -> 70000 | ... AN70: =SUMIFS( 'FS Qtr'!$J70:$EA70, 'FS Qtr'!$J$2:$EA$2, 'FS Ann'!AN$2) -> 70000
E71: ='FS Qtr'!E71 -> [Refi facility balance] | F71: ='FS Qtr'!F71 -> 0 | G71: ='FS Qtr'!G71 -> 0 | J71: =SUMIFS( 'FS Qtr'!$J71:$EA71, 'FS Qtr'!$J$2:$EA$2, 'FS Ann'!J$2) -> 0 | K71: =SUMIFS( 'FS Qtr'!$J71:$EA71, 'FS Qtr'!$J$2:$EA$2, 'FS Ann'!K$2) -> 0 | L71: =SUMIFS( 'FS Qtr'!$J71:$EA71, 'FS Qtr'!$J$2:$EA$2, 'FS Ann'!L$2) -> 0 | M71: =SUMIFS( 'FS Qtr'!$J71:$EA71, 'FS Qtr'!$J$2:$EA$2, 'FS Ann'!M$2) -> 0 | N71: =SUMIFS( 'FS Qtr'!$J71:$EA71, 'FS Qtr'!$J$2:$EA$2, 'FS Ann'!N$2) -> 0 | O71: =SUMIFS( 'FS Qtr'!$J71:$EA71, 'FS Qtr'!$J$2:$EA$2, 'FS Ann'!O$2) -> 0 | P71: =SUMIFS( 'FS Qtr'!$J71:$EA71, 'FS Qtr'!$J$2:$EA$2, 'FS Ann'!P$2) -> 0 | Q71: =SUMIFS( 'FS Qtr'!$J71:$EA71, 'FS Qtr'!$J$2:$EA$2, 'FS Ann'!Q$2) -> 0 | ... AN71: =SUMIFS( 'FS Qtr'!$J71:$EA71, 'FS Qtr'!$J$2:$EA$2, 'FS Ann'!AN$2) -> 0
E72: ='FS Qtr'!E72 -> [RCF balance] | F72: ='FS Qtr'!F72 -> 0 | G72: ='FS Qtr'!G72 -> 0 | J72: =SUMIFS( 'FS Qtr'!$J72:$EA72, 'FS Qtr'!$J$2:$EA$2, 'FS Ann'!J$2) -> 0 | K72: =SUMIFS( 'FS Qtr'!$J72:$EA72, 'FS Qtr'!$J$2:$EA$2, 'FS Ann'!K$2) -> 0 | L72: =SUMIFS( 'FS Qtr'!$J72:$EA72, 'FS Qtr'!$J$2:$EA$2, 'FS Ann'!L$2) -> 0 | M72: =SUMIFS( 'FS Qtr'!$J72:$EA72, 'FS Qtr'!$J$2:$EA$2, 'FS Ann'!M$2) -> 0 | N72: =SUMIFS( 'FS Qtr'!$J72:$EA72, 'FS Qtr'!$J$2:$EA$2, 'FS Ann'!N$2) -> 0 | O72: =SUMIFS( 'FS Qtr'!$J72:$EA72, 'FS Qtr'!$J$2:$EA$2, 'FS Ann'!O$2) -> 0 | P72: =SUMIFS( 'FS Qtr'!$J72:$EA72, 'FS Qtr'!$J$2:$EA$2, 'FS Ann'!P$2) -> 0 | Q72: =SUMIFS( 'FS Qtr'!$J72:$EA72, 'FS Qtr'!$J$2:$EA$2, 'FS Ann'!Q$2) -> 0 | ... AN72: =SUMIFS( 'FS Qtr'!$J72:$EA72, 'FS Qtr'!$J$2:$EA$2, 'FS Ann'!AN$2) -> 0
E73: ='FS Qtr'!E73 -> Share capital balance | F73: ='FS Qtr'!F73 -> 0 | G73: ='FS Qtr'!G73 -> $ 000s | J73: =SUMIFS( 'FS Qtr'!$J73:$EA73, 'FS Qtr'!$J$2:$EA$2, 'FS Ann'!J$2) -> 0 | K73: =SUMIFS( 'FS Qtr'!$J73:$EA73, 'FS Qtr'!$J$2:$EA$2, 'FS Ann'!K$2) -> 30000 | L73: =SUMIFS( 'FS Qtr'!$J73:$EA73, 'FS Qtr'!$J$2:$EA$2, 'FS Ann'!L$2) -> 30000 | M73: =SUMIFS( 'FS Qtr'!$J73:$EA73, 'FS Qtr'!$J$2:$EA$2, 'FS Ann'!M$2) -> 30000 | N73: =SUMIFS( 'FS Qtr'!$J73:$EA73, 'FS Qtr'!$J$2:$EA$2, 'FS Ann'!N$2) -> 30000 | O73: =SUMIFS( 'FS Qtr'!$J73:$EA73, 'FS Qtr'!$J$2:$EA$2, 'FS Ann'!O$2) -> 30000 | P73: =SUMIFS( 'FS Qtr'!$J73:$EA73, 'FS Qtr'!$J$2:$EA$2, 'FS Ann'!P$2) -> 30000 | Q73: =SUMIFS( 'FS Qtr'!$J73:$EA73, 'FS Qtr'!$J$2:$EA$2, 'FS Ann'!Q$2) -> 30000 | ... AN73: =SUMIFS( 'FS Qtr'!$J73:$EA73, 'FS Qtr'!$J$2:$EA$2, 'FS Ann'!AN$2) -> 0
E74: ='FS Qtr'!E74 -> Retained earnings balance | F74: ='FS Qtr'!F74 -> 0 | G74: ='FS Qtr'!G74 -> $ 000s | J74: =SUMIFS( 'FS Qtr'!$J74:$EA74, 'FS Qtr'!$J$2:$EA$2, 'FS Ann'!J$2) -> 0 | K74: =SUMIFS( 'FS Qtr'!$J74:$EA74, 'FS Qtr'!$J$2:$EA$2, 'FS Ann'!K$2) -> 0 | L74: =SUMIFS( 'FS Qtr'!$J74:$EA74, 'FS Qtr'!$J$2:$EA$2, 'FS Ann'!L$2) -> 0 | M74: =SUMIFS( 'FS Qtr'!$J74:$EA74, 'FS Qtr'!$J$2:$EA$2, 'FS Ann'!M$2) -> 0 | N74: =SUMIFS( 'FS Qtr'!$J74:$EA74, 'FS Qtr'!$J$2:$EA$2, 'FS Ann'!N$2) -> 0 | O74: =SUMIFS( 'FS Qtr'!$J74:$EA74, 'FS Qtr'!$J$2:$EA$2, 'FS Ann'!O$2) -> 0 | P74: =SUMIFS( 'FS Qtr'!$J74:$EA74, 'FS Qtr'!$J$2:$EA$2, 'FS Ann'!P$2) -> 0 | Q74: =SUMIFS( 'FS Qtr'!$J74:$EA74, 'FS Qtr'!$J$2:$EA$2, 'FS Ann'!Q$2) -> 0 | ... AN74: =SUMIFS( 'FS Qtr'!$J74:$EA74, 'FS Qtr'!$J$2:$EA$2, 'FS Ann'!AN$2) -> 0
E75: Total liabilities | G75: =SMU -> $ 000s | J75: =SUM(J69:J74) -> 0 | K75: =SUM(K69:K74) -> 100000 | L75: =SUM(L69:L74) -> 100127.52 | M75: =SUM(M69:M74) -> 100130.09 | N75: =SUM(N69:N74) -> 100131.25 | O75: =SUM(O69:O74) -> 100135.38 | P75: =SUM(P69:P74) -> 100138.11 | Q75: =SUM(Q69:Q74) -> 100140.89 | ... AN75: =SUM(AN69:AN74) -> 70000
A78: BALANCE SHEET CHECK
E80: =E$67 -> Total assets | F80: =F$67 -> 0 | G80: =G$67 -> $ 000s | H80: =H$67 -> 0 | I80: =I$67 -> 0 | J80: =J$67 -> 0 | K80: =K$67 -> 100000 | L80: =L$67 -> 100127.52 | ... AN80: =AN$67 -> 70000
E81: =E$75 -> Total liabilities | F81: =F$75 -> 0 | G81: =G$75 -> $ 000s | H81: =H$75 -> 0 | I81: =I$75 -> 0 | J81: =J$75 -> 0 | K81: =K$75 -> 100000 | L81: =L$75 -> 100127.52 | ... AN81: =AN$75 -> 70000
E82: Annual balance sheet check | F82: =IF(SUM(J82:AN82) <> 0, 1, 0) -> 0 | G82: check | J82: =IF(ABS(J80 - J81) > CHK_TOL, 1, 0) -> 0 | K82: =IF(ABS(K80 - K81) > CHK_TOL, 1, 0) -> 0 | L82: =IF(ABS(L80 - L81) > CHK_TOL, 1, 0) -> 0 | M82: =IF(ABS(M80 - M81) > CHK_TOL, 1, 0) -> 0 | N82: =IF(ABS(N80 - N81) > CHK_TOL, 1, 0) -> 0 | O82: =IF(ABS(O80 - O81) > CHK_TOL, 1, 0) -> 0 | P82: =IF(ABS(P80 - P81) > CHK_TOL, 1, 0) -> 0 | Q82: =IF(ABS(Q80 - Q81) > CHK_TOL, 1, 0) -> 0 | ... AN82: =IF(ABS(AN80 - AN81) > CHK_TOL, 1, 0) -> 0
E83: Annual balance sheet difference | H83: =SUM(J83:AN83) -> 0 | J83: =J80 - J81 -> 0 | K83: =K80 - K81 -> 0 | L83: =L80 - L81 -> 0 | M83: =M80 - M81 -> 0 | N83: =N80 - N81 -> 0 | O83: =O80 - O81 -> 0 | P83: =P80 - P81 -> 0 | Q83: =Q80 - Q81 -> 0 | ... AN83: =AN80 - AN81 -> 0
A86: END

Sheet Output
A1: =RIGHT(CELL("filename", A1), LEN(CELL("filename", A1)) - SEARCH("]", CELL("filename", A1))) & " - " & InpC!F3 -> Output - Base case 1
G2: Date | H2: =TODAY() -> 44575 | J2: =COUNTIF(J6:J74, "tu") -> 0 | N2: 44575 | O2: 44572 | P2: 44572 | Q2: 44572 | R2: 44572 | S2: 44571 | T2: 44571 | U2: 44564 | V2: 44564 | W2: 44564
G3: Case | H3: =InpC!F3 -> Base case 1 | N3: Base case 1 | O3: Base case 1 | P3: Base case 1 | Q3: Base case 1 | R3: Base case 1 | S3: Base case 1 | T3: Base case 1 | U3: Base case 1 | V3: Base case 1 | W3: Base case 1
E5: Comparison column label | G5: Unit | H5: 12 | J5: =MATCH($H$5, M5:Z5, 0) -> 2 | K5: Difference | L5: Diff Pct | N5: 12 | O5: 11 | P5: 10 | Q5: 9 | R5: 8 | S5: 7 | T5: 6 | U5: 5 | V5: 4 | W5: 3 | X5: 2 | Y5: 1
E6: [do not delete row]
A8: KEY OUTPUTS
E10: =Metrics!E$20 -> Equity IRR | G10: =Metrics!G$20 -> % | H10: =Metrics!F$20 -> 0.089617065 | J10: =IF(ABS(K10) > TRK_TOL, "tu", "vw") -> vw | K10: =H10 - INDEX(M10:Z10, $J$5) -> 0 | L10: =IF(ABS(K10) > TRK_TOL, IF(INDEX(M10:Z10, $J$5) = 0, 0, H10 / INDEX(M10:Z10, $J$5) - 1), 0) -> 0 | N10: 0.089617065 | O10: 0.098730558 | P10: 0.084725401 | Q10: 0.1347866
A17: PROFIT AND LOSS
E19: ='FS Qtr'!E9 -> Electricity revenue | F19: ='FS Qtr'!F9 -> 0 | G19: ='FS Qtr'!G$9 -> $ 000s | H19: ='FS Qtr'!H9 -> 371409.68 | J19: =IF(ABS(K19) > TRK_TOL, "tu", "vw") -> vw | K19: =H19 - INDEX(M19:Z19, $J$5) -> 0 | L19: =IF(ABS(K19) > TRK_TOL, IF(INDEX(M19:Z19, $J$5) = 0, 0, H19 / INDEX(M19:Z19, $J$5) - 1), 0) -> 0 | N19: 371409.68 | O19: 371409.68 | P19: 371409.68 | Q19: 371409.68 | R19: 371409.68 | S19: 371409.68 | T19: 371409.68 | U19: 371409.68 | V19: 371409.68 | W19: 0
E20: ='FS Qtr'!E10 -> O&M cost | F20: ='FS Qtr'!F10 -> 0 | G20: ='FS Qtr'!G$9 -> $ 000s | H20: ='FS Qtr'!H10 -> -48742.638 | J20: =IF(ABS(K20) > TRK_TOL, "tu", "vw") -> vw | K20: =H20 - INDEX(M20:Z20, $J$5) -> 0 | L20: =IF(ABS(K20) > TRK_TOL, IF(INDEX(M20:Z20, $J$5) = 0, 0, H20 / INDEX(M20:Z20, $J$5) - 1), 0) -> 0 | N20: -48742.638 | O20: -48742.638 | P20: -48742.638 | Q20: -48742.638 | R20: -48742.638 | S20: -48742.638 | T20: -48742.638 | U20: 0 | V20: 0 | W20: 0
E21: ='FS Qtr'!E11 -> EBITDA | F21: ='FS Qtr'!F11 -> 0 | G21: ='FS Qtr'!G$9 -> $ 000s | H21: ='FS Qtr'!H11 -> 322667.04 | J21: =IF(ABS(K21) > TRK_TOL, "tu", "vw") -> vw | K21: =H21 - INDEX(M21:Z21, $J$5) -> 0 | L21: =IF(ABS(K21) > TRK_TOL, IF(INDEX(M21:Z21, $J$5) = 0, 0, H21 / INDEX(M21:Z21, $J$5) - 1), 0) -> 0 | N21: 322667.04 | O21: 322667.04 | P21: 322667.04 | Q21: 322667.04 | R21: 322667.04 | S21: 322667.04 | T21: 322667.04 | U21: 371409.68 | V21: 371409.68 | W21: 10000
E23: ='FS Qtr'!E13 -> Depreciation of fixed asset | F23: ='FS Qtr'!F13 -> 0 | G23: ='FS Qtr'!G$9 -> $ 000s | H23: ='FS Qtr'!H13 -> -100000 | J23: =IF(ABS(K23) > TRK_TOL, "tu", "vw") -> vw | K23: =H23 - INDEX(M23:Z23, $J$5) -> 0 | L23: =IF(ABS(K23) > TRK_TOL, IF(INDEX(M23:Z23, $J$5) = 0, 0, H23 / INDEX(M23:Z23, $J$5) - 1), 0) -> 0 | N23: -100000 | O23: -100000 | P23: -100000 | Q23: 0 | R23: 0 | S23: 0 | T23: 0 | U23: 0 | V23: 0 | W23: 0
E24: ='FS Qtr'!E14 -> EBIT | F24: ='FS Qtr'!F14 -> 0 | G24: ='FS Qtr'!G$9 -> $ 000s | H24: ='FS Qtr'!H14 -> 222667.04 | J24: =IF(ABS(K24) > TRK_TOL, "tu", "vw") -> vw | K24: =H24 - INDEX(M24:Z24, $J$5) -> 0 | L24: =IF(ABS(K24) > TRK_TOL, IF(INDEX(M24:Z24, $J$5) = 0, 0, H24 / INDEX(M24:Z24, $J$5) - 1), 0) -> 0 | N24: 222667.04 | O24: 222667.04 | P24: 222667.04 | Q24: 322667.04 | R24: 322667.04 | S24: 322667.04 | T24: 322667.04 | U24: 371409.68 | V24: 371409.68 | W24: 10000
E26: ='FS Qtr'!E16 -> [Senior debt interest] | F26: ='FS Qtr'!F16 -> 0 | G26: ='FS Qtr'!G$9 -> $ 000s | H26: ='FS Qtr'!H16 -> 0 | J26: =IF(ABS(K26) > TRK_TOL, "tu", "vw") -> vw | K26: =H26 - INDEX(M26:Z26, $J$5) -> 0 | L26: =IF(ABS(K26) > TRK_TOL, IF(INDEX(M26:Z26, $J$5) = 0, 0, H26 / INDEX(M26:Z26, $J$5) - 1), 0) -> 0 | N26: 0 | O26: 0 | P26: 0 | Q26: 0 | R26: 0 | S26: 0 | T26: 0 | U26: 0 | V26: 0 | W26: 0
E27: ='FS Qtr'!E17 -> [Refi facility interest] | F27: ='FS Qtr'!F17 -> 0 | G27: ='FS Qtr'!G$9 -> $ 000s | H27: ='FS Qtr'!H17 -> 0 | J27: =IF(ABS(K27) > TRK_TOL, "tu", "vw") -> vw | K27: =H27 - INDEX(M27:Z27, $J$5) -> 0 | L27: =IF(ABS(K27) > TRK_TOL, IF(INDEX(M27:Z27, $J$5) = 0, 0, H27 / INDEX(M27:Z27, $J$5) - 1), 0) -> 0 | N27: 0 | O27: 0 | P27: 0 | Q27: 0 | R27: 0 | S27: 0 | T27: 0 | U27: 0 | V27: 0 | W27: 0
E28: ='FS Qtr'!E18 -> [RCF interest expense] | F28: ='FS Qtr'!F18 -> 0 | G28: ='FS Qtr'!G$9 -> $ 000s | H28: ='FS Qtr'!H18 -> 0 | J28: =IF(ABS(K28) > TRK_TOL, "tu", "vw") -> vw | K28: =H28 - INDEX(M28:Z28, $J$5) -> 0 | L28: =IF(ABS(K28) > TRK_TOL, IF(INDEX(M28:Z28, $J$5) = 0, 0, H28 / INDEX(M28:Z28, $J$5) - 1), 0) -> 0 | N28: 0 | O28: 0 | P28: 0 | Q28: 0 | R28: 0 | S28: 0 | T28: 0 | U28: 0 | V28: 0 | W28: 0
E29: ='FS Qtr'!E19 -> Profit before tax | F29: ='FS Qtr'!F19 -> 0 | G29: ='FS Qtr'!G$9 -> $ 000s | H29: ='FS Qtr'!H19 -> 222667.04 | J29: =IF(ABS(K29) > TRK_TOL, "tu", "vw") -> vw | K29: =H29 - INDEX(M29:Z29, $J$5) -> 0 | L29: =IF(ABS(K29) > TRK_TOL, IF(INDEX(M29:Z29, $J$5) = 0, 0, H29 / INDEX(M29:Z29, $J$5) - 1), 0) -> 0 | N29: 222667.04 | O29: 222667.04 | P29: 222667.04 | Q29: 322667.04 | R29: 322667.04 | S29: 322667.04 | T29: 322667.04 | U29: 371409.68 | V29: 371409.68 | W29: 10000
E31: ='FS Qtr'!E21 -> [Corporate income tax expense] | F31: ='FS Qtr'!F21 -> 0 | G31: ='FS Qtr'!G$9 -> $ 000s | H31: ='FS Qtr'!H21 -> 0 | J31: =IF(ABS(K31) > TRK_TOL, "tu", "vw") -> vw | K31: =H31 - INDEX(M31:Z31, $J$5) -> 0 | L31: =IF(ABS(K31) > TRK_TOL, IF(INDEX(M31:Z31, $J$5) = 0, 0, H31 / INDEX(M31:Z31, $J$5) - 1), 0) -> 0 | N31: 0 | O31: 0 | P31: 0 | Q31: 0 | R31: 0 | S31: 0 | T31: 0 | U31: 0 | V31: 0 | W31: 0
E32: ='FS Qtr'!E22 -> Profit after tax | F32: ='FS Qtr'!F22 -> 0 | G32: ='FS Qtr'!G$9 -> $ 000s | H32: ='FS Qtr'!H22 -> 222667.04 | J32: =IF(ABS(K32) > TRK_TOL, "tu", "vw") -> vw | K32: =H32 - INDEX(M32:Z32, $J$5) -> 0 | L32: =IF(ABS(K32) > TRK_TOL, IF(INDEX(M32:Z32, $J$5) = 0, 0, H32 / INDEX(M32:Z32, $J$5) - 1), 0) -> 0 | N32: 222667.04 | O32: 222667.04 | P32: 222667.04 | Q32: 322667.04 | R32: 322667.04 | S32: 322667.04 | T32: 322667.04 | U32: 371409.68 | V32: 371409.68 | W32: 10000
E34: ='FS Qtr'!E24 -> Dividends paid | F34: ='FS Qtr'!F24 -> 0 | G34: ='FS Qtr'!G$9 -> $ 000s | H34: ='FS Qtr'!H24 -> -222667.04 | J34: =IF(ABS(K34) > TRK_TOL, "tu", "vw") -> vw | K34: =H34 - INDEX(M34:Z34, $J$5) -> 0 | L34: =IF(ABS(K34) > TRK_TOL, IF(INDEX(M34:Z34, $J$5) = 0, 0, H34 / INDEX(M34:Z34, $J$5) - 1), 0) -> 0 | N34: -222667.04 | O34: -222667.04 | P34: -222667.04 | Q34: -322667.04 | R34: -322667.04 | S34: 0 | T34: 0 | U34: 0 | V34: 0 | W34: 0
E35: ='FS Qtr'!E25 -> Net income after dividends | F35: ='FS Qtr'!F25 -> 0 | G35: ='FS Qtr'!G$9 -> $ 000s | H35: ='FS Qtr'!H25 -> 0 | J35: =IF(ABS(K35) > TRK_TOL, "tu", "vw") -> vw | K35: =H35 - INDEX(M35:Z35, $J$5) -> 0 | L35: =IF(ABS(K35) > TRK_TOL, IF(INDEX(M35:Z35, $J$5) = 0, 0, H35 / INDEX(M35:Z35, $J$5) - 1), 0) -> 0 | N35: 0 | O35: 0 | P35: 0 | Q35: -9.094947e-13 | R35: -9.094947e-13 | S35: 322667.04 | T35: 322667.04 | U35: 371409.68 | V35: 371409.68 | W35: 10000
A38: CASH FLOW
E40: ='FS Qtr'!E30 -> Cash received from invoices | F40: ='FS Qtr'!F30 -> 0 | G40: ='FS Qtr'!G$9 -> $ 000s | H40: ='FS Qtr'!H30 -> 371409.68 | J40: =IF(ABS(K40) > TRK_TOL, "tu", "vw") -> vw | K40: =H40 - INDEX(M40:Z40, $J$5) -> 0 | L40: =IF(ABS(K40) > TRK_TOL, IF(INDEX(M40:Z40, $J$5) = 0, 0, H40 / INDEX(M40:Z40, $J$5) - 1), 0) -> 0 | N40: 371409.68 | O40: 371409.68 | P40: 371409.68 | Q40: 371409.68 | R40: 371409.68 | S40: 371409.68 | T40: 371409.68 | U40: 371409.68 | V40: 0 | W40: 0
E41: ='FS Qtr'!E31 -> Cash paid for operating costs | F41: ='FS Qtr'!F31 -> 0 | G41: ='FS Qtr'!G$9 -> $ 000s | H41: ='FS Qtr'!H31 -> -48742.638 | J41: =IF(ABS(K41) > TRK_TOL, "tu", "vw") -> vw | K41: =H41 - INDEX(M41:Z41, $J$5) -> 0 | L41: =IF(ABS(K41) > TRK_TOL, IF(INDEX(M41:Z41, $J$5) = 0, 0, H41 / INDEX(M41:Z41, $J$5) - 1), 0) -> 0 | N41: -48742.638 | O41: -48742.638 | P41: -48742.638 | Q41: -48742.638 | R41: -48742.638 | S41: -48742.638 | T41: 0 | U41: 0 | V41: 0 | W41: 0
E42: ='FS Qtr'!E32 -> [Corporate income tax expense] | F42: ='FS Qtr'!F32 -> 0 | G42: ='FS Qtr'!G$9 -> $ 000s | H42: ='FS Qtr'!H32 -> 0 | J42: =IF(ABS(K42) > TRK_TOL, "tu", "vw") -> vw | K42: =H42 - INDEX(M42:Z42, $J$5) -> 0 | L42: =IF(ABS(K42) > TRK_TOL, IF(INDEX(M42:Z42, $J$5) = 0, 0, H42 / INDEX(M42:Z42, $J$5) - 1), 0) -> 0 | N42: 0 | O42: 0 | P42: 0 | Q42: 0 | R42: 0 | S42: 0 | T42: 0 | U42: 0 | V42: 0 | W42: 0
E43: ='FS Qtr'!E33 -> Cash flow available for senior debt service | F43: ='FS Qtr'!F33 -> 0 | G43: ='FS Qtr'!G$9 -> $ 000s | H43: ='FS Qtr'!H33 -> 322667.04 | J43: =IF(ABS(K43) > TRK_TOL, "tu", "vw") -> vw | K43: =H43 - INDEX(M43:Z43, $J$5) -> 0 | L43: =IF(ABS(K43) > TRK_TOL, IF(INDEX(M43:Z43, $J$5) = 0, 0, H43 / INDEX(M43:Z43, $J$5) - 1), 0) -> 0 | N43: 322667.04 | O43: 322667.04 | P43: 322667.04 | Q43: 322667.04 | R43: 322667.04 | S43: 322667.04 | T43: 371409.68 | U43: 371409.68 | V43: 10000 | W43: 10000
E45: ='FS Qtr'!E35 -> [Senior debt interest] | F45: ='FS Qtr'!F35 -> 0 | G45: ='FS Qtr'!G$9 -> $ 000s | H45: ='FS Qtr'!H35 -> 0 | J45: =IF(ABS(K45) > TRK_TOL, "tu", "vw") -> vw | K45: =H45 - INDEX(M45:Z45, $J$5) -> 0 | L45: =IF(ABS(K45) > TRK_TOL, IF(INDEX(M45:Z45, $J$5) = 0, 0, H45 / INDEX(M45:Z45, $J$5) - 1), 0) -> 0 | N45: 0 | O45: 0 | P45: 0 | Q45: 0 | R45: 0 | S45: 0 | T45: 0 | U45: 0 | V45: 0 | W45: 0
E46: ='FS Qtr'!E36 -> [Senior debt repayment] | F46: ='FS Qtr'!F36 -> 0 | G46: ='FS Qtr'!G$9 -> $ 000s | H46: ='FS Qtr'!H36 -> 0 | J46: =IF(ABS(K46) > TRK_TOL, "tu", "vw") -> vw | K46: =H46 - INDEX(M46:Z46, $J$5) -> 0 | L46: =IF(ABS(K46) > TRK_TOL, IF(INDEX(M46:Z46, $J$5) = 0, 0, H46 / INDEX(M46:Z46, $J$5) - 1), 0) -> 0 | N46: 0 | O46: 0 | P46: 0 | Q46: 0 | R46: 0 | S46: 0 | T46: 0 | U46: 0 | V46: 0 | W46: 0
E47: ='FS Qtr'!E37 -> Cash flow available for refinancing facility | F47: ='FS Qtr'!F37 -> 0 | G47: ='FS Qtr'!G$9 -> $ 000s | H47: ='FS Qtr'!H37 -> 322667.04 | J47: =IF(ABS(K47) > TRK_TOL, "tu", "vw") -> vw | N47: 322667.04 | O47: 322667.04 | P47: 322667.04 | Q47: 322667.04 | R47: 322667.04 | S47: 322667.04 | T47: 371409.68 | U47: 371409.68 | V47: 10000 | W47: 10000
E49: ='FS Qtr'!E39 -> [Refi facility drawdown] | F49: ='FS Qtr'!F39 -> 0 | G49: ='FS Qtr'!G$9 -> $ 000s | H49: ='FS Qtr'!H39 -> 0 | J49: =IF(ABS(K49) > TRK_TOL, "tu", "vw") -> vw | K49: =H49 - INDEX(M49:Z49, $J$5) -> 0 | L49: =IF(ABS(K49) > TRK_TOL, IF(INDEX(M49:Z49, $J$5) = 0, 0, H49 / INDEX(M49:Z49, $J$5) - 1), 0) -> 0 | N49: 0 | O49: 0 | P49: 0 | Q49: 0 | R49: 0 | S49: 0 | T49: 0 | U49: 0 | V49: 0 | W49: 0
E50: ='FS Qtr'!E40 -> [Refi facility repayment] | F50: ='FS Qtr'!F40 -> 0 | G50: ='FS Qtr'!G$9 -> $ 000s | H50: ='FS Qtr'!H40 -> 0 | J50: =IF(ABS(K50) > TRK_TOL, "tu", "vw") -> vw | K50: =H50 - INDEX(M50:Z50, $J$5) -> 0 | L50: =IF(ABS(K50) > TRK_TOL, IF(INDEX(M50:Z50, $J$5) = 0, 0, H50 / INDEX(M50:Z50, $J$5) - 1), 0) -> 0 | N50: 0 | O50: 0 | P50: 0 | Q50: 0 | R50: 0 | S50: 0 | T50: 0 | U50: 0 | V50: 0 | W50: 0
E51: ='FS Qtr'!E41 -> [Refi facility interest] | F51: ='FS Qtr'!F41 -> 0 | G51: ='FS Qtr'!G$9 -> $ 000s | H51: ='FS Qtr'!H41 -> 0 | J51: =IF(ABS(K51) > TRK_TOL, "tu", "vw") -> vw | K51: =H51 - INDEX(M51:Z51, $J$5) -> 0 | L51: =IF(ABS(K51) > TRK_TOL, IF(INDEX(M51:Z51, $J$5) = 0, 0, H51 / INDEX(M51:Z51, $J$5) - 1), 0) -> 0 | N51: 0 | O51: 0 | P51: 0 | Q51: 0 | R51: 0 | S51: 0 | T51: 0 | U51: 0 | V51: 0 | W51: 0
E52: ='FS Qtr'!E42 -> Cash flow available for revolving credit facility | F52: ='FS Qtr'!F42 -> 0 | G52: ='FS Qtr'!G$9 -> $ 000s | H52: ='FS Qtr'!H42 -> 322667.04 | J52: =IF(ABS(K52) > TRK_TOL, "tu", "vw") -> vw | K52: =H52 - INDEX(M52:Z52, $J$5) -> 0 | L52: =IF(ABS(K52) > TRK_TOL, IF(INDEX(M52:Z52, $J$5) = 0, 0, H52 / INDEX(M52:Z52, $J$5) - 1), 0) -> 0 | N52: 322667.04 | O52: 322667.04 | P52: 322667.04 | Q52: 322667.04 | R52: 322667.04 | S52: 322667.04 | T52: 371409.68 | U52: 371409.68 | V52: 10000 | W52: 10000
E54: ='FS Qtr'!E44 -> [RCF drawdown] | F54: ='FS Qtr'!F44 -> 0 | G54: ='FS Qtr'!G$9 -> $ 000s | H54: ='FS Qtr'!H44 -> 0 | J54: =IF(ABS(K54) > TRK_TOL, "tu", "vw") -> vw | K54: =H54 - INDEX(M54:Z54, $J$5) -> 0 | L54: =IF(ABS(K54) > TRK_TOL, IF(INDEX(M54:Z54, $J$5) = 0, 0, H54 / INDEX(M54:Z54, $J$5) - 1), 0) -> 0 | N54: 0 | O54: 0 | P54: 0 | Q54: 0 | R54: 0 | S54: 0 | T54: 0 | U54: 0 | V54: 0 | W54: 0
E55: ='FS Qtr'!E45 -> [RCF repayment] | F55: ='FS Qtr'!F45 -> 0 | G55: ='FS Qtr'!G$9 -> $ 000s | H55: ='FS Qtr'!H45 -> 0 | J55: =IF(ABS(K55) > TRK_TOL, "tu", "vw") -> vw | K55: =H55 - INDEX(M55:Z55, $J$5) -> 0 | L55: =IF(ABS(K55) > TRK_TOL, IF(INDEX(M55:Z55, $J$5) = 0, 0, H55 / INDEX(M55:Z55, $J$5) - 1), 0) -> 0 | N55: 0 | O55: 0 | P55: 0 | Q55: 0 | R55: 0 | S55: 0 | T55: 0 | U55: 0 | V55: 0 | W55: 0
E56: ='FS Qtr'!E46 -> [RCF interest expense paid] | F56: ='FS Qtr'!F46 -> 0 | G56: ='FS Qtr'!G$9 -> $ 000s | H56: ='FS Qtr'!H46 -> 0 | J56: =IF(ABS(K56) > TRK_TOL, "tu", "vw") -> vw | K56: =H56 - INDEX(M56:Z56, $J$5) -> 0 | L56: =IF(ABS(K56) > TRK_TOL, IF(INDEX(M56:Z56, $J$5) = 0, 0, H56 / INDEX(M56:Z56, $J$5) - 1), 0) -> 0 | N56: 0 | O56: 0 | P56: 0 | Q56: 0 | R56: 0 | S56: 0 | T56: 0 | U56: 0 | V56: 0 | W56: 0
E57: ='FS Qtr'!E47 -> Cash flow available for distribution | F57: ='FS Qtr'!F47 -> 0 | G57: ='FS Qtr'!G$9 -> $ 000s | H57: ='FS Qtr'!H47 -> 322667.04 | J57: =IF(ABS(K57) > TRK_TOL, "tu", "vw") -> vw | K57: =H57 - INDEX(M57:Z57, $J$5) -> 0 | L57: =IF(ABS(K57) > TRK_TOL, IF(INDEX(M57:Z57, $J$5) = 0, 0, H57 / INDEX(M57:Z57, $J$5) - 1), 0) -> 0 | N57: 322667.04 | O57: 322667.04 | P57: 322667.04 | Q57: 322667.04 | R57: 322667.04 | S57: 322667.04 | T57: 371409.68 | U57: 371409.68 | V57: 10000 | W57: 10000
E59: ='FS Qtr'!E49 -> Share capital redemption | F59: ='FS Qtr'!F49 -> 0 | G59: ='FS Qtr'!G$9 -> $ 000s | H59: ='FS Qtr'!H49 -> -30000 | J59: =IF(ABS(K59) > TRK_TOL, "tu", "vw") -> vw | K59: =H59 - INDEX(M59:Z59, $J$5) -> 0 | L59: =IF(ABS(K59) > TRK_TOL, IF(INDEX(M59:Z59, $J$5) = 0, 0, H59 / INDEX(M59:Z59, $J$5) - 1), 0) -> 0 | N59: -30000 | O59: -100000 | P59: 0 | Q59: 0 | R59: 0 | S59: 0 | T59: 0 | U59: 0 | V59: 0 | W59: 0
E60: ='FS Qtr'!E50 -> Cash flow available for dividends | F60: ='FS Qtr'!F50 -> 0 | G60: ='FS Qtr'!G$9 -> $ 000s | H60: ='FS Qtr'!H50 -> 292667.04 | J60: =IF(ABS(K60) > TRK_TOL, "tu", "vw") -> vw | N60: 292667.04 | O60: 222667.04 | P60: 322667.04 | Q60: 322667.04 | R60: 322667.04 | S60: 322667.04 | T60: 371409.68 | U60: 371409.68 | V60: 10000 | W60: 10000
E62: ='FS Qtr'!E52 -> Dividends paid | F62: ='FS Qtr'!F52 -> 0 | G62: ='FS Qtr'!G$9 -> $ 000s | H62: ='FS Qtr'!H52 -> -222667.04 | J62: =IF(ABS(K62) > TRK_TOL, "tu", "vw") -> vw | K62: =H62 - INDEX(M62:Z62, $J$5) -> 0 | L62: =IF(ABS(K62) > TRK_TOL, IF(INDEX(M62:Z62, $J$5) = 0, 0, H62 / INDEX(M62:Z62, $J$5) - 1), 0) -> 0 | N62: -222667.04 | O62: -222667.04 | P62: -222667.04 | Q62: -322667.04 | R62: -322667.04 | S62: 0 | T62: 0 | U62: 0 | V62: 0 | W62: 0
E63: ='FS Qtr'!E53 -> Net cash flow after dividends | F63: ='FS Qtr'!F53 -> 0 | G63: ='FS Qtr'!G$9 -> $ 000s | H63: ='FS Qtr'!H53 -> 70000 | J63: =IF(ABS(K63) > TRK_TOL, "tu", "vw") -> vw | N63: 70000 | O63: 3.774403e-11 | P63: 100000 | Q63: 0 | R63: 0 | S63: 322667.04 | T63: 371409.68 | U63: 371409.68 | V63: 10000 | W63: 10000
A66: OUTPUT ROW TEMPLATE
E67: [Output row template] | J67: =IF(ABS(K67) > TRK_TOL, "tu", "vw") -> vw | K67: =H67 - INDEX(M67:Z67, $J$5) -> 0 | L67: =IF(ABS(K67) > TRK_TOL, IF(INDEX(M67:Z67, $J$5) = 0, 0, H67 / INDEX(M67:Z67, $J$5) - 1), 0) -> 0
A70: MODEL RUN INFO
E71: Time | H71: =NOW() -> 44575.402 | N71: 44575.401 | O71: 44572.709 | P71: 44572.467 | Q71: 44572.375 | R71: 44572.288 | S71: 44571.375 | T71: 44571.345 | U71: 44564.567 | V71: 44564.438 | W71: 44564.412 | X71: 43909.145
E72: Filename | H72: =MID(CELL("filename",$A$1), SEARCH("[", CELL("filename",$A$1)) + 1, SEARCH("]", CELL("filename",$A$1)) - SEARCH("[", CELL("filename",$A$1)) - 1) -> FMH debt step1 01a.xlsx | N72: FMH debt step1 01a.xlsx | O72: FMH scr END 01a.xlsx | P72: FMH dep END 01a.xlsx | Q72: FMH IRR END 01a (version 1).xlsb | R72: FMH div END 01a.xlsx | S72: FMH AP END 01a.xlsx | T72: FMH Opex END 01a.xlsx | U72: 4.4 END 01a.xlsx | V72: 4.3 END 01a.xlsx | W72: 4.2 END.xlsx | X72: EFM 01a.xlsx
E74: [do not delete row] | J74: range end
A76: END

Sheet Check
A1: =RIGHT(CELL("filename", A1), LEN(CELL("filename", A1)) - SEARCH("]", CELL("filename", A1))) & " - " & InpC!F3 -> Check - Base case 1
F2: =Check!$F$9 -> 0 | G2: Error chks
F3: =Output!J2 -> 0 | G3: Track chgs
F4: =Check!$F$21 -> 0 | G4: Alerts
F5: Constant | G5: Unit
A7: CHECK SUMMARY
E9: Total checks | F9: =SUM(F10:F16) -> 0 | G9: check
E10: [do not delete this row] | F10: [range start]
E12: ='FS Qtr'!E$82 -> Balance sheet check | F12: ='FS Qtr'!F$82 -> 0 | G12: ='FS Qtr'!G$82 -> check
E13: ='FS Ann'!E$82 -> Annual balance sheet check | F13: ='FS Ann'!F$82 -> 0 | G13: ='FS Ann'!G$82 -> check
E16: [do not delete this row] | F16: [range end]
A19: ALERT SUMMARY
E21: Total alerts | F21: =SUM(F22:F31) -> 0 | G21: alert
E22: [do not delete this row] | F22: [range start]
E31: [do not delete this row] | F31: [range end]

Sheet Tmp
A1: =RIGHT(CELL("filename", A1), LEN(CELL("filename", A1)) - SEARCH("]", CELL("filename", A1))) & " - " & InpC!F3 -> Tmp - Base case 1
E2: =Time!E$25 -> Model period ending | F2: =Check!$F$9 -> 0 | G2: Error chks | J2: =Time!J$25 -> 44104 | K2: =Time!K$25 -> 44196 | L2: =Time!L$25 -> 44286 | M2: =Time!M$25 -> 44377 | N2: =Time!N$25 -> 44469 | O2: =Time!O$25 -> 44561 | P2: =Time!P$25 -> 44651 | Q2: =Time!Q$25 -> 44742 | ... EA2: =Time!EA$25 -> 55153
E3: =Time!E$67 -> Timeline label | F3: =Output!J2 -> 0 | G3: Track chgs | J3: =Time!J$67 -> Pre-fcst | K3: =Time!K$67 -> Pre-fcst | L3: =Time!L$67 -> Fin Close | M3: =Time!M$67 -> Operations | N3: =Time!N$67 -> Operations | O3: =Time!O$67 -> Operations | P3: =Time!P$67 -> Operations | Q3: =Time!Q$67 -> Operations | ... EA3: =Time!EA$67 -> Post ops
E4: =Time!E$42 -> Contract year | F4: =Check!$F$21 -> 0 | G4: Alerts | J4: =Time!J$42 -> 2020 | K4: =Time!K$42 -> 2020 | L4: =Time!L$42 -> 2020 | M4: =Time!M$42 -> 2021 | N4: =Time!N$42 -> 2021 | O4: =Time!O$42 -> 2021 | P4: =Time!P$42 -> 2021 | Q4: =Time!Q$42 -> 2022 | ... EA4: =Time!EA$42 -> 2050
E5: =Time!E$10 -> Model column counter | F5: Constant | G5: Unit | H5: Total | J5: =Time!J$10 -> 1 | K5: =Time!K$10 -> 2 | L5: =Time!L$10 -> 3 | M5: =Time!M$10 -> 4 | N5: =Time!N$10 -> 5 | O5: =Time!O$10 -> 6 | P5: =Time!P$10 -> 7 | Q5: =Time!Q$10 -> 8 | ... EA5: =Time!EA$10 -> 122
E8: [xxx] balance BEG | J8: =I11 -> 0 | K8: =J11 -> 0 | L8: =K11 -> 0 | M8: =L11 -> 0 | N8: =M11 -> 0 | O8: =N11 -> 0 | P8: =O11 -> 0 | Q8: =P11 -> 0 | ... EA8: =DZ11 -> 0
E9: [upward flow]
E10: [downward flow]
E11: [xxx] balance | J11: =J8 + J9 - J10 -> 0 | K11: =K8 + K9 - K10 -> 0 | L11: =L8 + L9 - L10 -> 0 | M11: =M8 + M9 - M10 -> 0 | N11: =N8 + N9 - N10 -> 0 | O11: =O8 + O9 - O10 -> 0 | P11: =P8 + P9 - P10 -> 0 | Q11: =Q8 + Q9 - Q10 -> 0 | ... EA11: =EA8 + EA9 - EA10 -> 0
E14: [xxx] - initial balance | G14: =SMU -> $ 000s
E15: =Time!E$76 -> Financial close date flag | F15: =Time!F$76 -> 0 | G15: =Time!G$76 -> flag | H15: =Time!H$76 -> 1 | I15: =Time!I$76 -> 0 | J15: =Time!J$76 -> 0 | K15: =Time!K$76 -> 0 | L15: =Time!L$76 -> 1 | ... EA15: =Time!EA$76 -> 0
E17: [xxx] balance BEG | G17: =SMU -> $ 000s | J17: =I20 -> 0 | K17: =J20 -> 0 | L17: =K20 -> 0 | M17: =L20 -> 0 | N17: =M20 -> 0 | O17: =N20 -> 0 | P17: =O20 -> 0 | Q17: =P20 -> 0 | ... EA17: =DZ20 -> 0
E18: [upward flow]
E19: [downward flow]
E20: [xxx] balance | G20: =SMU -> $ 000s | J20: =IF( J15 = 1, $F14, J17 + J18 - J19) -> 0 | K20: =IF( K15 = 1, $F14, K17 + K18 - K19) -> 0 | L20: =IF( L15 = 1, $F14, L17 + L18 - L19) -> 0 | M20: =IF( M15 = 1, $F14, M17 + M18 - M19) -> 0 | N20: =IF( N15 = 1, $F14, N17 + N18 - N19) -> 0 | O20: =IF( O15 = 1, $F14, O17 + O18 - O19) -> 0 | P20: =IF( P15 = 1, $F14, P17 + P18 - P19) -> 0 | Q20: =IF( Q15 = 1, $F14, Q17 + Q18 - Q19) -> 0 | ... EA20: =IF( EA15 = 1, $F14, EA17 + EA18 - EA19) -> 0
E23: Sign switch line item POS | G23: =SMU -> $ 000s | H23: =SUM(J23:EA23) -> 12200 | J23: 100 | K23: 100 | L23: 100 | M23: 100 | N23: 100 | O23: 100 | P23: 100 | Q23: 100 | R23: 100 | S23: 100 | T23: 100 | U23: 100 | V23: 100 | W23: 100 | X23: 100 | Y23: 100 | Z23: 100 | AA23: 100 | AB23: 100 | AC23: 100 | AD23: 100 | AE23: 100 | AF23: 100 | AG23: 100 | AH23: 100 | AI23: 100 | AJ23: 100 | AK23: 100 | AL23: 100 | AM23: 100 | AN23: 100 | AO23: 100 | AP23: 100 | AQ23: 100 | AR23: 100 | AS23: 100 | AT23: 100 | AU23: 100 | AV23: 100 | AW23: 100 | AX23: 100 | AY23: 100 | AZ23: 100 | BA23: 100 | BB23: 100 | BC23: 100 | BD23: 100 | BE23: 100 | BF23: 100 | BG23: 100 | BH23: 100 | BI23: 100 | BJ23: 100 | BK23: 100 | BL23: 100 | BM23: 100 | BN23: 100 | BO23: 100 | BP23: 100 | BQ23: 100 | BR23: 100 | BS23: 100 | BT23: 100 | BU23: 100 | BV23: 100 | BW23: 100 | BX23: 100 | BY23: 100 | BZ23: 100 | CA23: 100 | CB23: 100 | CC23: 100 | CD23: 100 | CE23: 100 | CF23: 100 | CG23: 100 | CH23: 100 | CI23: 100 | CJ23: 100 | CK23: 100 | CL23: 100 | CM23: 100 | CN23: 100 | CO23: 100 | CP23: 100 | CQ23: 100 | CR23: 100 | CS23: 100 | CT23: 100 | CU23: 100 | CV23: 100 | CW23: 100 | CX23: 100 | CY23: 100 | CZ23: 100 | DA23: 100 | DB23: 100 | DC23: 100 | DD23: 100 | DE23: 100 | DF23: 100 | DG23: 100 | DH23: 100 | DI23: 100 | DJ23: 100 | DK23: 100 | DL23: 100 | DM23: 100 | DN23: 100 | DO23: 100 | DP23: 100 | DQ23: 100 | DR23: 100 | DS23: 100 | DT23: 100 | DU23: 100 | DV23: 100 | DW23: 100 | DX23: 100 | DY23: 100 | DZ23: 100 | EA23: 100
E24: =LEFT(E23, LEN(E23) - 4) -> Sign switch line item | G24: =SMU -> $ 000s | H24: =SUM(J24:EA24) -> -12200 | J24: =-1 * J23 -> -100 | K24: =-1 * K23 -> -100 | L24: =-1 * L23 -> -100 | M24: =-1 * M23 -> -100 | N24: =-1 * N23 -> -100 | O24: =-1 * O23 -> -100 | P24: =-1 * P23 -> -100 | Q24: =-1 * Q23 -> -100 | ... EA24: =-1 * EA23 -> -100
A28: END
