Workbook
Name BaseCaseIndicator: InpC!$J$7:$S$7
Name CASE_ACTIVE: InpC!$F$4
Name CHK_TOL: InpC!$F$72
Name InputRowTemplate: InpC!$E$87:$S$87
Name InputStored: InpC!$J$3:$S$3
Name OutputRowTemplate: Output!$E$69:$AF$69
Name SMU: InpC!$F$75
Name TrackActive: Output!$H$5
Name TrackLiveResults: Output!$H$6:$H$76
Name TrackStoredResults: Output!$M$5:$AF$5
Name TRK_TOL: InpC!$F$71

Sheet InpC
A1: =RIGHT(CELL("filename", A1), LEN(CELL("filename", A1)) - SEARCH("]", CELL("filename", A1))) & " - " & $F$3 -> InpC - Base case 1
K2: =IF(K4 = $F4, "q", "") -> q | L2: =IF(L4 = $F4, "q", "") | M2: =IF(M4 = $F4, "q", "") | O2: =IF(O4 = $F4, "q", "") | P2: =IF(P4 = $F4, "q", "") | Q2: =IF(Q4 = $F4, "q", "") | R2: =IF(R4 = $F4, "q", "")
F3: =INDEX(J3:S3,MATCH(F4,J4:S4)) -> Base case 1 | K3: Base case 1 | L3: Base case 2 | M3: Base case 3 | O3: Scenario 1 | P3: Scenario 2 | Q3: Scenario 3 | R3: Scenario 4
E4: Active scenario | F4: 1 | I4: =MATCH(F4, $J$4:$S$4) -> 2 | K4: 1 | L4: 2 | M4: 3 | O4: 5 | P4: 6 | Q4: 7 | R4: 8
E5: Comparison scenario | F5: 1 | I5: =MATCH(F5, $J$4:$S$4) -> 2
E6: Base case | F6: =INDEX(J6:S6,MATCH(F4,J4:S4,0)) -> 1 | I6: =MATCH(F6, $J$4:$S$4) -> 2 | K6: 1 | L6: 2 | M6: 3 | O6: 1 | P6: 1 | Q6: 2 | R6: 2
E7: Input differences | F7: =COUNTIF(I10:I69, "tu") -> 0 | K7: =IF(K6 = $F$6, "Base case", "") -> Base case | L7: =IF(L6 = $F$6, "Base case", "") | M7: =IF(M6 = $F$6, "Base case", "")
F9: Constant | G9: Unit | H9: Source
A11: TIMING ASSUMPTIONS
E13: First date of time rulers | F13: =IF( INDEX(J13:S13, $I$4) = "", INDEX(J13:R13, $I$6), INDEX(J13:S13, $I$4)) -> 44013 | G13: date | I13: {=IF( INDEX(J13:S13, I$5) = "", IF( INDEX(J13:S13, I$6) = F13, "vw", "tu"), IF(INDEX(J13:S13, I$5) = F13, "vw", "tu"))} -> vw | K13: 44013
E14: Annual year end date of first operating period | F14: =IF( INDEX(J14:S14, $I$4) = "", INDEX(J14:R14, $I$6), INDEX(J14:S14, $I$4)) -> 43921 | G14: date | I14: {=IF( INDEX(J14:S14, I$5) = "", IF( INDEX(J14:S14, I$6) = F14, "vw", "tu"), IF(INDEX(J14:S14, I$5) = F14, "vw", "tu"))} -> vw | K14: 43921
E15: Financial year end month number | F15: =IF( INDEX(J15:S15, $I$4) = "", INDEX(J15:R15, $I$6), INDEX(J15:S15, $I$4)) -> 12 | G15: month # | I15: {=IF( INDEX(J15:S15, I$5) = "", IF( INDEX(J15:S15, I$6) = F15, "vw", "tu"), IF(INDEX(J15:S15, I$5) = F15, "vw", "tu"))} -> vw | K15: 12
E16: Length of operating period | F16: =IF( INDEX(J16:S16, $I$4) = "", INDEX(J16:R16, $I$6), INDEX(J16:S16, $I$4)) -> 3 | G16: months | I16: {=IF( INDEX(J16:S16, I$5) = "", IF( INDEX(J16:S16, I$6) = F16, "vw", "tu"), IF(INDEX(J16:S16, I$5) = F16, "vw", "tu"))} -> vw | K16: 3
E18: Acquisition date | F18: =IF( INDEX(J18:S18, $I$4) = "", INDEX(J18:R18, $I$6), INDEX(J18:S18, $I$4)) -> 44286 | G18: date | I18: {=IF( INDEX(J18:S18, I$5) = "", IF( INDEX(J18:S18, I$6) = F18, "vw", "tu"), IF(INDEX(J18:S18, I$5) = F18, "vw", "tu"))} -> vw | K18: 44286
E20: Operating years remaining | F20: =IF( INDEX(J20:S20, $I$4) = "", INDEX(J20:R20, $I$6), INDEX(J20:S20, $I$4)) -> 25 | G20: years | I20: {=IF( INDEX(J20:S20, I$5) = "", IF( INDEX(J20:S20, I$6) = F20, "vw", "tu"), IF(INDEX(J20:S20, I$5) = F20, "vw", "tu"))} -> vw | K20: 25
E21: Contract extension | F21: =IF( INDEX(J21:S21, $I$4) = "", INDEX(J21:R21, $I$6), INDEX(J21:S21, $I$4)) -> 0 | G21: years | I21: {=IF( INDEX(J21:S21, I$5) = "", IF( INDEX(J21:S21, I$6) = F21, "vw", "tu"), IF(INDEX(J21:S21, I$5) = F21, "vw", "tu"))} -> vw | K21: 0
A23: REVENUE
E24: Q1 seasonal adjustment | F24: =IF( INDEX(J24:S24, $I$4) = "", INDEX(J24:R24, $I$6), INDEX(J24:S24, $I$4)) -> 0.33 | G24: % of annual yield | I24: {=IF( INDEX(J24:S24, I$5) = "", IF( INDEX(J24:S24, I$6) = F24, "vw", "tu"), IF(INDEX(J24:S24, I$5) = F24, "vw", "tu"))} -> vw | K24: 0.33 | L24: 0.33 | M24: 0.33
E25: Q2 seasonal adjustment | F25: =IF( INDEX(J25:S25, $I$4) = "", INDEX(J25:R25, $I$6), INDEX(J25:S25, $I$4)) -> 0.36 | G25: % of annual yield | I25: {=IF( INDEX(J25:S25, I$5) = "", IF( INDEX(J25:S25, I$6) = F25, "vw", "tu"), IF(INDEX(J25:S25, I$5) = F25, "vw", "tu"))} -> vw | K25: 0.36 | L25: 0.36 | M25: 0.36
E26: Q3 seasonal adjustment | F26: =IF( INDEX(J26:S26, $I$4) = "", INDEX(J26:R26, $I$6), INDEX(J26:S26, $I$4)) -> 0.155 | G26: % of annual yield | I26: {=IF( INDEX(J26:S26, I$5) = "", IF( INDEX(J26:S26, I$6) = F26, "vw", "tu"), IF(INDEX(J26:S26, I$5) = F26, "vw", "tu"))} -> vw | K26: 0.155 | L26: 0.155 | M26: 0.155
E27: Q4 seasonal adjustment | F27: =IF( INDEX(J27:S27, $I$4) = "", INDEX(J27:R27, $I$6), INDEX(J27:S27, $I$4)) -> 0.155 | G27: % of annual yield | I27: {=IF( INDEX(J27:S27, I$5) = "", IF( INDEX(J27:S27, I$6) = F27, "vw", "tu"), IF(INDEX(J27:S27, I$5) = F27, "vw", "tu"))} -> vw | K27: 0.155 | L27: 0.155 | M27: 0.155
E29: Annual degradation | F29: =IF( INDEX(J29:S29, $I$4) = "", INDEX(J29:R29, $I$6), INDEX(J29:S29, $I$4)) -> 0.005 | G29: % p.a. | I29: {=IF( INDEX(J29:S29, I$5) = "", IF( INDEX(J29:S29, I$6) = F29, "vw", "tu"), IF(INDEX(J29:S29, I$5) = F29, "vw", "tu"))} -> vw | K29: 0.005 | L29: 0.005 | M29: 0.005
E30: Year 1 P50 yield | F30: =IF( INDEX(J30:S30, $I$4) = "", INDEX(J30:R30, $I$6), INDEX(J30:S30, $I$4)) -> 250 | G30: GWh | I30: {=IF( INDEX(J30:S30, I$5) = "", IF( INDEX(J30:S30, I$6) = F30, "vw", "tu"), IF(INDEX(J30:S30, I$5) = F30, "vw", "tu"))} -> vw | K30: 250 | L30: 250 | M30: 250
E31: Availability | F31: =IF( INDEX(J31:S31, $I$4) = "", INDEX(J31:R31, $I$6), INDEX(J31:S31, $I$4)) -> 0.97 | G31: % | I31: {=IF( INDEX(J31:S31, I$5) = "", IF( INDEX(J31:S31, I$6) = F31, "vw", "tu"), IF(INDEX(J31:S31, I$5) = F31, "vw", "tu"))} -> vw | K31: 0.97 | L31: 0.97 | M31: 0.97
E33: Power tariff | F33: =IF( INDEX(J33:S33, $I$4) = "", INDEX(J33:R33, $I$6), INDEX(J33:S33, $I$4)) -> 0.065 | G33: USD / kWh | I33: {=IF( INDEX(J33:S33, I$5) = "", IF( INDEX(J33:S33, I$6) = F33, "vw", "tu"), IF(INDEX(J33:S33, I$5) = F33, "vw", "tu"))} -> vw | K33: 0.065 | L33: 0.065 | M33: 0.065
A36: OPERATING COSTS
E37: Annual fixed real O&M cost | F37: =IF( INDEX(J37:S37, $I$4) = "", INDEX(J37:R37, $I$6), INDEX(J37:S37, $I$4)) -> 1500 | G37: =SMU -> $ 000s | I37: {=IF( INDEX(J37:S37, I$5) = "", IF( INDEX(J37:S37, I$6) = F37, "vw", "tu"), IF(INDEX(J37:S37, I$5) = F37, "vw", "tu"))} -> vw | K37: 1500 | L37: 1500 | M37: 1500
A40: FIXED ASSET
E41: Useful life of asset | F41: =IF( INDEX(J41:S41, $I$4) = "", INDEX(J41:R41, $I$6), INDEX(J41:S41, $I$4)) -> 25 | G41: years | I41: {=IF( INDEX(J41:S41, I$5) = "", IF( INDEX(J41:S41, I$6) = F41, "vw", "tu"), IF(INDEX(J41:S41, I$5) = F41, "vw", "tu"))} -> vw | K41: 25 | L41: 25 | M41: 25
A44: SENIOR DEBT
E45: Senior debt repayment period | F45: =IF( INDEX(J45:S45, $I$4) = "", INDEX(J45:R45, $I$6), INDEX(J45:S45, $I$4)) -> 10 | G45: years | I45: {=IF( INDEX(J45:S45, I$5) = "", IF( INDEX(J45:S45, I$6) = F45, "vw", "tu"), IF(INDEX(J45:S45, I$5) = F45, "vw", "tu"))} -> vw | K45: 10 | L45: 10 | M45: 10
E46: Senior debt leverage | F46: =IF( INDEX(J46:S46, $I$4) = "", INDEX(J46:R46, $I$6), INDEX(J46:S46, $I$4)) -> 0.7 | G46: % | I46: {=IF( INDEX(J46:S46, I$5) = "", IF( INDEX(J46:S46, I$6) = F46, "vw", "tu"), IF(INDEX(J46:S46, I$5) = F46, "vw", "tu"))} -> vw | K46: 0.7 | L46: 0.7 | M46: 0.7
E47: Senior debt principal repayment profile selection | F47: =IF( INDEX(J47:S47, $I$4) = "", INDEX(J47:R47, $I$6), INDEX(J47:S47, $I$4)) -> 3 | G47: profile selection | I47: {=IF( INDEX(J47:S47, I$5) = "", IF( INDEX(J47:S47, I$6) = F47, "vw", "tu"), IF(INDEX(J47:S47, I$5) = F47, "vw", "tu"))} -> vw | K47: 3 | L47: 1 | M47: 1
E48: Senior debt swap rate | F48: =IF( INDEX(J48:S48, $I$4) = "", INDEX(J48:R48, $I$6), INDEX(J48:S48, $I$4)) -> 0.025 | G48: % p.a. | I48: {=IF( INDEX(J48:S48, I$5) = "", IF( INDEX(J48:S48, I$6) = F48, "vw", "tu"), IF(INDEX(J48:S48, I$5) = F48, "vw", "tu"))} -> vw | K48: 0.025 | L48: 0.025 | M48: 0.025
E49: Senior debt margin | F49: =IF( INDEX(J49:S49, $I$4) = "", INDEX(J49:R49, $I$6), INDEX(J49:S49, $I$4)) -> 0.035 | G49: % p.a. | I49: {=IF( INDEX(J49:S49, I$5) = "", IF( INDEX(J49:S49, I$6) = F49, "vw", "tu"), IF(INDEX(J49:S49, I$5) = F49, "vw", "tu"))} -> vw | K49: 0.035 | L49: 0.035 | M49: 0.035
E50: Senior debt day count convention | F50: =IF( INDEX(J50:S50, $I$4) = "", INDEX(J50:R50, $I$6), INDEX(J50:S50, $I$4)) -> 360 | G50: days / year | I50: {=IF( INDEX(J50:S50, I$5) = "", IF( INDEX(J50:S50, I$6) = F50, "vw", "tu"), IF(INDEX(J50:S50, I$5) = F50, "vw", "tu"))} -> vw | K50: 360 | L50: 360 | M50: 360
E51: DSCR for debt sizing | F51: =IF( INDEX(J51:S51, $I$4) = "", INDEX(J51:R51, $I$6), INDEX(J51:S51, $I$4)) -> 1.3 | G51: ratio | I51: {=IF( INDEX(J51:S51, I$5) = "", IF( INDEX(J51:S51, I$6) = F51, "vw", "tu"), IF(INDEX(J51:S51, I$5) = F51, "vw", "tu"))} -> vw | K51: 1.3 | L51: 1.3 | M51: 1.3
E52: Senior debt sizing method | F52: =IF( INDEX(J52:S52, $I$4) = "", INDEX(J52:R52, $I$6), INDEX(J52:S52, $I$4)) -> 2 | G52: 1 = leverage, 2 = DSCR | I52: {=IF( INDEX(J52:S52, I$5) = "", IF( INDEX(J52:S52, I$6) = F52, "vw", "tu"), IF(INDEX(J52:S52, I$5) = F52, "vw", "tu"))} -> vw | K52: 2 | L52: 2 | M52: 2
A56: WORKING CAPITAL
E57: Accounts receivable days | F57: =IF( INDEX(J57:S57, $I$4) = "", INDEX(J57:R57, $I$6), INDEX(J57:S57, $I$4)) -> 60 | G57: days | I57: {=IF( INDEX(J57:S57, I$5) = "", IF( INDEX(J57:S57, I$6) = F57, "vw", "tu"), IF(INDEX(J57:S57, I$5) = F57, "vw", "tu"))} -> vw | K57: 60 | L57: 60 | M57: 60
E58: Accounts payable days | F58: =IF( INDEX(J58:S58, $I$4) = "", INDEX(J58:R58, $I$6), INDEX(J58:S58, $I$4)) -> 30 | G58: days | I58: {=IF( INDEX(J58:S58, I$5) = "", IF( INDEX(J58:S58, I$6) = F58, "vw", "tu"), IF(INDEX(J58:S58, I$5) = F58, "vw", "tu"))} -> vw | K58: 30 | L58: 30 | M58: 30
A60: OPENING BALANCES
E61: Retained earnings - initial balance | F61: =IF( INDEX(J61:S61, $I$4) = "", INDEX(J61:R61, $I$6), INDEX(J61:S61, $I$4)) -> 0 | G61: =SMU -> $ 000s | I61: {=IF( INDEX(J61:S61, I$5) = "", IF( INDEX(J61:S61, I$6) = F61, "vw", "tu"), IF(INDEX(J61:S61, I$5) = F61, "vw", "tu"))} -> vw | K61: 0 | L61: 0 | M61: 0
E62: Retained cash - initial balance | F62: =IF( INDEX(J62:S62, $I$4) = "", INDEX(J62:R62, $I$6), INDEX(J62:S62, $I$4)) -> 0 | G62: =SMU -> $ 000s | I62: {=IF( INDEX(J62:S62, I$5) = "", IF( INDEX(J62:S62, I$6) = F62, "vw", "tu"), IF(INDEX(J62:S62, I$5) = F62, "vw", "tu"))} -> vw | K62: 0 | L62: 0 | M62: 0
E63: Accounts receivable - initial balance | F63: =IF( INDEX(J63:S63, $I$4) = "", INDEX(J63:R63, $I$6), INDEX(J63:S63, $I$4)) -> 0 | G63: =SMU -> $ 000s | I63: {=IF( INDEX(J63:S63, I$5) = "", IF( INDEX(J63:S63, I$6) = F63, "vw", "tu"), IF(INDEX(J63:S63, I$5) = F63, "vw", "tu"))} -> vw | K63: 0 | L63: 0 | M63: 0
E64: Accounts payable - initial balance | F64: =IF( INDEX(J64:S64, $I$4) = "", INDEX(J64:R64, $I$6), INDEX(J64:S64, $I$4)) -> 0 | G64: =SMU -> $ 000s | I64: {=IF( INDEX(J64:S64, I$5) = "", IF( INDEX(J64:S64, I$6) = F64, "vw", "tu"), IF(INDEX(J64:S64, I$5) = F64, "vw", "tu"))} -> vw | K64: 0 | L64: 0 | M64: 0
E65: Fixed asset - initial balance | F65: =IF( INDEX(J65:S65, $I$4) = "", INDEX(J65:R65, $I$6), INDEX(J65:S65, $I$4)) -> 100000 | G65: =SMU -> $ 000s | I65: {=IF( INDEX(J65:S65, I$5) = "", IF( INDEX(J65:S65, I$6) = F65, "vw", "tu"), IF(INDEX(J65:S65, I$5) = F65, "vw", "tu"))} -> vw | K65: 100000 | L65: 100000 | M65: 100000
A69: MODEL TECHNICAL INPUTS - DO NOT CHANGE
E71: Model track tolerance level | F71: 0.001 | G71: tolerance
E72: Model check tolerance level | F72: 0.001 | G72: tolerance
E73: Months in year | F73: 12 | G73: months
E74: Number of periods in a year | F74: 4 | G74: periods
E75: Standard Monetary Unit | F75: $ 000s | G75: named "SMU"
E76: US$c / US$ | F76: 100 | G76: US$c / US$
E77: GWh to kWh conversion | F77: 1000000 | G77: kWh / GWh
E78: Units in a thousand | F78: 1000 | G78: units
E79: Small negative value for XIRR | F79: -1e-07 | G79: $ 000s
B81: Timeline label
E82: Pre-forecast period | F82: Pre-fcst | G82: label
E83: Financial Close | F83: Fin Close | G83: label
E84: Operations | F84: Operations | G84: label
E85: Post ops | F85: Post ops | G85: label
E87: Input row template for relocation macro | F87: =IF( INDEX(J87:S87, $I$4) = "", INDEX(J87:R87, $I$6), INDEX(J87:S87, $I$4)) -> 0 | G87: unit | I87: {=IF( INDEX(J87:S87, I$5) = "", IF( INDEX(J87:S87, I$6) = F87, "vw", "tu"), IF(INDEX(J87:S87, I$5) = F87, "vw", "tu"))} -> vw
A90: END

Sheet Time
A1: =RIGHT(CELL("filename", A1), LEN(CELL("filename", A1)) - SEARCH("]", CELL("filename", A1))) & " - " & InpC!F3 -> Time - Base case 1
E2: =Time!E$25 -> Model period ending | F2: =Check!$F$9 -> 0 | G2: Error chks | J2: =Time!J$25 -> 44104 | K2: =Time!K$25 -> 44196 | L2: =Time!L$25 -> 44286 | M2: =Time!M$25 -> 44377 | N2: =Time!N$25 -> 44469 | O2: =Time!O$25 -> 44561 | P2: =Time!P$25 -> 44651 | Q2: =Time!Q$25 -> 44742 | ... EA2: =Time!EA$25 -> 55153
E3: =Time!E$67 -> Timeline label | F3: =Output!J2 -> 0 | G3: Track chgs | J3: =Time!J$67 -> Pre-fcst | K3: =Time!K$67 -> Pre-fcst | L3: =Time!L$67 -> Fin Close | M3: =Time!M$67 -> Operations | N3: =Time!N$67 -> Operations | O3: =Time!O$67 -> Operations | P3: =Time!P$67 -> Operations | Q3: =Time!Q$67 -> Operations | ... EA3: =Time!EA$67 -> Post ops
E4: =Time!E$42 -> Contract year | F4: =Check!$F$21 -> 0 | G4: Alerts | J4: =Time!J$42 -> 2020 | K4: =Time!K$42 -> 2020 | L4: =Time!L$42 -> 2020 | M4: =Time!M$42 -> 2021 | N4: =Time!N$42 -> 2021 | O4: =Time!O$42 -> 2021 | P4: =Time!P$42 -> 2021 | Q4: =Time!Q$42 -> 2022 | ... EA4: =Time!EA$42 -> 2050
E5: =Time!E$10 -> Model column counter | F5: Constant | G5: Unit | H5: Total | J5: =Time!J$10 -> 1 | K5: =Time!K$10 -> 2 | L5: =Time!L$10 -> 3 | M5: =Time!M$10 -> 4 | N5: =Time!N$10 -> 5 | O5: =Time!O$10 -> 6 | P5: =Time!P$10 -> 7 | Q5: =Time!Q$10 -> 8 | ... EA5: =Time!EA$10 -> 122
A7: TIME RULER
B9: First model column
E10: Model column counter | G10: counter | J10: =I10 + 1 -> 1 | K10: =J10 + 1 -> 2 | L10: =K10 + 1 -> 3 | M10: =L10 + 1 -> 4 | N10: =M10 + 1 -> 5 | O10: =N10 + 1 -> 6 | P10: =O10 + 1 -> 7 | Q10: =P10 + 1 -> 8 | ... EA10: =DZ10 + 1 -> 122
E11: Model column total | F11: =MAX(J10:EA10) -> 122 | G11: columns
E13: =E$10 -> Model column counter | F13: =F$10 -> 0 | G13: =G$10 -> counter | H13: =H$10 -> 0 | I13: =I$10 -> 0 | J13: =J$10 -> 1 | K13: =K$10 -> 2 | L13: =L$10 -> 3 | ... EA13: =EA$10 -> 122
E14: First model column flag | G14: flag | H14: =SUM(J14:EA14) -> 1 | J14: =IF(J13 = 1, 1, 0) -> 1 | K14: =IF(K13 = 1, 1, 0) -> 0 | L14: =IF(L13 = 1, 1, 0) -> 0 | M14: =IF(M13 = 1, 1, 0) -> 0 | N14: =IF(N13 = 1, 1, 0) -> 0 | O14: =IF(O13 = 1, 1, 0) -> 0 | P14: =IF(P13 = 1, 1, 0) -> 0 | Q14: =IF(Q13 = 1, 1, 0) -> 0 | ... EA14: =IF(EA13 = 1, 1, 0) -> 0
B16: Model period beginning
E17: =InpC!E$13 -> First date of time rulers | F17: =InpC!F$13 -> 44013 | G17: =InpC!G$13 -> date
E18: =InpC!E$16 -> Length of operating period | F18: =InpC!F$16 -> 3 | G18: =InpC!G$16 -> months
E19: =E$14 -> First model column flag | F19: =F$14 -> 0 | G19: =G$14 -> flag | H19: =H$14 -> 1 | I19: =I$14 -> 0 | J19: =J$14 -> 1 | K19: =K$14 -> 0 | L19: =L$14 -> 0 | ... EA19: =EA$14 -> 0
E20: Model period beginning | G20: date | J20: =IF(J19 = 1, $F17, DATE(YEAR(I20), MONTH(I20) + $F18, DAY(1))) -> 44013 | K20: =IF(K19 = 1, $F17, DATE(YEAR(J20), MONTH(J20) + $F18, DAY(1))) -> 44105 | L20: =IF(L19 = 1, $F17, DATE(YEAR(K20), MONTH(K20) + $F18, DAY(1))) -> 44197 | M20: =IF(M19 = 1, $F17, DATE(YEAR(L20), MONTH(L20) + $F18, DAY(1))) -> 44287 | N20: =IF(N19 = 1, $F17, DATE(YEAR(M20), MONTH(M20) + $F18, DAY(1))) -> 44378 | O20: =IF(O19 = 1, $F17, DATE(YEAR(N20), MONTH(N20) + $F18, DAY(1))) -> 44470 | P20: =IF(P19 = 1, $F17, DATE(YEAR(O20), MONTH(O20) + $F18, DAY(1))) -> 44562 | Q20: =IF(Q19 = 1, $F17, DATE(YEAR(P20), MONTH(P20) + $F18, DAY(1))) -> 44652 | ... EA20: =IF(EA19 = 1, $F17, DATE(YEAR(DZ20), MONTH(DZ20) + $F18, DAY(1))) -> 55062
B22: Model period ending
E23: =InpC!E$16 -> Length of operating period | F23: =InpC!F$16 -> 3 | G23: =InpC!G$16 -> months
E24: =E$20 -> Model period beginning | F24: =F$20 -> 0 | G24: =G$20 -> date | H24: =H$20 -> 0 | I24: =I$20 -> 0 | J24: =J$20 -> 44013 | K24: =K$20 -> 44105 | L24: =L$20 -> 44197 | ... EA24: =EA$20 -> 55062
E25: Model period ending | G25: date | J25: =DATE(YEAR(J24), MONTH(J24) + $F23, DAY(J24) -1) -> 44104 | K25: =DATE(YEAR(K24), MONTH(K24) + $F23, DAY(K24) -1) -> 44196 | L25: =DATE(YEAR(L24), MONTH(L24) + $F23, DAY(L24) -1) -> 44286 | M25: =DATE(YEAR(M24), MONTH(M24) + $F23, DAY(M24) -1) -> 44377 | N25: =DATE(YEAR(N24), MONTH(N24) + $F23, DAY(N24) -1) -> 44469 | O25: =DATE(YEAR(O24), MONTH(O24) + $F23, DAY(O24) -1) -> 44561 | P25: =DATE(YEAR(P24), MONTH(P24) + $F23, DAY(P24) -1) -> 44651 | Q25: =DATE(YEAR(Q24), MONTH(Q24) + $F23, DAY(Q24) -1) -> 44742 | ... EA25: =DATE(YEAR(EA24), MONTH(EA24) + $F23, DAY(EA24) -1) -> 55153
B27: Contract year
E28: =InpC!E$18 -> Acquisition date | F28: =InpC!F$18 -> 44286 | G28: =InpC!G$18 -> date
E29: Contract year end month | F29: =MONTH(F28) -> 3 | G29: month
E31: =E$29 -> Contract year end month | F31: =F$29 -> 3 | G31: =G$29 -> month
E32: =E$25 -> Model period ending | F32: =F$25 -> 0 | G32: =G$25 -> date | H32: =H$25 -> 0 | I32: =I$25 -> 0 | J32: =J$25 -> 44104 | K32: =K$25 -> 44196 | L32: =L$25 -> 44286 | ... EA32: =EA$25 -> 55153
E33: End of contract year flag | J33: =IF( MONTH(J32) = $F31, 1, 0) -> 0 | K33: =IF( MONTH(K32) = $F31, 1, 0) -> 0 | L33: =IF( MONTH(L32) = $F31, 1, 0) -> 1 | M33: =IF( MONTH(M32) = $F31, 1, 0) -> 0 | N33: =IF( MONTH(N32) = $F31, 1, 0) -> 0 | O33: =IF( MONTH(O32) = $F31, 1, 0) -> 0 | P33: =IF( MONTH(P32) = $F31, 1, 0) -> 1 | Q33: =IF( MONTH(Q32) = $F31, 1, 0) -> 0 | ... EA33: =IF( MONTH(EA32) = $F31, 1, 0) -> 0
E35: =InpC!E$14 -> Annual year end date of first operating period | F35: =InpC!F$14 -> 43921 | G35: =InpC!G$14 -> date
E36: =InpC!E$73 -> Months in year | F36: =InpC!F$73 -> 12 | G36: =InpC!G$73 -> months
E37: =E$14 -> First model column flag | F37: =F$14 -> 0 | G37: =G$14 -> flag | H37: =H$14 -> 1 | I37: =I$14 -> 0 | J37: =J$14 -> 1 | K37: =K$14 -> 0 | L37: =L$14 -> 0 | ... EA37: =EA$14 -> 0
E38: =E$33 -> End of contract year flag | F38: =F$33 -> 0 | G38: =G$33 -> 0 | H38: =H$33 -> 0 | I38: =I$33 -> 0 | J38: =J$33 -> 0 | K38: =K$33 -> 0 | L38: =L$33 -> 1 | ... EA38: =EA$33 -> 0
E39: Contract year applicable to period | G39: date | J39: =IF( J37 = 1, $F35, IF( I38 = 1, EOMONTH(I39, 12), I39)) -> 43921 | K39: =IF( K37 = 1, $F35, IF( J38 = 1, EOMONTH(J39, 12), J39)) -> 43921 | L39: =IF( L37 = 1, $F35, IF( K38 = 1, EOMONTH(K39, 12), K39)) -> 43921 | M39: =IF( M37 = 1, $F35, IF( L38 = 1, EOMONTH(L39, 12), L39)) -> 44286 | N39: =IF( N37 = 1, $F35, IF( M38 = 1, EOMONTH(M39, 12), M39)) -> 44286 | O39: =IF( O37 = 1, $F35, IF( N38 = 1, EOMONTH(N39, 12), N39)) -> 44286 | P39: =IF( P37 = 1, $F35, IF( O38 = 1, EOMONTH(O39, 12), O39)) -> 44286 | Q39: =IF( Q37 = 1, $F35, IF( P38 = 1, EOMONTH(P39, 12), P39)) -> 44651 | ... EA39: =IF( EA37 = 1, $F35, IF( DZ38 = 1, EOMONTH(DZ39, 12), DZ39)) -> 54878
E41: =E$39 -> Contract year applicable to period | F41: =F$39 -> 0 | G41: =G$39 -> date | H41: =H$39 -> 0 | I41: =I$39 -> 0 | J41: =J$39 -> 43921 | K41: =K$39 -> 43921 | L41: =L$39 -> 43921 | ... EA41: =EA$39 -> 54878
E42: Contract year | G42: year # | J42: =YEAR(J41) -> 2020 | K42: =YEAR(K41) -> 2020 | L42: =YEAR(L41) -> 2020 | M42: =YEAR(M41) -> 2021 | N42: =YEAR(N41) -> 2021 | O42: =YEAR(O41) -> 2021 | P42: =YEAR(P41) -> 2021 | Q42: =YEAR(Q41) -> 2022 | ... EA42: =YEAR(EA41) -> 2050
B44: Annual timeline
E45: =InpC!E$14 -> Annual year end date of first operating period | F45: =InpC!F$14 -> 43921 | G45: =InpC!G$14 -> date
E46: =InpC!E$73 -> Months in year | F46: =InpC!F$73 -> 12 | G46: =InpC!G$73 -> months
E47: =E$14 -> First model column flag | F47: =F$14 -> 0 | G47: =G$14 -> flag | H47: =H$14 -> 1 | I47: =I$14 -> 0 | J47: =J$14 -> 1 | K47: =K$14 -> 0 | L47: =L$14 -> 0 | ... EA47: =EA$14 -> 0
E48: Model period ending - annual | G48: date | J48: =IF(J47 = 1, $F45, EOMONTH(I48, $F46)) -> 43921 | K48: =IF(K47 = 1, $F45, EOMONTH(J48, $F46)) -> 44286 | L48: =IF(L47 = 1, $F45, EOMONTH(K48, $F46)) -> 44651 | M48: =IF(M47 = 1, $F45, EOMONTH(L48, $F46)) -> 45016 | N48: =IF(N47 = 1, $F45, EOMONTH(M48, $F46)) -> 45382 | O48: =IF(O47 = 1, $F45, EOMONTH(N48, $F46)) -> 45747 | P48: =IF(P47 = 1, $F45, EOMONTH(O48, $F46)) -> 46112 | Q48: =IF(Q47 = 1, $F45, EOMONTH(P48, $F46)) -> 46477 | ... EA48: =IF(EA47 = 1, $F45, EOMONTH(DZ48, $F46)) -> 88115
E50: =E$67 -> Timeline label | F50: =F$67 -> 0 | G50: =G$67 -> label | H50: =H$67 -> 0 | I50: =I$67 -> 0 | J50: =J$67 -> Pre-fcst | K50: =K$67 -> Pre-fcst | L50: =L$67 -> Fin Close | ... EA50: =EA$67 -> Post ops
E51: =E$48 -> Model period ending - annual | F51: =F$48 -> 0 | G51: =G$48 -> date | H51: =H$48 -> 0 | I51: =I$48 -> 0 | J51: =J$48 -> 43921 | K51: =K$48 -> 44286 | L51: =L$48 -> 44651 | ... EA51: =EA$48 -> 88115
E52: =E$41 -> Contract year applicable to period | F52: =F$41 -> 0 | G52: =G$41 -> date | H52: =H$41 -> 0 | I52: =I$41 -> 0 | J52: =J$41 -> 43921 | K52: =K$41 -> 43921 | L52: =L$41 -> 43921 | ... EA52: =EA$41 -> 54878
E53: Timeline label - annual | J53: =IF(ISNA(INDEX($J$50:$EA$50,MATCH(J51,$J$52:$EA$52,0))),"Pre-fcst",INDEX($J$50:$EA$50,MATCH(J51,$J$52:$EA$52,0))) -> Pre-fcst | K53: =IF(ISNA(INDEX($J$50:$EA$50,MATCH(K51,$J$52:$EA$52,0))),"Pre-fcst",INDEX($J$50:$EA$50,MATCH(K51,$J$52:$EA$52,0))) -> Operations | L53: =IF(ISNA(INDEX($J$50:$EA$50,MATCH(L51,$J$52:$EA$52,0))),"Pre-fcst",INDEX($J$50:$EA$50,MATCH(L51,$J$52:$EA$52,0))) -> Operations | M53: =IF(ISNA(INDEX($J$50:$EA$50,MATCH(M51,$J$52:$EA$52,0))),"Pre-fcst",INDEX($J$50:$EA$50,MATCH(M51,$J$52:$EA$52,0))) -> Operations | N53: =IF(ISNA(INDEX($J$50:$EA$50,MATCH(N51,$J$52:$EA$52,0))),"Pre-fcst",INDEX($J$50:$EA$50,MATCH(N51,$J$52:$EA$52,0))) -> Operations | O53: =IF(ISNA(INDEX($J$50:$EA$50,MATCH(O51,$J$52:$EA$52,0))),"Pre-fcst",INDEX($J$50:$EA$50,MATCH(O51,$J$52:$EA$52,0))) -> Operations | P53: =IF(ISNA(INDEX($J$50:$EA$50,MATCH(P51,$J$52:$EA$52,0))),"Pre-fcst",INDEX($J$50:$EA$50,MATCH(P51,$J$52:$EA$52,0))) -> Operations | Q53: =IF(ISNA(INDEX($J$50:$EA$50,MATCH(Q51,$J$52:$EA$52,0))),"Pre-fcst",INDEX($J$50:$EA$50,MATCH(Q51,$J$52:$EA$52,0))) -> Operations | ... BC53: =IF(ISNA(INDEX($J$50:$EA$50,MATCH(BC51,$J$52:$EA$52,0))),"Pre-fcst",INDEX($J$50:$EA$50,MATCH(BC51,$J$52:$EA$52,0))) -> Pre-fcst
B55: Quarterly timeline
E56: =E$14 -> First model column flag | F56: =F$14 -> 0 | G56: =G$14 -> flag | H56: =H$14 -> 1 | I56: =I$14 -> 0 | J56: =J$14 -> 1 | K56: =K$14 -> 0 | L56: =L$14 -> 0 | ... EA56: =EA$14 -> 0
E57: =E$76 -> Financial close date flag | F57: =F$76 -> 0 | G57: =G$76 -> flag | H57: =H$76 -> 1 | I57: =I$76 -> 0 | J57: =J$76 -> 0 | K57: =K$76 -> 0 | L57: =L$76 -> 1 | ... EA57: =EA$76 -> 0
E58: =E$80 -> First operating period flag | F58: =F$80 -> 0 | G58: =G$80 -> flag | H58: =H$80 -> 1 | I58: =I$80 -> 0 | J58: =J$80 -> 0 | K58: =K$80 -> 0 | L58: =L$80 -> 0 | ... EA58: =EA$80 -> 0
E59: =E$113 -> First post operating period flag | F59: =F$113 -> 0 | G59: =G$113 -> 0 | H59: =H$113 -> 0 | I59: =I$113 -> 0 | J59: =J$113 -> 0 | K59: =K$113 -> 0 | L59: =L$113 -> 0 | ... EA59: =EA$113 -> 0
E60: Timeline label counter | G60: counter | J60: =I60 + MAX(J56:J59) -> 1 | K60: =J60 + MAX(K56:K59) -> 1 | L60: =K60 + MAX(L56:L59) -> 2 | M60: =L60 + MAX(M56:M59) -> 3 | N60: =M60 + MAX(N56:N59) -> 3 | O60: =N60 + MAX(O56:O59) -> 3 | P60: =O60 + MAX(P56:P59) -> 3 | Q60: =P60 + MAX(Q56:Q59) -> 3 | ... EA60: =DZ60 + MAX(EA56:EA59) -> 4
E62: =InpC!E$82 -> Pre-forecast period | F62: =InpC!F$82 -> Pre-fcst | G62: =InpC!G$82 -> label
E63: =InpC!E$83 -> Financial Close | F63: =InpC!F$83 -> Fin Close | G63: =InpC!G$83 -> label
E64: =InpC!E$84 -> Operations | F64: =InpC!F$84 -> Operations | G64: =InpC!G$84 -> label
E65: =InpC!E$85 -> Post ops | F65: =InpC!F$85 -> Post ops | G65: =InpC!G$85 -> label
E66: =E$60 -> Timeline label counter | F66: =F$60 -> 0 | G66: =G$60 -> counter | H66: =H$60 -> 0 | I66: =I$60 -> 0 | J66: =J$60 -> 1 | K66: =K$60 -> 1 | L66: =L$60 -> 2 | ... EA66: =EA$60 -> 4
E67: Timeline label | G67: label | J67: =INDEX($F62:$F65, J66) -> Pre-fcst | K67: =INDEX($F62:$F65, K66) -> Pre-fcst | L67: =INDEX($F62:$F65, L66) -> Fin Close | M67: =INDEX($F62:$F65, M66) -> Operations | N67: =INDEX($F62:$F65, N66) -> Operations | O67: =INDEX($F62:$F65, O66) -> Operations | P67: =INDEX($F62:$F65, P66) -> Operations | Q67: =INDEX($F62:$F65, Q66) -> Operations | ... EA67: =INDEX($F62:$F65, EA66) -> Post ops
A71: FLAGS
B73: Financial close date flag
E74: =InpC!E$18 -> Acquisition date | F74: =InpC!F$18 -> 44286 | G74: =InpC!G$18 -> date
E75: =E$25 -> Model period ending | F75: =F$25 -> 0 | G75: =G$25 -> date | H75: =H$25 -> 0 | I75: =I$25 -> 0 | J75: =J$25 -> 44104 | K75: =K$25 -> 44196 | L75: =L$25 -> 44286 | ... EA75: =EA$25 -> 55153
E76: Financial close date flag | G76: flag | H76: =SUM(J76:EA76) -> 1 | J76: =IF(AND(I75 < $F74, J75 >= $F74), 1, 0) -> 0 | K76: =IF(AND(J75 < $F74, K75 >= $F74), 1, 0) -> 0 | L76: =IF(AND(K75 < $F74, L75 >= $F74), 1, 0) -> 1 | M76: =IF(AND(L75 < $F74, M75 >= $F74), 1, 0) -> 0 | N76: =IF(AND(M75 < $F74, N75 >= $F74), 1, 0) -> 0 | O76: =IF(AND(N75 < $F74, O75 >= $F74), 1, 0) -> 0 | P76: =IF(AND(O75 < $F74, P75 >= $F74), 1, 0) -> 0 | Q76: =IF(AND(P75 < $F74, Q75 >= $F74), 1, 0) -> 0 | ... EA76: =IF(AND(DZ75 < $F74, EA75 >= $F74), 1, 0) -> 0
B78: First operating period flag
E79: =E$76 -> Financial close date flag | F79: =F$76 -> 0 | G79: =G$76 -> flag | H79: =H$76 -> 1 | I79: =I$76 -> 0 | J79: =J$76 -> 0 | K79: =K$76 -> 0 | L79: =L$76 -> 1 | ... EA79: =EA$76 -> 0
E80: First operating period flag | G80: flag | H80: =SUM(J80:EA80) -> 1 | J80: =I79 -> 0 | K80: =J79 -> 0 | L80: =K79 -> 0 | M80: =L79 -> 1 | N80: =M79 -> 0 | O80: =N79 -> 0 | P80: =O79 -> 0 | Q80: =P79 -> 0 | ... EA80: =DZ79 -> 0
B82: Last operating period flag
E83: =InpC!E$18 -> Acquisition date | F83: =InpC!F$18 -> 44286 | G83: =InpC!G$18 -> date
E84: =InpC!E$20 -> Operating years remaining | F84: =InpC!F$20 -> 25 | G84: =InpC!G$20 -> years
E85: =InpC!E$21 -> Contract extension | F85: =InpC!F$21 -> 0 | G85: =InpC!G$21 -> years
E86: =InpC!E$73 -> Months in year | F86: =InpC!F$73 -> 12 | G86: =InpC!G$73 -> months
E87: End of operating period | F87: =EOMONTH(F83, ((F84 + F85) * F86)) -> 53417 | G87: date
E89: =E$87 -> End of operating period | F89: =F$87 -> 53417 | G89: =G$87 -> date
E90: =E$25 -> Model period ending | F90: =F$25 -> 0 | G90: =G$25 -> date | H90: =H$25 -> 0 | I90: =I$25 -> 0 | J90: =J$25 -> 44104 | K90: =K$25 -> 44196 | L90: =L$25 -> 44286 | ... EA90: =EA$25 -> 55153
E91: Last operating period flag | G91: flag | H91: =SUM(J91:EA91) -> 1 | J91: =IF(J90 = $F89, 1, 0) -> 0 | K91: =IF(K90 = $F89, 1, 0) -> 0 | L91: =IF(L90 = $F89, 1, 0) -> 0 | M91: =IF(M90 = $F89, 1, 0) -> 0 | N91: =IF(N90 = $F89, 1, 0) -> 0 | O91: =IF(O90 = $F89, 1, 0) -> 0 | P91: =IF(P90 = $F89, 1, 0) -> 0 | Q91: =IF(Q90 = $F89, 1, 0) -> 0 | ... EA91: =IF(EA90 = $F89, 1, 0) -> 0
B93: Operating period flag
E94: =InpC!E$18 -> Acquisition date | F94: =InpC!F$18 -> 44286 | G94: =InpC!G$18 -> date
E95: =E$87 -> End of operating period | F95: =F$87 -> 53417 | G95: =G$87 -> date
E96: =E$25 -> Model period ending | F96: =F$25 -> 0 | G96: =G$25 -> date | H96: =H$25 -> 0 | I96: =I$25 -> 0 | J96: =J$25 -> 44104 | K96: =K$25 -> 44196 | L96: =L$25 -> 44286 | ... EA96: =EA$25 -> 55153
E97: Operating period flag | G97: flag | H97: =SUM(J97:EA97) -> 100 | J97: =IF( AND(J96 > $F94, J96 <= $F95), 1, 0) -> 0 | K97: =IF( AND(K96 > $F94, K96 <= $F95), 1, 0) -> 0 | L97: =IF( AND(L96 > $F94, L96 <= $F95), 1, 0) -> 0 | M97: =IF( AND(M96 > $F94, M96 <= $F95), 1, 0) -> 1 | N97: =IF( AND(N96 > $F94, N96 <= $F95), 1, 0) -> 1 | O97: =IF( AND(O96 > $F94, O96 <= $F95), 1, 0) -> 1 | P97: =IF( AND(P96 > $F94, P96 <= $F95), 1, 0) -> 1 | Q97: =IF( AND(Q96 > $F94, Q96 <= $F95), 1, 0) -> 1 | ... EA97: =IF( AND(EA96 > $F94, EA96 <= $F95), 1, 0) -> 0
B99: Useful life of asset flag
E100: =InpC!E$18 -> Acquisition date | F100: =InpC!F$18 -> 44286 | G100: =InpC!G$18 -> date
E101: =InpC!E$41 -> Useful life of asset | F101: =InpC!F$41 -> 25 | G101: =InpC!G$41 -> years
E102: =InpC!E$21 -> Contract extension | F102: =InpC!F$21 -> 0 | G102: =InpC!G$21 -> years
E103: =InpC!E$73 -> Months in year | F103: =InpC!F$73 -> 12 | G103: =InpC!G$73 -> months
E104: End of useful life of asset | F104: =EOMONTH(F100, ((F101 + F102) * F103)) -> 53417 | G104: date
E106: =InpC!E$18 -> Acquisition date | F106: =InpC!F$18 -> 44286 | G106: =InpC!G$18 -> date
E107: =E$104 -> End of useful life of asset | F107: =F$104 -> 53417 | G107: =G$104 -> date | H107: =H$104 -> 0 | I107: =I$104 -> 0 | J107: =J$104 -> 0 | K107: =K$104 -> 0 | L107: =L$104 -> 0 | ... EA107: =EA$104 -> 0
E108: =E$25 -> Model period ending | F108: =F$25 -> 0 | G108: =G$25 -> date | H108: =H$25 -> 0 | I108: =I$25 -> 0 | J108: =J$25 -> 44104 | K108: =K$25 -> 44196 | L108: =L$25 -> 44286 | ... EA108: =EA$25 -> 55153
E109: Useful life of asset flag | G109: flag | H109: =SUM(J109:EA109) -> 100 | J109: =IF( AND(J108 > $F106, J108 <= $F107), 1, 0) -> 0 | K109: =IF( AND(K108 > $F106, K108 <= $F107), 1, 0) -> 0 | L109: =IF( AND(L108 > $F106, L108 <= $F107), 1, 0) -> 0 | M109: =IF( AND(M108 > $F106, M108 <= $F107), 1, 0) -> 1 | N109: =IF( AND(N108 > $F106, N108 <= $F107), 1, 0) -> 1 | O109: =IF( AND(O108 > $F106, O108 <= $F107), 1, 0) -> 1 | P109: =IF( AND(P108 > $F106, P108 <= $F107), 1, 0) -> 1 | Q109: =IF( AND(Q108 > $F106, Q108 <= $F107), 1, 0) -> 1 | ... EA109: =IF( AND(EA108 > $F106, EA108 <= $F107), 1, 0) -> 0
B111: First post operating period flag
E112: =E$91 -> Last operating period flag | F112: =F$91 -> 0 | G112: =G$91 -> flag | H112: =H$91 -> 1 | I112: =I$91 -> 0 | J112: =J$91 -> 0 | K112: =K$91 -> 0 | L112: =L$91 -> 0 | ... EA112: =EA$91 -> 0
E113: First post operating period flag | J113: =I112 -> 0 | K113: =J112 -> 0 | L113: =K112 -> 0 | M113: =L112 -> 0 | N113: =M112 -> 0 | O113: =N112 -> 0 | P113: =O112 -> 0 | Q113: =P112 -> 0 | ... EA113: =DZ112 -> 0
B115: Senior debt repayment period flag
E116: =InpC!E$18 -> Acquisition date | F116: =InpC!F$18 -> 44286 | G116: =InpC!G$18 -> date
E117: =InpC!E$45 -> Senior debt repayment period | F117: =InpC!F$45 -> 10 | G117: =InpC!G$45 -> years
E118: =InpC!E$21 -> Contract extension | F118: =InpC!F$21 -> 0 | G118: =InpC!G$21 -> years
E119: =InpC!E$73 -> Months in year | F119: =InpC!F$73 -> 12 | G119: =InpC!G$73 -> months
E120: Last senior debt repayment date | F120: =EOMONTH(F116, ((F117 + F118) * F119)) -> 47938 | G120: date
E122: =InpC!E$18 -> Acquisition date | F122: =InpC!F$18 -> 44286 | G122: =InpC!G$18 -> date
E123: =E$120 -> Last senior debt repayment date | F123: =F$120 -> 47938 | G123: =G$120 -> date
E124: =E$25 -> Model period ending | F124: =F$25 -> 0 | G124: =G$25 -> date | H124: =H$25 -> 0 | I124: =I$25 -> 0 | J124: =J$25 -> 44104 | K124: =K$25 -> 44196 | L124: =L$25 -> 44286 | ... EA124: =EA$25 -> 55153
E125: Senior debt repayment period flag | G125: flag | H125: =SUM(J125:EA125) -> 40 | J125: =IF( AND(J124 > $F122, J124 <= $F123), 1, 0) -> 0 | K125: =IF( AND(K124 > $F122, K124 <= $F123), 1, 0) -> 0 | L125: =IF( AND(L124 > $F122, L124 <= $F123), 1, 0) -> 0 | M125: =IF( AND(M124 > $F122, M124 <= $F123), 1, 0) -> 1 | N125: =IF( AND(N124 > $F122, N124 <= $F123), 1, 0) -> 1 | O125: =IF( AND(O124 > $F122, O124 <= $F123), 1, 0) -> 1 | P125: =IF( AND(P124 > $F122, P124 <= $F123), 1, 0) -> 1 | Q125: =IF( AND(Q124 > $F122, Q124 <= $F123), 1, 0) -> 1 | ... EA125: =IF( AND(EA124 > $F122, EA124 <= $F123), 1, 0) -> 0
A128: COUNTERS / PERIOD NUMBERS
...

Sheet Ops
A1: =RIGHT(CELL("filename", A1), LEN(CELL("filename", A1)) - SEARCH("]", CELL("filename", A1))) & " - " & InpC!F3 -> Ops - Base case 1
E2: =Time!E$25 -> Model period ending | F2: =Check!$F$9 -> 0 | G2: Error chks | J2: =Time!J$25 -> 44104 | K2: =Time!K$25 -> 44196 | L2: =Time!L$25 -> 44286 | M2: =Time!M$25 -> 44377 | N2: =Time!N$25 -> 44469 | O2: =Time!O$25 -> 44561 | P2: =Time!P$25 -> 44651 | Q2: =Time!Q$25 -> 44742 | ... EA2: =Time!EA$25 -> 55153
E3: =Time!E$67 -> Timeline label | F3: =Output!J2 -> 0 | G3: Track chgs | J3: =Time!J$67 -> Pre-fcst | K3: =Time!K$67 -> Pre-fcst | L3: =Time!L$67 -> Fin Close | M3: =Time!M$67 -> Operations | N3: =Time!N$67 -> Operations | O3: =Time!O$67 -> Operations | P3: =Time!P$67 -> Operations | Q3: =Time!Q$67 -> Operations | ... EA3: =Time!EA$67 -> Post ops
E4: =Time!E$42 -> Contract year | F4: =Check!$F$21 -> 0 | G4: Alerts | J4: =Time!J$42 -> 2020 | K4: =Time!K$42 -> 2020 | L4: =Time!L$42 -> 2020 | M4: =Time!M$42 -> 2021 | N4: =Time!N$42 -> 2021 | O4: =Time!O$42 -> 2021 | P4: =Time!P$42 -> 2021 | Q4: =Time!Q$42 -> 2022 | ... EA4: =Time!EA$42 -> 2050
E5: =Time!E$10 -> Model column counter | F5: Constant | G5: Unit | H5: Total | J5: =Time!J$10 -> 1 | K5: =Time!K$10 -> 2 | L5: =Time!L$10 -> 3 | M5: =Time!M$10 -> 4 | N5: =Time!N$10 -> 5 | O5: =Time!O$10 -> 6 | P5: =Time!P$10 -> 7 | Q5: =Time!Q$10 -> 8 | ... EA5: =Time!EA$10 -> 122
A8: REVENUE
B10: Degradation
E11: =InpC!E$29 -> Annual degradation | F11: =InpC!F$29 -> 0.005 | G11: =InpC!G$29 -> % p.a.
E12: =Time!E$143 -> Contract year number | F12: =Time!F$143 -> 0 | G12: =Time!G$143 -> counter | H12: =Time!H$143 -> 0 | I12: =Time!I$143 -> 0 | J12: =Time!J$143 -> 0 | K12: =Time!K$143 -> 0 | L12: =Time!L$143 -> 0 | ... EA12: =Time!EA$143 -> 0
E13: =Time!E$97 -> Operating period flag | F13: =Time!F$97 -> 0 | G13: =Time!G$97 -> flag | H13: =Time!H$97 -> 100 | I13: =Time!I$97 -> 0 | J13: =Time!J$97 -> 0 | K13: =Time!K$97 -> 0 | L13: =Time!L$97 -> 0 | ... EA13: =Time!EA$97 -> 0
E14: Compound degradation | G14: % | J14: =IF( J13 = 1, 1 / ((1 + $F11) ^ (J12 - 1)), 0) -> 0 | K14: =IF( K13 = 1, 1 / ((1 + $F11) ^ (K12 - 1)), 0) -> 0 | L14: =IF( L13 = 1, 1 / ((1 + $F11) ^ (L12 - 1)), 0) -> 0 | M14: =IF( M13 = 1, 1 / ((1 + $F11) ^ (M12 - 1)), 0) -> 1 | N14: =IF( N13 = 1, 1 / ((1 + $F11) ^ (N12 - 1)), 0) -> 1 | O14: =IF( O13 = 1, 1 / ((1 + $F11) ^ (O12 - 1)), 0) -> 1 | P14: =IF( P13 = 1, 1 / ((1 + $F11) ^ (P12 - 1)), 0) -> 1 | Q14: =IF( Q13 = 1, 1 / ((1 + $F11) ^ (Q12 - 1)), 0) -> 0.99502488 | ... EA14: =IF( EA13 = 1, 1 / ((1 + $F11) ^ (EA12 - 1)), 0) -> 0
B16: Seasonality adjustment
E17: =InpC!E$24 -> Q1 seasonal adjustment | F17: =InpC!F$24 -> 0.33 | G17: =InpC!G$24 -> % of annual yield
E18: =InpC!E$25 -> Q2 seasonal adjustment | F18: =InpC!F$25 -> 0.36 | G18: =InpC!G$25 -> % of annual yield
E19: =InpC!E$26 -> Q3 seasonal adjustment | F19: =InpC!F$26 -> 0.155 | G19: =InpC!G$26 -> % of annual yield
E20: =InpC!E$27 -> Q4 seasonal adjustment | F20: =InpC!F$27 -> 0.155 | G20: =InpC!G$27 -> % of annual yield
E21: =Time!E$137 -> Period number | F21: =Time!F$137 -> 0 | G21: =Time!G$137 -> counter | H21: =Time!H$137 -> 0 | I21: =Time!I$137 -> 0 | J21: =Time!J$137 -> 0 | K21: =Time!K$137 -> 0 | L21: =Time!L$137 -> 0 | ... EA21: =Time!EA$137 -> 0
E22: =Time!E$97 -> Operating period flag | F22: =Time!F$97 -> 0 | G22: =Time!G$97 -> flag | H22: =Time!H$97 -> 100 | I22: =Time!I$97 -> 0 | J22: =Time!J$97 -> 0 | K22: =Time!K$97 -> 0 | L22: =Time!L$97 -> 0 | ... EA22: =Time!EA$97 -> 0
E23: Seasonality adjustment | G23: % | H23: =SUM(J23:GJ23) -> 25 | J23: =IF(J22 = 1, INDEX($F17:$F20, J21), 0) -> 0 | K23: =IF(K22 = 1, INDEX($F17:$F20, K21), 0) -> 0 | L23: =IF(L22 = 1, INDEX($F17:$F20, L21), 0) -> 0 | M23: =IF(M22 = 1, INDEX($F17:$F20, M21), 0) -> 0.33 | N23: =IF(N22 = 1, INDEX($F17:$F20, N21), 0) -> 0.36 | O23: =IF(O22 = 1, INDEX($F17:$F20, O21), 0) -> 0.155 | P23: =IF(P22 = 1, INDEX($F17:$F20, P21), 0) -> 0.155 | Q23: =IF(Q22 = 1, INDEX($F17:$F20, Q21), 0) -> 0.33 | ... EA23: =IF(EA22 = 1, INDEX($F17:$F20, EA21), 0) -> 0
B25: Electricity generation
E26: =InpC!E$30 -> Year 1 P50 yield | F26: =InpC!F$30 -> 250 | G26: =InpC!G$30 -> GWh
E27: =InpC!E$31 -> Availability | F27: =InpC!F$31 -> 0.97 | G27: =InpC!G$31 -> %
E28: =E$14 -> Compound degradation | F28: =F$14 -> 0 | G28: =G$14 -> % | H28: =H$14 -> 0 | I28: =I$14 -> 0 | J28: =J$14 -> 0 | K28: =K$14 -> 0 | L28: =L$14 -> 0 | ... EA28: =EA$14 -> 0
E29: =E$23 -> Seasonality adjustment | F29: =F$23 -> 0 | G29: =G$23 -> % | H29: =H$23 -> 25 | I29: =I$23 -> 0 | J29: =J$23 -> 0 | K29: =K$23 -> 0 | L29: =L$23 -> 0 | ... EA29: =EA$23 -> 0
E30: Electricity generation | G30: GWh | H30: =SUM(J30:GJ30) -> 5713.9951 | J30: =$F26 * $F27 * J28 * J29 -> 0 | K30: =$F26 * $F27 * K28 * K29 -> 0 | L30: =$F26 * $F27 * L28 * L29 -> 0 | M30: =$F26 * $F27 * M28 * M29 -> 80.025 | N30: =$F26 * $F27 * N28 * N29 -> 87.3 | O30: =$F26 * $F27 * O28 * O29 -> 37.5875 | P30: =$F26 * $F27 * P28 * P29 -> 37.5875 | Q30: =$F26 * $F27 * Q28 * Q29 -> 79.626866 | ... EA30: =$F26 * $F27 * EA28 * EA29 -> 0
B32: Electricity revenue
E33: =InpC!E$33 -> Power tariff | F33: =InpC!F$33 -> 0.065 | G33: =InpC!G$33 -> USD / kWh
E34: =InpC!E$77 -> GWh to kWh conversion | F34: =InpC!F$77 -> 1000000 | G34: =InpC!G$77 -> kWh / GWh
E35: =InpC!E$78 -> Units in a thousand | F35: =InpC!F$78 -> 1000 | G35: =InpC!G$78 -> units
E36: =E$30 -> Electricity generation | F36: =F$30 -> 0 | G36: =G$30 -> GWh | H36: =H$30 -> 5713.9951 | I36: =I$30 -> 0 | J36: =J$30 -> 0 | K36: =K$30 -> 0 | L36: =L$30 -> 0 | ... EA36: =EA$30 -> 0
E37: =Time!E$97 -> Operating period flag | F37: =Time!F$97 -> 0 | G37: =Time!G$97 -> flag | H37: =Time!H$97 -> 100 | I37: =Time!I$97 -> 0 | J37: =Time!J$97 -> 0 | K37: =Time!K$97 -> 0 | L37: =Time!L$97 -> 0 | ... EA37: =Time!EA$97 -> 0
E38: Electricity revenue | G38: =SMU -> $ 000s | H38: =SUM(J38:GJ38) -> 371409.68 | J38: =$F33 * $F34 / $F35 * J36 * J37 -> 0 | K38: =$F33 * $F34 / $F35 * K36 * K37 -> 0 | L38: =$F33 * $F34 / $F35 * L36 * L37 -> 0 | M38: =$F33 * $F34 / $F35 * M36 * M37 -> 5201.625 | N38: =$F33 * $F34 / $F35 * N36 * N37 -> 5674.5 | O38: =$F33 * $F34 / $F35 * O36 * O37 -> 2443.1875 | P38: =$F33 * $F34 / $F35 * P36 * P37 -> 2443.1875 | Q38: =$F33 * $F34 / $F35 * Q36 * Q37 -> 5175.7463 | ... EA38: =$F33 * $F34 / $F35 * EA36 * EA37 -> 0
A41: ACCOUNTS RECEIVABLE
B43: Forecast accounts receivable balance
E44: =InpC!E$57 -> Accounts receivable days | F44: =InpC!F$57 -> 60 | G44: =InpC!G$57 -> days
E45: =E$38 -> Electricity revenue | F45: =F$38 -> 0 | G45: =G$38 -> $ 000s | H45: =H$38 -> 371409.68 | I45: =I$38 -> 0 | J45: =J$38 -> 0 | K45: =K$38 -> 0 | L45: =L$38 -> 0 | ... EA45: =EA$38 -> 0
E46: =Time!E$149 -> Days in period | F46: =Time!F$149 -> 0 | G46: =Time!G$149 -> days | H46: =Time!H$149 -> 0 | I46: =Time!I$149 -> 0 | J46: =Time!J$149 -> 92 | K46: =Time!K$149 -> 92 | L46: =Time!L$149 -> 90 | ... EA46: =Time!EA$149 -> 92
E47: Forecast accounts receivable balance | G47: =SMU -> $ 000s | J47: =J45 / J46 * $F44 -> 0 | K47: =K45 / K46 * $F44 -> 0 | L47: =L45 / L46 * $F44 -> 0 | M47: =M45 / M46 * $F44 -> 3429.6429 | N47: =N45 / N46 * $F44 -> 3700.7609 | O47: =O45 / O46 * $F44 -> 1593.3832 | P47: =P45 / P46 * $F44 -> 1628.7917 | Q47: =Q45 / Q46 * $F44 -> 3412.58 | ... EA47: =EA45 / EA46 * $F44 -> 0
B49: Cash received from invoices
E50: =E$38 -> Electricity revenue | F50: =F$38 -> 0 | G50: =G$38 -> $ 000s | H50: =H$38 -> 371409.68 | I50: =I$38 -> 0 | J50: =J$38 -> 0 | K50: =K$38 -> 0 | L50: =L$38 -> 0 | ... EA50: =EA$38 -> 0
D51: Less: | E51: =E$47 -> Forecast accounts receivable balance | F51: =F$47 -> 0 | G51: =G$47 -> $ 000s | H51: =H$47 -> 0 | I51: =I$47 -> 0 | J51: =J$47 -> 0 | K51: =K$47 -> 0 | L51: =L$47 -> 0 | ... EA51: =EA$47 -> 0
D52: Plus: | E52: =E$60 -> Accounts receivable balance BEG | F52: =F$60 -> 0 | G52: =G$60 -> $ 000s | H52: =H$60 -> 0 | I52: =I$60 -> 0 | J52: =J$60 -> 0 | K52: =K$60 -> 0 | L52: =L$60 -> 0 | ... EA52: =EA$60 -> 0
E53: Cash received from invoices | G53: =SMU -> $ 000s | H53: =SUM(J53:EA53) -> 371409.68 | J53: =J50 - J51 + J52 -> 0 | K53: =K50 - K51 + K52 -> 0 | L53: =L50 - L51 + L52 -> 0 | M53: =M50 - M51 + M52 -> 1771.9821 | N53: =N50 - N51 + N52 -> 5403.382 | O53: =O50 - O51 + O52 -> 4550.5652 | P53: =P50 - P51 + P52 -> 2407.779 | Q53: =Q50 - Q51 + Q52 -> 3391.958 | ... EA53: =EA50 - EA51 + EA52 -> 0
B55: Accounts receivable balance
E57: =InpC!E$63 -> Accounts receivable - initial balance | F57: =InpC!F$63 -> 0 | G57: =InpC!G$63 -> $ 000s
E58: =Time!E$76 -> Financial close date flag | F58: =Time!F$76 -> 0 | G58: =Time!G$76 -> flag | H58: =Time!H$76 -> 1 | I58: =Time!I$76 -> 0 | J58: =Time!J$76 -> 0 | K58: =Time!K$76 -> 0 | L58: =Time!L$76 -> 1 | ... EA58: =Time!EA$76 -> 0
E60: Accounts receivable balance BEG | G60: =SMU -> $ 000s | J60: =I63 -> 0 | K60: =J63 -> 0 | L60: =K63 -> 0 | M60: =L63 -> 0 | N60: =M63 -> 3429.6429 | O60: =N63 -> 3700.7609 | P60: =O63 -> 1593.3832 | Q60: =P63 -> 1628.7917 | ... EA60: =DZ63 -> 0
E61: =E$38 -> Electricity revenue | F61: =F$38 -> 0 | G61: =G$38 -> $ 000s | H61: =H$38 -> 371409.68 | I61: =I$38 -> 0 | J61: =J$38 -> 0 | K61: =K$38 -> 0 | L61: =L$38 -> 0 | ... EA61: =EA$38 -> 0
E62: =E$53 -> Cash received from invoices | F62: =F$53 -> 0 | G62: =G$53 -> $ 000s | H62: =H$53 -> 371409.68 | I62: =I$53 -> 0 | J62: =J$53 -> 0 | K62: =K$53 -> 0 | L62: =L$53 -> 0 | ... EA62: =EA$53 -> 0
E63: Accounts receivable balance | G63: =SMU -> $ 000s | J63: =IF( J58 = 1, $F57, J60 + J61 - J62) -> 0 | K63: =IF( K58 = 1, $F57, K60 + K61 - K62) -> 0 | L63: =IF( L58 = 1, $F57, L60 + L61 - L62) -> 0 | M63: =IF( M58 = 1, $F57, M60 + M61 - M62) -> 3429.6429 | N63: =IF( N58 = 1, $F57, N60 + N61 - N62) -> 3700.7609 | O63: =IF( O58 = 1, $F57, O60 + O61 - O62) -> 1593.3832 | P63: =IF( P58 = 1, $F57, P60 + P61 - P62) -> 1628.7917 | Q63: =IF( Q58 = 1, $F57, Q60 + Q61 - Q62) -> 3412.58 | ... EA63: =IF( EA58 = 1, $F57, EA60 + EA61 - EA62) -> 0
A67: ACCOUNTS RECEIVABLE - ALTERNATIVE METHOD - NOT USED IN MODEL
B69: Forecast cash received for current period invoices
E70: =InpC!E$57 -> Accounts receivable days | F70: =InpC!F$57 -> 60 | G70: =InpC!G$57 -> days
E71: =E$38 -> Electricity revenue | F71: =F$38 -> 0 | G71: =G$38 -> $ 000s | H71: =H$38 -> 371409.68 | I71: =I$38 -> 0 | J71: =J$38 -> 0 | K71: =K$38 -> 0 | L71: =L$38 -> 0 | ... EA71: =EA$38 -> 0
E72: =Time!E$149 -> Days in period | F72: =Time!F$149 -> 0 | G72: =Time!G$149 -> days | H72: =Time!H$149 -> 0 | I72: =Time!I$149 -> 0 | J72: =Time!J$149 -> 92 | K72: =Time!K$149 -> 92 | L72: =Time!L$149 -> 90 | ... EA72: =Time!EA$149 -> 92
E73: Cash received from current period invoices | G73: =SMU -> $ 000s | J73: =J71 / J72 * (J72 - $F70) -> 0 | K73: =K71 / K72 * (K72 - $F70) -> 0 | L73: =L71 / L72 * (L72 - $F70) -> 0 | M73: =M71 / M72 * (M72 - $F70) -> 1771.9821 | N73: =N71 / N72 * (N72 - $F70) -> 1973.7391 | O73: =O71 / O72 * (O72 - $F70) -> 849.80435 | P73: =P71 / P72 * (P72 - $F70) -> 814.39583 | Q73: =Q71 / Q72 * (Q72 - $F70) -> 1763.1663 | ... EA73: =EA71 / EA72 * (EA72 - $F70) -> 0
B75: Cash received from invoices
E76: =E$83 -> Accounts receivable - balance BEG | F76: =F$83 -> 0 | G76: =G$83 -> $ 000s | H76: =H$83 -> 0 | I76: =I$83 -> 0 | J76: =J$83 -> 0 | K76: =K$83 -> 0 | L76: =L$83 -> 0 | ... EA76: =EA$83 -> 0
E77: =E$73 -> Cash received from current period invoices | F77: =F$73 -> 0 | G77: =G$73 -> $ 000s | H77: =H$73 -> 0 | I77: =I$73 -> 0 | J77: =J$73 -> 0 | K77: =K$73 -> 0 | L77: =L$73 -> 0 | ... EA77: =EA$73 -> 0
E78: Cash received from invoices | J78: =SUM(J76:J77) -> 0 | K78: =SUM(K76:K77) -> 0 | L78: =SUM(L76:L77) -> 0 | M78: =SUM(M76:M77) -> 1771.9821 | N78: =SUM(N76:N77) -> 5403.382 | O78: =SUM(O76:O77) -> 4550.5652 | P78: =SUM(P76:P77) -> 2407.779 | Q78: =SUM(Q76:Q77) -> 3391.958 | ... EA78: =SUM(EA76:EA77) -> 0
E80: =InpC!E$63 -> Accounts receivable - initial balance | F80: =InpC!F$63 -> 0 | G80: =InpC!G$63 -> $ 000s
E81: =Time!E$76 -> Financial close date flag | F81: =Time!F$76 -> 0 | G81: =Time!G$76 -> flag | H81: =Time!H$76 -> 1 | I81: =Time!I$76 -> 0 | J81: =Time!J$76 -> 0 | K81: =Time!K$76 -> 0 | L81: =Time!L$76 -> 1 | ... EA81: =Time!EA$76 -> 0
E83: Accounts receivable - balance BEG | G83: =SMU -> $ 000s | J83: =I86 -> 0 | K83: =J86 -> 0 | L83: =K86 -> 0 | M83: =L86 -> 0 | N83: =M86 -> 3429.6429 | O83: =N86 -> 3700.7609 | P83: =O86 -> 1593.3832 | Q83: =P86 -> 1628.7917 | ... EA83: =DZ86 -> 0
E84: =E$38 -> Electricity revenue | F84: =F$38 -> 0 | G84: =G$38 -> $ 000s | H84: =H$38 -> 371409.68 | I84: =I$38 -> 0 | J84: =J$38 -> 0 | K84: =K$38 -> 0 | L84: =L$38 -> 0 | ... EA84: =EA$38 -> 0
E85: =E$78 -> Cash received from invoices | F85: =F$78 -> 0 | G85: =G$78 -> 0 | H85: =H$78 -> 0 | I85: =I$78 -> 0 | J85: =J$78 -> 0 | K85: =K$78 -> 0 | L85: =L$78 -> 0 | ... EA85: =EA$78 -> 0
E86: Accounts receivable - balance | G86: =SMU -> $ 000s | J86: =IF( J81 = 1, $F80, J83 + J84 - J85) -> 0 | K86: =IF( K81 = 1, $F80, K83 + K84 - K85) -> 0 | L86: =IF( L81 = 1, $F80, L83 + L84 - L85) -> 0 | M86: =IF( M81 = 1, $F80, M83 + M84 - M85) -> 3429.6429 | N86: =IF( N81 = 1, $F80, N83 + N84 - N85) -> 3700.7609 | O86: =IF( O81 = 1, $F80, O83 + O84 - O85) -> 1593.3832 | P86: =IF( P81 = 1, $F80, P83 + P84 - P85) -> 1628.7917 | Q86: =IF( Q81 = 1, $F80, Q83 + Q84 - Q85) -> 3412.58 | ... EA86: =IF( EA81 = 1, $F80, EA83 + EA84 - EA85) -> 0
A91: OPERATING COSTS
E93: =InpC!E$37 -> Annual fixed real O&M cost | F93: =InpC!F$37 -> 1500 | G93: =InpC!G$37 -> $ 000s
E94: =InpC!E$74 -> Number of periods in a year | F94: =InpC!F$74 -> 4 | G94: =InpC!G$74 -> periods
E95: [us cpi indexation factor] | L95: 1 | M95: =L95 * 1.005 -> 1.005 | N95: =M95 * 1.005 -> 1.010025 | O95: =N95 * 1.005 -> 1.0150751 | P95: =O95 * 1.005 -> 1.0201505 | Q95: =P95 * 1.005 -> 1.0252513 | R95: =Q95 * 1.005 -> 1.0303775 | S95: =R95 * 1.005 -> 1.0355294 | T95: =S95 * 1.005 -> 1.040707 | ... EA95: =DZ95 * 1.005 -> 1.810345
E96: =Time!E$97 -> Operating period flag | F96: =Time!F$97 -> 0 | G96: =Time!G$97 -> flag | H96: =Time!H$97 -> 100 | I96: =Time!I$97 -> 0 | J96: =Time!J$97 -> 0 | K96: =Time!K$97 -> 0 | L96: =Time!L$97 -> 0 | ... EA96: =Time!EA$97 -> 0
E97: O&M cost POS | G97: =SMU -> $ 000s | H97: =SUM(J97:EA97) -> 48742.638 | J97: =$F93 / $F94 * J95 * J96 -> 0 | K97: =$F93 / $F94 * K95 * K96 -> 0 | L97: =$F93 / $F94 * L95 * L96 -> 0 | M97: =$F93 / $F94 * M95 * M96 -> 376.875 | N97: =$F93 / $F94 * N95 * N96 -> 378.75937 | O97: =$F93 / $F94 * O95 * O96 -> 380.65317 | P97: =$F93 / $F94 * P95 * P96 -> 382.55644 | Q97: =$F93 / $F94 * Q95 * Q96 -> 384.46922 | ... EA97: =$F93 / $F94 * EA95 * EA96 -> 0
E98: =LEFT(E97, LEN(E97) - 4) -> O&M cost | G98: =SMU -> $ 000s | H98: =SUM(J98:EA98) -> -48742.638 | J98: =-1 * J97 -> 0 | K98: =-1 * K97 -> 0 | L98: =-1 * L97 -> 0 | M98: =-1 * M97 -> -376.875 | N98: =-1 * N97 -> -378.75937 | O98: =-1 * O97 -> -380.65317 | P98: =-1 * P97 -> -382.55644 | Q98: =-1 * Q97 -> -384.46922 | ... EA98: =-1 * EA97 -> 0
A101: ACCOUNTS PAYABLE
B103: Forecast accounts payable balance
E104: =InpC!E$58 -> Accounts payable days | F104: =InpC!F$58 -> 30 | G104: =InpC!G$58 -> days
E105: =E$97 -> O&M cost POS | F105: =F$97 -> 0 | G105: =G$97 -> $ 000s | H105: =H$97 -> 48742.638 | I105: =I$97 -> 0 | J105: =J$97 -> 0 | K105: =K$97 -> 0 | L105: =L$97 -> 0 | ... EA105: =EA$97 -> 0
E106: =Time!E$149 -> Days in period | F106: =Time!F$149 -> 0 | G106: =Time!G$149 -> days | H106: =Time!H$149 -> 0 | I106: =Time!I$149 -> 0 | J106: =Time!J$149 -> 92 | K106: =Time!K$149 -> 92 | L106: =Time!L$149 -> 90 | ... EA106: =Time!EA$149 -> 92
E107: Forecast accounts payable balance | G107: =SMU -> $ 000s | J107: =J105 / J106 * $F104 -> 0 | K107: =K105 / K106 * $F104 -> 0 | L107: =L105 / L106 * $F104 -> 0 | M107: =M105 / M106 * $F104 -> 124.24451 | N107: =N105 / N106 * $F104 -> 123.50849 | O107: =O105 / O106 * $F104 -> 124.12603 | P107: =P105 / P106 * $F104 -> 127.51881 | Q107: =Q105 / Q106 * $F104 -> 126.74809 | ... EA107: =EA105 / EA106 * $F104 -> 0
B109: Cash received from invoices
E110: =E$97 -> O&M cost POS | F110: =F$97 -> 0 | G110: =G$97 -> $ 000s | H110: =H$97 -> 48742.638 | I110: =I$97 -> 0 | J110: =J$97 -> 0 | K110: =K$97 -> 0 | L110: =L$97 -> 0 | ... EA110: =EA$97 -> 0
D111: Less: | E111: =E$107 -> Forecast accounts payable balance | F111: =F$107 -> 0 | G111: =G$107 -> $ 000s | H111: =H$107 -> 0 | I111: =I$107 -> 0 | J111: =J$107 -> 0 | K111: =K$107 -> 0 | L111: =L$107 -> 0 | ... EA111: =EA$107 -> 0
D112: Plus: | E112: =E$121 -> Accounts payable balance BEG | F112: =F$121 -> 0 | G112: =G$121 -> $ 000s | H112: =H$121 -> 0 | I112: =I$121 -> 0 | J112: =J$121 -> 0 | K112: =K$121 -> 0 | L112: =L$121 -> 0 | ... EA112: =EA$121 -> 0
E113: Cash paid for operating costs POS | G113: =SMU -> $ 000s | H113: =SUM(J113:EA113) -> 48742.638 | J113: =J110 - J111 + J112 -> 0 | K113: =K110 - K111 + K112 -> 0 | L113: =L110 - L111 + L112 -> 0 | M113: =M110 - M111 + M112 -> 252.63049 | N113: =N110 - N111 + N112 -> 379.49539 | O113: =O110 - O111 + O112 -> 380.03563 | P113: =P110 - P111 + P112 -> 379.16366 | Q113: =Q110 - Q111 + Q112 -> 385.23994 | ... EA113: =EA110 - EA111 + EA112 -> 0
E114: =LEFT(E113, LEN(E113) - 4) -> Cash paid for operating costs | G114: =SMU -> $ 000s | H114: =SUM(J114:EA114) -> -48742.638 | J114: =-1 * J113 -> 0 | K114: =-1 * K113 -> 0 | L114: =-1 * L113 -> 0 | M114: =-1 * M113 -> -252.63049 | N114: =-1 * N113 -> -379.49539 | O114: =-1 * O113 -> -380.03563 | P114: =-1 * P113 -> -379.16366 | Q114: =-1 * Q113 -> -385.23994 | ... EA114: =-1 * EA113 -> 0
B116: Accounts payable balance
E118: =InpC!E$64 -> Accounts payable - initial balance | F118: =InpC!F$64 -> 0 | G118: =InpC!G$64 -> $ 000s
E119: =Time!E$76 -> Financial close date flag | F119: =Time!F$76 -> 0 | G119: =Time!G$76 -> flag | H119: =Time!H$76 -> 1 | I119: =Time!I$76 -> 0 | J119: =Time!J$76 -> 0 | K119: =Time!K$76 -> 0 | L119: =Time!L$76 -> 1 | ... EA119: =Time!EA$76 -> 0
E121: Accounts payable balance BEG | G121: =SMU -> $ 000s | J121: =I124 -> 0 | K121: =J124 -> 0 | L121: =K124 -> 0 | M121: =L124 -> 0 | N121: =M124 -> 124.24451 | O121: =N124 -> 123.50849 | P121: =O124 -> 124.12603 | Q121: =P124 -> 127.51881 | ... EA121: =DZ124 -> 0
E122: =E$97 -> O&M cost POS | F122: =F$97 -> 0 | G122: =G$97 -> $ 000s | H122: =H$97 -> 48742.638 | I122: =I$97 -> 0 | J122: =J$97 -> 0 | K122: =K$97 -> 0 | L122: =L$97 -> 0 | ... EA122: =EA$97 -> 0
E123: =E$113 -> Cash paid for operating costs POS | F123: =F$113 -> 0 | G123: =G$113 -> $ 000s | H123: =H$113 -> 48742.638 | I123: =I$113 -> 0 | J123: =J$113 -> 0 | K123: =K$113 -> 0 | L123: =L$113 -> 0 | ... EA123: =EA$113 -> 0
E124: Accounts payable balance | G124: =SMU -> $ 000s | J124: =IF( J119 = 1, $F118, J121 + J122 - J123) -> 0 | K124: =IF( K119 = 1, $F118, K121 + K122 - K123) -> 0 | L124: =IF( L119 = 1, $F118, L121 + L122 - L123) -> 0 | M124: =IF( M119 = 1, $F118, M121 + M122 - M123) -> 124.24451 | N124: =IF( N119 = 1, $F118, N121 + N122 - N123) -> 123.50849 | O124: =IF( O119 = 1, $F118, O121 + O122 - O123) -> 124.12603 | P124: =IF( P119 = 1, $F118, P121 + P122 - P123) -> 127.51881 | Q124: =IF( Q119 = 1, $F118, Q121 + Q122 - Q123) -> 126.74809 | ... EA124: =IF( EA119 = 1, $F118, EA121 + EA122 - EA123) -> 0
A127: END

Sheet Asset
A1: =RIGHT(CELL("filename", A1), LEN(CELL("filename", A1)) - SEARCH("]", CELL("filename", A1))) & " - " & InpC!F3 -> Asset - Base case 1
E2: =Time!E$25 -> Model period ending | F2: =Check!$F$9 -> 0 | G2: Error chks | J2: =Time!J$25 -> 44104 | K2: =Time!K$25 -> 44196 | L2: =Time!L$25 -> 44286 | M2: =Time!M$25 -> 44377 | N2: =Time!N$25 -> 44469 | O2: =Time!O$25 -> 44561 | P2: =Time!P$25 -> 44651 | Q2: =Time!Q$25 -> 44742 | ... EA2: =Time!EA$25 -> 55153
E3: =Time!E$67 -> Timeline label | F3: =Output!J2 -> 0 | G3: Track chgs | J3: =Time!J$67 -> Pre-fcst | K3: =Time!K$67 -> Pre-fcst | L3: =Time!L$67 -> Fin Close | M3: =Time!M$67 -> Operations | N3: =Time!N$67 -> Operations | O3: =Time!O$67 -> Operations | P3: =Time!P$67 -> Operations | Q3: =Time!Q$67 -> Operations | ... EA3: =Time!EA$67 -> Post ops
E4: =Time!E$42 -> Contract year | F4: =Check!$F$21 -> 0 | G4: Alerts | J4: =Time!J$42 -> 2020 | K4: =Time!K$42 -> 2020 | L4: =Time!L$42 -> 2020 | M4: =Time!M$42 -> 2021 | N4: =Time!N$42 -> 2021 | O4: =Time!O$42 -> 2021 | P4: =Time!P$42 -> 2021 | Q4: =Time!Q$42 -> 2022 | ... EA4: =Time!EA$42 -> 2050
E5: =Time!E$10 -> Model column counter | F5: Constant | G5: Unit | H5: Total | J5: =Time!J$10 -> 1 | K5: =Time!K$10 -> 2 | L5: =Time!L$10 -> 3 | M5: =Time!M$10 -> 4 | N5: =Time!N$10 -> 5 | O5: =Time!O$10 -> 6 | P5: =Time!P$10 -> 7 | Q5: =Time!Q$10 -> 8 | ... EA5: =Time!EA$10 -> 122
A8: FIXED ASSET
B10: Depreciation
E11: =InpC!E$65 -> Fixed asset - initial balance | F11: =InpC!F$65 -> 100000 | G11: =InpC!G$65 -> $ 000s
E12: =InpC!E$41 -> Useful life of asset | F12: =InpC!F$41 -> 25 | G12: =InpC!G$41 -> years
E13: =InpC!E$74 -> Number of periods in a year | F13: =InpC!F$74 -> 4 | G13: =InpC!G$74 -> periods
E14: =Time!E$109 -> Useful life of asset flag | F14: =Time!F$109 -> 0 | G14: =Time!G$109 -> flag | H14: =Time!H$109 -> 100 | I14: =Time!I$109 -> 0 | J14: =Time!J$109 -> 0 | K14: =Time!K$109 -> 0 | L14: =Time!L$109 -> 0 | ... EA14: =Time!EA$109 -> 0
E15: Depreciation of fixed asset POS | G15: =SMU -> $ 000s | H15: =SUM(J15:EA15) -> 100000 | J15: =$F11 / $F12 / $F13 * J14 -> 0 | K15: =$F11 / $F12 / $F13 * K14 -> 0 | L15: =$F11 / $F12 / $F13 * L14 -> 0 | M15: =$F11 / $F12 / $F13 * M14 -> 1000 | N15: =$F11 / $F12 / $F13 * N14 -> 1000 | O15: =$F11 / $F12 / $F13 * O14 -> 1000 | P15: =$F11 / $F12 / $F13 * P14 -> 1000 | Q15: =$F11 / $F12 / $F13 * Q14 -> 1000 | ... EA15: =$F11 / $F12 / $F13 * EA14 -> 0
E16: =LEFT(E15, LEN(E15) - 4) -> Depreciation of fixed asset | G16: =SMU -> $ 000s | H16: =SUM(J16:EA16) -> -100000 | J16: =-1 * J15 -> 0 | K16: =-1 * K15 -> 0 | L16: =-1 * L15 -> 0 | M16: =-1 * M15 -> -1000 | N16: =-1 * N15 -> -1000 | O16: =-1 * O15 -> -1000 | P16: =-1 * P15 -> -1000 | Q16: =-1 * Q15 -> -1000 | ... EA16: =-1 * EA15 -> 0
B18: Fixed asset balance
E20: =InpC!E$65 -> Fixed asset - initial balance | F20: =InpC!F$65 -> 100000 | G20: =InpC!G$65 -> $ 000s
E21: =Time!E$76 -> Financial close date flag | F21: =Time!F$76 -> 0 | G21: =Time!G$76 -> flag | H21: =Time!H$76 -> 1 | I21: =Time!I$76 -> 0 | J21: =Time!J$76 -> 0 | K21: =Time!K$76 -> 0 | L21: =Time!L$76 -> 1 | ... EA21: =Time!EA$76 -> 0
E23: Fixed asset balance BEG | G23: =SMU -> $ 000s | J23: =I26 -> 0 | K23: =J26 -> 0 | L23: =K26 -> 0 | M23: =L26 -> 100000 | N23: =M26 -> 99000 | O23: =N26 -> 98000 | P23: =O26 -> 97000 | Q23: =P26 -> 96000 | ... EA23: =DZ26 -> 0
E24: [Additional capex]
E25: =E$15 -> Depreciation of fixed asset POS | F25: =F$15 -> 0 | G25: =G$15 -> $ 000s | H25: =H$15 -> 100000 | I25: =I$15 -> 0 | J25: =J$15 -> 0 | K25: =K$15 -> 0 | L25: =L$15 -> 0 | ... EA25: =EA$15 -> 0
E26: Fixed asset balance | G26: =SMU -> $ 000s | J26: =IF( J21 = 1, $F20, J23 + J24 - J25) -> 0 | K26: =IF( K21 = 1, $F20, K23 + K24 - K25) -> 0 | L26: =IF( L21 = 1, $F20, L23 + L24 - L25) -> 100000 | M26: =IF( M21 = 1, $F20, M23 + M24 - M25) -> 99000 | N26: =IF( N21 = 1, $F20, N23 + N24 - N25) -> 98000 | O26: =IF( O21 = 1, $F20, O23 + O24 - O25) -> 97000 | P26: =IF( P21 = 1, $F20, P23 + P24 - P25) -> 96000 | Q26: =IF( Q21 = 1, $F20, Q23 + Q24 - Q25) -> 95000 | ... EA26: =IF( EA21 = 1, $F20, EA23 + EA24 - EA25) -> 0
A30: END

Sheet Debt
A1: =RIGHT(CELL("filename", A1), LEN(CELL("filename", A1)) - SEARCH("]", CELL("filename", A1))) & " - " & InpC!F3 -> Debt - Base case 1
E2: =Time!E$25 -> Model period ending | F2: =Check!$F$9 -> 0 | G2: Error chks | J2: =Time!J$25 -> 44104 | K2: =Time!K$25 -> 44196 | L2: =Time!L$25 -> 44286 | M2: =Time!M$25 -> 44377 | N2: =Time!N$25 -> 44469 | O2: =Time!O$25 -> 44561 | P2: =Time!P$25 -> 44651 | Q2: =Time!Q$25 -> 44742 | ... EA2: =Time!EA$25 -> 55153
E3: =Time!E$67 -> Timeline label | F3: =Output!J2 -> 0 | G3: Track chgs | J3: =Time!J$67 -> Pre-fcst | K3: =Time!K$67 -> Pre-fcst | L3: =Time!L$67 -> Fin Close | M3: =Time!M$67 -> Operations | N3: =Time!N$67 -> Operations | O3: =Time!O$67 -> Operations | P3: =Time!P$67 -> Operations | Q3: =Time!Q$67 -> Operations | ... EA3: =Time!EA$67 -> Post ops
E4: =Time!E$42 -> Contract year | F4: =Check!$F$21 -> 0 | G4: Alerts | J4: =Time!J$42 -> 2020 | K4: =Time!K$42 -> 2020 | L4: =Time!L$42 -> 2020 | M4: =Time!M$42 -> 2021 | N4: =Time!N$42 -> 2021 | O4: =Time!O$42 -> 2021 | P4: =Time!P$42 -> 2021 | Q4: =Time!Q$42 -> 2022 | ... EA4: =Time!EA$42 -> 2050
E5: =Time!E$10 -> Model column counter | F5: Constant | G5: Unit | H5: Total | J5: =Time!J$10 -> 1 | K5: =Time!K$10 -> 2 | L5: =Time!L$10 -> 3 | M5: =Time!M$10 -> 4 | N5: =Time!N$10 -> 5 | O5: =Time!O$10 -> 6 | P5: =Time!P$10 -> 7 | Q5: =Time!Q$10 -> 8 | ... EA5: =Time!EA$10 -> 122
A7: SENIOR DEBT
B9: Debt capacity
E10: ='FS Qtr'!E$33 -> Cash flow available for senior debt service | F10: ='FS Qtr'!F$33 -> 0 | G10: ='FS Qtr'!G$33 -> $ 000s | H10: ='FS Qtr'!H$33 -> 322667.04 | I10: ='FS Qtr'!I$33 -> 0 | J10: ='FS Qtr'!J$33 -> 0 | K10: ='FS Qtr'!K$33 -> 0 | L10: ='FS Qtr'!L$33 -> 0 | ... EA10: ='FS Qtr'!EA$33 -> 0
E11: =Time!E$125 -> Senior debt repayment period flag | F11: =Time!F$125 -> 0 | G11: =Time!G$125 -> flag | H11: =Time!H$125 -> 40 | I11: =Time!I$125 -> 0 | J11: =Time!J$125 -> 0 | K11: =Time!K$125 -> 0 | L11: =Time!L$125 -> 0 | ... EA11: =Time!EA$125 -> 0
E12: CFADS during debt term | G12: =SMU -> $ 000s | H12: =SUM(J12:EA12) -> 136095.43 | J12: =J10 * J11 -> 0 | K12: =K10 * K11 -> 0 | L12: =L10 * L11 -> 0 | M12: =M10 * M11 -> 1519.3516 | N12: =N10 * N11 -> 5023.8866 | O12: =O10 * O11 -> 4170.5296 | P12: =P10 * P11 -> 2028.6153 | Q12: =Q10 * Q11 -> 3006.718 | ... EA12: =EA10 * EA11 -> 0
E14: =InpC!E$51 -> DSCR for debt sizing | F14: =InpC!F$51 -> 1.3 | G14: =InpC!G$51 -> ratio
E15: =E$12 -> CFADS during debt term | F15: =F$12 -> 0 | G15: =G$12 -> $ 000s | H15: =H$12 -> 136095.43 | I15: =I$12 -> 0 | J15: =J$12 -> 0 | K15: =K$12 -> 0 | L15: =L$12 -> 0 | ... EA15: =EA$12 -> 0
E16: Debt service at target DSCR | G16: =SMU -> $ 000s | H16: =SUM(J16:EA16) -> 104688.79 | J16: =J15 / $F14 -> 0 | K16: =K15 / $F14 -> 0 | L16: =L15 / $F14 -> 0 | M16: =M15 / $F14 -> 1168.732 | N16: =N15 / $F14 -> 3864.5282 | O16: =O15 / $F14 -> 3208.0997 | P16: =P15 / $F14 -> 1560.4733 | Q16: =Q15 / $F14 -> 2312.86 | ... EA16: =EA15 / $F14 -> 0
E18: =Time!E$76 -> Financial close date flag | F18: =Time!F$76 -> 0 | G18: =Time!G$76 -> flag | H18: =Time!H$76 -> 1 | I18: =Time!I$76 -> 0 | J18: =Time!J$76 -> 0 | K18: =Time!K$76 -> 0 | L18: =Time!L$76 -> 1 | ... EA18: =Time!EA$76 -> 0
E19: =E$77 -> Senior debt period interest rate | F19: =F$77 -> 0 | G19: =G$77 -> rate | H19: =H$77 -> 0 | I19: =I$77 -> 0 | J19: =J$77 -> 0.015333333 | K19: =K$77 -> 0.015333333 | L19: =L$77 -> 0.015 | ... EA19: =EA$77 -> 0.015333333
E20: Senior debt discount factor | G20: ratio | J20: =IF( J18 = 1, 1, I20 / (1 + J19)) -> 0 | K20: =IF( K18 = 1, 1, J20 / (1 + K19)) -> 0 | L20: =IF( L18 = 1, 1, K20 / (1 + L19)) -> 1 | M20: =IF( M18 = 1, 1, L20 / (1 + M19)) -> 0.98505992 | N20: =IF( N18 = 1, 1, M20 / (1 + N19)) -> 0.97018377 | O20: =IF( O18 = 1, 1, N20 / (1 + O19)) -> 0.95553228 | P20: =IF( P18 = 1, 1, O20 / (1 + P19)) -> 0.94141111 | Q20: =IF( Q18 = 1, 1, P20 / (1 + Q19)) -> 0.92734636 | ... EA20: =IF( EA18 = 1, 1, DZ20 / (1 + EA19)) -> 0.16570915
E22: =E$16 -> Debt service at target DSCR | F22: =F$16 -> 0 | G22: =G$16 -> $ 000s | H22: =H$16 -> 104688.79 | I22: =I$16 -> 0 | J22: =J$16 -> 0 | K22: =K$16 -> 0 | L22: =L$16 -> 0 | ... EA22: =EA$16 -> 0
E23: =E$20 -> Senior debt discount factor | F23: =F$20 -> 0 | G23: =G$20 -> ratio | H23: =H$20 -> 0 | I23: =I$20 -> 0 | J23: =J$20 -> 0 | K23: =K$20 -> 0 | L23: =L$20 -> 1 | ... EA23: =EA$20 -> 0.16570915
E24: Debt capacity at target ratio | F24: =SUMPRODUCT(J22:EA22, J23:EA23) -> 78175.933 | G24: =SMU -> $ 000s
B27: Senior debt initial drawdown
E28: =InpC!E$52 -> Senior debt sizing method | F28: =InpC!F$52 -> 2 | G28: =InpC!G$52 -> 1 = leverage, 2 = DSCR
E29: =InpC!E$46 -> Senior debt leverage | F29: =InpC!F$46 -> 0.7 | G29: =InpC!G$46 -> %
E30: =InpC!E$65 -> Fixed asset - initial balance | F30: =InpC!F$65 -> 100000 | G30: =InpC!G$65 -> $ 000s
E31: =E$24 -> Debt capacity at target ratio | F31: =F$24 -> 78175.933 | G31: =G$24 -> $ 000s
E32: Senior debt initial drawdown | F32: =IF( F28 = 1, F29 * F30, F31) -> 78175.933 | G32: =SMU -> $ 000s
B34: Senior debt principal repayment
C35: Level principal repayment
E36: =E$32 -> Senior debt initial drawdown | F36: =F$32 -> 78175.933 | G36: =G$32 -> $ 000s
E37: =InpC!E$45 -> Senior debt repayment period | F37: =InpC!F$45 -> 10 | G37: =InpC!G$45 -> years
E38: =InpC!E$74 -> Number of periods in a year | F38: =InpC!F$74 -> 4 | G38: =InpC!G$74 -> periods
E39: =Time!E$125 -> Senior debt repayment period flag | F39: =Time!F$125 -> 0 | G39: =Time!G$125 -> flag | H39: =Time!H$125 -> 40 | I39: =Time!I$125 -> 0 | J39: =Time!J$125 -> 0 | K39: =Time!K$125 -> 0 | L39: =Time!L$125 -> 0 | ... EA39: =Time!EA$125 -> 0
E40: Senior debt straight line principal repayment | G40: =SMU -> $ 000s | H40: =SUM(J40:EA40) -> 78175.933 | J40: =$F36 / $F37 / $F38 * J39 -> 0 | K40: =$F36 / $F37 / $F38 * K39 -> 0 | L40: =$F36 / $F37 / $F38 * L39 -> 0 | M40: =$F36 / $F37 / $F38 * M39 -> 1954.3983 | N40: =$F36 / $F37 / $F38 * N39 -> 1954.3983 | O40: =$F36 / $F37 / $F38 * O39 -> 1954.3983 | P40: =$F36 / $F37 / $F38 * P39 -> 1954.3983 | Q40: =$F36 / $F37 / $F38 * Q39 -> 1954.3983 | ... EA40: =$F36 / $F37 / $F38 * EA39 -> 0
C42: Amortising debt repayment
E43: =E$20 -> Senior debt discount factor | F43: =F$20 -> 0 | G43: =G$20 -> ratio | H43: =H$20 -> 0 | I43: =I$20 -> 0 | J43: =J$20 -> 0 | K43: =K$20 -> 0 | L43: =L$20 -> 1 | ... EA43: =EA$20 -> 0.16570915
E44: =Time!E$125 -> Senior debt repayment period flag | F44: =Time!F$125 -> 0 | G44: =Time!G$125 -> flag | H44: =Time!H$125 -> 40 | I44: =Time!I$125 -> 0 | J44: =Time!J$125 -> 0 | K44: =Time!K$125 -> 0 | L44: =Time!L$125 -> 0 | ... EA44: =Time!EA$125 -> 0
E45: Sum of senior debt discount factors | F45: =SUMPRODUCT(J43:EA43, J44:EA44) -> 29.796052 | G45: ratio
E47: =E$32 -> Senior debt initial drawdown | F47: =F$32 -> 78175.933 | G47: =G$32 -> $ 000s
E48: =E$45 -> Sum of senior debt discount factors | F48: =F$45 -> 29.796052 | G48: =G$45 -> ratio
E49: Senior debt periodic amortising debt service | F49: =F47 / F48 -> 2623.701 | G49: =SMU -> $ 000s
E51: =E$49 -> Senior debt periodic amortising debt service | F51: =F$49 -> 2623.701 | G51: =G$49 -> $ 000s
E52: =Time!E$125 -> Senior debt repayment period flag | F52: =Time!F$125 -> 0 | G52: =Time!G$125 -> flag | H52: =Time!H$125 -> 40 | I52: =Time!I$125 -> 0 | J52: =Time!J$125 -> 0 | K52: =Time!K$125 -> 0 | L52: =Time!L$125 -> 0 | ... EA52: =Time!EA$125 -> 0
E53: Senior debt amortising debt service | G53: =SMU -> $ 000s | H53: =SUM(J53:EA53) -> 104948.04 | J53: =$F51 * J52 -> 0 | K53: =$F51 * K52 -> 0 | L53: =$F51 * L52 -> 0 | M53: =$F51 * M52 -> 2623.701 | N53: =$F51 * N52 -> 2623.701 | O53: =$F51 * O52 -> 2623.701 | P53: =$F51 * P52 -> 2623.701 | Q53: =$F51 * Q52 -> 2623.701 | ... EA53: =$F51 * EA52 -> 0
E55: =E$53 -> Senior debt amortising debt service | F55: =F$53 -> 0 | G55: =G$53 -> $ 000s | H55: =H$53 -> 104948.04 | I55: =I$53 -> 0 | J55: =J$53 -> 0 | K55: =K$53 -> 0 | L55: =L$53 -> 0 | ... EA55: =EA$53 -> 0
E56: =E$81 -> Senior debt interest POS | F56: =F$81 -> 0 | G56: =G$81 -> $ 000s | H56: =H$81 -> 26512.862 | I56: =I$81 -> 0 | J56: =J$81 -> 0 | K56: =K$81 -> 0 | L56: =L$81 -> 0 | ... EA56: =EA$81 -> -7.0333755e-12
E57: Senior debt amortising principal repayment | G57: =SMU -> $ 000s | H57: =SUM(J57:EA57) -> 78435.179 | J57: =J55 - J56 -> 0 | K57: =K55 - K56 -> 0 | L57: =L55 - L56 -> 0 | M57: =M55 - M56 -> 1438.0327 | N57: =N55 - N56 -> 1424.7437 | O57: =O55 - O56 -> 1465.6158 | P57: =P55 - P56 -> 1521.5418 | Q57: =Q55 - Q56 -> 1516.2467 | ... EA57: =EA55 - EA56 -> 7.0333755e-12
C59: Sculpted debt repayment
E60: =E$16 -> Debt service at target DSCR | F60: =F$16 -> 0 | G60: =G$16 -> $ 000s | H60: =H$16 -> 104688.79 | I60: =I$16 -> 0 | J60: =J$16 -> 0 | K60: =K$16 -> 0 | L60: =L$16 -> 0 | ... EA60: =EA$16 -> 0
E61: =E$81 -> Senior debt interest POS | F61: =F$81 -> 0 | G61: =G$81 -> $ 000s | H61: =H$81 -> 26512.862 | I61: =I$81 -> 0 | J61: =J$81 -> 0 | K61: =K$81 -> 0 | L61: =L$81 -> 0 | ... EA61: =EA$81 -> -7.0333755e-12
E62: Senior debt sculpted principal repayment | G62: =SMU -> $ 000s | H62: =SUM(J62:EA62) -> 78175.933 | J62: =J60 - J61 -> 0 | K62: =K60 - K61 -> 0 | L62: =L60 - L61 -> 0 | M62: =M60 - M61 -> -16.936274 | N62: =N60 - N61 -> 2665.5708 | O62: =O60 - O61 -> 2050.0144 | P62: =P60 - P61 -> 458.31407 | Q62: =Q60 - Q61 -> 1205.4057 | ... EA62: =EA60 - EA61 -> 7.0333755e-12
E64: =InpC!E$47 -> Senior debt principal repayment profile selection | F64: =InpC!F$47 -> 3 | G64: =InpC!G$47 -> profile selection
E65: =E$40 -> Senior debt straight line principal repayment | F65: =F$40 -> 0 | G65: =G$40 -> $ 000s | H65: =H$40 -> 78175.933 | I65: =I$40 -> 0 | J65: =J$40 -> 0 | K65: =K$40 -> 0 | L65: =L$40 -> 0 | ... EA65: =EA$40 -> 0
E66: =E$57 -> Senior debt amortising principal repayment | F66: =F$57 -> 0 | G66: =G$57 -> $ 000s | H66: =H$57 -> 78435.179 | I66: =I$57 -> 0 | J66: =J$57 -> 0 | K66: =K$57 -> 0 | L66: =L$57 -> 0 | ... EA66: =EA$57 -> 7.0333755e-12
E67: =E$62 -> Senior debt sculpted principal repayment | F67: =F$62 -> 0 | G67: =G$62 -> $ 000s | H67: =H$62 -> 78175.933 | I67: =I$62 -> 0 | J67: =J$62 -> 0 | K67: =K$62 -> 0 | L67: =L$62 -> 0 | ... EA67: =EA$62 -> 7.0333755e-12
E68: Senior debt principal repayment POS | G68: =SMU -> $ 000s | H68: =SUM(J68:EA68) -> 78175.933 | J68: =INDEX(J65:J67, $F64) -> 0 | K68: =INDEX(K65:K67, $F64) -> 0 | L68: =INDEX(L65:L67, $F64) -> 0 | M68: =INDEX(M65:M67, $F64) -> -16.936274 | N68: =INDEX(N65:N67, $F64) -> 2665.5708 | O68: =INDEX(O65:O67, $F64) -> 2050.0144 | P68: =INDEX(P65:P67, $F64) -> 458.31407 | Q68: =INDEX(Q65:Q67, $F64) -> 1205.4057 | ... EA68: =INDEX(EA65:EA67, $F64) -> 7.0333755e-12
E69: =LEFT(E68, LEN(E68) - 4) -> Senior debt principal repayment | G69: =SMU -> $ 000s | H69: =SUM(J69:EA69) -> -78175.933 | J69: =-1 * J68 -> 0 | K69: =-1 * K68 -> 0 | L69: =-1 * L68 -> 0 | M69: =-1 * M68 -> 16.936274 | N69: =-1 * N68 -> -2665.5708 | O69: =-1 * O68 -> -2050.0144 | P69: =-1 * P68 -> -458.31407 | Q69: =-1 * Q68 -> -1205.4057 | ... EA69: =-1 * EA68 -> -7.0333755e-12
B71: Senior debt interest
E73: =InpC!E$48 -> Senior debt swap rate | F73: =InpC!F$48 -> 0.025 | G73: =InpC!G$48 -> % p.a.
E74: =InpC!E$49 -> Senior debt margin | F74: =InpC!F$49 -> 0.035 | G74: =InpC!G$49 -> % p.a.
E75: =InpC!E$50 -> Senior debt day count convention | F75: =InpC!F$50 -> 360 | G75: =InpC!G$50 -> days / year
E76: =Time!E$149 -> Days in period | F76: =Time!F$149 -> 0 | G76: =Time!G$149 -> days | H76: =Time!H$149 -> 0 | I76: =Time!I$149 -> 0 | J76: =Time!J$149 -> 92 | K76: =Time!K$149 -> 92 | L76: =Time!L$149 -> 90 | ... EA76: =Time!EA$149 -> 92
E77: Senior debt period interest rate | G77: rate | J77: =($F73 + $F74) / $F75 * J76 -> 0.015333333 | K77: =($F73 + $F74) / $F75 * K76 -> 0.015333333 | L77: =($F73 + $F74) / $F75 * L76 -> 0.015 | M77: =($F73 + $F74) / $F75 * M76 -> 0.015166667 | N77: =($F73 + $F74) / $F75 * N76 -> 0.015333333 | O77: =($F73 + $F74) / $F75 * O76 -> 0.015333333 | P77: =($F73 + $F74) / $F75 * P76 -> 0.015 | Q77: =($F73 + $F74) / $F75 * Q76 -> 0.015166667 | ... EA77: =($F73 + $F74) / $F75 * EA76 -> 0.015333333
E79: =E$90 -> Senior debt balance BEG | F79: =F$90 -> 0 | G79: =G$90 -> $ 000s | H79: =H$90 -> 0 | I79: =I$90 -> 0 | J79: =J$90 -> 0 | K79: =K$90 -> 0 | L79: =L$90 -> 0 | ... EA79: =EA$90 -> -4.586984e-10
E80: =E$77 -> Senior debt period interest rate | F80: =F$77 -> 0 | G80: =G$77 -> rate | H80: =H$77 -> 0 | I80: =I$77 -> 0 | J80: =J$77 -> 0.015333333 | K80: =K$77 -> 0.015333333 | L80: =L$77 -> 0.015 | ... EA80: =EA$77 -> 0.015333333
E81: Senior debt interest POS | G81: =SMU -> $ 000s | H81: =SUM(J81:EA81) -> 26512.862 | J81: =J79 * J80 -> 0 | K81: =K79 * K80 -> 0 | L81: =L79 * L80 -> 0 | M81: =M79 * M80 -> 1185.6683 | N81: =N79 * N80 -> 1198.9573 | O81: =O79 * O80 -> 1158.0852 | P81: =P79 * P80 -> 1102.1593 | Q81: =Q79 * Q80 -> 1107.4544 | ... EA81: =EA79 * EA80 -> -7.0333755e-12
E82: =LEFT(E81, LEN(E81) - 4) -> Senior debt interest | G82: =SMU -> $ 000s | H82: =SUM(J82:EA82) -> -26512.862 | J82: =-1 * J81 -> 0 | K82: =-1 * K81 -> 0 | L82: =-1 * L81 -> 0 | M82: =-1 * M81 -> -1185.6683 | N82: =-1 * N81 -> -1198.9573 | O82: =-1 * O81 -> -1158.0852 | P82: =-1 * P81 -> -1102.1593 | Q82: =-1 * Q81 -> -1107.4544 | ... EA82: =-1 * EA81 -> 7.0333755e-12
B85: Senior debt balance
E87: =E$32 -> Senior debt initial drawdown | F87: =F$32 -> 78175.933 | G87: =G$32 -> $ 000s
E88: =Time!E$76 -> Financial close date flag | F88: =Time!F$76 -> 0 | G88: =Time!G$76 -> flag | H88: =Time!H$76 -> 1 | I88: =Time!I$76 -> 0 | J88: =Time!J$76 -> 0 | K88: =Time!K$76 -> 0 | L88: =Time!L$76 -> 1 | ... EA88: =Time!EA$76 -> 0
E90: Senior debt balance BEG | G90: =SMU -> $ 000s | J90: =I92 -> 0 | K90: =J92 -> 0 | L90: =K92 -> 0 | M90: =L92 -> 78175.933 | N90: =M92 -> 78192.869 | O90: =N92 -> 75527.298 | P90: =O92 -> 73477.284 | Q90: =P92 -> 73018.97 | ... EA90: =DZ92 -> -4.586984e-10
E91: =E$68 -> Senior debt principal repayment POS | F91: =F$68 -> 0 | G91: =G$68 -> $ 000s | H91: =H$68 -> 78175.933 | I91: =I$68 -> 0 | J91: =J$68 -> 0 | K91: =K$68 -> 0 | L91: =L$68 -> 0 | ... EA91: =EA$68 -> 7.0333755e-12
E92: Senior debt balance | G92: =SMU -> $ 000s | J92: =IF( J88 = 1, $F87, J90 - J91) -> 0 | K92: =IF( K88 = 1, $F87, K90 - K91) -> 0 | L92: =IF( L88 = 1, $F87, L90 - L91) -> 78175.933 | M92: =IF( M88 = 1, $F87, M90 - M91) -> 78192.869 | N92: =IF( N88 = 1, $F87, N90 - N91) -> 75527.298 | O92: =IF( O88 = 1, $F87, O90 - O91) -> 73477.284 | P92: =IF( P88 = 1, $F87, P90 - P91) -> 73018.97 | Q92: =IF( Q88 = 1, $F87, Q90 - Q91) -> 71813.564 | ... EA92: =IF( EA88 = 1, $F87, EA90 - EA91) -> -4.6573178e-10
B95: Senior debt service
E96: =E$81 -> Senior debt interest POS | F96: =F$81 -> 0 | G96: =G$81 -> $ 000s | H96: =H$81 -> 26512.862 | I96: =I$81 -> 0 | J96: =J$81 -> 0 | K96: =K$81 -> 0 | L96: =L$81 -> 0 | ... EA96: =EA$81 -> -7.0333755e-12
E97: =E$68 -> Senior debt principal repayment POS | F97: =F$68 -> 0 | G97: =G$68 -> $ 000s | H97: =H$68 -> 78175.933 | I97: =I$68 -> 0 | J97: =J$68 -> 0 | K97: =K$68 -> 0 | L97: =L$68 -> 0 | ... EA97: =EA$68 -> 7.0333755e-12
E98: Senior debt service | G98: =SMU -> $ 000s | H98: =SUM(J98:EA98) -> 104688.79 | J98: =SUM(J96:J97) -> 0 | K98: =SUM(K96:K97) -> 0 | L98: =SUM(L96:L97) -> 0 | M98: =SUM(M96:M97) -> 1168.732 | N98: =SUM(N96:N97) -> 3864.5282 | O98: =SUM(O96:O97) -> 3208.0997 | P98: =SUM(P96:P97) -> 1560.4733 | Q98: =SUM(Q96:Q97) -> 2312.86 | ... EA98: =SUM(EA96:EA97) -> 0
A102: END

Sheet Equity
A1: =RIGHT(CELL("filename", A1), LEN(CELL("filename", A1)) - SEARCH("]", CELL("filename", A1))) & " - " & InpC!F3 -> Equity - Base case 1
E2: =Time!E$25 -> Model period ending | F2: =Check!$F$9 -> 0 | G2: Error chks | J2: =Time!J$25 -> 44104 | K2: =Time!K$25 -> 44196 | L2: =Time!L$25 -> 44286 | M2: =Time!M$25 -> 44377 | N2: =Time!N$25 -> 44469 | O2: =Time!O$25 -> 44561 | P2: =Time!P$25 -> 44651 | Q2: =Time!Q$25 -> 44742 | ... EA2: =Time!EA$25 -> 55153
E3: =Time!E$67 -> Timeline label | F3: =Output!J2 -> 0 | G3: Track chgs | J3: =Time!J$67 -> Pre-fcst | K3: =Time!K$67 -> Pre-fcst | L3: =Time!L$67 -> Fin Close | M3: =Time!M$67 -> Operations | N3: =Time!N$67 -> Operations | O3: =Time!O$67 -> Operations | P3: =Time!P$67 -> Operations | Q3: =Time!Q$67 -> Operations | ... EA3: =Time!EA$67 -> Post ops
E4: =Time!E$42 -> Contract year | F4: =Check!$F$21 -> 0 | G4: Alerts | J4: =Time!J$42 -> 2020 | K4: =Time!K$42 -> 2020 | L4: =Time!L$42 -> 2020 | M4: =Time!M$42 -> 2021 | N4: =Time!N$42 -> 2021 | O4: =Time!O$42 -> 2021 | P4: =Time!P$42 -> 2021 | Q4: =Time!Q$42 -> 2022 | ... EA4: =Time!EA$42 -> 2050
E5: =Time!E$10 -> Model column counter | F5: Constant | G5: Unit | H5: Total | J5: =Time!J$10 -> 1 | K5: =Time!K$10 -> 2 | L5: =Time!L$10 -> 3 | M5: =Time!M$10 -> 4 | N5: =Time!N$10 -> 5 | O5: =Time!O$10 -> 6 | P5: =Time!P$10 -> 7 | Q5: =Time!Q$10 -> 8 | ... EA5: =Time!EA$10 -> 122
A8: SHARE CAPITAL
B10: Share capital initial drawdown
E11: =InpC!E$65 -> Fixed asset - initial balance | F11: =InpC!F$65 -> 100000 | G11: =InpC!G$65 -> $ 000s
E12: =Debt!E$32 -> Senior debt initial drawdown | F12: =Debt!F$32 -> 78175.933 | G12: =Debt!G$32 -> $ 000s
E13: Share capital - initial drawdown | F13: =F11 - F12 -> 21824.067 | G13: =SMU -> $ 000s
B15: Share capital redemption
E16: =E$26 -> Share capital balance BEG | F16: =F$26 -> 0 | G16: =G$26 -> $ 000s | H16: =H$26 -> 0 | I16: =I$26 -> 0 | J16: =J$26 -> 0 | K16: =K$26 -> 0 | L16: =L$26 -> 0 | ... EA16: =EA$26 -> 0
E17: =Time!E$91 -> Last operating period flag | F17: =Time!F$91 -> 0 | G17: =Time!G$91 -> flag | H17: =Time!H$91 -> 1 | I17: =Time!I$91 -> 0 | J17: =Time!J$91 -> 0 | K17: =Time!K$91 -> 0 | L17: =Time!L$91 -> 0 | ... EA17: =Time!EA$91 -> 0
E18: Share capital redemption POS | G18: =SMU -> $ 000s | H18: =SUM(J18:EA18) -> 21824.067 | J18: =J16 * J17 -> 0 | K18: =K16 * K17 -> 0 | L18: =L16 * L17 -> 0 | M18: =M16 * M17 -> 0 | N18: =N16 * N17 -> 0 | O18: =O16 * O17 -> 0 | P18: =P16 * P17 -> 0 | Q18: =Q16 * Q17 -> 0 | ... EA18: =EA16 * EA17 -> 0
E19: =LEFT(E18, LEN(E18) - 4) -> Share capital redemption | G19: =SMU -> $ 000s | H19: =SUM(J19:EA19) -> -21824.067 | J19: =-1 * J18 -> 0 | K19: =-1 * K18 -> 0 | L19: =-1 * L18 -> 0 | M19: =-1 * M18 -> 0 | N19: =-1 * N18 -> 0 | O19: =-1 * O18 -> 0 | P19: =-1 * P18 -> 0 | Q19: =-1 * Q18 -> 0 | ... EA19: =-1 * EA18 -> 0
B21: Share capital balance
E23: =E$13 -> Share capital - initial drawdown | F23: =F$13 -> 21824.067 | G23: =G$13 -> $ 000s
E24: =Time!E$76 -> Financial close date flag | F24: =Time!F$76 -> 0 | G24: =Time!G$76 -> flag | H24: =Time!H$76 -> 1 | I24: =Time!I$76 -> 0 | J24: =Time!J$76 -> 0 | K24: =Time!K$76 -> 0 | L24: =Time!L$76 -> 1 | ... EA24: =Time!EA$76 -> 0
E26: Share capital balance BEG | G26: =SMU -> $ 000s | J26: =I29 -> 0 | K26: =J29 -> 0 | L26: =K29 -> 0 | M26: =L29 -> 21824.067 | N26: =M29 -> 21824.067 | O26: =N29 -> 21824.067 | P26: =O29 -> 21824.067 | Q26: =P29 -> 21824.067 | ... EA26: =DZ29 -> 0
E27: [Additional share capital issued]
E28: =E$18 -> Share capital redemption POS | F28: =F$18 -> 0 | G28: =G$18 -> $ 000s | H28: =H$18 -> 21824.067 | I28: =I$18 -> 0 | J28: =J$18 -> 0 | K28: =K$18 -> 0 | L28: =L$18 -> 0 | ... EA28: =EA$18 -> 0
E29: Share capital balance | G29: =SMU -> $ 000s | J29: =IF( J24 = 1, $F23, J26 + J27 - J28) -> 0 | K29: =IF( K24 = 1, $F23, K26 + K27 - K28) -> 0 | L29: =IF( L24 = 1, $F23, L26 + L27 - L28) -> 21824.067 | M29: =IF( M24 = 1, $F23, M26 + M27 - M28) -> 21824.067 | N29: =IF( N24 = 1, $F23, N26 + N27 - N28) -> 21824.067 | O29: =IF( O24 = 1, $F23, O26 + O27 - O28) -> 21824.067 | P29: =IF( P24 = 1, $F23, P26 + P27 - P28) -> 21824.067 | Q29: =IF( Q24 = 1, $F23, Q26 + Q27 - Q28) -> 21824.067 | ... EA29: =IF( EA24 = 1, $F23, EA26 + EA27 - EA28) -> 0
A33: RETAINED EARNINGS
E35: =InpC!E$61 -> Retained earnings - initial balance | F35: =InpC!F$61 -> 0 | G35: =InpC!G$61 -> $ 000s
E36: =Time!E$76 -> Financial close date flag | F36: =Time!F$76 -> 0 | G36: =Time!G$76 -> flag | H36: =Time!H$76 -> 1 | I36: =Time!I$76 -> 0 | J36: =Time!J$76 -> 0 | K36: =Time!K$76 -> 0 | L36: =Time!L$76 -> 1 | ... EA36: =Time!EA$76 -> 0
E38: Retained earnings balance BEG | G38: =SMU -> $ 000s | J38: =I41 -> 0 | K38: =J41 -> 0 | L38: =K41 -> 0 | M38: =L41 -> 0 | N38: =M41 -> 2288.4621 | O38: =N41 -> 4225.8869 | P38: =O41 -> 3167.9061 | Q38: =P41 -> 2658.2359 | ... EA38: =DZ41 -> 4.5497892e-10
E39: ='FS Qtr'!E$22 -> Profit after tax | F39: ='FS Qtr'!F$22 -> 0 | G39: ='FS Qtr'!G$22 -> $ 000s | H39: ='FS Qtr'!H$22 -> 196154.18 | I39: ='FS Qtr'!I$22 -> 0 | J39: ='FS Qtr'!J$22 -> 0 | K39: ='FS Qtr'!K$22 -> 0 | L39: ='FS Qtr'!L$22 -> 0 | ... EA39: ='FS Qtr'!EA$22 -> 7.0333755e-12
E40: =E$69 -> Dividends paid POS | F40: =F$69 -> 0 | G40: =G$69 -> $ 000s | H40: =H$69 -> 196154.18 | I40: =I$69 -> 0 | J40: =J$69 -> 0 | K40: =K$69 -> 0 | L40: =L$69 -> 0 | ... EA40: =EA$69 -> 0
E41: Retained earnings balance | G41: =SMU -> $ 000s | J41: =IF( J36 = 1, $F35, J38 + J39 - J40) -> 0 | K41: =IF( K36 = 1, $F35, K38 + K39 - K40) -> 0 | L41: =IF( L36 = 1, $F35, L38 + L39 - L40) -> 0 | M41: =IF( M36 = 1, $F35, M38 + M39 - M40) -> 2288.4621 | N41: =IF( N36 = 1, $F35, N38 + N39 - N40) -> 4225.8869 | O41: =IF( O36 = 1, $F35, O38 + O39 - O40) -> 3167.9061 | P41: =IF( P36 = 1, $F35, P38 + P39 - P40) -> 2658.2359 | Q41: =IF( Q36 = 1, $F35, Q38 + Q39 - Q40) -> 4648.2006 | ... EA41: =IF( EA36 = 1, $F35, EA38 + EA39 - EA40) -> 4.620123e-10
A44: RETAINED CASH
E46: =InpC!E$62 -> Retained cash - initial balance | F46: =InpC!F$62 -> 0 | G46: =InpC!G$62 -> $ 000s
E47: =Time!E$76 -> Financial close date flag | F47: =Time!F$76 -> 0 | G47: =Time!G$76 -> flag | H47: =Time!H$76 -> 1 | I47: =Time!I$76 -> 0 | J47: =Time!J$76 -> 0 | K47: =Time!K$76 -> 0 | L47: =Time!L$76 -> 1 | ... EA47: =Time!EA$76 -> 0
E49: Retained cash balance BEG | G49: =SMU -> $ 000s | J49: =I52 -> 0 | K49: =J52 -> 0 | L49: =K52 -> 0 | M49: =L52 -> 0 | N49: =M52 -> 0 | O49: =N52 -> 0 | P49: =O52 -> 0 | Q49: =P52 -> 0 | ... EA49: =DZ52 -> 0
E50: ='FS Qtr'!E$50 -> Cash flow available for dividends | F50: ='FS Qtr'!F$50 -> 0 | G50: ='FS Qtr'!G$50 -> $ 000s | H50: ='FS Qtr'!H$50 -> 196154.18 | I50: ='FS Qtr'!I$50 -> 0 | J50: ='FS Qtr'!J$50 -> 0 | K50: ='FS Qtr'!K$50 -> 0 | L50: ='FS Qtr'!L$50 -> 0 | ... EA50: ='FS Qtr'!EA$50 -> 0
E51: =E$69 -> Dividends paid POS | F51: =F$69 -> 0 | G51: =G$69 -> $ 000s | H51: =H$69 -> 196154.18 | I51: =I$69 -> 0 | J51: =J$69 -> 0 | K51: =K$69 -> 0 | L51: =L$69 -> 0 | ... EA51: =EA$69 -> 0
E52: Retained cash balance | G52: =SMU -> $ 000s | J52: =IF( J47 = 1, $F46, J49 + J50 - J51) -> 0 | K52: =IF( K47 = 1, $F46, K49 + K50 - K51) -> 0 | L52: =IF( L47 = 1, $F46, L49 + L50 - L51) -> 0 | M52: =IF( M47 = 1, $F46, M49 + M50 - M51) -> 0 | N52: =IF( N47 = 1, $F46, N49 + N50 - N51) -> 0 | O52: =IF( O47 = 1, $F46, O49 + O50 - O51) -> 0 | P52: =IF( P47 = 1, $F46, P49 + P50 - P51) -> 0 | Q52: =IF( Q47 = 1, $F46, Q49 + Q50 - Q51) -> 0 | ... EA52: =IF( EA47 = 1, $F46, EA49 + EA50 - EA51) -> 0
A54: DIVIDENDS
B56: Earnings available for dividend
E57: =E$38 -> Retained earnings balance BEG | F57: =F$38 -> 0 | G57: =G$38 -> $ 000s | H57: =H$38 -> 0 | I57: =I$38 -> 0 | J57: =J$38 -> 0 | K57: =K$38 -> 0 | L57: =L$38 -> 0 | ... EA57: =EA$38 -> 4.5497892e-10
E58: ='FS Qtr'!E$22 -> Profit after tax | F58: ='FS Qtr'!F$22 -> 0 | G58: ='FS Qtr'!G$22 -> $ 000s | H58: ='FS Qtr'!H$22 -> 196154.18 | I58: ='FS Qtr'!I$22 -> 0 | J58: ='FS Qtr'!J$22 -> 0 | K58: ='FS Qtr'!K$22 -> 0 | L58: ='FS Qtr'!L$22 -> 0 | ... EA58: ='FS Qtr'!EA$22 -> 7.0333755e-12
E59: Earnings available for dividend | G59: =SMU -> $ 000s | J59: =SUM(J57:J58) -> 0 | K59: =SUM(K57:K58) -> 0 | L59: =SUM(L57:L58) -> 0 | M59: =SUM(M57:M58) -> 2639.0817 | N59: =SUM(N57:N58) -> 5385.2454 | O59: =SUM(O57:O58) -> 4130.336 | P59: =SUM(P57:P58) -> 3126.3779 | Q59: =SUM(Q57:Q58) -> 5342.0586 | ... EA59: =SUM(EA57:EA58) -> 4.620123e-10
B61: Cash available for dividend
E62: =E$49 -> Retained cash balance BEG | F62: =F$49 -> 0 | G62: =G$49 -> $ 000s | H62: =H$49 -> 0 | I62: =I$49 -> 0 | J62: =J$49 -> 0 | K62: =K$49 -> 0 | L62: =L$49 -> 0 | ... EA62: =EA$49 -> 0
E63: ='FS Qtr'!E$50 -> Cash flow available for dividends | F63: ='FS Qtr'!F$50 -> 0 | G63: ='FS Qtr'!G$50 -> $ 000s | H63: ='FS Qtr'!H$50 -> 196154.18 | I63: ='FS Qtr'!I$50 -> 0 | J63: ='FS Qtr'!J$50 -> 0 | K63: ='FS Qtr'!K$50 -> 0 | L63: ='FS Qtr'!L$50 -> 0 | ... EA63: ='FS Qtr'!EA$50 -> 0
E64: Cash available for dividend | G64: =SMU -> $ 000s | J64: =SUM(J62:J63) -> 0 | K64: =SUM(K62:K63) -> 0 | L64: =SUM(L62:L63) -> 0 | M64: =SUM(M62:M63) -> 350.61961 | N64: =SUM(N62:N63) -> 1159.3584 | O64: =SUM(O62:O63) -> 962.4299 | P64: =SUM(P62:P63) -> 468.142 | Q64: =SUM(Q62:Q63) -> 693.85801 | ... EA64: =SUM(EA62:EA63) -> 0
B66: Dividends paid
E67: =E$59 -> Earnings available for dividend | F67: =F$59 -> 0 | G67: =G$59 -> $ 000s | H67: =H$59 -> 0 | I67: =I$59 -> 0 | J67: =J$59 -> 0 | K67: =K$59 -> 0 | L67: =L$59 -> 0 | ... EA67: =EA$59 -> 4.620123e-10
E68: =E$64 -> Cash available for dividend | F68: =F$64 -> 0 | G68: =G$64 -> $ 000s | H68: =H$64 -> 0 | I68: =I$64 -> 0 | J68: =J$64 -> 0 | K68: =K$64 -> 0 | L68: =L$64 -> 0 | ... EA68: =EA$64 -> 0
E69: Dividends paid POS | G69: =SMU -> $ 000s | H69: =SUM(J69:EA69) -> 196154.18 | J69: =MAX(0, MIN(J67:J68)) -> 0 | K69: =MAX(0, MIN(K67:K68)) -> 0 | L69: =MAX(0, MIN(L67:L68)) -> 0 | M69: =MAX(0, MIN(M67:M68)) -> 350.61961 | N69: =MAX(0, MIN(N67:N68)) -> 1159.3584 | O69: =MAX(0, MIN(O67:O68)) -> 962.4299 | P69: =MAX(0, MIN(P67:P68)) -> 468.142 | Q69: =MAX(0, MIN(Q67:Q68)) -> 693.85801 | ... EA69: =MAX(0, MIN(EA67:EA68)) -> 0
E70: =LEFT(E69, LEN(E69) - 4) -> Dividends paid | G70: =SMU -> $ 000s | H70: =SUM(J70:EA70) -> -196154.18 | J70: =-1 * J69 -> 0 | K70: =-1 * K69 -> 0 | L70: =-1 * L69 -> 0 | M70: =-1 * M69 -> -350.61961 | N70: =-1 * N69 -> -1159.3584 | O70: =-1 * O69 -> -962.4299 | P70: =-1 * P69 -> -468.142 | Q70: =-1 * Q69 -> -693.85801 | ... EA70: =-1 * EA69 -> 0
A72: END

Sheet Metrics
A1: =RIGHT(CELL("filename", A1), LEN(CELL("filename", A1)) - SEARCH("]", CELL("filename", A1))) & " - " & InpC!F3 -> Metrics - Base case 1
E2: =Time!E$25 -> Model period ending | F2: =Check!$F$9 -> 0 | G2: Error chks | J2: =Time!J$25 -> 44104 | K2: =Time!K$25 -> 44196 | L2: =Time!L$25 -> 44286 | M2: =Time!M$25 -> 44377 | N2: =Time!N$25 -> 44469 | O2: =Time!O$25 -> 44561 | P2: =Time!P$25 -> 44651 | Q2: =Time!Q$25 -> 44742 | ... EA2: =Time!EA$25 -> 55153
E3: =Time!E$67 -> Timeline label | F3: =Output!J2 -> 0 | G3: Track chgs | J3: =Time!J$67 -> Pre-fcst | K3: =Time!K$67 -> Pre-fcst | L3: =Time!L$67 -> Fin Close | M3: =Time!M$67 -> Operations | N3: =Time!N$67 -> Operations | O3: =Time!O$67 -> Operations | P3: =Time!P$67 -> Operations | Q3: =Time!Q$67 -> Operations | ... EA3: =Time!EA$67 -> Post ops
E4: =Time!E$42 -> Contract year | F4: =Check!$F$21 -> 0 | G4: Alerts | J4: =Time!J$42 -> 2020 | K4: =Time!K$42 -> 2020 | L4: =Time!L$42 -> 2020 | M4: =Time!M$42 -> 2021 | N4: =Time!N$42 -> 2021 | O4: =Time!O$42 -> 2021 | P4: =Time!P$42 -> 2021 | Q4: =Time!Q$42 -> 2022 | ... EA4: =Time!EA$42 -> 2050
E5: =Time!E$10 -> Model column counter | F5: Constant | G5: Unit | H5: Total | J5: =Time!J$10 -> 1 | K5: =Time!K$10 -> 2 | L5: =Time!L$10 -> 3 | M5: =Time!M$10 -> 4 | N5: =Time!N$10 -> 5 | O5: =Time!O$10 -> 6 | P5: =Time!P$10 -> 7 | Q5: =Time!Q$10 -> 8 | ... EA5: =Time!EA$10 -> 122
A7: IRR
B9: Equity IRR
E10: =Equity!E$13 -> Share capital - initial drawdown | F10: =Equity!F$13 -> 21824.067 | G10: =Equity!G$13 -> $ 000s
E11: =InpC!E$79 -> Small negative value for XIRR | F11: =InpC!F$79 -> -1e-07 | G11: =InpC!G$79 -> $ 000s
E12: =Time!E$76 -> Financial close date flag | F12: =Time!F$76 -> 0 | G12: =Time!G$76 -> flag | H12: =Time!H$76 -> 1 | I12: =Time!I$76 -> 0 | J12: =Time!J$76 -> 0 | K12: =Time!K$76 -> 0 | L12: =Time!L$76 -> 1 | ... EA12: =Time!EA$76 -> 0
E13: =Time!E$14 -> First model column flag | F13: =Time!F$14 -> 0 | G13: =Time!G$14 -> flag | H13: =Time!H$14 -> 1 | I13: =Time!I$14 -> 0 | J13: =Time!J$14 -> 1 | K13: =Time!K$14 -> 0 | L13: =Time!L$14 -> 0 | ... EA13: =Time!EA$14 -> 0
E14: =Equity!E$69 -> Dividends paid POS | F14: =Equity!F$69 -> 0 | G14: =Equity!G$69 -> $ 000s | H14: =Equity!H$69 -> 196154.18 | I14: =Equity!I$69 -> 0 | J14: =Equity!J$69 -> 0 | K14: =Equity!K$69 -> 0 | L14: =Equity!L$69 -> 0 | ... EA14: =Equity!EA$69 -> 0
E15: =Equity!E$18 -> Share capital redemption POS | F15: =Equity!F$18 -> 0 | G15: =Equity!G$18 -> $ 000s | H15: =Equity!H$18 -> 21824.067 | I15: =Equity!I$18 -> 0 | J15: =Equity!J$18 -> 0 | K15: =Equity!K$18 -> 0 | L15: =Equity!L$18 -> 0 | ... EA15: =Equity!EA$18 -> 0
E16: Net cashflow to / (from) equity | G16: =SMU -> $ 000s | H16: =SUM(J16:EA16) -> 196154.18 | J16: =$F11 * J13 + -1 * $F10 * J12 + J14 + J15 -> -1e-07 | K16: =$F11 * K13 + -1 * $F10 * K12 + K14 + K15 -> 0 | L16: =$F11 * L13 + -1 * $F10 * L12 + L14 + L15 -> -21824.067 | M16: =$F11 * M13 + -1 * $F10 * M12 + M14 + M15 -> 350.61961 | N16: =$F11 * N13 + -1 * $F10 * N12 + N14 + N15 -> 1159.3584 | O16: =$F11 * O13 + -1 * $F10 * O12 + O14 + O15 -> 962.4299 | P16: =$F11 * P13 + -1 * $F10 * P12 + P14 + P15 -> 468.142 | Q16: =$F11 * Q13 + -1 * $F10 * Q12 + Q14 + Q15 -> 693.85801 | ... EA16: =$F11 * EA13 + -1 * $F10 * EA12 + EA14 + EA15 -> 0
E18: =E$16 -> Net cashflow to / (from) equity | F18: =F$16 -> 0 | G18: =G$16 -> $ 000s | H18: =H$16 -> 196154.18 | I18: =I$16 -> 0 | J18: =J$16 -> -1e-07 | K18: =K$16 -> 0 | L18: =L$16 -> -21824.067 | ... EA18: =EA$16 -> 0
E19: =Time!E$25 -> Model period ending | F19: =Time!F$25 -> 0 | G19: =Time!G$25 -> date | H19: =Time!H$25 -> 0 | I19: =Time!I$25 -> 0 | J19: =Time!J$25 -> 44104 | K19: =Time!K$25 -> 44196 | L19: =Time!L$25 -> 44286 | ... EA19: =Time!EA$25 -> 55153
E20: Equity IRR | F20: =XIRR(J18:EA18, J19:EA19) -> 0.21705926 | G20: %
A23: DEBT RATIOS
B25: 3m historic DSCR
E27: ='FS Qtr'!E$33 -> Cash flow available for senior debt service | F27: ='FS Qtr'!F$33 -> 0 | G27: ='FS Qtr'!G$33 -> $ 000s | H27: ='FS Qtr'!H$33 -> 322667.04 | I27: ='FS Qtr'!I$33 -> 0 | J27: ='FS Qtr'!J$33 -> 0 | K27: ='FS Qtr'!K$33 -> 0 | L27: ='FS Qtr'!L$33 -> 0 | ... EA27: ='FS Qtr'!EA$33 -> 0
E28: =Debt!E$98 -> Senior debt service | F28: =Debt!F$98 -> 0 | G28: =Debt!G$98 -> $ 000s | H28: =Debt!H$98 -> 104688.79 | I28: =Debt!I$98 -> 0 | J28: =Debt!J$98 -> 0 | K28: =Debt!K$98 -> 0 | L28: =Debt!L$98 -> 0 | ... EA28: =Debt!EA$98 -> 0
E29: =Time!E$125 -> Senior debt repayment period flag | F29: =Time!F$125 -> 0 | G29: =Time!G$125 -> flag | H29: =Time!H$125 -> 40 | I29: =Time!I$125 -> 0 | J29: =Time!J$125 -> 0 | K29: =Time!K$125 -> 0 | L29: =Time!L$125 -> 0 | ... EA29: =Time!EA$125 -> 0
E30: 3m historic DSCR | G30: ratio | J30: =IF( J29 = 1, J27 / J28, "na") -> na | K30: =IF( K29 = 1, K27 / K28, "na") -> na | L30: =IF( L29 = 1, L27 / L28, "na") -> na | M30: =IF( M29 = 1, M27 / M28, "na") -> 1.3 | N30: =IF( N29 = 1, N27 / N28, "na") -> 1.3 | O30: =IF( O29 = 1, O27 / O28, "na") -> 1.3 | P30: =IF( P29 = 1, P27 / P28, "na") -> 1.3 | Q30: =IF( Q29 = 1, Q27 / Q28, "na") -> 1.3 | ... EA30: =IF( EA29 = 1, EA27 / EA28, "na") -> na
E31: Min 3m historic DSCR | F31: =MIN(J30:EA30) -> 1.3 | G31: ratio
E32: Avg 3m historic DSCR | F32: =AVERAGE(J30:EA30) -> 1.3 | G32: ratio

Sheet FS Qtr
A1: =RIGHT(CELL("filename", A1), LEN(CELL("filename", A1)) - SEARCH("]", CELL("filename", A1))) & " - " & InpC!F3 -> FS Qtr - Base case 1
E2: =Time!E$25 -> Model period ending | F2: =Check!$F$9 -> 0 | G2: Error chks | J2: =Time!J$25 -> 44104 | K2: =Time!K$25 -> 44196 | L2: =Time!L$25 -> 44286 | M2: =Time!M$25 -> 44377 | N2: =Time!N$25 -> 44469 | O2: =Time!O$25 -> 44561 | P2: =Time!P$25 -> 44651 | Q2: =Time!Q$25 -> 44742 | ... EA2: =Time!EA$25 -> 55153
E3: =Time!E$67 -> Timeline label | F3: =Output!J2 -> 0 | G3: Track chgs | J3: =Time!J$67 -> Pre-fcst | K3: =Time!K$67 -> Pre-fcst | L3: =Time!L$67 -> Fin Close | M3: =Time!M$67 -> Operations | N3: =Time!N$67 -> Operations | O3: =Time!O$67 -> Operations | P3: =Time!P$67 -> Operations | Q3: =Time!Q$67 -> Operations | ... EA3: =Time!EA$67 -> Post ops
E4: =Time!E$42 -> Contract year | F4: =Check!$F$21 -> 0 | G4: Alerts | J4: =Time!J$42 -> 2020 | K4: =Time!K$42 -> 2020 | L4: =Time!L$42 -> 2020 | M4: =Time!M$42 -> 2021 | N4: =Time!N$42 -> 2021 | O4: =Time!O$42 -> 2021 | P4: =Time!P$42 -> 2021 | Q4: =Time!Q$42 -> 2022 | ... EA4: =Time!EA$42 -> 2050
E5: =Time!E$10 -> Model column counter | F5: Constant | G5: Unit | H5: Total | J5: =Time!J$10 -> 1 | K5: =Time!K$10 -> 2 | L5: =Time!L$10 -> 3 | M5: =Time!M$10 -> 4 | N5: =Time!N$10 -> 5 | O5: =Time!O$10 -> 6 | P5: =Time!P$10 -> 7 | Q5: =Time!Q$10 -> 8 | ... EA5: =Time!EA$10 -> 122
A7: INCOME STATEMENT
E9: =Ops!E$38 -> Electricity revenue | F9: =Ops!F$38 -> 0 | G9: =Ops!G$38 -> $ 000s | H9: =Ops!H$38 -> 371409.68 | I9: =Ops!I$38 -> 0 | J9: =Ops!J$38 -> 0 | K9: =Ops!K$38 -> 0 | L9: =Ops!L$38 -> 0 | ... EA9: =Ops!EA$38 -> 0
E10: =Ops!E$98 -> O&M cost | F10: =Ops!F$98 -> 0 | G10: =Ops!G$98 -> $ 000s | H10: =Ops!H$98 -> -48742.638 | I10: =Ops!I$98 -> 0 | J10: =Ops!J$98 -> 0 | K10: =Ops!K$98 -> 0 | L10: =Ops!L$98 -> 0 | ... EA10: =Ops!EA$98 -> 0
E11: EBITDA | G11: =SMU -> $ 000s | H11: =SUM(J11:EA11) -> 322667.04 | J11: =SUM(J9:J10) -> 0 | K11: =SUM(K9:K10) -> 0 | L11: =SUM(L9:L10) -> 0 | M11: =SUM(M9:M10) -> 4824.75 | N11: =SUM(N9:N10) -> 5295.7406 | O11: =SUM(O9:O10) -> 2062.5343 | P11: =SUM(P9:P10) -> 2060.6311 | Q11: =SUM(Q9:Q10) -> 4791.277 | ... EA11: =SUM(EA9:EA10) -> 0
E13: =Asset!E$16 -> Depreciation of fixed asset | F13: =Asset!F$16 -> 0 | G13: =Asset!G$16 -> $ 000s | H13: =Asset!H$16 -> -100000 | I13: =Asset!I$16 -> 0 | J13: =Asset!J$16 -> 0 | K13: =Asset!K$16 -> 0 | L13: =Asset!L$16 -> 0 | ... EA13: =Asset!EA$16 -> 0
E14: EBIT | G14: =SMU -> $ 000s | H14: =SUM(J14:EA14) -> 222667.04 | J14: =J11 + SUM(J13:J13) -> 0 | K14: =K11 + SUM(K13:K13) -> 0 | L14: =L11 + SUM(L13:L13) -> 0 | M14: =M11 + SUM(M13:M13) -> 3824.75 | N14: =N11 + SUM(N13:N13) -> 4295.7406 | O14: =O11 + SUM(O13:O13) -> 1062.5343 | P14: =P11 + SUM(P13:P13) -> 1060.6311 | Q14: =Q11 + SUM(Q13:Q13) -> 3791.277 | ... EA14: =EA11 + SUM(EA13:EA13) -> 0
E16: =Debt!E$82 -> Senior debt interest | F16: =Debt!F$82 -> 0 | G16: =Debt!G$82 -> $ 000s | H16: =Debt!H$82 -> -26512.862 | I16: =Debt!I$82 -> 0 | J16: =Debt!J$82 -> 0 | K16: =Debt!K$82 -> 0 | L16: =Debt!L$82 -> 0 | ... EA16: =Debt!EA$82 -> 7.0333755e-12
E17: [Refi facility interest]
E18: [RCF interest expense]
E19: Profit before tax | G19: =SMU -> $ 000s | H19: =SUM(J19:EA19) -> 196154.18 | J19: =J14 + SUM(J16:J18) -> 0 | K19: =K14 + SUM(K16:K18) -> 0 | L19: =L14 + SUM(L16:L18) -> 0 | M19: =M14 + SUM(M16:M18) -> 2639.0817 | N19: =N14 + SUM(N16:N18) -> 3096.7833 | O19: =O14 + SUM(O16:O18) -> -95.550908 | P19: =P14 + SUM(P16:P18) -> -41.528192 | Q19: =Q14 + SUM(Q16:Q18) -> 2683.8227 | ... EA19: =EA14 + SUM(EA16:EA18) -> 7.0333755e-12
E21: [Corporate income tax expense]
E22: Profit after tax | G22: =SMU -> $ 000s | H22: =SUM(J22:EA22) -> 196154.18 | J22: =J19 + J21 -> 0 | K22: =K19 + K21 -> 0 | L22: =L19 + L21 -> 0 | M22: =M19 + M21 -> 2639.0817 | N22: =N19 + N21 -> 3096.7833 | O22: =O19 + O21 -> -95.550908 | P22: =P19 + P21 -> -41.528192 | Q22: =Q19 + Q21 -> 2683.8227 | ... EA22: =EA19 + EA21 -> 7.0333755e-12
E24: =Equity!E$70 -> Dividends paid | F24: =Equity!F$70 -> 0 | G24: =Equity!G$70 -> $ 000s | H24: =Equity!H$70 -> -196154.18 | I24: =Equity!I$70 -> 0 | J24: =Equity!J$70 -> 0 | K24: =Equity!K$70 -> 0 | L24: =Equity!L$70 -> 0 | ... EA24: =Equity!EA$70 -> 0
E25: Net income after dividends | G25: =SMU -> $ 000s | H25: =SUM(J25:EA25) -> 4.8656866e-10 | J25: =J22 + J24 -> 0 | K25: =K22 + K24 -> 0 | L25: =L22 + L24 -> 0 | M25: =M22 + M24 -> 2288.4621 | N25: =N22 + N24 -> 1937.4249 | O25: =O22 + O24 -> -1057.9808 | P25: =P22 + P24 -> -509.67019 | Q25: =Q22 + Q24 -> 1989.9647 | ... EA25: =EA22 + EA24 -> 7.0333755e-12
A28: CASH FLOW STATEMENT
E30: =Ops!E$53 -> Cash received from invoices | F30: =Ops!F$53 -> 0 | G30: =Ops!G$53 -> $ 000s | H30: =Ops!H$53 -> 371409.68 | I30: =Ops!I$53 -> 0 | J30: =Ops!J$53 -> 0 | K30: =Ops!K$53 -> 0 | L30: =Ops!L$53 -> 0 | ... EA30: =Ops!EA$53 -> 0
E31: =Ops!E$114 -> Cash paid for operating costs | F31: =Ops!F$114 -> 0 | G31: =Ops!G$114 -> $ 000s | H31: =Ops!H$114 -> -48742.638 | I31: =Ops!I$114 -> 0 | J31: =Ops!J$114 -> 0 | K31: =Ops!K$114 -> 0 | L31: =Ops!L$114 -> 0 | ... EA31: =Ops!EA$114 -> 0
E32: [Corporate income tax expense]
E33: Cash flow available for senior debt service | G33: =SMU -> $ 000s | H33: =SUM(J33:EA33) -> 322667.04 | J33: =SUM(J30:J32) -> 0 | K33: =SUM(K30:K32) -> 0 | L33: =SUM(L30:L32) -> 0 | M33: =SUM(M30:M32) -> 1519.3516 | N33: =SUM(N30:N32) -> 5023.8866 | O33: =SUM(O30:O32) -> 4170.5296 | P33: =SUM(P30:P32) -> 2028.6153 | Q33: =SUM(Q30:Q32) -> 3006.718 | ... EA33: =SUM(EA30:EA32) -> 0
E35: =Debt!E$82 -> Senior debt interest | F35: =Debt!F$82 -> 0 | G35: =Debt!G$82 -> $ 000s | H35: =Debt!H$82 -> -26512.862 | I35: =Debt!I$82 -> 0 | J35: =Debt!J$82 -> 0 | K35: =Debt!K$82 -> 0 | L35: =Debt!L$82 -> 0 | ... EA35: =Debt!EA$82 -> 7.0333755e-12
E36: =Debt!E$69 -> Senior debt principal repayment | F36: =Debt!F$69 -> 0 | G36: =Debt!G$69 -> $ 000s | H36: =Debt!H$69 -> -78175.933 | I36: =Debt!I$69 -> 0 | J36: =Debt!J$69 -> 0 | K36: =Debt!K$69 -> 0 | L36: =Debt!L$69 -> 0 | ... EA36: =Debt!EA$69 -> -7.0333755e-12
E37: Cash flow available for refinancing facility | G37: =SMU -> $ 000s | H37: =SUM(J37:EA37) -> 217978.25 | J37: =J33 + SUM(J35:J36) -> 0 | K37: =K33 + SUM(K35:K36) -> 0 | L37: =L33 + SUM(L35:L36) -> 0 | M37: =M33 + SUM(M35:M36) -> 350.61961 | N37: =N33 + SUM(N35:N36) -> 1159.3584 | O37: =O33 + SUM(O35:O36) -> 962.4299 | P37: =P33 + SUM(P35:P36) -> 468.142 | Q37: =Q33 + SUM(Q35:Q36) -> 693.85801 | ... EA37: =EA33 + SUM(EA35:EA36) -> 0
E39: [Refi facility drawdown]
E40: [Refi facility repayment]
E41: [Refi facility interest]
E42: Cash flow available for revolving credit facility | G42: =SMU -> $ 000s | H42: =SUM(J42:EA42) -> 217978.25 | J42: =J37 + SUM(J39:J41) -> 0 | K42: =K37 + SUM(K39:K41) -> 0 | L42: =L37 + SUM(L39:L41) -> 0 | M42: =M37 + SUM(M39:M41) -> 350.61961 | N42: =N37 + SUM(N39:N41) -> 1159.3584 | O42: =O37 + SUM(O39:O41) -> 962.4299 | P42: =P37 + SUM(P39:P41) -> 468.142 | Q42: =Q37 + SUM(Q39:Q41) -> 693.85801 | ... EA42: =EA37 + SUM(EA39:EA41) -> 0
E44: [RCF drawdown]
E45: [RCF repayment]
E46: [RCF interest expense paid]
E47: Cash flow available for distribution | G47: =SMU -> $ 000s | H47: =SUM(J47:EA47) -> 217978.25 | J47: =J42 + SUM(J44:J46) -> 0 | K47: =K42 + SUM(K44:K46) -> 0 | L47: =L42 + SUM(L44:L46) -> 0 | M47: =M42 + SUM(M44:M46) -> 350.61961 | N47: =N42 + SUM(N44:N46) -> 1159.3584 | O47: =O42 + SUM(O44:O46) -> 962.4299 | P47: =P42 + SUM(P44:P46) -> 468.142 | Q47: =Q42 + SUM(Q44:Q46) -> 693.85801 | ... EA47: =EA42 + SUM(EA44:EA46) -> 0
E49: =Equity!E$19 -> Share capital redemption | F49: =Equity!F$19 -> 0 | G49: =Equity!G$19 -> $ 000s | H49: =Equity!H$19 -> -21824.067 | I49: =Equity!I$19 -> 0 | J49: =Equity!J$19 -> 0 | K49: =Equity!K$19 -> 0 | L49: =Equity!L$19 -> 0 | ... EA49: =Equity!EA$19 -> 0
E50: Cash flow available for dividends | G50: =SMU -> $ 000s | H50: =SUM(J50:EA50) -> 196154.18 | J50: =J47 + J49 -> 0 | K50: =K47 + K49 -> 0 | L50: =L47 + L49 -> 0 | M50: =M47 + M49 -> 350.61961 | N50: =N47 + N49 -> 1159.3584 | O50: =O47 + O49 -> 962.4299 | P50: =P47 + P49 -> 468.142 | Q50: =Q47 + Q49 -> 693.85801 | ... EA50: =EA47 + EA49 -> 0
E52: =Equity!E$70 -> Dividends paid | F52: =Equity!F$70 -> 0 | G52: =Equity!G$70 -> $ 000s | H52: =Equity!H$70 -> -196154.18 | I52: =Equity!I$70 -> 0 | J52: =Equity!J$70 -> 0 | K52: =Equity!K$70 -> 0 | L52: =Equity!L$70 -> 0 | ... EA52: =Equity!EA$70 -> 0
E53: Net cash flow after dividends | G53: =SMU -> $ 000s | H53: =SUM(J53:EA53) -> 0 | J53: =J50 + J52 -> 0 | K53: =K50 + K52 -> 0 | L53: =L50 + L52 -> 0 | M53: =M50 + M52 -> 0 | N53: =N50 + N52 -> 0 | O53: =O50 + O52 -> 0 | P53: =P50 + P52 -> 0 | Q53: =Q50 + Q52 -> 0 | ... EA53: =EA50 + EA52 -> 0
A56: BALANCE SHEET
B58: Non current assets
E59: =Asset!E$26 -> Fixed asset balance | F59: =Asset!F$26 -> 0 | G59: =Asset!G$26 -> $ 000s | H59: =Asset!H$26 -> 0 | I59: =Asset!I$26 -> 0 | J59: =Asset!J$26 -> 0 | K59: =Asset!K$26 -> 0 | L59: =Asset!L$26 -> 100000 | ... EA59: =Asset!EA$26 -> 0
E60: Non current assets | G60: =SMU -> $ 000s | J60: =SUM(J59) -> 0 | K60: =SUM(K59) -> 0 | L60: =SUM(L59) -> 100000 | M60: =SUM(M59) -> 99000 | N60: =SUM(N59) -> 98000 | O60: =SUM(O59) -> 97000 | P60: =SUM(P59) -> 96000 | Q60: =SUM(Q59) -> 95000 | ... EA60: =SUM(EA59) -> 0
B62: Current assets
E63: =Equity!E$52 -> Retained cash balance | F63: =Equity!F$52 -> 0 | G63: =Equity!G$52 -> $ 000s | H63: =Equity!H$52 -> 0 | I63: =Equity!I$52 -> 0 | J63: =Equity!J$52 -> 0 | K63: =Equity!K$52 -> 0 | L63: =Equity!L$52 -> 0 | ... EA63: =Equity!EA$52 -> 0
E64: =Ops!E$63 -> Accounts receivable balance | F64: =Ops!F$63 -> 0 | G64: =Ops!G$63 -> $ 000s | H64: =Ops!H$63 -> 0 | I64: =Ops!I$63 -> 0 | J64: =Ops!J$63 -> 0 | K64: =Ops!K$63 -> 0 | L64: =Ops!L$63 -> 0 | ... EA64: =Ops!EA$63 -> 0
E65: Current assets | G65: =SMU -> $ 000s | J65: =SUM(J63:J64) -> 0 | K65: =SUM(K63:K64) -> 0 | L65: =SUM(L63:L64) -> 0 | M65: =SUM(M63:M64) -> 3429.6429 | N65: =SUM(N63:N64) -> 3700.7609 | O65: =SUM(O63:O64) -> 1593.3832 | P65: =SUM(P63:P64) -> 1628.7917 | Q65: =SUM(Q63:Q64) -> 3412.58 | ... EA65: =SUM(EA63:EA64) -> 0
E67: Total assets | G67: =SMU -> $ 000s | J67: =J65 + J60 -> 0 | K67: =K65 + K60 -> 0 | L67: =L65 + L60 -> 100000 | M67: =M65 + M60 -> 102429.64 | N67: =N65 + N60 -> 101700.76 | O67: =O65 + O60 -> 98593.383 | P67: =P65 + P60 -> 97628.792 | Q67: =Q65 + Q60 -> 98412.58 | ... EA67: =EA65 + EA60 -> 0
E69: =Ops!E$124 -> Accounts payable balance | F69: =Ops!F$124 -> 0 | G69: =Ops!G$124 -> $ 000s | H69: =Ops!H$124 -> 0 | I69: =Ops!I$124 -> 0 | J69: =Ops!J$124 -> 0 | K69: =Ops!K$124 -> 0 | L69: =Ops!L$124 -> 0 | ... EA69: =Ops!EA$124 -> 0
E70: =Debt!E$92 -> Senior debt balance | F70: =Debt!F$92 -> 0 | G70: =Debt!G$92 -> $ 000s | H70: =Debt!H$92 -> 0 | I70: =Debt!I$92 -> 0 | J70: =Debt!J$92 -> 0 | K70: =Debt!K$92 -> 0 | L70: =Debt!L$92 -> 78175.933 | ... EA70: =Debt!EA$92 -> -4.6573178e-10
E71: [Refi facility balance]
E72: [RCF balance]
E73: =Equity!E$29 -> Share capital balance | F73: =Equity!F$29 -> 0 | G73: =Equity!G$29 -> $ 000s | H73: =Equity!H$29 -> 0 | I73: =Equity!I$29 -> 0 | J73: =Equity!J$29 -> 0 | K73: =Equity!K$29 -> 0 | L73: =Equity!L$29 -> 21824.067 | ... EA73: =Equity!EA$29 -> 0
E74: =Equity!E$41 -> Retained earnings balance | F74: =Equity!F$41 -> 0 | G74: =Equity!G$41 -> $ 000s | H74: =Equity!H$41 -> 0 | I74: =Equity!I$41 -> 0 | J74: =Equity!J$41 -> 0 | K74: =Equity!K$41 -> 0 | L74: =Equity!L$41 -> 0 | ... EA74: =Equity!EA$41 -> 4.620123e-10
E75: Total liabilities | G75: =SMU -> $ 000s | J75: =SUM(J69:J74) -> 0 | K75: =SUM(K69:K74) -> 0 | L75: =SUM(L69:L74) -> 100000 | M75: =SUM(M69:M74) -> 102429.64 | N75: =SUM(N69:N74) -> 101700.76 | O75: =SUM(O69:O74) -> 98593.383 | P75: =SUM(P69:P74) -> 97628.792 | Q75: =SUM(Q69:Q74) -> 98412.58 | ... EA75: =SUM(EA69:EA74) -> -3.7194797e-12
A78: BALANCE SHEET CHECK
E80: =E$67 -> Total assets | F80: =F$67 -> 0 | G80: =G$67 -> $ 000s | H80: =H$67 -> 0 | I80: =I$67 -> 0 | J80: =J$67 -> 0 | K80: =K$67 -> 0 | L80: =L$67 -> 100000 | ... EA80: =EA$67 -> 0
E81: =E$75 -> Total liabilities | F81: =F$75 -> 0 | G81: =G$75 -> $ 000s | H81: =H$75 -> 0 | I81: =I$75 -> 0 | J81: =J$75 -> 0 | K81: =K$75 -> 0 | L81: =L$75 -> 100000 | ... EA81: =EA$75 -> -3.7194797e-12
E82: Balance sheet check | F82: =IF(SUM(J82:EA82) <> 0, 1, 0) -> 0 | G82: check | J82: =IF(ABS(J80 - J81) > CHK_TOL, 1, 0) -> 0 | K82: =IF(ABS(K80 - K81) > CHK_TOL, 1, 0) -> 0 | L82: =IF(ABS(L80 - L81) > CHK_TOL, 1, 0) -> 0 | M82: =IF(ABS(M80 - M81) > CHK_TOL, 1, 0) -> 0 | N82: =IF(ABS(N80 - N81) > CHK_TOL, 1, 0) -> 0 | O82: =IF(ABS(O80 - O81) > CHK_TOL, 1, 0) -> 0 | P82: =IF(ABS(P80 - P81) > CHK_TOL, 1, 0) -> 0 | Q82: =IF(ABS(Q80 - Q81) > CHK_TOL, 1, 0) -> 0 | ... EA82: =IF(ABS(EA80 - EA81) > CHK_TOL, 1, 0) -> 0
E83: Balance sheet difference | H83: =SUM(J83:EA83) -> 7.4535466e-11 | J83: =J80 - J81 -> 0 | K83: =K80 - K81 -> 0 | L83: =L80 - L81 -> 0 | M83: =M80 - M81 -> 0 | N83: =N80 - N81 -> 0 | O83: =O80 - O81 -> 0 | P83: =P80 - P81 -> 0 | Q83: =Q80 - Q81 -> 0 | ... EA83: =EA80 - EA81 -> 3.7194797e-12
A87: END

Sheet FS Ann
A1: =RIGHT(CELL("filename", A1), LEN(CELL("filename", A1)) - SEARCH("]", CELL("filename", A1))) & " - " & InpC!F3 -> FS Ann - Base case 1
E2: =Time!E$48 -> Model period ending - annual | F2: =Check!$F$9 -> 0 | G2: Error chks | J2: =Time!J$48 -> 43921 | K2: =Time!K$48 -> 44286 | L2: =Time!L$48 -> 44651 | M2: =Time!M$48 -> 45016 | N2: =Time!N$48 -> 45382 | O2: =Time!O$48 -> 45747 | P2: =Time!P$48 -> 46112 | Q2: =Time!Q$48 -> 46477 | ... AN2: =Time!AN$48 -> 54878
E3: =Time!E$53 -> Timeline label - annual | F3: =Output!J2 -> 0 | G3: Track chgs | J3: =Time!J$53 -> Pre-fcst | K3: =Time!K$53 -> Operations | L3: =Time!L$53 -> Operations | M3: =Time!M$53 -> Operations | N3: =Time!N$53 -> Operations | O3: =Time!O$53 -> Operations | P3: =Time!P$53 -> Operations | Q3: =Time!Q$53 -> Operations | ... AN3: =Time!AN$53 -> Post ops
E4: =Time!E$42 -> Contract year | F4: =Check!$F$21 -> 0 | G4: Alerts | J4: =YEAR(J2) -> 2020 | K4: =YEAR(K2) -> 2021 | L4: =YEAR(L2) -> 2022 | M4: =YEAR(M2) -> 2023 | N4: =YEAR(N2) -> 2024 | O4: =YEAR(O2) -> 2025 | P4: =YEAR(P2) -> 2026 | Q4: =YEAR(Q2) -> 2027 | ... AN4: =YEAR(AN2) -> 2050
E5: =Time!E$10 -> Model column counter | F5: Constant | G5: Unit | H5: Total | J5: =Time!J$10 -> 1 | K5: =Time!K$10 -> 2 | L5: =Time!L$10 -> 3 | M5: =Time!M$10 -> 4 | N5: =Time!N$10 -> 5 | O5: =Time!O$10 -> 6 | P5: =Time!P$10 -> 7 | Q5: =Time!Q$10 -> 8 | ... AN5: =Time!AN$10 -> 31
A7: INCOME STATEMENT
E9: ='FS Qtr'!E9 -> Electricity revenue | F9: ='FS Qtr'!F9 -> 0 | G9: ='FS Qtr'!G9 -> $ 000s | H9: =SUM(J9:AN9) -> 371409.68 | J9: =SUMIFS('FS Qtr'!$J9:$EA9, 'FS Qtr'!$J$4:$EA$4, 'FS Ann'!J$4) -> 0 | K9: =SUMIFS('FS Qtr'!$J9:$EA9, 'FS Qtr'!$J$4:$EA$4, 'FS Ann'!K$4) -> 15762.5 | L9: =SUMIFS('FS Qtr'!$J9:$EA9, 'FS Qtr'!$J$4:$EA$4, 'FS Ann'!L$4) -> 15684.08 | M9: =SUMIFS('FS Qtr'!$J9:$EA9, 'FS Qtr'!$J$4:$EA$4, 'FS Ann'!M$4) -> 15606.049 | N9: =SUMIFS('FS Qtr'!$J9:$EA9, 'FS Qtr'!$J$4:$EA$4, 'FS Ann'!N$4) -> 15528.407 | O9: =SUMIFS('FS Qtr'!$J9:$EA9, 'FS Qtr'!$J$4:$EA$4, 'FS Ann'!O$4) -> 15451.152 | P9: =SUMIFS('FS Qtr'!$J9:$EA9, 'FS Qtr'!$J$4:$EA$4, 'FS Ann'!P$4) -> 15374.28 | Q9: =SUMIFS('FS Qtr'!$J9:$EA9, 'FS Qtr'!$J$4:$EA$4, 'FS Ann'!Q$4) -> 15297.791 | ... AN9: =SUMIFS('FS Qtr'!$J9:$EA9, 'FS Qtr'!$J$4:$EA$4, 'FS Ann'!AN$4) -> 0
E10: ='FS Qtr'!E10 -> O&M cost | F10: ='FS Qtr'!F10 -> 0 | G10: ='FS Qtr'!G10 -> $ 000s | H10: =SUM(J10:AN10) -> -48742.638 | J10: =SUMIFS('FS Qtr'!$J10:$EA10, 'FS Qtr'!$J$4:$EA$4, 'FS Ann'!J$4) -> 0 | K10: =SUMIFS('FS Qtr'!$J10:$EA10, 'FS Qtr'!$J$4:$EA$4, 'FS Ann'!K$4) -> -1518.844 | L10: =SUMIFS('FS Qtr'!$J10:$EA10, 'FS Qtr'!$J$4:$EA$4, 'FS Ann'!L$4) -> -1549.4495 | M10: =SUMIFS('FS Qtr'!$J10:$EA10, 'FS Qtr'!$J$4:$EA$4, 'FS Ann'!M$4) -> -1580.6716 | N10: =SUMIFS('FS Qtr'!$J10:$EA10, 'FS Qtr'!$J$4:$EA$4, 'FS Ann'!N$4) -> -1612.523 | O10: =SUMIFS('FS Qtr'!$J10:$EA10, 'FS Qtr'!$J$4:$EA$4, 'FS Ann'!O$4) -> -1645.0161 | P10: =SUMIFS('FS Qtr'!$J10:$EA10, 'FS Qtr'!$J$4:$EA$4, 'FS Ann'!P$4) -> -1678.164 | Q10: =SUMIFS('FS Qtr'!$J10:$EA10, 'FS Qtr'!$J$4:$EA$4, 'FS Ann'!Q$4) -> -1711.9798 | ... AN10: =SUMIFS('FS Qtr'!$J10:$EA10, 'FS Qtr'!$J$4:$EA$4, 'FS Ann'!AN$4) -> 0
E11: EBITDA | G11: =SMU -> $ 000s | H11: =SUM(J11:AN11) -> 322667.04 | J11: =SUM(J9:J10) -> 0 | K11: =SUM(K9:K10) -> 14243.656 | L11: =SUM(L9:L10) -> 14134.63 | M11: =SUM(M9:M10) -> 14025.378 | N11: =SUM(N9:N10) -> 13915.884 | O11: =SUM(O9:O10) -> 13806.135 | P11: =SUM(P9:P10) -> 13696.116 | Q11: =SUM(Q9:Q10) -> 13585.811 | ... AN11: =SUM(AN9:AN10) -> 0
E13: ='FS Qtr'!E13 -> Depreciation of fixed asset | F13: ='FS Qtr'!F13 -> 0 | G13: ='FS Qtr'!G13 -> $ 000s | H13: =SUM(J13:AN13) -> -100000 | J13: =SUMIFS('FS Qtr'!$J13:$EA13, 'FS Qtr'!$J$4:$EA$4, 'FS Ann'!J$4) -> 0 | K13: =SUMIFS('FS Qtr'!$J13:$EA13, 'FS Qtr'!$J$4:$EA$4, 'FS Ann'!K$4) -> -4000 | L13: =SUMIFS('FS Qtr'!$J13:$EA13, 'FS Qtr'!$J$4:$EA$4, 'FS Ann'!L$4) -> -4000 | M13: =SUMIFS('FS Qtr'!$J13:$EA13, 'FS Qtr'!$J$4:$EA$4, 'FS Ann'!M$4) -> -4000 | N13: =SUMIFS('FS Qtr'!$J13:$EA13, 'FS Qtr'!$J$4:$EA$4, 'FS Ann'!N$4) -> -4000 | O13: =SUMIFS('FS Qtr'!$J13:$EA13, 'FS Qtr'!$J$4:$EA$4, 'FS Ann'!O$4) -> -4000 | P13: =SUMIFS('FS Qtr'!$J13:$EA13, 'FS Qtr'!$J$4:$EA$4, 'FS Ann'!P$4) -> -4000 | Q13: =SUMIFS('FS Qtr'!$J13:$EA13, 'FS Qtr'!$J$4:$EA$4, 'FS Ann'!Q$4) -> -4000 | ... AN13: =SUMIFS('FS Qtr'!$J13:$EA13, 'FS Qtr'!$J$4:$EA$4, 'FS Ann'!AN$4) -> 0
E14: EBIT | G14: =SMU -> $ 000s | H14: =SUM(J14:AN14) -> 222667.04 | J14: =J11 + J13 -> 0 | K14: =K11 + K13 -> 10243.656 | L14: =L11 + L13 -> 10134.63 | M14: =M11 + M13 -> 10025.378 | N14: =N11 + N13 -> 9915.8844 | O14: =O11 + O13 -> 9806.1355 | P14: =P11 + P13 -> 9696.1162 | Q14: =Q11 + Q13 -> 9585.8114 | ... AN14: =AN11 + AN13 -> 0
E16: ='FS Qtr'!E16 -> Senior debt interest | F16: ='FS Qtr'!F16 -> 0 | G16: ='FS Qtr'!G16 -> $ 000s | H16: =SUM(J16:AN16) -> -26512.862 | J16: =SUMIFS('FS Qtr'!$J16:$EA16, 'FS Qtr'!$J$4:$EA$4, 'FS Ann'!J$4) -> 0 | K16: =SUMIFS('FS Qtr'!$J16:$EA16, 'FS Qtr'!$J$4:$EA$4, 'FS Ann'!K$4) -> -4644.8701 | L16: =SUMIFS('FS Qtr'!$J16:$EA16, 'FS Qtr'!$J$4:$EA$4, 'FS Ann'!L$4) -> -4272.0391 | M16: =SUMIFS('FS Qtr'!$J16:$EA16, 'FS Qtr'!$J$4:$EA$4, 'FS Ann'!M$4) -> -3872.7876 | N16: =SUMIFS('FS Qtr'!$J16:$EA16, 'FS Qtr'!$J$4:$EA$4, 'FS Ann'!N$4) -> -3433.6887 | O16: =SUMIFS('FS Qtr'!$J16:$EA16, 'FS Qtr'!$J$4:$EA$4, 'FS Ann'!O$4) -> -2982.9219 | P16: =SUMIFS('FS Qtr'!$J16:$EA16, 'FS Qtr'!$J$4:$EA$4, 'FS Ann'!P$4) -> -2509.1606 | Q16: =SUMIFS('FS Qtr'!$J16:$EA16, 'FS Qtr'!$J$4:$EA$4, 'FS Ann'!Q$4) -> -2016.0373 | ... AN16: =SUMIFS('FS Qtr'!$J16:$EA16, 'FS Qtr'!$J$4:$EA$4, 'FS Ann'!AN$4) -> 2.0710031e-11
E17: ='FS Qtr'!E17 -> [Refi facility interest] | F17: ='FS Qtr'!F17 -> 0 | G17: ='FS Qtr'!G17 -> 0 | H17: =SUM(J17:AN17) -> 0 | J17: =SUMIFS('FS Qtr'!$J17:$EA17, 'FS Qtr'!$J$4:$EA$4, 'FS Ann'!J$4) -> 0 | K17: =SUMIFS('FS Qtr'!$J17:$EA17, 'FS Qtr'!$J$4:$EA$4, 'FS Ann'!K$4) -> 0 | L17: =SUMIFS('FS Qtr'!$J17:$EA17, 'FS Qtr'!$J$4:$EA$4, 'FS Ann'!L$4) -> 0 | M17: =SUMIFS('FS Qtr'!$J17:$EA17, 'FS Qtr'!$J$4:$EA$4, 'FS Ann'!M$4) -> 0 | N17: =SUMIFS('FS Qtr'!$J17:$EA17, 'FS Qtr'!$J$4:$EA$4, 'FS Ann'!N$4) -> 0 | O17: =SUMIFS('FS Qtr'!$J17:$EA17, 'FS Qtr'!$J$4:$EA$4, 'FS Ann'!O$4) -> 0 | P17: =SUMIFS('FS Qtr'!$J17:$EA17, 'FS Qtr'!$J$4:$EA$4, 'FS Ann'!P$4) -> 0 | Q17: =SUMIFS('FS Qtr'!$J17:$EA17, 'FS Qtr'!$J$4:$EA$4, 'FS Ann'!Q$4) -> 0 | ... AN17: =SUMIFS('FS Qtr'!$J17:$EA17, 'FS Qtr'!$J$4:$EA$4, 'FS Ann'!AN$4) -> 0
E18: ='FS Qtr'!E18 -> [RCF interest expense] | F18: ='FS Qtr'!F18 -> 0 | G18: ='FS Qtr'!G18 -> 0 | H18: =SUM(J18:AN18) -> 0 | J18: =SUMIFS('FS Qtr'!$J18:$EA18, 'FS Qtr'!$J$4:$EA$4, 'FS Ann'!J$4) -> 0 | K18: =SUMIFS('FS Qtr'!$J18:$EA18, 'FS Qtr'!$J$4:$EA$4, 'FS Ann'!K$4) -> 0 | L18: =SUMIFS('FS Qtr'!$J18:$EA18, 'FS Qtr'!$J$4:$EA$4, 'FS Ann'!L$4) -> 0 | M18: =SUMIFS('FS Qtr'!$J18:$EA18, 'FS Qtr'!$J$4:$EA$4, 'FS Ann'!M$4) -> 0 | N18: =SUMIFS('FS Qtr'!$J18:$EA18, 'FS Qtr'!$J$4:$EA$4, 'FS Ann'!N$4) -> 0 | O18: =SUMIFS('FS Qtr'!$J18:$EA18, 'FS Qtr'!$J$4:$EA$4, 'FS Ann'!O$4) -> 0 | P18: =SUMIFS('FS Qtr'!$J18:$EA18, 'FS Qtr'!$J$4:$EA$4, 'FS Ann'!P$4) -> 0 | Q18: =SUMIFS('FS Qtr'!$J18:$EA18, 'FS Qtr'!$J$4:$EA$4, 'FS Ann'!Q$4) -> 0 | ... AN18: =SUMIFS('FS Qtr'!$J18:$EA18, 'FS Qtr'!$J$4:$EA$4, 'FS Ann'!AN$4) -> 0
E19: EBT | G19: =SMU -> $ 000s | H19: =SUM(J19:AN19) -> 196154.18 | J19: =J14 + SUM(J16:J18) -> 0 | K19: =K14 + SUM(K16:K18) -> 5598.7859 | L19: =L14 + SUM(L16:L18) -> 5862.591 | M19: =M14 + SUM(M16:M18) -> 6152.5901 | N19: =N14 + SUM(N16:N18) -> 6482.1957 | O19: =O14 + SUM(O16:O18) -> 6823.2136 | P19: =P14 + SUM(P16:P18) -> 7186.9556 | Q19: =Q14 + SUM(Q16:Q18) -> 7569.7741 | ... AN19: =AN14 + SUM(AN16:AN18) -> 2.0710031e-11
E21: ='FS Qtr'!E21 -> [Corporate income tax expense] | F21: ='FS Qtr'!F21 -> 0 | G21: ='FS Qtr'!G21 -> 0 | H21: =SUM(J21:AN21) -> 0 | J21: =SUMIFS('FS Qtr'!$J21:$EA21, 'FS Qtr'!$J$4:$EA$4, 'FS Ann'!J$4) -> 0 | K21: =SUMIFS('FS Qtr'!$J21:$EA21, 'FS Qtr'!$J$4:$EA$4, 'FS Ann'!K$4) -> 0 | L21: =SUMIFS('FS Qtr'!$J21:$EA21, 'FS Qtr'!$J$4:$EA$4, 'FS Ann'!L$4) -> 0 | M21: =SUMIFS('FS Qtr'!$J21:$EA21, 'FS Qtr'!$J$4:$EA$4, 'FS Ann'!M$4) -> 0 | N21: =SUMIFS('FS Qtr'!$J21:$EA21, 'FS Qtr'!$J$4:$EA$4, 'FS Ann'!N$4) -> 0 | O21: =SUMIFS('FS Qtr'!$J21:$EA21, 'FS Qtr'!$J$4:$EA$4, 'FS Ann'!O$4) -> 0 | P21: =SUMIFS('FS Qtr'!$J21:$EA21, 'FS Qtr'!$J$4:$EA$4, 'FS Ann'!P$4) -> 0 | Q21: =SUMIFS('FS Qtr'!$J21:$EA21, 'FS Qtr'!$J$4:$EA$4, 'FS Ann'!Q$4) -> 0 | ... AN21: =SUMIFS('FS Qtr'!$J21:$EA21, 'FS Qtr'!$J$4:$EA$4, 'FS Ann'!AN$4) -> 0
E22: EBT | G22: =SMU -> $ 000s | H22: =SUM(J22:AN22) -> 196154.18 | J22: =J19 + J21 -> 0 | K22: =K19 + K21 -> 5598.7859 | L22: =L19 + L21 -> 5862.591 | M22: =M19 + M21 -> 6152.5901 | N22: =N19 + N21 -> 6482.1957 | O22: =O19 + O21 -> 6823.2136 | P22: =P19 + P21 -> 7186.9556 | Q22: =Q19 + Q21 -> 7569.7741 | ... AN22: =AN19 + AN21 -> 2.0710031e-11
E24: ='FS Qtr'!E24 -> Dividends paid | F24: ='FS Qtr'!F24 -> 0 | G24: ='FS Qtr'!G24 -> $ 000s | H24: =SUM(J24:AN24) -> -196154.18 | J24: =SUMIFS('FS Qtr'!$J24:$EA24, 'FS Qtr'!$J$4:$EA$4, 'FS Ann'!J$4) -> 0 | K24: =SUMIFS('FS Qtr'!$J24:$EA24, 'FS Qtr'!$J$4:$EA$4, 'FS Ann'!K$4) -> -2940.55 | L24: =SUMIFS('FS Qtr'!$J24:$EA24, 'FS Qtr'!$J$4:$EA$4, 'FS Ann'!L$4) -> -3264.3007 | M24: =SUMIFS('FS Qtr'!$J24:$EA24, 'FS Qtr'!$J$4:$EA$4, 'FS Ann'!M$4) -> -3242.8442 | N24: =SUMIFS('FS Qtr'!$J24:$EA24, 'FS Qtr'!$J$4:$EA$4, 'FS Ann'!N$4) -> -3210.0736 | O24: =SUMIFS('FS Qtr'!$J24:$EA24, 'FS Qtr'!$J$4:$EA$4, 'FS Ann'!O$4) -> -3188.5031 | P24: =SUMIFS('FS Qtr'!$J24:$EA24, 'FS Qtr'!$J$4:$EA$4, 'FS Ann'!P$4) -> -3163.1175 | Q24: =SUMIFS('FS Qtr'!$J24:$EA24, 'FS Qtr'!$J$4:$EA$4, 'FS Ann'!Q$4) -> -3141.3106 | ... AN24: =SUMIFS('FS Qtr'!$J24:$EA24, 'FS Qtr'!$J$4:$EA$4, 'FS Ann'!AN$4) -> 0
E25: Net income | G25: =SMU -> $ 000s | H25: =SUM(J25:AN25) -> 4.6682205e-10 | J25: =J22 + J24 -> 0 | K25: =K22 + K24 -> 2658.2359 | L25: =L22 + L24 -> 2598.2903 | M25: =M22 + M24 -> 2909.7459 | N25: =N22 + N24 -> 3272.1221 | O25: =O22 + O24 -> 3634.7105 | P25: =P22 + P24 -> 4023.838 | Q25: =Q22 + Q24 -> 4428.4635 | ... AN25: =AN22 + AN24 -> 2.0710031e-11
A28: CASH FLOW STATEMENT
E30: ='FS Qtr'!E30 -> Cash received from invoices | F30: ='FS Qtr'!F30 -> 0 | G30: ='FS Qtr'!G30 -> $ 000s | H30: =SUM(J30:AN30) -> 371409.68 | J30: =SUMIFS('FS Qtr'!$J30:$EA30, 'FS Qtr'!$J$4:$EA$4, 'FS Ann'!J$4) -> 0 | K30: =SUMIFS('FS Qtr'!$J30:$EA30, 'FS Qtr'!$J$4:$EA$4, 'FS Ann'!K$4) -> 14133.708 | L30: =SUMIFS('FS Qtr'!$J30:$EA30, 'FS Qtr'!$J$4:$EA$4, 'FS Ann'!L$4) -> 15692.183 | M30: =SUMIFS('FS Qtr'!$J30:$EA30, 'FS Qtr'!$J$4:$EA$4, 'FS Ann'!M$4) -> 15631.834 | N30: =SUMIFS('FS Qtr'!$J30:$EA30, 'FS Qtr'!$J$4:$EA$4, 'FS Ann'!N$4) -> 15518.709 | O30: =SUMIFS('FS Qtr'!$J30:$EA30, 'FS Qtr'!$J$4:$EA$4, 'FS Ann'!O$4) -> 15459.135 | P30: =SUMIFS('FS Qtr'!$J30:$EA30, 'FS Qtr'!$J$4:$EA$4, 'FS Ann'!P$4) -> 15382.224 | Q30: =SUMIFS('FS Qtr'!$J30:$EA30, 'FS Qtr'!$J$4:$EA$4, 'FS Ann'!Q$4) -> 15323.066 | ... AN30: =SUMIFS('FS Qtr'!$J30:$EA30, 'FS Qtr'!$J$4:$EA$4, 'FS Ann'!AN$4) -> 0
E31: ='FS Qtr'!E31 -> Cash paid for operating costs | F31: ='FS Qtr'!F31 -> 0 | G31: ='FS Qtr'!G31 -> $ 000s | H31: =SUM(J31:AN31) -> -48742.638 | J31: =SUMIFS('FS Qtr'!$J31:$EA31, 'FS Qtr'!$J$4:$EA$4, 'FS Ann'!J$4) -> 0 | K31: =SUMIFS('FS Qtr'!$J31:$EA31, 'FS Qtr'!$J$4:$EA$4, 'FS Ann'!K$4) -> -1391.3252 | L31: =SUMIFS('FS Qtr'!$J31:$EA31, 'FS Qtr'!$J$4:$EA$4, 'FS Ann'!L$4) -> -1546.8799 | M31: =SUMIFS('FS Qtr'!$J31:$EA31, 'FS Qtr'!$J$4:$EA$4, 'FS Ann'!M$4) -> -1579.5086 | N31: =SUMIFS('FS Qtr'!$J31:$EA31, 'FS Qtr'!$J$4:$EA$4, 'FS Ann'!N$4) -> -1608.3904 | O31: =SUMIFS('FS Qtr'!$J31:$EA31, 'FS Qtr'!$J$4:$EA$4, 'FS Ann'!O$4) -> -1642.288 | P31: =SUMIFS('FS Qtr'!$J31:$EA31, 'FS Qtr'!$J$4:$EA$4, 'FS Ann'!P$4) -> -1675.381 | Q31: =SUMIFS('FS Qtr'!$J31:$EA31, 'FS Qtr'!$J$4:$EA$4, 'FS Ann'!Q$4) -> -1710.7202 | ... AN31: =SUMIFS('FS Qtr'!$J31:$EA31, 'FS Qtr'!$J$4:$EA$4, 'FS Ann'!AN$4) -> 0
E32: ='FS Qtr'!E32 -> [Corporate income tax expense] | F32: ='FS Qtr'!F32 -> 0 | G32: ='FS Qtr'!G32 -> 0 | H32: =SUM(J32:AN32) -> 0 | J32: =SUMIFS('FS Qtr'!$J32:$EA32, 'FS Qtr'!$J$4:$EA$4, 'FS Ann'!J$4) -> 0 | K32: =SUMIFS('FS Qtr'!$J32:$EA32, 'FS Qtr'!$J$4:$EA$4, 'FS Ann'!K$4) -> 0 | L32: =SUMIFS('FS Qtr'!$J32:$EA32, 'FS Qtr'!$J$4:$EA$4, 'FS Ann'!L$4) -> 0 | M32: =SUMIFS('FS Qtr'!$J32:$EA32, 'FS Qtr'!$J$4:$EA$4, 'FS Ann'!M$4) -> 0 | N32: =SUMIFS('FS Qtr'!$J32:$EA32, 'FS Qtr'!$J$4:$EA$4, 'FS Ann'!N$4) -> 0 | O32: =SUMIFS('FS Qtr'!$J32:$EA32, 'FS Qtr'!$J$4:$EA$4, 'FS Ann'!O$4) -> 0 | P32: =SUMIFS('FS Qtr'!$J32:$EA32, 'FS Qtr'!$J$4:$EA$4, 'FS Ann'!P$4) -> 0 | Q32: =SUMIFS('FS Qtr'!$J32:$EA32, 'FS Qtr'!$J$4:$EA$4, 'FS Ann'!Q$4) -> 0 | ... AN32: =SUMIFS('FS Qtr'!$J32:$EA32, 'FS Qtr'!$J$4:$EA$4, 'FS Ann'!AN$4) -> 0
E33: Cash flow available for debt service | G33: =SMU -> $ 000s | H33: =SUM(J33:AN33) -> 322667.04 | J33: =SUM(J30:J32) -> 0 | K33: =SUM(K30:K32) -> 12742.383 | L33: =SUM(L30:L32) -> 14145.303 | M33: =SUM(M30:M32) -> 14052.325 | N33: =SUM(N30:N32) -> 13910.319 | O33: =SUM(O30:O32) -> 13816.847 | P33: =SUM(P30:P32) -> 13706.843 | Q33: =SUM(Q30:Q32) -> 13612.346 | ... AN33: =SUM(AN30:AN32) -> 0
E35: ='FS Qtr'!E35 -> Senior debt interest | F35: ='FS Qtr'!F35 -> 0 | G35: ='FS Qtr'!G35 -> $ 000s | H35: =SUM(J35:AN35) -> -26512.862 | J35: =SUMIFS('FS Qtr'!$J35:$EA35, 'FS Qtr'!$J$4:$EA$4, 'FS Ann'!J$4) -> 0 | K35: =SUMIFS('FS Qtr'!$J35:$EA35, 'FS Qtr'!$J$4:$EA$4, 'FS Ann'!K$4) -> -4644.8701 | L35: =SUMIFS('FS Qtr'!$J35:$EA35, 'FS Qtr'!$J$4:$EA$4, 'FS Ann'!L$4) -> -4272.0391 | M35: =SUMIFS('FS Qtr'!$J35:$EA35, 'FS Qtr'!$J$4:$EA$4, 'FS Ann'!M$4) -> -3872.7876 | N35: =SUMIFS('FS Qtr'!$J35:$EA35, 'FS Qtr'!$J$4:$EA$4, 'FS Ann'!N$4) -> -3433.6887 | O35: =SUMIFS('FS Qtr'!$J35:$EA35, 'FS Qtr'!$J$4:$EA$4, 'FS Ann'!O$4) -> -2982.9219 | P35: =SUMIFS('FS Qtr'!$J35:$EA35, 'FS Qtr'!$J$4:$EA$4, 'FS Ann'!P$4) -> -2509.1606 | Q35: =SUMIFS('FS Qtr'!$J35:$EA35, 'FS Qtr'!$J$4:$EA$4, 'FS Ann'!Q$4) -> -2016.0373 | ... AN35: =SUMIFS('FS Qtr'!$J35:$EA35, 'FS Qtr'!$J$4:$EA$4, 'FS Ann'!AN$4) -> 2.0710031e-11
E36: ='FS Qtr'!E36 -> Senior debt principal repayment | F36: ='FS Qtr'!F36 -> 0 | G36: ='FS Qtr'!G36 -> $ 000s | H36: =SUM(J36:AN36) -> -78175.933 | J36: =SUMIFS('FS Qtr'!$J36:$EA36, 'FS Qtr'!$J$4:$EA$4, 'FS Ann'!J$4) -> 0 | K36: =SUMIFS('FS Qtr'!$J36:$EA36, 'FS Qtr'!$J$4:$EA$4, 'FS Ann'!K$4) -> -5156.9631 | L36: =SUMIFS('FS Qtr'!$J36:$EA36, 'FS Qtr'!$J$4:$EA$4, 'FS Ann'!L$4) -> -6608.9633 | M36: =SUMIFS('FS Qtr'!$J36:$EA36, 'FS Qtr'!$J$4:$EA$4, 'FS Ann'!M$4) -> -6936.6931 | N36: =SUMIFS('FS Qtr'!$J36:$EA36, 'FS Qtr'!$J$4:$EA$4, 'FS Ann'!N$4) -> -7266.5565 | O36: =SUMIFS('FS Qtr'!$J36:$EA36, 'FS Qtr'!$J$4:$EA$4, 'FS Ann'!O$4) -> -7645.4216 | P36: =SUMIFS('FS Qtr'!$J36:$EA36, 'FS Qtr'!$J$4:$EA$4, 'FS Ann'!P$4) -> -8034.5644 | Q36: =SUMIFS('FS Qtr'!$J36:$EA36, 'FS Qtr'!$J$4:$EA$4, 'FS Ann'!Q$4) -> -8454.9981 | ... AN36: =SUMIFS('FS Qtr'!$J36:$EA36, 'FS Qtr'!$J$4:$EA$4, 'FS Ann'!AN$4) -> -2.0710031e-11
E37: Cash flow available for refinancing facility | G37: =SMU -> $ 000s | H37: =SUM(J37:AN37) -> 217978.25 | J37: =J33 + SUM(J35:J36) -> 0 | K37: =K33 + SUM(K35:K36) -> 2940.55 | L37: =L33 + SUM(L35:L36) -> 3264.3007 | M37: =M33 + SUM(M35:M36) -> 3242.8442 | N37: =N33 + SUM(N35:N36) -> 3210.0736 | O37: =O33 + SUM(O35:O36) -> 3188.5031 | P37: =P33 + SUM(P35:P36) -> 3163.1175 | Q37: =Q33 + SUM(Q35:Q36) -> 3141.3106 | ... AN37: =AN33 + SUM(AN35:AN36) -> 0
E39: ='FS Qtr'!E40 -> [Refi facility repayment] | F39: ='FS Qtr'!F40 -> 0 | G39: ='FS Qtr'!G40 -> 0 | H39: =SUM(J39:AN39) -> 0 | J39: =SUMIFS('FS Qtr'!$J40:$EA40, 'FS Qtr'!$J$4:$EA$4, 'FS Ann'!J$4) -> 0 | K39: =SUMIFS('FS Qtr'!$J40:$EA40, 'FS Qtr'!$J$4:$EA$4, 'FS Ann'!K$4) -> 0 | L39: =SUMIFS('FS Qtr'!$J40:$EA40, 'FS Qtr'!$J$4:$EA$4, 'FS Ann'!L$4) -> 0 | M39: =SUMIFS('FS Qtr'!$J40:$EA40, 'FS Qtr'!$J$4:$EA$4, 'FS Ann'!M$4) -> 0 | N39: =SUMIFS('FS Qtr'!$J40:$EA40, 'FS Qtr'!$J$4:$EA$4, 'FS Ann'!N$4) -> 0 | O39: =SUMIFS('FS Qtr'!$J40:$EA40, 'FS Qtr'!$J$4:$EA$4, 'FS Ann'!O$4) -> 0 | P39: =SUMIFS('FS Qtr'!$J40:$EA40, 'FS Qtr'!$J$4:$EA$4, 'FS Ann'!P$4) -> 0 | Q39: =SUMIFS('FS Qtr'!$J40:$EA40, 'FS Qtr'!$J$4:$EA$4, 'FS Ann'!Q$4) -> 0 | ... AN39: =SUMIFS('FS Qtr'!$J40:$EA40, 'FS Qtr'!$J$4:$EA$4, 'FS Ann'!AN$4) -> 0
E40: ='FS Qtr'!E41 -> [Refi facility interest] | F40: ='FS Qtr'!F41 -> 0 | G40: ='FS Qtr'!G41 -> 0 | H40: =SUM(J40:AN40) -> 0 | J40: =SUMIFS('FS Qtr'!$J41:$EA41, 'FS Qtr'!$J$4:$EA$4, 'FS Ann'!J$4) -> 0 | K40: =SUMIFS('FS Qtr'!$J41:$EA41, 'FS Qtr'!$J$4:$EA$4, 'FS Ann'!K$4) -> 0 | L40: =SUMIFS('FS Qtr'!$J41:$EA41, 'FS Qtr'!$J$4:$EA$4, 'FS Ann'!L$4) -> 0 | M40: =SUMIFS('FS Qtr'!$J41:$EA41, 'FS Qtr'!$J$4:$EA$4, 'FS Ann'!M$4) -> 0 | N40: =SUMIFS('FS Qtr'!$J41:$EA41, 'FS Qtr'!$J$4:$EA$4, 'FS Ann'!N$4) -> 0 | O40: =SUMIFS('FS Qtr'!$J41:$EA41, 'FS Qtr'!$J$4:$EA$4, 'FS Ann'!O$4) -> 0 | P40: =SUMIFS('FS Qtr'!$J41:$EA41, 'FS Qtr'!$J$4:$EA$4, 'FS Ann'!P$4) -> 0 | Q40: =SUMIFS('FS Qtr'!$J41:$EA41, 'FS Qtr'!$J$4:$EA$4, 'FS Ann'!Q$4) -> 0 | ... AN40: =SUMIFS('FS Qtr'!$J41:$EA41, 'FS Qtr'!$J$4:$EA$4, 'FS Ann'!AN$4) -> 0
E41: Cash flow available for revolving credit facility | G41: =SMU -> $ 000s | H41: =SUM(J41:AN41) -> 217978.25 | J41: =J37 + SUM(J39:J40) -> 0 | K41: =K37 + SUM(K39:K40) -> 2940.55 | L41: =L37 + SUM(L39:L40) -> 3264.3007 | M41: =M37 + SUM(M39:M40) -> 3242.8442 | N41: =N37 + SUM(N39:N40) -> 3210.0736 | O41: =O37 + SUM(O39:O40) -> 3188.5031 | P41: =P37 + SUM(P39:P40) -> 3163.1175 | Q41: =Q37 + SUM(Q39:Q40) -> 3141.3106 | ... AN41: =AN37 + SUM(AN39:AN40) -> 0
E43: ='FS Qtr'!E44 -> [RCF drawdown] | F43: ='FS Qtr'!F44 -> 0 | G43: ='FS Qtr'!G44 -> 0 | H43: =SUM(J43:AN43) -> 0 | J43: =SUMIFS('FS Qtr'!$J44:$EA44, 'FS Qtr'!$J$4:$EA$4, 'FS Ann'!J$4) -> 0 | K43: =SUMIFS('FS Qtr'!$J44:$EA44, 'FS Qtr'!$J$4:$EA$4, 'FS Ann'!K$4) -> 0 | L43: =SUMIFS('FS Qtr'!$J44:$EA44, 'FS Qtr'!$J$4:$EA$4, 'FS Ann'!L$4) -> 0 | M43: =SUMIFS('FS Qtr'!$J44:$EA44, 'FS Qtr'!$J$4:$EA$4, 'FS Ann'!M$4) -> 0 | N43: =SUMIFS('FS Qtr'!$J44:$EA44, 'FS Qtr'!$J$4:$EA$4, 'FS Ann'!N$4) -> 0 | O43: =SUMIFS('FS Qtr'!$J44:$EA44, 'FS Qtr'!$J$4:$EA$4, 'FS Ann'!O$4) -> 0 | P43: =SUMIFS('FS Qtr'!$J44:$EA44, 'FS Qtr'!$J$4:$EA$4, 'FS Ann'!P$4) -> 0 | Q43: =SUMIFS('FS Qtr'!$J44:$EA44, 'FS Qtr'!$J$4:$EA$4, 'FS Ann'!Q$4) -> 0 | ... AN43: =SUMIFS('FS Qtr'!$J44:$EA44, 'FS Qtr'!$J$4:$EA$4, 'FS Ann'!AN$4) -> 0
E44: ='FS Qtr'!E45 -> [RCF repayment] | F44: ='FS Qtr'!F45 -> 0 | G44: ='FS Qtr'!G45 -> 0 | H44: =SUM(J44:AN44) -> 0 | J44: =SUMIFS('FS Qtr'!$J45:$EA45, 'FS Qtr'!$J$4:$EA$4, 'FS Ann'!J$4) -> 0 | K44: =SUMIFS('FS Qtr'!$J45:$EA45, 'FS Qtr'!$J$4:$EA$4, 'FS Ann'!K$4) -> 0 | L44: =SUMIFS('FS Qtr'!$J45:$EA45, 'FS Qtr'!$J$4:$EA$4, 'FS Ann'!L$4) -> 0 | M44: =SUMIFS('FS Qtr'!$J45:$EA45, 'FS Qtr'!$J$4:$EA$4, 'FS Ann'!M$4) -> 0 | N44: =SUMIFS('FS Qtr'!$J45:$EA45, 'FS Qtr'!$J$4:$EA$4, 'FS Ann'!N$4) -> 0 | O44: =SUMIFS('FS Qtr'!$J45:$EA45, 'FS Qtr'!$J$4:$EA$4, 'FS Ann'!O$4) -> 0 | P44: =SUMIFS('FS Qtr'!$J45:$EA45, 'FS Qtr'!$J$4:$EA$4, 'FS Ann'!P$4) -> 0 | Q44: =SUMIFS('FS Qtr'!$J45:$EA45, 'FS Qtr'!$J$4:$EA$4, 'FS Ann'!Q$4) -> 0 | ... AN44: =SUMIFS('FS Qtr'!$J45:$EA45, 'FS Qtr'!$J$4:$EA$4, 'FS Ann'!AN$4) -> 0
E45: ='FS Qtr'!E46 -> [RCF interest expense paid] | F45: ='FS Qtr'!F46 -> 0 | G45: ='FS Qtr'!G46 -> 0 | H45: =SUM(J45:AN45) -> 0 | J45: =SUMIFS('FS Qtr'!$J46:$EA46, 'FS Qtr'!$J$4:$EA$4, 'FS Ann'!J$4) -> 0 | K45: =SUMIFS('FS Qtr'!$J46:$EA46, 'FS Qtr'!$J$4:$EA$4, 'FS Ann'!K$4) -> 0 | L45: =SUMIFS('FS Qtr'!$J46:$EA46, 'FS Qtr'!$J$4:$EA$4, 'FS Ann'!L$4) -> 0 | M45: =SUMIFS('FS Qtr'!$J46:$EA46, 'FS Qtr'!$J$4:$EA$4, 'FS Ann'!M$4) -> 0 | N45: =SUMIFS('FS Qtr'!$J46:$EA46, 'FS Qtr'!$J$4:$EA$4, 'FS Ann'!N$4) -> 0 | O45: =SUMIFS('FS Qtr'!$J46:$EA46, 'FS Qtr'!$J$4:$EA$4, 'FS Ann'!O$4) -> 0 | P45: =SUMIFS('FS Qtr'!$J46:$EA46, 'FS Qtr'!$J$4:$EA$4, 'FS Ann'!P$4) -> 0 | Q45: =SUMIFS('FS Qtr'!$J46:$EA46, 'FS Qtr'!$J$4:$EA$4, 'FS Ann'!Q$4) -> 0 | ... AN45: =SUMIFS('FS Qtr'!$J46:$EA46, 'FS Qtr'!$J$4:$EA$4, 'FS Ann'!AN$4) -> 0
E46: Cash available for shareholders | G46: =SMU -> $ 000s | H46: =SUM(J46:AN46) -> 217978.25 | J46: =J41 + SUM(J43:J45) -> 0 | K46: =K41 + SUM(K43:K45) -> 2940.55 | L46: =L41 + SUM(L43:L45) -> 3264.3007 | M46: =M41 + SUM(M43:M45) -> 3242.8442 | N46: =N41 + SUM(N43:N45) -> 3210.0736 | O46: =O41 + SUM(O43:O45) -> 3188.5031 | P46: =P41 + SUM(P43:P45) -> 3163.1175 | Q46: =Q41 + SUM(Q43:Q45) -> 3141.3106 | ... AN46: =AN41 + SUM(AN43:AN45) -> 0
E48: ='FS Qtr'!E49 -> Share capital redemption | F48: ='FS Qtr'!F49 -> 0 | G48: ='FS Qtr'!G49 -> $ 000s | H48: =SUM(J48:AN48) -> -21824.067 | J48: =SUMIFS('FS Qtr'!$J49:$EA49, 'FS Qtr'!$J$4:$EA$4, 'FS Ann'!J$4) -> 0 | K48: =SUMIFS('FS Qtr'!$J49:$EA49, 'FS Qtr'!$J$4:$EA$4, 'FS Ann'!K$4) -> 0 | L48: =SUMIFS('FS Qtr'!$J49:$EA49, 'FS Qtr'!$J$4:$EA$4, 'FS Ann'!L$4) -> 0 | M48: =SUMIFS('FS Qtr'!$J49:$EA49, 'FS Qtr'!$J$4:$EA$4, 'FS Ann'!M$4) -> 0 | N48: =SUMIFS('FS Qtr'!$J49:$EA49, 'FS Qtr'!$J$4:$EA$4, 'FS Ann'!N$4) -> 0 | O48: =SUMIFS('FS Qtr'!$J49:$EA49, 'FS Qtr'!$J$4:$EA$4, 'FS Ann'!O$4) -> 0 | P48: =SUMIFS('FS Qtr'!$J49:$EA49, 'FS Qtr'!$J$4:$EA$4, 'FS Ann'!P$4) -> 0 | Q48: =SUMIFS('FS Qtr'!$J49:$EA49, 'FS Qtr'!$J$4:$EA$4, 'FS Ann'!Q$4) -> 0 | ... AN48: =SUMIFS('FS Qtr'!$J49:$EA49, 'FS Qtr'!$J$4:$EA$4, 'FS Ann'!AN$4) -> 0
E49: Cash flow available for dividends | G49: =SMU -> $ 000s | H49: =SUM(J49:AN49) -> 196154.18 | J49: =J46 + J48 -> 0 | K49: =K46 + K48 -> 2940.55 | L49: =L46 + L48 -> 3264.3007 | M49: =M46 + M48 -> 3242.8442 | N49: =N46 + N48 -> 3210.0736 | O49: =O46 + O48 -> 3188.5031 | P49: =P46 + P48 -> 3163.1175 | Q49: =Q46 + Q48 -> 3141.3106 | ... AN49: =AN46 + AN48 -> 0
E51: ='FS Qtr'!E52 -> Dividends paid | F51: ='FS Qtr'!F52 -> 0 | G51: ='FS Qtr'!G52 -> $ 000s | H51: =SUM(J51:AN51) -> -196154.18 | J51: =SUMIFS('FS Qtr'!$J52:$EA52, 'FS Qtr'!$J$4:$EA$4, 'FS Ann'!J$4) -> 0 | K51: =SUMIFS('FS Qtr'!$J52:$EA52, 'FS Qtr'!$J$4:$EA$4, 'FS Ann'!K$4) -> -2940.55 | L51: =SUMIFS('FS Qtr'!$J52:$EA52, 'FS Qtr'!$J$4:$EA$4, 'FS Ann'!L$4) -> -3264.3007 | M51: =SUMIFS('FS Qtr'!$J52:$EA52, 'FS Qtr'!$J$4:$EA$4, 'FS Ann'!M$4) -> -3242.8442 | N51: =SUMIFS('FS Qtr'!$J52:$EA52, 'FS Qtr'!$J$4:$EA$4, 'FS Ann'!N$4) -> -3210.0736 | O51: =SUMIFS('FS Qtr'!$J52:$EA52, 'FS Qtr'!$J$4:$EA$4, 'FS Ann'!O$4) -> -3188.5031 | P51: =SUMIFS('FS Qtr'!$J52:$EA52, 'FS Qtr'!$J$4:$EA$4, 'FS Ann'!P$4) -> -3163.1175 | Q51: =SUMIFS('FS Qtr'!$J52:$EA52, 'FS Qtr'!$J$4:$EA$4, 'FS Ann'!Q$4) -> -3141.3106 | ... AN51: =SUMIFS('FS Qtr'!$J52:$EA52, 'FS Qtr'!$J$4:$EA$4, 'FS Ann'!AN$4) -> 0
E52: Net cash flow | G52: =SMU -> $ 000s | H52: =SUM(J52:AN52) -> -1.0913936e-11 | J52: =J49 + J51 -> 0 | K52: =K49 + K51 -> 0 | L52: =L49 + L51 -> 0 | M52: =M49 + M51 -> 0 | N52: =N49 + N51 -> 0 | O52: =O49 + O51 -> 0 | P52: =P49 + P51 -> 0 | Q52: =Q49 + Q51 -> 0 | ... AN52: =AN49 + AN51 -> 0
A56: BALANCE SHEET
B58: Non current assets
E59: ='FS Qtr'!E59 -> Fixed asset balance | F59: ='FS Qtr'!F59 -> 0 | G59: ='FS Qtr'!G59 -> $ 000s | J59: =SUMIFS( 'FS Qtr'!$J59:$EA59, 'FS Qtr'!$J$2:$EA$2, 'FS Ann'!J$2) -> 0 | K59: =SUMIFS( 'FS Qtr'!$J59:$EA59, 'FS Qtr'!$J$2:$EA$2, 'FS Ann'!K$2) -> 100000 | L59: =SUMIFS( 'FS Qtr'!$J59:$EA59, 'FS Qtr'!$J$2:$EA$2, 'FS Ann'!L$2) -> 96000 | M59: =SUMIFS( 'FS Qtr'!$J59:$EA59, 'FS Qtr'!$J$2:$EA$2, 'FS Ann'!M$2) -> 92000 | N59: =SUMIFS( 'FS Qtr'!$J59:$EA59, 'FS Qtr'!$J$2:$EA$2, 'FS Ann'!N$2) -> 88000 | O59: =SUMIFS( 'FS Qtr'!$J59:$EA59, 'FS Qtr'!$J$2:$EA$2, 'FS Ann'!O$2) -> 84000 | P59: =SUMIFS( 'FS Qtr'!$J59:$EA59, 'FS Qtr'!$J$2:$EA$2, 'FS Ann'!P$2) -> 80000 | Q59: =SUMIFS( 'FS Qtr'!$J59:$EA59, 'FS Qtr'!$J$2:$EA$2, 'FS Ann'!Q$2) -> 76000 | ... AN59: =SUMIFS( 'FS Qtr'!$J59:$EA59, 'FS Qtr'!$J$2:$EA$2, 'FS Ann'!AN$2) -> 0
E60: Non current assets | G60: =SMU -> $ 000s | J60: =SUM(J59) -> 0 | K60: =SUM(K59) -> 100000 | L60: =SUM(L59) -> 96000 | M60: =SUM(M59) -> 92000 | N60: =SUM(N59) -> 88000 | O60: =SUM(O59) -> 84000 | P60: =SUM(P59) -> 80000 | Q60: =SUM(Q59) -> 76000 | ... AN60: =SUM(AN59) -> 0
B62: Current assets
E63: ='FS Qtr'!E63 -> Retained cash balance | F63: ='FS Qtr'!F63 -> 0 | G63: ='FS Qtr'!G63 -> $ 000s | J63: =SUMIFS( 'FS Qtr'!$J63:$EA63, 'FS Qtr'!$J$2:$EA$2, 'FS Ann'!J$2) -> 0 | K63: =SUMIFS( 'FS Qtr'!$J63:$EA63, 'FS Qtr'!$J$2:$EA$2, 'FS Ann'!K$2) -> 0 | L63: =SUMIFS( 'FS Qtr'!$J63:$EA63, 'FS Qtr'!$J$2:$EA$2, 'FS Ann'!L$2) -> 0 | M63: =SUMIFS( 'FS Qtr'!$J63:$EA63, 'FS Qtr'!$J$2:$EA$2, 'FS Ann'!M$2) -> 0 | N63: =SUMIFS( 'FS Qtr'!$J63:$EA63, 'FS Qtr'!$J$2:$EA$2, 'FS Ann'!N$2) -> 0 | O63: =SUMIFS( 'FS Qtr'!$J63:$EA63, 'FS Qtr'!$J$2:$EA$2, 'FS Ann'!O$2) -> 0 | P63: =SUMIFS( 'FS Qtr'!$J63:$EA63, 'FS Qtr'!$J$2:$EA$2, 'FS Ann'!P$2) -> 0 | Q63: =SUMIFS( 'FS Qtr'!$J63:$EA63, 'FS Qtr'!$J$2:$EA$2, 'FS Ann'!Q$2) -> 0 | ... AN63: =SUMIFS( 'FS Qtr'!$J63:$EA63, 'FS Qtr'!$J$2:$EA$2, 'FS Ann'!AN$2) -> 0
E64: ='FS Qtr'!E64 -> Accounts receivable balance | F64: ='FS Qtr'!F64 -> 0 | G64: ='FS Qtr'!G64 -> $ 000s | J64: =SUMIFS( 'FS Qtr'!$J64:$EA64, 'FS Qtr'!$J$2:$EA$2, 'FS Ann'!J$2) -> 0 | K64: =SUMIFS( 'FS Qtr'!$J64:$EA64, 'FS Qtr'!$J$2:$EA$2, 'FS Ann'!K$2) -> 0 | L64: =SUMIFS( 'FS Qtr'!$J64:$EA64, 'FS Qtr'!$J$2:$EA$2, 'FS Ann'!L$2) -> 1628.7917 | M64: =SUMIFS( 'FS Qtr'!$J64:$EA64, 'FS Qtr'!$J$2:$EA$2, 'FS Ann'!M$2) -> 1620.6882 | N64: =SUMIFS( 'FS Qtr'!$J64:$EA64, 'FS Qtr'!$J$2:$EA$2, 'FS Ann'!N$2) -> 1594.9039 | O64: =SUMIFS( 'FS Qtr'!$J64:$EA64, 'FS Qtr'!$J$2:$EA$2, 'FS Ann'!O$2) -> 1604.6021 | P64: =SUMIFS( 'FS Qtr'!$J64:$EA64, 'FS Qtr'!$J$2:$EA$2, 'FS Ann'!P$2) -> 1596.619 | Q64: =SUMIFS( 'FS Qtr'!$J64:$EA64, 'FS Qtr'!$J$2:$EA$2, 'FS Ann'!Q$2) -> 1588.6756 | ... AN64: =SUMIFS( 'FS Qtr'!$J64:$EA64, 'FS Qtr'!$J$2:$EA$2, 'FS Ann'!AN$2) -> 0
E65: Current assets | G65: =SMU -> $ 000s | J65: =SUM(J63:J64) -> 0 | K65: =SUM(K63:K64) -> 0 | L65: =SUM(L63:L64) -> 1628.7917 | M65: =SUM(M63:M64) -> 1620.6882 | N65: =SUM(N63:N64) -> 1594.9039 | O65: =SUM(O63:O64) -> 1604.6021 | P65: =SUM(P63:P64) -> 1596.619 | Q65: =SUM(Q63:Q64) -> 1588.6756 | ... AN65: =SUM(AN63:AN64) -> 0
E67: Total assets | G67: =SMU -> $ 000s | J67: =J65 + J60 -> 0 | K67: =K65 + K60 -> 100000 | L67: =L65 + L60 -> 97628.792 | M67: =M65 + M60 -> 93620.688 | N67: =N65 + N60 -> 89594.904 | O67: =O65 + O60 -> 85604.602 | P67: =P65 + P60 -> 81596.619 | Q67: =Q65 + Q60 -> 77588.676 | ... AN67: =AN65 + AN60 -> 0
E69: ='FS Qtr'!E69 -> Accounts payable balance | F69: ='FS Qtr'!F69 -> 0 | G69: ='FS Qtr'!G69 -> $ 000s | J69: =SUMIFS( 'FS Qtr'!$J69:$EA69, 'FS Qtr'!$J$2:$EA$2, 'FS Ann'!J$2) -> 0 | K69: =SUMIFS( 'FS Qtr'!$J69:$EA69, 'FS Qtr'!$J$2:$EA$2, 'FS Ann'!K$2) -> 0 | L69: =SUMIFS( 'FS Qtr'!$J69:$EA69, 'FS Qtr'!$J$2:$EA$2, 'FS Ann'!L$2) -> 127.51881 | M69: =SUMIFS( 'FS Qtr'!$J69:$EA69, 'FS Qtr'!$J$2:$EA$2, 'FS Ann'!M$2) -> 130.08838 | N69: =SUMIFS( 'FS Qtr'!$J69:$EA69, 'FS Qtr'!$J$2:$EA$2, 'FS Ann'!N$2) -> 131.25138 | O69: =SUMIFS( 'FS Qtr'!$J69:$EA69, 'FS Qtr'!$J$2:$EA$2, 'FS Ann'!O$2) -> 135.38389 | P69: =SUMIFS( 'FS Qtr'!$J69:$EA69, 'FS Qtr'!$J$2:$EA$2, 'FS Ann'!P$2) -> 138.11195 | Q69: =SUMIFS( 'FS Qtr'!$J69:$EA69, 'FS Qtr'!$J$2:$EA$2, 'FS Ann'!Q$2) -> 140.89497 | ... AN69: =SUMIFS( 'FS Qtr'!$J69:$EA69, 'FS Qtr'!$J$2:$EA$2, 'FS Ann'!AN$2) -> 0
E70: ='FS Qtr'!E70 -> Senior debt balance | F70: ='FS Qtr'!F70 -> 0 | G70: ='FS Qtr'!G70 -> $ 000s | J70: =SUMIFS( 'FS Qtr'!$J70:$EA70, 'FS Qtr'!$J$2:$EA$2, 'FS Ann'!J$2) -> 0 | K70: =SUMIFS( 'FS Qtr'!$J70:$EA70, 'FS Qtr'!$J$2:$EA$2, 'FS Ann'!K$2) -> 78175.933 | L70: =SUMIFS( 'FS Qtr'!$J70:$EA70, 'FS Qtr'!$J$2:$EA$2, 'FS Ann'!L$2) -> 73018.97 | M70: =SUMIFS( 'FS Qtr'!$J70:$EA70, 'FS Qtr'!$J$2:$EA$2, 'FS Ann'!M$2) -> 66410.006 | N70: =SUMIFS( 'FS Qtr'!$J70:$EA70, 'FS Qtr'!$J$2:$EA$2, 'FS Ann'!N$2) -> 59473.313 | O70: =SUMIFS( 'FS Qtr'!$J70:$EA70, 'FS Qtr'!$J$2:$EA$2, 'FS Ann'!O$2) -> 52206.757 | P70: =SUMIFS( 'FS Qtr'!$J70:$EA70, 'FS Qtr'!$J$2:$EA$2, 'FS Ann'!P$2) -> 44561.335 | Q70: =SUMIFS( 'FS Qtr'!$J70:$EA70, 'FS Qtr'!$J$2:$EA$2, 'FS Ann'!Q$2) -> 36526.77 | ... AN70: =SUMIFS( 'FS Qtr'!$J70:$EA70, 'FS Qtr'!$J$2:$EA$2, 'FS Ann'!AN$2) -> -4.4502175e-10
E71: ='FS Qtr'!E71 -> [Refi facility balance] | F71: ='FS Qtr'!F71 -> 0 | G71: ='FS Qtr'!G71 -> 0 | J71: =SUMIFS( 'FS Qtr'!$J71:$EA71, 'FS Qtr'!$J$2:$EA$2, 'FS Ann'!J$2) -> 0 | K71: =SUMIFS( 'FS Qtr'!$J71:$EA71, 'FS Qtr'!$J$2:$EA$2, 'FS Ann'!K$2) -> 0 | L71: =SUMIFS( 'FS Qtr'!$J71:$EA71, 'FS Qtr'!$J$2:$EA$2, 'FS Ann'!L$2) -> 0 | M71: =SUMIFS( 'FS Qtr'!$J71:$EA71, 'FS Qtr'!$J$2:$EA$2, 'FS Ann'!M$2) -> 0 | N71: =SUMIFS( 'FS Qtr'!$J71:$EA71, 'FS Qtr'!$J$2:$EA$2, 'FS Ann'!N$2) -> 0 | O71: =SUMIFS( 'FS Qtr'!$J71:$EA71, 'FS Qtr'!$J$2:$EA$2, 'FS Ann'!O$2) -> 0 | P71: =SUMIFS( 'FS Qtr'!$J71:$EA71, 'FS Qtr'!$J$2:$EA$2, 'FS Ann'!P$2) -> 0 | Q71: =SUMIFS( 'FS Qtr'!$J71:$EA71, 'FS Qtr'!$J$2:$EA$2, 'FS Ann'!Q$2) -> 0 | ... AN71: =SUMIFS( 'FS Qtr'!$J71:$EA71, 'FS Qtr'!$J$2:$EA$2, 'FS Ann'!AN$2) -> 0
E72: ='FS Qtr'!E72 -> [RCF balance] | F72: ='FS Qtr'!F72 -> 0 | G72: ='FS Qtr'!G72 -> 0 | J72: =SUMIFS( 'FS Qtr'!$J72:$EA72, 'FS Qtr'!$J$2:$EA$2, 'FS Ann'!J$2) -> 0 | K72: =SUMIFS( 'FS Qtr'!$J72:$EA72, 'FS Qtr'!$J$2:$EA$2, 'FS Ann'!K$2) -> 0 | L72: =SUMIFS( 'FS Qtr'!$J72:$EA72, 'FS Qtr'!$J$2:$EA$2, 'FS Ann'!L$2) -> 0 | M72: =SUMIFS( 'FS Qtr'!$J72:$EA72, 'FS Qtr'!$J$2:$EA$2, 'FS Ann'!M$2) -> 0 | N72: =SUMIFS( 'FS Qtr'!$J72:$EA72, 'FS Qtr'!$J$2:$EA$2, 'FS Ann'!N$2) -> 0 | O72: =SUMIFS( 'FS Qtr'!$J72:$EA72, 'FS Qtr'!$J$2:$EA$2, 'FS Ann'!O$2) -> 0 | P72: =SUMIFS( 'FS Qtr'!$J72:$EA72, 'FS Qtr'!$J$2:$EA$2, 'FS Ann'!P$2) -> 0 | Q72: =SUMIFS( 'FS Qtr'!$J72:$EA72, 'FS Qtr'!$J$2:$EA$2, 'FS Ann'!Q$2) -> 0 | ... AN72: =SUMIFS( 'FS Qtr'!$J72:$EA72, 'FS Qtr'!$J$2:$EA$2, 'FS Ann'!AN$2) -> 0
E73: ='FS Qtr'!E73 -> Share capital balance | F73: ='FS Qtr'!F73 -> 0 | G73: ='FS Qtr'!G73 -> $ 000s | J73: =SUMIFS( 'FS Qtr'!$J73:$EA73, 'FS Qtr'!$J$2:$EA$2, 'FS Ann'!J$2) -> 0 | K73: =SUMIFS( 'FS Qtr'!$J73:$EA73, 'FS Qtr'!$J$2:$EA$2, 'FS Ann'!K$2) -> 21824.067 | L73: =SUMIFS( 'FS Qtr'!$J73:$EA73, 'FS Qtr'!$J$2:$EA$2, 'FS Ann'!L$2) -> 21824.067 | M73: =SUMIFS( 'FS Qtr'!$J73:$EA73, 'FS Qtr'!$J$2:$EA$2, 'FS Ann'!M$2) -> 21824.067 | N73: =SUMIFS( 'FS Qtr'!$J73:$EA73, 'FS Qtr'!$J$2:$EA$2, 'FS Ann'!N$2) -> 21824.067 | O73: =SUMIFS( 'FS Qtr'!$J73:$EA73, 'FS Qtr'!$J$2:$EA$2, 'FS Ann'!O$2) -> 21824.067 | P73: =SUMIFS( 'FS Qtr'!$J73:$EA73, 'FS Qtr'!$J$2:$EA$2, 'FS Ann'!P$2) -> 21824.067 | Q73: =SUMIFS( 'FS Qtr'!$J73:$EA73, 'FS Qtr'!$J$2:$EA$2, 'FS Ann'!Q$2) -> 21824.067 | ... AN73: =SUMIFS( 'FS Qtr'!$J73:$EA73, 'FS Qtr'!$J$2:$EA$2, 'FS Ann'!AN$2) -> 0
E74: ='FS Qtr'!E74 -> Retained earnings balance | F74: ='FS Qtr'!F74 -> 0 | G74: ='FS Qtr'!G74 -> $ 000s | J74: =SUMIFS( 'FS Qtr'!$J74:$EA74, 'FS Qtr'!$J$2:$EA$2, 'FS Ann'!J$2) -> 0 | K74: =SUMIFS( 'FS Qtr'!$J74:$EA74, 'FS Qtr'!$J$2:$EA$2, 'FS Ann'!K$2) -> 0 | L74: =SUMIFS( 'FS Qtr'!$J74:$EA74, 'FS Qtr'!$J$2:$EA$2, 'FS Ann'!L$2) -> 2658.2359 | M74: =SUMIFS( 'FS Qtr'!$J74:$EA74, 'FS Qtr'!$J$2:$EA$2, 'FS Ann'!M$2) -> 5256.5262 | N74: =SUMIFS( 'FS Qtr'!$J74:$EA74, 'FS Qtr'!$J$2:$EA$2, 'FS Ann'!N$2) -> 8166.2721 | O74: =SUMIFS( 'FS Qtr'!$J74:$EA74, 'FS Qtr'!$J$2:$EA$2, 'FS Ann'!O$2) -> 11438.394 | P74: =SUMIFS( 'FS Qtr'!$J74:$EA74, 'FS Qtr'!$J$2:$EA$2, 'FS Ann'!P$2) -> 15073.105 | Q74: =SUMIFS( 'FS Qtr'!$J74:$EA74, 'FS Qtr'!$J$2:$EA$2, 'FS Ann'!Q$2) -> 19096.943 | ... AN74: =SUMIFS( 'FS Qtr'!$J74:$EA74, 'FS Qtr'!$J$2:$EA$2, 'FS Ann'!AN$2) -> 4.4130227e-10
E75: Total liabilities | G75: =SMU -> $ 000s | J75: =SUM(J69:J74) -> 0 | K75: =SUM(K69:K74) -> 100000 | L75: =SUM(L69:L74) -> 97628.792 | M75: =SUM(M69:M74) -> 93620.688 | N75: =SUM(N69:N74) -> 89594.904 | O75: =SUM(O69:O74) -> 85604.602 | P75: =SUM(P69:P74) -> 81596.619 | Q75: =SUM(Q69:Q74) -> 77588.676 | ... AN75: =SUM(AN69:AN74) -> -3.7194797e-12
A78: BALANCE SHEET CHECK
E80: =E$67 -> Total assets | F80: =F$67 -> 0 | G80: =G$67 -> $ 000s | H80: =H$67 -> 0 | I80: =I$67 -> 0 | J80: =J$67 -> 0 | K80: =K$67 -> 100000 | L80: =L$67 -> 97628.792 | ... AN80: =AN$67 -> 0
E81: =E$75 -> Total liabilities | F81: =F$75 -> 0 | G81: =G$75 -> $ 000s | H81: =H$75 -> 0 | I81: =I$75 -> 0 | J81: =J$75 -> 0 | K81: =K$75 -> 100000 | L81: =L$75 -> 97628.792 | ... AN81: =AN$75 -> -3.7194797e-12
E82: Annual balance sheet check | F82: =IF(SUM(J82:AN82) <> 0, 1, 0) -> 0 | G82: check | J82: =IF(ABS(J80 - J81) > CHK_TOL, 1, 0) -> 0 | K82: =IF(ABS(K80 - K81) > CHK_TOL, 1, 0) -> 0 | L82: =IF(ABS(L80 - L81) > CHK_TOL, 1, 0) -> 0 | M82: =IF(ABS(M80 - M81) > CHK_TOL, 1, 0) -> 0 | N82: =IF(ABS(N80 - N81) > CHK_TOL, 1, 0) -> 0 | O82: =IF(ABS(O80 - O81) > CHK_TOL, 1, 0) -> 0 | P82: =IF(ABS(P80 - P81) > CHK_TOL, 1, 0) -> 0 | Q82: =IF(ABS(Q80 - Q81) > CHK_TOL, 1, 0) -> 0 | ... AN82: =IF(ABS(AN80 - AN81) > CHK_TOL, 1, 0) -> 0
E83: Annual balance sheet difference | H83: =SUM(J83:AN83) -> 1.8743271e-11 | J83: =J80 - J81 -> 0 | K83: =K80 - K81 -> 0 | L83: =L80 - L81 -> 0 | M83: =M80 - M81 -> 0 | N83: =N80 - N81 -> 0 | O83: =O80 - O81 -> 0 | P83: =P80 - P81 -> 0 | Q83: =Q80 - Q81 -> 0 | ... AN83: =AN80 - AN81 -> 3.7194797e-12
A86: END

Sheet Output
A1: =RIGHT(CELL("filename", A1), LEN(CELL("filename", A1)) - SEARCH("]", CELL("filename", A1))) & " - " & InpC!F3 -> Output - Base case 1
G2: Date | H2: =TODAY() -> 44576 | J2: =COUNTIF(J6:J76, "tu") -> 0 | N2: 44576 | O2: 44576 | P2: 44576 | Q2: 44576 | R2: 44576 | S2: 44576 | T2: 44575 | U2: 44572 | V2: 44572 | W2: 44572 | X2: 44572 | Y2: 44571 | Z2: 44571 | AA2: 44564 | AB2: 44564 | AC2: 44564
G3: Case | H3: =InpC!F3 -> Base case 1 | N3: Base case 1 | O3: Base case 1 | P3: Base case 1 | Q3: Base case 1 | R3: Base case 1 | S3: Base case 1 | T3: Base case 1 | U3: Base case 1 | V3: Base case 1 | W3: Base case 1 | X3: Base case 1 | Y3: Base case 1 | Z3: Base case 1 | AA3: Base case 1 | AB3: Base case 1 | AC3: Base case 1
E5: Comparison column label | G5: Unit | H5: 18 | J5: =MATCH($H$5, M5:AF5, 0) -> 2 | K5: Difference | L5: Diff Pct | N5: 18 | O5: 17 | P5: 16 | Q5: 15 | R5: 14 | S5: 13 | T5: 12 | U5: 11 | V5: 10 | W5: 9 | X5: 8 | Y5: 7 | Z5: 6 | AA5: 5 | AB5: 4 | AC5: 3 | AD5: 2 | AE5: 1
E6: [do not delete row]
A8: KEY OUTPUTS
E10: =Metrics!E$20 -> Equity IRR | G10: =Metrics!G$20 -> % | H10: =Metrics!F$20 -> 0.21705926 | J10: =IF(ABS(K10) > TRK_TOL, "tu", "vw") -> vw | K10: =H10 - INDEX(M10:AF10, $J$5) -> 0 | L10: =IF(ABS(K10) > TRK_TOL, IF(INDEX(M10:AF10, $J$5) = 0, 0, H10 / INDEX(M10:AF10, $J$5) - 1), 0) -> 0 | N10: 0.21705926 | O10: 0.19669247 | P10: 0.19669247 | Q10: 0.18807239 | R10: 0.26290707 | S10: 0.075917241 | T10: 0.089617065 | U10: 0.098730558 | V10: 0.084725401 | W10: 0.1347866
E11: =Metrics!E$31 -> Min 3m historic DSCR | G11: =Metrics!G$31 -> ratio | H11: =Metrics!F$31 -> 1.3 | J11: =IF(ABS(K11) > TRK_TOL, "tu", "vw") -> vw | K11: =H11 - INDEX(M11:AF11, $J$5) -> 0 | L11: =IF(ABS(K11) > TRK_TOL, IF(INDEX(M11:AF11, $J$5) = 0, 0, H11 / INDEX(M11:AF11, $J$5) - 1), 0) -> 0 | N11: 1.3 | O11: 0.64672401
E12: =Metrics!E$32 -> Avg 3m historic DSCR | G12: =Metrics!G$32 -> ratio | H12: =Metrics!F$32 -> 1.3 | J12: =IF(ABS(K12) > TRK_TOL, "tu", "vw") -> vw | K12: =H12 - INDEX(M12:AF12, $J$5) -> 0 | L12: =IF(ABS(K12) > TRK_TOL, IF(INDEX(M12:AF12, $J$5) = 0, 0, H12 / INDEX(M12:AF12, $J$5) - 1), 0) -> 0 | N12: 1.3 | O12: 1.4482524
A19: PROFIT AND LOSS
E21: ='FS Qtr'!E9 -> Electricity revenue | F21: ='FS Qtr'!F9 -> 0 | G21: ='FS Qtr'!G$9 -> $ 000s | H21: ='FS Qtr'!H9 -> 371409.68 | J21: =IF(ABS(K21) > TRK_TOL, "tu", "vw") -> vw | K21: =H21 - INDEX(M21:AF21, $J$5) -> 0 | L21: =IF(ABS(K21) > TRK_TOL, IF(INDEX(M21:AF21, $J$5) = 0, 0, H21 / INDEX(M21:AF21, $J$5) - 1), 0) -> 0 | N21: 371409.68 | O21: 371409.68 | P21: 371409.68 | Q21: 371409.68 | R21: 371409.68 | S21: 371409.68 | T21: 371409.68 | U21: 371409.68 | V21: 371409.68 | W21: 371409.68 | X21: 371409.68 | Y21: 371409.68 | Z21: 371409.68 | AA21: 371409.68 | AB21: 371409.68 | AC21: 0
E22: ='FS Qtr'!E10 -> O&M cost | F22: ='FS Qtr'!F10 -> 0 | G22: ='FS Qtr'!G$9 -> $ 000s | H22: ='FS Qtr'!H10 -> -48742.638 | J22: =IF(ABS(K22) > TRK_TOL, "tu", "vw") -> vw | K22: =H22 - INDEX(M22:AF22, $J$5) -> 0 | L22: =IF(ABS(K22) > TRK_TOL, IF(INDEX(M22:AF22, $J$5) = 0, 0, H22 / INDEX(M22:AF22, $J$5) - 1), 0) -> 0 | N22: -48742.638 | O22: -48742.638 | P22: -48742.638 | Q22: -48742.638 | R22: -48742.638 | S22: -48742.638 | T22: -48742.638 | U22: -48742.638 | V22: -48742.638 | W22: -48742.638 | X22: -48742.638 | Y22: -48742.638 | Z22: -48742.638 | AA22: 0 | AB22: 0 | AC22: 0
E23: ='FS Qtr'!E11 -> EBITDA | F23: ='FS Qtr'!F11 -> 0 | G23: ='FS Qtr'!G$9 -> $ 000s | H23: ='FS Qtr'!H11 -> 322667.04 | J23: =IF(ABS(K23) > TRK_TOL, "tu", "vw") -> vw | K23: =H23 - INDEX(M23:AF23, $J$5) -> 0 | L23: =IF(ABS(K23) > TRK_TOL, IF(INDEX(M23:AF23, $J$5) = 0, 0, H23 / INDEX(M23:AF23, $J$5) - 1), 0) -> 0 | N23: 322667.04 | O23: 322667.04 | P23: 322667.04 | Q23: 322667.04 | R23: 322667.04 | S23: 322667.04 | T23: 322667.04 | U23: 322667.04 | V23: 322667.04 | W23: 322667.04 | X23: 322667.04 | Y23: 322667.04 | Z23: 322667.04 | AA23: 371409.68 | AB23: 371409.68 | AC23: 10000
E25: ='FS Qtr'!E13 -> Depreciation of fixed asset | F25: ='FS Qtr'!F13 -> 0 | G25: ='FS Qtr'!G$9 -> $ 000s | H25: ='FS Qtr'!H13 -> -100000 | J25: =IF(ABS(K25) > TRK_TOL, "tu", "vw") -> vw | K25: =H25 - INDEX(M25:AF25, $J$5) -> 0 | L25: =IF(ABS(K25) > TRK_TOL, IF(INDEX(M25:AF25, $J$5) = 0, 0, H25 / INDEX(M25:AF25, $J$5) - 1), 0) -> 0 | N25: -100000 | O25: -100000 | P25: -100000 | Q25: -100000 | R25: -100000 | S25: -100000 | T25: -100000 | U25: -100000 | V25: -100000 | W25: 0 | X25: 0 | Y25: 0 | Z25: 0 | AA25: 0 | AB25: 0 | AC25: 0
E26: ='FS Qtr'!E14 -> EBIT | F26: ='FS Qtr'!F14 -> 0 | G26: ='FS Qtr'!G$9 -> $ 000s | H26: ='FS Qtr'!H14 -> 222667.04 | J26: =IF(ABS(K26) > TRK_TOL, "tu", "vw") -> vw | K26: =H26 - INDEX(M26:AF26, $J$5) -> 0 | L26: =IF(ABS(K26) > TRK_TOL, IF(INDEX(M26:AF26, $J$5) = 0, 0, H26 / INDEX(M26:AF26, $J$5) - 1), 0) -> 0 | N26: 222667.04 | O26: 222667.04 | P26: 222667.04 | Q26: 222667.04 | R26: 222667.04 | S26: 222667.04 | T26: 222667.04 | U26: 222667.04 | V26: 222667.04 | W26: 322667.04 | X26: 322667.04 | Y26: 322667.04 | Z26: 322667.04 | AA26: 371409.68 | AB26: 371409.68 | AC26: 10000
E28: ='FS Qtr'!E16 -> Senior debt interest | F28: ='FS Qtr'!F16 -> 0 | G28: ='FS Qtr'!G$9 -> $ 000s | H28: ='FS Qtr'!H16 -> -26512.862 | J28: =IF(ABS(K28) > TRK_TOL, "tu", "vw") -> vw | K28: =H28 - INDEX(M28:AF28, $J$5) -> 0 | L28: =IF(ABS(K28) > TRK_TOL, IF(INDEX(M28:AF28, $J$5) = 0, 0, H28 / INDEX(M28:AF28, $J$5) - 1), 0) -> 0 | N28: -26512.862 | O28: -23972.181 | P28: -23972.181 | Q28: -21840.583 | R28: 0 | S28: 0 | T28: 0 | U28: 0 | V28: 0 | W28: 0 | X28: 0 | Y28: 0 | Z28: 0 | AA28: 0 | AB28: 0 | AC28: 0
E29: ='FS Qtr'!E17 -> [Refi facility interest] | F29: ='FS Qtr'!F17 -> 0 | G29: ='FS Qtr'!G$9 -> $ 000s | H29: ='FS Qtr'!H17 -> 0 | J29: =IF(ABS(K29) > TRK_TOL, "tu", "vw") -> vw | K29: =H29 - INDEX(M29:AF29, $J$5) -> 0 | L29: =IF(ABS(K29) > TRK_TOL, IF(INDEX(M29:AF29, $J$5) = 0, 0, H29 / INDEX(M29:AF29, $J$5) - 1), 0) -> 0 | N29: 0 | O29: 0 | P29: 0 | Q29: 0 | R29: 0 | S29: 0 | T29: 0 | U29: 0 | V29: 0 | W29: 0 | X29: 0 | Y29: 0 | Z29: 0 | AA29: 0 | AB29: 0 | AC29: 0
E30: ='FS Qtr'!E18 -> [RCF interest expense] | F30: ='FS Qtr'!F18 -> 0 | G30: ='FS Qtr'!G$9 -> $ 000s | H30: ='FS Qtr'!H18 -> 0 | J30: =IF(ABS(K30) > TRK_TOL, "tu", "vw") -> vw | K30: =H30 - INDEX(M30:AF30, $J$5) -> 0 | L30: =IF(ABS(K30) > TRK_TOL, IF(INDEX(M30:AF30, $J$5) = 0, 0, H30 / INDEX(M30:AF30, $J$5) - 1), 0) -> 0 | N30: 0 | O30: 0 | P30: 0 | Q30: 0 | R30: 0 | S30: 0 | T30: 0 | U30: 0 | V30: 0 | W30: 0 | X30: 0 | Y30: 0 | Z30: 0 | AA30: 0 | AB30: 0 | AC30: 0
E31: ='FS Qtr'!E19 -> Profit before tax | F31: ='FS Qtr'!F19 -> 0 | G31: ='FS Qtr'!G$9 -> $ 000s | H31: ='FS Qtr'!H19 -> 196154.18 | J31: =IF(ABS(K31) > TRK_TOL, "tu", "vw") -> vw | K31: =H31 - INDEX(M31:AF31, $J$5) -> 0 | L31: =IF(ABS(K31) > TRK_TOL, IF(INDEX(M31:AF31, $J$5) = 0, 0, H31 / INDEX(M31:AF31, $J$5) - 1), 0) -> 0 | N31: 196154.18 | O31: 198694.86 | P31: 198694.86 | Q31: 200826.46 | R31: 222667.04 | S31: 222667.04 | T31: 222667.04 | U31: 222667.04 | V31: 222667.04 | W31: 322667.04 | X31: 322667.04 | Y31: 322667.04 | Z31: 322667.04 | AA31: 371409.68 | AB31: 371409.68 | AC31: 10000
E33: ='FS Qtr'!E21 -> [Corporate income tax expense] | F33: ='FS Qtr'!F21 -> 0 | G33: ='FS Qtr'!G$9 -> $ 000s | H33: ='FS Qtr'!H21 -> 0 | J33: =IF(ABS(K33) > TRK_TOL, "tu", "vw") -> vw | K33: =H33 - INDEX(M33:AF33, $J$5) -> 0 | L33: =IF(ABS(K33) > TRK_TOL, IF(INDEX(M33:AF33, $J$5) = 0, 0, H33 / INDEX(M33:AF33, $J$5) - 1), 0) -> 0 | N33: 0 | O33: 0 | P33: 0 | Q33: 0 | R33: 0 | S33: 0 | T33: 0 | U33: 0 | V33: 0 | W33: 0 | X33: 0 | Y33: 0 | Z33: 0 | AA33: 0 | AB33: 0 | AC33: 0
E34: ='FS Qtr'!E22 -> Profit after tax | F34: ='FS Qtr'!F22 -> 0 | G34: ='FS Qtr'!G$9 -> $ 000s | H34: ='FS Qtr'!H22 -> 196154.18 | J34: =IF(ABS(K34) > TRK_TOL, "tu", "vw") -> vw | K34: =H34 - INDEX(M34:AF34, $J$5) -> 0 | L34: =IF(ABS(K34) > TRK_TOL, IF(INDEX(M34:AF34, $J$5) = 0, 0, H34 / INDEX(M34:AF34, $J$5) - 1), 0) -> 0 | N34: 196154.18 | O34: 198694.86 | P34: 198694.86 | Q34: 200826.46 | R34: 222667.04 | S34: 222667.04 | T34: 222667.04 | U34: 222667.04 | V34: 222667.04 | W34: 322667.04 | X34: 322667.04 | Y34: 322667.04 | Z34: 322667.04 | AA34: 371409.68 | AB34: 371409.68 | AC34: 10000
E36: ='FS Qtr'!E24 -> Dividends paid | F36: ='FS Qtr'!F24 -> 0 | G36: ='FS Qtr'!G$9 -> $ 000s | H36: ='FS Qtr'!H24 -> -196154.18 | J36: =IF(ABS(K36) > TRK_TOL, "tu", "vw") -> vw | K36: =H36 - INDEX(M36:AF36, $J$5) -> 0 | L36: =IF(ABS(K36) > TRK_TOL, IF(INDEX(M36:AF36, $J$5) = 0, 0, H36 / INDEX(M36:AF36, $J$5) - 1), 0) -> 0 | N36: -196154.18 | O36: -198694.86 | P36: -198694.86 | Q36: -200826.46 | R36: -222667.04 | S36: -222667.04 | T36: -222667.04 | U36: -222667.04 | V36: -222667.04 | W36: -322667.04 | X36: -322667.04 | Y36: 0 | Z36: 0 | AA36: 0 | AB36: 0 | AC36: 0
E37: ='FS Qtr'!E25 -> Net income after dividends | F37: ='FS Qtr'!F25 -> 0 | G37: ='FS Qtr'!G$9 -> $ 000s | H37: ='FS Qtr'!H25 -> 4.8656866e-10 | J37: =IF(ABS(K37) > TRK_TOL, "tu", "vw") -> vw | K37: =H37 - INDEX(M37:AF37, $J$5) -> 0 | L37: =IF(ABS(K37) > TRK_TOL, IF(INDEX(M37:AF37, $J$5) = 0, 0, H37 / INDEX(M37:AF37, $J$5) - 1), 0) -> 0 | N37: 4.8656866e-10 | O37: 4.2634685e-10 | P37: 4.2634685e-10 | Q37: -1.3642421e-12 | R37: -1.3642421e-12 | S37: -1.3642421e-12 | T37: 0 | U37: 0 | V37: 0 | W37: -9.094947e-13 | X37: -9.094947e-13 | Y37: 322667.04 | Z37: 322667.04 | AA37: 371409.68 | AB37: 371409.68 | AC37: 10000
A40: CASH FLOW
E42: ='FS Qtr'!E30 -> Cash received from invoices | F42: ='FS Qtr'!F30 -> 0 | G42: ='FS Qtr'!G$9 -> $ 000s | H42: ='FS Qtr'!H30 -> 371409.68 | J42: =IF(ABS(K42) > TRK_TOL, "tu", "vw") -> vw | K42: =H42 - INDEX(M42:AF42, $J$5) -> 0 | L42: =IF(ABS(K42) > TRK_TOL, IF(INDEX(M42:AF42, $J$5) = 0, 0, H42 / INDEX(M42:AF42, $J$5) - 1), 0) -> 0 | N42: 371409.68 | O42: 371409.68 | P42: 371409.68 | Q42: 371409.68 | R42: 371409.68 | S42: 371409.68 | T42: 371409.68 | U42: 371409.68 | V42: 371409.68 | W42: 371409.68 | X42: 371409.68 | Y42: 371409.68 | Z42: 371409.68 | AA42: 371409.68 | AB42: 0 | AC42: 0
E43: ='FS Qtr'!E31 -> Cash paid for operating costs | F43: ='FS Qtr'!F31 -> 0 | G43: ='FS Qtr'!G$9 -> $ 000s | H43: ='FS Qtr'!H31 -> -48742.638 | J43: =IF(ABS(K43) > TRK_TOL, "tu", "vw") -> vw | K43: =H43 - INDEX(M43:AF43, $J$5) -> 0 | L43: =IF(ABS(K43) > TRK_TOL, IF(INDEX(M43:AF43, $J$5) = 0, 0, H43 / INDEX(M43:AF43, $J$5) - 1), 0) -> 0 | N43: -48742.638 | O43: -48742.638 | P43: -48742.638 | Q43: -48742.638 | R43: -48742.638 | S43: -48742.638 | T43: -48742.638 | U43: -48742.638 | V43: -48742.638 | W43: -48742.638 | X43: -48742.638 | Y43: -48742.638 | Z43: 0 | AA43: 0 | AB43: 0 | AC43: 0
E44: ='FS Qtr'!E32 -> [Corporate income tax expense] | F44: ='FS Qtr'!F32 -> 0 | G44: ='FS Qtr'!G$9 -> $ 000s | H44: ='FS Qtr'!H32 -> 0 | J44: =IF(ABS(K44) > TRK_TOL, "tu", "vw") -> vw | K44: =H44 - INDEX(M44:AF44, $J$5) -> 0 | L44: =IF(ABS(K44) > TRK_TOL, IF(INDEX(M44:AF44, $J$5) = 0, 0, H44 / INDEX(M44:AF44, $J$5) - 1), 0) -> 0 | N44: 0 | O44: 0 | P44: 0 | Q44: 0 | R44: 0 | S44: 0 | T44: 0 | U44: 0 | V44: 0 | W44: 0 | X44: 0 | Y44: 0 | Z44: 0 | AA44: 0 | AB44: 0 | AC44: 0
E45: ='FS Qtr'!E33 -> Cash flow available for senior debt service | F45: ='FS Qtr'!F33 -> 0 | G45: ='FS Qtr'!G$9 -> $ 000s | H45: ='FS Qtr'!H33 -> 322667.04 | J45: =IF(ABS(K45) > TRK_TOL, "tu", "vw") -> vw | K45: =H45 - INDEX(M45:AF45, $J$5) -> 0 | L45: =IF(ABS(K45) > TRK_TOL, IF(INDEX(M45:AF45, $J$5) = 0, 0, H45 / INDEX(M45:AF45, $J$5) - 1), 0) -> 0 | N45: 322667.04 | O45: 322667.04 | P45: 322667.04 | Q45: 322667.04 | R45: 322667.04 | S45: 322667.04 | T45: 322667.04 | U45: 322667.04 | V45: 322667.04 | W45: 322667.04 | X45: 322667.04 | Y45: 322667.04 | Z45: 371409.68 | AA45: 371409.68 | AB45: 10000 | AC45: 10000
E47: ='FS Qtr'!E35 -> Senior debt interest | F47: ='FS Qtr'!F35 -> 0 | G47: ='FS Qtr'!G$9 -> $ 000s | H47: ='FS Qtr'!H35 -> -26512.862 | J47: =IF(ABS(K47) > TRK_TOL, "tu", "vw") -> vw | K47: =H47 - INDEX(M47:AF47, $J$5) -> 0 | L47: =IF(ABS(K47) > TRK_TOL, IF(INDEX(M47:AF47, $J$5) = 0, 0, H47 / INDEX(M47:AF47, $J$5) - 1), 0) -> 0 | N47: -26512.862 | O47: -23972.181 | P47: -23972.181 | Q47: -21840.583 | R47: 0 | S47: 0 | T47: 0 | U47: 0 | V47: 0 | W47: 0 | X47: 0 | Y47: 0 | Z47: 0 | AA47: 0 | AB47: 0 | AC47: 0
E48: ='FS Qtr'!E36 -> Senior debt principal repayment | F48: ='FS Qtr'!F36 -> 0 | G48: ='FS Qtr'!G$9 -> $ 000s | H48: ='FS Qtr'!H36 -> -78175.933 | J48: =IF(ABS(K48) > TRK_TOL, "tu", "vw") -> vw | K48: =H48 - INDEX(M48:AF48, $J$5) -> 0 | L48: =IF(ABS(K48) > TRK_TOL, IF(INDEX(M48:AF48, $J$5) = 0, 0, H48 / INDEX(M48:AF48, $J$5) - 1), 0) -> 0 | N48: -78175.933 | O48: -70000 | P48: -70000 | Q48: -70000 | R48: -70000 | S48: -70000 | T48: 0 | U48: 0 | V48: 0 | W48: 0 | X48: 0 | Y48: 0 | Z48: 0 | AA48: 0 | AB48: 0 | AC48: 0
E49: ='FS Qtr'!E37 -> Cash flow available for refinancing facility | F49: ='FS Qtr'!F37 -> 0 | G49: ='FS Qtr'!G$9 -> $ 000s | H49: ='FS Qtr'!H37 -> 217978.25 | J49: =IF(ABS(K49) > TRK_TOL, "tu", "vw") -> vw | N49: 217978.25 | O49: 228694.86 | P49: 228694.86 | Q49: 230826.46 | R49: 252667.04 | S49: 252667.04 | T49: 322667.04 | U49: 322667.04 | V49: 322667.04 | W49: 322667.04 | X49: 322667.04 | Y49: 322667.04 | Z49: 371409.68 | AA49: 371409.68 | AB49: 10000 | AC49: 10000
E51: ='FS Qtr'!E39 -> [Refi facility drawdown] | F51: ='FS Qtr'!F39 -> 0 | G51: ='FS Qtr'!G$9 -> $ 000s | H51: ='FS Qtr'!H39 -> 0 | J51: =IF(ABS(K51) > TRK_TOL, "tu", "vw") -> vw | K51: =H51 - INDEX(M51:AF51, $J$5) -> 0 | L51: =IF(ABS(K51) > TRK_TOL, IF(INDEX(M51:AF51, $J$5) = 0, 0, H51 / INDEX(M51:AF51, $J$5) - 1), 0) -> 0 | N51: 0 | O51: 0 | P51: 0 | Q51: 0 | R51: 0 | S51: 0 | T51: 0 | U51: 0 | V51: 0 | W51: 0 | X51: 0 | Y51: 0 | Z51: 0 | AA51: 0 | AB51: 0 | AC51: 0
E52: ='FS Qtr'!E40 -> [Refi facility repayment] | F52: ='FS Qtr'!F40 -> 0 | G52: ='FS Qtr'!G$9 -> $ 000s | H52: ='FS Qtr'!H40 -> 0 | J52: =IF(ABS(K52) > TRK_TOL, "tu", "vw") -> vw | K52: =H52 - INDEX(M52:AF52, $J$5) -> 0 | L52: =IF(ABS(K52) > TRK_TOL, IF(INDEX(M52:AF52, $J$5) = 0, 0, H52 / INDEX(M52:AF52, $J$5) - 1), 0) -> 0 | N52: 0 | O52: 0 | P52: 0 | Q52: 0 | R52: 0 | S52: 0 | T52: 0 | U52: 0 | V52: 0 | W52: 0 | X52: 0 | Y52: 0 | Z52: 0 | AA52: 0 | AB52: 0 | AC52: 0
E53: ='FS Qtr'!E41 -> [Refi facility interest] | F53: ='FS Qtr'!F41 -> 0 | G53: ='FS Qtr'!G$9 -> $ 000s | H53: ='FS Qtr'!H41 -> 0 | J53: =IF(ABS(K53) > TRK_TOL, "tu", "vw") -> vw | K53: =H53 - INDEX(M53:AF53, $J$5) -> 0 | L53: =IF(ABS(K53) > TRK_TOL, IF(INDEX(M53:AF53, $J$5) = 0, 0, H53 / INDEX(M53:AF53, $J$5) - 1), 0) -> 0 | N53: 0 | O53: 0 | P53: 0 | Q53: 0 | R53: 0 | S53: 0 | T53: 0 | U53: 0 | V53: 0 | W53: 0 | X53: 0 | Y53: 0 | Z53: 0 | AA53: 0 | AB53: 0 | AC53: 0
E54: ='FS Qtr'!E42 -> Cash flow available for revolving credit facility | F54: ='FS Qtr'!F42 -> 0 | G54: ='FS Qtr'!G$9 -> $ 000s | H54: ='FS Qtr'!H42 -> 217978.25 | J54: =IF(ABS(K54) > TRK_TOL, "tu", "vw") -> vw | K54: =H54 - INDEX(M54:AF54, $J$5) -> 0 | L54: =IF(ABS(K54) > TRK_TOL, IF(INDEX(M54:AF54, $J$5) = 0, 0, H54 / INDEX(M54:AF54, $J$5) - 1), 0) -> 0 | N54: 217978.25 | O54: 228694.86 | P54: 228694.86 | Q54: 230826.46 | R54: 252667.04 | S54: 252667.04 | T54: 322667.04 | U54: 322667.04 | V54: 322667.04 | W54: 322667.04 | X54: 322667.04 | Y54: 322667.04 | Z54: 371409.68 | AA54: 371409.68 | AB54: 10000 | AC54: 10000
E56: ='FS Qtr'!E44 -> [RCF drawdown] | F56: ='FS Qtr'!F44 -> 0 | G56: ='FS Qtr'!G$9 -> $ 000s | H56: ='FS Qtr'!H44 -> 0 | J56: =IF(ABS(K56) > TRK_TOL, "tu", "vw") -> vw | K56: =H56 - INDEX(M56:AF56, $J$5) -> 0 | L56: =IF(ABS(K56) > TRK_TOL, IF(INDEX(M56:AF56, $J$5) = 0, 0, H56 / INDEX(M56:AF56, $J$5) - 1), 0) -> 0 | N56: 0 | O56: 0 | P56: 0 | Q56: 0 | R56: 0 | S56: 0 | T56: 0 | U56: 0 | V56: 0 | W56: 0 | X56: 0 | Y56: 0 | Z56: 0 | AA56: 0 | AB56: 0 | AC56: 0
E57: ='FS Qtr'!E45 -> [RCF repayment] | F57: ='FS Qtr'!F45 -> 0 | G57: ='FS Qtr'!G$9 -> $ 000s | H57: ='FS Qtr'!H45 -> 0 | J57: =IF(ABS(K57) > TRK_TOL, "tu", "vw") -> vw | K57: =H57 - INDEX(M57:AF57, $J$5) -> 0 | L57: =IF(ABS(K57) > TRK_TOL, IF(INDEX(M57:AF57, $J$5) = 0, 0, H57 / INDEX(M57:AF57, $J$5) - 1), 0) -> 0 | N57: 0 | O57: 0 | P57: 0 | Q57: 0 | R57: 0 | S57: 0 | T57: 0 | U57: 0 | V57: 0 | W57: 0 | X57: 0 | Y57: 0 | Z57: 0 | AA57: 0 | AB57: 0 | AC57: 0
E58: ='FS Qtr'!E46 -> [RCF interest expense paid] | F58: ='FS Qtr'!F46 -> 0 | G58: ='FS Qtr'!G$9 -> $ 000s | H58: ='FS Qtr'!H46 -> 0 | J58: =IF(ABS(K58) > TRK_TOL, "tu", "vw") -> vw | K58: =H58 - INDEX(M58:AF58, $J$5) -> 0 | L58: =IF(ABS(K58) > TRK_TOL, IF(INDEX(M58:AF58, $J$5) = 0, 0, H58 / INDEX(M58:AF58, $J$5) - 1), 0) -> 0 | N58: 0 | O58: 0 | P58: 0 | Q58: 0 | R58: 0 | S58: 0 | T58: 0 | U58: 0 | V58: 0 | W58: 0 | X58: 0 | Y58: 0 | Z58: 0 | AA58: 0 | AB58: 0 | AC58: 0
E59: ='FS Qtr'!E47 -> Cash flow available for distribution | F59: ='FS Qtr'!F47 -> 0 | G59: ='FS Qtr'!G$9 -> $ 000s | H59: ='FS Qtr'!H47 -> 217978.25 | J59: =IF(ABS(K59) > TRK_TOL, "tu", "vw") -> vw | K59: =H59 - INDEX(M59:AF59, $J$5) -> 0 | L59: =IF(ABS(K59) > TRK_TOL, IF(INDEX(M59:AF59, $J$5) = 0, 0, H59 / INDEX(M59:AF59, $J$5) - 1), 0) -> 0 | N59: 217978.25 | O59: 228694.86 | P59: 228694.86 | Q59: 230826.46 | R59: 252667.04 | S59: 252667.04 | T59: 322667.04 | U59: 322667.04 | V59: 322667.04 | W59: 322667.04 | X59: 322667.04 | Y59: 322667.04 | Z59: 371409.68 | AA59: 371409.68 | AB59: 10000 | AC59: 10000
E61: ='FS Qtr'!E49 -> Share capital redemption | F61: ='FS Qtr'!F49 -> 0 | G61: ='FS Qtr'!G$9 -> $ 000s | H61: ='FS Qtr'!H49 -> -21824.067 | J61: =IF(ABS(K61) > TRK_TOL, "tu", "vw") -> vw | K61: =H61 - INDEX(M61:AF61, $J$5) -> 0 | L61: =IF(ABS(K61) > TRK_TOL, IF(INDEX(M61:AF61, $J$5) = 0, 0, H61 / INDEX(M61:AF61, $J$5) - 1), 0) -> 0 | N61: -21824.067 | O61: -30000 | P61: -30000 | Q61: -30000 | R61: -30000 | S61: -30000 | T61: -30000 | U61: -100000 | V61: 0 | W61: 0 | X61: 0 | Y61: 0 | Z61: 0 | AA61: 0 | AB61: 0 | AC61: 0
E62: ='FS Qtr'!E50 -> Cash flow available for dividends | F62: ='FS Qtr'!F50 -> 0 | G62: ='FS Qtr'!G$9 -> $ 000s | H62: ='FS Qtr'!H50 -> 196154.18 | J62: =IF(ABS(K62) > TRK_TOL, "tu", "vw") -> vw | N62: 196154.18 | O62: 198694.86 | P62: 198694.86 | Q62: 200826.46 | R62: 222667.04 | S62: 222667.04 | T62: 292667.04 | U62: 222667.04 | V62: 322667.04 | W62: 322667.04 | X62: 322667.04 | Y62: 322667.04 | Z62: 371409.68 | AA62: 371409.68 | AB62: 10000 | AC62: 10000
E64: ='FS Qtr'!E52 -> Dividends paid | F64: ='FS Qtr'!F52 -> 0 | G64: ='FS Qtr'!G$9 -> $ 000s | H64: ='FS Qtr'!H52 -> -196154.18 | J64: =IF(ABS(K64) > TRK_TOL, "tu", "vw") -> vw | K64: =H64 - INDEX(M64:AF64, $J$5) -> 0 | L64: =IF(ABS(K64) > TRK_TOL, IF(INDEX(M64:AF64, $J$5) = 0, 0, H64 / INDEX(M64:AF64, $J$5) - 1), 0) -> 0 | N64: -196154.18 | O64: -198694.86 | P64: -198694.86 | Q64: -200826.46 | R64: -222667.04 | S64: -222667.04 | T64: -222667.04 | U64: -222667.04 | V64: -222667.04 | W64: -322667.04 | X64: -322667.04 | Y64: 0 | Z64: 0 | AA64: 0 | AB64: 0 | AC64: 0
E65: ='FS Qtr'!E53 -> Net cash flow after dividends | F65: ='FS Qtr'!F53 -> 0 | G65: ='FS Qtr'!G$9 -> $ 000s | H65: ='FS Qtr'!H53 -> 0 | J65: =IF(ABS(K65) > TRK_TOL, "tu", "vw") -> vw | N65: 0 | O65: -7.2759576e-12 | P65: -7.2759576e-12 | Q65: -7.2759576e-12 | R65: -7.2759576e-12 | S65: -7.2759576e-12 | T65: 70000 | U65: 3.774403e-11 | V65: 100000 | W65: 0 | X65: 0 | Y65: 322667.04 | Z65: 371409.68 | AA65: 371409.68 | AB65: 10000 | AC65: 10000
A68: OUTPUT ROW TEMPLATE
E69: [Output row template] | J69: =IF(ABS(K69) > TRK_TOL, "tu", "vw") -> vw | K69: =H69 - INDEX(M69:AF69, $J$5) -> 0 | L69: =IF(ABS(K69) > TRK_TOL, IF(INDEX(M69:AF69, $J$5) = 0, 0, H69 / INDEX(M69:AF69, $J$5) - 1), 0) -> 0
A72: MODEL RUN INFO
E73: Time | H73: =NOW() -> 44576.387 | N73: 44576.387 | O73: 44576.372 | P73: 44576.364 | Q73: 44576.304 | R73: 44576.275 | S73: 44576.271 | T73: 44575.401 | U73: 44572.709 | V73: 44572.467 | W73: 44572.375 | X73: 44572.288 | Y73: 44571.375 | Z73: 44571.345 | AA73: 44564.567 | AB73: 44564.438 | AC73: 44564.412 | AD73: 43909.145
E74: Filename | H74: =MID(CELL("filename",$A$1), SEARCH("[", CELL("filename",$A$1)) + 1, SEARCH("]", CELL("filename",$A$1)) - SEARCH("[", CELL("filename",$A$1)) - 1) -> FMH debt8 END 01a.xlsx | N74: FMH debt8 END 01a.xlsx | O74: FMH debt7 END 01a.xlsx | P74: FMH debt6 BEG 01a.xlsx | Q74: FMH debt4 END 01a.xlsx | R74: FMH debt3 END 01a.xlsx | S74: FMH debt2 BEG 01a.xlsx | T74: FMH debt step1 01a.xlsx | U74: FMH scr END 01a.xlsx | V74: FMH dep END 01a.xlsx | W74: FMH IRR END 01a (version 1).xlsb | X74: FMH div END 01a.xlsx | Y74: FMH AP END 01a.xlsx | Z74: FMH Opex END 01a.xlsx | AA74: 4.4 END 01a.xlsx | AB74: 4.3 END 01a.xlsx | AC74: 4.2 END.xlsx | AD74: EFM 01a.xlsx
E76: [do not delete row] | J76: range end
A78: END

Sheet Check
A1: =RIGHT(CELL("filename", A1), LEN(CELL("filename", A1)) - SEARCH("]", CELL("filename", A1))) & " - " & InpC!F3 -> Check - Base case 1
F2: =Check!$F$9 -> 0 | G2: Error chks
F3: =Output!J2 -> 0 | G3: Track chgs
F4: =Check!$F$21 -> 0 | G4: Alerts
F5: Constant | G5: Unit
A7: CHECK SUMMARY
E9: Total checks | F9: =SUM(F10:F16) -> 0 | G9: check
E10: [do not delete this row] | F10: [range start]
E12: ='FS Qtr'!E$82 -> Balance sheet check | F12: ='FS Qtr'!F$82 -> 0 | G12: ='FS Qtr'!G$82 -> check
E13: ='FS Ann'!E$82 -> Annual balance sheet check | F13: ='FS Ann'!F$82 -> 0 | G13: ='FS Ann'!G$82 -> check
E16: [do not delete this row] | F16: [range end]
A19: ALERT SUMMARY
E21: Total alerts | F21: =SUM(F22:F31) -> 0 | G21: alert
E22: [do not delete this row] | F22: [range start]
E31: [do not delete this row] | F31: [range end]

Sheet Tmp
A1: =RIGHT(CELL("filename", A1), LEN(CELL("filename", A1)) - SEARCH("]", CELL("filename", A1))) & " - " & InpC!F3 -> Tmp - Base case 1
E2: =Time!E$25 -> Model period ending | F2: =Check!$F$9 -> 0 | G2: Error chks | J2: =Time!J$25 -> 44104 | K2: =Time!K$25 -> 44196 | L2: =Time!L$25 -> 44286 | M2: =Time!M$25 -> 44377 | N2: =Time!N$25 -> 44469 | O2: =Time!O$25 -> 44561 | P2: =Time!P$25 -> 44651 | Q2: =Time!Q$25 -> 44742 | ... EA2: =Time!EA$25 -> 55153
E3: =Time!E$67 -> Timeline label | F3: =Output!J2 -> 0 | G3: Track chgs | J3: =Time!J$67 -> Pre-fcst | K3: =Time!K$67 -> Pre-fcst | L3: =Time!L$67 -> Fin Close | M3: =Time!M$67 -> Operations | N3: =Time!N$67 -> Operations | O3: =Time!O$67 -> Operations | P3: =Time!P$67 -> Operations | Q3: =Time!Q$67 -> Operations | ... EA3: =Time!EA$67 -> Post ops
E4: =Time!E$42 -> Contract year | F4: =Check!$F$21 -> 0 | G4: Alerts | J4: =Time!J$42 -> 2020 | K4: =Time!K$42 -> 2020 | L4: =Time!L$42 -> 2020 | M4: =Time!M$42 -> 2021 | N4: =Time!N$42 -> 2021 | O4: =Time!O$42 -> 2021 | P4: =Time!P$42 -> 2021 | Q4: =Time!Q$42 -> 2022 | ... EA4: =Time!EA$42 -> 2050
E5: =Time!E$10 -> Model column counter | F5: Constant | G5: Unit | H5: Total | J5: =Time!J$10 -> 1 | K5: =Time!K$10 -> 2 | L5: =Time!L$10 -> 3 | M5: =Time!M$10 -> 4 | N5: =Time!N$10 -> 5 | O5: =Time!O$10 -> 6 | P5: =Time!P$10 -> 7 | Q5: =Time!Q$10 -> 8 | ... EA5: =Time!EA$10 -> 122
E8: [xxx] balance BEG | J8: =I11 -> 0 | K8: =J11 -> 0 | L8: =K11 -> 0 | M8: =L11 -> 0 | N8: =M11 -> 0 | O8: =N11 -> 0 | P8: =O11 -> 0 | Q8: =P11 -> 0 | ... EA8: =DZ11 -> 0
E9: [upward flow]
E10: [downward flow]
E11: [xxx] balance | J11: =J8 + J9 - J10 -> 0 | K11: =K8 + K9 - K10 -> 0 | L11: =L8 + L9 - L10 -> 0 | M11: =M8 + M9 - M10 -> 0 | N11: =N8 + N9 - N10 -> 0 | O11: =O8 + O9 - O10 -> 0 | P11: =P8 + P9 - P10 -> 0 | Q11: =Q8 + Q9 - Q10 -> 0 | ... EA11: =EA8 + EA9 - EA10 -> 0
E14: [xxx] - initial balance | G14: =SMU -> $ 000s
E15: =Time!E$76 -> Financial close date flag | F15: =Time!F$76 -> 0 | G15: =Time!G$76 -> flag | H15: =Time!H$76 -> 1 | I15: =Time!I$76 -> 0 | J15: =Time!J$76 -> 0 | K15: =Time!K$76 -> 0 | L15: =Time!L$76 -> 1 | ... EA15: =Time!EA$76 -> 0
E17: [xxx] balance BEG | G17: =SMU -> $ 000s | J17: =I20 -> 0 | K17: =J20 -> 0 | L17: =K20 -> 0 | M17: =L20 -> 0 | N17: =M20 -> 0 | O17: =N20 -> 0 | P17: =O20 -> 0 | Q17: =P20 -> 0 | ... EA17: =DZ20 -> 0
E18: [upward flow]
E19: [downward flow]
E20: [xxx] balance | G20: =SMU -> $ 000s | J20: =IF( J15 = 1, $F14, J17 + J18 - J19) -> 0 | K20: =IF( K15 = 1, $F14, K17 + K18 - K19) -> 0 | L20: =IF( L15 = 1, $F14, L17 + L18 - L19) -> 0 | M20: =IF( M15 = 1, $F14, M17 + M18 - M19) -> 0 | N20: =IF( N15 = 1, $F14, N17 + N18 - N19) -> 0 | O20: =IF( O15 = 1, $F14, O17 + O18 - O19) -> 0 | P20: =IF( P15 = 1, $F14, P17 + P18 - P19) -> 0 | Q20: =IF( Q15 = 1, $F14, Q17 + Q18 - Q19) -> 0 | ... EA20: =IF( EA15 = 1, $F14, EA17 + EA18 - EA19) -> 0
E23: Sign switch line item POS | G23: =SMU -> $ 000s | H23: =SUM(J23:EA23) -> 12200 | J23: 100 | K23: 100 | L23: 100 | M23: 100 | N23: 100 | O23: 100 | P23: 100 | Q23: 100 | R23: 100 | S23: 100 | T23: 100 | U23: 100 | V23: 100 | W23: 100 | X23: 100 | Y23: 100 | Z23: 100 | AA23: 100 | AB23: 100 | AC23: 100 | AD23: 100 | AE23: 100 | AF23: 100 | AG23: 100 | AH23: 100 | AI23: 100 | AJ23: 100 | AK23: 100 | AL23: 100 | AM23: 100 | AN23: 100 | AO23: 100 | AP23: 100 | AQ23: 100 | AR23: 100 | AS23: 100 | AT23: 100 | AU23: 100 | AV23: 100 | AW23: 100 | AX23: 100 | AY23: 100 | AZ23: 100 | BA23: 100 | BB23: 100 | BC23: 100 | BD23: 100 | BE23: 100 | BF23: 100 | BG23: 100 | BH23: 100 | BI23: 100 | BJ23: 100 | BK23: 100 | BL23: 100 | BM23: 100 | BN23: 100 | BO23: 100 | BP23: 100 | BQ23: 100 | BR23: 100 | BS23: 100 | BT23: 100 | BU23: 100 | BV23: 100 | BW23: 100 | BX23: 100 | BY23: 100 | BZ23: 100 | CA23: 100 | CB23: 100 | CC23: 100 | CD23: 100 | CE23: 100 | CF23: 100 | CG23: 100 | CH23: 100 | CI23: 100 | CJ23: 100 | CK23: 100 | CL23: 100 | CM23: 100 | CN23: 100 | CO23: 100 | CP23: 100 | CQ23: 100 | CR23: 100 | CS23: 100 | CT23: 100 | CU23: 100 | CV23: 100 | CW23: 100 | CX23: 100 | CY23: 100 | CZ23: 100 | DA23: 100 | DB23: 100 | DC23: 100 | DD23: 100 | DE23: 100 | DF23: 100 | DG23: 100 | DH23: 100 | DI23: 100 | DJ23: 100 | DK23: 100 | DL23: 100 | DM23: 100 | DN23: 100 | DO23: 100 | DP23: 100 | DQ23: 100 | DR23: 100 | DS23: 100 | DT23: 100 | DU23: 100 | DV23: 100 | DW23: 100 | DX23: 100 | DY23: 100 | DZ23: 100 | EA23: 100
E24: =LEFT(E23, LEN(E23) - 4) -> Sign switch line item | G24: =SMU -> $ 000s | H24: =SUM(J24:EA24) -> -12200 | J24: =-1 * J23 -> -100 | K24: =-1 * K23 -> -100 | L24: =-1 * L23 -> -100 | M24: =-1 * M23 -> -100 | N24: =-1 * N23 -> -100 | O24: =-1 * O23 -> -100 | P24: =-1 * P23 -> -100 | Q24: =-1 * Q23 -> -100 | ... EA24: =-1 * EA23 -> -100
A28: END
