Workbook
Name BaseCaseIndicator: InpC!$J$7:$S$7
Name CASE_ACTIVE: InpC!$F$4
Name CHK_TOL: InpC!$F$28
Name InputRowTemplate: InpC!$E$41:$S$41
Name InputStored: InpC!$J$3:$S$3
Name SMU: InpC!$F$31
Name TrackActive: Output!$H$5
Name TrackLiveResults: Output!$H$6:$H$71
Name TrackStoredResults: Output!$M$5:$Q$5
Name TRK_TOL: InpC!$F$27

Sheet InpC
A1: =RIGHT(CELL("filename", A1), LEN(CELL("filename", A1)) - SEARCH("]", CELL("filename", A1))) & " - " & $F$3 -> InpC - Base case 1
K2: =IF(K4 = $F4, "q", "") -> q | L2: =IF(L4 = $F4, "q", "") | M2: =IF(M4 = $F4, "q", "") | O2: =IF(O4 = $F4, "q", "") | P2: =IF(P4 = $F4, "q", "") | Q2: =IF(Q4 = $F4, "q", "") | R2: =IF(R4 = $F4, "q", "")
F3: =INDEX(J3:S3,MATCH(F4,J4:S4)) -> Base case 1 | K3: Base case 1 | L3: Base case 2 | M3: Base case 3 | O3: Scenario 1 | P3: Scenario 2 | Q3: Scenario 3 | R3: Scenario 4
E4: Active scenario | F4: 1 | I4: =MATCH(F4, $J$4:$S$4) -> 2 | K4: 1 | L4: 2 | M4: 3 | O4: 5 | P4: 6 | Q4: 7 | R4: 8
E5: Comparison scenario | F5: 1 | I5: =MATCH(F5, $J$4:$S$4) -> 2
E6: Base case | F6: =INDEX(J6:S6,MATCH(F4,J4:S4,0)) -> 1 | I6: =MATCH(F6, $J$4:$S$4) -> 2 | K6: 1 | L6: 2 | M6: 3 | O6: 1 | P6: 1 | Q6: 2 | R6: 2
E7: Input differences | F7: =COUNTIF(I10:I25, "tu") -> 0 | K7: =IF(K6 = $F$6, "Base case", "") -> Base case | L7: =IF(L6 = $F$6, "Base case", "") | M7: =IF(M6 = $F$6, "Base case", "")
F9: Constant | G9: Unit | H9: Source
A11: TIMING ASSUMPTIONS
E13: First date of time rulers | F13: =IF( INDEX(J13:S13, $I$4) = "", INDEX(J13:R13, $I$6), INDEX(J13:S13, $I$4)) -> 44013 | G13: date | I13: {=IF( INDEX(J13:S13, I$5) = "", IF( INDEX(J13:S13, I$6) = F13, "vw", "tu"), IF(INDEX(J13:S13, I$5) = F13, "vw", "tu"))} -> vw | K13: 44013
E14: Annual year end date of first operating period | F14: =IF( INDEX(J14:S14, $I$4) = "", INDEX(J14:R14, $I$6), INDEX(J14:S14, $I$4)) -> 43921 | G14: date | I14: {=IF( INDEX(J14:S14, I$5) = "", IF( INDEX(J14:S14, I$6) = F14, "vw", "tu"), IF(INDEX(J14:S14, I$5) = F14, "vw", "tu"))} -> vw | K14: 43921
E15: Financial year end month number | F15: =IF( INDEX(J15:S15, $I$4) = "", INDEX(J15:R15, $I$6), INDEX(J15:S15, $I$4)) -> 12 | G15: month # | I15: {=IF( INDEX(J15:S15, I$5) = "", IF( INDEX(J15:S15, I$6) = F15, "vw", "tu"), IF(INDEX(J15:S15, I$5) = F15, "vw", "tu"))} -> vw | K15: 12
E16: Length of operating period | F16: =IF( INDEX(J16:S16, $I$4) = "", INDEX(J16:R16, $I$6), INDEX(J16:S16, $I$4)) -> 3 | G16: months | I16: {=IF( INDEX(J16:S16, I$5) = "", IF( INDEX(J16:S16, I$6) = F16, "vw", "tu"), IF(INDEX(J16:S16, I$5) = F16, "vw", "tu"))} -> vw | K16: 3
E18: Acquisition date | F18: =IF( INDEX(J18:S18, $I$4) = "", INDEX(J18:R18, $I$6), INDEX(J18:S18, $I$4)) -> 44286 | G18: date | I18: {=IF( INDEX(J18:S18, I$5) = "", IF( INDEX(J18:S18, I$6) = F18, "vw", "tu"), IF(INDEX(J18:S18, I$5) = F18, "vw", "tu"))} -> vw | K18: 44286
E20: Operating years remaining | F20: =IF( INDEX(J20:S20, $I$4) = "", INDEX(J20:R20, $I$6), INDEX(J20:S20, $I$4)) -> 25 | G20: years | I20: {=IF( INDEX(J20:S20, I$5) = "", IF( INDEX(J20:S20, I$6) = F20, "vw", "tu"), IF(INDEX(J20:S20, I$5) = F20, "vw", "tu"))} -> vw | K20: 25
E21: Contract extension | F21: =IF( INDEX(J21:S21, $I$4) = "", INDEX(J21:R21, $I$6), INDEX(J21:S21, $I$4)) -> 0 | G21: years | I21: {=IF( INDEX(J21:S21, I$5) = "", IF( INDEX(J21:S21, I$6) = F21, "vw", "tu"), IF(INDEX(J21:S21, I$5) = F21, "vw", "tu"))} -> vw | K21: 0
A25: MODEL TECHNICAL INPUTS - DO NOT CHANGE
E27: Model track tolerance level | F27: 0.001 | G27: tolerance
E28: Model check tolerance level | F28: 0.001 | G28: tolerance
E29: Months in year | F29: 12 | G29: months
E30: Number of periods in a year | F30: 4 | G30: periods
E31: Standard Monetary Unit | F31: $ 000s | G31: named "SMU"
E32: US$c / US$ | F32: 100 | G32: US$c / US$
E33: Units in a thousand | F33: 1000 | G33: units
B35: Timeline label
E36: Pre-forecast period | F36: Pre-fcst | G36: label
E37: Financial Close | F37: Fin Close | G37: label
E38: Operations | F38: Operations | G38: label
E39: Post ops | F39: Post ops | G39: label
E41: Input row template for relocation macro | F41: =IF( INDEX(J41:S41, $I$4) = "", INDEX(J41:R41, $I$6), INDEX(J41:S41, $I$4)) -> 0 | G41: unit | I41: {=IF( INDEX(J41:S41, I$5) = "", IF( INDEX(J41:S41, I$6) = F41, "vw", "tu"), IF(INDEX(J41:S41, I$5) = F41, "vw", "tu"))} -> vw
A44: END

Sheet Time
A1: =RIGHT(CELL("filename", A1), LEN(CELL("filename", A1)) - SEARCH("]", CELL("filename", A1))) & " - " & InpC!F3 -> Time - Base case 1
E2: =Time!E$25 -> Model period ending | F2: =Check!$F$9 -> 0 | G2: Error chks | J2: =Time!J$25 -> 44104 | K2: =Time!K$25 -> 44196 | L2: =Time!L$25 -> 44286 | M2: =Time!M$25 -> 44377 | N2: =Time!N$25 -> 44469 | O2: =Time!O$25 -> 44561 | P2: =Time!P$25 -> 44651 | Q2: =Time!Q$25 -> 44742 | ... EA2: =Time!EA$25 -> 55153
E3: =Time!E$67 -> Timeline label | F3: =Output!J2 -> 8 | G3: Track chgs | J3: =Time!J$67 -> Pre-fcst | K3: =Time!K$67 -> Pre-fcst | L3: =Time!L$67 -> Fin Close | M3: =Time!M$67 -> Operations | N3: =Time!N$67 -> Operations | O3: =Time!O$67 -> Operations | P3: =Time!P$67 -> Operations | Q3: =Time!Q$67 -> Operations | ... EA3: =Time!EA$67 -> Post ops
E4: =Time!E$42 -> Contract year | F4: =Check!$F$21 -> 0 | G4: Alerts | J4: =Time!J$42 -> 2020 | K4: =Time!K$42 -> 2020 | L4: =Time!L$42 -> 2020 | M4: =Time!M$42 -> 2021 | N4: =Time!N$42 -> 2021 | O4: =Time!O$42 -> 2021 | P4: =Time!P$42 -> 2021 | Q4: =Time!Q$42 -> 2022 | ... EA4: =Time!EA$42 -> 2050
E5: =Time!E$10 -> Model column counter | F5: Constant | G5: Unit | H5: Total | J5: =Time!J$10 -> 1 | K5: =Time!K$10 -> 2 | L5: =Time!L$10 -> 3 | M5: =Time!M$10 -> 4 | N5: =Time!N$10 -> 5 | O5: =Time!O$10 -> 6 | P5: =Time!P$10 -> 7 | Q5: =Time!Q$10 -> 8 | ... EA5: =Time!EA$10 -> 122
A7: TIME RULER
B9: First model column
E10: Model column counter | G10: counter | J10: =I10 + 1 -> 1 | K10: =J10 + 1 -> 2 | L10: =K10 + 1 -> 3 | M10: =L10 + 1 -> 4 | N10: =M10 + 1 -> 5 | O10: =N10 + 1 -> 6 | P10: =O10 + 1 -> 7 | Q10: =P10 + 1 -> 8 | ... EA10: =DZ10 + 1 -> 122
E11: Model column total | F11: =MAX(J10:EA10) -> 122 | G11: columns
E13: =E$10 -> Model column counter | F13: =F$10 -> 0 | G13: =G$10 -> counter | H13: =H$10 -> 0 | I13: =I$10 -> 0 | J13: =J$10 -> 1 | K13: =K$10 -> 2 | L13: =L$10 -> 3 | ... EA13: =EA$10 -> 122
E14: First model column flag | G14: flag | H14: =SUM(J14:EA14) -> 1 | J14: =IF(J13 = 1, 1, 0) -> 1 | K14: =IF(K13 = 1, 1, 0) -> 0 | L14: =IF(L13 = 1, 1, 0) -> 0 | M14: =IF(M13 = 1, 1, 0) -> 0 | N14: =IF(N13 = 1, 1, 0) -> 0 | O14: =IF(O13 = 1, 1, 0) -> 0 | P14: =IF(P13 = 1, 1, 0) -> 0 | Q14: =IF(Q13 = 1, 1, 0) -> 0 | ... EA14: =IF(EA13 = 1, 1, 0) -> 0
B16: Model period beginning
E17: =InpC!E$13 -> First date of time rulers | F17: =InpC!F$13 -> 44013 | G17: =InpC!G$13 -> date
E18: =InpC!E$16 -> Length of operating period | F18: =InpC!F$16 -> 3 | G18: =InpC!G$16 -> months
E19: =E$14 -> First model column flag | F19: =F$14 -> 0 | G19: =G$14 -> flag | H19: =H$14 -> 1 | I19: =I$14 -> 0 | J19: =J$14 -> 1 | K19: =K$14 -> 0 | L19: =L$14 -> 0 | ... EA19: =EA$14 -> 0
E20: Model period beginning | G20: date | J20: =IF(J19 = 1, $F17, DATE(YEAR(I20), MONTH(I20) + $F18, DAY(1))) -> 44013 | K20: =IF(K19 = 1, $F17, DATE(YEAR(J20), MONTH(J20) + $F18, DAY(1))) -> 44105 | L20: =IF(L19 = 1, $F17, DATE(YEAR(K20), MONTH(K20) + $F18, DAY(1))) -> 44197 | M20: =IF(M19 = 1, $F17, DATE(YEAR(L20), MONTH(L20) + $F18, DAY(1))) -> 44287 | N20: =IF(N19 = 1, $F17, DATE(YEAR(M20), MONTH(M20) + $F18, DAY(1))) -> 44378 | O20: =IF(O19 = 1, $F17, DATE(YEAR(N20), MONTH(N20) + $F18, DAY(1))) -> 44470 | P20: =IF(P19 = 1, $F17, DATE(YEAR(O20), MONTH(O20) + $F18, DAY(1))) -> 44562 | Q20: =IF(Q19 = 1, $F17, DATE(YEAR(P20), MONTH(P20) + $F18, DAY(1))) -> 44652 | ... EA20: =IF(EA19 = 1, $F17, DATE(YEAR(DZ20), MONTH(DZ20) + $F18, DAY(1))) -> 55062
B22: Model period ending
E23: =InpC!E$16 -> Length of operating period | F23: =InpC!F$16 -> 3 | G23: =InpC!G$16 -> months
E24: =E$20 -> Model period beginning | F24: =F$20 -> 0 | G24: =G$20 -> date | H24: =H$20 -> 0 | I24: =I$20 -> 0 | J24: =J$20 -> 44013 | K24: =K$20 -> 44105 | L24: =L$20 -> 44197 | ... EA24: =EA$20 -> 55062
E25: Model period ending | G25: date | J25: =DATE(YEAR(J24), MONTH(J24) + $F23, DAY(J24) -1) -> 44104 | K25: =DATE(YEAR(K24), MONTH(K24) + $F23, DAY(K24) -1) -> 44196 | L25: =DATE(YEAR(L24), MONTH(L24) + $F23, DAY(L24) -1) -> 44286 | M25: =DATE(YEAR(M24), MONTH(M24) + $F23, DAY(M24) -1) -> 44377 | N25: =DATE(YEAR(N24), MONTH(N24) + $F23, DAY(N24) -1) -> 44469 | O25: =DATE(YEAR(O24), MONTH(O24) + $F23, DAY(O24) -1) -> 44561 | P25: =DATE(YEAR(P24), MONTH(P24) + $F23, DAY(P24) -1) -> 44651 | Q25: =DATE(YEAR(Q24), MONTH(Q24) + $F23, DAY(Q24) -1) -> 44742 | ... EA25: =DATE(YEAR(EA24), MONTH(EA24) + $F23, DAY(EA24) -1) -> 55153
B27: Contract year
E28: =InpC!E$18 -> Acquisition date | F28: =InpC!F$18 -> 44286 | G28: =InpC!G$18 -> date
E29: Contract year end month | F29: =MONTH(F28) -> 3 | G29: month
E31: =E$29 -> Contract year end month | F31: =F$29 -> 3 | G31: =G$29 -> month
E32: =E$25 -> Model period ending | F32: =F$25 -> 0 | G32: =G$25 -> date | H32: =H$25 -> 0 | I32: =I$25 -> 0 | J32: =J$25 -> 44104 | K32: =K$25 -> 44196 | L32: =L$25 -> 44286 | ... EA32: =EA$25 -> 55153
E33: End of contract year flag | J33: =IF( MONTH(J32) = $F31, 1, 0) -> 0 | K33: =IF( MONTH(K32) = $F31, 1, 0) -> 0 | L33: =IF( MONTH(L32) = $F31, 1, 0) -> 1 | M33: =IF( MONTH(M32) = $F31, 1, 0) -> 0 | N33: =IF( MONTH(N32) = $F31, 1, 0) -> 0 | O33: =IF( MONTH(O32) = $F31, 1, 0) -> 0 | P33: =IF( MONTH(P32) = $F31, 1, 0) -> 1 | Q33: =IF( MONTH(Q32) = $F31, 1, 0) -> 0 | ... EA33: =IF( MONTH(EA32) = $F31, 1, 0) -> 0
E35: =InpC!E$14 -> Annual year end date of first operating period | F35: =InpC!F$14 -> 43921 | G35: =InpC!G$14 -> date
E36: =InpC!E$29 -> Months in year | F36: =InpC!F$29 -> 12 | G36: =InpC!G$29 -> months
E37: =E$14 -> First model column flag | F37: =F$14 -> 0 | G37: =G$14 -> flag | H37: =H$14 -> 1 | I37: =I$14 -> 0 | J37: =J$14 -> 1 | K37: =K$14 -> 0 | L37: =L$14 -> 0 | ... EA37: =EA$14 -> 0
E38: =E$33 -> End of contract year flag | F38: =F$33 -> 0 | G38: =G$33 -> 0 | H38: =H$33 -> 0 | I38: =I$33 -> 0 | J38: =J$33 -> 0 | K38: =K$33 -> 0 | L38: =L$33 -> 1 | ... EA38: =EA$33 -> 0
E39: Contract year applicable to period | G39: date | J39: =IF( J37 = 1, $F35, IF( I38 = 1, EOMONTH(I39, 12), I39)) -> 43921 | K39: =IF( K37 = 1, $F35, IF( J38 = 1, EOMONTH(J39, 12), J39)) -> 43921 | L39: =IF( L37 = 1, $F35, IF( K38 = 1, EOMONTH(K39, 12), K39)) -> 43921 | M39: =IF( M37 = 1, $F35, IF( L38 = 1, EOMONTH(L39, 12), L39)) -> 44286 | N39: =IF( N37 = 1, $F35, IF( M38 = 1, EOMONTH(M39, 12), M39)) -> 44286 | O39: =IF( O37 = 1, $F35, IF( N38 = 1, EOMONTH(N39, 12), N39)) -> 44286 | P39: =IF( P37 = 1, $F35, IF( O38 = 1, EOMONTH(O39, 12), O39)) -> 44286 | Q39: =IF( Q37 = 1, $F35, IF( P38 = 1, EOMONTH(P39, 12), P39)) -> 44651 | ... EA39: =IF( EA37 = 1, $F35, IF( DZ38 = 1, EOMONTH(DZ39, 12), DZ39)) -> 54878
E41: =E$39 -> Contract year applicable to period | F41: =F$39 -> 0 | G41: =G$39 -> date | H41: =H$39 -> 0 | I41: =I$39 -> 0 | J41: =J$39 -> 43921 | K41: =K$39 -> 43921 | L41: =L$39 -> 43921 | ... EA41: =EA$39 -> 54878
E42: Contract year | G42: year # | J42: =YEAR(J41) -> 2020 | K42: =YEAR(K41) -> 2020 | L42: =YEAR(L41) -> 2020 | M42: =YEAR(M41) -> 2021 | N42: =YEAR(N41) -> 2021 | O42: =YEAR(O41) -> 2021 | P42: =YEAR(P41) -> 2021 | Q42: =YEAR(Q41) -> 2022 | ... EA42: =YEAR(EA41) -> 2050
B44: Annual timeline
E45: =InpC!E$14 -> Annual year end date of first operating period | F45: =InpC!F$14 -> 43921 | G45: =InpC!G$14 -> date
E46: =InpC!E$29 -> Months in year | F46: =InpC!F$29 -> 12 | G46: =InpC!G$29 -> months
E47: =E$14 -> First model column flag | F47: =F$14 -> 0 | G47: =G$14 -> flag | H47: =H$14 -> 1 | I47: =I$14 -> 0 | J47: =J$14 -> 1 | K47: =K$14 -> 0 | L47: =L$14 -> 0 | ... EA47: =EA$14 -> 0
E48: Model period ending - annual | G48: date | J48: =IF(J47 = 1, $F45, EOMONTH(I48, $F46)) -> 43921 | K48: =IF(K47 = 1, $F45, EOMONTH(J48, $F46)) -> 44286 | L48: =IF(L47 = 1, $F45, EOMONTH(K48, $F46)) -> 44651 | M48: =IF(M47 = 1, $F45, EOMONTH(L48, $F46)) -> 45016 | N48: =IF(N47 = 1, $F45, EOMONTH(M48, $F46)) -> 45382 | O48: =IF(O47 = 1, $F45, EOMONTH(N48, $F46)) -> 45747 | P48: =IF(P47 = 1, $F45, EOMONTH(O48, $F46)) -> 46112 | Q48: =IF(Q47 = 1, $F45, EOMONTH(P48, $F46)) -> 46477 | ... EA48: =IF(EA47 = 1, $F45, EOMONTH(DZ48, $F46)) -> 88115
E50: =E$67 -> Timeline label | F50: =F$67 -> 0 | G50: =G$67 -> label | H50: =H$67 -> 0 | I50: =I$67 -> 0 | J50: =J$67 -> Pre-fcst | K50: =K$67 -> Pre-fcst | L50: =L$67 -> Fin Close | ... EA50: =EA$67 -> Post ops
E51: =E$48 -> Model period ending - annual | F51: =F$48 -> 0 | G51: =G$48 -> date | H51: =H$48 -> 0 | I51: =I$48 -> 0 | J51: =J$48 -> 43921 | K51: =K$48 -> 44286 | L51: =L$48 -> 44651 | ... EA51: =EA$48 -> 88115
E52: =E$41 -> Contract year applicable to period | F52: =F$41 -> 0 | G52: =G$41 -> date | H52: =H$41 -> 0 | I52: =I$41 -> 0 | J52: =J$41 -> 43921 | K52: =K$41 -> 43921 | L52: =L$41 -> 43921 | ... EA52: =EA$41 -> 54878
E53: Timeline label - annual | J53: =IF(ISNA(INDEX($J$50:$EA$50,MATCH(J51,$J$52:$EA$52,0))),"Pre-fcst",INDEX($J$50:$EA$50,MATCH(J51,$J$52:$EA$52,0))) -> Pre-fcst | K53: =IF(ISNA(INDEX($J$50:$EA$50,MATCH(K51,$J$52:$EA$52,0))),"Pre-fcst",INDEX($J$50:$EA$50,MATCH(K51,$J$52:$EA$52,0))) -> Operations | L53: =IF(ISNA(INDEX($J$50:$EA$50,MATCH(L51,$J$52:$EA$52,0))),"Pre-fcst",INDEX($J$50:$EA$50,MATCH(L51,$J$52:$EA$52,0))) -> Operations | M53: =IF(ISNA(INDEX($J$50:$EA$50,MATCH(M51,$J$52:$EA$52,0))),"Pre-fcst",INDEX($J$50:$EA$50,MATCH(M51,$J$52:$EA$52,0))) -> Operations | N53: =IF(ISNA(INDEX($J$50:$EA$50,MATCH(N51,$J$52:$EA$52,0))),"Pre-fcst",INDEX($J$50:$EA$50,MATCH(N51,$J$52:$EA$52,0))) -> Operations | O53: =IF(ISNA(INDEX($J$50:$EA$50,MATCH(O51,$J$52:$EA$52,0))),"Pre-fcst",INDEX($J$50:$EA$50,MATCH(O51,$J$52:$EA$52,0))) -> Operations | P53: =IF(ISNA(INDEX($J$50:$EA$50,MATCH(P51,$J$52:$EA$52,0))),"Pre-fcst",INDEX($J$50:$EA$50,MATCH(P51,$J$52:$EA$52,0))) -> Operations | Q53: =IF(ISNA(INDEX($J$50:$EA$50,MATCH(Q51,$J$52:$EA$52,0))),"Pre-fcst",INDEX($J$50:$EA$50,MATCH(Q51,$J$52:$EA$52,0))) -> Operations | ... BC53: =IF(ISNA(INDEX($J$50:$EA$50,MATCH(BC51,$J$52:$EA$52,0))),"Pre-fcst",INDEX($J$50:$EA$50,MATCH(BC51,$J$52:$EA$52,0))) -> Pre-fcst
B55: Quarterly timeline
E56: =E$14 -> First model column flag | F56: =F$14 -> 0 | G56: =G$14 -> flag | H56: =H$14 -> 1 | I56: =I$14 -> 0 | J56: =J$14 -> 1 | K56: =K$14 -> 0 | L56: =L$14 -> 0 | ... EA56: =EA$14 -> 0
E57: =E$76 -> Financial close date flag | F57: =F$76 -> 0 | G57: =G$76 -> flag | H57: =H$76 -> 1 | I57: =I$76 -> 0 | J57: =J$76 -> 0 | K57: =K$76 -> 0 | L57: =L$76 -> 1 | ... EA57: =EA$76 -> 0
E58: =E$80 -> First operating period flag | F58: =F$80 -> 0 | G58: =G$80 -> flag | H58: =H$80 -> 1 | I58: =I$80 -> 0 | J58: =J$80 -> 0 | K58: =K$80 -> 0 | L58: =L$80 -> 0 | ... EA58: =EA$80 -> 0
E59: =E$101 -> First post operating period flag | F59: =F$101 -> 0 | G59: =G$101 -> 0 | H59: =H$101 -> 0 | I59: =I$101 -> 0 | J59: =J$101 -> 0 | K59: =K$101 -> 0 | L59: =L$101 -> 0 | ... EA59: =EA$101 -> 0
E60: Timeline label counter | G60: counter | J60: =I60 + MAX(J56:J59) -> 1 | K60: =J60 + MAX(K56:K59) -> 1 | L60: =K60 + MAX(L56:L59) -> 2 | M60: =L60 + MAX(M56:M59) -> 3 | N60: =M60 + MAX(N56:N59) -> 3 | O60: =N60 + MAX(O56:O59) -> 3 | P60: =O60 + MAX(P56:P59) -> 3 | Q60: =P60 + MAX(Q56:Q59) -> 3 | ... EA60: =DZ60 + MAX(EA56:EA59) -> 4
E62: =InpC!E$36 -> Pre-forecast period | F62: =InpC!F$36 -> Pre-fcst | G62: =InpC!G$36 -> label
E63: =InpC!E$37 -> Financial Close | F63: =InpC!F$37 -> Fin Close | G63: =InpC!G$37 -> label
E64: =InpC!E$38 -> Operations | F64: =InpC!F$38 -> Operations | G64: =InpC!G$38 -> label
E65: =InpC!E$39 -> Post ops | F65: =InpC!F$39 -> Post ops | G65: =InpC!G$39 -> label
E66: =E$60 -> Timeline label counter | F66: =F$60 -> 0 | G66: =G$60 -> counter | H66: =H$60 -> 0 | I66: =I$60 -> 0 | J66: =J$60 -> 1 | K66: =K$60 -> 1 | L66: =L$60 -> 2 | ... EA66: =EA$60 -> 4
E67: Timeline label | G67: label | J67: =INDEX($F62:$F65, J66) -> Pre-fcst | K67: =INDEX($F62:$F65, K66) -> Pre-fcst | L67: =INDEX($F62:$F65, L66) -> Fin Close | M67: =INDEX($F62:$F65, M66) -> Operations | N67: =INDEX($F62:$F65, N66) -> Operations | O67: =INDEX($F62:$F65, O66) -> Operations | P67: =INDEX($F62:$F65, P66) -> Operations | Q67: =INDEX($F62:$F65, Q66) -> Operations | ... EA67: =INDEX($F62:$F65, EA66) -> Post ops
A71: FLAGS
B73: Financial close date flag
E74: =InpC!E$18 -> Acquisition date | F74: =InpC!F$18 -> 44286 | G74: =InpC!G$18 -> date
E75: =E$25 -> Model period ending | F75: =F$25 -> 0 | G75: =G$25 -> date | H75: =H$25 -> 0 | I75: =I$25 -> 0 | J75: =J$25 -> 44104 | K75: =K$25 -> 44196 | L75: =L$25 -> 44286 | ... EA75: =EA$25 -> 55153
E76: Financial close date flag | G76: flag | H76: =SUM(J76:EA76) -> 1 | J76: =IF(AND(I75 < $F74, J75 >= $F74), 1, 0) -> 0 | K76: =IF(AND(J75 < $F74, K75 >= $F74), 1, 0) -> 0 | L76: =IF(AND(K75 < $F74, L75 >= $F74), 1, 0) -> 1 | M76: =IF(AND(L75 < $F74, M75 >= $F74), 1, 0) -> 0 | N76: =IF(AND(M75 < $F74, N75 >= $F74), 1, 0) -> 0 | O76: =IF(AND(N75 < $F74, O75 >= $F74), 1, 0) -> 0 | P76: =IF(AND(O75 < $F74, P75 >= $F74), 1, 0) -> 0 | Q76: =IF(AND(P75 < $F74, Q75 >= $F74), 1, 0) -> 0 | ... EA76: =IF(AND(DZ75 < $F74, EA75 >= $F74), 1, 0) -> 0
B78: First operating period flag
E79: =E$76 -> Financial close date flag | F79: =F$76 -> 0 | G79: =G$76 -> flag | H79: =H$76 -> 1 | I79: =I$76 -> 0 | J79: =J$76 -> 0 | K79: =K$76 -> 0 | L79: =L$76 -> 1 | ... EA79: =EA$76 -> 0
E80: First operating period flag | G80: flag | H80: =SUM(J80:EA80) -> 1 | J80: =I79 -> 0 | K80: =J79 -> 0 | L80: =K79 -> 0 | M80: =L79 -> 1 | N80: =M79 -> 0 | O80: =N79 -> 0 | P80: =O79 -> 0 | Q80: =P79 -> 0 | ... EA80: =DZ79 -> 0
B82: Last operating period flag
E83: =InpC!E$18 -> Acquisition date | F83: =InpC!F$18 -> 44286 | G83: =InpC!G$18 -> date
E84: =InpC!E$20 -> Operating years remaining | F84: =InpC!F$20 -> 25 | G84: =InpC!G$20 -> years
E85: =InpC!E$21 -> Contract extension | F85: =InpC!F$21 -> 0 | G85: =InpC!G$21 -> years
E86: =InpC!E$29 -> Months in year | F86: =InpC!F$29 -> 12 | G86: =InpC!G$29 -> months
E87: End of operating period | F87: =EOMONTH(F83, ((F84 + F85) * F86)) -> 53417 | G87: date
E89: =E$87 -> End of operating period | F89: =F$87 -> 53417 | G89: =G$87 -> date
E90: =E$25 -> Model period ending | F90: =F$25 -> 0 | G90: =G$25 -> date | H90: =H$25 -> 0 | I90: =I$25 -> 0 | J90: =J$25 -> 44104 | K90: =K$25 -> 44196 | L90: =L$25 -> 44286 | ... EA90: =EA$25 -> 55153
E91: Last operating period flag | G91: flag | H91: =SUM(J91:EA91) -> 1 | J91: =IF(J90 = $F89, 1, 0) -> 0 | K91: =IF(K90 = $F89, 1, 0) -> 0 | L91: =IF(L90 = $F89, 1, 0) -> 0 | M91: =IF(M90 = $F89, 1, 0) -> 0 | N91: =IF(N90 = $F89, 1, 0) -> 0 | O91: =IF(O90 = $F89, 1, 0) -> 0 | P91: =IF(P90 = $F89, 1, 0) -> 0 | Q91: =IF(Q90 = $F89, 1, 0) -> 0 | ... EA91: =IF(EA90 = $F89, 1, 0) -> 0
B93: Operating period flag
E94: =InpC!E$18 -> Acquisition date | F94: =InpC!F$18 -> 44286 | G94: =InpC!G$18 -> date
E95: =E$87 -> End of operating period | F95: =F$87 -> 53417 | G95: =G$87 -> date
E96: =E$25 -> Model period ending | F96: =F$25 -> 0 | G96: =G$25 -> date | H96: =H$25 -> 0 | I96: =I$25 -> 0 | J96: =J$25 -> 44104 | K96: =K$25 -> 44196 | L96: =L$25 -> 44286 | ... EA96: =EA$25 -> 55153
E97: Operating period flag | G97: flag | H97: =SUM(J97:EA97) -> 100 | J97: =IF( AND(J96 > $F94, J96 <= $F95), 1, 0) -> 0 | K97: =IF( AND(K96 > $F94, K96 <= $F95), 1, 0) -> 0 | L97: =IF( AND(L96 > $F94, L96 <= $F95), 1, 0) -> 0 | M97: =IF( AND(M96 > $F94, M96 <= $F95), 1, 0) -> 1 | N97: =IF( AND(N96 > $F94, N96 <= $F95), 1, 0) -> 1 | O97: =IF( AND(O96 > $F94, O96 <= $F95), 1, 0) -> 1 | P97: =IF( AND(P96 > $F94, P96 <= $F95), 1, 0) -> 1 | Q97: =IF( AND(Q96 > $F94, Q96 <= $F95), 1, 0) -> 1 | ... EA97: =IF( AND(EA96 > $F94, EA96 <= $F95), 1, 0) -> 0
B99: First post operating period flag
E100: =E$91 -> Last operating period flag | F100: =F$91 -> 0 | G100: =G$91 -> flag | H100: =H$91 -> 1 | I100: =I$91 -> 0 | J100: =J$91 -> 0 | K100: =K$91 -> 0 | L100: =L$91 -> 0 | ... EA100: =EA$91 -> 0
E101: First post operating period flag | J101: =I100 -> 0 | K101: =J100 -> 0 | L101: =K100 -> 0 | M101: =L100 -> 0 | N101: =M100 -> 0 | O101: =N100 -> 0 | P101: =O100 -> 0 | Q101: =P100 -> 0 | ... EA101: =DZ100 -> 0
A105: COUNTERS / PERIOD NUMBERS
B107: Period number
E108: =E$97 -> Operating period flag | F108: =F$97 -> 0 | G108: =G$97 -> flag | H108: =H$97 -> 100 | I108: =I$97 -> 0 | J108: =J$97 -> 0 | K108: =K$97 -> 0 | L108: =L$97 -> 0 | ... EA108: =EA$97 -> 0
E109: Contract period number | J109: =I109 + J108 -> 0 | K109: =J109 + K108 -> 0 | L109: =K109 + L108 -> 0 | M109: =L109 + M108 -> 1 | N109: =M109 + N108 -> 2 | O109: =N109 + O108 -> 3 | P109: =O109 + P108 -> 4 | Q109: =P109 + Q108 -> 5 | ... EA109: =DZ109 + EA108 -> 100
E111: =InpC!E$30 -> Number of periods in a year | F111: =InpC!F$30 -> 4 | G111: =InpC!G$30 -> periods
E112: =E$109 -> Contract period number | F112: =F$109 -> 0 | G112: =G$109 -> 0 | H112: =H$109 -> 0 | I112: =I$109 -> 0 | J112: =J$109 -> 0 | K112: =K$109 -> 0 | L112: =L$109 -> 0 | ... EA112: =EA$109 -> 100
E113: =E$97 -> Operating period flag | F113: =F$97 -> 0 | G113: =G$97 -> flag | H113: =H$97 -> 100 | I113: =I$97 -> 0 | J113: =J$97 -> 0 | K113: =K$97 -> 0 | L113: =L$97 -> 0 | ... EA113: =EA$97 -> 0
E114: Period number | G114: counter | J114: =IF( I114 = $F111, 1, I114 + 1) * J113 -> 0 | K114: =IF( J114 = $F111, 1, J114 + 1) * K113 -> 0 | L114: =IF( K114 = $F111, 1, K114 + 1) * L113 -> 0 | M114: =IF( L114 = $F111, 1, L114 + 1) * M113 -> 1 | N114: =IF( M114 = $F111, 1, M114 + 1) * N113 -> 2 | O114: =IF( N114 = $F111, 1, N114 + 1) * O113 -> 3 | P114: =IF( O114 = $F111, 1, O114 + 1) * P113 -> 4 | Q114: =IF( P114 = $F111, 1, P114 + 1) * Q113 -> 1 | ... EA114: =IF( DZ114 = $F111, 1, DZ114 + 1) * EA113 -> 0
B116: Contract year number
E117: =InpC!E$30 -> Number of periods in a year | F117: =InpC!F$30 -> 4 | G117: =InpC!G$30 -> periods
E118: =E$33 -> End of contract year flag | F118: =F$33 -> 0 | G118: =G$33 -> 0 | H118: =H$33 -> 0 | I118: =I$33 -> 0 | J118: =J$33 -> 0 | K118: =K$33 -> 0 | L118: =L$33 -> 1 | ... EA118: =EA$33 -> 0
E119: =E$97 -> Operating period flag | F119: =F$97 -> 0 | G119: =G$97 -> flag | H119: =H$97 -> 100 | I119: =I$97 -> 0 | J119: =J$97 -> 0 | K119: =K$97 -> 0 | L119: =L$97 -> 0 | ... EA119: =EA$97 -> 0
E120: Contract year number | G120: counter | J120: =(I120 + I118) * J119 -> 0 | K120: =(J120 + J118) * K119 -> 0 | L120: =(K120 + K118) * L119 -> 0 | M120: =(L120 + L118) * M119 -> 1 | N120: =(M120 + M118) * N119 -> 1 | O120: =(N120 + N118) * O119 -> 1 | P120: =(O120 + O118) * P119 -> 1 | Q120: =(P120 + P118) * Q119 -> 2 | ... EA120: =(DZ120 + DZ118) * EA119 -> 0
A129: END

Sheet Equity
A1: =RIGHT(CELL("filename", A1), LEN(CELL("filename", A1)) - SEARCH("]", CELL("filename", A1))) & " - " & InpC!F3 -> Equity - Base case 1
E2: =Time!E$25 -> Model period ending | F2: =Check!$F$9 -> 0 | G2: Error chks | J2: =Time!J$25 -> 44104 | K2: =Time!K$25 -> 44196 | L2: =Time!L$25 -> 44286 | M2: =Time!M$25 -> 44377 | N2: =Time!N$25 -> 44469 | O2: =Time!O$25 -> 44561 | P2: =Time!P$25 -> 44651 | Q2: =Time!Q$25 -> 44742 | ... EA2: =Time!EA$25 -> 55153
E3: =Time!E$67 -> Timeline label | F3: =Output!J2 -> 8 | G3: Track chgs | J3: =Time!J$67 -> Pre-fcst | K3: =Time!K$67 -> Pre-fcst | L3: =Time!L$67 -> Fin Close | M3: =Time!M$67 -> Operations | N3: =Time!N$67 -> Operations | O3: =Time!O$67 -> Operations | P3: =Time!P$67 -> Operations | Q3: =Time!Q$67 -> Operations | ... EA3: =Time!EA$67 -> Post ops
E4: =Time!E$42 -> Contract year | F4: =Check!$F$21 -> 0 | G4: Alerts | J4: =Time!J$42 -> 2020 | K4: =Time!K$42 -> 2020 | L4: =Time!L$42 -> 2020 | M4: =Time!M$42 -> 2021 | N4: =Time!N$42 -> 2021 | O4: =Time!O$42 -> 2021 | P4: =Time!P$42 -> 2021 | Q4: =Time!Q$42 -> 2022 | ... EA4: =Time!EA$42 -> 2050
E5: =Time!E$10 -> Model column counter | F5: Constant | G5: Unit | H5: Total | J5: =Time!J$10 -> 1 | K5: =Time!K$10 -> 2 | L5: =Time!L$10 -> 3 | M5: =Time!M$10 -> 4 | N5: =Time!N$10 -> 5 | O5: =Time!O$10 -> 6 | P5: =Time!P$10 -> 7 | Q5: =Time!Q$10 -> 8 | ... EA5: =Time!EA$10 -> 122
A8: RETAINED EARNINGS
E10: Retained earnings - initial balance | G10: =SMU -> $ 000s
E11: =Time!E$76 -> Financial close date flag | F11: =Time!F$76 -> 0 | G11: =Time!G$76 -> flag | H11: =Time!H$76 -> 1 | I11: =Time!I$76 -> 0 | J11: =Time!J$76 -> 0 | K11: =Time!K$76 -> 0 | L11: =Time!L$76 -> 1 | ... EA11: =Time!EA$76 -> 0
E13: Retained earnings balance BEG | G13: =SMU -> $ 000s | J13: =I16 -> 0 | K13: =J16 -> 0 | L13: =K16 -> 0 | M13: =L16 -> 0 | N13: =M16 -> 100 | O13: =N16 -> 200 | P13: =O16 -> 300 | Q13: =P16 -> 400 | ... EA13: =DZ16 -> 10000
E14: ='FS Qtr'!E$22 -> Profit after tax | F14: ='FS Qtr'!F$22 -> 0 | G14: ='FS Qtr'!G$22 -> $ 000s | H14: ='FS Qtr'!H$22 -> 10000 | I14: ='FS Qtr'!I$22 -> 0 | J14: ='FS Qtr'!J$22 -> 0 | K14: ='FS Qtr'!K$22 -> 0 | L14: ='FS Qtr'!L$22 -> 0 | ... EA14: ='FS Qtr'!EA$22 -> 0
E15: [dividends paid]
E16: Retained earnings balance | G16: =SMU -> $ 000s | J16: =IF( J11 = 1, $F10, J13 + J14 - J15) -> 0 | K16: =IF( K11 = 1, $F10, K13 + K14 - K15) -> 0 | L16: =IF( L11 = 1, $F10, L13 + L14 - L15) -> 0 | M16: =IF( M11 = 1, $F10, M13 + M14 - M15) -> 100 | N16: =IF( N11 = 1, $F10, N13 + N14 - N15) -> 200 | O16: =IF( O11 = 1, $F10, O13 + O14 - O15) -> 300 | P16: =IF( P11 = 1, $F10, P13 + P14 - P15) -> 400 | Q16: =IF( Q11 = 1, $F10, Q13 + Q14 - Q15) -> 500 | ... EA16: =IF( EA11 = 1, $F10, EA13 + EA14 - EA15) -> 10000
A19: RETAINED CASH
E21: Retained cash - initial balance | G21: =SMU -> $ 000s
E22: =Time!E$76 -> Financial close date flag | F22: =Time!F$76 -> 0 | G22: =Time!G$76 -> flag | H22: =Time!H$76 -> 1 | I22: =Time!I$76 -> 0 | J22: =Time!J$76 -> 0 | K22: =Time!K$76 -> 0 | L22: =Time!L$76 -> 1 | ... EA22: =Time!EA$76 -> 0
E24: Retained cash balance BEG | G24: =SMU -> $ 000s | J24: =I27 -> 0 | K24: =J27 -> 0 | L24: =K27 -> 0 | M24: =L27 -> 0 | N24: =M27 -> 100 | O24: =N27 -> 200 | P24: =O27 -> 300 | Q24: =P27 -> 400 | ... EA24: =DZ27 -> 10000
E25: ='FS Qtr'!E$50 -> Cash flow available for dividends | F25: ='FS Qtr'!F$50 -> 0 | G25: ='FS Qtr'!G$50 -> $ 000s | H25: ='FS Qtr'!H$50 -> 10000 | I25: ='FS Qtr'!I$50 -> 0 | J25: ='FS Qtr'!J$50 -> 0 | K25: ='FS Qtr'!K$50 -> 0 | L25: ='FS Qtr'!L$50 -> 0 | ... EA25: ='FS Qtr'!EA$50 -> 0
E26: [dividends paid]
E27: Retained cash balance | G27: =SMU -> $ 000s | J27: =IF( J22 = 1, $F21, J24 + J25 - J26) -> 0 | K27: =IF( K22 = 1, $F21, K24 + K25 - K26) -> 0 | L27: =IF( L22 = 1, $F21, L24 + L25 - L26) -> 0 | M27: =IF( M22 = 1, $F21, M24 + M25 - M26) -> 100 | N27: =IF( N22 = 1, $F21, N24 + N25 - N26) -> 200 | O27: =IF( O22 = 1, $F21, O24 + O25 - O26) -> 300 | P27: =IF( P22 = 1, $F21, P24 + P25 - P26) -> 400 | Q27: =IF( Q22 = 1, $F21, Q24 + Q25 - Q26) -> 500 | ... EA27: =IF( EA22 = 1, $F21, EA24 + EA25 - EA26) -> 10000

Sheet FS Qtr
A1: =RIGHT(CELL("filename", A1), LEN(CELL("filename", A1)) - SEARCH("]", CELL("filename", A1))) & " - " & InpC!F3 -> FS Qtr - Base case 1
E2: =Time!E$25 -> Model period ending | F2: =Check!$F$9 -> 0 | G2: Error chks | J2: =Time!J$25 -> 44104 | K2: =Time!K$25 -> 44196 | L2: =Time!L$25 -> 44286 | M2: =Time!M$25 -> 44377 | N2: =Time!N$25 -> 44469 | O2: =Time!O$25 -> 44561 | P2: =Time!P$25 -> 44651 | Q2: =Time!Q$25 -> 44742 | ... EA2: =Time!EA$25 -> 55153
E3: =Time!E$67 -> Timeline label | F3: =Output!J2 -> 8 | G3: Track chgs | J3: =Time!J$67 -> Pre-fcst | K3: =Time!K$67 -> Pre-fcst | L3: =Time!L$67 -> Fin Close | M3: =Time!M$67 -> Operations | N3: =Time!N$67 -> Operations | O3: =Time!O$67 -> Operations | P3: =Time!P$67 -> Operations | Q3: =Time!Q$67 -> Operations | ... EA3: =Time!EA$67 -> Post ops
E4: =Time!E$42 -> Contract year | F4: =Check!$F$21 -> 0 | G4: Alerts | J4: =Time!J$42 -> 2020 | K4: =Time!K$42 -> 2020 | L4: =Time!L$42 -> 2020 | M4: =Time!M$42 -> 2021 | N4: =Time!N$42 -> 2021 | O4: =Time!O$42 -> 2021 | P4: =Time!P$42 -> 2021 | Q4: =Time!Q$42 -> 2022 | ... EA4: =Time!EA$42 -> 2050
E5: =Time!E$10 -> Model column counter | F5: Constant | G5: Unit | H5: Total | J5: =Time!J$10 -> 1 | K5: =Time!K$10 -> 2 | L5: =Time!L$10 -> 3 | M5: =Time!M$10 -> 4 | N5: =Time!N$10 -> 5 | O5: =Time!O$10 -> 6 | P5: =Time!P$10 -> 7 | Q5: =Time!Q$10 -> 8 | ... EA5: =Time!EA$10 -> 122
A7: INCOME STATEMENT
E9: [Electricity generation revenue] | M9: 100 | N9: 100 | O9: 100 | P9: 100 | Q9: 100 | R9: 100 | S9: 100 | T9: 100 | U9: 100 | V9: 100 | W9: 100 | X9: 100 | Y9: 100 | Z9: 100 | AA9: 100 | AB9: 100 | AC9: 100 | AD9: 100 | AE9: 100 | AF9: 100 | AG9: 100 | AH9: 100 | AI9: 100 | AJ9: 100 | AK9: 100 | AL9: 100 | AM9: 100 | AN9: 100 | AO9: 100 | AP9: 100 | AQ9: 100 | AR9: 100 | AS9: 100 | AT9: 100 | AU9: 100 | AV9: 100 | AW9: 100 | AX9: 100 | AY9: 100 | AZ9: 100 | BA9: 100 | BB9: 100 | BC9: 100 | BD9: 100 | BE9: 100 | BF9: 100 | BG9: 100 | BH9: 100 | BI9: 100 | BJ9: 100 | BK9: 100 | BL9: 100 | BM9: 100 | BN9: 100 | BO9: 100 | BP9: 100 | BQ9: 100 | BR9: 100 | BS9: 100 | BT9: 100 | BU9: 100 | BV9: 100 | BW9: 100 | BX9: 100 | BY9: 100 | BZ9: 100 | CA9: 100 | CB9: 100 | CC9: 100 | CD9: 100 | CE9: 100 | CF9: 100 | CG9: 100 | CH9: 100 | CI9: 100 | CJ9: 100 | CK9: 100 | CL9: 100 | CM9: 100 | CN9: 100 | CO9: 100 | CP9: 100 | CQ9: 100 | CR9: 100 | CS9: 100 | CT9: 100 | CU9: 100 | CV9: 100 | CW9: 100 | CX9: 100 | CY9: 100 | CZ9: 100 | DA9: 100 | DB9: 100 | DC9: 100 | DD9: 100 | DE9: 100 | DF9: 100 | DG9: 100 | DH9: 100
E10: [O&M]
E11: EBITDA | G11: =SMU -> $ 000s | H11: =SUM(J11:EA11) -> 10000 | J11: =SUM(J9:J10) -> 0 | K11: =SUM(K9:K10) -> 0 | L11: =SUM(L9:L10) -> 0 | M11: =SUM(M9:M10) -> 100 | N11: =SUM(N9:N10) -> 100 | O11: =SUM(O9:O10) -> 100 | P11: =SUM(P9:P10) -> 100 | Q11: =SUM(Q9:Q10) -> 100 | ... EA11: =SUM(EA9:EA10) -> 0
E13: [Depreciation of non current assets]
E14: EBIT | G14: =SMU -> $ 000s | H14: =SUM(J14:EA14) -> 10000 | J14: =J11 + SUM(J13:J13) -> 0 | K14: =K11 + SUM(K13:K13) -> 0 | L14: =L11 + SUM(L13:L13) -> 0 | M14: =M11 + SUM(M13:M13) -> 100 | N14: =N11 + SUM(N13:N13) -> 100 | O14: =O11 + SUM(O13:O13) -> 100 | P14: =P11 + SUM(P13:P13) -> 100 | Q14: =Q11 + SUM(Q13:Q13) -> 100 | ... EA14: =EA11 + SUM(EA13:EA13) -> 0
E16: [Senior debt interest]
E17: [Refi facility interest]
E18: [RCF interest expense]
E19: Profit before tax | G19: =SMU -> $ 000s | H19: =SUM(J19:EA19) -> 10000 | J19: =J14 + SUM(J16:J18) -> 0 | K19: =K14 + SUM(K16:K18) -> 0 | L19: =L14 + SUM(L16:L18) -> 0 | M19: =M14 + SUM(M16:M18) -> 100 | N19: =N14 + SUM(N16:N18) -> 100 | O19: =O14 + SUM(O16:O18) -> 100 | P19: =P14 + SUM(P16:P18) -> 100 | Q19: =Q14 + SUM(Q16:Q18) -> 100 | ... EA19: =EA14 + SUM(EA16:EA18) -> 0
E21: [Corporate income tax expense]
E22: Profit after tax | G22: =SMU -> $ 000s | H22: =SUM(J22:EA22) -> 10000 | J22: =J19 + J21 -> 0 | K22: =K19 + K21 -> 0 | L22: =L19 + L21 -> 0 | M22: =M19 + M21 -> 100 | N22: =N19 + N21 -> 100 | O22: =O19 + O21 -> 100 | P22: =P19 + P21 -> 100 | Q22: =Q19 + Q21 -> 100 | ... EA22: =EA19 + EA21 -> 0
E24: [Dividends paid]
E25: Net income | G25: =SMU -> $ 000s | H25: =SUM(J25:EA25) -> 10000 | J25: =J22 + J24 -> 0 | K25: =K22 + K24 -> 0 | L25: =L22 + L24 -> 0 | M25: =M22 + M24 -> 100 | N25: =N22 + N24 -> 100 | O25: =O22 + O24 -> 100 | P25: =P22 + P24 -> 100 | Q25: =Q22 + Q24 -> 100 | ... EA25: =EA22 + EA24 -> 0
A28: CASH FLOW STATEMENT
E30: [Cash received from invoices] | M30: 100 | N30: 100 | O30: 100 | P30: 100 | Q30: 100 | R30: 100 | S30: 100 | T30: 100 | U30: 100 | V30: 100 | W30: 100 | X30: 100 | Y30: 100 | Z30: 100 | AA30: 100 | AB30: 100 | AC30: 100 | AD30: 100 | AE30: 100 | AF30: 100 | AG30: 100 | AH30: 100 | AI30: 100 | AJ30: 100 | AK30: 100 | AL30: 100 | AM30: 100 | AN30: 100 | AO30: 100 | AP30: 100 | AQ30: 100 | AR30: 100 | AS30: 100 | AT30: 100 | AU30: 100 | AV30: 100 | AW30: 100 | AX30: 100 | AY30: 100 | AZ30: 100 | BA30: 100 | BB30: 100 | BC30: 100 | BD30: 100 | BE30: 100 | BF30: 100 | BG30: 100 | BH30: 100 | BI30: 100 | BJ30: 100 | BK30: 100 | BL30: 100 | BM30: 100 | BN30: 100 | BO30: 100 | BP30: 100 | BQ30: 100 | BR30: 100 | BS30: 100 | BT30: 100 | BU30: 100 | BV30: 100 | BW30: 100 | BX30: 100 | BY30: 100 | BZ30: 100 | CA30: 100 | CB30: 100 | CC30: 100 | CD30: 100 | CE30: 100 | CF30: 100 | CG30: 100 | CH30: 100 | CI30: 100 | CJ30: 100 | CK30: 100 | CL30: 100 | CM30: 100 | CN30: 100 | CO30: 100 | CP30: 100 | CQ30: 100 | CR30: 100 | CS30: 100 | CT30: 100 | CU30: 100 | CV30: 100 | CW30: 100 | CX30: 100 | CY30: 100 | CZ30: 100 | DA30: 100 | DB30: 100 | DC30: 100 | DD30: 100 | DE30: 100 | DF30: 100 | DG30: 100 | DH30: 100
E31: [Cash paid for operating costs]
E32: [Corporate income tax expense]
E33: Cash flow available for senior debt service | G33: =SMU -> $ 000s | H33: =SUM(J33:EA33) -> 10000 | J33: =SUM(J30:J32) -> 0 | K33: =SUM(K30:K32) -> 0 | L33: =SUM(L30:L32) -> 0 | M33: =SUM(M30:M32) -> 100 | N33: =SUM(N30:N32) -> 100 | O33: =SUM(O30:O32) -> 100 | P33: =SUM(P30:P32) -> 100 | Q33: =SUM(Q30:Q32) -> 100 | ... EA33: =SUM(EA30:EA32) -> 0
E35: [Senior debt interest]
E36: [Senior debt repayment]
E37: Cash flow available for refinancing facility | G37: =SMU -> $ 000s | H37: =SUM(J37:EA37) -> 10000 | J37: =J33 + SUM(J35:J36) -> 0 | K37: =K33 + SUM(K35:K36) -> 0 | L37: =L33 + SUM(L35:L36) -> 0 | M37: =M33 + SUM(M35:M36) -> 100 | N37: =N33 + SUM(N35:N36) -> 100 | O37: =O33 + SUM(O35:O36) -> 100 | P37: =P33 + SUM(P35:P36) -> 100 | Q37: =Q33 + SUM(Q35:Q36) -> 100 | ... EA37: =EA33 + SUM(EA35:EA36) -> 0
E39: [Refi facility drawdown]
E40: [Refi facility repayment]
E41: [Refi facility interest]
E42: Cash flow available for revolving credit facility | G42: =SMU -> $ 000s | H42: =SUM(J42:EA42) -> 10000 | J42: =J37 + SUM(J39:J41) -> 0 | K42: =K37 + SUM(K39:K41) -> 0 | L42: =L37 + SUM(L39:L41) -> 0 | M42: =M37 + SUM(M39:M41) -> 100 | N42: =N37 + SUM(N39:N41) -> 100 | O42: =O37 + SUM(O39:O41) -> 100 | P42: =P37 + SUM(P39:P41) -> 100 | Q42: =Q37 + SUM(Q39:Q41) -> 100 | ... EA42: =EA37 + SUM(EA39:EA41) -> 0
E44: [RCF drawdown]
E45: [RCF repayment]
E46: [RCF interest expense paid]
E47: Cash available for shareholders | G47: =SMU -> $ 000s | H47: =SUM(J47:EA47) -> 10000 | J47: =J42 + SUM(J44:J46) -> 0 | K47: =K42 + SUM(K44:K46) -> 0 | L47: =L42 + SUM(L44:L46) -> 0 | M47: =M42 + SUM(M44:M46) -> 100 | N47: =N42 + SUM(N44:N46) -> 100 | O47: =O42 + SUM(O44:O46) -> 100 | P47: =P42 + SUM(P44:P46) -> 100 | Q47: =Q42 + SUM(Q44:Q46) -> 100 | ... EA47: =EA42 + SUM(EA44:EA46) -> 0
E49: [Share capital redemption]
E50: Cash flow available for dividends | G50: =SMU -> $ 000s | H50: =SUM(J50:EA50) -> 10000 | J50: =J47 + J49 -> 0 | K50: =K47 + K49 -> 0 | L50: =L47 + L49 -> 0 | M50: =M47 + M49 -> 100 | N50: =N47 + N49 -> 100 | O50: =O47 + O49 -> 100 | P50: =P47 + P49 -> 100 | Q50: =Q47 + Q49 -> 100 | ... EA50: =EA47 + EA49 -> 0
E52: [Dividends paid]
E53: Net cash flow | G53: =SMU -> $ 000s | H53: =SUM(J53:EA53) -> 10000 | J53: =J50 + J52 -> 0 | K53: =K50 + K52 -> 0 | L53: =L50 + L52 -> 0 | M53: =M50 + M52 -> 100 | N53: =N50 + N52 -> 100 | O53: =O50 + O52 -> 100 | P53: =P50 + P52 -> 100 | Q53: =Q50 + Q52 -> 100 | ... EA53: =EA50 + EA52 -> 0
A56: BALANCE SHEET
B58: Non current assets
E59: [Non current assets balance]
E60: Non current assets | G60: =SMU -> $ 000s | J60: =SUM(J59) -> 0 | K60: =SUM(K59) -> 0 | L60: =SUM(L59) -> 0 | M60: =SUM(M59) -> 0 | N60: =SUM(N59) -> 0 | O60: =SUM(O59) -> 0 | P60: =SUM(P59) -> 0 | Q60: =SUM(Q59) -> 0 | ... EA60: =SUM(EA59) -> 0
B62: Current assets
E63: =Equity!E$27 -> Retained cash balance | F63: =Equity!F$27 -> 0 | G63: =Equity!G$27 -> $ 000s | H63: =Equity!H$27 -> 0 | I63: =Equity!I$27 -> 0 | J63: =Equity!J$27 -> 0 | K63: =Equity!K$27 -> 0 | L63: =Equity!L$27 -> 0 | ... EA63: =Equity!EA$27 -> 10000
E64: [Accounts receivable balance]
E65: Current assets | G65: =SMU -> $ 000s | J65: =SUM(J63:J64) -> 0 | K65: =SUM(K63:K64) -> 0 | L65: =SUM(L63:L64) -> 0 | M65: =SUM(M63:M64) -> 100 | N65: =SUM(N63:N64) -> 200 | O65: =SUM(O63:O64) -> 300 | P65: =SUM(P63:P64) -> 400 | Q65: =SUM(Q63:Q64) -> 500 | ... EA65: =SUM(EA63:EA64) -> 10000
E67: Total assets | G67: =SMU -> $ 000s | J67: =J65 + J60 -> 0 | K67: =K65 + K60 -> 0 | L67: =L65 + L60 -> 0 | M67: =M65 + M60 -> 100 | N67: =N65 + N60 -> 200 | O67: =O65 + O60 -> 300 | P67: =P65 + P60 -> 400 | Q67: =Q65 + Q60 -> 500 | ... EA67: =EA65 + EA60 -> 10000
E69: [Accounts payable balance]
E70: [Senior debt balance]
E71: [Refi facility balance]
E72: [RCF balance]
E73: [Share capital balance]
E74: =Equity!E$16 -> Retained earnings balance | F74: =Equity!F$16 -> 0 | G74: =Equity!G$16 -> $ 000s | H74: =Equity!H$16 -> 0 | I74: =Equity!I$16 -> 0 | J74: =Equity!J$16 -> 0 | K74: =Equity!K$16 -> 0 | L74: =Equity!L$16 -> 0 | ... EA74: =Equity!EA$16 -> 10000
E75: Total liabilities | G75: =SMU -> $ 000s | J75: =SUM(J69:J74) -> 0 | K75: =SUM(K69:K74) -> 0 | L75: =SUM(L69:L74) -> 0 | M75: =SUM(M69:M74) -> 100 | N75: =SUM(N69:N74) -> 200 | O75: =SUM(O69:O74) -> 300 | P75: =SUM(P69:P74) -> 400 | Q75: =SUM(Q69:Q74) -> 500 | ... EA75: =SUM(EA69:EA74) -> 10000
A78: BALANCE SHEET CHECK
E80: =E$67 -> Total assets | F80: =F$67 -> 0 | G80: =G$67 -> $ 000s | H80: =H$67 -> 0 | I80: =I$67 -> 0 | J80: =J$67 -> 0 | K80: =K$67 -> 0 | L80: =L$67 -> 0 | ... EA80: =EA$67 -> 10000
E81: =E$75 -> Total liabilities | F81: =F$75 -> 0 | G81: =G$75 -> $ 000s | H81: =H$75 -> 0 | I81: =I$75 -> 0 | J81: =J$75 -> 0 | K81: =K$75 -> 0 | L81: =L$75 -> 0 | ... EA81: =EA$75 -> 10000
E82: Balance sheet check | F82: =IF(SUM(J82:EA82) <> 0, 1, 0) -> 0 | G82: check | J82: =IF(ABS(J80 - J81) > CHK_TOL, 1, 0) -> 0 | K82: =IF(ABS(K80 - K81) > CHK_TOL, 1, 0) -> 0 | L82: =IF(ABS(L80 - L81) > CHK_TOL, 1, 0) -> 0 | M82: =IF(ABS(M80 - M81) > CHK_TOL, 1, 0) -> 0 | N82: =IF(ABS(N80 - N81) > CHK_TOL, 1, 0) -> 0 | O82: =IF(ABS(O80 - O81) > CHK_TOL, 1, 0) -> 0 | P82: =IF(ABS(P80 - P81) > CHK_TOL, 1, 0) -> 0 | Q82: =IF(ABS(Q80 - Q81) > CHK_TOL, 1, 0) -> 0 | ... EA82: =IF(ABS(EA80 - EA81) > CHK_TOL, 1, 0) -> 0
E83: Balance sheet difference | H83: =SUM(J83:EA83) -> 0 | J83: =J80 - J81 -> 0 | K83: =K80 - K81 -> 0 | L83: =L80 - L81 -> 0 | M83: =M80 - M81 -> 0 | N83: =N80 - N81 -> 0 | O83: =O80 - O81 -> 0 | P83: =P80 - P81 -> 0 | Q83: =Q80 - Q81 -> 0 | ... EA83: =EA80 - EA81 -> 0
A87: END

Sheet FS Ann
A1: =RIGHT(CELL("filename", A1), LEN(CELL("filename", A1)) - SEARCH("]", CELL("filename", A1))) & " - " & InpC!F3 -> FS Ann - Base case 1
E2: =Time!E$48 -> Model period ending - annual | F2: =Check!$F$9 -> 0 | G2: Error chks | J2: =Time!J$48 -> 43921 | K2: =Time!K$48 -> 44286 | L2: =Time!L$48 -> 44651 | M2: =Time!M$48 -> 45016 | N2: =Time!N$48 -> 45382 | O2: =Time!O$48 -> 45747 | P2: =Time!P$48 -> 46112 | Q2: =Time!Q$48 -> 46477 | ... AN2: =Time!AN$48 -> 54878
E3: =Time!E$53 -> Timeline label - annual | F3: =Output!J2 -> 8 | G3: Track chgs | J3: =Time!J$53 -> Pre-fcst | K3: =Time!K$53 -> Operations | L3: =Time!L$53 -> Operations | M3: =Time!M$53 -> Operations | N3: =Time!N$53 -> Operations | O3: =Time!O$53 -> Operations | P3: =Time!P$53 -> Operations | Q3: =Time!Q$53 -> Operations | ... AN3: =Time!AN$53 -> Post ops
E4: =Time!E$42 -> Contract year | F4: =Check!$F$21 -> 0 | G4: Alerts | J4: =YEAR(J2) -> 2020 | K4: =YEAR(K2) -> 2021 | L4: =YEAR(L2) -> 2022 | M4: =YEAR(M2) -> 2023 | N4: =YEAR(N2) -> 2024 | O4: =YEAR(O2) -> 2025 | P4: =YEAR(P2) -> 2026 | Q4: =YEAR(Q2) -> 2027 | ... AN4: =YEAR(AN2) -> 2050
E5: =Time!E$10 -> Model column counter | F5: Constant | G5: Unit | H5: Total | J5: =Time!J$10 -> 1 | K5: =Time!K$10 -> 2 | L5: =Time!L$10 -> 3 | M5: =Time!M$10 -> 4 | N5: =Time!N$10 -> 5 | O5: =Time!O$10 -> 6 | P5: =Time!P$10 -> 7 | Q5: =Time!Q$10 -> 8 | ... AN5: =Time!AN$10 -> 31
A7: INCOME STATEMENT
E9: ='FS Qtr'!E9 -> [Electricity generation revenue] | F9: ='FS Qtr'!F9 -> 0 | G9: ='FS Qtr'!G9 -> 0 | H9: =SUM(J9:AN9) -> 10000 | J9: =SUMIFS('FS Qtr'!$J9:$EA9, 'FS Qtr'!$J$4:$EA$4, 'FS Ann'!J$4) -> 0 | K9: =SUMIFS('FS Qtr'!$J9:$EA9, 'FS Qtr'!$J$4:$EA$4, 'FS Ann'!K$4) -> 400 | L9: =SUMIFS('FS Qtr'!$J9:$EA9, 'FS Qtr'!$J$4:$EA$4, 'FS Ann'!L$4) -> 400 | M9: =SUMIFS('FS Qtr'!$J9:$EA9, 'FS Qtr'!$J$4:$EA$4, 'FS Ann'!M$4) -> 400 | N9: =SUMIFS('FS Qtr'!$J9:$EA9, 'FS Qtr'!$J$4:$EA$4, 'FS Ann'!N$4) -> 400 | O9: =SUMIFS('FS Qtr'!$J9:$EA9, 'FS Qtr'!$J$4:$EA$4, 'FS Ann'!O$4) -> 400 | P9: =SUMIFS('FS Qtr'!$J9:$EA9, 'FS Qtr'!$J$4:$EA$4, 'FS Ann'!P$4) -> 400 | Q9: =SUMIFS('FS Qtr'!$J9:$EA9, 'FS Qtr'!$J$4:$EA$4, 'FS Ann'!Q$4) -> 400 | ... AN9: =SUMIFS('FS Qtr'!$J9:$EA9, 'FS Qtr'!$J$4:$EA$4, 'FS Ann'!AN$4) -> 0
E10: ='FS Qtr'!E10 -> [O&M] | F10: ='FS Qtr'!F10 -> 0 | G10: ='FS Qtr'!G10 -> 0 | H10: =SUM(J10:AN10) -> 0 | J10: =SUMIFS('FS Qtr'!$J10:$EA10, 'FS Qtr'!$J$4:$EA$4, 'FS Ann'!J$4) -> 0 | K10: =SUMIFS('FS Qtr'!$J10:$EA10, 'FS Qtr'!$J$4:$EA$4, 'FS Ann'!K$4) -> 0 | L10: =SUMIFS('FS Qtr'!$J10:$EA10, 'FS Qtr'!$J$4:$EA$4, 'FS Ann'!L$4) -> 0 | M10: =SUMIFS('FS Qtr'!$J10:$EA10, 'FS Qtr'!$J$4:$EA$4, 'FS Ann'!M$4) -> 0 | N10: =SUMIFS('FS Qtr'!$J10:$EA10, 'FS Qtr'!$J$4:$EA$4, 'FS Ann'!N$4) -> 0 | O10: =SUMIFS('FS Qtr'!$J10:$EA10, 'FS Qtr'!$J$4:$EA$4, 'FS Ann'!O$4) -> 0 | P10: =SUMIFS('FS Qtr'!$J10:$EA10, 'FS Qtr'!$J$4:$EA$4, 'FS Ann'!P$4) -> 0 | Q10: =SUMIFS('FS Qtr'!$J10:$EA10, 'FS Qtr'!$J$4:$EA$4, 'FS Ann'!Q$4) -> 0 | ... AN10: =SUMIFS('FS Qtr'!$J10:$EA10, 'FS Qtr'!$J$4:$EA$4, 'FS Ann'!AN$4) -> 0
E11: EBITDA | G11: =SMU -> $ 000s | H11: =SUM(J11:AN11) -> 10000 | J11: =SUM(J9:J10) -> 0 | K11: =SUM(K9:K10) -> 400 | L11: =SUM(L9:L10) -> 400 | M11: =SUM(M9:M10) -> 400 | N11: =SUM(N9:N10) -> 400 | O11: =SUM(O9:O10) -> 400 | P11: =SUM(P9:P10) -> 400 | Q11: =SUM(Q9:Q10) -> 400 | ... AN11: =SUM(AN9:AN10) -> 0
E13: ='FS Qtr'!E13 -> [Depreciation of non current assets] | F13: ='FS Qtr'!F13 -> 0 | G13: ='FS Qtr'!G13 -> 0 | H13: =SUM(J13:AN13) -> 0 | J13: =SUMIFS('FS Qtr'!$J13:$EA13, 'FS Qtr'!$J$4:$EA$4, 'FS Ann'!J$4) -> 0 | K13: =SUMIFS('FS Qtr'!$J13:$EA13, 'FS Qtr'!$J$4:$EA$4, 'FS Ann'!K$4) -> 0 | L13: =SUMIFS('FS Qtr'!$J13:$EA13, 'FS Qtr'!$J$4:$EA$4, 'FS Ann'!L$4) -> 0 | M13: =SUMIFS('FS Qtr'!$J13:$EA13, 'FS Qtr'!$J$4:$EA$4, 'FS Ann'!M$4) -> 0 | N13: =SUMIFS('FS Qtr'!$J13:$EA13, 'FS Qtr'!$J$4:$EA$4, 'FS Ann'!N$4) -> 0 | O13: =SUMIFS('FS Qtr'!$J13:$EA13, 'FS Qtr'!$J$4:$EA$4, 'FS Ann'!O$4) -> 0 | P13: =SUMIFS('FS Qtr'!$J13:$EA13, 'FS Qtr'!$J$4:$EA$4, 'FS Ann'!P$4) -> 0 | Q13: =SUMIFS('FS Qtr'!$J13:$EA13, 'FS Qtr'!$J$4:$EA$4, 'FS Ann'!Q$4) -> 0 | ... AN13: =SUMIFS('FS Qtr'!$J13:$EA13, 'FS Qtr'!$J$4:$EA$4, 'FS Ann'!AN$4) -> 0
E14: EBIT | G14: =SMU -> $ 000s | H14: =SUM(J14:AN14) -> 10000 | J14: =J11 + J13 -> 0 | K14: =K11 + K13 -> 400 | L14: =L11 + L13 -> 400 | M14: =M11 + M13 -> 400 | N14: =N11 + N13 -> 400 | O14: =O11 + O13 -> 400 | P14: =P11 + P13 -> 400 | Q14: =Q11 + Q13 -> 400 | ... AN14: =AN11 + AN13 -> 0
E16: ='FS Qtr'!E16 -> [Senior debt interest] | F16: ='FS Qtr'!F16 -> 0 | G16: ='FS Qtr'!G16 -> 0 | H16: =SUM(J16:AN16) -> 0 | J16: =SUMIFS('FS Qtr'!$J16:$EA16, 'FS Qtr'!$J$4:$EA$4, 'FS Ann'!J$4) -> 0 | K16: =SUMIFS('FS Qtr'!$J16:$EA16, 'FS Qtr'!$J$4:$EA$4, 'FS Ann'!K$4) -> 0 | L16: =SUMIFS('FS Qtr'!$J16:$EA16, 'FS Qtr'!$J$4:$EA$4, 'FS Ann'!L$4) -> 0 | M16: =SUMIFS('FS Qtr'!$J16:$EA16, 'FS Qtr'!$J$4:$EA$4, 'FS Ann'!M$4) -> 0 | N16: =SUMIFS('FS Qtr'!$J16:$EA16, 'FS Qtr'!$J$4:$EA$4, 'FS Ann'!N$4) -> 0 | O16: =SUMIFS('FS Qtr'!$J16:$EA16, 'FS Qtr'!$J$4:$EA$4, 'FS Ann'!O$4) -> 0 | P16: =SUMIFS('FS Qtr'!$J16:$EA16, 'FS Qtr'!$J$4:$EA$4, 'FS Ann'!P$4) -> 0 | Q16: =SUMIFS('FS Qtr'!$J16:$EA16, 'FS Qtr'!$J$4:$EA$4, 'FS Ann'!Q$4) -> 0 | ... AN16: =SUMIFS('FS Qtr'!$J16:$EA16, 'FS Qtr'!$J$4:$EA$4, 'FS Ann'!AN$4) -> 0
E17: ='FS Qtr'!E17 -> [Refi facility interest] | F17: ='FS Qtr'!F17 -> 0 | G17: ='FS Qtr'!G17 -> 0 | H17: =SUM(J17:AN17) -> 0 | J17: =SUMIFS('FS Qtr'!$J17:$EA17, 'FS Qtr'!$J$4:$EA$4, 'FS Ann'!J$4) -> 0 | K17: =SUMIFS('FS Qtr'!$J17:$EA17, 'FS Qtr'!$J$4:$EA$4, 'FS Ann'!K$4) -> 0 | L17: =SUMIFS('FS Qtr'!$J17:$EA17, 'FS Qtr'!$J$4:$EA$4, 'FS Ann'!L$4) -> 0 | M17: =SUMIFS('FS Qtr'!$J17:$EA17, 'FS Qtr'!$J$4:$EA$4, 'FS Ann'!M$4) -> 0 | N17: =SUMIFS('FS Qtr'!$J17:$EA17, 'FS Qtr'!$J$4:$EA$4, 'FS Ann'!N$4) -> 0 | O17: =SUMIFS('FS Qtr'!$J17:$EA17, 'FS Qtr'!$J$4:$EA$4, 'FS Ann'!O$4) -> 0 | P17: =SUMIFS('FS Qtr'!$J17:$EA17, 'FS Qtr'!$J$4:$EA$4, 'FS Ann'!P$4) -> 0 | Q17: =SUMIFS('FS Qtr'!$J17:$EA17, 'FS Qtr'!$J$4:$EA$4, 'FS Ann'!Q$4) -> 0 | ... AN17: =SUMIFS('FS Qtr'!$J17:$EA17, 'FS Qtr'!$J$4:$EA$4, 'FS Ann'!AN$4) -> 0
E18: ='FS Qtr'!E18 -> [RCF interest expense] | F18: ='FS Qtr'!F18 -> 0 | G18: ='FS Qtr'!G18 -> 0 | H18: =SUM(J18:AN18) -> 0 | J18: =SUMIFS('FS Qtr'!$J18:$EA18, 'FS Qtr'!$J$4:$EA$4, 'FS Ann'!J$4) -> 0 | K18: =SUMIFS('FS Qtr'!$J18:$EA18, 'FS Qtr'!$J$4:$EA$4, 'FS Ann'!K$4) -> 0 | L18: =SUMIFS('FS Qtr'!$J18:$EA18, 'FS Qtr'!$J$4:$EA$4, 'FS Ann'!L$4) -> 0 | M18: =SUMIFS('FS Qtr'!$J18:$EA18, 'FS Qtr'!$J$4:$EA$4, 'FS Ann'!M$4) -> 0 | N18: =SUMIFS('FS Qtr'!$J18:$EA18, 'FS Qtr'!$J$4:$EA$4, 'FS Ann'!N$4) -> 0 | O18: =SUMIFS('FS Qtr'!$J18:$EA18, 'FS Qtr'!$J$4:$EA$4, 'FS Ann'!O$4) -> 0 | P18: =SUMIFS('FS Qtr'!$J18:$EA18, 'FS Qtr'!$J$4:$EA$4, 'FS Ann'!P$4) -> 0 | Q18: =SUMIFS('FS Qtr'!$J18:$EA18, 'FS Qtr'!$J$4:$EA$4, 'FS Ann'!Q$4) -> 0 | ... AN18: =SUMIFS('FS Qtr'!$J18:$EA18, 'FS Qtr'!$J$4:$EA$4, 'FS Ann'!AN$4) -> 0
E19: EBT | G19: =SMU -> $ 000s | H19: =SUM(J19:AN19) -> 10000 | J19: =J14 + SUM(J16:J18) -> 0 | K19: =K14 + SUM(K16:K18) -> 400 | L19: =L14 + SUM(L16:L18) -> 400 | M19: =M14 + SUM(M16:M18) -> 400 | N19: =N14 + SUM(N16:N18) -> 400 | O19: =O14 + SUM(O16:O18) -> 400 | P19: =P14 + SUM(P16:P18) -> 400 | Q19: =Q14 + SUM(Q16:Q18) -> 400 | ... AN19: =AN14 + SUM(AN16:AN18) -> 0
E21: ='FS Qtr'!E21 -> [Corporate income tax expense] | F21: ='FS Qtr'!F21 -> 0 | G21: ='FS Qtr'!G21 -> 0 | H21: =SUM(J21:AN21) -> 0 | J21: =SUMIFS('FS Qtr'!$J21:$EA21, 'FS Qtr'!$J$4:$EA$4, 'FS Ann'!J$4) -> 0 | K21: =SUMIFS('FS Qtr'!$J21:$EA21, 'FS Qtr'!$J$4:$EA$4, 'FS Ann'!K$4) -> 0 | L21: =SUMIFS('FS Qtr'!$J21:$EA21, 'FS Qtr'!$J$4:$EA$4, 'FS Ann'!L$4) -> 0 | M21: =SUMIFS('FS Qtr'!$J21:$EA21, 'FS Qtr'!$J$4:$EA$4, 'FS Ann'!M$4) -> 0 | N21: =SUMIFS('FS Qtr'!$J21:$EA21, 'FS Qtr'!$J$4:$EA$4, 'FS Ann'!N$4) -> 0 | O21: =SUMIFS('FS Qtr'!$J21:$EA21, 'FS Qtr'!$J$4:$EA$4, 'FS Ann'!O$4) -> 0 | P21: =SUMIFS('FS Qtr'!$J21:$EA21, 'FS Qtr'!$J$4:$EA$4, 'FS Ann'!P$4) -> 0 | Q21: =SUMIFS('FS Qtr'!$J21:$EA21, 'FS Qtr'!$J$4:$EA$4, 'FS Ann'!Q$4) -> 0 | ... AN21: =SUMIFS('FS Qtr'!$J21:$EA21, 'FS Qtr'!$J$4:$EA$4, 'FS Ann'!AN$4) -> 0
E22: EBT | G22: =SMU -> $ 000s | H22: =SUM(J22:AN22) -> 10000 | J22: =J19 + J21 -> 0 | K22: =K19 + K21 -> 400 | L22: =L19 + L21 -> 400 | M22: =M19 + M21 -> 400 | N22: =N19 + N21 -> 400 | O22: =O19 + O21 -> 400 | P22: =P19 + P21 -> 400 | Q22: =Q19 + Q21 -> 400 | ... AN22: =AN19 + AN21 -> 0
E24: ='FS Qtr'!E24 -> [Dividends paid] | F24: ='FS Qtr'!F24 -> 0 | G24: ='FS Qtr'!G24 -> 0 | H24: =SUM(J24:AN24) -> 0 | J24: =SUMIFS('FS Qtr'!$J24:$EA24, 'FS Qtr'!$J$4:$EA$4, 'FS Ann'!J$4) -> 0 | K24: =SUMIFS('FS Qtr'!$J24:$EA24, 'FS Qtr'!$J$4:$EA$4, 'FS Ann'!K$4) -> 0 | L24: =SUMIFS('FS Qtr'!$J24:$EA24, 'FS Qtr'!$J$4:$EA$4, 'FS Ann'!L$4) -> 0 | M24: =SUMIFS('FS Qtr'!$J24:$EA24, 'FS Qtr'!$J$4:$EA$4, 'FS Ann'!M$4) -> 0 | N24: =SUMIFS('FS Qtr'!$J24:$EA24, 'FS Qtr'!$J$4:$EA$4, 'FS Ann'!N$4) -> 0 | O24: =SUMIFS('FS Qtr'!$J24:$EA24, 'FS Qtr'!$J$4:$EA$4, 'FS Ann'!O$4) -> 0 | P24: =SUMIFS('FS Qtr'!$J24:$EA24, 'FS Qtr'!$J$4:$EA$4, 'FS Ann'!P$4) -> 0 | Q24: =SUMIFS('FS Qtr'!$J24:$EA24, 'FS Qtr'!$J$4:$EA$4, 'FS Ann'!Q$4) -> 0 | ... AN24: =SUMIFS('FS Qtr'!$J24:$EA24, 'FS Qtr'!$J$4:$EA$4, 'FS Ann'!AN$4) -> 0
E25: Net income | G25: =SMU -> $ 000s | H25: =SUM(J25:AN25) -> 10000 | J25: =J22 + J24 -> 0 | K25: =K22 + K24 -> 400 | L25: =L22 + L24 -> 400 | M25: =M22 + M24 -> 400 | N25: =N22 + N24 -> 400 | O25: =O22 + O24 -> 400 | P25: =P22 + P24 -> 400 | Q25: =Q22 + Q24 -> 400 | ... AN25: =AN22 + AN24 -> 0
A28: CASH FLOW STATEMENT
E30: ='FS Qtr'!E30 -> [Cash received from invoices] | F30: ='FS Qtr'!F30 -> 0 | G30: ='FS Qtr'!G30 -> 0 | H30: =SUM(J30:AN30) -> 10000 | J30: =SUMIFS('FS Qtr'!$J30:$EA30, 'FS Qtr'!$J$4:$EA$4, 'FS Ann'!J$4) -> 0 | K30: =SUMIFS('FS Qtr'!$J30:$EA30, 'FS Qtr'!$J$4:$EA$4, 'FS Ann'!K$4) -> 400 | L30: =SUMIFS('FS Qtr'!$J30:$EA30, 'FS Qtr'!$J$4:$EA$4, 'FS Ann'!L$4) -> 400 | M30: =SUMIFS('FS Qtr'!$J30:$EA30, 'FS Qtr'!$J$4:$EA$4, 'FS Ann'!M$4) -> 400 | N30: =SUMIFS('FS Qtr'!$J30:$EA30, 'FS Qtr'!$J$4:$EA$4, 'FS Ann'!N$4) -> 400 | O30: =SUMIFS('FS Qtr'!$J30:$EA30, 'FS Qtr'!$J$4:$EA$4, 'FS Ann'!O$4) -> 400 | P30: =SUMIFS('FS Qtr'!$J30:$EA30, 'FS Qtr'!$J$4:$EA$4, 'FS Ann'!P$4) -> 400 | Q30: =SUMIFS('FS Qtr'!$J30:$EA30, 'FS Qtr'!$J$4:$EA$4, 'FS Ann'!Q$4) -> 400 | ... AN30: =SUMIFS('FS Qtr'!$J30:$EA30, 'FS Qtr'!$J$4:$EA$4, 'FS Ann'!AN$4) -> 0
E31: ='FS Qtr'!E31 -> [Cash paid for operating costs] | F31: ='FS Qtr'!F31 -> 0 | G31: ='FS Qtr'!G31 -> 0 | H31: =SUM(J31:AN31) -> 0 | J31: =SUMIFS('FS Qtr'!$J31:$EA31, 'FS Qtr'!$J$4:$EA$4, 'FS Ann'!J$4) -> 0 | K31: =SUMIFS('FS Qtr'!$J31:$EA31, 'FS Qtr'!$J$4:$EA$4, 'FS Ann'!K$4) -> 0 | L31: =SUMIFS('FS Qtr'!$J31:$EA31, 'FS Qtr'!$J$4:$EA$4, 'FS Ann'!L$4) -> 0 | M31: =SUMIFS('FS Qtr'!$J31:$EA31, 'FS Qtr'!$J$4:$EA$4, 'FS Ann'!M$4) -> 0 | N31: =SUMIFS('FS Qtr'!$J31:$EA31, 'FS Qtr'!$J$4:$EA$4, 'FS Ann'!N$4) -> 0 | O31: =SUMIFS('FS Qtr'!$J31:$EA31, 'FS Qtr'!$J$4:$EA$4, 'FS Ann'!O$4) -> 0 | P31: =SUMIFS('FS Qtr'!$J31:$EA31, 'FS Qtr'!$J$4:$EA$4, 'FS Ann'!P$4) -> 0 | Q31: =SUMIFS('FS Qtr'!$J31:$EA31, 'FS Qtr'!$J$4:$EA$4, 'FS Ann'!Q$4) -> 0 | ... AN31: =SUMIFS('FS Qtr'!$J31:$EA31, 'FS Qtr'!$J$4:$EA$4, 'FS Ann'!AN$4) -> 0
E32: ='FS Qtr'!E32 -> [Corporate income tax expense] | F32: ='FS Qtr'!F32 -> 0 | G32: ='FS Qtr'!G32 -> 0 | H32: =SUM(J32:AN32) -> 0 | J32: =SUMIFS('FS Qtr'!$J32:$EA32, 'FS Qtr'!$J$4:$EA$4, 'FS Ann'!J$4) -> 0 | K32: =SUMIFS('FS Qtr'!$J32:$EA32, 'FS Qtr'!$J$4:$EA$4, 'FS Ann'!K$4) -> 0 | L32: =SUMIFS('FS Qtr'!$J32:$EA32, 'FS Qtr'!$J$4:$EA$4, 'FS Ann'!L$4) -> 0 | M32: =SUMIFS('FS Qtr'!$J32:$EA32, 'FS Qtr'!$J$4:$EA$4, 'FS Ann'!M$4) -> 0 | N32: =SUMIFS('FS Qtr'!$J32:$EA32, 'FS Qtr'!$J$4:$EA$4, 'FS Ann'!N$4) -> 0 | O32: =SUMIFS('FS Qtr'!$J32:$EA32, 'FS Qtr'!$J$4:$EA$4, 'FS Ann'!O$4) -> 0 | P32: =SUMIFS('FS Qtr'!$J32:$EA32, 'FS Qtr'!$J$4:$EA$4, 'FS Ann'!P$4) -> 0 | Q32: =SUMIFS('FS Qtr'!$J32:$EA32, 'FS Qtr'!$J$4:$EA$4, 'FS Ann'!Q$4) -> 0 | ... AN32: =SUMIFS('FS Qtr'!$J32:$EA32, 'FS Qtr'!$J$4:$EA$4, 'FS Ann'!AN$4) -> 0
E33: Cash flow available for debt service | G33: =SMU -> $ 000s | H33: =SUM(J33:AN33) -> 10000 | J33: =SUM(J30:J32) -> 0 | K33: =SUM(K30:K32) -> 400 | L33: =SUM(L30:L32) -> 400 | M33: =SUM(M30:M32) -> 400 | N33: =SUM(N30:N32) -> 400 | O33: =SUM(O30:O32) -> 400 | P33: =SUM(P30:P32) -> 400 | Q33: =SUM(Q30:Q32) -> 400 | ... AN33: =SUM(AN30:AN32) -> 0
E35: ='FS Qtr'!E35 -> [Senior debt interest] | F35: ='FS Qtr'!F35 -> 0 | G35: ='FS Qtr'!G35 -> 0 | H35: =SUM(J35:AN35) -> 0 | J35: =SUMIFS('FS Qtr'!$J35:$EA35, 'FS Qtr'!$J$4:$EA$4, 'FS Ann'!J$4) -> 0 | K35: =SUMIFS('FS Qtr'!$J35:$EA35, 'FS Qtr'!$J$4:$EA$4, 'FS Ann'!K$4) -> 0 | L35: =SUMIFS('FS Qtr'!$J35:$EA35, 'FS Qtr'!$J$4:$EA$4, 'FS Ann'!L$4) -> 0 | M35: =SUMIFS('FS Qtr'!$J35:$EA35, 'FS Qtr'!$J$4:$EA$4, 'FS Ann'!M$4) -> 0 | N35: =SUMIFS('FS Qtr'!$J35:$EA35, 'FS Qtr'!$J$4:$EA$4, 'FS Ann'!N$4) -> 0 | O35: =SUMIFS('FS Qtr'!$J35:$EA35, 'FS Qtr'!$J$4:$EA$4, 'FS Ann'!O$4) -> 0 | P35: =SUMIFS('FS Qtr'!$J35:$EA35, 'FS Qtr'!$J$4:$EA$4, 'FS Ann'!P$4) -> 0 | Q35: =SUMIFS('FS Qtr'!$J35:$EA35, 'FS Qtr'!$J$4:$EA$4, 'FS Ann'!Q$4) -> 0 | ... AN35: =SUMIFS('FS Qtr'!$J35:$EA35, 'FS Qtr'!$J$4:$EA$4, 'FS Ann'!AN$4) -> 0
E36: ='FS Qtr'!E36 -> [Senior debt repayment] | F36: ='FS Qtr'!F36 -> 0 | G36: ='FS Qtr'!G36 -> 0 | H36: =SUM(J36:AN36) -> 0 | J36: =SUMIFS('FS Qtr'!$J36:$EA36, 'FS Qtr'!$J$4:$EA$4, 'FS Ann'!J$4) -> 0 | K36: =SUMIFS('FS Qtr'!$J36:$EA36, 'FS Qtr'!$J$4:$EA$4, 'FS Ann'!K$4) -> 0 | L36: =SUMIFS('FS Qtr'!$J36:$EA36, 'FS Qtr'!$J$4:$EA$4, 'FS Ann'!L$4) -> 0 | M36: =SUMIFS('FS Qtr'!$J36:$EA36, 'FS Qtr'!$J$4:$EA$4, 'FS Ann'!M$4) -> 0 | N36: =SUMIFS('FS Qtr'!$J36:$EA36, 'FS Qtr'!$J$4:$EA$4, 'FS Ann'!N$4) -> 0 | O36: =SUMIFS('FS Qtr'!$J36:$EA36, 'FS Qtr'!$J$4:$EA$4, 'FS Ann'!O$4) -> 0 | P36: =SUMIFS('FS Qtr'!$J36:$EA36, 'FS Qtr'!$J$4:$EA$4, 'FS Ann'!P$4) -> 0 | Q36: =SUMIFS('FS Qtr'!$J36:$EA36, 'FS Qtr'!$J$4:$EA$4, 'FS Ann'!Q$4) -> 0 | ... AN36: =SUMIFS('FS Qtr'!$J36:$EA36, 'FS Qtr'!$J$4:$EA$4, 'FS Ann'!AN$4) -> 0
E37: Cash flow available for refinancing facility | G37: =SMU -> $ 000s | H37: =SUM(J37:AN37) -> 10000 | J37: =J33 + SUM(J35:J36) -> 0 | K37: =K33 + SUM(K35:K36) -> 400 | L37: =L33 + SUM(L35:L36) -> 400 | M37: =M33 + SUM(M35:M36) -> 400 | N37: =N33 + SUM(N35:N36) -> 400 | O37: =O33 + SUM(O35:O36) -> 400 | P37: =P33 + SUM(P35:P36) -> 400 | Q37: =Q33 + SUM(Q35:Q36) -> 400 | ... AN37: =AN33 + SUM(AN35:AN36) -> 0
E39: ='FS Qtr'!E40 -> [Refi facility repayment] | F39: ='FS Qtr'!F40 -> 0 | G39: ='FS Qtr'!G40 -> 0 | H39: =SUM(J39:AN39) -> 0 | J39: =SUMIFS('FS Qtr'!$J40:$EA40, 'FS Qtr'!$J$4:$EA$4, 'FS Ann'!J$4) -> 0 | K39: =SUMIFS('FS Qtr'!$J40:$EA40, 'FS Qtr'!$J$4:$EA$4, 'FS Ann'!K$4) -> 0 | L39: =SUMIFS('FS Qtr'!$J40:$EA40, 'FS Qtr'!$J$4:$EA$4, 'FS Ann'!L$4) -> 0 | M39: =SUMIFS('FS Qtr'!$J40:$EA40, 'FS Qtr'!$J$4:$EA$4, 'FS Ann'!M$4) -> 0 | N39: =SUMIFS('FS Qtr'!$J40:$EA40, 'FS Qtr'!$J$4:$EA$4, 'FS Ann'!N$4) -> 0 | O39: =SUMIFS('FS Qtr'!$J40:$EA40, 'FS Qtr'!$J$4:$EA$4, 'FS Ann'!O$4) -> 0 | P39: =SUMIFS('FS Qtr'!$J40:$EA40, 'FS Qtr'!$J$4:$EA$4, 'FS Ann'!P$4) -> 0 | Q39: =SUMIFS('FS Qtr'!$J40:$EA40, 'FS Qtr'!$J$4:$EA$4, 'FS Ann'!Q$4) -> 0 | ... AN39: =SUMIFS('FS Qtr'!$J40:$EA40, 'FS Qtr'!$J$4:$EA$4, 'FS Ann'!AN$4) -> 0
E40: ='FS Qtr'!E41 -> [Refi facility interest] | F40: ='FS Qtr'!F41 -> 0 | G40: ='FS Qtr'!G41 -> 0 | H40: =SUM(J40:AN40) -> 0 | J40: =SUMIFS('FS Qtr'!$J41:$EA41, 'FS Qtr'!$J$4:$EA$4, 'FS Ann'!J$4) -> 0 | K40: =SUMIFS('FS Qtr'!$J41:$EA41, 'FS Qtr'!$J$4:$EA$4, 'FS Ann'!K$4) -> 0 | L40: =SUMIFS('FS Qtr'!$J41:$EA41, 'FS Qtr'!$J$4:$EA$4, 'FS Ann'!L$4) -> 0 | M40: =SUMIFS('FS Qtr'!$J41:$EA41, 'FS Qtr'!$J$4:$EA$4, 'FS Ann'!M$4) -> 0 | N40: =SUMIFS('FS Qtr'!$J41:$EA41, 'FS Qtr'!$J$4:$EA$4, 'FS Ann'!N$4) -> 0 | O40: =SUMIFS('FS Qtr'!$J41:$EA41, 'FS Qtr'!$J$4:$EA$4, 'FS Ann'!O$4) -> 0 | P40: =SUMIFS('FS Qtr'!$J41:$EA41, 'FS Qtr'!$J$4:$EA$4, 'FS Ann'!P$4) -> 0 | Q40: =SUMIFS('FS Qtr'!$J41:$EA41, 'FS Qtr'!$J$4:$EA$4, 'FS Ann'!Q$4) -> 0 | ... AN40: =SUMIFS('FS Qtr'!$J41:$EA41, 'FS Qtr'!$J$4:$EA$4, 'FS Ann'!AN$4) -> 0
E41: Cash flow available for revolving credit facility | G41: =SMU -> $ 000s | H41: =SUM(J41:AN41) -> 10000 | J41: =J37 + SUM(J39:J40) -> 0 | K41: =K37 + SUM(K39:K40) -> 400 | L41: =L37 + SUM(L39:L40) -> 400 | M41: =M37 + SUM(M39:M40) -> 400 | N41: =N37 + SUM(N39:N40) -> 400 | O41: =O37 + SUM(O39:O40) -> 400 | P41: =P37 + SUM(P39:P40) -> 400 | Q41: =Q37 + SUM(Q39:Q40) -> 400 | ... AN41: =AN37 + SUM(AN39:AN40) -> 0
E43: ='FS Qtr'!E44 -> [RCF drawdown] | F43: ='FS Qtr'!F44 -> 0 | G43: ='FS Qtr'!G44 -> 0 | H43: =SUM(J43:AN43) -> 0 | J43: =SUMIFS('FS Qtr'!$J44:$EA44, 'FS Qtr'!$J$4:$EA$4, 'FS Ann'!J$4) -> 0 | K43: =SUMIFS('FS Qtr'!$J44:$EA44, 'FS Qtr'!$J$4:$EA$4, 'FS Ann'!K$4) -> 0 | L43: =SUMIFS('FS Qtr'!$J44:$EA44, 'FS Qtr'!$J$4:$EA$4, 'FS Ann'!L$4) -> 0 | M43: =SUMIFS('FS Qtr'!$J44:$EA44, 'FS Qtr'!$J$4:$EA$4, 'FS Ann'!M$4) -> 0 | N43: =SUMIFS('FS Qtr'!$J44:$EA44, 'FS Qtr'!$J$4:$EA$4, 'FS Ann'!N$4) -> 0 | O43: =SUMIFS('FS Qtr'!$J44:$EA44, 'FS Qtr'!$J$4:$EA$4, 'FS Ann'!O$4) -> 0 | P43: =SUMIFS('FS Qtr'!$J44:$EA44, 'FS Qtr'!$J$4:$EA$4, 'FS Ann'!P$4) -> 0 | Q43: =SUMIFS('FS Qtr'!$J44:$EA44, 'FS Qtr'!$J$4:$EA$4, 'FS Ann'!Q$4) -> 0 | ... AN43: =SUMIFS('FS Qtr'!$J44:$EA44, 'FS Qtr'!$J$4:$EA$4, 'FS Ann'!AN$4) -> 0
E44: ='FS Qtr'!E45 -> [RCF repayment] | F44: ='FS Qtr'!F45 -> 0 | G44: ='FS Qtr'!G45 -> 0 | H44: =SUM(J44:AN44) -> 0 | J44: =SUMIFS('FS Qtr'!$J45:$EA45, 'FS Qtr'!$J$4:$EA$4, 'FS Ann'!J$4) -> 0 | K44: =SUMIFS('FS Qtr'!$J45:$EA45, 'FS Qtr'!$J$4:$EA$4, 'FS Ann'!K$4) -> 0 | L44: =SUMIFS('FS Qtr'!$J45:$EA45, 'FS Qtr'!$J$4:$EA$4, 'FS Ann'!L$4) -> 0 | M44: =SUMIFS('FS Qtr'!$J45:$EA45, 'FS Qtr'!$J$4:$EA$4, 'FS Ann'!M$4) -> 0 | N44: =SUMIFS('FS Qtr'!$J45:$EA45, 'FS Qtr'!$J$4:$EA$4, 'FS Ann'!N$4) -> 0 | O44: =SUMIFS('FS Qtr'!$J45:$EA45, 'FS Qtr'!$J$4:$EA$4, 'FS Ann'!O$4) -> 0 | P44: =SUMIFS('FS Qtr'!$J45:$EA45, 'FS Qtr'!$J$4:$EA$4, 'FS Ann'!P$4) -> 0 | Q44: =SUMIFS('FS Qtr'!$J45:$EA45, 'FS Qtr'!$J$4:$EA$4, 'FS Ann'!Q$4) -> 0 | ... AN44: =SUMIFS('FS Qtr'!$J45:$EA45, 'FS Qtr'!$J$4:$EA$4, 'FS Ann'!AN$4) -> 0
E45: ='FS Qtr'!E46 -> [RCF interest expense paid] | F45: ='FS Qtr'!F46 -> 0 | G45: ='FS Qtr'!G46 -> 0 | H45: =SUM(J45:AN45) -> 0 | J45: =SUMIFS('FS Qtr'!$J46:$EA46, 'FS Qtr'!$J$4:$EA$4, 'FS Ann'!J$4) -> 0 | K45: =SUMIFS('FS Qtr'!$J46:$EA46, 'FS Qtr'!$J$4:$EA$4, 'FS Ann'!K$4) -> 0 | L45: =SUMIFS('FS Qtr'!$J46:$EA46, 'FS Qtr'!$J$4:$EA$4, 'FS Ann'!L$4) -> 0 | M45: =SUMIFS('FS Qtr'!$J46:$EA46, 'FS Qtr'!$J$4:$EA$4, 'FS Ann'!M$4) -> 0 | N45: =SUMIFS('FS Qtr'!$J46:$EA46, 'FS Qtr'!$J$4:$EA$4, 'FS Ann'!N$4) -> 0 | O45: =SUMIFS('FS Qtr'!$J46:$EA46, 'FS Qtr'!$J$4:$EA$4, 'FS Ann'!O$4) -> 0 | P45: =SUMIFS('FS Qtr'!$J46:$EA46, 'FS Qtr'!$J$4:$EA$4, 'FS Ann'!P$4) -> 0 | Q45: =SUMIFS('FS Qtr'!$J46:$EA46, 'FS Qtr'!$J$4:$EA$4, 'FS Ann'!Q$4) -> 0 | ... AN45: =SUMIFS('FS Qtr'!$J46:$EA46, 'FS Qtr'!$J$4:$EA$4, 'FS Ann'!AN$4) -> 0
E46: Cash available for shareholders | G46: =SMU -> $ 000s | H46: =SUM(J46:AN46) -> 10000 | J46: =J41 + SUM(J43:J45) -> 0 | K46: =K41 + SUM(K43:K45) -> 400 | L46: =L41 + SUM(L43:L45) -> 400 | M46: =M41 + SUM(M43:M45) -> 400 | N46: =N41 + SUM(N43:N45) -> 400 | O46: =O41 + SUM(O43:O45) -> 400 | P46: =P41 + SUM(P43:P45) -> 400 | Q46: =Q41 + SUM(Q43:Q45) -> 400 | ... AN46: =AN41 + SUM(AN43:AN45) -> 0
E48: ='FS Qtr'!E49 -> [Share capital redemption] | F48: ='FS Qtr'!F49 -> 0 | G48: ='FS Qtr'!G49 -> 0 | H48: =SUM(J48:AN48) -> 0 | J48: =SUMIFS('FS Qtr'!$J49:$EA49, 'FS Qtr'!$J$4:$EA$4, 'FS Ann'!J$4) -> 0 | K48: =SUMIFS('FS Qtr'!$J49:$EA49, 'FS Qtr'!$J$4:$EA$4, 'FS Ann'!K$4) -> 0 | L48: =SUMIFS('FS Qtr'!$J49:$EA49, 'FS Qtr'!$J$4:$EA$4, 'FS Ann'!L$4) -> 0 | M48: =SUMIFS('FS Qtr'!$J49:$EA49, 'FS Qtr'!$J$4:$EA$4, 'FS Ann'!M$4) -> 0 | N48: =SUMIFS('FS Qtr'!$J49:$EA49, 'FS Qtr'!$J$4:$EA$4, 'FS Ann'!N$4) -> 0 | O48: =SUMIFS('FS Qtr'!$J49:$EA49, 'FS Qtr'!$J$4:$EA$4, 'FS Ann'!O$4) -> 0 | P48: =SUMIFS('FS Qtr'!$J49:$EA49, 'FS Qtr'!$J$4:$EA$4, 'FS Ann'!P$4) -> 0 | Q48: =SUMIFS('FS Qtr'!$J49:$EA49, 'FS Qtr'!$J$4:$EA$4, 'FS Ann'!Q$4) -> 0 | ... AN48: =SUMIFS('FS Qtr'!$J49:$EA49, 'FS Qtr'!$J$4:$EA$4, 'FS Ann'!AN$4) -> 0
E49: Cash flow available for dividends | G49: =SMU -> $ 000s | H49: =SUM(J49:AN49) -> 10000 | J49: =J46 + J48 -> 0 | K49: =K46 + K48 -> 400 | L49: =L46 + L48 -> 400 | M49: =M46 + M48 -> 400 | N49: =N46 + N48 -> 400 | O49: =O46 + O48 -> 400 | P49: =P46 + P48 -> 400 | Q49: =Q46 + Q48 -> 400 | ... AN49: =AN46 + AN48 -> 0
E51: ='FS Qtr'!E52 -> [Dividends paid] | F51: ='FS Qtr'!F52 -> 0 | G51: ='FS Qtr'!G52 -> 0 | H51: =SUM(J51:AN51) -> 0 | J51: =SUMIFS('FS Qtr'!$J52:$EA52, 'FS Qtr'!$J$4:$EA$4, 'FS Ann'!J$4) -> 0 | K51: =SUMIFS('FS Qtr'!$J52:$EA52, 'FS Qtr'!$J$4:$EA$4, 'FS Ann'!K$4) -> 0 | L51: =SUMIFS('FS Qtr'!$J52:$EA52, 'FS Qtr'!$J$4:$EA$4, 'FS Ann'!L$4) -> 0 | M51: =SUMIFS('FS Qtr'!$J52:$EA52, 'FS Qtr'!$J$4:$EA$4, 'FS Ann'!M$4) -> 0 | N51: =SUMIFS('FS Qtr'!$J52:$EA52, 'FS Qtr'!$J$4:$EA$4, 'FS Ann'!N$4) -> 0 | O51: =SUMIFS('FS Qtr'!$J52:$EA52, 'FS Qtr'!$J$4:$EA$4, 'FS Ann'!O$4) -> 0 | P51: =SUMIFS('FS Qtr'!$J52:$EA52, 'FS Qtr'!$J$4:$EA$4, 'FS Ann'!P$4) -> 0 | Q51: =SUMIFS('FS Qtr'!$J52:$EA52, 'FS Qtr'!$J$4:$EA$4, 'FS Ann'!Q$4) -> 0 | ... AN51: =SUMIFS('FS Qtr'!$J52:$EA52, 'FS Qtr'!$J$4:$EA$4, 'FS Ann'!AN$4) -> 0
E52: Net cash flow | G52: =SMU -> $ 000s | H52: =SUM(J52:AN52) -> 10000 | J52: =J49 + J51 -> 0 | K52: =K49 + K51 -> 400 | L52: =L49 + L51 -> 400 | M52: =M49 + M51 -> 400 | N52: =N49 + N51 -> 400 | O52: =O49 + O51 -> 400 | P52: =P49 + P51 -> 400 | Q52: =Q49 + Q51 -> 400 | ... AN52: =AN49 + AN51 -> 0
A56: BALANCE SHEET
B58: Non current assets
E59: ='FS Qtr'!E59 -> [Non current assets balance] | F59: ='FS Qtr'!F59 -> 0 | G59: ='FS Qtr'!G59 -> 0 | J59: =SUMIFS( 'FS Qtr'!$J59:$EA59, 'FS Qtr'!$J$2:$EA$2, 'FS Ann'!J$2) -> 0 | K59: =SUMIFS( 'FS Qtr'!$J59:$EA59, 'FS Qtr'!$J$2:$EA$2, 'FS Ann'!K$2) -> 0 | L59: =SUMIFS( 'FS Qtr'!$J59:$EA59, 'FS Qtr'!$J$2:$EA$2, 'FS Ann'!L$2) -> 0 | M59: =SUMIFS( 'FS Qtr'!$J59:$EA59, 'FS Qtr'!$J$2:$EA$2, 'FS Ann'!M$2) -> 0 | N59: =SUMIFS( 'FS Qtr'!$J59:$EA59, 'FS Qtr'!$J$2:$EA$2, 'FS Ann'!N$2) -> 0 | O59: =SUMIFS( 'FS Qtr'!$J59:$EA59, 'FS Qtr'!$J$2:$EA$2, 'FS Ann'!O$2) -> 0 | P59: =SUMIFS( 'FS Qtr'!$J59:$EA59, 'FS Qtr'!$J$2:$EA$2, 'FS Ann'!P$2) -> 0 | Q59: =SUMIFS( 'FS Qtr'!$J59:$EA59, 'FS Qtr'!$J$2:$EA$2, 'FS Ann'!Q$2) -> 0 | ... AN59: =SUMIFS( 'FS Qtr'!$J59:$EA59, 'FS Qtr'!$J$2:$EA$2, 'FS Ann'!AN$2) -> 0
E60: Non current assets | G60: =SMU -> $ 000s | J60: =SUM(J59) -> 0 | K60: =SUM(K59) -> 0 | L60: =SUM(L59) -> 0 | M60: =SUM(M59) -> 0 | N60: =SUM(N59) -> 0 | O60: =SUM(O59) -> 0 | P60: =SUM(P59) -> 0 | Q60: =SUM(Q59) -> 0 | ... AN60: =SUM(AN59) -> 0
B62: Current assets
E63: ='FS Qtr'!E63 -> Retained cash balance | F63: ='FS Qtr'!F63 -> 0 | G63: ='FS Qtr'!G63 -> $ 000s | J63: =SUMIFS( 'FS Qtr'!$J63:$EA63, 'FS Qtr'!$J$2:$EA$2, 'FS Ann'!J$2) -> 0 | K63: =SUMIFS( 'FS Qtr'!$J63:$EA63, 'FS Qtr'!$J$2:$EA$2, 'FS Ann'!K$2) -> 0 | L63: =SUMIFS( 'FS Qtr'!$J63:$EA63, 'FS Qtr'!$J$2:$EA$2, 'FS Ann'!L$2) -> 400 | M63: =SUMIFS( 'FS Qtr'!$J63:$EA63, 'FS Qtr'!$J$2:$EA$2, 'FS Ann'!M$2) -> 800 | N63: =SUMIFS( 'FS Qtr'!$J63:$EA63, 'FS Qtr'!$J$2:$EA$2, 'FS Ann'!N$2) -> 1200 | O63: =SUMIFS( 'FS Qtr'!$J63:$EA63, 'FS Qtr'!$J$2:$EA$2, 'FS Ann'!O$2) -> 1600 | P63: =SUMIFS( 'FS Qtr'!$J63:$EA63, 'FS Qtr'!$J$2:$EA$2, 'FS Ann'!P$2) -> 2000 | Q63: =SUMIFS( 'FS Qtr'!$J63:$EA63, 'FS Qtr'!$J$2:$EA$2, 'FS Ann'!Q$2) -> 2400 | ... AN63: =SUMIFS( 'FS Qtr'!$J63:$EA63, 'FS Qtr'!$J$2:$EA$2, 'FS Ann'!AN$2) -> 10000
E64: ='FS Qtr'!E64 -> [Accounts receivable balance] | F64: ='FS Qtr'!F64 -> 0 | G64: ='FS Qtr'!G64 -> 0 | J64: =SUMIFS( 'FS Qtr'!$J64:$EA64, 'FS Qtr'!$J$2:$EA$2, 'FS Ann'!J$2) -> 0 | K64: =SUMIFS( 'FS Qtr'!$J64:$EA64, 'FS Qtr'!$J$2:$EA$2, 'FS Ann'!K$2) -> 0 | L64: =SUMIFS( 'FS Qtr'!$J64:$EA64, 'FS Qtr'!$J$2:$EA$2, 'FS Ann'!L$2) -> 0 | M64: =SUMIFS( 'FS Qtr'!$J64:$EA64, 'FS Qtr'!$J$2:$EA$2, 'FS Ann'!M$2) -> 0 | N64: =SUMIFS( 'FS Qtr'!$J64:$EA64, 'FS Qtr'!$J$2:$EA$2, 'FS Ann'!N$2) -> 0 | O64: =SUMIFS( 'FS Qtr'!$J64:$EA64, 'FS Qtr'!$J$2:$EA$2, 'FS Ann'!O$2) -> 0 | P64: =SUMIFS( 'FS Qtr'!$J64:$EA64, 'FS Qtr'!$J$2:$EA$2, 'FS Ann'!P$2) -> 0 | Q64: =SUMIFS( 'FS Qtr'!$J64:$EA64, 'FS Qtr'!$J$2:$EA$2, 'FS Ann'!Q$2) -> 0 | ... AN64: =SUMIFS( 'FS Qtr'!$J64:$EA64, 'FS Qtr'!$J$2:$EA$2, 'FS Ann'!AN$2) -> 0
E65: Current assets | G65: =SMU -> $ 000s | J65: =SUM(J63:J64) -> 0 | K65: =SUM(K63:K64) -> 0 | L65: =SUM(L63:L64) -> 400 | M65: =SUM(M63:M64) -> 800 | N65: =SUM(N63:N64) -> 1200 | O65: =SUM(O63:O64) -> 1600 | P65: =SUM(P63:P64) -> 2000 | Q65: =SUM(Q63:Q64) -> 2400 | ... AN65: =SUM(AN63:AN64) -> 10000
E67: Total assets | G67: =SMU -> $ 000s | J67: =J65 + J60 -> 0 | K67: =K65 + K60 -> 0 | L67: =L65 + L60 -> 400 | M67: =M65 + M60 -> 800 | N67: =N65 + N60 -> 1200 | O67: =O65 + O60 -> 1600 | P67: =P65 + P60 -> 2000 | Q67: =Q65 + Q60 -> 2400 | ... AN67: =AN65 + AN60 -> 10000
E69: ='FS Qtr'!E69 -> [Accounts payable balance] | F69: ='FS Qtr'!F69 -> 0 | G69: ='FS Qtr'!G69 -> 0 | J69: =SUMIFS( 'FS Qtr'!$J69:$EA69, 'FS Qtr'!$J$2:$EA$2, 'FS Ann'!J$2) -> 0 | K69: =SUMIFS( 'FS Qtr'!$J69:$EA69, 'FS Qtr'!$J$2:$EA$2, 'FS Ann'!K$2) -> 0 | L69: =SUMIFS( 'FS Qtr'!$J69:$EA69, 'FS Qtr'!$J$2:$EA$2, 'FS Ann'!L$2) -> 0 | M69: =SUMIFS( 'FS Qtr'!$J69:$EA69, 'FS Qtr'!$J$2:$EA$2, 'FS Ann'!M$2) -> 0 | N69: =SUMIFS( 'FS Qtr'!$J69:$EA69, 'FS Qtr'!$J$2:$EA$2, 'FS Ann'!N$2) -> 0 | O69: =SUMIFS( 'FS Qtr'!$J69:$EA69, 'FS Qtr'!$J$2:$EA$2, 'FS Ann'!O$2) -> 0 | P69: =SUMIFS( 'FS Qtr'!$J69:$EA69, 'FS Qtr'!$J$2:$EA$2, 'FS Ann'!P$2) -> 0 | Q69: =SUMIFS( 'FS Qtr'!$J69:$EA69, 'FS Qtr'!$J$2:$EA$2, 'FS Ann'!Q$2) -> 0 | ... AN69: =SUMIFS( 'FS Qtr'!$J69:$EA69, 'FS Qtr'!$J$2:$EA$2, 'FS Ann'!AN$2) -> 0
E70: ='FS Qtr'!E70 -> [Senior debt balance] | F70: ='FS Qtr'!F70 -> 0 | G70: ='FS Qtr'!G70 -> 0 | J70: =SUMIFS( 'FS Qtr'!$J70:$EA70, 'FS Qtr'!$J$2:$EA$2, 'FS Ann'!J$2) -> 0 | K70: =SUMIFS( 'FS Qtr'!$J70:$EA70, 'FS Qtr'!$J$2:$EA$2, 'FS Ann'!K$2) -> 0 | L70: =SUMIFS( 'FS Qtr'!$J70:$EA70, 'FS Qtr'!$J$2:$EA$2, 'FS Ann'!L$2) -> 0 | M70: =SUMIFS( 'FS Qtr'!$J70:$EA70, 'FS Qtr'!$J$2:$EA$2, 'FS Ann'!M$2) -> 0 | N70: =SUMIFS( 'FS Qtr'!$J70:$EA70, 'FS Qtr'!$J$2:$EA$2, 'FS Ann'!N$2) -> 0 | O70: =SUMIFS( 'FS Qtr'!$J70:$EA70, 'FS Qtr'!$J$2:$EA$2, 'FS Ann'!O$2) -> 0 | P70: =SUMIFS( 'FS Qtr'!$J70:$EA70, 'FS Qtr'!$J$2:$EA$2, 'FS Ann'!P$2) -> 0 | Q70: =SUMIFS( 'FS Qtr'!$J70:$EA70, 'FS Qtr'!$J$2:$EA$2, 'FS Ann'!Q$2) -> 0 | ... AN70: =SUMIFS( 'FS Qtr'!$J70:$EA70, 'FS Qtr'!$J$2:$EA$2, 'FS Ann'!AN$2) -> 0
E71: ='FS Qtr'!E71 -> [Refi facility balance] | F71: ='FS Qtr'!F71 -> 0 | G71: ='FS Qtr'!G71 -> 0 | J71: =SUMIFS( 'FS Qtr'!$J71:$EA71, 'FS Qtr'!$J$2:$EA$2, 'FS Ann'!J$2) -> 0 | K71: =SUMIFS( 'FS Qtr'!$J71:$EA71, 'FS Qtr'!$J$2:$EA$2, 'FS Ann'!K$2) -> 0 | L71: =SUMIFS( 'FS Qtr'!$J71:$EA71, 'FS Qtr'!$J$2:$EA$2, 'FS Ann'!L$2) -> 0 | M71: =SUMIFS( 'FS Qtr'!$J71:$EA71, 'FS Qtr'!$J$2:$EA$2, 'FS Ann'!M$2) -> 0 | N71: =SUMIFS( 'FS Qtr'!$J71:$EA71, 'FS Qtr'!$J$2:$EA$2, 'FS Ann'!N$2) -> 0 | O71: =SUMIFS( 'FS Qtr'!$J71:$EA71, 'FS Qtr'!$J$2:$EA$2, 'FS Ann'!O$2) -> 0 | P71: =SUMIFS( 'FS Qtr'!$J71:$EA71, 'FS Qtr'!$J$2:$EA$2, 'FS Ann'!P$2) -> 0 | Q71: =SUMIFS( 'FS Qtr'!$J71:$EA71, 'FS Qtr'!$J$2:$EA$2, 'FS Ann'!Q$2) -> 0 | ... AN71: =SUMIFS( 'FS Qtr'!$J71:$EA71, 'FS Qtr'!$J$2:$EA$2, 'FS Ann'!AN$2) -> 0
E72: ='FS Qtr'!E72 -> [RCF balance] | F72: ='FS Qtr'!F72 -> 0 | G72: ='FS Qtr'!G72 -> 0 | J72: =SUMIFS( 'FS Qtr'!$J72:$EA72, 'FS Qtr'!$J$2:$EA$2, 'FS Ann'!J$2) -> 0 | K72: =SUMIFS( 'FS Qtr'!$J72:$EA72, 'FS Qtr'!$J$2:$EA$2, 'FS Ann'!K$2) -> 0 | L72: =SUMIFS( 'FS Qtr'!$J72:$EA72, 'FS Qtr'!$J$2:$EA$2, 'FS Ann'!L$2) -> 0 | M72: =SUMIFS( 'FS Qtr'!$J72:$EA72, 'FS Qtr'!$J$2:$EA$2, 'FS Ann'!M$2) -> 0 | N72: =SUMIFS( 'FS Qtr'!$J72:$EA72, 'FS Qtr'!$J$2:$EA$2, 'FS Ann'!N$2) -> 0 | O72: =SUMIFS( 'FS Qtr'!$J72:$EA72, 'FS Qtr'!$J$2:$EA$2, 'FS Ann'!O$2) -> 0 | P72: =SUMIFS( 'FS Qtr'!$J72:$EA72, 'FS Qtr'!$J$2:$EA$2, 'FS Ann'!P$2) -> 0 | Q72: =SUMIFS( 'FS Qtr'!$J72:$EA72, 'FS Qtr'!$J$2:$EA$2, 'FS Ann'!Q$2) -> 0 | ... AN72: =SUMIFS( 'FS Qtr'!$J72:$EA72, 'FS Qtr'!$J$2:$EA$2, 'FS Ann'!AN$2) -> 0
E73: ='FS Qtr'!E73 -> [Share capital balance] | F73: ='FS Qtr'!F73 -> 0 | G73: ='FS Qtr'!G73 -> 0 | J73: =SUMIFS( 'FS Qtr'!$J73:$EA73, 'FS Qtr'!$J$2:$EA$2, 'FS Ann'!J$2) -> 0 | K73: =SUMIFS( 'FS Qtr'!$J73:$EA73, 'FS Qtr'!$J$2:$EA$2, 'FS Ann'!K$2) -> 0 | L73: =SUMIFS( 'FS Qtr'!$J73:$EA73, 'FS Qtr'!$J$2:$EA$2, 'FS Ann'!L$2) -> 0 | M73: =SUMIFS( 'FS Qtr'!$J73:$EA73, 'FS Qtr'!$J$2:$EA$2, 'FS Ann'!M$2) -> 0 | N73: =SUMIFS( 'FS Qtr'!$J73:$EA73, 'FS Qtr'!$J$2:$EA$2, 'FS Ann'!N$2) -> 0 | O73: =SUMIFS( 'FS Qtr'!$J73:$EA73, 'FS Qtr'!$J$2:$EA$2, 'FS Ann'!O$2) -> 0 | P73: =SUMIFS( 'FS Qtr'!$J73:$EA73, 'FS Qtr'!$J$2:$EA$2, 'FS Ann'!P$2) -> 0 | Q73: =SUMIFS( 'FS Qtr'!$J73:$EA73, 'FS Qtr'!$J$2:$EA$2, 'FS Ann'!Q$2) -> 0 | ... AN73: =SUMIFS( 'FS Qtr'!$J73:$EA73, 'FS Qtr'!$J$2:$EA$2, 'FS Ann'!AN$2) -> 0
E74: ='FS Qtr'!E74 -> Retained earnings balance | F74: ='FS Qtr'!F74 -> 0 | G74: ='FS Qtr'!G74 -> $ 000s | J74: =SUMIFS( 'FS Qtr'!$J74:$EA74, 'FS Qtr'!$J$2:$EA$2, 'FS Ann'!J$2) -> 0 | K74: =SUMIFS( 'FS Qtr'!$J74:$EA74, 'FS Qtr'!$J$2:$EA$2, 'FS Ann'!K$2) -> 0 | L74: =SUMIFS( 'FS Qtr'!$J74:$EA74, 'FS Qtr'!$J$2:$EA$2, 'FS Ann'!L$2) -> 400 | M74: =SUMIFS( 'FS Qtr'!$J74:$EA74, 'FS Qtr'!$J$2:$EA$2, 'FS Ann'!M$2) -> 800 | N74: =SUMIFS( 'FS Qtr'!$J74:$EA74, 'FS Qtr'!$J$2:$EA$2, 'FS Ann'!N$2) -> 1200 | O74: =SUMIFS( 'FS Qtr'!$J74:$EA74, 'FS Qtr'!$J$2:$EA$2, 'FS Ann'!O$2) -> 1600 | P74: =SUMIFS( 'FS Qtr'!$J74:$EA74, 'FS Qtr'!$J$2:$EA$2, 'FS Ann'!P$2) -> 2000 | Q74: =SUMIFS( 'FS Qtr'!$J74:$EA74, 'FS Qtr'!$J$2:$EA$2, 'FS Ann'!Q$2) -> 2400 | ... AN74: =SUMIFS( 'FS Qtr'!$J74:$EA74, 'FS Qtr'!$J$2:$EA$2, 'FS Ann'!AN$2) -> 10000
E75: Total liabilities | G75: =SMU -> $ 000s | J75: =SUM(J69:J74) -> 0 | K75: =SUM(K69:K74) -> 0 | L75: =SUM(L69:L74) -> 400 | M75: =SUM(M69:M74) -> 800 | N75: =SUM(N69:N74) -> 1200 | O75: =SUM(O69:O74) -> 1600 | P75: =SUM(P69:P74) -> 2000 | Q75: =SUM(Q69:Q74) -> 2400 | ... AN75: =SUM(AN69:AN74) -> 10000
A78: BALANCE SHEET CHECK
E80: =E$67 -> Total assets | F80: =F$67 -> 0 | G80: =G$67 -> $ 000s | H80: =H$67 -> 0 | I80: =I$67 -> 0 | J80: =J$67 -> 0 | K80: =K$67 -> 0 | L80: =L$67 -> 400 | ... AN80: =AN$67 -> 10000
E81: =E$75 -> Total liabilities | F81: =F$75 -> 0 | G81: =G$75 -> $ 000s | H81: =H$75 -> 0 | I81: =I$75 -> 0 | J81: =J$75 -> 0 | K81: =K$75 -> 0 | L81: =L$75 -> 400 | ... AN81: =AN$75 -> 10000
E82: Annual balance sheet check | F82: =IF(SUM(J82:AN82) <> 0, 1, 0) -> 0 | G82: check | J82: =IF(ABS(J80 - J81) > CHK_TOL, 1, 0) -> 0 | K82: =IF(ABS(K80 - K81) > CHK_TOL, 1, 0) -> 0 | L82: =IF(ABS(L80 - L81) > CHK_TOL, 1, 0) -> 0 | M82: =IF(ABS(M80 - M81) > CHK_TOL, 1, 0) -> 0 | N82: =IF(ABS(N80 - N81) > CHK_TOL, 1, 0) -> 0 | O82: =IF(ABS(O80 - O81) > CHK_TOL, 1, 0) -> 0 | P82: =IF(ABS(P80 - P81) > CHK_TOL, 1, 0) -> 0 | Q82: =IF(ABS(Q80 - Q81) > CHK_TOL, 1, 0) -> 0 | ... AN82: =IF(ABS(AN80 - AN81) > CHK_TOL, 1, 0) -> 0
E83: Annual balance sheet difference | H83: =SUM(J83:AN83) -> 0 | J83: =J80 - J81 -> 0 | K83: =K80 - K81 -> 0 | L83: =L80 - L81 -> 0 | M83: =M80 - M81 -> 0 | N83: =N80 - N81 -> 0 | O83: =O80 - O81 -> 0 | P83: =P80 - P81 -> 0 | Q83: =Q80 - Q81 -> 0 | ... AN83: =AN80 - AN81 -> 0
A86: END

Sheet Output
A1: =RIGHT(CELL("filename", A1), LEN(CELL("filename", A1)) - SEARCH("]", CELL("filename", A1))) & " - " & InpC!F3 -> Output - Base case 1
G2: Date | H2: =TODAY() -> 44565 | J2: =COUNTIF(J6:J71, "tu") -> 8
G3: Case | H3: =InpC!F3 -> Base case 1
E5: Comparison column label | G5: Unit | H5: 3 | J5: =MATCH($H$5, M5:Q5, 0) -> 4 | K5: Difference | L5: Diff Pct | N5: 1 | O5: 2 | P5: 3
E6: [do not delete row]
A8: KEY OUTPUTS
J10: =IF(ABS(K10) > TRK_TOL, "tu", "vw") -> vw | K10: =H10 - INDEX(M10:Q10, $J$5) -> 0 | L10: =IF(ABS(K10) > TRK_TOL, IF(INDEX(M10:Q10, $J$5) = 0, 0, H10 / INDEX(M10:Q10, $J$5) - 1), 0) -> 0
J11: =IF(ABS(K11) > TRK_TOL, "tu", "vw") -> vw | K11: =H11 - INDEX(M11:Q11, $J$5) -> 0 | L11: =IF(ABS(K11) > TRK_TOL, IF(INDEX(M11:Q11, $J$5) = 0, 0, H11 / INDEX(M11:Q11, $J$5) - 1), 0) -> 0
J12: =IF(ABS(K12) > TRK_TOL, "tu", "vw") -> vw | K12: =H12 - INDEX(M12:Q12, $J$5) -> 0 | L12: =IF(ABS(K12) > TRK_TOL, IF(INDEX(M12:Q12, $J$5) = 0, 0, H12 / INDEX(M12:Q12, $J$5) - 1), 0) -> 0
J13: =IF(ABS(K13) > TRK_TOL, "tu", "vw") -> vw | K13: =H13 - INDEX(M13:Q13, $J$5) -> 0 | L13: =IF(ABS(K13) > TRK_TOL, IF(INDEX(M13:Q13, $J$5) = 0, 0, H13 / INDEX(M13:Q13, $J$5) - 1), 0) -> 0
A17: PROFIT AND LOSS
E19: ='FS Qtr'!E9 -> [Electricity generation revenue] | F19: ='FS Qtr'!F9 -> 0 | G19: ='FS Qtr'!G$9 -> 0 | H19: ='FS Qtr'!H9 -> 0 | J19: =IF(ABS(K19) > TRK_TOL, "tu", "vw") -> vw | K19: =H19 - INDEX(M19:Q19, $J$5) -> 0 | L19: =IF(ABS(K19) > TRK_TOL, IF(INDEX(M19:Q19, $J$5) = 0, 0, H19 / INDEX(M19:Q19, $J$5) - 1), 0) -> 0
E20: ='FS Qtr'!E10 -> [O&M] | F20: ='FS Qtr'!F10 -> 0 | G20: ='FS Qtr'!G$9 -> 0 | H20: ='FS Qtr'!H10 -> 0 | J20: =IF(ABS(K20) > TRK_TOL, "tu", "vw") -> vw | K20: =H20 - INDEX(M20:Q20, $J$5) -> 0 | L20: =IF(ABS(K20) > TRK_TOL, IF(INDEX(M20:Q20, $J$5) = 0, 0, H20 / INDEX(M20:Q20, $J$5) - 1), 0) -> 0
E21: ='FS Qtr'!E11 -> EBITDA | F21: ='FS Qtr'!F11 -> 0 | G21: ='FS Qtr'!G$9 -> 0 | H21: ='FS Qtr'!H11 -> 10000 | J21: =IF(ABS(K21) > TRK_TOL, "tu", "vw") -> tu | K21: =H21 - INDEX(M21:Q21, $J$5) -> 10000 | L21: =IF(ABS(K21) > TRK_TOL, IF(INDEX(M21:Q21, $J$5) = 0, 0, H21 / INDEX(M21:Q21, $J$5) - 1), 0) -> 0
E23: ='FS Qtr'!E13 -> [Depreciation of non current assets] | F23: ='FS Qtr'!F13 -> 0 | G23: ='FS Qtr'!G$9 -> 0 | H23: ='FS Qtr'!H13 -> 0 | J23: =IF(ABS(K23) > TRK_TOL, "tu", "vw") -> vw | K23: =H23 - INDEX(M23:Q23, $J$5) -> 0 | L23: =IF(ABS(K23) > TRK_TOL, IF(INDEX(M23:Q23, $J$5) = 0, 0, H23 / INDEX(M23:Q23, $J$5) - 1), 0) -> 0
E24: ='FS Qtr'!E14 -> EBIT | F24: ='FS Qtr'!F14 -> 0 | G24: ='FS Qtr'!G$9 -> 0 | H24: ='FS Qtr'!H14 -> 10000 | J24: =IF(ABS(K24) > TRK_TOL, "tu", "vw") -> tu | K24: =H24 - INDEX(M24:Q24, $J$5) -> 10000 | L24: =IF(ABS(K24) > TRK_TOL, IF(INDEX(M24:Q24, $J$5) = 0, 0, H24 / INDEX(M24:Q24, $J$5) - 1), 0) -> 0
E26: ='FS Qtr'!E16 -> [Senior debt interest] | F26: ='FS Qtr'!F16 -> 0 | G26: ='FS Qtr'!G$9 -> 0 | H26: ='FS Qtr'!H16 -> 0 | J26: =IF(ABS(K26) > TRK_TOL, "tu", "vw") -> vw | K26: =H26 - INDEX(M26:Q26, $J$5) -> 0 | L26: =IF(ABS(K26) > TRK_TOL, IF(INDEX(M26:Q26, $J$5) = 0, 0, H26 / INDEX(M26:Q26, $J$5) - 1), 0) -> 0
E27: ='FS Qtr'!E17 -> [Refi facility interest] | F27: ='FS Qtr'!F17 -> 0 | G27: ='FS Qtr'!G$9 -> 0 | H27: ='FS Qtr'!H17 -> 0 | J27: =IF(ABS(K27) > TRK_TOL, "tu", "vw") -> vw | K27: =H27 - INDEX(M27:Q27, $J$5) -> 0 | L27: =IF(ABS(K27) > TRK_TOL, IF(INDEX(M27:Q27, $J$5) = 0, 0, H27 / INDEX(M27:Q27, $J$5) - 1), 0) -> 0
E28: ='FS Qtr'!E18 -> [RCF interest expense] | F28: ='FS Qtr'!F18 -> 0 | G28: ='FS Qtr'!G$9 -> 0 | H28: ='FS Qtr'!H18 -> 0 | J28: =IF(ABS(K28) > TRK_TOL, "tu", "vw") -> vw | K28: =H28 - INDEX(M28:Q28, $J$5) -> 0 | L28: =IF(ABS(K28) > TRK_TOL, IF(INDEX(M28:Q28, $J$5) = 0, 0, H28 / INDEX(M28:Q28, $J$5) - 1), 0) -> 0
E29: ='FS Qtr'!E19 -> Profit before tax | F29: ='FS Qtr'!F19 -> 0 | G29: ='FS Qtr'!G$9 -> 0 | H29: ='FS Qtr'!H19 -> 10000 | J29: =IF(ABS(K29) > TRK_TOL, "tu", "vw") -> tu | K29: =H29 - INDEX(M29:Q29, $J$5) -> 10000 | L29: =IF(ABS(K29) > TRK_TOL, IF(INDEX(M29:Q29, $J$5) = 0, 0, H29 / INDEX(M29:Q29, $J$5) - 1), 0) -> 0
E31: ='FS Qtr'!E21 -> [Corporate income tax expense] | F31: ='FS Qtr'!F21 -> 0 | G31: ='FS Qtr'!G$9 -> 0 | H31: ='FS Qtr'!H21 -> 0 | J31: =IF(ABS(K31) > TRK_TOL, "tu", "vw") -> vw | K31: =H31 - INDEX(M31:Q31, $J$5) -> 0 | L31: =IF(ABS(K31) > TRK_TOL, IF(INDEX(M31:Q31, $J$5) = 0, 0, H31 / INDEX(M31:Q31, $J$5) - 1), 0) -> 0
E32: ='FS Qtr'!E22 -> Profit after tax | F32: ='FS Qtr'!F22 -> 0 | G32: ='FS Qtr'!G$9 -> 0 | H32: ='FS Qtr'!H22 -> 10000 | J32: =IF(ABS(K32) > TRK_TOL, "tu", "vw") -> tu | K32: =H32 - INDEX(M32:Q32, $J$5) -> 10000 | L32: =IF(ABS(K32) > TRK_TOL, IF(INDEX(M32:Q32, $J$5) = 0, 0, H32 / INDEX(M32:Q32, $J$5) - 1), 0) -> 0
E34: ='FS Qtr'!E24 -> [Dividends paid] | F34: ='FS Qtr'!F24 -> 0 | G34: ='FS Qtr'!G$9 -> 0 | H34: ='FS Qtr'!H24 -> 0 | J34: =IF(ABS(K34) > TRK_TOL, "tu", "vw") -> vw | K34: =H34 - INDEX(M34:Q34, $J$5) -> 0 | L34: =IF(ABS(K34) > TRK_TOL, IF(INDEX(M34:Q34, $J$5) = 0, 0, H34 / INDEX(M34:Q34, $J$5) - 1), 0) -> 0
E35: ='FS Qtr'!E25 -> Net income | F35: ='FS Qtr'!F25 -> 0 | G35: ='FS Qtr'!G$9 -> 0 | H35: ='FS Qtr'!H25 -> 10000 | J35: =IF(ABS(K35) > TRK_TOL, "tu", "vw") -> tu | K35: =H35 - INDEX(M35:Q35, $J$5) -> 10000 | L35: =IF(ABS(K35) > TRK_TOL, IF(INDEX(M35:Q35, $J$5) = 0, 0, H35 / INDEX(M35:Q35, $J$5) - 1), 0) -> 0
A38: CASH FLOW
E40: ='FS Qtr'!E30 -> [Cash received from invoices] | F40: ='FS Qtr'!F30 -> 0 | G40: ='FS Qtr'!G$9 -> 0 | H40: ='FS Qtr'!H30 -> 0 | J40: =IF(ABS(K40) > TRK_TOL, "tu", "vw") -> vw | K40: =H40 - INDEX(M40:Q40, $J$5) -> 0 | L40: =IF(ABS(K40) > TRK_TOL, IF(INDEX(M40:Q40, $J$5) = 0, 0, H40 / INDEX(M40:Q40, $J$5) - 1), 0) -> 0
E41: ='FS Qtr'!E31 -> [Cash paid for operating costs] | F41: ='FS Qtr'!F31 -> 0 | G41: ='FS Qtr'!G$9 -> 0 | H41: ='FS Qtr'!H31 -> 0 | J41: =IF(ABS(K41) > TRK_TOL, "tu", "vw") -> vw | K41: =H41 - INDEX(M41:Q41, $J$5) -> 0 | L41: =IF(ABS(K41) > TRK_TOL, IF(INDEX(M41:Q41, $J$5) = 0, 0, H41 / INDEX(M41:Q41, $J$5) - 1), 0) -> 0
E42: ='FS Qtr'!E32 -> [Corporate income tax expense] | F42: ='FS Qtr'!F32 -> 0 | G42: ='FS Qtr'!G$9 -> 0 | H42: ='FS Qtr'!H32 -> 0 | J42: =IF(ABS(K42) > TRK_TOL, "tu", "vw") -> vw | K42: =H42 - INDEX(M42:Q42, $J$5) -> 0 | L42: =IF(ABS(K42) > TRK_TOL, IF(INDEX(M42:Q42, $J$5) = 0, 0, H42 / INDEX(M42:Q42, $J$5) - 1), 0) -> 0
E43: ='FS Qtr'!E33 -> Cash flow available for senior debt service | F43: ='FS Qtr'!F33 -> 0 | G43: ='FS Qtr'!G$9 -> 0 | H43: ='FS Qtr'!H33 -> 10000 | J43: =IF(ABS(K43) > TRK_TOL, "tu", "vw") -> tu | K43: =H43 - INDEX(M43:Q43, $J$5) -> 10000 | L43: =IF(ABS(K43) > TRK_TOL, IF(INDEX(M43:Q43, $J$5) = 0, 0, H43 / INDEX(M43:Q43, $J$5) - 1), 0) -> 0
E45: ='FS Qtr'!E35 -> [Senior debt interest] | F45: ='FS Qtr'!F35 -> 0 | G45: ='FS Qtr'!G$9 -> 0 | H45: ='FS Qtr'!H35 -> 0 | J45: =IF(ABS(K45) > TRK_TOL, "tu", "vw") -> vw | K45: =H45 - INDEX(M45:Q45, $J$5) -> 0 | L45: =IF(ABS(K45) > TRK_TOL, IF(INDEX(M45:Q45, $J$5) = 0, 0, H45 / INDEX(M45:Q45, $J$5) - 1), 0) -> 0
E46: ='FS Qtr'!E36 -> [Senior debt repayment] | F46: ='FS Qtr'!F36 -> 0 | G46: ='FS Qtr'!G$9 -> 0 | H46: ='FS Qtr'!H36 -> 0 | J46: =IF(ABS(K46) > TRK_TOL, "tu", "vw") -> vw | K46: =H46 - INDEX(M46:Q46, $J$5) -> 0 | L46: =IF(ABS(K46) > TRK_TOL, IF(INDEX(M46:Q46, $J$5) = 0, 0, H46 / INDEX(M46:Q46, $J$5) - 1), 0) -> 0
E47: ='FS Qtr'!E37 -> Cash flow available for refinancing facility | F47: ='FS Qtr'!F37 -> 0 | G47: ='FS Qtr'!G$9 -> 0 | H47: ='FS Qtr'!H37 -> 10000 | J47: =IF(ABS(K47) > TRK_TOL, "tu", "vw") -> vw
E49: ='FS Qtr'!E39 -> [Refi facility drawdown] | F49: ='FS Qtr'!F39 -> 0 | G49: ='FS Qtr'!G$9 -> 0 | H49: ='FS Qtr'!H39 -> 0 | J49: =IF(ABS(K49) > TRK_TOL, "tu", "vw") -> vw | K49: =H49 - INDEX(M49:Q49, $J$5) -> 0 | L49: =IF(ABS(K49) > TRK_TOL, IF(INDEX(M49:Q49, $J$5) = 0, 0, H49 / INDEX(M49:Q49, $J$5) - 1), 0) -> 0
E50: ='FS Qtr'!E40 -> [Refi facility repayment] | F50: ='FS Qtr'!F40 -> 0 | G50: ='FS Qtr'!G$9 -> 0 | H50: ='FS Qtr'!H40 -> 0 | J50: =IF(ABS(K50) > TRK_TOL, "tu", "vw") -> vw | K50: =H50 - INDEX(M50:Q50, $J$5) -> 0 | L50: =IF(ABS(K50) > TRK_TOL, IF(INDEX(M50:Q50, $J$5) = 0, 0, H50 / INDEX(M50:Q50, $J$5) - 1), 0) -> 0
E51: ='FS Qtr'!E41 -> [Refi facility interest] | F51: ='FS Qtr'!F41 -> 0 | G51: ='FS Qtr'!G$9 -> 0 | H51: ='FS Qtr'!H41 -> 0 | J51: =IF(ABS(K51) > TRK_TOL, "tu", "vw") -> vw | K51: =H51 - INDEX(M51:Q51, $J$5) -> 0 | L51: =IF(ABS(K51) > TRK_TOL, IF(INDEX(M51:Q51, $J$5) = 0, 0, H51 / INDEX(M51:Q51, $J$5) - 1), 0) -> 0
E52: ='FS Qtr'!E42 -> Cash flow available for revolving credit facility | F52: ='FS Qtr'!F42 -> 0 | G52: ='FS Qtr'!G$9 -> 0 | H52: ='FS Qtr'!H42 -> 10000 | J52: =IF(ABS(K52) > TRK_TOL, "tu", "vw") -> tu | K52: =H52 - INDEX(M52:Q52, $J$5) -> 10000 | L52: =IF(ABS(K52) > TRK_TOL, IF(INDEX(M52:Q52, $J$5) = 0, 0, H52 / INDEX(M52:Q52, $J$5) - 1), 0) -> 0
E54: ='FS Qtr'!E44 -> [RCF drawdown] | F54: ='FS Qtr'!F44 -> 0 | G54: ='FS Qtr'!G$9 -> 0 | H54: ='FS Qtr'!H44 -> 0 | J54: =IF(ABS(K54) > TRK_TOL, "tu", "vw") -> vw | K54: =H54 - INDEX(M54:Q54, $J$5) -> 0 | L54: =IF(ABS(K54) > TRK_TOL, IF(INDEX(M54:Q54, $J$5) = 0, 0, H54 / INDEX(M54:Q54, $J$5) - 1), 0) -> 0
E55: ='FS Qtr'!E45 -> [RCF repayment] | F55: ='FS Qtr'!F45 -> 0 | G55: ='FS Qtr'!G$9 -> 0 | H55: ='FS Qtr'!H45 -> 0 | J55: =IF(ABS(K55) > TRK_TOL, "tu", "vw") -> vw | K55: =H55 - INDEX(M55:Q55, $J$5) -> 0 | L55: =IF(ABS(K55) > TRK_TOL, IF(INDEX(M55:Q55, $J$5) = 0, 0, H55 / INDEX(M55:Q55, $J$5) - 1), 0) -> 0
E56: ='FS Qtr'!E46 -> [RCF interest expense paid] | F56: ='FS Qtr'!F46 -> 0 | G56: ='FS Qtr'!G$9 -> 0 | H56: ='FS Qtr'!H46 -> 0 | J56: =IF(ABS(K56) > TRK_TOL, "tu", "vw") -> vw | K56: =H56 - INDEX(M56:Q56, $J$5) -> 0 | L56: =IF(ABS(K56) > TRK_TOL, IF(INDEX(M56:Q56, $J$5) = 0, 0, H56 / INDEX(M56:Q56, $J$5) - 1), 0) -> 0
E57: ='FS Qtr'!E47 -> Cash available for shareholders | F57: ='FS Qtr'!F47 -> 0 | G57: ='FS Qtr'!G$9 -> 0 | H57: ='FS Qtr'!H47 -> 10000 | J57: =IF(ABS(K57) > TRK_TOL, "tu", "vw") -> tu | K57: =H57 - INDEX(M57:Q57, $J$5) -> 10000 | L57: =IF(ABS(K57) > TRK_TOL, IF(INDEX(M57:Q57, $J$5) = 0, 0, H57 / INDEX(M57:Q57, $J$5) - 1), 0) -> 0
E59: ='FS Qtr'!E49 -> [Share capital redemption] | F59: ='FS Qtr'!F49 -> 0 | G59: ='FS Qtr'!G$9 -> 0 | H59: ='FS Qtr'!H49 -> 0 | J59: =IF(ABS(K59) > TRK_TOL, "tu", "vw") -> vw | K59: =H59 - INDEX(M59:Q59, $J$5) -> 0 | L59: =IF(ABS(K59) > TRK_TOL, IF(INDEX(M59:Q59, $J$5) = 0, 0, H59 / INDEX(M59:Q59, $J$5) - 1), 0) -> 0
E60: ='FS Qtr'!E50 -> Cash flow available for dividends | F60: ='FS Qtr'!F50 -> 0 | G60: ='FS Qtr'!G$9 -> 0 | H60: ='FS Qtr'!H50 -> 10000 | J60: =IF(ABS(K60) > TRK_TOL, "tu", "vw") -> vw
E62: ='FS Qtr'!E52 -> [Dividends paid] | F62: ='FS Qtr'!F52 -> 0 | G62: ='FS Qtr'!G$9 -> 0 | H62: ='FS Qtr'!H52 -> 0 | J62: =IF(ABS(K62) > TRK_TOL, "tu", "vw") -> vw | K62: =H62 - INDEX(M62:Q62, $J$5) -> 0 | L62: =IF(ABS(K62) > TRK_TOL, IF(INDEX(M62:Q62, $J$5) = 0, 0, H62 / INDEX(M62:Q62, $J$5) - 1), 0) -> 0
E63: ='FS Qtr'!E53 -> Net cash flow | F63: ='FS Qtr'!F53 -> 0 | G63: ='FS Qtr'!G$9 -> 0 | H63: ='FS Qtr'!H53 -> 10000 | J63: =IF(ABS(K63) > TRK_TOL, "tu", "vw") -> vw
A66: MODEL RUN INFO
E67: Time | H67: =NOW() -> 44565.578 | N67: 43909.145
E68: Filename | H68: =MID(CELL("filename",$A$1), SEARCH("[", CELL("filename",$A$1)) + 1, SEARCH("]", CELL("filename",$A$1)) - SEARCH("[", CELL("filename",$A$1)) - 1) -> FMH FinStats END 01.xlsx | N68: EFM 01a.xlsx
E71: [do not delete row] | J71: range end

Sheet Check
A1: =RIGHT(CELL("filename", A1), LEN(CELL("filename", A1)) - SEARCH("]", CELL("filename", A1))) & " - " & InpC!F3 -> Check - Base case 1
F2: =Check!$F$9 -> 0 | G2: Error chks
F3: =Output!J2 -> 8 | G3: Track chgs
F4: =Check!$F$21 -> 0 | G4: Alerts
F5: Constant | G5: Unit
A7: CHECK SUMMARY
E9: Total checks | F9: =SUM(F10:F16) -> 0 | G9: check
E10: [do not delete this row] | F10: [range start]
E12: ='FS Qtr'!E$82 -> Balance sheet check | F12: ='FS Qtr'!F$82 -> 0 | G12: ='FS Qtr'!G$82 -> check
E13: ='FS Ann'!E$82 -> Annual balance sheet check | F13: ='FS Ann'!F$82 -> 0 | G13: ='FS Ann'!G$82 -> check
E16: [do not delete this row] | F16: [range end]
A19: ALERT SUMMARY
E21: Total alerts | F21: =SUM(F22:F31) -> 0 | G21: alert
E22: [do not delete this row] | F22: [range start]
E31: [do not delete this row] | F31: [range end]

Sheet Tmp
A1: =RIGHT(CELL("filename", A1), LEN(CELL("filename", A1)) - SEARCH("]", CELL("filename", A1))) & " - " & InpC!F3 -> Tmp - Base case 1
E2: =Time!E$25 -> Model period ending | F2: =Check!$F$9 -> 0 | G2: Error chks | J2: =Time!J$25 -> 44104 | K2: =Time!K$25 -> 44196 | L2: =Time!L$25 -> 44286 | M2: =Time!M$25 -> 44377 | N2: =Time!N$25 -> 44469 | O2: =Time!O$25 -> 44561 | P2: =Time!P$25 -> 44651 | Q2: =Time!Q$25 -> 44742 | ... EA2: =Time!EA$25 -> 55153
E3: =Time!E$67 -> Timeline label | F3: =Output!J2 -> 8 | G3: Track chgs | J3: =Time!J$67 -> Pre-fcst | K3: =Time!K$67 -> Pre-fcst | L3: =Time!L$67 -> Fin Close | M3: =Time!M$67 -> Operations | N3: =Time!N$67 -> Operations | O3: =Time!O$67 -> Operations | P3: =Time!P$67 -> Operations | Q3: =Time!Q$67 -> Operations | ... EA3: =Time!EA$67 -> Post ops
E4: =Time!E$42 -> Contract year | F4: =Check!$F$21 -> 0 | G4: Alerts | J4: =Time!J$42 -> 2020 | K4: =Time!K$42 -> 2020 | L4: =Time!L$42 -> 2020 | M4: =Time!M$42 -> 2021 | N4: =Time!N$42 -> 2021 | O4: =Time!O$42 -> 2021 | P4: =Time!P$42 -> 2021 | Q4: =Time!Q$42 -> 2022 | ... EA4: =Time!EA$42 -> 2050
E5: =Time!E$10 -> Model column counter | F5: Constant | G5: Unit | H5: Total | J5: =Time!J$10 -> 1 | K5: =Time!K$10 -> 2 | L5: =Time!L$10 -> 3 | M5: =Time!M$10 -> 4 | N5: =Time!N$10 -> 5 | O5: =Time!O$10 -> 6 | P5: =Time!P$10 -> 7 | Q5: =Time!Q$10 -> 8 | ... EA5: =Time!EA$10 -> 122
E8: [xxx] balance BEG | J8: =I11 -> 0 | K8: =J11 -> 0 | L8: =K11 -> 0 | M8: =L11 -> 0 | N8: =M11 -> 0 | O8: =N11 -> 0 | P8: =O11 -> 0 | Q8: =P11 -> 0 | ... EA8: =DZ11 -> 0
E9: [upward flow]
E10: [downward flow]
E11: [xxx] balance | J11: =J8 + J9 - J10 -> 0 | K11: =K8 + K9 - K10 -> 0 | L11: =L8 + L9 - L10 -> 0 | M11: =M8 + M9 - M10 -> 0 | N11: =N8 + N9 - N10 -> 0 | O11: =O8 + O9 - O10 -> 0 | P11: =P8 + P9 - P10 -> 0 | Q11: =Q8 + Q9 - Q10 -> 0 | ... EA11: =EA8 + EA9 - EA10 -> 0
E14: [xxx] - initial balance | G14: =SMU -> $ 000s
E15: =Time!E$76 -> Financial close date flag | F15: =Time!F$76 -> 0 | G15: =Time!G$76 -> flag | H15: =Time!H$76 -> 1 | I15: =Time!I$76 -> 0 | J15: =Time!J$76 -> 0 | K15: =Time!K$76 -> 0 | L15: =Time!L$76 -> 1 | ... EA15: =Time!EA$76 -> 0
E17: [xxx] balance BEG | G17: =SMU -> $ 000s | J17: =I20 -> 0 | K17: =J20 -> 0 | L17: =K20 -> 0 | M17: =L20 -> 0 | N17: =M20 -> 0 | O17: =N20 -> 0 | P17: =O20 -> 0 | Q17: =P20 -> 0 | ... EA17: =DZ20 -> 0
E18: [upward flow]
E19: [downward flow]
E20: [xxx] balance | G20: =SMU -> $ 000s | J20: =IF( J15 = 1, $F14, J17 + J18 - J19) -> 0 | K20: =IF( K15 = 1, $F14, K17 + K18 - K19) -> 0 | L20: =IF( L15 = 1, $F14, L17 + L18 - L19) -> 0 | M20: =IF( M15 = 1, $F14, M17 + M18 - M19) -> 0 | N20: =IF( N15 = 1, $F14, N17 + N18 - N19) -> 0 | O20: =IF( O15 = 1, $F14, O17 + O18 - O19) -> 0 | P20: =IF( P15 = 1, $F14, P17 + P18 - P19) -> 0 | Q20: =IF( Q15 = 1, $F14, Q17 + Q18 - Q19) -> 0 | ... EA20: =IF( EA15 = 1, $F14, EA17 + EA18 - EA19) -> 0
E23: Sign switch line item POS | G23: =SMU -> $ 000s | H23: =SUM(J23:EA23) -> 12200 | J23: 100 | K23: 100 | L23: 100 | M23: 100 | N23: 100 | O23: 100 | P23: 100 | Q23: 100 | R23: 100 | S23: 100 | T23: 100 | U23: 100 | V23: 100 | W23: 100 | X23: 100 | Y23: 100 | Z23: 100 | AA23: 100 | AB23: 100 | AC23: 100 | AD23: 100 | AE23: 100 | AF23: 100 | AG23: 100 | AH23: 100 | AI23: 100 | AJ23: 100 | AK23: 100 | AL23: 100 | AM23: 100 | AN23: 100 | AO23: 100 | AP23: 100 | AQ23: 100 | AR23: 100 | AS23: 100 | AT23: 100 | AU23: 100 | AV23: 100 | AW23: 100 | AX23: 100 | AY23: 100 | AZ23: 100 | BA23: 100 | BB23: 100 | BC23: 100 | BD23: 100 | BE23: 100 | BF23: 100 | BG23: 100 | BH23: 100 | BI23: 100 | BJ23: 100 | BK23: 100 | BL23: 100 | BM23: 100 | BN23: 100 | BO23: 100 | BP23: 100 | BQ23: 100 | BR23: 100 | BS23: 100 | BT23: 100 | BU23: 100 | BV23: 100 | BW23: 100 | BX23: 100 | BY23: 100 | BZ23: 100 | CA23: 100 | CB23: 100 | CC23: 100 | CD23: 100 | CE23: 100 | CF23: 100 | CG23: 100 | CH23: 100 | CI23: 100 | CJ23: 100 | CK23: 100 | CL23: 100 | CM23: 100 | CN23: 100 | CO23: 100 | CP23: 100 | CQ23: 100 | CR23: 100 | CS23: 100 | CT23: 100 | CU23: 100 | CV23: 100 | CW23: 100 | CX23: 100 | CY23: 100 | CZ23: 100 | DA23: 100 | DB23: 100 | DC23: 100 | DD23: 100 | DE23: 100 | DF23: 100 | DG23: 100 | DH23: 100 | DI23: 100 | DJ23: 100 | DK23: 100 | DL23: 100 | DM23: 100 | DN23: 100 | DO23: 100 | DP23: 100 | DQ23: 100 | DR23: 100 | DS23: 100 | DT23: 100 | DU23: 100 | DV23: 100 | DW23: 100 | DX23: 100 | DY23: 100 | DZ23: 100 | EA23: 100
E24: =LEFT(E23, LEN(E23) - 4) -> Sign switch line item | G24: =SMU -> $ 000s | H24: =SUM(J24:EA24) -> -12200 | J24: =-1 * J23 -> -100 | K24: =-1 * K23 -> -100 | L24: =-1 * L23 -> -100 | M24: =-1 * M23 -> -100 | N24: =-1 * N23 -> -100 | O24: =-1 * O23 -> -100 | P24: =-1 * P23 -> -100 | Q24: =-1 * Q23 -> -100 | ... EA24: =-1 * EA23 -> -100
