Workbook

Sheet Instructions Sheet
B2: Instructions for using this financial projections document
O3: Figure 1
B4: This document should be used to create a high level financial projection for the income generated and the costs incurred in delivering programmes or products in the South West as part of the transform Ageing Programme. Please develop this model as you feel fit.
B6: Income
B8: The income sheet allows you to input the price of each product/service in the section "unit price income #" (e.g. £300 p/h). Jointly the activity represents the amount of sales you are making in each income stream (e.g. 2 hours). This is then multiplied into the income coloumn (e.g. 2 hours * £300 = £600) (as figure 1 shows). Please feel free to name the Unit price, activities and income sections as you feel fit. The titles you give each income will feed through to the cash flow.
B13: Expenditure
B15: This sheet should be used to record any outgoing that you'll incur. The titles that you give each expenditure will feed through automatically into the cash flow forecast (please note if you change the title of an expenditure in the cash flow sheet this will not feed that title back into the expenditure sheet)
B18: Cash Flow
B20: The information that you put into the income and expenditure sheets will automatically feed into the cash flow sheet. But please do check everything is coming through correctly!
B23: General and Project Milestones
B25: I have started the model off with a 1 year forward look. If you need to model beyond this (which you should) please drag across the formula and the worksheet should perform as expected
B28: The project milestones page can be used or deleted. If you think it would be helpful to explain your work visually then please feel free to use it.
B31: I've included some examples throughout just to make it clearer how this workbook is put together

Sheet Income
B3: Unit Price Income 1 | D3: 1000 | E3: Unit Price Income 2 | G3: 25 | H3: Unit Price Income 3 | J3: 400 | K3: Unit Price Income 4 | M3: 0 | N3: Unit Price Income 5 | P3: 0 | Q3: Unit Price Income 6 | S3: 0
C6: 43160 | D6: 43191 | E6: 43221 | F6: 43252 | G6: 43282 | H6: 43313 | I6: 43344 | J6: 43374 | K6: 43405 | L6: 43435 | M6: 43466 | N6: 43497 | O6: 43525 | P6: 43556 | Q6: 43586 | R6: 43617 | S6: 43647 | T6: 43678 | U6: 43709 | V6: 43739 | W6: 43770 | X6: 43800 | Y6: 43831 | Z6: 43862 | AA6: 43891 | AB6: 43922 | AC6: 43952 | AD6: 43983 | AE6: 44013 | AF6: 44044 | AG6: 44075 | AH6: 44105 | AI6: 44136 | AJ6: 44166 | AK6: 44197 | AL6: 44228 | AM6: 44256 | AN6: 44287 | AO6: 44317 | AP6: 44348 | AQ6: 44378 | AR6: 44409 | AS6: 44440 | AT6: 44470 | AU6: 44501 | AV6: 44531
A7: Service/Product Delivery | B7: Activity 1 | E7: 4 | F7: 4 | G7: 4 | H7: 5
B8: Activity 2 | E8: 4 | F8: 8 | G8: 12 | H8: 17 | I8: 17 | J8: 17 | K8: 17 | L8: 17 | M8: 17 | N8: 17 | O8: 17 | P8: 17 | Q8: 17 | R8: 17 | S8: 17 | T8: 17 | U8: 17 | V8: 17 | W8: 17 | X8: 17 | Y8: 17 | Z8: 17 | AA8: 17 | AB8: 17 | AC8: 17 | AD8: 17 | AE8: 17 | AF8: 17 | AG8: 17 | AH8: 17 | AI8: 17 | AJ8: 17 | AK8: 17 | AL8: 17 | AM8: 17 | AN8: 17 | AO8: 17 | AP8: 17 | AQ8: 17 | AR8: 17 | AS8: 17 | AT8: 17 | AU8: 17 | AV8: 17
B9: Activity 3 | I9: 1 | M9: 1 | P9: 2 | Q9: 2 | R9: 2 | S9: 2 | T9: 2 | U9: 2 | V9: 2 | W9: 2 | X9: 2 | Y9: 2 | Z9: 2 | AA9: 2 | AB9: 2 | AC9: 2 | AD9: 2 | AE9: 2 | AF9: 2 | AG9: 2 | AH9: 2 | AI9: 2 | AJ9: 2 | AK9: 2 | AL9: 2 | AM9: 2 | AN9: 2 | AO9: 2 | AP9: 2 | AQ9: 2 | AR9: 2 | AS9: 2 | AT9: 2 | AU9: 2 | AV9: 2
B10: Activity 4
B11: Activity 5
B12: Activity 6
C15: =C6 -> 43160 | D15: =D6 -> 43191 | E15: =E6 -> 43221 | F15: =F6 -> 43252 | G15: =G6 -> 43282 | H15: =H6 -> 43313 | I15: =I6 -> 43344 | J15: =J6 -> 43374 | ... AV15: =AV6 -> 44531
A16: Income from Activity | B16: Full Package | C16: =C7*$D$3 -> 0 | D16: =D7*$D$3 -> 0 | E16: =E7*$D$3 -> 4000 | F16: =F7*$D$3 -> 4000 | G16: =G7*$D$3 -> 4000 | H16: =H7*$D$3 -> 5000 | I16: =I7*$D$3 -> 0 | J16: =J7*$D$3 -> 0 | ... AV16: =AV7*$D$3 -> 0
B17: App Download | C17: =C8*$G$3 -> 0 | D17: =D8*$G$3 -> 0 | E17: =E8*$G$3 -> 100 | F17: =F8*$G$3 -> 200 | G17: =G8*$G$3 -> 300 | H17: =H8*$G$3 -> 425 | I17: =I8*$G$3 -> 425 | J17: =J8*$G$3 -> 425 | ... AV17: =AV8*$G$3 -> 425
B18: Consultancy | C18: =C9*$J$3 -> 0 | D18: =D9*$J$3 -> 0 | E18: =E9*$J$3 -> 0 | F18: =F9*$J$3 -> 0 | G18: =G9*$J$3 -> 0 | H18: =H9*$J$3 -> 0 | I18: =I9*$J$3 -> 400 | J18: =J9*$J$3 -> 0 | ... AV18: =AV9*$J$3 -> 800
B19: Income 4 | C19: =C10*$M$3 -> 0 | D19: =D10*$M$3 -> 0 | E19: =E10*$M$3 -> 0 | F19: =F10*$M$3 -> 0 | G19: =G10*$M$3 -> 0 | H19: =H10*$M$3 -> 0 | I19: =I10*$M$3 -> 0 | J19: =J10*$M$3 -> 0 | ... AV19: =AV10*$M$3 -> 0
B20: Income 5 | C20: =C11*$P$3 -> 0 | D20: =D11*$P$3 -> 0 | E20: =E11*$P$3 -> 0 | F20: =F11*$P$3 -> 0 | G20: =G11*$P$3 -> 0 | H20: =H11*$P$3 -> 0 | I20: =I11*$P$3 -> 0 | J20: =J11*$P$3 -> 0 | ... AV20: =AV11*$P$3 -> 0
B21: Income 6 | C21: =C12*$S$3 -> 0 | D21: =D12*$S$3 -> 0 | E21: =E12*$S$3 -> 0 | F21: =F12*$S$3 -> 0 | G21: =G12*$S$3 -> 0 | H21: =H12*$S$3 -> 0 | I21: =I12*$S$3 -> 0 | J21: =J12*$S$3 -> 0 | ... AV21: =AV12*$S$3 -> 0
B23: Total | C23: =SUM(C16:C21) -> 0 | D23: =SUM(D16:D21) -> 0 | E23: =SUM(E16:E21) -> 4100 | F23: =SUM(F16:F21) -> 4200 | G23: =SUM(G16:G21) -> 4300 | H23: =SUM(H16:H21) -> 5425 | I23: =SUM(I16:I21) -> 825 | J23: =SUM(J16:J21) -> 425 | ... AV23: =SUM(AV16:AV21) -> 1225
B24: Running Total | C24: =C23 -> 0 | D24: =D23+C24 -> 0 | E24: =E23+D24 -> 4100 | F24: =F23+E24 -> 8300 | G24: =G23+F24 -> 12600 | H24: =H23+G24 -> 18025 | I24: =I23+H24 -> 18850 | J24: =J23+I24 -> 19275 | K24: =K23+J24 -> 19700 | ... AV24: =AV23+AU24 -> 62225

Sheet Expenditure
C3: =Income!C6 -> 43160 | D3: =Income!D6 -> 43191 | E3: =Income!E6 -> 43221 | F3: =Income!F6 -> 43252 | G3: =Income!G6 -> 43282 | H3: =Income!H6 -> 43313 | I3: =Income!I6 -> 43344 | J3: =Income!J6 -> 43374 | ... AV3: =Income!AV6 -> 44531
B4: Salaries | C4: 1500 | D4: 1500 | E4: 1500 | F4: 1500 | G4: 1500 | H4: 1500 | I4: 1500 | J4: 1500 | K4: 1500 | L4: 1500 | M4: 1500 | N4: 1500 | O4: 1500 | P4: 1500 | Q4: 1501 | R4: 1502 | S4: 1503 | T4: 1504 | U4: 1505 | V4: 1506 | W4: 1507 | X4: 1508 | Y4: 1509 | Z4: 1510 | AA4: 1511 | AB4: 1512 | AC4: 1513 | AD4: 1514 | AE4: 1515 | AF4: 1516 | AG4: 1517 | AH4: 1518 | AI4: 1519 | AJ4: 1520 | AK4: 1521 | AL4: 1522 | AM4: 1523 | AN4: 1524 | AO4: 1525 | AP4: 1526 | AQ4: 1527 | AR4: 1528 | AS4: 1529 | AT4: 1530 | AU4: 1531 | AV4: 1532
B5: Outgoing 2
B6: Outgoing 3
B7: Outgoing 4
B8: Outgoing 5
B9: Outgoing 6
B10: Outgoing 7
B11: Outgoing 8
B12: Outgoing 9
B13: Outgoing 10
B14: Outgoing 11
B15: Outgoing 12
B17: Total | C17: =SUM(C4:C15) -> 1500 | D17: =SUM(D4:D15) -> 1500 | E17: =SUM(E4:E15) -> 1500 | F17: =SUM(F4:F15) -> 1500 | G17: =SUM(G4:G15) -> 1500 | H17: =SUM(H4:H15) -> 1500 | I17: =SUM(I4:I15) -> 1500 | J17: =SUM(J4:J15) -> 1500 | ... AV17: =SUM(AV4:AV15) -> 1532
B18: Running Total | C18: =C17+C19 -> 2000 | D18: =D17+C18 -> 3500 | E18: =E17+D18 -> 5000 | F18: =F17+E18 -> 6500 | G18: =G17+F18 -> 8000 | H18: =H17+G18 -> 9500 | I18: =I17+H18 -> 11000 | J18: =J17+I18 -> 12500 | K18: =K17+J18 -> 14000 | ... AV18: =AV17+AU18 -> 70028
B19: Opening Balance | C19: 500

Sheet Cash Flow
C3: =Income!C6 -> 43160 | D3: =Income!D6 -> 43191 | E3: =Income!E6 -> 43221 | F3: =Income!F6 -> 43252 | G3: =Income!G6 -> 43282 | H3: =Income!H6 -> 43313 | I3: =Income!I6 -> 43344 | J3: =Income!J6 -> 43374 | ... AV3: =Income!AV6 -> 44531
B4: Income
B5: =Income!B16 -> Full Package | C5: =Income!C16 -> 0 | D5: =Income!D16 -> 0 | E5: =Income!E16 -> 4000 | F5: =Income!F16 -> 4000 | G5: =Income!G16 -> 4000 | H5: =Income!H16 -> 5000 | I5: =Income!I16 -> 0 | ... AV5: =Income!AV16 -> 0
B6: =Income!B17 -> App Download | C6: =Income!C17 -> 0 | D6: =Income!D17 -> 0 | E6: =Income!E17 -> 100 | F6: =Income!F17 -> 200 | G6: =Income!G17 -> 300 | H6: =Income!H17 -> 425 | I6: =Income!I17 -> 425 | ... AV6: =Income!AV17 -> 425
B7: =Income!B18 -> Consultancy | C7: =Income!C18 -> 0 | D7: =Income!D18 -> 0 | E7: =Income!E18 -> 0 | F7: =Income!F18 -> 0 | G7: =Income!G18 -> 0 | H7: =Income!H18 -> 0 | I7: =Income!I18 -> 400 | ... AV7: =Income!AV18 -> 800
B8: =Income!B19 -> Income 4 | C8: =Income!C19 -> 0 | D8: =Income!D19 -> 0 | E8: =Income!E19 -> 0 | F8: =Income!F19 -> 0 | G8: =Income!G19 -> 0 | H8: =Income!H19 -> 0 | I8: =Income!I19 -> 0 | ... AV8: =Income!AV19 -> 0
B9: =Income!B20 -> Income 5 | C9: =Income!C20 -> 0 | D9: =Income!D20 -> 0 | E9: =Income!E20 -> 0 | F9: =Income!F20 -> 0 | G9: =Income!G20 -> 0 | H9: =Income!H20 -> 0 | I9: =Income!I20 -> 0 | ... AV9: =Income!AV20 -> 0
B10: =Income!B21 -> Income 6 | C10: =Income!C21 -> 0 | D10: =Income!D21 -> 0 | E10: =Income!E21 -> 0 | F10: =Income!F21 -> 0 | G10: =Income!G21 -> 0 | H10: =Income!H21 -> 0 | I10: =Income!I21 -> 0 | ... AV10: =Income!AV21 -> 0
B12: =Income!B23 -> Total | C12: =Income!C23 -> 0 | D12: =Income!D23 -> 0 | E12: =Income!E23 -> 4100 | F12: =Income!F23 -> 4200 | G12: =Income!G23 -> 4300 | H12: =Income!H23 -> 5425 | I12: =Income!I23 -> 825 | ... AV12: =Income!AV23 -> 1225
B13: =Income!B24 -> Running Total | C13: =Income!C24 -> 0 | D13: =Income!D24 -> 0 | E13: =Income!E24 -> 4100 | F13: =Income!F24 -> 8300 | G13: =Income!G24 -> 12600 | H13: =Income!H24 -> 18025 | I13: =Income!I24 -> 18850 | ... AV13: =Income!AV24 -> 62225
B15: Expenditure
B16: =Expenditure!B4 -> Salaries | C16: =Expenditure!C4 -> 1500 | D16: =Expenditure!D4 -> 1500 | E16: =Expenditure!E4 -> 1500 | F16: =Expenditure!F4 -> 1500 | G16: =Expenditure!G4 -> 1500 | H16: =Expenditure!H4 -> 1500 | I16: =Expenditure!I4 -> 1500 | ... AV16: =Expenditure!AV4 -> 1532
B17: =Expenditure!B5 -> Outgoing 2 | C17: =Expenditure!C5 -> 0 | D17: =Expenditure!D5 -> 0 | E17: =Expenditure!E5 -> 0 | F17: =Expenditure!F5 -> 0 | G17: =Expenditure!G5 -> 0 | H17: =Expenditure!H5 -> 0 | I17: =Expenditure!I5 -> 0 | ... AV17: =Expenditure!AV5 -> 0
B18: =Expenditure!B6 -> Outgoing 3 | C18: =Expenditure!C6 -> 0 | D18: =Expenditure!D6 -> 0 | E18: =Expenditure!E6 -> 0 | F18: =Expenditure!F6 -> 0 | G18: =Expenditure!G6 -> 0 | H18: =Expenditure!H6 -> 0 | I18: =Expenditure!I6 -> 0 | ... AV18: =Expenditure!AV6 -> 0
B19: =Expenditure!B7 -> Outgoing 4 | C19: =Expenditure!C7 -> 0 | D19: =Expenditure!D7 -> 0 | E19: =Expenditure!E7 -> 0 | F19: =Expenditure!F7 -> 0 | G19: =Expenditure!G7 -> 0 | H19: =Expenditure!H7 -> 0 | I19: =Expenditure!I7 -> 0 | ... AV19: =Expenditure!AV7 -> 0
B20: =Expenditure!B8 -> Outgoing 5 | C20: =Expenditure!C8 -> 0 | D20: =Expenditure!D8 -> 0 | E20: =Expenditure!E8 -> 0 | F20: =Expenditure!F8 -> 0 | G20: =Expenditure!G8 -> 0 | H20: =Expenditure!H8 -> 0 | I20: =Expenditure!I8 -> 0 | ... AV20: =Expenditure!AV8 -> 0
B21: =Expenditure!B9 -> Outgoing 6 | C21: =Expenditure!C9 -> 0 | D21: =Expenditure!D9 -> 0 | E21: =Expenditure!E9 -> 0 | F21: =Expenditure!F9 -> 0 | G21: =Expenditure!G9 -> 0 | H21: =Expenditure!H9 -> 0 | I21: =Expenditure!I9 -> 0 | ... AV21: =Expenditure!AV9 -> 0
B22: =Expenditure!B10 -> Outgoing 7 | C22: =Expenditure!C10 -> 0 | D22: =Expenditure!D10 -> 0 | E22: =Expenditure!E10 -> 0 | F22: =Expenditure!F10 -> 0 | G22: =Expenditure!G10 -> 0 | H22: =Expenditure!H10 -> 0 | I22: =Expenditure!I10 -> 0 | ... AV22: =Expenditure!AV10 -> 0
B23: =Expenditure!B11 -> Outgoing 8 | C23: =Expenditure!C11 -> 0 | D23: =Expenditure!D11 -> 0 | E23: =Expenditure!E11 -> 0 | F23: =Expenditure!F11 -> 0 | G23: =Expenditure!G11 -> 0 | H23: =Expenditure!H11 -> 0 | I23: =Expenditure!I11 -> 0 | ... AV23: =Expenditure!AV11 -> 0
B24: =Expenditure!B12 -> Outgoing 9 | C24: =Expenditure!C12 -> 0 | D24: =Expenditure!D12 -> 0 | E24: =Expenditure!E12 -> 0 | F24: =Expenditure!F12 -> 0 | G24: =Expenditure!G12 -> 0 | H24: =Expenditure!H12 -> 0 | I24: =Expenditure!I12 -> 0 | ... AV24: =Expenditure!AV12 -> 0
B25: =Expenditure!B13 -> Outgoing 10 | C25: =Expenditure!C13 -> 0 | D25: =Expenditure!D13 -> 0 | E25: =Expenditure!E13 -> 0 | F25: =Expenditure!F13 -> 0 | G25: =Expenditure!G13 -> 0 | H25: =Expenditure!H13 -> 0 | I25: =Expenditure!I13 -> 0 | ... AV25: =Expenditure!AV13 -> 0
B26: =Expenditure!B14 -> Outgoing 11 | C26: =Expenditure!C14 -> 0 | D26: =Expenditure!D14 -> 0 | E26: =Expenditure!E14 -> 0 | F26: =Expenditure!F14 -> 0 | G26: =Expenditure!G14 -> 0 | H26: =Expenditure!H14 -> 0 | I26: =Expenditure!I14 -> 0 | ... AV26: =Expenditure!AV14 -> 0
B27: =Expenditure!B15 -> Outgoing 12 | C27: =Expenditure!C15 -> 0 | D27: =Expenditure!D15 -> 0 | E27: =Expenditure!E15 -> 0 | F27: =Expenditure!F15 -> 0 | G27: =Expenditure!G15 -> 0 | H27: =Expenditure!H15 -> 0 | I27: =Expenditure!I15 -> 0 | ... AV27: =Expenditure!AV15 -> 0
... B30: =Expenditure!B18 -> Running Total | C30: =Expenditure!C18 -> 2000 | D30: =Expenditure!D18 -> 3500 | E30: =Expenditure!E18 -> 5000 | F30: =Expenditure!F18 -> 6500 | G30: =Expenditure!G18 -> 8000 | H30: =Expenditure!H18 -> 9500 | I30: =Expenditure!I18 -> 11000 | ... AV30: =Expenditure!AV18 -> 70028
B32: Total | C32: =C12-C29 -> -1500 | D32: =D12-D29 -> -1500 | E32: =E12-E29 -> 2600 | F32: =F12-F29 -> 2700 | G32: =G12-G29 -> 2800 | H32: =H12-H29 -> 3925 | I32: =I12-I29 -> -675 | J32: =J12-J29 -> -1075 | ... AV32: =AV12-AV29 -> -307
B33: Running Total | C33: =C32+C34 -> -1500 | D33: =D32+C33 -> -3000 | E33: =E32+D33 -> -400 | F33: =F32+E33 -> 2300 | G33: =G32+F33 -> 5100 | H33: =H32+G33 -> 9025 | I33: =I32+H33 -> 8350 | J33: =J32+I33 -> 7275 | K33: =K32+J33 -> 6200 | ... AV33: =AV32+AU33 -> -7303
B34: Opening Total | C34: 0

Sheet Project Milestones
B3: Comments | C3: =Income!C6 -> 43160 | D3: =Income!D6 -> 43191 | E3: =Income!E6 -> 43221 | F3: =Income!F6 -> 43252 | G3: =Income!G6 -> 43282 | H3: =Income!H6 -> 43313 | I3: =Income!I6 -> 43344 | J3: =Income!J6 -> 43374 | ... P3: =Income!P6 -> 43556
C4: Partnership with Charity A formalised and training booked in | D4: Partnership with Charity B formalised | E4: Training Begins with both Charities | F4: Training ends and marketing begins with support of local charities
B5: Milestones | C5: =C3 -> 43160 | D5: =D3 -> 43191 | E5: =E3 -> 43221 | F5: =F3 -> 43252 | G5: =G3 -> 43282 | H5: =H3 -> 43313 | I5: =I3 -> 43344 | J5: =J3 -> 43374 | ... P5: =P3 -> 43556
B6: Partnerships Formalised
B7: Training
B8: Marketing
B9: Lead Generation
B10: Sales
B11: Events
