Workbook
Name BSCheck: #REF!
Name BSCheck: #REF!
Name BSCheck: #REF!
Name BSCheck: #REF!
Name BSCheck: #REF!
Name BSCheck: #REF!
Name BSCheck: #REF!
Name BSCheck: #REF!
Name BSCheck: #REF!
Name CentralCosts: 'Other income'!$K$32:$BS$32
Name CentralCosts: CentralCosts!$K$32:$BS$32
Name CentralStaff: StaffCosts!$K$15:$BS$15
Name Creditors: #REF!
Name Creditors: #REF!
Name Creditors: #REF!
Name Creditors: #REF!
Name Creditors: #REF!
Name Creditors: #REF!
Name Creditors: #REF!
Name Creditors: #REF!
Name Creditors: #REF!
Name DebtIssued: [1]Input!$E$33
Name Debtors: #REF!
Name Debtors: #REF!
Name Debtors: #REF!
Name Debtors: #REF!
Name Debtors: #REF!
Name Debtors: #REF!
Name Debtors: #REF!
Name Debtors: #REF!
Name Debtors: #REF!
Name DebtRec: DebtFinancing!#REF!
Name DebtRec: DebtFinancing!#REF!
Name DebtRec: GrantIncome!#REF!
Name DebtRec: DebtFinancing!#REF!
Name DebtRec: DebtFinancing!#REF!
Name DebtRec: DebtFinancing!#REF!
Name DebtRec: DebtFinancing!#REF!
Name DebtRec: DebtFinancing!#REF!
Name DebtRec: DebtFinancing!#REF!
Name DebtTerm: [1]Input!$E$36
Name Depreciation: Capex!#REF!
Name Depreciation: Capex!#REF!
Name Depreciation: Capex!#REF!
Name Depreciation: Capex!#REF!
Name Depreciation: Capex!#REF!
Name Depreciation: Capex!#REF!
Name Depreciation: Capex!#REF!
Name Depreciation: Capex!#REF!
Name Depreciation: Capex!#REF!
Name EquityVal: [2]DCF!$E$20
Name GrantRec: EquityFinancing!$K$22:$BS$22
Name GrantRec: #REF!
Name GrantRec: #REF!
Name IntRate: [1]Input!$E$35
Name Months1: Worksheet!$A$1:$A$12
Name RevBusLine1: Revenue!$K$16:$BS$16
Name RevBusLine2: Revenue!$K$22:$BS$22
Name RevBusLine3: Revenue!$K$28:$BS$28
Name StaffCosts: StaffCosts!$K$116:$BS$116

Sheet Key Inputs
D2: Started | E2: Completed
C4: General Assumptions
C6: Volume Sales
C8: Pricing
C10: Variable Costs
C12: Staff Costs
C14: Central Costs
C16: Stock Orders
C18: Capital Expenditure
C20: Grant Income
C22: Investment Income
B24: Yes
B25: No

Sheet Disclaimer
A1: Disclaimer

Sheet Outputs - Summary
A3: =IF(KeyInputs!$F$14=0,"Company Name",KeyInputs!$F$14) -> Company Name
A4: Outputs summary
A5: =KeyInputs!C5 -> 0 | D5: =KeyInputs!D5 -> Year | E5: =KeyInputs!E5 -> 2012 | F5: =KeyInputs!F5 -> 2013 | G5: =KeyInputs!G5 -> 2014 | H5: =KeyInputs!H5 -> 2015 | I5: =KeyInputs!I5 -> 2016 | J5: =KeyInputs!J5 -> 2017 | K5: =KeyInputs!K5 -> 2018 | L5: =KeyInputs!L5 -> 2019
D6: =KeyInputs!D6 -> Period number | E6: =KeyInputs!E6 -> -2 | F6: =KeyInputs!F6 -> -1 | G6: =KeyInputs!G6 -> 0 | H6: =KeyInputs!H6 -> 1 | I6: =KeyInputs!I6 -> 2 | J6: =KeyInputs!J6 -> 3 | K6: =KeyInputs!K6 -> 4 | L6: =KeyInputs!L6 -> 5
D7: =KeyInputs!D7 -> Period starts | E7: =KeyInputs!E7 -> 40909 | F7: =KeyInputs!F7 -> 41275 | G7: =KeyInputs!G7 -> 41640 | H7: =KeyInputs!H7 -> 42005 | I7: =KeyInputs!I7 -> 42370 | J7: =KeyInputs!J7 -> 42736 | K7: =KeyInputs!K7 -> 43101 | L7: =KeyInputs!L7 -> 43466
B8: =IF(Check!$C$12=0,"All checks are OK","There are "&Check!$C$12&" error/errors") -> All checks are OK | D8: =KeyInputs!D8 -> Period ends | E8: =KeyInputs!E8 -> 41274 | F8: =KeyInputs!F8 -> 41639 | G8: =KeyInputs!G8 -> 42004 | H8: =KeyInputs!H8 -> 42369 | I8: =KeyInputs!I8 -> 42735 | J8: =KeyInputs!J8 -> 43100 | K8: =KeyInputs!K8 -> 43465 | L8: =KeyInputs!L8 -> 43830
A10: =Header1 -> 1 | B10: Profit & Loss Account
B12: Sales | D12: =unit -> £ | E12: =SUM(E13:E15) -> 0 | F12: =SUM(F13:F15) -> 0 | G12: =SUM(G13:G15) -> 0 | H12: =SUM(H13:H15) -> 0 | I12: =SUM(I13:I15) -> 0 | J12: =SUM(J13:J15) -> 0 | K12: =SUM(K13:K15) -> 0 | L12: =SUM(L13:L15) -> 0
B13: =KeyInputs!F21 -> Test | D13: =unit -> £ | E13: =KeyInputs!E156 -> 0 | F13: =KeyInputs!F156 -> 0 | G13: =KeyInputs!G156 -> 0 | H13: ='Outputs - P&L'!E13 -> 0 | I13: ='Outputs - P&L'!F13 -> 0 | J13: ='Outputs - P&L'!G13 -> 0 | K13: ='Outputs - P&L'!H13 -> 0 | L13: ='Outputs - P&L'!I13 -> 0
B14: =KeyInputs!F26 -> Insert Business Line2 | D14: =unit -> £ | E14: =KeyInputs!E157 -> 0 | F14: =KeyInputs!F157 -> 0 | G14: =KeyInputs!G157 -> 0 | H14: ='Outputs - P&L'!E14 -> 0 | I14: ='Outputs - P&L'!F14 -> 0 | J14: ='Outputs - P&L'!G14 -> 0 | K14: ='Outputs - P&L'!H14 -> 0 | L14: ='Outputs - P&L'!I14 -> 0
B15: =KeyInputs!F31 -> Insert Business Line3 | D15: =unit -> £ | E15: =KeyInputs!E158 -> 0 | F15: =KeyInputs!F158 -> 0 | G15: =KeyInputs!G158 -> 0 | H15: ='Outputs - P&L'!E15 -> 0 | I15: ='Outputs - P&L'!F15 -> 0 | J15: ='Outputs - P&L'!G15 -> 0 | K15: ='Outputs - P&L'!H15 -> 0 | L15: ='Outputs - P&L'!I15 -> 0
B17: Variable costs | D17: =unit -> £ | E17: =SUM(E18:E20) -> 0 | F17: =SUM(F18:F20) -> 0 | G17: =SUM(G18:G20) -> 0 | H17: =SUM(H18:H20) -> 0 | I17: =SUM(I18:I20) -> 0 | J17: =SUM(J18:J20) -> 0 | K17: =SUM(K18:K20) -> 0 | L17: =SUM(L18:L20) -> 0
B18: =B13 -> Test | D18: =unit -> £ | E18: =KeyInputs!E161 -> 0 | F18: =KeyInputs!F161 -> 0 | G18: =KeyInputs!G161 -> 0 | H18: ='Outputs - P&L'!E18 -> 0 | I18: ='Outputs - P&L'!F18 -> 0 | J18: ='Outputs - P&L'!G18 -> 0 | K18: ='Outputs - P&L'!H18 -> 0 | L18: ='Outputs - P&L'!I18 -> 0 | O18: =IFERROR(F18/F$17,"-") -> - | P18: =IFERROR(G18/G$17,"-") -> - | Q18: =IFERROR(H18/H$17,"-") -> - | R18: =IFERROR(I18/I$17,"-") -> - | S18: =IFERROR(J18/J$17,"-") -> - | T18: =IFERROR(K18/K$17,"-") -> - | U18: =IFERROR(L18/L$17,"-") -> -
B19: =B14 -> Insert Business Line2 | D19: =unit -> £ | E19: =KeyInputs!E162 -> 0 | F19: =KeyInputs!F162 -> 0 | G19: =KeyInputs!G162 -> 0 | H19: ='Outputs - P&L'!E19 -> 0 | I19: ='Outputs - P&L'!F19 -> 0 | J19: ='Outputs - P&L'!G19 -> 0 | K19: ='Outputs - P&L'!H19 -> 0 | L19: ='Outputs - P&L'!I19 -> 0 | O19: =IFERROR(F19/F$17,"-") -> - | P19: =IFERROR(G19/G$17,"-") -> - | Q19: =IFERROR(H19/H$17,"-") -> - | R19: =IFERROR(I19/I$17,"-") -> - | S19: =IFERROR(J19/J$17,"-") -> - | T19: =IFERROR(K19/K$17,"-") -> - | U19: =IFERROR(L19/L$17,"-") -> -
B20: =B15 -> Insert Business Line3 | D20: =unit -> £ | E20: =KeyInputs!E163 -> 0 | F20: =KeyInputs!F163 -> 0 | G20: =KeyInputs!G163 -> 0 | H20: ='Outputs - P&L'!E20 -> 0 | I20: ='Outputs - P&L'!F20 -> 0 | J20: ='Outputs - P&L'!G20 -> 0 | K20: ='Outputs - P&L'!H20 -> 0 | L20: ='Outputs - P&L'!I20 -> 0 | O20: =IFERROR(F20/F$17,"-") -> - | P20: =IFERROR(G20/G$17,"-") -> - | Q20: =IFERROR(H20/H$17,"-") -> - | R20: =IFERROR(I20/I$17,"-") -> - | S20: =IFERROR(J20/J$17,"-") -> - | T20: =IFERROR(K20/K$17,"-") -> - | U20: =IFERROR(L20/L$17,"-") -> -
B22: Direct staff costs | D22: =unit -> £ | E22: =SUM(E23:E25) -> 0 | F22: =SUM(F23:F25) -> 0 | G22: =SUM(G23:G25) -> 0 | H22: =SUM(H23:H25) -> 0 | I22: =SUM(I23:I25) -> 0 | J22: =SUM(J23:J25) -> 0 | K22: =SUM(K23:K25) -> 0 | L22: =SUM(L23:L25) -> 0
B23: =B13 -> Test | D23: =unit -> £ | E23: =KeyInputs!E166 -> 0 | F23: =KeyInputs!F166 -> 0 | G23: =KeyInputs!G166 -> 0 | H23: ='Outputs - P&L'!E23 -> 0 | I23: ='Outputs - P&L'!F23 -> 0 | J23: ='Outputs - P&L'!G23 -> 0 | K23: ='Outputs - P&L'!H23 -> 0 | L23: ='Outputs - P&L'!I23 -> 0 | O23: =IFERROR(F23/F$22,"-") -> - | P23: =IFERROR(G23/G$22,"-") -> - | Q23: =IFERROR(H23/H$22,"-") -> - | R23: =IFERROR(I23/I$22,"-") -> - | S23: =IFERROR(J23/J$22,"-") -> - | T23: =IFERROR(K23/K$22,"-") -> - | U23: =IFERROR(L23/L$22,"-") -> -
B24: =B14 -> Insert Business Line2 | D24: =unit -> £ | E24: =KeyInputs!E167 -> 0 | F24: =KeyInputs!F167 -> 0 | G24: =KeyInputs!G167 -> 0 | H24: ='Outputs - P&L'!E24 -> 0 | I24: ='Outputs - P&L'!F24 -> 0 | J24: ='Outputs - P&L'!G24 -> 0 | K24: ='Outputs - P&L'!H24 -> 0 | L24: ='Outputs - P&L'!I24 -> 0 | O24: =IFERROR(F24/F$22,"-") -> - | P24: =IFERROR(G24/G$22,"-") -> - | Q24: =IFERROR(H24/H$22,"-") -> - | R24: =IFERROR(I24/I$22,"-") -> - | S24: =IFERROR(J24/J$22,"-") -> - | T24: =IFERROR(K24/K$22,"-") -> - | U24: =IFERROR(L24/L$22,"-") -> -
B25: =B15 -> Insert Business Line3 | D25: =unit -> £ | E25: =KeyInputs!E168 -> 0 | F25: =KeyInputs!F168 -> 0 | G25: =KeyInputs!G168 -> 0 | H25: ='Outputs - P&L'!E25 -> 0 | I25: ='Outputs - P&L'!F25 -> 0 | J25: ='Outputs - P&L'!G25 -> 0 | K25: ='Outputs - P&L'!H25 -> 0 | L25: ='Outputs - P&L'!I25 -> 0 | O25: =IFERROR(F25/F$22,"-") -> - | P25: =IFERROR(G25/G$22,"-") -> - | Q25: =IFERROR(H25/H$22,"-") -> - | R25: =IFERROR(I25/I$22,"-") -> - | S25: =IFERROR(J25/J$22,"-") -> - | T25: =IFERROR(K25/K$22,"-") -> - | U25: =IFERROR(L25/L$22,"-") -> -
B27: Gross profit | D27: =unit -> £ | E27: =SUM(E12,E17,E22) -> 0 | F27: =SUM(F12,F17,F22) -> 0 | G27: =SUM(G12,G17,G22) -> 0 | H27: =SUM(H12,H17,H22) -> 0 | I27: =SUM(I12,I17,I22) -> 0 | J27: =SUM(J12,J17,J22) -> 0 | K27: =SUM(K12,K17,K22) -> 0 | L27: =SUM(L12,L17,L22) -> 0
B29: Central staff costs | D29: =unit -> £ | E29: =KeyInputs!E172 -> 0 | F29: =KeyInputs!F172 -> 0 | G29: =KeyInputs!G172 -> 0 | H29: ='Outputs - P&L'!E29 -> 0 | I29: ='Outputs - P&L'!F29 -> 0 | J29: ='Outputs - P&L'!G29 -> 0 | K29: ='Outputs - P&L'!H29 -> 0 | L29: ='Outputs - P&L'!I29 -> 0
B30: Central costs | D30: =unit -> £ | E30: =KeyInputs!E173 -> 0 | F30: =KeyInputs!F173 -> 0 | G30: =KeyInputs!G173 -> 0 | H30: ='Outputs - P&L'!E30 -> 0 | I30: ='Outputs - P&L'!F30 -> 0 | J30: ='Outputs - P&L'!G30 -> 0 | K30: ='Outputs - P&L'!H30 -> 0 | L30: ='Outputs - P&L'!I30 -> 0
B31: Depreciation | D31: =unit -> £ | E31: =KeyInputs!E174 -> 0 | F31: =KeyInputs!F174 -> 0 | G31: =KeyInputs!G174 -> 0 | H31: ='Outputs - P&L'!E31 -> 0 | I31: ='Outputs - P&L'!F31 -> 0 | J31: ='Outputs - P&L'!G31 -> 0 | K31: ='Outputs - P&L'!H31 -> 0 | L31: ='Outputs - P&L'!I31 -> 0
B32: Operating profit | D32: =unit -> £ | E32: =SUM(E27:E31) -> 0 | F32: =SUM(F27:F31) -> 0 | G32: =SUM(G27:G31) -> 0 | H32: =SUM(H27:H31) -> 0 | I32: =SUM(I27:I31) -> 0 | J32: =SUM(J27:J31) -> 0 | K32: =SUM(K27:K31) -> 0 | L32: =SUM(L27:L31) -> 0
B34: Grant income | D34: =unit -> £ | E34: =KeyInputs!E177 -> 0 | F34: =KeyInputs!F177 -> 0 | G34: =KeyInputs!G177 -> 0 | H34: ='Outputs - P&L'!E34 -> 0 | I34: ='Outputs - P&L'!F34 -> 0 | J34: ='Outputs - P&L'!G34 -> 0 | K34: ='Outputs - P&L'!H34 -> 0 | L34: ='Outputs - P&L'!I34 -> 0
B35: Other income | D35: =unit -> £ | E35: =KeyInputs!E178 -> 0 | F35: =KeyInputs!F178 -> 0 | G35: =KeyInputs!G178 -> 0 | H35: ='Outputs - P&L'!E35 -> 0 | I35: ='Outputs - P&L'!F35 -> 0 | J35: ='Outputs - P&L'!G35 -> 0 | K35: ='Outputs - P&L'!H35 -> 0 | L35: ='Outputs - P&L'!I35 -> 0
B36: Interest on debt | D36: =unit -> £ | E36: =KeyInputs!E179 -> 0 | F36: =KeyInputs!F179 -> 0 | G36: =KeyInputs!G179 -> 0 | H36: ='Outputs - P&L'!E36 -> 0 | I36: ='Outputs - P&L'!F36 -> 0 | J36: ='Outputs - P&L'!G36 -> 0 | K36: ='Outputs - P&L'!H36 -> 0 | L36: ='Outputs - P&L'!I36 -> 0
B37: Overdraft interest | E37: =KeyInputs!E180 -> 0 | F37: =KeyInputs!F180 -> 0 | G37: =KeyInputs!G180 -> 0 | H37: ='Outputs - P&L'!E37 -> 0 | I37: ='Outputs - P&L'!F37 -> 0 | J37: ='Outputs - P&L'!G37 -> 0 | K37: ='Outputs - P&L'!H37 -> 0 | L37: ='Outputs - P&L'!I37 -> 0
B38: PBT | D38: =unit -> £ | E38: =SUM(E32:E37) -> 0 | F38: =SUM(F32:F37) -> 0 | G38: =SUM(G32:G37) -> 0 | H38: =SUM(H32:H37) -> 0 | I38: =SUM(I32:I37) -> 0 | J38: =SUM(J32:J37) -> 0 | K38: =SUM(K32:K37) -> 0 | L38: =SUM(L32:L37) -> 0
B40: Current tax | D40: =unit -> £ | E40: =KeyInputs!E183 -> 0 | F40: =KeyInputs!F183 -> 0 | G40: =KeyInputs!G183 -> 0 | H40: ='Outputs - P&L'!E40 -> 0 | I40: ='Outputs - P&L'!F40 -> 0 | J40: ='Outputs - P&L'!G40 -> 0 | K40: ='Outputs - P&L'!H40 -> 0 | L40: ='Outputs - P&L'!I40 -> 0
B41: PAT | D41: =unit -> £ | E41: =SUM(E38:E40) -> 0 | F41: =SUM(F38:F40) -> 0 | G41: =SUM(G38:G40) -> 0 | H41: =SUM(H38:H40) -> 0 | I41: =SUM(I38:I40) -> 0 | J41: =SUM(J38:J40) -> 0 | K41: =SUM(K38:K40) -> 0 | L41: =SUM(L38:L40) -> 0
B43: Dividends Payable | D43: =unit -> £ | E43: =KeyInputs!E186 -> 0 | F43: =KeyInputs!F186 -> 0 | G43: =KeyInputs!G186 -> 0 | H43: ='Outputs - P&L'!E43 -> 0 | I43: ='Outputs - P&L'!F43 -> 0 | J43: ='Outputs - P&L'!G43 -> 0 | K43: ='Outputs - P&L'!H43 -> 0 | L43: ='Outputs - P&L'!I43 -> 0
B45: Retained profit | D45: =unit -> £ | E45: =SUM(E41:E43) -> 0 | F45: =SUM(F41:F43) -> 0 | G45: =SUM(G41:G43) -> 0 | H45: =SUM(H41:H43) -> 0 | I45: =SUM(I41:I43) -> 0 | J45: =SUM(J41:J43) -> 0 | K45: =SUM(K41:K43) -> 0 | L45: =SUM(L41:L43) -> 0
B47: EBITDA | E47: =E32+E34-E31 -> 0 | F47: =F32+F34-F31 -> 0 | G47: =G32+G34-G31 -> 0 | H47: =H32+H34-H31 -> 0 | I47: =I32+I34-I31 -> 0 | J47: =J32+J34-J31 -> 0 | K47: =K32+K34-K31 -> 0 | L47: =L32+L34-L31 -> 0
B49: KPI's
B50: Revenue growth | D50: % | E50: na | F50: =(F12-E12)/E12*100 -> #DIV/0! | G50: =(G12-F12)/F12*100 -> #DIV/0! | H50: =(H12-G12)/G12*100 -> #DIV/0! | I50: =(I12-H12)/H12*100 -> #DIV/0! | J50: =(J12-I12)/I12*100 -> #DIV/0! | K50: =(K12-J12)/J12*100 -> #DIV/0! | L50: =(L12-K12)/K12*100 -> #DIV/0!
B51: Gross margin | D51: % | E51: =E27/E12*100 -> #DIV/0! | F51: =F27/F12*100 -> #DIV/0! | G51: =G27/G12*100 -> #DIV/0! | H51: =H27/H12*100 -> #DIV/0! | I51: =I27/I12*100 -> #DIV/0! | J51: =J27/J12*100 -> #DIV/0! | K51: =K27/K12*100 -> #DIV/0! | L51: =L27/L12*100 -> #DIV/0!
B52: Gross profit growth | D52: % | E52: na | F52: =(F27-E27)/E27*100 -> #DIV/0! | G52: =(G27-F27)/F27*100 -> #DIV/0! | H52: =(H27-G27)/G27*100 -> #DIV/0! | I52: =(I27-H27)/H27*100 -> #DIV/0! | J52: =(J27-I27)/I27*100 -> #DIV/0! | K52: =(K27-J27)/J27*100 -> #DIV/0! | L52: =(L27-K27)/K27*100 -> #DIV/0!
B53: Operating margin | D53: % | E53: =E32/E12*100 -> #DIV/0! | F53: =F32/F12*100 -> #DIV/0! | G53: =G32/G12*100 -> #DIV/0! | H53: =H32/H12*100 -> #DIV/0! | I53: =I32/I12*100 -> #DIV/0! | J53: =J32/J12*100 -> #DIV/0! | K53: =K32/K12*100 -> #DIV/0! | L53: =L32/L12*100 -> #DIV/0!
B54: Sales volumes
B55: =KeyInputs!F21 -> Test | H55: =SUM(Revenue!E35:E37) -> 0 | I55: =SUM(Revenue!F35:F37) -> 0 | J55: =SUM(Revenue!G35:G37) -> 0 | K55: =SUM(Revenue!H35:H37) -> 0 | L55: =SUM(Revenue!I35:I37) -> 0
B56: =KeyInputs!F26 -> Insert Business Line2 | H56: =SUM(Revenue!E40:E42) -> 0 | I56: =SUM(Revenue!F40:F42) -> 0 | J56: =SUM(Revenue!G40:G42) -> 0 | K56: =SUM(Revenue!H40:H42) -> 0 | L56: =SUM(Revenue!I40:I42) -> 0
B57: =KeyInputs!F31 -> Insert Business Line3 | H57: =SUM(Revenue!E45:E47) -> 0 | I57: =SUM(Revenue!F45:F47) -> 0 | J57: =SUM(Revenue!G45:G47) -> 0 | K57: =SUM(Revenue!H45:H47) -> 0 | L57: =SUM(Revenue!I45:I47) -> 0
B58: EBITDA Interest cover | E58: =IFERROR(E47/-E36,0) -> 0 | F58: =IFERROR(F47/-F36,0) -> 0 | G58: =IFERROR(G47/-G36,0) -> 0 | H58: =IFERROR(H47/-H36,0) -> 0 | I58: =IFERROR(I47/-I36,0) -> 0 | J58: =IFERROR(J47/-J36,0) -> 0 | K58: =IFERROR(K47/-K36,0) -> 0 | L58: =IFERROR(L47/-L36,0) -> 0
A60: =Header1 -> 2 | B60: Balance Sheet
B62: Fixed assets | D62: =unit -> £ | E62: =SUM(E63:E66) -> 0 | F62: =SUM(F63:F66) -> 0 | G62: =SUM(G63:G66) -> 0 | H62: =SUM(H63:H66) -> 0 | I62: =SUM(I63:I66) -> 0 | J62: =SUM(J63:J66) -> 0 | K62: =SUM(K63:K66) -> 0 | L62: =SUM(L63:L66) -> 0 | X62: =SUM(X63:X67) -> 0 | Y62: =SUM(Y63:Y67) -> 0 | Z62: =SUM(Z63:Z67) -> 0 | AA62: =SUM(AA63:AA67) -> 0 | AB62: =SUM(AB63:AB67) -> 0 | AC62: =SUM(AC63:AC67) -> 0 | AD62: =SUM(AD63:AD67) -> 0 | AE62: =SUM(AE63:AE67) -> 0 | ... BW62: =SUM(BW63:BW67) -> 0
B63: =KeyInputs!C112 -> ICT equipement | D63: =unit -> £ | E63: =KeyInputs!E112 -> 0 | F63: =KeyInputs!F112 -> 0 | G63: =KeyInputs!G112 -> 0 | H63: ='Outputs - BalanceSheet'!E13 -> 0 | I63: ='Outputs - BalanceSheet'!F13 -> 0 | J63: ='Outputs - BalanceSheet'!G13 -> 0 | K63: ='Outputs - BalanceSheet'!H13 -> 0 | L63: ='Outputs - BalanceSheet'!I13 -> 0 | X63: =Capex!S73 -> 0 | Y63: =Capex!T73 -> 0 | Z63: =Capex!U73 -> 0 | AA63: =Capex!V73 -> 0 | AB63: =Capex!W73 -> 0 | AC63: =Capex!X73 -> 0 | AD63: =Capex!Y73 -> 0 | AE63: =Capex!Z73 -> 0 | ... BW63: =Capex!BR73 -> 0
B64: =KeyInputs!C113 -> F&F | D64: =unit -> £ | E64: =KeyInputs!E113 -> 0 | F64: =KeyInputs!F113 -> 0 | G64: =KeyInputs!G113 -> 0 | H64: ='Outputs - BalanceSheet'!E14 -> 0 | I64: ='Outputs - BalanceSheet'!F14 -> 0 | J64: ='Outputs - BalanceSheet'!G14 -> 0 | K64: ='Outputs - BalanceSheet'!H14 -> 0 | L64: ='Outputs - BalanceSheet'!I14 -> 0 | X64: =Capex!S83 -> 0 | Y64: =Capex!T83 -> 0 | Z64: =Capex!U83 -> 0 | AA64: =Capex!V83 -> 0 | AB64: =Capex!W83 -> 0 | AC64: =Capex!X83 -> 0 | AD64: =Capex!Y83 -> 0 | AE64: =Capex!Z83 -> 0 | ... BW64: =Capex!BR83 -> 0
B65: =KeyInputs!C114 -> Property | D65: =unit -> £ | E65: =KeyInputs!E114 -> 0 | F65: =KeyInputs!F114 -> 0 | G65: =KeyInputs!G114 -> 0 | H65: ='Outputs - BalanceSheet'!E15 -> 0 | I65: ='Outputs - BalanceSheet'!F15 -> 0 | J65: ='Outputs - BalanceSheet'!G15 -> 0 | K65: ='Outputs - BalanceSheet'!H15 -> 0 | L65: ='Outputs - BalanceSheet'!I15 -> 0 | X65: =Capex!S93 -> 0 | Y65: =Capex!T93 -> 0 | Z65: =Capex!U93 -> 0 | AA65: =Capex!V93 -> 0 | AB65: =Capex!W93 -> 0 | AC65: =Capex!X93 -> 0 | AD65: =Capex!Y93 -> 0 | AE65: =Capex!Z93 -> 0 | ... BW65: =Capex!BR93 -> 0
B66: =KeyInputs!C115 -> Vehicles | D66: =unit -> £ | E66: =KeyInputs!E115 -> 0 | F66: =KeyInputs!F115 -> 0 | G66: =KeyInputs!G115 -> 0 | H66: ='Outputs - BalanceSheet'!E16 -> 0 | I66: ='Outputs - BalanceSheet'!F16 -> 0 | J66: ='Outputs - BalanceSheet'!G16 -> 0 | K66: ='Outputs - BalanceSheet'!H16 -> 0 | L66: ='Outputs - BalanceSheet'!I16 -> 0 | X66: =Capex!S103 -> 0 | Y66: =Capex!T103 -> 0 | Z66: =Capex!U103 -> 0 | AA66: =Capex!V103 -> 0 | AB66: =Capex!W103 -> 0 | AC66: =Capex!X103 -> 0 | AD66: =Capex!Y103 -> 0 | AE66: =Capex!Z103 -> 0 | ... BW66: =Capex!BR103 -> 0
B67: =KeyInputs!C116 -> n/a | D67: =unit -> £ | E67: =KeyInputs!E116 -> 0 | F67: =KeyInputs!F116 -> 0 | G67: =KeyInputs!G116 -> 0 | H67: ='Outputs - BalanceSheet'!E17 -> 0 | I67: ='Outputs - BalanceSheet'!F17 -> 0 | J67: ='Outputs - BalanceSheet'!G17 -> 0 | K67: ='Outputs - BalanceSheet'!H17 -> 0 | L67: ='Outputs - BalanceSheet'!I17 -> 0 | X67: =Capex!S113 -> 0 | Y67: =Capex!T113 -> 0 | Z67: =Capex!U113 -> 0 | AA67: =Capex!V113 -> 0 | AB67: =Capex!W113 -> 0 | AC67: =Capex!X113 -> 0 | AD67: =Capex!Y113 -> 0 | AE67: =Capex!Z113 -> 0 | ... BW67: =Capex!BR113 -> 0
B69: Trade debtors | D69: =unit -> £ | E69: =SUM(E70:E72) -> 0 | F69: =SUM(F70:F72) -> 0 | G69: =SUM(G70:G72) -> 0 | H69: =SUM(H70:H72) -> 0 | I69: =SUM(I70:I72) -> 0 | J69: =SUM(J70:J72) -> 0 | K69: =SUM(K70:K72) -> 0 | L69: =SUM(L70:L72) -> 0 | X69: =SUM(X70:X72) -> 0 | Y69: =SUM(Y70:Y72) -> 0 | Z69: =SUM(Z70:Z72) -> 0 | AA69: =SUM(AA70:AA72) -> 0 | AB69: =SUM(AB70:AB72) -> 0 | AC69: =SUM(AC70:AC72) -> 0 | AD69: =SUM(AD70:AD72) -> 0 | AE69: =SUM(AE70:AE72) -> 0 | ... BW69: =SUM(BW70:BW72) -> 0
B70: =KeyInputs!C119 -> Test | D70: =unit -> £ | E70: =KeyInputs!E119 -> 0 | F70: =KeyInputs!F119 -> 0 | G70: =KeyInputs!G119 -> 0 | H70: ='Outputs - BalanceSheet'!E20 -> 0 | I70: ='Outputs - BalanceSheet'!F20 -> 0 | J70: ='Outputs - BalanceSheet'!G20 -> 0 | K70: ='Outputs - BalanceSheet'!H20 -> 0 | L70: ='Outputs - BalanceSheet'!I20 -> 0 | X70: =WorkingCapital!S57 -> 0 | Y70: =WorkingCapital!T57 -> 0 | Z70: =WorkingCapital!U57 -> 0 | AA70: =WorkingCapital!V57 -> 0 | AB70: =WorkingCapital!W57 -> 0 | AC70: =WorkingCapital!X57 -> 0 | AD70: =WorkingCapital!Y57 -> 0 | AE70: =WorkingCapital!Z57 -> 0 | ... BW70: =WorkingCapital!BR57 -> 0
B71: =KeyInputs!C120 -> Insert Business Line2 | D71: =unit -> £ | E71: =KeyInputs!E120 -> 0 | F71: =KeyInputs!F120 -> 0 | G71: =KeyInputs!G120 -> 0 | H71: ='Outputs - BalanceSheet'!E21 -> 0 | I71: ='Outputs - BalanceSheet'!F21 -> 0 | J71: ='Outputs - BalanceSheet'!G21 -> 0 | K71: ='Outputs - BalanceSheet'!H21 -> 0 | L71: ='Outputs - BalanceSheet'!I21 -> 0 | X71: =WorkingCapital!S68 -> 0 | Y71: =WorkingCapital!T68 -> 0 | Z71: =WorkingCapital!U68 -> 0 | AA71: =WorkingCapital!V68 -> 0 | AB71: =WorkingCapital!W68 -> 0 | AC71: =WorkingCapital!X68 -> 0 | AD71: =WorkingCapital!Y68 -> 0 | AE71: =WorkingCapital!Z68 -> 0 | ... BW71: =WorkingCapital!BR68 -> 0
B72: =KeyInputs!C121 -> Insert Business Line3 | D72: =unit -> £ | E72: =KeyInputs!E121 -> 0 | F72: =KeyInputs!F121 -> 0 | G72: =KeyInputs!G121 -> 0 | H72: ='Outputs - BalanceSheet'!E22 -> 0 | I72: ='Outputs - BalanceSheet'!F22 -> 0 | J72: ='Outputs - BalanceSheet'!G22 -> 0 | K72: ='Outputs - BalanceSheet'!H22 -> 0 | L72: ='Outputs - BalanceSheet'!I22 -> 0 | X72: =WorkingCapital!S79 -> 0 | Y72: =WorkingCapital!T79 -> 0 | Z72: =WorkingCapital!U79 -> 0 | AA72: =WorkingCapital!V79 -> 0 | AB72: =WorkingCapital!W79 -> 0 | AC72: =WorkingCapital!X79 -> 0 | AD72: =WorkingCapital!Y79 -> 0 | AE72: =WorkingCapital!Z79 -> 0 | ... BW72: =WorkingCapital!BR79 -> 0
B74: Stocks | D74: =unit -> £ | E74: =SUM(E75:E77) -> 0 | F74: =SUM(F75:F77) -> 0 | G74: =SUM(G75:G77) -> 0 | H74: =SUM(H75:H77) -> 0 | I74: =SUM(I75:I77) -> 0 | J74: =SUM(J75:J77) -> 0 | K74: =SUM(K75:K77) -> 0 | L74: =SUM(L75:L77) -> 0 | X74: =SUM(X75:X77) -> 0 | Y74: =SUM(Y75:Y77) -> 0 | Z74: =SUM(Z75:Z77) -> 0 | AA74: =SUM(AA75:AA77) -> 0 | AB74: =SUM(AB75:AB77) -> 0 | AC74: =SUM(AC75:AC77) -> 0 | AD74: =SUM(AD75:AD77) -> 0 | AE74: =SUM(AE75:AE77) -> 0 | ... BW74: =SUM(BW75:BW77) -> 0
B75: =B70 -> Test | D75: =unit -> £ | E75: =KeyInputs!E124 -> 0 | F75: =KeyInputs!F124 -> 0 | G75: =KeyInputs!G124 -> 0 | H75: ='Outputs - BalanceSheet'!E25 -> 0 | I75: ='Outputs - BalanceSheet'!F25 -> 0 | J75: ='Outputs - BalanceSheet'!G25 -> 0 | K75: ='Outputs - BalanceSheet'!H25 -> 0 | L75: ='Outputs - BalanceSheet'!I25 -> 0 | X75: =WorkingCapital!S94 -> 0 | Y75: =WorkingCapital!T94 -> 0 | Z75: =WorkingCapital!U94 -> 0 | AA75: =WorkingCapital!V94 -> 0 | AB75: =WorkingCapital!W94 -> 0 | AC75: =WorkingCapital!X94 -> 0 | AD75: =WorkingCapital!Y94 -> 0 | AE75: =WorkingCapital!Z94 -> 0 | ... BW75: =WorkingCapital!BR94 -> 0
B76: =B71 -> Insert Business Line2 | D76: =unit -> £ | E76: =KeyInputs!E125 -> 0 | F76: =KeyInputs!F125 -> 0 | G76: =KeyInputs!G125 -> 0 | H76: ='Outputs - BalanceSheet'!E26 -> 0 | I76: ='Outputs - BalanceSheet'!F26 -> 0 | J76: ='Outputs - BalanceSheet'!G26 -> 0 | K76: ='Outputs - BalanceSheet'!H26 -> 0 | L76: ='Outputs - BalanceSheet'!I26 -> 0 | X76: =WorkingCapital!S112 -> 0 | Y76: =WorkingCapital!T112 -> 0 | Z76: =WorkingCapital!U112 -> 0 | AA76: =WorkingCapital!V112 -> 0 | AB76: =WorkingCapital!W112 -> 0 | AC76: =WorkingCapital!X112 -> 0 | AD76: =WorkingCapital!Y112 -> 0 | AE76: =WorkingCapital!Z112 -> 0 | ... BW76: =WorkingCapital!BR112 -> 0
B77: =B72 -> Insert Business Line3 | D77: =unit -> £ | E77: =KeyInputs!E126 -> 0 | F77: =KeyInputs!F126 -> 0 | G77: =KeyInputs!G126 -> 0 | H77: ='Outputs - BalanceSheet'!E27 -> 0 | I77: ='Outputs - BalanceSheet'!F27 -> 0 | J77: ='Outputs - BalanceSheet'!G27 -> 0 | K77: ='Outputs - BalanceSheet'!H27 -> 0 | L77: ='Outputs - BalanceSheet'!I27 -> 0 | X77: =WorkingCapital!S123 -> 0 | Y77: =WorkingCapital!T123 -> 0 | Z77: =WorkingCapital!U123 -> 0 | AA77: =WorkingCapital!V123 -> 0 | AB77: =WorkingCapital!W123 -> 0 | AC77: =WorkingCapital!X123 -> 0 | AD77: =WorkingCapital!Y123 -> 0 | AE77: =WorkingCapital!Z123 -> 0 | ... BW77: =WorkingCapital!BR123 -> 0
B79: Cash at bank | D79: =unit -> £ | E79: =KeyInputs!E128 -> 0 | F79: =KeyInputs!F128 -> 0 | G79: =KeyInputs!G128 -> 0 | H79: ='Outputs - BalanceSheet'!E29 -> 0 | I79: ='Outputs - BalanceSheet'!F29 -> 0 | J79: ='Outputs - BalanceSheet'!G29 -> 0 | K79: ='Outputs - BalanceSheet'!H29 -> 0 | L79: ='Outputs - BalanceSheet'!I29 -> 0 | X79: =MAX('Outputs - Cashflow'!S$39,0) -> 0 | Y79: =MAX('Outputs - Cashflow'!T$39,0) -> 0 | Z79: =MAX('Outputs - Cashflow'!U$39,0) -> 0 | AA79: =MAX('Outputs - Cashflow'!V$39,0) -> 0 | AB79: =MAX('Outputs - Cashflow'!W$39,0) -> 0 | AC79: =MAX('Outputs - Cashflow'!X$39,0) -> 0 | AD79: =MAX('Outputs - Cashflow'!Y$39,0) -> 0 | AE79: =MAX('Outputs - Cashflow'!Z$39,0) -> 0 | ... BW79: =MAX('Outputs - Cashflow'!BR$39,0) -> 0
B80: Total assets | E80: =E79+E74+E69+E62 -> 0 | F80: =F79+F74+F69+F62 -> 0 | G80: =G79+G74+G69+G62 -> 0 | H80: =H79+H74+H69+H62 -> 0 | I80: =I79+I74+I69+I62 -> 0 | J80: =J79+J74+J69+J62 -> 0 | K80: =K79+K74+K69+K62 -> 0 | L80: =L79+L74+L69+L62 -> 0
B82: Overdraft | D82: =unit -> £ | E82: =KeyInputs!E130 -> 0 | F82: =KeyInputs!F130 -> 0 | G82: =KeyInputs!G130 -> 0 | H82: ='Outputs - BalanceSheet'!E31 -> 0 | I82: ='Outputs - BalanceSheet'!F31 -> 0 | J82: ='Outputs - BalanceSheet'!G31 -> 0 | K82: ='Outputs - BalanceSheet'!H31 -> 0 | L82: ='Outputs - BalanceSheet'!I31 -> 0 | X82: =MIN('Outputs - Cashflow'!S$39,0) -> 0 | Y82: =MIN('Outputs - Cashflow'!T$39,0) -> 0 | Z82: =MIN('Outputs - Cashflow'!U$39,0) -> 0 | AA82: =MIN('Outputs - Cashflow'!V$39,0) -> 0 | AB82: =MIN('Outputs - Cashflow'!W$39,0) -> 0 | AC82: =MIN('Outputs - Cashflow'!X$39,0) -> 0 | AD82: =MIN('Outputs - Cashflow'!Y$39,0) -> 0 | AE82: =MIN('Outputs - Cashflow'!Z$39,0) -> 0 | ... BW82: =MIN('Outputs - Cashflow'!BR$39,0) -> 0
B83: Trade creditors | D83: =unit -> £ | E83: =KeyInputs!E131 -> 0 | F83: =KeyInputs!F131 -> 0 | G83: =KeyInputs!G131 -> 0 | H83: ='Outputs - BalanceSheet'!E32 -> 0 | I83: ='Outputs - BalanceSheet'!F32 -> 0 | J83: ='Outputs - BalanceSheet'!G32 -> 0 | K83: ='Outputs - BalanceSheet'!H32 -> 0 | L83: ='Outputs - BalanceSheet'!I32 -> 0 | X83: =WorkingCapital!S$91 -> 0 | Y83: =WorkingCapital!T$91 -> 0 | Z83: =WorkingCapital!U$91 -> 0 | AA83: =WorkingCapital!V$91 -> 0 | AB83: =WorkingCapital!W$91 -> 0 | AC83: =WorkingCapital!X$91 -> 0 | AD83: =WorkingCapital!Y$91 -> 0 | AE83: =WorkingCapital!Z$91 -> 0 | ... BW83: =WorkingCapital!BR$91 -> 0
B84: VAT | D84: =unit -> £ | E84: =KeyInputs!E132 -> 0 | F84: =KeyInputs!F132 -> 0 | G84: =KeyInputs!G132 -> 0 | H84: ='Outputs - BalanceSheet'!E33 -> 0 | I84: ='Outputs - BalanceSheet'!F33 -> 0 | J84: ='Outputs - BalanceSheet'!G33 -> 0 | K84: ='Outputs - BalanceSheet'!H33 -> 0 | L84: ='Outputs - BalanceSheet'!I33 -> 0
B85: Interest on debt payable | D85: =unit -> £ | E85: =KeyInputs!E133 -> 0 | F85: =KeyInputs!F133 -> 0 | G85: =KeyInputs!G133 -> 0 | H85: ='Outputs - BalanceSheet'!E34 -> 0 | I85: ='Outputs - BalanceSheet'!F34 -> 0 | J85: ='Outputs - BalanceSheet'!G34 -> 0 | K85: ='Outputs - BalanceSheet'!H34 -> 0 | L85: ='Outputs - BalanceSheet'!I34 -> 0 | X85: =DebtFinancing!S$24 -> 0 | Y85: =DebtFinancing!T$24 -> 0 | Z85: =DebtFinancing!U$24 -> 0 | AA85: =DebtFinancing!V$24 -> 0 | AB85: =DebtFinancing!W$24 -> 0 | AC85: =DebtFinancing!X$24 -> 0 | AD85: =DebtFinancing!Y$24 -> 0 | AE85: =DebtFinancing!Z$24 -> 0 | ... BW85: =DebtFinancing!BR$24 -> 0
B86: Term debt | D86: =unit -> £ | E86: =KeyInputs!E134 -> 0 | F86: =KeyInputs!F134 -> 0 | G86: =KeyInputs!G134 -> 0 | H86: ='Outputs - BalanceSheet'!E35 -> 0 | I86: ='Outputs - BalanceSheet'!F35 -> 0 | J86: ='Outputs - BalanceSheet'!G35 -> 0 | K86: ='Outputs - BalanceSheet'!H35 -> 0 | L86: ='Outputs - BalanceSheet'!I35 -> 0 | X86: =DebtFinancing!S$17 -> 0 | Y86: =DebtFinancing!T$17 -> 0 | Z86: =DebtFinancing!U$17 -> 0 | AA86: =DebtFinancing!V$17 -> 0 | AB86: =DebtFinancing!W$17 -> 0 | AC86: =DebtFinancing!X$17 -> 0 | AD86: =DebtFinancing!Y$17 -> 0 | AE86: =DebtFinancing!Z$17 -> 0 | ... BW86: =DebtFinancing!BR$17 -> 0
B87: Grant deferred income | D87: =unit -> £ | E87: =KeyInputs!E135 -> 0 | F87: =KeyInputs!F135 -> 0 | G87: =KeyInputs!G135 -> 0 | H87: ='Outputs - BalanceSheet'!E36 -> 0 | I87: ='Outputs - BalanceSheet'!F36 -> 0 | J87: ='Outputs - BalanceSheet'!G36 -> 0 | K87: ='Outputs - BalanceSheet'!H36 -> 0 | L87: ='Outputs - BalanceSheet'!I36 -> 0
B88: Current tax | D88: =unit -> £ | E88: =KeyInputs!E136 -> 0 | F88: =KeyInputs!F136 -> 0 | G88: =KeyInputs!G136 -> 0 | H88: ='Outputs - BalanceSheet'!E37 -> 0 | I88: ='Outputs - BalanceSheet'!F37 -> 0 | J88: ='Outputs - BalanceSheet'!G37 -> 0 | K88: ='Outputs - BalanceSheet'!H37 -> 0 | L88: ='Outputs - BalanceSheet'!I37 -> 0 | X88: =TAX!S$44 -> 0 | Y88: =TAX!T$44 -> 0 | Z88: =TAX!U$44 -> 0 | AA88: =TAX!V$44 -> 0 | AB88: =TAX!W$44 -> 0 | AC88: =TAX!X$44 -> 0 | AD88: =TAX!Y$44 -> 0 | AE88: =TAX!Z$44 -> 0 | ... BW88: =TAX!BR$44 -> 0
B90: Net assets | D90: =unit -> £ | E90: =SUM(E62,E69,E74,E79,E82:E88) -> 0 | F90: =SUM(F62,F69,F74,F79,F82:F88) -> 0 | G90: =SUM(G62,G69,G74,G79,G82:G88) -> 0 | H90: =SUM(H62,H69,H74,H79,H82:H88) -> 0 | I90: =SUM(I62,I69,I74,I79,I82:I88) -> 0 | J90: =SUM(J62,J69,J74,J79,J82:J88) -> 0 | K90: =SUM(K62,K69,K74,K79,K82:K88) -> 0 | L90: =SUM(L62,L69,L74,L79,L82:L88) -> 0 | X90: =SUM(X62,X69,X74,X79,X82:X88) -> 0 | Y90: =SUM(Y62,Y69,Y74,Y79,Y82:Y88) -> 0 | Z90: =SUM(Z62,Z69,Z74,Z79,Z82:Z88) -> 0 | AA90: =SUM(AA62,AA69,AA74,AA79,AA82:AA88) -> 0 | AB90: =SUM(AB62,AB69,AB74,AB79,AB82:AB88) -> 0 | AC90: =SUM(AC62,AC69,AC74,AC79,AC82:AC88) -> 0 | AD90: =SUM(AD62,AD69,AD74,AD79,AD82:AD88) -> 0 | AE90: =SUM(AE62,AE69,AE74,AE79,AE82:AE88) -> 0 | ... BW90: =SUM(BW62,BW69,BW74,BW79,BW82:BW88) -> 0
B92: Share capital | D92: =unit -> £ | E92: =KeyInputs!E140 -> 0 | F92: =KeyInputs!F140 -> 0 | G92: =KeyInputs!G140 -> 0 | H92: ='Outputs - BalanceSheet'!E41 -> 0 | I92: ='Outputs - BalanceSheet'!F41 -> 0 | J92: ='Outputs - BalanceSheet'!G41 -> 0 | K92: ='Outputs - BalanceSheet'!H41 -> 0 | L92: ='Outputs - BalanceSheet'!I41 -> 0 | X92: =W92 -> 0 | Y92: =X92 -> 0 | Z92: =Y92 -> 0 | AA92: =Z92 -> 0 | AB92: =AA92 -> 0 | AC92: =AB92 -> 0 | AD92: =AC92 -> 0 | AE92: =AD92 -> 0 | ... BW92: =BV92 -> 0
B93: P&L reserve | D93: =unit -> £ | E93: =KeyInputs!E141 -> 0 | F93: =KeyInputs!F141 -> 0 | G93: =KeyInputs!G141 -> 0 | H93: ='Outputs - BalanceSheet'!E42 -> 0 | I93: ='Outputs - BalanceSheet'!F42 -> 0 | J93: ='Outputs - BalanceSheet'!G42 -> 0 | K93: ='Outputs - BalanceSheet'!H42 -> 0 | L93: ='Outputs - BalanceSheet'!I42 -> 0 | X93: ='Outputs - P&L'!S84 -> 0 | Y93: ='Outputs - P&L'!T84 -> 0 | Z93: ='Outputs - P&L'!U84 -> 0 | AA93: ='Outputs - P&L'!V84 -> 0 | AB93: ='Outputs - P&L'!W84 -> 0 | AC93: ='Outputs - P&L'!X84 -> 0 | AD93: ='Outputs - P&L'!Y84 -> 0 | AE93: ='Outputs - P&L'!Z84 -> 0 | ... BW93: ='Outputs - P&L'!BR84 -> 0
B95: Shareholders' funds | D95: =unit -> £ | E95: =SUM(E92:E94) -> 0 | F95: =SUM(F92:F94) -> 0 | G95: =SUM(G92:G94) -> 0 | H95: =SUM(H92:H94) -> 0 | I95: =SUM(I92:I94) -> 0 | J95: =SUM(J92:J94) -> 0 | K95: =SUM(K92:K94) -> 0 | L95: =SUM(L92:L94) -> 0 | X95: =SUM(X92:X94) -> 0 | Y95: =SUM(Y92:Y94) -> 0 | Z95: =SUM(Z92:Z94) -> 0 | AA95: =SUM(AA92:AA94) -> 0 | AB95: =SUM(AB92:AB94) -> 0 | AC95: =SUM(AC92:AC94) -> 0 | AD95: =SUM(AD92:AD94) -> 0 | AE95: =SUM(AE92:AE94) -> 0 | ... BW95: =SUM(BW92:BW94) -> 0
A97: =Header1 -> 3 | B97: Cash Flow Statement
B99: Operating profit | D99: =unit -> £ | E99: =KeyInputs!E196 -> 0 | F99: =KeyInputs!F196 -> 0 | G99: =KeyInputs!G196 -> 0 | H99: ='Outputs - Cashflow'!E12 -> 0 | I99: ='Outputs - Cashflow'!F12 -> 0 | J99: ='Outputs - Cashflow'!G12 -> 0 | K99: ='Outputs - Cashflow'!H12 -> 0 | L99: ='Outputs - Cashflow'!I12 -> 0
B101: add back depreciation | D101: =unit -> £ | E101: =KeyInputs!E198 -> 0 | F101: =KeyInputs!F198 -> 0 | G101: =KeyInputs!G198 -> 0 | H101: ='Outputs - Cashflow'!E14 -> 0 | I101: ='Outputs - Cashflow'!F14 -> 0 | J101: ='Outputs - Cashflow'!G14 -> 0 | K101: ='Outputs - Cashflow'!H14 -> 0 | L101: ='Outputs - Cashflow'!I14 -> 0
B102: movement in trade debtors | D102: =unit -> £ | E102: =KeyInputs!E199 -> 0 | F102: =KeyInputs!F199 -> 0 | G102: =KeyInputs!G199 -> 0 | H102: ='Outputs - Cashflow'!E15 -> 0 | I102: ='Outputs - Cashflow'!F15 -> 0 | J102: ='Outputs - Cashflow'!G15 -> 0 | K102: ='Outputs - Cashflow'!H15 -> 0 | L102: ='Outputs - Cashflow'!I15 -> 0
B103: movement in stocks | D103: =unit -> £ | E103: =KeyInputs!E200 -> 0 | F103: =KeyInputs!F200 -> 0 | G103: =KeyInputs!G200 -> 0 | H103: ='Outputs - Cashflow'!E16 -> 0 | I103: ='Outputs - Cashflow'!F16 -> 0 | J103: ='Outputs - Cashflow'!G16 -> 0 | K103: ='Outputs - Cashflow'!H16 -> 0 | L103: ='Outputs - Cashflow'!I16 -> 0
B104: movement in trade creditors | D104: =unit -> £ | E104: =KeyInputs!E201 -> 0 | F104: =KeyInputs!F201 -> 0 | G104: =KeyInputs!G201 -> 0 | H104: ='Outputs - Cashflow'!E17 -> 0 | I104: ='Outputs - Cashflow'!F17 -> 0 | J104: ='Outputs - Cashflow'!G17 -> 0 | K104: ='Outputs - Cashflow'!H17 -> 0 | L104: ='Outputs - Cashflow'!I17 -> 0
B105: movement in VAT | D105: =unit -> £ | E105: =KeyInputs!E202 -> 0 | F105: =KeyInputs!F202 -> 0 | G105: =KeyInputs!G202 -> 0 | H105: ='Outputs - Cashflow'!E18 -> 0 | I105: ='Outputs - Cashflow'!F18 -> 0 | J105: ='Outputs - Cashflow'!G18 -> 0 | K105: ='Outputs - Cashflow'!H18 -> 0 | L105: ='Outputs - Cashflow'!I18 -> 0
B106: Operating cash flow | D106: =unit -> £ | E106: =SUM(E99:E105) -> 0 | F106: =SUM(F99:F105) -> 0 | G106: =SUM(G99:G105) -> 0 | H106: =SUM(H99:H105) -> 0 | I106: =SUM(I99:I105) -> 0 | J106: =SUM(J99:J105) -> 0 | K106: =SUM(K99:K105) -> 0 | L106: =SUM(L99:L105) -> 0
B108: Capital expenditure | D108: =unit -> £ | E108: =KeyInputs!E205 -> 0 | F108: =KeyInputs!F205 -> 0 | G108: =KeyInputs!G205 -> 0 | H108: ='Outputs - Cashflow'!E21 -> 0 | I108: ='Outputs - Cashflow'!F21 -> 0 | J108: ='Outputs - Cashflow'!G21 -> 0 | K108: ='Outputs - Cashflow'!H21 -> 0 | L108: ='Outputs - Cashflow'!I21 -> 0
B109: Proceeds of disposals | D109: =unit -> £ | E109: =KeyInputs!E206 -> 0 | F109: =KeyInputs!F206 -> 0 | G109: =KeyInputs!G206 -> 0 | H109: ='Outputs - Cashflow'!E22 -> 0 | I109: ='Outputs - Cashflow'!F22 -> 0 | J109: ='Outputs - Cashflow'!G22 -> 0 | K109: ='Outputs - Cashflow'!H22 -> 0 | L109: ='Outputs - Cashflow'!I22 -> 0
B111: Grant received | D111: =unit -> £ | E111: =KeyInputs!E208 -> 0 | F111: =KeyInputs!F208 -> 0 | G111: =KeyInputs!G208 -> 0 | H111: ='Outputs - Cashflow'!E24 -> 0 | I111: ='Outputs - Cashflow'!F24 -> 0 | J111: ='Outputs - Cashflow'!G24 -> 0 | K111: ='Outputs - Cashflow'!H24 -> 0 | L111: ='Outputs - Cashflow'!I24 -> 0
B113: Other income | D113: =unit -> £ | H113: ='Outputs - Cashflow'!E25 -> 0 | I113: ='Outputs - Cashflow'!F25 -> 0 | J113: ='Outputs - Cashflow'!G25 -> 0 | K113: ='Outputs - Cashflow'!H25 -> 0 | L113: ='Outputs - Cashflow'!I25 -> 0
B114: Equity finance received | D114: =unit -> £ | H114: ='Outputs - Cashflow'!E26 -> 0 | I114: ='Outputs - Cashflow'!F26 -> 0 | J114: ='Outputs - Cashflow'!G26 -> 0 | K114: ='Outputs - Cashflow'!H26 -> 0 | L114: ='Outputs - Cashflow'!I26 -> 0
B115: Drawings on debt | D115: =unit -> £ | E115: =KeyInputs!E210 -> 0 | F115: =KeyInputs!F210 -> 0 | G115: =KeyInputs!G210 -> 0 | H115: ='Outputs - Cashflow'!E27 -> 0 | I115: ='Outputs - Cashflow'!F27 -> 0 | J115: ='Outputs - Cashflow'!G27 -> 0 | K115: ='Outputs - Cashflow'!H27 -> 0 | L115: ='Outputs - Cashflow'!I27 -> 0
B116: Repayments of debt | D116: =unit -> £ | E116: =KeyInputs!E211 -> 0 | F116: =KeyInputs!F211 -> 0 | G116: =KeyInputs!G211 -> 0 | H116: ='Outputs - Cashflow'!E28 -> 0 | I116: ='Outputs - Cashflow'!F28 -> 0 | J116: ='Outputs - Cashflow'!G28 -> 0 | K116: ='Outputs - Cashflow'!H28 -> 0 | L116: ='Outputs - Cashflow'!I28 -> 0
B118: Interest on debt | D118: =unit -> £ | E118: =KeyInputs!E213 -> 0 | F118: =KeyInputs!F213 -> 0 | G118: =KeyInputs!G213 -> 0 | H118: ='Outputs - Cashflow'!E30 -> 0 | I118: ='Outputs - Cashflow'!F30 -> 0 | J118: ='Outputs - Cashflow'!G30 -> 0 | K118: ='Outputs - Cashflow'!H30 -> 0 | L118: ='Outputs - Cashflow'!I30 -> 0
B120: Taxation | D120: =unit -> £ | E120: =KeyInputs!E215 -> 0 | F120: =KeyInputs!F215 -> 0 | G120: =KeyInputs!G215 -> 0 | H120: ='Outputs - Cashflow'!E32 -> 0 | I120: ='Outputs - Cashflow'!F32 -> 0 | J120: ='Outputs - Cashflow'!G32 -> 0 | K120: ='Outputs - Cashflow'!H32 -> 0 | L120: ='Outputs - Cashflow'!I32 -> 0
B122: Dividends payable | D122: =unit -> £ | E122: =KeyInputs!E217 -> 0 | F122: =KeyInputs!F217 -> 0 | G122: =KeyInputs!G217 -> 0 | H122: ='Outputs - Cashflow'!E34 -> 0 | I122: ='Outputs - Cashflow'!F34 -> 0 | J122: ='Outputs - Cashflow'!G34 -> 0 | K122: ='Outputs - Cashflow'!H34 -> 0 | L122: ='Outputs - Cashflow'!I34 -> 0
B124: Net cash flow | D124: =unit -> £ | E124: =SUM(E106:E123) -> 0 | F124: =SUM(F106:F123) -> 0 | G124: =SUM(G106:G123) -> 0 | H124: =SUM(H106:H123) -> 0 | I124: =SUM(I106:I123) -> 0 | J124: =SUM(J106:J123) -> 0 | K124: =SUM(K106:K123) -> 0 | L124: =SUM(L106:L123) -> 0
B126: Cash balance BF | D126: =unit -> £ | E126: =KeyInputs!E221 -> 0 | F126: =KeyInputs!F221 -> 0 | G126: =KeyInputs!G221 -> 0 | H126: ='Outputs - Cashflow'!E38 -> 0 | I126: ='Outputs - Cashflow'!F38 -> 0 | J126: ='Outputs - Cashflow'!G38 -> 0 | K126: ='Outputs - Cashflow'!H38 -> 0 | L126: ='Outputs - Cashflow'!I38 -> 0
B127: Cash balance CF | D127: =unit -> £ | E127: =SUM(E124:E126) -> 0 | F127: =SUM(F124:F126) -> 0 | G127: =SUM(G124:G126) -> 0 | H127: =SUM(H124:H126) -> 0 | I127: =SUM(I124:I126) -> 0 | J127: =SUM(J124:J126) -> 0 | K127: =SUM(K124:K126) -> 0 | L127: =SUM(L124:L126) -> 0
B128: Cash/Overdraft interest | E128: =KeyInputs!E223 -> 0 | F128: =KeyInputs!F223 -> 0 | G128: =KeyInputs!G223 -> 0 | H128: ='Outputs - Cashflow'!E40 -> 0 | I128: ='Outputs - Cashflow'!F40 -> 0 | J128: ='Outputs - Cashflow'!G40 -> 0 | K128: ='Outputs - Cashflow'!H40 -> 0 | L128: ='Outputs - Cashflow'!I40 -> 0
B129: Cash balance CF | E129: =SUM(E127:E128) -> 0 | F129: =SUM(F127:F128) -> 0 | G129: =SUM(G127:G128) -> 0 | H129: =SUM(H127:H128) -> 0 | I129: =SUM(I127:I128) -> 0 | J129: =SUM(J127:J128) -> 0 | K129: =SUM(K127:K128) -> 0 | L129: =SUM(L127:L128) -> 0
B131: KPI's
B132: Operating cash flow conversion | D132: % | E132: =IFERROR(E124/E99,"-") -> - | F132: =IFERROR(F124/F99,"-") -> - | G132: =IFERROR(G124/G99,"-") -> - | H132: =IFERROR(H124/H99,"-") -> - | I132: =IFERROR(I124/I99,"-") -> - | J132: =IFERROR(J124/J99,"-") -> - | K132: =IFERROR(K124/K99,"-") -> - | L132: =IFERROR(L124/L99,"-") -> -
A134: End of sheet
B136: Checks
B137: Retained profit | H137: =H45-'Outputs - P&L'!E45 -> 0 | I137: =I45-'Outputs - P&L'!F45 -> 0 | J137: =J45-'Outputs - P&L'!G45 -> 0 | K137: =K45-'Outputs - P&L'!H45 -> 0 | L137: =L45-'Outputs - P&L'!I45 -> 0
...

Sheet Outputs - P&L
A3: =IF(KeyInputs!$F$14=0,"Company Name",KeyInputs!$F$14) -> Company Name
A4: Profit and Loss Account
D5: =KeyInputs!D5 -> Year | E5: =KeyInputs!H5 -> 2015 | F5: =KeyInputs!I5 -> 2016 | G5: =KeyInputs!J5 -> 2017 | H5: =KeyInputs!K5 -> 2018 | I5: =KeyInputs!L5 -> 2019 | K5: =KeyInputs!N5 -> 2015 | L5: =KeyInputs!O5 -> 2015 | M5: =KeyInputs!P5 -> 2015 | N5: =KeyInputs!Q5 -> 2015 | O5: =KeyInputs!R5 -> 2015 | P5: =KeyInputs!S5 -> 2015 | Q5: =KeyInputs!T5 -> 2015 | R5: =KeyInputs!U5 -> 2015 | ... BR5: =KeyInputs!BU5 -> 2019
D6: =KeyInputs!D6 -> Period number | E6: =KeyInputs!H6 -> 1 | F6: =KeyInputs!I6 -> 2 | G6: =KeyInputs!J6 -> 3 | H6: =KeyInputs!K6 -> 4 | I6: =KeyInputs!L6 -> 5 | K6: =KeyInputs!N6 -> 1 | L6: =KeyInputs!O6 -> 2 | M6: =KeyInputs!P6 -> 3 | N6: =KeyInputs!Q6 -> 4 | O6: =KeyInputs!R6 -> 5 | P6: =KeyInputs!S6 -> 6 | Q6: =KeyInputs!T6 -> 7 | R6: =KeyInputs!U6 -> 8 | ... BR6: =KeyInputs!BU6 -> 60
D7: =KeyInputs!D7 -> Period starts | E7: =KeyInputs!H7 -> 42005 | F7: =KeyInputs!I7 -> 42370 | G7: =KeyInputs!J7 -> 42736 | H7: =KeyInputs!K7 -> 43101 | I7: =KeyInputs!L7 -> 43466 | K7: =KeyInputs!N7 -> 42005 | L7: =KeyInputs!O7 -> 42036 | M7: =KeyInputs!P7 -> 42064 | N7: =KeyInputs!Q7 -> 42095 | O7: =KeyInputs!R7 -> 42125 | P7: =KeyInputs!S7 -> 42156 | Q7: =KeyInputs!T7 -> 42186 | R7: =KeyInputs!U7 -> 42217 | ... BR7: =KeyInputs!BU7 -> 43800
B8: =IF(Check!$C$12=0,"All checks are OK","There are "&Check!$C$12&" error/errors") -> All checks are OK | D8: =KeyInputs!D8 -> Period ends | E8: =KeyInputs!H8 -> 42369 | F8: =KeyInputs!I8 -> 42735 | G8: =KeyInputs!J8 -> 43100 | H8: =KeyInputs!K8 -> 43465 | I8: =KeyInputs!L8 -> 43830 | K8: =KeyInputs!N8 -> 42035 | L8: =KeyInputs!O8 -> 42063 | M8: =KeyInputs!P8 -> 42094 | N8: =KeyInputs!Q8 -> 42124 | O8: =KeyInputs!R8 -> 42155 | P8: =KeyInputs!S8 -> 42185 | Q8: =KeyInputs!T8 -> 42216 | R8: =KeyInputs!U8 -> 42247 | ... BR8: =KeyInputs!BU8 -> 43830
A10: =Header1 -> 1 | B10: Profit & Loss Account
B12: Sales | D12: =unit -> £ | E12: =SUMIF($K$5:$BR$5,E$5,$K12:$BR12) -> 0 | F12: =SUMIF($K$5:$BR$5,F$5,$K12:$BR12) -> 0 | G12: =SUMIF($K$5:$BR$5,G$5,$K12:$BR12) -> 0 | H12: =SUMIF($K$5:$BR$5,H$5,$K12:$BR12) -> 0 | I12: =SUMIF($K$5:$BR$5,I$5,$K12:$BR12) -> 0 | K12: =SUM(K13:K15) -> 0 | L12: =SUM(L13:L15) -> 0 | M12: =SUM(M13:M15) -> 0 | N12: =SUM(N13:N15) -> 0 | O12: =SUM(O13:O15) -> 0 | P12: =SUM(P13:P15) -> 0 | Q12: =SUM(Q13:Q15) -> 0 | R12: =SUM(R13:R15) -> 0 | ... BR12: =SUM(BR13:BR15) -> 0
B13: =KeyInputs!F21 -> Test | D13: =unit -> £ | E13: =SUMIF($K$5:$BR$5,E$5,$K13:$BR13) -> 0 | F13: =SUMIF($K$5:$BR$5,F$5,$K13:$BR13) -> 0 | G13: =SUMIF($K$5:$BR$5,G$5,$K13:$BR13) -> 0 | H13: =SUMIF($K$5:$BR$5,H$5,$K13:$BR13) -> 0 | I13: =SUMIF($K$5:$BR$5,I$5,$K13:$BR13) -> 0 | K13: =Revenue!K16 -> 0 | L13: =Revenue!L16 -> 0 | M13: =Revenue!M16 -> 0 | N13: =Revenue!N16 -> 0 | O13: =Revenue!O16 -> 0 | P13: =Revenue!P16 -> 0 | Q13: =Revenue!Q16 -> 0 | R13: =Revenue!R16 -> 0 | ... BR13: =Revenue!BR16 -> 0
B14: =KeyInputs!F26 -> Insert Business Line2 | D14: =unit -> £ | E14: =SUMIF($K$5:$BR$5,E$5,$K14:$BR14) -> 0 | F14: =SUMIF($K$5:$BR$5,F$5,$K14:$BR14) -> 0 | G14: =SUMIF($K$5:$BR$5,G$5,$K14:$BR14) -> 0 | H14: =SUMIF($K$5:$BR$5,H$5,$K14:$BR14) -> 0 | I14: =SUMIF($K$5:$BR$5,I$5,$K14:$BR14) -> 0 | K14: =Revenue!K22 -> 0 | L14: =Revenue!L22 -> 0 | M14: =Revenue!M22 -> 0 | N14: =Revenue!N22 -> 0 | O14: =Revenue!O22 -> 0 | P14: =Revenue!P22 -> 0 | Q14: =Revenue!Q22 -> 0 | R14: =Revenue!R22 -> 0 | ... BR14: =Revenue!BR22 -> 0
B15: =KeyInputs!F31 -> Insert Business Line3 | D15: =unit -> £ | E15: =SUMIF($K$5:$BR$5,E$5,$K15:$BR15) -> 0 | F15: =SUMIF($K$5:$BR$5,F$5,$K15:$BR15) -> 0 | G15: =SUMIF($K$5:$BR$5,G$5,$K15:$BR15) -> 0 | H15: =SUMIF($K$5:$BR$5,H$5,$K15:$BR15) -> 0 | I15: =SUMIF($K$5:$BR$5,I$5,$K15:$BR15) -> 0 | K15: =Revenue!K28 -> 0 | L15: =Revenue!L28 -> 0 | M15: =Revenue!M28 -> 0 | N15: =Revenue!N28 -> 0 | O15: =Revenue!O28 -> 0 | P15: =Revenue!P28 -> 0 | Q15: =Revenue!Q28 -> 0 | R15: =Revenue!R28 -> 0 | ... BR15: =Revenue!BR28 -> 0
B17: Variable costs | D17: =unit -> £ | E17: =SUMIF($K$5:$BR$5,E$5,$K17:$BR17) -> 0 | F17: =SUMIF($K$5:$BR$5,F$5,$K17:$BR17) -> 0 | G17: =SUMIF($K$5:$BR$5,G$5,$K17:$BR17) -> 0 | H17: =SUMIF($K$5:$BR$5,H$5,$K17:$BR17) -> 0 | I17: =SUMIF($K$5:$BR$5,I$5,$K17:$BR17) -> 0 | K17: =SUM(K18:K20) -> 0 | L17: =SUM(L18:L20) -> 0 | M17: =SUM(M18:M20) -> 0 | N17: =SUM(N18:N20) -> 0 | O17: =SUM(O18:O20) -> 0 | P17: =SUM(P18:P20) -> 0 | Q17: =SUM(Q18:Q20) -> 0 | R17: =SUM(R18:R20) -> 0 | ... BR17: =SUM(BR18:BR20) -> 0
B18: =B13 -> Test | D18: =unit -> £ | E18: =SUMIF($K$5:$BR$5,E$5,$K18:$BR18) -> 0 | F18: =SUMIF($K$5:$BR$5,F$5,$K18:$BR18) -> 0 | G18: =SUMIF($K$5:$BR$5,G$5,$K18:$BR18) -> 0 | H18: =SUMIF($K$5:$BR$5,H$5,$K18:$BR18) -> 0 | I18: =SUMIF($K$5:$BR$5,I$5,$K18:$BR18) -> 0 | K18: =VariableCosts!K16 -> 0 | L18: =VariableCosts!L16 -> 0 | M18: =VariableCosts!M16 -> 0 | N18: =VariableCosts!N16 -> 0 | O18: =VariableCosts!O16 -> 0 | P18: =VariableCosts!P16 -> 0 | Q18: =VariableCosts!Q16 -> 0 | R18: =VariableCosts!R16 -> 0 | ... BR18: =VariableCosts!BR16 -> 0
B19: =B14 -> Insert Business Line2 | D19: =unit -> £ | E19: =SUMIF($K$5:$BR$5,E$5,$K19:$BR19) -> 0 | F19: =SUMIF($K$5:$BR$5,F$5,$K19:$BR19) -> 0 | G19: =SUMIF($K$5:$BR$5,G$5,$K19:$BR19) -> 0 | H19: =SUMIF($K$5:$BR$5,H$5,$K19:$BR19) -> 0 | I19: =SUMIF($K$5:$BR$5,I$5,$K19:$BR19) -> 0 | K19: =VariableCosts!K22 -> 0 | L19: =VariableCosts!L22 -> 0 | M19: =VariableCosts!M22 -> 0 | N19: =VariableCosts!N22 -> 0 | O19: =VariableCosts!O22 -> 0 | P19: =VariableCosts!P22 -> 0 | Q19: =VariableCosts!Q22 -> 0 | R19: =VariableCosts!R22 -> 0 | ... BR19: =VariableCosts!BR22 -> 0
B20: =B15 -> Insert Business Line3 | D20: =unit -> £ | E20: =SUMIF($K$5:$BR$5,E$5,$K20:$BR20) -> 0 | F20: =SUMIF($K$5:$BR$5,F$5,$K20:$BR20) -> 0 | G20: =SUMIF($K$5:$BR$5,G$5,$K20:$BR20) -> 0 | H20: =SUMIF($K$5:$BR$5,H$5,$K20:$BR20) -> 0 | I20: =SUMIF($K$5:$BR$5,I$5,$K20:$BR20) -> 0 | K20: =VariableCosts!K27 -> 0 | L20: =VariableCosts!L27 -> 0 | M20: =VariableCosts!M27 -> 0 | N20: =VariableCosts!N27 -> 0 | O20: =VariableCosts!O27 -> 0 | P20: =VariableCosts!P27 -> 0 | Q20: =VariableCosts!Q27 -> 0 | R20: =VariableCosts!R27 -> 0 | ... BR20: =VariableCosts!BR27 -> 0
B22: Direct staff costs | D22: =unit -> £ | E22: =SUMIF($K$5:$BR$5,E$5,$K22:$BR22) -> 0 | F22: =SUMIF($K$5:$BR$5,F$5,$K22:$BR22) -> 0 | G22: =SUMIF($K$5:$BR$5,G$5,$K22:$BR22) -> 0 | H22: =SUMIF($K$5:$BR$5,H$5,$K22:$BR22) -> 0 | I22: =SUMIF($K$5:$BR$5,I$5,$K22:$BR22) -> 0 | K22: =SUM(K23:K25) -> 0 | L22: =SUM(L23:L25) -> 0 | M22: =SUM(M23:M25) -> 0 | N22: =SUM(N23:N25) -> 0 | O22: =SUM(O23:O25) -> 0 | P22: =SUM(P23:P25) -> 0 | Q22: =SUM(Q23:Q25) -> 0 | R22: =SUM(R23:R25) -> 0 | ... BR22: =SUM(BR23:BR25) -> 0
B23: =B13 -> Test | D23: =unit -> £ | E23: =SUMIF($K$5:$BR$5,E$5,$K23:$BR23) -> 0 | F23: =SUMIF($K$5:$BR$5,F$5,$K23:$BR23) -> 0 | G23: =SUMIF($K$5:$BR$5,G$5,$K23:$BR23) -> 0 | H23: =SUMIF($K$5:$BR$5,H$5,$K23:$BR23) -> 0 | I23: =SUMIF($K$5:$BR$5,I$5,$K23:$BR23) -> 0 | K23: =StaffCosts!K12 -> 0 | L23: =StaffCosts!L12 -> 0 | M23: =StaffCosts!M12 -> 0 | N23: =StaffCosts!N12 -> 0 | O23: =StaffCosts!O12 -> 0 | P23: =StaffCosts!P12 -> 0 | Q23: =StaffCosts!Q12 -> 0 | R23: =StaffCosts!R12 -> 0 | ... BR23: =StaffCosts!BR12 -> 0
B24: =B14 -> Insert Business Line2 | D24: =unit -> £ | E24: =SUMIF($K$5:$BR$5,E$5,$K24:$BR24) -> 0 | F24: =SUMIF($K$5:$BR$5,F$5,$K24:$BR24) -> 0 | G24: =SUMIF($K$5:$BR$5,G$5,$K24:$BR24) -> 0 | H24: =SUMIF($K$5:$BR$5,H$5,$K24:$BR24) -> 0 | I24: =SUMIF($K$5:$BR$5,I$5,$K24:$BR24) -> 0 | K24: =StaffCosts!K13 -> 0 | L24: =StaffCosts!L13 -> 0 | M24: =StaffCosts!M13 -> 0 | N24: =StaffCosts!N13 -> 0 | O24: =StaffCosts!O13 -> 0 | P24: =StaffCosts!P13 -> 0 | Q24: =StaffCosts!Q13 -> 0 | R24: =StaffCosts!R13 -> 0 | ... BR24: =StaffCosts!BR13 -> 0
B25: =B15 -> Insert Business Line3 | D25: =unit -> £ | E25: =SUMIF($K$5:$BR$5,E$5,$K25:$BR25) -> 0 | F25: =SUMIF($K$5:$BR$5,F$5,$K25:$BR25) -> 0 | G25: =SUMIF($K$5:$BR$5,G$5,$K25:$BR25) -> 0 | H25: =SUMIF($K$5:$BR$5,H$5,$K25:$BR25) -> 0 | I25: =SUMIF($K$5:$BR$5,I$5,$K25:$BR25) -> 0 | K25: =StaffCosts!K14 -> 0 | L25: =StaffCosts!L14 -> 0 | M25: =StaffCosts!M14 -> 0 | N25: =StaffCosts!N14 -> 0 | O25: =StaffCosts!O14 -> 0 | P25: =StaffCosts!P14 -> 0 | Q25: =StaffCosts!Q14 -> 0 | R25: =StaffCosts!R14 -> 0 | ... BR25: =StaffCosts!BR14 -> 0
B27: Gross profit | D27: =unit -> £ | E27: =SUM(E12,E17,E22) -> 0 | F27: =SUM(F12,F17,F22) -> 0 | G27: =SUM(G12,G17,G22) -> 0 | H27: =SUM(H12,H17,H22) -> 0 | I27: =SUM(I12,I17,I22) -> 0 | K27: =SUM(K12,K17,K22) -> 0 | L27: =SUM(L12,L17,L22) -> 0 | M27: =SUM(M12,M17,M22) -> 0 | N27: =SUM(N12,N17,N22) -> 0 | O27: =SUM(O12,O17,O22) -> 0 | P27: =SUM(P12,P17,P22) -> 0 | Q27: =SUM(Q12,Q17,Q22) -> 0 | R27: =SUM(R12,R17,R22) -> 0 | ... BR27: =SUM(BR12,BR17,BR22) -> 0
B29: Central staff costs | D29: =unit -> £ | E29: =SUMIF($K$5:$BR$5,E$5,$K29:$BR29) -> 0 | F29: =SUMIF($K$5:$BR$5,F$5,$K29:$BR29) -> 0 | G29: =SUMIF($K$5:$BR$5,G$5,$K29:$BR29) -> 0 | H29: =SUMIF($K$5:$BR$5,H$5,$K29:$BR29) -> 0 | I29: =SUMIF($K$5:$BR$5,I$5,$K29:$BR29) -> 0 | K29: =StaffCosts!K15 -> 0 | L29: =StaffCosts!L15 -> 0 | M29: =StaffCosts!M15 -> 0 | N29: =StaffCosts!N15 -> 0 | O29: =StaffCosts!O15 -> 0 | P29: =StaffCosts!P15 -> 0 | Q29: =StaffCosts!Q15 -> 0 | R29: =StaffCosts!R15 -> 0 | ... BR29: =StaffCosts!BR15 -> 0
B30: Central costs | D30: =unit -> £ | E30: =SUMIF($K$5:$BR$5,E$5,$K30:$BR30) -> 0 | F30: =SUMIF($K$5:$BR$5,F$5,$K30:$BR30) -> 0 | G30: =SUMIF($K$5:$BR$5,G$5,$K30:$BR30) -> 0 | H30: =SUMIF($K$5:$BR$5,H$5,$K30:$BR30) -> 0 | I30: =SUMIF($K$5:$BR$5,I$5,$K30:$BR30) -> 0 | K30: =-CentralCosts!K32 -> 0 | L30: =-CentralCosts!L32 -> 0 | M30: =-CentralCosts!M32 -> 0 | N30: =-CentralCosts!N32 -> 0 | O30: =-CentralCosts!O32 -> 0 | P30: =-CentralCosts!P32 -> 0 | Q30: =-CentralCosts!Q32 -> 0 | R30: =-CentralCosts!R32 -> 0 | ... BR30: =-CentralCosts!BR32 -> 0
B31: Depreciation | D31: =unit -> £ | E31: =SUMIF($K$5:$BR$5,E$5,$K31:$BR31) -> 0 | F31: =SUMIF($K$5:$BR$5,F$5,$K31:$BR31) -> 0 | G31: =SUMIF($K$5:$BR$5,G$5,$K31:$BR31) -> 0 | H31: =SUMIF($K$5:$BR$5,H$5,$K31:$BR31) -> 0 | I31: =SUMIF($K$5:$BR$5,I$5,$K31:$BR31) -> 0 | K31: =SUM(Capex!K35,Capex!K45,Capex!K55,Capex!K65,Capex!K75) -> 0 | L31: =SUM(Capex!L35,Capex!L45,Capex!L55,Capex!L65,Capex!L75) -> 0 | M31: =SUM(Capex!M35,Capex!M45,Capex!M55,Capex!M65,Capex!M75) -> 0 | N31: =SUM(Capex!N35,Capex!N45,Capex!N55,Capex!N65,Capex!N75) -> 0 | O31: =SUM(Capex!O35,Capex!O45,Capex!O55,Capex!O65,Capex!O75) -> 0 | P31: =SUM(Capex!P35,Capex!P45,Capex!P55,Capex!P65,Capex!P75) -> 0 | Q31: =SUM(Capex!Q35,Capex!Q45,Capex!Q55,Capex!Q65,Capex!Q75) -> 0 | R31: =SUM(Capex!R35,Capex!R45,Capex!R55,Capex!R65,Capex!R75) -> 0 | ... BR31: =SUM(Capex!BR35,Capex!BR45,Capex!BR55,Capex!BR65,Capex!BR75) -> 0
B32: Operating profit | D32: =unit -> £ | E32: =SUM(E27:E31) -> 0 | F32: =SUM(F27:F31) -> 0 | G32: =SUM(G27:G31) -> 0 | H32: =SUM(H27:H31) -> 0 | I32: =SUM(I27:I31) -> 0 | K32: =SUM(K27:K31) -> 0 | L32: =SUM(L27:L31) -> 0 | M32: =SUM(M27:M31) -> 0 | N32: =SUM(N27:N31) -> 0 | O32: =SUM(O27:O31) -> 0 | P32: =SUM(P27:P31) -> 0 | Q32: =SUM(Q27:Q31) -> 0 | R32: =SUM(R27:R31) -> 0 | ... BR32: =SUM(BR27:BR31) -> 0
B34: Grant income | D34: =unit -> £ | E34: =SUMIF($K$5:$BR$5,E$5,$K34:$BR34) -> 0 | F34: =SUMIF($K$5:$BR$5,F$5,$K34:$BR34) -> 0 | G34: =SUMIF($K$5:$BR$5,G$5,$K34:$BR34) -> 0 | H34: =SUMIF($K$5:$BR$5,H$5,$K34:$BR34) -> 0 | I34: =SUMIF($K$5:$BR$5,I$5,$K34:$BR34) -> 0 | K34: =GrantIncome!K16 -> 0 | L34: =GrantIncome!L16 -> 0 | M34: =GrantIncome!M16 -> 0 | N34: =GrantIncome!N16 -> 0 | O34: =GrantIncome!O16 -> 0 | P34: =GrantIncome!P16 -> 0 | Q34: =GrantIncome!Q16 -> 0 | R34: =GrantIncome!R16 -> 0 | ... BR34: =GrantIncome!BR16 -> 0
B35: Other income | D35: =unit -> £ | E35: =SUMIF($K$5:$BR$5,E$5,$K35:$BR35) -> 0 | F35: =SUMIF($K$5:$BR$5,F$5,$K35:$BR35) -> 0 | G35: =SUMIF($K$5:$BR$5,G$5,$K35:$BR35) -> 0 | H35: =SUMIF($K$5:$BR$5,H$5,$K35:$BR35) -> 0 | I35: =SUMIF($K$5:$BR$5,I$5,$K35:$BR35) -> 0 | K35: ='Other income'!K32 -> 0 | L35: ='Other income'!L32 -> 0 | M35: ='Other income'!M32 -> 0 | N35: ='Other income'!N32 -> 0 | O35: ='Other income'!O32 -> 0 | P35: ='Other income'!P32 -> 0 | Q35: ='Other income'!Q32 -> 0 | R35: ='Other income'!R32 -> 0 | ... BR35: ='Other income'!BR32 -> 0
B36: Interest on debt | D36: =unit -> £ | E36: =SUMIF($K$5:$BR$5,E$5,$K36:$BR36) -> 0 | F36: =SUMIF($K$5:$BR$5,F$5,$K36:$BR36) -> 0 | G36: =SUMIF($K$5:$BR$5,G$5,$K36:$BR36) -> 0 | H36: =SUMIF($K$5:$BR$5,H$5,$K36:$BR36) -> 0 | I36: =SUMIF($K$5:$BR$5,I$5,$K36:$BR36) -> 0 | K36: =DebtFinancing!K22 -> 0 | L36: =DebtFinancing!L22 -> 0 | M36: =DebtFinancing!M22 -> 0 | N36: =DebtFinancing!N22 -> 0 | O36: =DebtFinancing!O22 -> 0 | P36: =DebtFinancing!P22 -> 0 | Q36: =DebtFinancing!Q22 -> 0 | R36: =DebtFinancing!R22 -> 0 | ... BR36: =DebtFinancing!BR22 -> 0
B37: Overdraft interest | E37: =SUMIF($K$5:$BR$5,E$5,$K37:$BR37) -> 0 | F37: =SUMIF($K$5:$BR$5,F$5,$K37:$BR37) -> 0 | G37: =SUMIF($K$5:$BR$5,G$5,$K37:$BR37) -> 0 | H37: =SUMIF($K$5:$BR$5,H$5,$K37:$BR37) -> 0 | I37: =SUMIF($K$5:$BR$5,I$5,$K37:$BR37) -> 0 | K37: ='Outputs - Cashflow'!K40 -> 0 | L37: ='Outputs - Cashflow'!L40 -> 0 | M37: ='Outputs - Cashflow'!M40 -> 0 | N37: ='Outputs - Cashflow'!N40 -> 0 | O37: ='Outputs - Cashflow'!O40 -> 0 | P37: ='Outputs - Cashflow'!P40 -> 0 | Q37: ='Outputs - Cashflow'!Q40 -> 0 | R37: ='Outputs - Cashflow'!R40 -> 0 | ... BR37: ='Outputs - Cashflow'!BR40 -> 0
B38: PBT | D38: =unit -> £ | E38: =SUM(E32:E37) -> 0 | F38: =SUM(F32:F37) -> 0 | G38: =SUM(G32:G37) -> 0 | H38: =SUM(H32:H37) -> 0 | I38: =SUM(I32:I37) -> 0 | K38: =SUM(K32:K37) -> 0 | L38: =SUM(L32:L37) -> 0 | M38: =SUM(M32:M37) -> 0 | N38: =SUM(N32:N37) -> 0 | O38: =SUM(O32:O37) -> 0 | P38: =SUM(P32:P37) -> 0 | Q38: =SUM(Q32:Q37) -> 0 | R38: =SUM(R32:R37) -> 0 | ... BR38: =SUM(BR32:BR37) -> 0
B40: Current tax | D40: =unit -> £ | E40: =SUMIF($K$5:$BR$5,E$5,$K40:$BR40) -> 0 | F40: =SUMIF($K$5:$BR$5,F$5,$K40:$BR40) -> 0 | G40: =SUMIF($K$5:$BR$5,G$5,$K40:$BR40) -> 0 | H40: =SUMIF($K$5:$BR$5,H$5,$K40:$BR40) -> 0 | I40: =SUMIF($K$5:$BR$5,I$5,$K40:$BR40) -> 0 | K40: =TAX!K30 -> 0 | L40: =TAX!L30 -> 0 | M40: =TAX!M30 -> 0 | N40: =TAX!N30 -> 0 | O40: =TAX!O30 -> 0 | P40: =TAX!P30 -> 0 | Q40: =TAX!Q30 -> 0 | R40: =TAX!R30 -> 0 | ... BR40: =TAX!BR30 -> 0
B41: PAT | D41: =unit -> £ | E41: =SUM(E38:E40) -> 0 | F41: =SUM(F38:F40) -> 0 | G41: =SUM(G38:G40) -> 0 | H41: =SUM(H38:H40) -> 0 | I41: =SUM(I38:I40) -> 0 | K41: =SUM(K38:K40) -> 0 | L41: =SUM(L38:L40) -> 0 | M41: =SUM(M38:M40) -> 0 | N41: =SUM(N38:N40) -> 0 | O41: =SUM(O38:O40) -> 0 | P41: =SUM(P38:P40) -> 0 | Q41: =SUM(Q38:Q40) -> 0 | R41: =SUM(R38:R40) -> 0 | ... BR41: =SUM(BR38:BR40) -> 0
B43: Dividends Payable | D43: =unit -> £ | E43: =SUMIF($K$5:$BR$5,E$5,$K43:$BR43) -> 0 | F43: =SUMIF($K$5:$BR$5,F$5,$K43:$BR43) -> 0 | G43: =SUMIF($K$5:$BR$5,G$5,$K43:$BR43) -> 0 | H43: =SUMIF($K$5:$BR$5,H$5,$K43:$BR43) -> 0 | I43: =SUMIF($K$5:$BR$5,I$5,$K43:$BR43) -> 0 | K43: =Dividends!K14 -> 0 | L43: =Dividends!L14 -> 0 | M43: =Dividends!M14 -> 0 | N43: =Dividends!N14 -> 0 | O43: =Dividends!O14 -> 0 | P43: =Dividends!P14 -> 0 | Q43: =Dividends!Q14 -> 0 | R43: =Dividends!R14 -> 0 | ... BR43: =Dividends!BR14 -> 0
B45: Retained profit | D45: =unit -> £ | E45: =SUM(E41:E43) -> 0 | F45: =SUM(F41:F43) -> 0 | G45: =SUM(G41:G43) -> 0 | H45: =SUM(H41:H43) -> 0 | I45: =SUM(I41:I43) -> 0 | K45: =SUM(K41:K43) -> 0 | L45: =SUM(L41:L43) -> 0 | M45: =SUM(M41:M43) -> 0 | N45: =SUM(N41:N43) -> 0 | O45: =SUM(O41:O43) -> 0 | P45: =SUM(P41:P43) -> 0 | Q45: =SUM(Q41:Q43) -> 0 | R45: =SUM(R41:R43) -> 0 | ... BR45: =SUM(BR41:BR43) -> 0
B47: P&L reserve BF | D47: =unit -> £ | E47: =D48 -> 0 | F47: =E48 -> 0 | G47: =F48 -> 0 | H47: =G48 -> 0 | I47: =H48 -> 0 | K47: =J48 -> 0 | L47: =K48 -> 0 | M47: =L48 -> 0 | N47: =M48 -> 0 | O47: =N48 -> 0 | P47: =O48 -> 0 | Q47: =P48 -> 0 | R47: =Q48 -> 0 | ... BR47: =BQ48 -> 0
B48: P&L reserve CF | D48: =KeyInputs!G141 -> 0 | E48: =SUM(E45:E47) -> 0 | F48: =SUM(F45:F47) -> 0 | G48: =SUM(G45:G47) -> 0 | H48: =SUM(H45:H47) -> 0 | I48: =SUM(I45:I47) -> 0 | J48: =D48 -> 0 | K48: =SUM(K45:K47) -> 0 | L48: =SUM(L45:L47) -> 0 | M48: =SUM(M45:M47) -> 0 | N48: =SUM(N45:N47) -> 0 | O48: =SUM(O45:O47) -> 0 | P48: =SUM(P45:P47) -> 0 | Q48: =SUM(Q45:Q47) -> 0 | R48: =SUM(R45:R47) -> 0 | ... BR48: =SUM(BR45:BR47) -> 0
A51: End of sheet

Sheet Outputs - BalanceSheet
A3: =IF(KeyInputs!$F$14=0,"Company Name",KeyInputs!$F$14) -> Company Name
A4: Balance Sheet
D5: =KeyInputs!D5 -> Year | E5: =KeyInputs!H5 -> 2015 | F5: =KeyInputs!I5 -> 2016 | G5: =KeyInputs!J5 -> 2017 | H5: =KeyInputs!K5 -> 2018 | I5: =KeyInputs!L5 -> 2019 | K5: =KeyInputs!N5 -> 2015 | L5: =KeyInputs!O5 -> 2015 | M5: =KeyInputs!P5 -> 2015 | N5: =KeyInputs!Q5 -> 2015 | O5: =KeyInputs!R5 -> 2015 | P5: =KeyInputs!S5 -> 2015 | Q5: =KeyInputs!T5 -> 2015 | R5: =KeyInputs!U5 -> 2015 | ... BR5: =KeyInputs!BU5 -> 2019
D6: =KeyInputs!D6 -> Period number | E6: =KeyInputs!H6 -> 1 | F6: =KeyInputs!I6 -> 2 | G6: =KeyInputs!J6 -> 3 | H6: =KeyInputs!K6 -> 4 | I6: =KeyInputs!L6 -> 5 | K6: =KeyInputs!N6 -> 1 | L6: =KeyInputs!O6 -> 2 | M6: =KeyInputs!P6 -> 3 | N6: =KeyInputs!Q6 -> 4 | O6: =KeyInputs!R6 -> 5 | P6: =KeyInputs!S6 -> 6 | Q6: =KeyInputs!T6 -> 7 | R6: =KeyInputs!U6 -> 8 | ... BR6: =KeyInputs!BU6 -> 60
D7: =KeyInputs!D7 -> Period starts | E7: =KeyInputs!H7 -> 42005 | F7: =KeyInputs!I7 -> 42370 | G7: =KeyInputs!J7 -> 42736 | H7: =KeyInputs!K7 -> 43101 | I7: =KeyInputs!L7 -> 43466 | K7: =KeyInputs!N7 -> 42005 | L7: =KeyInputs!O7 -> 42036 | M7: =KeyInputs!P7 -> 42064 | N7: =KeyInputs!Q7 -> 42095 | O7: =KeyInputs!R7 -> 42125 | P7: =KeyInputs!S7 -> 42156 | Q7: =KeyInputs!T7 -> 42186 | R7: =KeyInputs!U7 -> 42217 | ... BR7: =KeyInputs!BU7 -> 43800
B8: =IF(Check!$C$12=0,"All checks are OK","There are "&Check!$C$12&" error/errors") -> All checks are OK | D8: =KeyInputs!D8 -> Period ends | E8: =KeyInputs!H8 -> 42369 | F8: =KeyInputs!I8 -> 42735 | G8: =KeyInputs!J8 -> 43100 | H8: =KeyInputs!K8 -> 43465 | I8: =KeyInputs!L8 -> 43830 | K8: =KeyInputs!N8 -> 42035 | L8: =KeyInputs!O8 -> 42063 | M8: =KeyInputs!P8 -> 42094 | N8: =KeyInputs!Q8 -> 42124 | O8: =KeyInputs!R8 -> 42155 | P8: =KeyInputs!S8 -> 42185 | Q8: =KeyInputs!T8 -> 42216 | R8: =KeyInputs!U8 -> 42247 | ... BR8: =KeyInputs!BU8 -> 43830
A10: =Header1 -> 1 | B10: Balance Sheet
B12: Fixed assets | D12: =unit -> £ | E12: =INDEX($K12:$BR12,0,MATCH(E$8,$K$8:$BR$8,0)) -> 0 | F12: =INDEX($K12:$BR12,0,MATCH(F$8,$K$8:$BR$8,0)) -> 0 | G12: =INDEX($K12:$BR12,0,MATCH(G$8,$K$8:$BR$8,0)) -> 0 | H12: =INDEX($K12:$BR12,0,MATCH(H$8,$K$8:$BR$8,0)) -> 0 | I12: =INDEX($K12:$BR12,0,MATCH(I$8,$K$8:$BR$8,0)) -> 0 | K12: =SUM(K13:K17) -> 0 | L12: =SUM(L13:L17) -> 0 | M12: =SUM(M13:M17) -> 0 | N12: =SUM(N13:N17) -> 0 | O12: =SUM(O13:O17) -> 0 | P12: =SUM(P13:P17) -> 0 | Q12: =SUM(Q13:Q17) -> 0 | R12: =SUM(R13:R17) -> 0 | ... BR12: =SUM(BR13:BR17) -> 0
B13: =KeyInputs!F61 -> ICT equipement | D13: =unit -> £ | E13: =INDEX($K13:$BR13,0,MATCH(E$8,$K$8:$BR$8,0)) -> 0 | F13: =INDEX($K13:$BR13,0,MATCH(F$8,$K$8:$BR$8,0)) -> 0 | G13: =INDEX($K13:$BR13,0,MATCH(G$8,$K$8:$BR$8,0)) -> 0 | H13: =INDEX($K13:$BR13,0,MATCH(H$8,$K$8:$BR$8,0)) -> 0 | I13: =INDEX($K13:$BR13,0,MATCH(I$8,$K$8:$BR$8,0)) -> 0 | K13: =Capex!K37 -> 0 | L13: =Capex!L37 -> 0 | M13: =Capex!M37 -> 0 | N13: =Capex!N37 -> 0 | O13: =Capex!O37 -> 0 | P13: =Capex!P37 -> 0 | Q13: =Capex!Q37 -> 0 | R13: =Capex!R37 -> 0 | ... BR13: =Capex!BR37 -> 0
B14: =KeyInputs!F62 -> F&F | D14: =unit -> £ | E14: =INDEX($K14:$BR14,0,MATCH(E$8,$K$8:$BR$8,0)) -> 0 | F14: =INDEX($K14:$BR14,0,MATCH(F$8,$K$8:$BR$8,0)) -> 0 | G14: =INDEX($K14:$BR14,0,MATCH(G$8,$K$8:$BR$8,0)) -> 0 | H14: =INDEX($K14:$BR14,0,MATCH(H$8,$K$8:$BR$8,0)) -> 0 | I14: =INDEX($K14:$BR14,0,MATCH(I$8,$K$8:$BR$8,0)) -> 0 | K14: =Capex!K47 -> 0 | L14: =Capex!L47 -> 0 | M14: =Capex!M47 -> 0 | N14: =Capex!N47 -> 0 | O14: =Capex!O47 -> 0 | P14: =Capex!P47 -> 0 | Q14: =Capex!Q47 -> 0 | R14: =Capex!R47 -> 0 | ... BR14: =Capex!BR47 -> 0
B15: =KeyInputs!F63 -> Property | D15: =unit -> £ | E15: =INDEX($K15:$BR15,0,MATCH(E$8,$K$8:$BR$8,0)) -> 0 | F15: =INDEX($K15:$BR15,0,MATCH(F$8,$K$8:$BR$8,0)) -> 0 | G15: =INDEX($K15:$BR15,0,MATCH(G$8,$K$8:$BR$8,0)) -> 0 | H15: =INDEX($K15:$BR15,0,MATCH(H$8,$K$8:$BR$8,0)) -> 0 | I15: =INDEX($K15:$BR15,0,MATCH(I$8,$K$8:$BR$8,0)) -> 0 | K15: =Capex!K57 -> 0 | L15: =Capex!L57 -> 0 | M15: =Capex!M57 -> 0 | N15: =Capex!N57 -> 0 | O15: =Capex!O57 -> 0 | P15: =Capex!P57 -> 0 | Q15: =Capex!Q57 -> 0 | R15: =Capex!R57 -> 0 | ... BR15: =Capex!BR57 -> 0
B16: =KeyInputs!F64 -> Vehicles | D16: =unit -> £ | E16: =INDEX($K16:$BR16,0,MATCH(E$8,$K$8:$BR$8,0)) -> 0 | F16: =INDEX($K16:$BR16,0,MATCH(F$8,$K$8:$BR$8,0)) -> 0 | G16: =INDEX($K16:$BR16,0,MATCH(G$8,$K$8:$BR$8,0)) -> 0 | H16: =INDEX($K16:$BR16,0,MATCH(H$8,$K$8:$BR$8,0)) -> 0 | I16: =INDEX($K16:$BR16,0,MATCH(I$8,$K$8:$BR$8,0)) -> 0 | K16: =Capex!K67 -> 0 | L16: =Capex!L67 -> 0 | M16: =Capex!M67 -> 0 | N16: =Capex!N67 -> 0 | O16: =Capex!O67 -> 0 | P16: =Capex!P67 -> 0 | Q16: =Capex!Q67 -> 0 | R16: =Capex!R67 -> 0 | ... BR16: =Capex!BR67 -> 0
B17: =KeyInputs!F65 -> n/a | D17: =unit -> £ | E17: =INDEX($K17:$BR17,0,MATCH(E$8,$K$8:$BR$8,0)) -> 0 | F17: =INDEX($K17:$BR17,0,MATCH(F$8,$K$8:$BR$8,0)) -> 0 | G17: =INDEX($K17:$BR17,0,MATCH(G$8,$K$8:$BR$8,0)) -> 0 | H17: =INDEX($K17:$BR17,0,MATCH(H$8,$K$8:$BR$8,0)) -> 0 | I17: =INDEX($K17:$BR17,0,MATCH(I$8,$K$8:$BR$8,0)) -> 0 | K17: =Capex!K77 -> 0 | L17: =Capex!L77 -> 0 | M17: =Capex!M77 -> 0 | N17: =Capex!N77 -> 0 | O17: =Capex!O77 -> 0 | P17: =Capex!P77 -> 0 | Q17: =Capex!Q77 -> 0 | R17: =Capex!R77 -> 0 | ... BR17: =Capex!BR77 -> 0
B19: Trade debtors | D19: =unit -> £ | E19: =INDEX($K19:$BR19,0,MATCH(E$8,$K$8:$BR$8,0)) -> 0 | F19: =INDEX($K19:$BR19,0,MATCH(F$8,$K$8:$BR$8,0)) -> 0 | G19: =INDEX($K19:$BR19,0,MATCH(G$8,$K$8:$BR$8,0)) -> 0 | H19: =INDEX($K19:$BR19,0,MATCH(H$8,$K$8:$BR$8,0)) -> 0 | I19: =INDEX($K19:$BR19,0,MATCH(I$8,$K$8:$BR$8,0)) -> 0 | K19: =SUM(K20:K22) -> 0 | L19: =SUM(L20:L22) -> 0 | M19: =SUM(M20:M22) -> 0 | N19: =SUM(N20:N22) -> 0 | O19: =SUM(O20:O22) -> 0 | P19: =SUM(P20:P22) -> 0 | Q19: =SUM(Q20:Q22) -> 0 | R19: =SUM(R20:R22) -> 0 | ... BR19: =SUM(BR20:BR22) -> 0
B20: =KeyInputs!F21 -> Test | D20: =unit -> £ | E20: =INDEX($K20:$BR20,0,MATCH(E$8,$K$8:$BR$8,0)) -> 0 | F20: =INDEX($K20:$BR20,0,MATCH(F$8,$K$8:$BR$8,0)) -> 0 | G20: =INDEX($K20:$BR20,0,MATCH(G$8,$K$8:$BR$8,0)) -> 0 | H20: =INDEX($K20:$BR20,0,MATCH(H$8,$K$8:$BR$8,0)) -> 0 | I20: =INDEX($K20:$BR20,0,MATCH(I$8,$K$8:$BR$8,0)) -> 0 | K20: =WorkingCapital!K21 -> 0 | L20: =WorkingCapital!L21 -> 0 | M20: =WorkingCapital!M21 -> 0 | N20: =WorkingCapital!N21 -> 0 | O20: =WorkingCapital!O21 -> 0 | P20: =WorkingCapital!P21 -> 0 | Q20: =WorkingCapital!Q21 -> 0 | R20: =WorkingCapital!R21 -> 0 | ... BR20: =WorkingCapital!BR21 -> 0
B21: =KeyInputs!F26 -> Insert Business Line2 | D21: =unit -> £ | E21: =INDEX($K21:$BR21,0,MATCH(E$8,$K$8:$BR$8,0)) -> 0 | F21: =INDEX($K21:$BR21,0,MATCH(F$8,$K$8:$BR$8,0)) -> 0 | G21: =INDEX($K21:$BR21,0,MATCH(G$8,$K$8:$BR$8,0)) -> 0 | H21: =INDEX($K21:$BR21,0,MATCH(H$8,$K$8:$BR$8,0)) -> 0 | I21: =INDEX($K21:$BR21,0,MATCH(I$8,$K$8:$BR$8,0)) -> 0 | K21: =WorkingCapital!K32 -> 0 | L21: =WorkingCapital!L32 -> 0 | M21: =WorkingCapital!M32 -> 0 | N21: =WorkingCapital!N32 -> 0 | O21: =WorkingCapital!O32 -> 0 | P21: =WorkingCapital!P32 -> 0 | Q21: =WorkingCapital!Q32 -> 0 | R21: =WorkingCapital!R32 -> 0 | ... BR21: =WorkingCapital!BR32 -> 0
B22: =KeyInputs!F31 -> Insert Business Line3 | D22: =unit -> £ | E22: =INDEX($K22:$BR22,0,MATCH(E$8,$K$8:$BR$8,0)) -> 0 | F22: =INDEX($K22:$BR22,0,MATCH(F$8,$K$8:$BR$8,0)) -> 0 | G22: =INDEX($K22:$BR22,0,MATCH(G$8,$K$8:$BR$8,0)) -> 0 | H22: =INDEX($K22:$BR22,0,MATCH(H$8,$K$8:$BR$8,0)) -> 0 | I22: =INDEX($K22:$BR22,0,MATCH(I$8,$K$8:$BR$8,0)) -> 0 | K22: =WorkingCapital!K43 -> 0 | L22: =WorkingCapital!L43 -> 0 | M22: =WorkingCapital!M43 -> 0 | N22: =WorkingCapital!N43 -> 0 | O22: =WorkingCapital!O43 -> 0 | P22: =WorkingCapital!P43 -> 0 | Q22: =WorkingCapital!Q43 -> 0 | R22: =WorkingCapital!R43 -> 0 | ... BR22: =WorkingCapital!BR43 -> 0
B24: Stocks | D24: =unit -> £ | E24: =INDEX($K24:$BR24,0,MATCH(E$8,$K$8:$BR$8,0)) -> 0 | F24: =INDEX($K24:$BR24,0,MATCH(F$8,$K$8:$BR$8,0)) -> 0 | G24: =INDEX($K24:$BR24,0,MATCH(G$8,$K$8:$BR$8,0)) -> 0 | H24: =INDEX($K24:$BR24,0,MATCH(H$8,$K$8:$BR$8,0)) -> 0 | I24: =INDEX($K24:$BR24,0,MATCH(I$8,$K$8:$BR$8,0)) -> 0 | K24: =SUM(K25:K27) -> 0 | L24: =SUM(L25:L27) -> 0 | M24: =SUM(M25:M27) -> 0 | N24: =SUM(N25:N27) -> 0 | O24: =SUM(O25:O27) -> 0 | P24: =SUM(P25:P27) -> 0 | Q24: =SUM(Q25:Q27) -> 0 | R24: =SUM(R25:R27) -> 0 | ... BR24: =SUM(BR25:BR27) -> 0
B25: =B20 -> Test | D25: =unit -> £ | E25: =INDEX($K25:$BR25,0,MATCH(E$8,$K$8:$BR$8,0)) -> 0 | F25: =INDEX($K25:$BR25,0,MATCH(F$8,$K$8:$BR$8,0)) -> 0 | G25: =INDEX($K25:$BR25,0,MATCH(G$8,$K$8:$BR$8,0)) -> 0 | H25: =INDEX($K25:$BR25,0,MATCH(H$8,$K$8:$BR$8,0)) -> 0 | I25: =INDEX($K25:$BR25,0,MATCH(I$8,$K$8:$BR$8,0)) -> 0 | K25: =WorkingCapital!K56 -> 0 | L25: =WorkingCapital!L56 -> 0 | M25: =WorkingCapital!M56 -> 0 | N25: =WorkingCapital!N56 -> 0 | O25: =WorkingCapital!O56 -> 0 | P25: =WorkingCapital!P56 -> 0 | Q25: =WorkingCapital!Q56 -> 0 | R25: =WorkingCapital!R56 -> 0 | ... BR25: =WorkingCapital!BR56 -> 0
B26: =B21 -> Insert Business Line2 | D26: =unit -> £ | E26: =INDEX($K26:$BR26,0,MATCH(E$8,$K$8:$BR$8,0)) -> 0 | F26: =INDEX($K26:$BR26,0,MATCH(F$8,$K$8:$BR$8,0)) -> 0 | G26: =INDEX($K26:$BR26,0,MATCH(G$8,$K$8:$BR$8,0)) -> 0 | H26: =INDEX($K26:$BR26,0,MATCH(H$8,$K$8:$BR$8,0)) -> 0 | I26: =INDEX($K26:$BR26,0,MATCH(I$8,$K$8:$BR$8,0)) -> 0 | K26: =WorkingCapital!K67 -> 0 | L26: =WorkingCapital!L67 -> 0 | M26: =WorkingCapital!M67 -> 0 | N26: =WorkingCapital!N67 -> 0 | O26: =WorkingCapital!O67 -> 0 | P26: =WorkingCapital!P67 -> 0 | Q26: =WorkingCapital!Q67 -> 0 | R26: =WorkingCapital!R67 -> 0 | ... BR26: =WorkingCapital!BR67 -> 0
B27: =B22 -> Insert Business Line3 | D27: =unit -> £ | E27: =INDEX($K27:$BR27,0,MATCH(E$8,$K$8:$BR$8,0)) -> 0 | F27: =INDEX($K27:$BR27,0,MATCH(F$8,$K$8:$BR$8,0)) -> 0 | G27: =INDEX($K27:$BR27,0,MATCH(G$8,$K$8:$BR$8,0)) -> 0 | H27: =INDEX($K27:$BR27,0,MATCH(H$8,$K$8:$BR$8,0)) -> 0 | I27: =INDEX($K27:$BR27,0,MATCH(I$8,$K$8:$BR$8,0)) -> 0 | K27: =WorkingCapital!K78 -> 0 | L27: =WorkingCapital!L78 -> 0 | M27: =WorkingCapital!M78 -> 0 | N27: =WorkingCapital!N78 -> 0 | O27: =WorkingCapital!O78 -> 0 | P27: =WorkingCapital!P78 -> 0 | Q27: =WorkingCapital!Q78 -> 0 | R27: =WorkingCapital!R78 -> 0 | ... BR27: =WorkingCapital!BR78 -> 0
B29: Cash at bank | D29: =unit -> £ | E29: =INDEX($K29:$BR29,0,MATCH(E$8,$K$8:$BR$8,0)) -> 0 | F29: =INDEX($K29:$BR29,0,MATCH(F$8,$K$8:$BR$8,0)) -> 0 | G29: =INDEX($K29:$BR29,0,MATCH(G$8,$K$8:$BR$8,0)) -> 0 | H29: =INDEX($K29:$BR29,0,MATCH(H$8,$K$8:$BR$8,0)) -> 0 | I29: =INDEX($K29:$BR29,0,MATCH(I$8,$K$8:$BR$8,0)) -> 0 | K29: =MAX('Outputs - Cashflow'!K$41,0) -> 0 | L29: =MAX('Outputs - Cashflow'!L$41,0) -> 0 | M29: =MAX('Outputs - Cashflow'!M$41,0) -> 0 | N29: =MAX('Outputs - Cashflow'!N$41,0) -> 0 | O29: =MAX('Outputs - Cashflow'!O$41,0) -> 0 | P29: =MAX('Outputs - Cashflow'!P$41,0) -> 0 | Q29: =MAX('Outputs - Cashflow'!Q$41,0) -> 0 | R29: =MAX('Outputs - Cashflow'!R$41,0) -> 0 | ... BR29: =MAX('Outputs - Cashflow'!BR$41,0) -> 0
B31: Overdraft | D31: =unit -> £ | E31: =INDEX($K31:$BR31,0,MATCH(E$8,$K$8:$BR$8,0)) -> 0 | F31: =INDEX($K31:$BR31,0,MATCH(F$8,$K$8:$BR$8,0)) -> 0 | G31: =INDEX($K31:$BR31,0,MATCH(G$8,$K$8:$BR$8,0)) -> 0 | H31: =INDEX($K31:$BR31,0,MATCH(H$8,$K$8:$BR$8,0)) -> 0 | I31: =INDEX($K31:$BR31,0,MATCH(I$8,$K$8:$BR$8,0)) -> 0 | K31: =MIN('Outputs - Cashflow'!K$41,0) -> 0 | L31: =MIN('Outputs - Cashflow'!L$41,0) -> 0 | M31: =MIN('Outputs - Cashflow'!M$41,0) -> 0 | N31: =MIN('Outputs - Cashflow'!N$41,0) -> 0 | O31: =MIN('Outputs - Cashflow'!O$41,0) -> 0 | P31: =MIN('Outputs - Cashflow'!P$41,0) -> 0 | Q31: =MIN('Outputs - Cashflow'!Q$41,0) -> 0 | R31: =MIN('Outputs - Cashflow'!R$41,0) -> 0 | ... BR31: =MIN('Outputs - Cashflow'!BR$41,0) -> 0
B32: Trade creditors | D32: =unit -> £ | E32: =INDEX($K32:$BR32,0,MATCH(E$8,$K$8:$BR$8,0)) -> 0 | F32: =INDEX($K32:$BR32,0,MATCH(F$8,$K$8:$BR$8,0)) -> 0 | G32: =INDEX($K32:$BR32,0,MATCH(G$8,$K$8:$BR$8,0)) -> 0 | H32: =INDEX($K32:$BR32,0,MATCH(H$8,$K$8:$BR$8,0)) -> 0 | I32: =INDEX($K32:$BR32,0,MATCH(I$8,$K$8:$BR$8,0)) -> 0 | K32: =WorkingCapital!K$91 -> 0 | L32: =WorkingCapital!L$91 -> 0 | M32: =WorkingCapital!M$91 -> 0 | N32: =WorkingCapital!N$91 -> 0 | O32: =WorkingCapital!O$91 -> 0 | P32: =WorkingCapital!P$91 -> 0 | Q32: =WorkingCapital!Q$91 -> 0 | R32: =WorkingCapital!R$91 -> 0 | ... BR32: =WorkingCapital!BR$91 -> 0
B33: VAT CHANGED | D33: =unit -> £ | E33: =INDEX($K33:$BR33,0,MATCH(E$8,$K$8:$BR$8,0)) -> 0 | F33: =INDEX($K33:$BR33,0,MATCH(F$8,$K$8:$BR$8,0)) -> 0 | G33: =INDEX($K33:$BR33,0,MATCH(G$8,$K$8:$BR$8,0)) -> 0 | H33: =INDEX($K33:$BR33,0,MATCH(H$8,$K$8:$BR$8,0)) -> 0 | I33: =INDEX($K33:$BR33,0,MATCH(I$8,$K$8:$BR$8,0)) -> 0 | K33: =WorkingCapital!K108*-1 -> 0 | L33: =WorkingCapital!L108*-1 -> 0 | M33: =WorkingCapital!M108*-1 -> 0 | N33: =WorkingCapital!N108*-1 -> 0 | O33: =WorkingCapital!O108*-1 -> 0 | P33: =WorkingCapital!P108*-1 -> 0 | Q33: =WorkingCapital!Q108*-1 -> 0 | R33: =WorkingCapital!R108*-1 -> 0 | ... BR33: =WorkingCapital!BR108*-1 -> 0
B34: Interest on debt payable | D34: =unit -> £ | E34: =INDEX($K34:$BR34,0,MATCH(E$8,$K$8:$BR$8,0)) -> 0 | F34: =INDEX($K34:$BR34,0,MATCH(F$8,$K$8:$BR$8,0)) -> 0 | G34: =INDEX($K34:$BR34,0,MATCH(G$8,$K$8:$BR$8,0)) -> 0 | H34: =INDEX($K34:$BR34,0,MATCH(H$8,$K$8:$BR$8,0)) -> 0 | I34: =INDEX($K34:$BR34,0,MATCH(I$8,$K$8:$BR$8,0)) -> 0 | K34: =DebtFinancing!K$24 -> 0 | L34: =DebtFinancing!L$24 -> 0 | M34: =DebtFinancing!M$24 -> 0 | N34: =DebtFinancing!N$24 -> 0 | O34: =DebtFinancing!O$24 -> 0 | P34: =DebtFinancing!P$24 -> 0 | Q34: =DebtFinancing!Q$24 -> 0 | R34: =DebtFinancing!R$24 -> 0 | ... BR34: =DebtFinancing!BR$24 -> 0
B35: Term debt | D35: =unit -> £ | E35: =INDEX($K35:$BR35,0,MATCH(E$8,$K$8:$BR$8,0)) -> 0 | F35: =INDEX($K35:$BR35,0,MATCH(F$8,$K$8:$BR$8,0)) -> 0 | G35: =INDEX($K35:$BR35,0,MATCH(G$8,$K$8:$BR$8,0)) -> 0 | H35: =INDEX($K35:$BR35,0,MATCH(H$8,$K$8:$BR$8,0)) -> 0 | I35: =INDEX($K35:$BR35,0,MATCH(I$8,$K$8:$BR$8,0)) -> 0 | K35: =DebtFinancing!K$17 -> 0 | L35: =DebtFinancing!L$17 -> 0 | M35: =DebtFinancing!M$17 -> 0 | N35: =DebtFinancing!N$17 -> 0 | O35: =DebtFinancing!O$17 -> 0 | P35: =DebtFinancing!P$17 -> 0 | Q35: =DebtFinancing!Q$17 -> 0 | R35: =DebtFinancing!R$17 -> 0 | ... BR35: =DebtFinancing!BR$17 -> 0
B36: Grant deferred income | D36: =unit -> £ | E36: =INDEX($K36:$BR36,0,MATCH(E$8,$K$8:$BR$8,0)) -> 0 | F36: =INDEX($K36:$BR36,0,MATCH(F$8,$K$8:$BR$8,0)) -> 0 | G36: =INDEX($K36:$BR36,0,MATCH(G$8,$K$8:$BR$8,0)) -> 0 | H36: =INDEX($K36:$BR36,0,MATCH(H$8,$K$8:$BR$8,0)) -> 0 | I36: =INDEX($K36:$BR36,0,MATCH(I$8,$K$8:$BR$8,0)) -> 0 | K36: =GrantIncome!K17 -> 0 | L36: =GrantIncome!L17 -> 0 | M36: =GrantIncome!M17 -> 0 | N36: =GrantIncome!N17 -> 0 | O36: =GrantIncome!O17 -> 0 | P36: =GrantIncome!P17 -> 0 | Q36: =GrantIncome!Q17 -> 0 | R36: =GrantIncome!R17 -> 0 | ... BR36: =GrantIncome!BR17 -> 0
B37: Current tax | D37: =unit -> £ | E37: =INDEX($K37:$BR37,0,MATCH(E$8,$K$8:$BR$8,0)) -> 0 | F37: =INDEX($K37:$BR37,0,MATCH(F$8,$K$8:$BR$8,0)) -> 0 | G37: =INDEX($K37:$BR37,0,MATCH(G$8,$K$8:$BR$8,0)) -> 0 | H37: =INDEX($K37:$BR37,0,MATCH(H$8,$K$8:$BR$8,0)) -> 0 | I37: =INDEX($K37:$BR37,0,MATCH(I$8,$K$8:$BR$8,0)) -> 0 | K37: =TAX!K$44 -> 0 | L37: =TAX!L$44 -> 0 | M37: =TAX!M$44 -> 0 | N37: =TAX!N$44 -> 0 | O37: =TAX!O$44 -> 0 | P37: =TAX!P$44 -> 0 | Q37: =TAX!Q$44 -> 0 | R37: =TAX!R$44 -> 0 | ... BR37: =TAX!BR$44 -> 0
B39: Net assets | D39: =unit -> £ | E39: =SUM(E12,E19,E24,E29,E31:E37) -> 0 | F39: =SUM(F12,F19,F24,F29,F31:F37) -> 0 | G39: =SUM(G12,G19,G24,G29,G31:G37) -> 0 | H39: =SUM(H12,H19,H24,H29,H31:H37) -> 0 | I39: =SUM(I12,I19,I24,I29,I31:I37) -> 0 | K39: =SUM(K12,K19,K24,K29,K31:K37) -> 0 | L39: =SUM(L12,L19,L24,L29,L31:L37) -> 0 | M39: =SUM(M12,M19,M24,M29,M31:M37) -> 0 | N39: =SUM(N12,N19,N24,N29,N31:N37) -> 0 | O39: =SUM(O12,O19,O24,O29,O31:O37) -> 0 | P39: =SUM(P12,P19,P24,P29,P31:P37) -> 0 | Q39: =SUM(Q12,Q19,Q24,Q29,Q31:Q37) -> 0 | R39: =SUM(R12,R19,R24,R29,R31:R37) -> 0 | ... BR39: =SUM(BR12,BR19,BR24,BR29,BR31:BR37) -> 0
B41: Share capital | D41: =unit -> £ | E41: =INDEX($K41:$BR41,0,MATCH(E$8,$K$8:$BR$8,0)) -> 0 | F41: =INDEX($K41:$BR41,0,MATCH(F$8,$K$8:$BR$8,0)) -> 0 | G41: =INDEX($K41:$BR41,0,MATCH(G$8,$K$8:$BR$8,0)) -> 0 | H41: =INDEX($K41:$BR41,0,MATCH(H$8,$K$8:$BR$8,0)) -> 0 | I41: =INDEX($K41:$BR41,0,MATCH(I$8,$K$8:$BR$8,0)) -> 0 | K41: =KeyInputs!G140+EquityFinancing!K22 -> 0 | L41: =K41+EquityFinancing!L22 -> 0 | M41: =L41+EquityFinancing!M22 -> 0 | N41: =M41+EquityFinancing!N22 -> 0 | O41: =N41+EquityFinancing!O22 -> 0 | P41: =O41+EquityFinancing!P22 -> 0 | Q41: =P41+EquityFinancing!Q22 -> 0 | R41: =Q41+EquityFinancing!R22 -> 0 | S41: =R41+EquityFinancing!S22 -> 0 | ... BR41: =BQ41+EquityFinancing!BR22 -> 0
B42: P&L reserve | D42: =unit -> £ | E42: =INDEX($K42:$BR42,0,MATCH(E$8,$K$8:$BR$8,0)) -> 0 | F42: =INDEX($K42:$BR42,0,MATCH(F$8,$K$8:$BR$8,0)) -> 0 | G42: =INDEX($K42:$BR42,0,MATCH(G$8,$K$8:$BR$8,0)) -> 0 | H42: =INDEX($K42:$BR42,0,MATCH(H$8,$K$8:$BR$8,0)) -> 0 | I42: =INDEX($K42:$BR42,0,MATCH(I$8,$K$8:$BR$8,0)) -> 0 | K42: ='Outputs - P&L'!K48 -> 0 | L42: ='Outputs - P&L'!L48 -> 0 | M42: ='Outputs - P&L'!M48 -> 0 | N42: ='Outputs - P&L'!N48 -> 0 | O42: ='Outputs - P&L'!O48 -> 0 | P42: ='Outputs - P&L'!P48 -> 0 | Q42: ='Outputs - P&L'!Q48 -> 0 | R42: ='Outputs - P&L'!R48 -> 0 | ... BR42: ='Outputs - P&L'!BR48 -> 0
B44: Shareholders' funds | D44: =unit -> £ | E44: =SUM(E41:E43) -> 0 | F44: =SUM(F41:F43) -> 0 | G44: =SUM(G41:G43) -> 0 | H44: =SUM(H41:H43) -> 0 | I44: =SUM(I41:I43) -> 0 | K44: =SUM(K41:K43) -> 0 | L44: =SUM(L41:L43) -> 0 | M44: =SUM(M41:M43) -> 0 | N44: =SUM(N41:N43) -> 0 | O44: =SUM(O41:O43) -> 0 | P44: =SUM(P41:P43) -> 0 | Q44: =SUM(Q41:Q43) -> 0 | R44: =SUM(R41:R43) -> 0 | ... BR44: =SUM(BR41:BR43) -> 0
B46: Check | E46: =IF(ABS(E44-E39)>Tolerance,1,0) -> 0 | F46: =IF(ABS(F44-F39)>Tolerance,1,0) -> 0 | G46: =IF(ABS(G44-G39)>Tolerance,1,0) -> 0 | H46: =IF(ABS(H44-H39)>Tolerance,1,0) -> 0 | I46: =IF(ABS(I44-I39)>Tolerance,1,0) -> 0 | K46: =IF(ABS(K44-K39)>Tolerance,1,0) -> 0 | L46: =IF(ABS(L44-L39)>Tolerance,1,0) -> 0 | M46: =IF(ABS(M44-M39)>Tolerance,1,0) -> 0 | N46: =IF(ABS(N44-N39)>Tolerance,1,0) -> 0 | O46: =IF(ABS(O44-O39)>Tolerance,1,0) -> 0 | P46: =IF(ABS(P44-P39)>Tolerance,1,0) -> 0 | Q46: =IF(ABS(Q44-Q39)>Tolerance,1,0) -> 0 | R46: =IF(ABS(R44-R39)>Tolerance,1,0) -> 0 | ... BR46: =IF(ABS(BR44-BR39)>Tolerance,1,0) -> 0
A48: End of sheet

Sheet Outputs - Cashflow
A3: =IF(KeyInputs!$F$14=0,"Company Name",KeyInputs!$F$14) -> Company Name
A4: Cash Flow Statement
D5: =KeyInputs!D5 -> Year | E5: =KeyInputs!H5 -> 2015 | F5: =KeyInputs!I5 -> 2016 | G5: =KeyInputs!J5 -> 2017 | H5: =KeyInputs!K5 -> 2018 | I5: =KeyInputs!L5 -> 2019 | K5: =KeyInputs!N5 -> 2015 | L5: =KeyInputs!O5 -> 2015 | M5: =KeyInputs!P5 -> 2015 | N5: =KeyInputs!Q5 -> 2015 | O5: =KeyInputs!R5 -> 2015 | P5: =KeyInputs!S5 -> 2015 | Q5: =KeyInputs!T5 -> 2015 | R5: =KeyInputs!U5 -> 2015 | ... BR5: =KeyInputs!BU5 -> 2019
D6: =KeyInputs!D6 -> Period number | E6: =KeyInputs!H6 -> 1 | F6: =KeyInputs!I6 -> 2 | G6: =KeyInputs!J6 -> 3 | H6: =KeyInputs!K6 -> 4 | I6: =KeyInputs!L6 -> 5 | K6: =KeyInputs!N6 -> 1 | L6: =KeyInputs!O6 -> 2 | M6: =KeyInputs!P6 -> 3 | N6: =KeyInputs!Q6 -> 4 | O6: =KeyInputs!R6 -> 5 | P6: =KeyInputs!S6 -> 6 | Q6: =KeyInputs!T6 -> 7 | R6: =KeyInputs!U6 -> 8 | ... BR6: =KeyInputs!BU6 -> 60
D7: =KeyInputs!D7 -> Period starts | E7: =KeyInputs!H7 -> 42005 | F7: =KeyInputs!I7 -> 42370 | G7: =KeyInputs!J7 -> 42736 | H7: =KeyInputs!K7 -> 43101 | I7: =KeyInputs!L7 -> 43466 | K7: =KeyInputs!N7 -> 42005 | L7: =KeyInputs!O7 -> 42036 | M7: =KeyInputs!P7 -> 42064 | N7: =KeyInputs!Q7 -> 42095 | O7: =KeyInputs!R7 -> 42125 | P7: =KeyInputs!S7 -> 42156 | Q7: =KeyInputs!T7 -> 42186 | R7: =KeyInputs!U7 -> 42217 | ... BR7: =KeyInputs!BU7 -> 43800
B8: =IF(Check!$C$12=0,"All checks are OK","There are "&Check!$C$12&" error/errors") -> All checks are OK | D8: =KeyInputs!D8 -> Period ends | E8: =KeyInputs!H8 -> 42369 | F8: =KeyInputs!I8 -> 42735 | G8: =KeyInputs!J8 -> 43100 | H8: =KeyInputs!K8 -> 43465 | I8: =KeyInputs!L8 -> 43830 | K8: =KeyInputs!N8 -> 42035 | L8: =KeyInputs!O8 -> 42063 | M8: =KeyInputs!P8 -> 42094 | N8: =KeyInputs!Q8 -> 42124 | O8: =KeyInputs!R8 -> 42155 | P8: =KeyInputs!S8 -> 42185 | Q8: =KeyInputs!T8 -> 42216 | R8: =KeyInputs!U8 -> 42247 | ... BR8: =KeyInputs!BU8 -> 43830
A10: =Header1 -> 1 | B10: Cash Flow Statement
B12: Operating profit | D12: =unit -> £ | E12: =SUMIF($K$5:$BR$5,E$5,$K12:$BR12) -> 0 | F12: =SUMIF($K$5:$BR$5,F$5,$K12:$BR12) -> 0 | G12: =SUMIF($K$5:$BR$5,G$5,$K12:$BR12) -> 0 | H12: =SUMIF($K$5:$BR$5,H$5,$K12:$BR12) -> 0 | I12: =SUMIF($K$5:$BR$5,I$5,$K12:$BR12) -> 0 | K12: ='Outputs - P&L'!K$32 -> 0 | L12: ='Outputs - P&L'!L$32 -> 0 | M12: ='Outputs - P&L'!M$32 -> 0 | N12: ='Outputs - P&L'!N$32 -> 0 | O12: ='Outputs - P&L'!O$32 -> 0 | P12: ='Outputs - P&L'!P$32 -> 0 | Q12: ='Outputs - P&L'!Q$32 -> 0 | R12: ='Outputs - P&L'!R$32 -> 0 | ... BR12: ='Outputs - P&L'!BR$32 -> 0
B14: add back depreciation | D14: =unit -> £ | E14: =SUMIF($K$5:$BR$5,E$5,$K14:$BR14) -> 0 | F14: =SUMIF($K$5:$BR$5,F$5,$K14:$BR14) -> 0 | G14: =SUMIF($K$5:$BR$5,G$5,$K14:$BR14) -> 0 | H14: =SUMIF($K$5:$BR$5,H$5,$K14:$BR14) -> 0 | I14: =SUMIF($K$5:$BR$5,I$5,$K14:$BR14) -> 0 | K14: =-'Outputs - P&L'!K$31 -> 0 | L14: =-'Outputs - P&L'!L$31 -> 0 | M14: =-'Outputs - P&L'!M$31 -> 0 | N14: =-'Outputs - P&L'!N$31 -> 0 | O14: =-'Outputs - P&L'!O$31 -> 0 | P14: =-'Outputs - P&L'!P$31 -> 0 | Q14: =-'Outputs - P&L'!Q$31 -> 0 | R14: =-'Outputs - P&L'!R$31 -> 0 | ... BR14: =-'Outputs - P&L'!BR$31 -> 0
B15: movement in trade debtors | D15: =unit -> £ | E15: =SUMIF($K$5:$BR$5,E$5,$K15:$BR15) -> 0 | F15: =SUMIF($K$5:$BR$5,F$5,$K15:$BR15) -> 0 | G15: =SUMIF($K$5:$BR$5,G$5,$K15:$BR15) -> 0 | H15: =SUMIF($K$5:$BR$5,H$5,$K15:$BR15) -> 0 | I15: =SUMIF($K$5:$BR$5,I$5,$K15:$BR15) -> 0 | K15: =WorkingCapital!K23+WorkingCapital!K34+WorkingCapital!K45 -> 0 | L15: =WorkingCapital!L23+WorkingCapital!L34+WorkingCapital!L45 -> 0 | M15: =WorkingCapital!M23+WorkingCapital!M34+WorkingCapital!M45 -> 0 | N15: =WorkingCapital!N23+WorkingCapital!N34+WorkingCapital!N45 -> 0 | O15: =WorkingCapital!O23+WorkingCapital!O34+WorkingCapital!O45 -> 0 | P15: =WorkingCapital!P23+WorkingCapital!P34+WorkingCapital!P45 -> 0 | Q15: =WorkingCapital!Q23+WorkingCapital!Q34+WorkingCapital!Q45 -> 0 | R15: =WorkingCapital!R23+WorkingCapital!R34+WorkingCapital!R45 -> 0 | ... BR15: =WorkingCapital!BR23+WorkingCapital!BR34+WorkingCapital!BR45 -> 0
B16: movement in stocks | D16: =unit -> £ | E16: =SUMIF($K$5:$BR$5,E$5,$K16:$BR16) -> 0 | F16: =SUMIF($K$5:$BR$5,F$5,$K16:$BR16) -> 0 | G16: =SUMIF($K$5:$BR$5,G$5,$K16:$BR16) -> 0 | H16: =SUMIF($K$5:$BR$5,H$5,$K16:$BR16) -> 0 | I16: =SUMIF($K$5:$BR$5,I$5,$K16:$BR16) -> 0 | K16: =WorkingCapital!K58+WorkingCapital!K69+WorkingCapital!K80 -> 0 | L16: =WorkingCapital!L58+WorkingCapital!L69+WorkingCapital!L80 -> 0 | M16: =WorkingCapital!M58+WorkingCapital!M69+WorkingCapital!M80 -> 0 | N16: =WorkingCapital!N58+WorkingCapital!N69+WorkingCapital!N80 -> 0 | O16: =WorkingCapital!O58+WorkingCapital!O69+WorkingCapital!O80 -> 0 | P16: =WorkingCapital!P58+WorkingCapital!P69+WorkingCapital!P80 -> 0 | Q16: =WorkingCapital!Q58+WorkingCapital!Q69+WorkingCapital!Q80 -> 0 | R16: =WorkingCapital!R58+WorkingCapital!R69+WorkingCapital!R80 -> 0 | ... BR16: =WorkingCapital!BR58+WorkingCapital!BR69+WorkingCapital!BR80 -> 0
B17: movement in trade creditors | D17: =unit -> £ | E17: =SUMIF($K$5:$BR$5,E$5,$K17:$BR17) -> 0 | F17: =SUMIF($K$5:$BR$5,F$5,$K17:$BR17) -> 0 | G17: =SUMIF($K$5:$BR$5,G$5,$K17:$BR17) -> 0 | H17: =SUMIF($K$5:$BR$5,H$5,$K17:$BR17) -> 0 | I17: =SUMIF($K$5:$BR$5,I$5,$K17:$BR17) -> 0 | K17: =WorkingCapital!K93 -> 0 | L17: =WorkingCapital!L93 -> 0 | M17: =WorkingCapital!M93 -> 0 | N17: =WorkingCapital!N93 -> 0 | O17: =WorkingCapital!O93 -> 0 | P17: =WorkingCapital!P93 -> 0 | Q17: =WorkingCapital!Q93 -> 0 | R17: =WorkingCapital!R93 -> 0 | ... BR17: =WorkingCapital!BR93 -> 0
B18: movement in VAT | D18: =unit -> £ | E18: =SUMIF($K$5:$BR$5,E$5,$K18:$BR18) -> 0 | F18: =SUMIF($K$5:$BR$5,F$5,$K18:$BR18) -> 0 | G18: =SUMIF($K$5:$BR$5,G$5,$K18:$BR18) -> 0 | H18: =SUMIF($K$5:$BR$5,H$5,$K18:$BR18) -> 0 | I18: =SUMIF($K$5:$BR$5,I$5,$K18:$BR18) -> 0 | K18: =WorkingCapital!K110 -> 0 | L18: =WorkingCapital!L110 -> 0 | M18: =WorkingCapital!M110 -> 0 | N18: =WorkingCapital!N110 -> 0 | O18: =WorkingCapital!O110 -> 0 | P18: =WorkingCapital!P110 -> 0 | Q18: =WorkingCapital!Q110 -> 0 | R18: =WorkingCapital!R110 -> 0 | ... BR18: =WorkingCapital!BR110 -> 0
B19: Operating cash flow | D19: =unit -> £ | E19: =SUM(E12:E18) -> 0 | F19: =SUM(F12:F18) -> 0 | G19: =SUM(G12:G18) -> 0 | H19: =SUM(H12:H18) -> 0 | I19: =SUM(I12:I18) -> 0 | K19: =SUM(K12:K18) -> 0 | L19: =SUM(L12:L18) -> 0 | M19: =SUM(M12:M18) -> 0 | N19: =SUM(N12:N18) -> 0 | O19: =SUM(O12:O18) -> 0 | P19: =SUM(P12:P18) -> 0 | Q19: =SUM(Q12:Q18) -> 0 | R19: =SUM(R12:R18) -> 0 | ... BR19: =SUM(BR12:BR18) -> 0
B21: Capital expenditure | D21: =unit -> £ | E21: =SUMIF($K$5:$BR$5,E$5,$K21:$BR21) -> 0 | F21: =SUMIF($K$5:$BR$5,F$5,$K21:$BR21) -> 0 | G21: =SUMIF($K$5:$BR$5,G$5,$K21:$BR21) -> 0 | H21: =SUMIF($K$5:$BR$5,H$5,$K21:$BR21) -> 0 | I21: =SUMIF($K$5:$BR$5,I$5,$K21:$BR21) -> 0 | K21: =-SUM(Capex!K13:K17) -> 0 | L21: =-SUM(Capex!L13:L17) -> 0 | M21: =-SUM(Capex!M13:M17) -> 0 | N21: =-SUM(Capex!N13:N17) -> 0 | O21: =-SUM(Capex!O13:O17) -> 0 | P21: =-SUM(Capex!P13:P17) -> 0 | Q21: =-SUM(Capex!Q13:Q17) -> 0 | R21: =-SUM(Capex!R13:R17) -> 0 | ... BR21: =-SUM(Capex!BR13:BR17) -> 0
B22: Proceeds of disposals | D22: =unit -> £ | E22: =SUMIF($K$5:$BR$5,E$5,$K22:$BR22) -> 0 | F22: =SUMIF($K$5:$BR$5,F$5,$K22:$BR22) -> 0 | G22: =SUMIF($K$5:$BR$5,G$5,$K22:$BR22) -> 0 | H22: =SUMIF($K$5:$BR$5,H$5,$K22:$BR22) -> 0 | I22: =SUMIF($K$5:$BR$5,I$5,$K22:$BR22) -> 0 | K22: =-SUM(Capex!K21:K25) -> 0 | L22: =-SUM(Capex!L21:L25) -> 0 | M22: =-SUM(Capex!M21:M25) -> 0 | N22: =-SUM(Capex!N21:N25) -> 0 | O22: =-SUM(Capex!O21:O25) -> 0 | P22: =-SUM(Capex!P21:P25) -> 0 | Q22: =-SUM(Capex!Q21:Q25) -> 0 | R22: =-SUM(Capex!R21:R25) -> 0 | ... BR22: =-SUM(Capex!BR21:BR25) -> 0
B24: Grant received | D24: =unit -> £ | E24: =SUMIF($K$5:$BR$5,E$5,$K24:$BR24) -> 0 | F24: =SUMIF($K$5:$BR$5,F$5,$K24:$BR24) -> 0 | G24: =SUMIF($K$5:$BR$5,G$5,$K24:$BR24) -> 0 | H24: =SUMIF($K$5:$BR$5,H$5,$K24:$BR24) -> 0 | I24: =SUMIF($K$5:$BR$5,I$5,$K24:$BR24) -> 0 | K24: =-GrantIncome!K15 -> 0 | L24: =-GrantIncome!L15 -> 0 | M24: =-GrantIncome!M15 -> 0 | N24: =-GrantIncome!N15 -> 0 | O24: =-GrantIncome!O15 -> 0 | P24: =-GrantIncome!P15 -> 0 | Q24: =-GrantIncome!Q15 -> 0 | R24: =-GrantIncome!R15 -> 0 | ... BR24: =-GrantIncome!BR15 -> 0
B25: Other income | D25: =unit -> £ | E25: =SUMIF($K$5:$BR$5,E$5,$K25:$BR25) -> 0 | F25: =SUMIF($K$5:$BR$5,F$5,$K25:$BR25) -> 0 | G25: =SUMIF($K$5:$BR$5,G$5,$K25:$BR25) -> 0 | H25: =SUMIF($K$5:$BR$5,H$5,$K25:$BR25) -> 0 | I25: =SUMIF($K$5:$BR$5,I$5,$K25:$BR25) -> 0 | K25: ='Other income'!K32 -> 0 | L25: ='Other income'!L32 -> 0 | M25: ='Other income'!M32 -> 0 | N25: ='Other income'!N32 -> 0 | O25: ='Other income'!O32 -> 0 | P25: ='Other income'!P32 -> 0 | Q25: ='Other income'!Q32 -> 0 | R25: ='Other income'!R32 -> 0 | ... BR25: ='Other income'!BR32 -> 0
B26: Equity finance received | D26: =unit -> £ | E26: =SUMIF($K$5:$BR$5,E$5,$K26:$BR26) -> 0 | F26: =SUMIF($K$5:$BR$5,F$5,$K26:$BR26) -> 0 | G26: =SUMIF($K$5:$BR$5,G$5,$K26:$BR26) -> 0 | H26: =SUMIF($K$5:$BR$5,H$5,$K26:$BR26) -> 0 | I26: =SUMIF($K$5:$BR$5,I$5,$K26:$BR26) -> 0 | K26: =EquityFinancing!K22 -> 0 | L26: =EquityFinancing!L22 -> 0 | M26: =EquityFinancing!M22 -> 0 | N26: =EquityFinancing!N22 -> 0 | O26: =EquityFinancing!O22 -> 0 | P26: =EquityFinancing!P22 -> 0 | Q26: =EquityFinancing!Q22 -> 0 | R26: =EquityFinancing!R22 -> 0 | ... BR26: =EquityFinancing!BR22 -> 0
B27: Drawings on debt | D27: =unit -> £ | E27: =SUMIF($K$5:$BR$5,E$5,$K27:$BR27) -> 0 | F27: =SUMIF($K$5:$BR$5,F$5,$K27:$BR27) -> 0 | G27: =SUMIF($K$5:$BR$5,G$5,$K27:$BR27) -> 0 | H27: =SUMIF($K$5:$BR$5,H$5,$K27:$BR27) -> 0 | I27: =SUMIF($K$5:$BR$5,I$5,$K27:$BR27) -> 0 | K27: =-DebtFinancing!K15 -> 0 | L27: =-DebtFinancing!L15 -> 0 | M27: =-DebtFinancing!M15 -> 0 | N27: =-DebtFinancing!N15 -> 0 | O27: =-DebtFinancing!O15 -> 0 | P27: =-DebtFinancing!P15 -> 0 | Q27: =-DebtFinancing!Q15 -> 0 | R27: =-DebtFinancing!R15 -> 0 | ... BR27: =-DebtFinancing!BR15 -> 0
B28: Repayments of debt | D28: =unit -> £ | E28: =SUMIF($K$5:$BR$5,E$5,$K28:$BR28) -> 0 | F28: =SUMIF($K$5:$BR$5,F$5,$K28:$BR28) -> 0 | G28: =SUMIF($K$5:$BR$5,G$5,$K28:$BR28) -> 0 | H28: =SUMIF($K$5:$BR$5,H$5,$K28:$BR28) -> 0 | I28: =SUMIF($K$5:$BR$5,I$5,$K28:$BR28) -> 0 | K28: =-DebtFinancing!K16 -> 0 | L28: =-DebtFinancing!L16 -> 0 | M28: =-DebtFinancing!M16 -> 0 | N28: =-DebtFinancing!N16 -> 0 | O28: =-DebtFinancing!O16 -> 0 | P28: =-DebtFinancing!P16 -> 0 | Q28: =-DebtFinancing!Q16 -> 0 | R28: =-DebtFinancing!R16 -> 0 | ... BR28: =-DebtFinancing!BR16 -> 0
B30: Interest on debt | D30: =unit -> £ | E30: =SUMIF($K$5:$BR$5,E$5,$K30:$BR30) -> 0 | F30: =SUMIF($K$5:$BR$5,F$5,$K30:$BR30) -> 0 | G30: =SUMIF($K$5:$BR$5,G$5,$K30:$BR30) -> 0 | H30: =SUMIF($K$5:$BR$5,H$5,$K30:$BR30) -> 0 | I30: =SUMIF($K$5:$BR$5,I$5,$K30:$BR30) -> 0 | K30: =-DebtFinancing!K23 -> 0 | L30: =-DebtFinancing!L23 -> 0 | M30: =-DebtFinancing!M23 -> 0 | N30: =-DebtFinancing!N23 -> 0 | O30: =-DebtFinancing!O23 -> 0 | P30: =-DebtFinancing!P23 -> 0 | Q30: =-DebtFinancing!Q23 -> 0 | R30: =-DebtFinancing!R23 -> 0 | ... BR30: =-DebtFinancing!BR23 -> 0
B32: Taxation | D32: =unit -> £ | E32: =SUMIF($K$5:$BR$5,E$5,$K32:$BR32) -> 0 | F32: =SUMIF($K$5:$BR$5,F$5,$K32:$BR32) -> 0 | G32: =SUMIF($K$5:$BR$5,G$5,$K32:$BR32) -> 0 | H32: =SUMIF($K$5:$BR$5,H$5,$K32:$BR32) -> 0 | I32: =SUMIF($K$5:$BR$5,I$5,$K32:$BR32) -> 0 | K32: =-TAX!K43 -> 0 | L32: =-TAX!L43 -> 0 | M32: =-TAX!M43 -> 0 | N32: =-TAX!N43 -> 0 | O32: =-TAX!O43 -> 0 | P32: =-TAX!P43 -> 0 | Q32: =-TAX!Q43 -> 0 | R32: =-TAX!R43 -> 0 | ... BR32: =-TAX!BR43 -> 0
B34: Dividends payable | D34: =unit -> £ | E34: =SUMIF($K$5:$BR$5,E$5,$K34:$BR34) -> 0 | F34: =SUMIF($K$5:$BR$5,F$5,$K34:$BR34) -> 0 | G34: =SUMIF($K$5:$BR$5,G$5,$K34:$BR34) -> 0 | H34: =SUMIF($K$5:$BR$5,H$5,$K34:$BR34) -> 0 | I34: =SUMIF($K$5:$BR$5,I$5,$K34:$BR34) -> 0 | K34: ='Outputs - P&L'!K43 -> 0 | L34: ='Outputs - P&L'!L43 -> 0 | M34: ='Outputs - P&L'!M43 -> 0 | N34: ='Outputs - P&L'!N43 -> 0 | O34: ='Outputs - P&L'!O43 -> 0 | P34: ='Outputs - P&L'!P43 -> 0 | Q34: ='Outputs - P&L'!Q43 -> 0 | R34: ='Outputs - P&L'!R43 -> 0 | ... BR34: ='Outputs - P&L'!BR43 -> 0
B36: Net cash flow | D36: =unit -> £ | E36: =SUM(E19:E35) -> 0 | F36: =SUM(F19:F35) -> 0 | G36: =SUM(G19:G35) -> 0 | H36: =SUM(H19:H35) -> 0 | I36: =SUM(I19:I35) -> 0 | K36: =SUM(K19:K35) -> 0 | L36: =SUM(L19:L35) -> 0 | M36: =SUM(M19:M35) -> 0 | N36: =SUM(N19:N35) -> 0 | O36: =SUM(O19:O35) -> 0 | P36: =SUM(P19:P35) -> 0 | Q36: =SUM(Q19:Q35) -> 0 | R36: =SUM(R19:R35) -> 0 | ... BR36: =SUM(BR19:BR35) -> 0
B38: Cash balance BF | D38: =unit -> £ | E38: =D41 -> 0 | F38: =E41 -> 0 | G38: =F41 -> 0 | H38: =G41 -> 0 | I38: =H41 -> 0 | K38: =J39 -> 0 | L38: =K41 -> 0 | M38: =L41 -> 0 | N38: =M41 -> 0 | O38: =N41 -> 0 | P38: =O41 -> 0 | Q38: =P41 -> 0 | R38: =Q41 -> 0 | S38: =R41 -> 0 | ... BR38: =BQ41 -> 0
B39: Cash balance CF (before interest) | D39: =KeyInputs!G128+KeyInputs!G130 -> 0 | E39: =SUM(E36:E38) -> 0 | F39: =SUM(F36:F38) -> 0 | G39: =SUM(G36:G38) -> 0 | H39: =SUM(H36:H38) -> 0 | I39: =SUM(I36:I38) -> 0 | J39: =D39 -> 0 | K39: =SUM(K36:K38) -> 0 | L39: =SUM(L36:L38) -> 0 | M39: =SUM(M36:M38) -> 0 | N39: =SUM(N36:N38) -> 0 | O39: =SUM(O36:O38) -> 0 | P39: =SUM(P36:P38) -> 0 | Q39: =SUM(Q36:Q38) -> 0 | R39: =SUM(R36:R38) -> 0 | ... BR39: =SUM(BR36:BR38) -> 0
B40: Cash/Overdraft interest | E40: =SUMIF($K$5:$BR$5,E$5,$K40:$BR40) -> 0 | F40: =SUMIF($K$5:$BR$5,F$5,$K40:$BR40) -> 0 | G40: =SUMIF($K$5:$BR$5,G$5,$K40:$BR40) -> 0 | H40: =SUMIF($K$5:$BR$5,H$5,$K40:$BR40) -> 0 | I40: =SUMIF($K$5:$BR$5,I$5,$K40:$BR40) -> 0 | K40: =IF(K39<0,K39*KeyInputs!$F$80,'Outputs - Cashflow'!K39*KeyInputs!$F$81)/12 -> 0 | L40: =IF(L39<0,L39*KeyInputs!$F$80,'Outputs - Cashflow'!L39*KeyInputs!$F$81)/12 -> 0 | M40: =IF(M39<0,M39*KeyInputs!$F$80,'Outputs - Cashflow'!M39*KeyInputs!$F$81)/12 -> 0 | N40: =IF(N39<0,N39*KeyInputs!$F$80,'Outputs - Cashflow'!N39*KeyInputs!$F$81)/12 -> 0 | O40: =IF(O39<0,O39*KeyInputs!$F$80,'Outputs - Cashflow'!O39*KeyInputs!$F$81)/12 -> 0 | P40: =IF(P39<0,P39*KeyInputs!$F$80,'Outputs - Cashflow'!P39*KeyInputs!$F$81)/12 -> 0 | Q40: =IF(Q39<0,Q39*KeyInputs!$F$80,'Outputs - Cashflow'!Q39*KeyInputs!$F$81)/12 -> 0 | R40: =IF(R39<0,R39*KeyInputs!$F$80,'Outputs - Cashflow'!R39*KeyInputs!$F$81)/12 -> 0 | ... BR40: =IF(BR39<0,BR39*KeyInputs!$F$80,'Outputs - Cashflow'!BR39*KeyInputs!$F$81)/12 -> 0
B41: Cash balance CF | D41: =KeyInputs!G128 -> 0 | E41: =SUM(E39:E40) -> 0 | F41: =SUM(F39:F40) -> 0 | G41: =SUM(G39:G40) -> 0 | H41: =SUM(H39:H40) -> 0 | I41: =SUM(I39:I40) -> 0 | J41: =D41 -> 0 | K41: =SUM(K39:K40) -> 0 | L41: =SUM(L39:L40) -> 0 | M41: =SUM(M39:M40) -> 0 | N41: =SUM(N39:N40) -> 0 | O41: =SUM(O39:O40) -> 0 | P41: =SUM(P39:P40) -> 0 | Q41: =SUM(Q39:Q40) -> 0 | R41: =SUM(R39:R40) -> 0 | ... BR41: =SUM(BR39:BR40) -> 0
A44: End of sheet

Sheet Outputs - Sensitivities
A3: =IF(KeyInputs!$F$14=0,"Company Name",KeyInputs!$F$14) -> Company Name
A4: Sensitivities
D5: =KeyInputs!D5 -> Year | E5: =KeyInputs!E5 -> 2012 | F5: =KeyInputs!F5 -> 2013 | G5: =KeyInputs!G5 -> 2014 | H5: =KeyInputs!H5 -> 2015 | I5: =KeyInputs!I5 -> 2016 | J5: =KeyInputs!J5 -> 2017 | K5: =KeyInputs!K5 -> 2018 | L5: =KeyInputs!L5 -> 2019 | N5: =E5 -> 2012 | O5: =F5 -> 2013 | P5: =G5 -> 2014 | Q5: =H5 -> 2015 | R5: =I5 -> 2016 | S5: =J5 -> 2017 | T5: =K5 -> 2018 | U5: =L5 -> 2019 | W5: =N5 -> 2012 | X5: =O5 -> 2013 | Y5: =P5 -> 2014 | Z5: =Q5 -> 2015 | AA5: =R5 -> 2016 | AB5: =S5 -> 2017 | AC5: =T5 -> 2018 | AD5: =U5 -> 2019
D6: =KeyInputs!D6 -> Period number | E6: =KeyInputs!E6 -> -2 | F6: =KeyInputs!F6 -> -1 | G6: =KeyInputs!G6 -> 0 | H6: =KeyInputs!H6 -> 1 | I6: =KeyInputs!I6 -> 2 | J6: =KeyInputs!J6 -> 3 | K6: =KeyInputs!K6 -> 4 | L6: =KeyInputs!L6 -> 5 | N6: =E6 -> -2 | O6: =F6 -> -1 | P6: =G6 -> 0 | Q6: =H6 -> 1 | R6: =I6 -> 2 | S6: =J6 -> 3 | T6: =K6 -> 4 | U6: =L6 -> 5 | W6: =N6 -> -2 | X6: =O6 -> -1 | Y6: =P6 -> 0 | Z6: =Q6 -> 1 | AA6: =R6 -> 2 | AB6: =S6 -> 3 | AC6: =T6 -> 4 | AD6: =U6 -> 5
D7: =KeyInputs!D7 -> Period starts | E7: =KeyInputs!E7 -> 40909 | F7: =KeyInputs!F7 -> 41275 | G7: =KeyInputs!G7 -> 41640 | H7: =KeyInputs!H7 -> 42005 | I7: =KeyInputs!I7 -> 42370 | J7: =KeyInputs!J7 -> 42736 | K7: =KeyInputs!K7 -> 43101 | L7: =KeyInputs!L7 -> 43466 | N7: =E7 -> 40909 | O7: =F7 -> 41275 | P7: =G7 -> 41640 | Q7: =H7 -> 42005 | R7: =I7 -> 42370 | S7: =J7 -> 42736 | T7: =K7 -> 43101 | U7: =L7 -> 43466 | W7: =N7 -> 40909 | X7: =O7 -> 41275 | Y7: =P7 -> 41640 | Z7: =Q7 -> 42005 | AA7: =R7 -> 42370 | AB7: =S7 -> 42736 | AC7: =T7 -> 43101 | AD7: =U7 -> 43466
B8: =IF(Check!$C$12=0,"All checks are OK","There are "&Check!$C$12&" error/errors") -> All checks are OK | D8: =KeyInputs!D8 -> Period ends | E8: =KeyInputs!E8 -> 41274 | F8: =KeyInputs!F8 -> 41639 | G8: =KeyInputs!G8 -> 42004 | H8: =KeyInputs!H8 -> 42369 | I8: =KeyInputs!I8 -> 42735 | J8: =KeyInputs!J8 -> 43100 | K8: =KeyInputs!K8 -> 43465 | L8: =KeyInputs!L8 -> 43830 | N8: =E8 -> 41274 | O8: =F8 -> 41639 | P8: =G8 -> 42004 | Q8: =H8 -> 42369 | R8: =I8 -> 42735 | S8: =J8 -> 43100 | T8: =K8 -> 43465 | U8: =L8 -> 43830 | W8: =N8 -> 41274 | X8: =O8 -> 41639 | Y8: =P8 -> 42004 | Z8: =Q8 -> 42369 | AA8: =R8 -> 42735 | AB8: =S8 -> 43100 | AC8: =T8 -> 43465 | AD8: =U8 -> 43830
B10: Base case scenario | N10: Sensitised case scenario | W10: Variance
A12: =Header1 -> 1 | B12: Profit & Loss Account
B14: Sales | D14: =unit -> £ | E14: =SUM(E15:E17) -> 0 | F14: =SUM(F15:F17) -> 0 | G14: =SUM(G15:G17) -> 0 | H14: =SUM(H15:H17) -> 0 | I14: =SUM(I15:I17) -> 0 | J14: =SUM(J15:J17) -> 0 | K14: =SUM(K15:K17) -> 0 | L14: =SUM(L15:L17) -> 0 | N14: ='Outputs - Summary'!E12 -> 0 | O14: ='Outputs - Summary'!F12 -> 0 | P14: ='Outputs - Summary'!G12 -> 0 | Q14: ='Outputs - Summary'!H12 -> 0 | R14: ='Outputs - Summary'!I12 -> 0 | S14: ='Outputs - Summary'!J12 -> 0 | T14: ='Outputs - Summary'!K12 -> 0 | U14: ='Outputs - Summary'!L12 -> 0 | W14: =N14-E14 -> 0 | X14: =O14-F14 -> 0 | Y14: =P14-G14 -> 0 | Z14: =Q14-H14 -> 0 | AA14: =R14-I14 -> 0 | AB14: =S14-J14 -> 0 | AC14: =T14-K14 -> 0 | AD14: =U14-L14 -> 0
B15: =KeyInputs!F21 -> Test | D15: =unit -> £ | E15: =KeyInputs!E156 -> 0 | F15: =KeyInputs!F156 -> 0 | G15: =KeyInputs!G156 -> 0 | H15: ='Outputs - P&L'!E13 -> 0 | I15: ='Outputs - P&L'!F13 -> 0 | J15: ='Outputs - P&L'!G13 -> 0 | K15: ='Outputs - P&L'!H13 -> 0 | L15: ='Outputs - P&L'!I13 -> 0 | N15: ='Outputs - Summary'!E13 -> 0 | O15: ='Outputs - Summary'!F13 -> 0 | P15: ='Outputs - Summary'!G13 -> 0 | Q15: ='Outputs - Summary'!H13 -> 0 | R15: ='Outputs - Summary'!I13 -> 0 | S15: ='Outputs - Summary'!J13 -> 0 | T15: ='Outputs - Summary'!K13 -> 0 | U15: ='Outputs - Summary'!L13 -> 0 | W15: =N15-E15 -> 0 | X15: =O15-F15 -> 0 | Y15: =P15-G15 -> 0 | Z15: =Q15-H15 -> 0 | AA15: =R15-I15 -> 0 | AB15: =S15-J15 -> 0 | AC15: =T15-K15 -> 0 | AD15: =U15-L15 -> 0
B16: =KeyInputs!F26 -> Insert Business Line2 | D16: =unit -> £ | E16: =KeyInputs!E157 -> 0 | F16: =KeyInputs!F157 -> 0 | G16: =KeyInputs!G157 -> 0 | H16: ='Outputs - P&L'!E14 -> 0 | I16: ='Outputs - P&L'!F14 -> 0 | J16: ='Outputs - P&L'!G14 -> 0 | K16: ='Outputs - P&L'!H14 -> 0 | L16: ='Outputs - P&L'!I14 -> 0 | N16: ='Outputs - Summary'!E14 -> 0 | O16: ='Outputs - Summary'!F14 -> 0 | P16: ='Outputs - Summary'!G14 -> 0 | Q16: ='Outputs - Summary'!H14 -> 0 | R16: ='Outputs - Summary'!I14 -> 0 | S16: ='Outputs - Summary'!J14 -> 0 | T16: ='Outputs - Summary'!K14 -> 0 | U16: ='Outputs - Summary'!L14 -> 0 | W16: =N16-E16 -> 0 | X16: =O16-F16 -> 0 | Y16: =P16-G16 -> 0 | Z16: =Q16-H16 -> 0 | AA16: =R16-I16 -> 0 | AB16: =S16-J16 -> 0 | AC16: =T16-K16 -> 0 | AD16: =U16-L16 -> 0
B17: =KeyInputs!F31 -> Insert Business Line3 | D17: =unit -> £ | E17: =KeyInputs!E158 -> 0 | F17: =KeyInputs!F158 -> 0 | G17: =KeyInputs!G158 -> 0 | H17: ='Outputs - P&L'!E15 -> 0 | I17: ='Outputs - P&L'!F15 -> 0 | J17: ='Outputs - P&L'!G15 -> 0 | K17: ='Outputs - P&L'!H15 -> 0 | L17: ='Outputs - P&L'!I15 -> 0 | N17: ='Outputs - Summary'!E15 -> 0 | O17: ='Outputs - Summary'!F15 -> 0 | P17: ='Outputs - Summary'!G15 -> 0 | Q17: ='Outputs - Summary'!H15 -> 0 | R17: ='Outputs - Summary'!I15 -> 0 | S17: ='Outputs - Summary'!J15 -> 0 | T17: ='Outputs - Summary'!K15 -> 0 | U17: ='Outputs - Summary'!L15 -> 0 | W17: =N17-E17 -> 0 | X17: =O17-F17 -> 0 | Y17: =P17-G17 -> 0 | Z17: =Q17-H17 -> 0 | AA17: =R17-I17 -> 0 | AB17: =S17-J17 -> 0 | AC17: =T17-K17 -> 0 | AD17: =U17-L17 -> 0
B19: Variable costs | D19: =unit -> £ | E19: =SUM(E20:E22) -> 0 | F19: =SUM(F20:F22) -> 0 | G19: =SUM(G20:G22) -> 0 | H19: =SUM(H20:H22) -> 0 | I19: =SUM(I20:I22) -> 0 | J19: =SUM(J20:J22) -> 0 | K19: =SUM(K20:K22) -> 0 | L19: =SUM(L20:L22) -> 0 | N19: ='Outputs - Summary'!E17 -> 0 | O19: ='Outputs - Summary'!F17 -> 0 | P19: ='Outputs - Summary'!G17 -> 0 | Q19: ='Outputs - Summary'!H17 -> 0 | R19: ='Outputs - Summary'!I17 -> 0 | S19: ='Outputs - Summary'!J17 -> 0 | T19: ='Outputs - Summary'!K17 -> 0 | U19: ='Outputs - Summary'!L17 -> 0 | W19: =N19-E19 -> 0 | X19: =O19-F19 -> 0 | Y19: =P19-G19 -> 0 | Z19: =Q19-H19 -> 0 | AA19: =R19-I19 -> 0 | AB19: =S19-J19 -> 0 | AC19: =T19-K19 -> 0 | AD19: =U19-L19 -> 0
B20: =B15 -> Test | D20: =unit -> £ | E20: =KeyInputs!E161 -> 0 | F20: =KeyInputs!F161 -> 0 | G20: =KeyInputs!G161 -> 0 | H20: ='Outputs - P&L'!E18 -> 0 | I20: ='Outputs - P&L'!F18 -> 0 | J20: ='Outputs - P&L'!G18 -> 0 | K20: ='Outputs - P&L'!H18 -> 0 | L20: ='Outputs - P&L'!I18 -> 0 | N20: ='Outputs - Summary'!E18 -> 0 | O20: ='Outputs - Summary'!F18 -> 0 | P20: ='Outputs - Summary'!G18 -> 0 | Q20: ='Outputs - Summary'!H18 -> 0 | R20: ='Outputs - Summary'!I18 -> 0 | S20: ='Outputs - Summary'!J18 -> 0 | T20: ='Outputs - Summary'!K18 -> 0 | U20: ='Outputs - Summary'!L18 -> 0 | W20: =N20-E20 -> 0 | X20: =O20-F20 -> 0 | Y20: =P20-G20 -> 0 | Z20: =Q20-H20 -> 0 | AA20: =R20-I20 -> 0 | AB20: =S20-J20 -> 0 | AC20: =T20-K20 -> 0 | AD20: =U20-L20 -> 0
B21: =B16 -> Insert Business Line2 | D21: =unit -> £ | E21: =KeyInputs!E162 -> 0 | F21: =KeyInputs!F162 -> 0 | G21: =KeyInputs!G162 -> 0 | H21: ='Outputs - P&L'!E19 -> 0 | I21: ='Outputs - P&L'!F19 -> 0 | J21: ='Outputs - P&L'!G19 -> 0 | K21: ='Outputs - P&L'!H19 -> 0 | L21: ='Outputs - P&L'!I19 -> 0 | N21: ='Outputs - Summary'!E19 -> 0 | O21: ='Outputs - Summary'!F19 -> 0 | P21: ='Outputs - Summary'!G19 -> 0 | Q21: ='Outputs - Summary'!H19 -> 0 | R21: ='Outputs - Summary'!I19 -> 0 | S21: ='Outputs - Summary'!J19 -> 0 | T21: ='Outputs - Summary'!K19 -> 0 | U21: ='Outputs - Summary'!L19 -> 0 | W21: =N21-E21 -> 0 | X21: =O21-F21 -> 0 | Y21: =P21-G21 -> 0 | Z21: =Q21-H21 -> 0 | AA21: =R21-I21 -> 0 | AB21: =S21-J21 -> 0 | AC21: =T21-K21 -> 0 | AD21: =U21-L21 -> 0
B22: =B17 -> Insert Business Line3 | D22: =unit -> £ | E22: =KeyInputs!E163 -> 0 | F22: =KeyInputs!F163 -> 0 | G22: =KeyInputs!G163 -> 0 | H22: ='Outputs - P&L'!E20 -> 0 | I22: ='Outputs - P&L'!F20 -> 0 | J22: ='Outputs - P&L'!G20 -> 0 | K22: ='Outputs - P&L'!H20 -> 0 | L22: ='Outputs - P&L'!I20 -> 0 | N22: ='Outputs - Summary'!E20 -> 0 | O22: ='Outputs - Summary'!F20 -> 0 | P22: ='Outputs - Summary'!G20 -> 0 | Q22: ='Outputs - Summary'!H20 -> 0 | R22: ='Outputs - Summary'!I20 -> 0 | S22: ='Outputs - Summary'!J20 -> 0 | T22: ='Outputs - Summary'!K20 -> 0 | U22: ='Outputs - Summary'!L20 -> 0 | W22: =N22-E22 -> 0 | X22: =O22-F22 -> 0 | Y22: =P22-G22 -> 0 | Z22: =Q22-H22 -> 0 | AA22: =R22-I22 -> 0 | AB22: =S22-J22 -> 0 | AC22: =T22-K22 -> 0 | AD22: =U22-L22 -> 0
B24: Direct staff costs | D24: =unit -> £ | E24: =SUM(E25:E27) -> 0 | F24: =SUM(F25:F27) -> 0 | G24: =SUM(G25:G27) -> 0 | H24: =SUM(H25:H27) -> 0 | I24: =SUM(I25:I27) -> 0 | J24: =SUM(J25:J27) -> 0 | K24: =SUM(K25:K27) -> 0 | L24: =SUM(L25:L27) -> 0 | N24: ='Outputs - Summary'!E22 -> 0 | O24: ='Outputs - Summary'!F22 -> 0 | P24: ='Outputs - Summary'!G22 -> 0 | Q24: ='Outputs - Summary'!H22 -> 0 | R24: ='Outputs - Summary'!I22 -> 0 | S24: ='Outputs - Summary'!J22 -> 0 | T24: ='Outputs - Summary'!K22 -> 0 | U24: ='Outputs - Summary'!L22 -> 0 | W24: =N24-E24 -> 0 | X24: =O24-F24 -> 0 | Y24: =P24-G24 -> 0 | Z24: =Q24-H24 -> 0 | AA24: =R24-I24 -> 0 | AB24: =S24-J24 -> 0 | AC24: =T24-K24 -> 0 | AD24: =U24-L24 -> 0
B25: =B15 -> Test | D25: =unit -> £ | E25: =KeyInputs!E166 -> 0 | F25: =KeyInputs!F166 -> 0 | G25: =KeyInputs!G166 -> 0 | H25: ='Outputs - P&L'!E23 -> 0 | I25: ='Outputs - P&L'!F23 -> 0 | J25: ='Outputs - P&L'!G23 -> 0 | K25: ='Outputs - P&L'!H23 -> 0 | L25: ='Outputs - P&L'!I23 -> 0 | N25: ='Outputs - Summary'!E23 -> 0 | O25: ='Outputs - Summary'!F23 -> 0 | P25: ='Outputs - Summary'!G23 -> 0 | Q25: ='Outputs - Summary'!H23 -> 0 | R25: ='Outputs - Summary'!I23 -> 0 | S25: ='Outputs - Summary'!J23 -> 0 | T25: ='Outputs - Summary'!K23 -> 0 | U25: ='Outputs - Summary'!L23 -> 0 | W25: =N25-E25 -> 0 | X25: =O25-F25 -> 0 | Y25: =P25-G25 -> 0 | Z25: =Q25-H25 -> 0 | AA25: =R25-I25 -> 0 | AB25: =S25-J25 -> 0 | AC25: =T25-K25 -> 0 | AD25: =U25-L25 -> 0
B26: =B16 -> Insert Business Line2 | D26: =unit -> £ | E26: =KeyInputs!E167 -> 0 | F26: =KeyInputs!F167 -> 0 | G26: =KeyInputs!G167 -> 0 | H26: ='Outputs - P&L'!E24 -> 0 | I26: ='Outputs - P&L'!F24 -> 0 | J26: ='Outputs - P&L'!G24 -> 0 | K26: ='Outputs - P&L'!H24 -> 0 | L26: ='Outputs - P&L'!I24 -> 0 | N26: ='Outputs - Summary'!E24 -> 0 | O26: ='Outputs - Summary'!F24 -> 0 | P26: ='Outputs - Summary'!G24 -> 0 | Q26: ='Outputs - Summary'!H24 -> 0 | R26: ='Outputs - Summary'!I24 -> 0 | S26: ='Outputs - Summary'!J24 -> 0 | T26: ='Outputs - Summary'!K24 -> 0 | U26: ='Outputs - Summary'!L24 -> 0 | W26: =N26-E26 -> 0 | X26: =O26-F26 -> 0 | Y26: =P26-G26 -> 0 | Z26: =Q26-H26 -> 0 | AA26: =R26-I26 -> 0 | AB26: =S26-J26 -> 0 | AC26: =T26-K26 -> 0 | AD26: =U26-L26 -> 0
B27: =B17 -> Insert Business Line3 | D27: =unit -> £ | E27: =KeyInputs!E168 -> 0 | F27: =KeyInputs!F168 -> 0 | G27: =KeyInputs!G168 -> 0 | H27: ='Outputs - P&L'!E25 -> 0 | I27: ='Outputs - P&L'!F25 -> 0 | J27: ='Outputs - P&L'!G25 -> 0 | K27: ='Outputs - P&L'!H25 -> 0 | L27: ='Outputs - P&L'!I25 -> 0 | N27: ='Outputs - Summary'!E25 -> 0 | O27: ='Outputs - Summary'!F25 -> 0 | P27: ='Outputs - Summary'!G25 -> 0 | Q27: ='Outputs - Summary'!H25 -> 0 | R27: ='Outputs - Summary'!I25 -> 0 | S27: ='Outputs - Summary'!J25 -> 0 | T27: ='Outputs - Summary'!K25 -> 0 | U27: ='Outputs - Summary'!L25 -> 0 | W27: =N27-E27 -> 0 | X27: =O27-F27 -> 0 | Y27: =P27-G27 -> 0 | Z27: =Q27-H27 -> 0 | AA27: =R27-I27 -> 0 | AB27: =S27-J27 -> 0 | AC27: =T27-K27 -> 0 | AD27: =U27-L27 -> 0
B29: Gross profit | D29: =unit -> £ | E29: =SUM(E14,E19,E24) -> 0 | F29: =SUM(F14,F19,F24) -> 0 | G29: =SUM(G14,G19,G24) -> 0 | H29: =SUM(H14,H19,H24) -> 0 | I29: =SUM(I14,I19,I24) -> 0 | J29: =SUM(J14,J19,J24) -> 0 | K29: =SUM(K14,K19,K24) -> 0 | L29: =SUM(L14,L19,L24) -> 0 | N29: ='Outputs - Summary'!E27 -> 0 | O29: ='Outputs - Summary'!F27 -> 0 | P29: ='Outputs - Summary'!G27 -> 0 | Q29: ='Outputs - Summary'!H27 -> 0 | R29: ='Outputs - Summary'!I27 -> 0 | S29: ='Outputs - Summary'!J27 -> 0 | T29: ='Outputs - Summary'!K27 -> 0 | U29: ='Outputs - Summary'!L27 -> 0 | W29: =N29-E29 -> 0 | X29: =O29-F29 -> 0 | Y29: =P29-G29 -> 0 | Z29: =Q29-H29 -> 0 | AA29: =R29-I29 -> 0 | AB29: =S29-J29 -> 0 | AC29: =T29-K29 -> 0 | AD29: =U29-L29 -> 0
B31: Central staff costs | D31: =unit -> £ | E31: =KeyInputs!E172 -> 0 | F31: =KeyInputs!F172 -> 0 | G31: =KeyInputs!G172 -> 0 | H31: ='Outputs - P&L'!E29 -> 0 | I31: ='Outputs - P&L'!F29 -> 0 | J31: ='Outputs - P&L'!G29 -> 0 | K31: ='Outputs - P&L'!H29 -> 0 | L31: ='Outputs - P&L'!I29 -> 0 | N31: ='Outputs - Summary'!E29 -> 0 | O31: ='Outputs - Summary'!F29 -> 0 | P31: ='Outputs - Summary'!G29 -> 0 | Q31: ='Outputs - Summary'!H29 -> 0 | R31: ='Outputs - Summary'!I29 -> 0 | S31: ='Outputs - Summary'!J29 -> 0 | T31: ='Outputs - Summary'!K29 -> 0 | U31: ='Outputs - Summary'!L29 -> 0 | W31: =N31-E31 -> 0 | X31: =O31-F31 -> 0 | Y31: =P31-G31 -> 0 | Z31: =Q31-H31 -> 0 | AA31: =R31-I31 -> 0 | AB31: =S31-J31 -> 0 | AC31: =T31-K31 -> 0 | AD31: =U31-L31 -> 0
B32: Central costs | D32: =unit -> £ | E32: =KeyInputs!E173 -> 0 | F32: =KeyInputs!F173 -> 0 | G32: =KeyInputs!G173 -> 0 | H32: ='Outputs - P&L'!E30 -> 0 | I32: ='Outputs - P&L'!F30 -> 0 | J32: ='Outputs - P&L'!G30 -> 0 | K32: ='Outputs - P&L'!H30 -> 0 | L32: ='Outputs - P&L'!I30 -> 0 | N32: ='Outputs - Summary'!E30 -> 0 | O32: ='Outputs - Summary'!F30 -> 0 | P32: ='Outputs - Summary'!G30 -> 0 | Q32: ='Outputs - Summary'!H30 -> 0 | R32: ='Outputs - Summary'!I30 -> 0 | S32: ='Outputs - Summary'!J30 -> 0 | T32: ='Outputs - Summary'!K30 -> 0 | U32: ='Outputs - Summary'!L30 -> 0 | W32: =N32-E32 -> 0 | X32: =O32-F32 -> 0 | Y32: =P32-G32 -> 0 | Z32: =Q32-H32 -> 0 | AA32: =R32-I32 -> 0 | AB32: =S32-J32 -> 0 | AC32: =T32-K32 -> 0 | AD32: =U32-L32 -> 0
B33: Depreciation | D33: =unit -> £ | E33: =KeyInputs!E174 -> 0 | F33: =KeyInputs!F174 -> 0 | G33: =KeyInputs!G174 -> 0 | H33: ='Outputs - P&L'!E31 -> 0 | I33: ='Outputs - P&L'!F31 -> 0 | J33: ='Outputs - P&L'!G31 -> 0 | K33: ='Outputs - P&L'!H31 -> 0 | L33: ='Outputs - P&L'!I31 -> 0 | N33: ='Outputs - Summary'!E31 -> 0 | O33: ='Outputs - Summary'!F31 -> 0 | P33: ='Outputs - Summary'!G31 -> 0 | Q33: ='Outputs - Summary'!H31 -> 0 | R33: ='Outputs - Summary'!I31 -> 0 | S33: ='Outputs - Summary'!J31 -> 0 | T33: ='Outputs - Summary'!K31 -> 0 | U33: ='Outputs - Summary'!L31 -> 0 | W33: =N33-E33 -> 0 | X33: =O33-F33 -> 0 | Y33: =P33-G33 -> 0 | Z33: =Q33-H33 -> 0 | AA33: =R33-I33 -> 0 | AB33: =S33-J33 -> 0 | AC33: =T33-K33 -> 0 | AD33: =U33-L33 -> 0
B34: Operating profit | D34: =unit -> £ | E34: =SUM(E29:E33) -> 0 | F34: =SUM(F29:F33) -> 0 | G34: =SUM(G29:G33) -> 0 | H34: =SUM(H29:H33) -> 0 | I34: =SUM(I29:I33) -> 0 | J34: =SUM(J29:J33) -> 0 | K34: =SUM(K29:K33) -> 0 | L34: =SUM(L29:L33) -> 0 | N34: ='Outputs - Summary'!E32 -> 0 | O34: ='Outputs - Summary'!F32 -> 0 | P34: ='Outputs - Summary'!G32 -> 0 | Q34: ='Outputs - Summary'!H32 -> 0 | R34: ='Outputs - Summary'!I32 -> 0 | S34: ='Outputs - Summary'!J32 -> 0 | T34: ='Outputs - Summary'!K32 -> 0 | U34: ='Outputs - Summary'!L32 -> 0 | W34: =N34-E34 -> 0 | X34: =O34-F34 -> 0 | Y34: =P34-G34 -> 0 | Z34: =Q34-H34 -> 0 | AA34: =R34-I34 -> 0 | AB34: =S34-J34 -> 0 | AC34: =T34-K34 -> 0 | AD34: =U34-L34 -> 0
B36: Grant income | D36: =unit -> £ | E36: =KeyInputs!E177 -> 0 | F36: =KeyInputs!F177 -> 0 | G36: =KeyInputs!G177 -> 0 | H36: ='Outputs - P&L'!E34 -> 0 | I36: ='Outputs - P&L'!F34 -> 0 | J36: ='Outputs - P&L'!G34 -> 0 | K36: ='Outputs - P&L'!H34 -> 0 | L36: ='Outputs - P&L'!I34 -> 0 | N36: ='Outputs - Summary'!E34 -> 0 | O36: ='Outputs - Summary'!F34 -> 0 | P36: ='Outputs - Summary'!G34 -> 0 | Q36: ='Outputs - Summary'!H34 -> 0 | R36: ='Outputs - Summary'!I34 -> 0 | S36: ='Outputs - Summary'!J34 -> 0 | T36: ='Outputs - Summary'!K34 -> 0 | U36: ='Outputs - Summary'!L34 -> 0 | W36: =N36-E36 -> 0 | X36: =O36-F36 -> 0 | Y36: =P36-G36 -> 0 | Z36: =Q36-H36 -> 0 | AA36: =R36-I36 -> 0 | AB36: =S36-J36 -> 0 | AC36: =T36-K36 -> 0 | AD36: =U36-L36 -> 0
B37: Interest on debt | D37: =unit -> £ | E37: =KeyInputs!E179 -> 0 | F37: =KeyInputs!F179 -> 0 | G37: =KeyInputs!G179 -> 0 | H37: ='Outputs - P&L'!E36 -> 0 | I37: ='Outputs - P&L'!F36 -> 0 | J37: ='Outputs - P&L'!G36 -> 0 | K37: ='Outputs - P&L'!H36 -> 0 | L37: ='Outputs - P&L'!I36 -> 0 | N37: ='Outputs - Summary'!E36 -> 0 | O37: ='Outputs - Summary'!F36 -> 0 | P37: ='Outputs - Summary'!G36 -> 0 | Q37: ='Outputs - Summary'!H36 -> 0 | R37: ='Outputs - Summary'!I36 -> 0 | S37: ='Outputs - Summary'!J36 -> 0 | T37: ='Outputs - Summary'!K36 -> 0 | U37: ='Outputs - Summary'!L36 -> 0 | W37: =N37-E37 -> 0 | X37: =O37-F37 -> 0 | Y37: =P37-G37 -> 0 | Z37: =Q37-H37 -> 0 | AA37: =R37-I37 -> 0 | AB37: =S37-J37 -> 0 | AC37: =T37-K37 -> 0 | AD37: =U37-L37 -> 0
B38: Overdraft interest | E38: =KeyInputs!E180 -> 0 | F38: =KeyInputs!F180 -> 0 | G38: =KeyInputs!G180 -> 0 | H38: ='Outputs - P&L'!E37 -> 0 | I38: ='Outputs - P&L'!F37 -> 0 | J38: ='Outputs - P&L'!G37 -> 0 | K38: ='Outputs - P&L'!H37 -> 0 | L38: ='Outputs - P&L'!I37 -> 0 | N38: ='Outputs - Summary'!E37 -> 0 | O38: ='Outputs - Summary'!F37 -> 0 | P38: ='Outputs - Summary'!G37 -> 0 | Q38: ='Outputs - Summary'!H37 -> 0 | R38: ='Outputs - Summary'!I37 -> 0 | S38: ='Outputs - Summary'!J37 -> 0 | T38: ='Outputs - Summary'!K37 -> 0 | U38: ='Outputs - Summary'!L37 -> 0
B39: PBT | D39: =unit -> £ | E39: =SUM(E34:E38) -> 0 | F39: =SUM(F34:F38) -> 0 | G39: =SUM(G34:G38) -> 0 | H39: =SUM(H34:H38) -> 0 | I39: =SUM(I34:I38) -> 0 | J39: =SUM(J34:J38) -> 0 | K39: =SUM(K34:K38) -> 0 | L39: =SUM(L34:L38) -> 0 | N39: =SUM(N34:N38) -> 0 | O39: =SUM(O34:O38) -> 0 | P39: =SUM(P34:P38) -> 0 | Q39: =SUM(Q34:Q38) -> 0 | R39: =SUM(R34:R38) -> 0 | S39: =SUM(S34:S38) -> 0 | T39: =SUM(T34:T38) -> 0 | U39: =SUM(U34:U38) -> 0 | W39: =N39-E39 -> 0 | X39: =O39-F39 -> 0 | Y39: =P39-G39 -> 0 | Z39: =Q39-H39 -> 0 | AA39: =R39-I39 -> 0 | AB39: =S39-J39 -> 0 | AC39: =T39-K39 -> 0 | AD39: =U39-L39 -> 0
B41: Current tax | D41: =unit -> £ | E41: =KeyInputs!E183 -> 0 | F41: =KeyInputs!F183 -> 0 | G41: =KeyInputs!G183 -> 0 | H41: ='Outputs - P&L'!E40 -> 0 | I41: ='Outputs - P&L'!F40 -> 0 | J41: ='Outputs - P&L'!G40 -> 0 | K41: ='Outputs - P&L'!H40 -> 0 | L41: ='Outputs - P&L'!I40 -> 0 | N41: ='Outputs - Summary'!E40 -> 0 | O41: ='Outputs - Summary'!F40 -> 0 | P41: ='Outputs - Summary'!G40 -> 0 | Q41: ='Outputs - Summary'!H40 -> 0 | R41: ='Outputs - Summary'!I40 -> 0 | S41: ='Outputs - Summary'!J40 -> 0 | T41: ='Outputs - Summary'!K40 -> 0 | U41: ='Outputs - Summary'!L40 -> 0 | W41: =N41-E41 -> 0 | X41: =O41-F41 -> 0 | Y41: =P41-G41 -> 0 | Z41: =Q41-H41 -> 0 | AA41: =R41-I41 -> 0 | AB41: =S41-J41 -> 0 | AC41: =T41-K41 -> 0 | AD41: =U41-L41 -> 0
B42: PAT | D42: =unit -> £ | E42: =SUM(E39:E41) -> 0 | F42: =SUM(F39:F41) -> 0 | G42: =SUM(G39:G41) -> 0 | H42: =SUM(H39:H41) -> 0 | I42: =SUM(I39:I41) -> 0 | J42: =SUM(J39:J41) -> 0 | K42: =SUM(K39:K41) -> 0 | L42: =SUM(L39:L41) -> 0 | N42: ='Outputs - Summary'!E41 -> 0 | O42: ='Outputs - Summary'!F41 -> 0 | P42: ='Outputs - Summary'!G41 -> 0 | Q42: ='Outputs - Summary'!H41 -> 0 | R42: ='Outputs - Summary'!I41 -> 0 | S42: ='Outputs - Summary'!J41 -> 0 | T42: ='Outputs - Summary'!K41 -> 0 | U42: ='Outputs - Summary'!L41 -> 0 | W42: =N42-E42 -> 0 | X42: =O42-F42 -> 0 | Y42: =P42-G42 -> 0 | Z42: =Q42-H42 -> 0 | AA42: =R42-I42 -> 0 | AB42: =S42-J42 -> 0 | AC42: =T42-K42 -> 0 | AD42: =U42-L42 -> 0
B44: Dividends Payable | D44: =unit -> £ | E44: =KeyInputs!E186 -> 0 | F44: =KeyInputs!F186 -> 0 | G44: =KeyInputs!G186 -> 0 | H44: ='Outputs - P&L'!E43 -> 0 | I44: ='Outputs - P&L'!F43 -> 0 | J44: ='Outputs - P&L'!G43 -> 0 | K44: ='Outputs - P&L'!H43 -> 0 | L44: ='Outputs - P&L'!I43 -> 0 | N44: ='Outputs - Summary'!E43 -> 0 | O44: ='Outputs - Summary'!F43 -> 0 | P44: ='Outputs - Summary'!G43 -> 0 | Q44: ='Outputs - Summary'!H43 -> 0 | R44: ='Outputs - Summary'!I43 -> 0 | S44: ='Outputs - Summary'!J43 -> 0 | T44: ='Outputs - Summary'!K43 -> 0 | U44: ='Outputs - Summary'!L43 -> 0 | W44: =N44-E44 -> 0 | X44: =O44-F44 -> 0 | Y44: =P44-G44 -> 0 | Z44: =Q44-H44 -> 0 | AA44: =R44-I44 -> 0 | AB44: =S44-J44 -> 0 | AC44: =T44-K44 -> 0 | AD44: =U44-L44 -> 0
B46: Retained profit | D46: =unit -> £ | E46: =SUM(E42:E44) -> 0 | F46: =SUM(F42:F44) -> 0 | G46: =SUM(G42:G44) -> 0 | H46: =SUM(H42:H44) -> 0 | I46: =SUM(I42:I44) -> 0 | J46: =SUM(J42:J44) -> 0 | K46: =SUM(K42:K44) -> 0 | L46: =SUM(L42:L44) -> 0 | N46: ='Outputs - Summary'!E45 -> 0 | O46: ='Outputs - Summary'!F45 -> 0 | P46: ='Outputs - Summary'!G45 -> 0 | Q46: ='Outputs - Summary'!H45 -> 0 | R46: ='Outputs - Summary'!I45 -> 0 | S46: ='Outputs - Summary'!J45 -> 0 | T46: ='Outputs - Summary'!K45 -> 0 | U46: ='Outputs - Summary'!L45 -> 0 | W46: =N46-E46 -> 0 | X46: =O46-F46 -> 0 | Y46: =P46-G46 -> 0 | Z46: =Q46-H46 -> 0 | AA46: =R46-I46 -> 0 | AB46: =S46-J46 -> 0 | AC46: =T46-K46 -> 0 | AD46: =U46-L46 -> 0
B48: KPI's
B49: Revenue growth | D49: % | E49: na | F49: na | G49: =(G14-F14)/F14*100 -> #DIV/0! | H49: =(H14-G14)/G14*100 -> #DIV/0! | I49: =(I14-H14)/H14*100 -> #DIV/0! | J49: =(J14-I14)/I14*100 -> #DIV/0! | K49: =(K14-J14)/J14*100 -> #DIV/0! | L49: =(L14-K14)/K14*100 -> #DIV/0! | N49: ='Outputs - Summary'!E50 -> na | O49: ='Outputs - Summary'!F50 -> #DIV/0! | P49: ='Outputs - Summary'!G50 -> #DIV/0! | Q49: ='Outputs - Summary'!H50 -> #DIV/0! | R49: ='Outputs - Summary'!I50 -> #DIV/0! | S49: ='Outputs - Summary'!J50 -> #DIV/0! | T49: ='Outputs - Summary'!K50 -> #DIV/0! | U49: ='Outputs - Summary'!L50 -> #DIV/0! | W49: na | X49: na | Y49: =P49-G49 -> #DIV/0! | Z49: =Q49-H49 -> #DIV/0! | AA49: =R49-I49 -> #DIV/0! | AB49: =S49-J49 -> #DIV/0! | AC49: =T49-K49 -> #DIV/0! | AD49: =U49-L49 -> #DIV/0!
B50: Gross margin | D50: % | E50: =E29/E14*100 -> #DIV/0! | F50: =F29/F14*100 -> #DIV/0! | G50: =G29/G14*100 -> #DIV/0! | H50: =H29/H14*100 -> #DIV/0! | I50: =I29/I14*100 -> #DIV/0! | J50: =J29/J14*100 -> #DIV/0! | K50: =K29/K14*100 -> #DIV/0! | L50: =L29/L14*100 -> #DIV/0! | N50: ='Outputs - Summary'!E51 -> #DIV/0! | O50: ='Outputs - Summary'!F51 -> #DIV/0! | P50: ='Outputs - Summary'!G51 -> #DIV/0! | Q50: ='Outputs - Summary'!H51 -> #DIV/0! | R50: ='Outputs - Summary'!I51 -> #DIV/0! | S50: ='Outputs - Summary'!J51 -> #DIV/0! | T50: ='Outputs - Summary'!K51 -> #DIV/0! | U50: ='Outputs - Summary'!L51 -> #DIV/0! | W50: =N50-E50 -> #DIV/0! | X50: =O50-F50 -> #DIV/0! | Y50: =P50-G50 -> #DIV/0! | Z50: =Q50-H50 -> #DIV/0! | AA50: =R50-I50 -> #DIV/0! | AB50: =S50-J50 -> #DIV/0! | AC50: =T50-K50 -> #DIV/0! | AD50: =U50-L50 -> #DIV/0!
B51: Gross profit growth | D51: % | E51: na | F51: na | G51: =(G29-F29)/F29*100 -> #DIV/0! | H51: =(H29-G29)/G29*100 -> #DIV/0! | I51: =(I29-H29)/H29*100 -> #DIV/0! | J51: =(J29-I29)/I29*100 -> #DIV/0! | K51: =(K29-J29)/J29*100 -> #DIV/0! | L51: =(L29-K29)/K29*100 -> #DIV/0! | N51: ='Outputs - Summary'!E52 -> na | O51: ='Outputs - Summary'!F52 -> #DIV/0! | P51: ='Outputs - Summary'!G52 -> #DIV/0! | Q51: ='Outputs - Summary'!H52 -> #DIV/0! | R51: ='Outputs - Summary'!I52 -> #DIV/0! | S51: ='Outputs - Summary'!J52 -> #DIV/0! | T51: ='Outputs - Summary'!K52 -> #DIV/0! | U51: ='Outputs - Summary'!L52 -> #DIV/0! | W51: na | X51: na | Y51: =P51-G51 -> #DIV/0! | Z51: =Q51-H51 -> #DIV/0! | AA51: =R51-I51 -> #DIV/0! | AB51: =S51-J51 -> #DIV/0! | AC51: =T51-K51 -> #DIV/0! | AD51: =U51-L51 -> #DIV/0!
B52: Operating margin | D52: % | E52: =E34/E14*100 -> #DIV/0! | F52: =F34/F14*100 -> #DIV/0! | G52: =G34/G14*100 -> #DIV/0! | H52: =H34/H14*100 -> #DIV/0! | I52: =I34/I14*100 -> #DIV/0! | J52: =J34/J14*100 -> #DIV/0! | K52: =K34/K14*100 -> #DIV/0! | L52: =L34/L14*100 -> #DIV/0! | N52: ='Outputs - Summary'!E53 -> #DIV/0! | O52: ='Outputs - Summary'!F53 -> #DIV/0! | P52: ='Outputs - Summary'!G53 -> #DIV/0! | Q52: ='Outputs - Summary'!H53 -> #DIV/0! | R52: ='Outputs - Summary'!I53 -> #DIV/0! | S52: ='Outputs - Summary'!J53 -> #DIV/0! | T52: ='Outputs - Summary'!K53 -> #DIV/0! | U52: ='Outputs - Summary'!L53 -> #DIV/0! | W52: =N52-E52 -> #DIV/0! | X52: =O52-F52 -> #DIV/0! | Y52: =P52-G52 -> #DIV/0! | Z52: =Q52-H52 -> #DIV/0! | AA52: =R52-I52 -> #DIV/0! | AB52: =S52-J52 -> #DIV/0! | AC52: =T52-K52 -> #DIV/0! | AD52: =U52-L52 -> #DIV/0!
B53: Sales volumes | N53: ='Outputs - Summary'!E54 -> 0 | O53: ='Outputs - Summary'!F54 -> 0 | P53: ='Outputs - Summary'!G54 -> 0 | Q53: ='Outputs - Summary'!H54 -> 0 | R53: ='Outputs - Summary'!I54 -> 0 | S53: ='Outputs - Summary'!J54 -> 0 | T53: ='Outputs - Summary'!K54 -> 0 | U53: ='Outputs - Summary'!L54 -> 0 | W53: =N53-E53 -> 0 | X53: =O53-F53 -> 0 | Y53: =P53-G53 -> 0 | Z53: =Q53-H53 -> 0 | AA53: =R53-I53 -> 0 | AB53: =S53-J53 -> 0 | AC53: =T53-K53 -> 0 | AD53: =U53-L53 -> 0
B54: =KeyInputs!F21 -> Test | H54: =SUM(Revenue!E35:E37) -> 0 | I54: =SUM(Revenue!F35:F37) -> 0 | J54: =SUM(Revenue!G35:G37) -> 0 | K54: =SUM(Revenue!H35:H37) -> 0 | L54: =SUM(Revenue!I35:I37) -> 0 | N54: ='Outputs - Summary'!E55 -> 0 | O54: ='Outputs - Summary'!F55 -> 0 | P54: ='Outputs - Summary'!G55 -> 0 | Q54: ='Outputs - Summary'!H55 -> 0 | R54: ='Outputs - Summary'!I55 -> 0 | S54: ='Outputs - Summary'!J55 -> 0 | T54: ='Outputs - Summary'!K55 -> 0 | U54: ='Outputs - Summary'!L55 -> 0 | W54: =N54-E54 -> 0 | X54: =O54-F54 -> 0 | Y54: =P54-G54 -> 0 | Z54: =Q54-H54 -> 0 | AA54: =R54-I54 -> 0 | AB54: =S54-J54 -> 0 | AC54: =T54-K54 -> 0 | AD54: =U54-L54 -> 0
B55: =KeyInputs!F26 -> Insert Business Line2 | H55: =SUM(Revenue!E40:E42) -> 0 | I55: =SUM(Revenue!F40:F42) -> 0 | J55: =SUM(Revenue!G40:G42) -> 0 | K55: =SUM(Revenue!H40:H42) -> 0 | L55: =SUM(Revenue!I40:I42) -> 0 | N55: ='Outputs - Summary'!E56 -> 0 | O55: ='Outputs - Summary'!F56 -> 0 | P55: ='Outputs - Summary'!G56 -> 0 | Q55: ='Outputs - Summary'!H56 -> 0 | R55: ='Outputs - Summary'!I56 -> 0 | S55: ='Outputs - Summary'!J56 -> 0 | T55: ='Outputs - Summary'!K56 -> 0 | U55: ='Outputs - Summary'!L56 -> 0 | W55: =N55-E55 -> 0 | X55: =O55-F55 -> 0 | Y55: =P55-G55 -> 0 | Z55: =Q55-H55 -> 0 | AA55: =R55-I55 -> 0 | AB55: =S55-J55 -> 0 | AC55: =T55-K55 -> 0 | AD55: =U55-L55 -> 0
B56: =KeyInputs!F31 -> Insert Business Line3 | H56: =SUM(Revenue!E45:E47) -> 0 | I56: =SUM(Revenue!F45:F47) -> 0 | J56: =SUM(Revenue!G45:G47) -> 0 | K56: =SUM(Revenue!H45:H47) -> 0 | L56: =SUM(Revenue!I45:I47) -> 0 | N56: ='Outputs - Summary'!E57 -> 0 | O56: ='Outputs - Summary'!F57 -> 0 | P56: ='Outputs - Summary'!G57 -> 0 | Q56: ='Outputs - Summary'!H57 -> 0 | R56: ='Outputs - Summary'!I57 -> 0 | S56: ='Outputs - Summary'!J57 -> 0 | T56: ='Outputs - Summary'!K57 -> 0 | U56: ='Outputs - Summary'!L57 -> 0 | W56: =N56-E56 -> 0 | X56: =O56-F56 -> 0 | Y56: =P56-G56 -> 0 | Z56: =Q56-H56 -> 0 | AA56: =R56-I56 -> 0 | AB56: =S56-J56 -> 0 | AC56: =T56-K56 -> 0 | AD56: =U56-L56 -> 0
A59: =Header1 -> 2 | B59: Balance Sheet
B61: Fixed assets | D61: =unit -> £ | E61: =SUM(E62:E65) -> 0 | F61: =SUM(F62:F65) -> 0 | G61: =SUM(G62:G65) -> 0 | H61: =SUM(H62:H65) -> 0 | I61: =SUM(I62:I65) -> 0 | J61: =SUM(J62:J65) -> 0 | K61: =SUM(K62:K65) -> 0 | L61: =SUM(L62:L65) -> 0 | N61: ='Outputs - Summary'!E62 -> 0 | O61: ='Outputs - Summary'!F62 -> 0 | P61: ='Outputs - Summary'!G62 -> 0 | Q61: ='Outputs - Summary'!H62 -> 0 | R61: ='Outputs - Summary'!I62 -> 0 | S61: ='Outputs - Summary'!J62 -> 0 | T61: ='Outputs - Summary'!K62 -> 0 | U61: ='Outputs - Summary'!L62 -> 0 | W61: =N61-E61 -> 0 | X61: =O61-F61 -> 0 | Y61: =P61-G61 -> 0 | Z61: =Q61-H61 -> 0 | AA61: =R61-I61 -> 0 | AB61: =S61-J61 -> 0 | AC61: =T61-K61 -> 0 | AD61: =U61-L61 -> 0 | AG61: =SUM(AG62:AG66) -> 0 | AH61: =SUM(AH62:AH66) -> 0 | AI61: =SUM(AI62:AI66) -> 0 | AJ61: =SUM(AJ62:AJ66) -> 0 | AK61: =SUM(AK62:AK66) -> 0 | AL61: =SUM(AL62:AL66) -> 0 | AM61: =SUM(AM62:AM66) -> 0 | AN61: =SUM(AN62:AN66) -> 0 | ... CF61: =SUM(CF62:CF66) -> 0
B62: =KeyInputs!C112 -> ICT equipement | D62: =unit -> £ | E62: =KeyInputs!E112 -> 0 | F62: =KeyInputs!F112 -> 0 | G62: =KeyInputs!G112 -> 0 | H62: ='Outputs - BalanceSheet'!E13 -> 0 | I62: ='Outputs - BalanceSheet'!F13 -> 0 | J62: ='Outputs - BalanceSheet'!G13 -> 0 | K62: ='Outputs - BalanceSheet'!H13 -> 0 | L62: ='Outputs - BalanceSheet'!I13 -> 0 | N62: ='Outputs - Summary'!E63 -> 0 | O62: ='Outputs - Summary'!F63 -> 0 | P62: ='Outputs - Summary'!G63 -> 0 | Q62: ='Outputs - Summary'!H63 -> 0 | R62: ='Outputs - Summary'!I63 -> 0 | S62: ='Outputs - Summary'!J63 -> 0 | T62: ='Outputs - Summary'!K63 -> 0 | U62: ='Outputs - Summary'!L63 -> 0 | W62: =N62-E62 -> 0 | X62: =O62-F62 -> 0 | Y62: =P62-G62 -> 0 | Z62: =Q62-H62 -> 0 | AA62: =R62-I62 -> 0 | AB62: =S62-J62 -> 0 | AC62: =T62-K62 -> 0 | AD62: =U62-L62 -> 0 | AG62: =Capex!S73 -> 0 | AH62: =Capex!T73 -> 0 | AI62: =Capex!U73 -> 0 | AJ62: =Capex!V73 -> 0 | AK62: =Capex!W73 -> 0 | AL62: =Capex!X73 -> 0 | AM62: =Capex!Y73 -> 0 | AN62: =Capex!Z73 -> 0 | ... CF62: =Capex!BR73 -> 0
B63: =KeyInputs!C113 -> F&F | D63: =unit -> £ | E63: =KeyInputs!E113 -> 0 | F63: =KeyInputs!F113 -> 0 | G63: =KeyInputs!G113 -> 0 | H63: ='Outputs - BalanceSheet'!E14 -> 0 | I63: ='Outputs - BalanceSheet'!F14 -> 0 | J63: ='Outputs - BalanceSheet'!G14 -> 0 | K63: ='Outputs - BalanceSheet'!H14 -> 0 | L63: ='Outputs - BalanceSheet'!I14 -> 0 | N63: ='Outputs - Summary'!E64 -> 0 | O63: ='Outputs - Summary'!F64 -> 0 | P63: ='Outputs - Summary'!G64 -> 0 | Q63: ='Outputs - Summary'!H64 -> 0 | R63: ='Outputs - Summary'!I64 -> 0 | S63: ='Outputs - Summary'!J64 -> 0 | T63: ='Outputs - Summary'!K64 -> 0 | U63: ='Outputs - Summary'!L64 -> 0 | W63: =N63-E63 -> 0 | X63: =O63-F63 -> 0 | Y63: =P63-G63 -> 0 | Z63: =Q63-H63 -> 0 | AA63: =R63-I63 -> 0 | AB63: =S63-J63 -> 0 | AC63: =T63-K63 -> 0 | AD63: =U63-L63 -> 0 | AG63: =Capex!S83 -> 0 | AH63: =Capex!T83 -> 0 | AI63: =Capex!U83 -> 0 | AJ63: =Capex!V83 -> 0 | AK63: =Capex!W83 -> 0 | AL63: =Capex!X83 -> 0 | AM63: =Capex!Y83 -> 0 | AN63: =Capex!Z83 -> 0 | ... CF63: =Capex!BR83 -> 0
B64: =KeyInputs!C114 -> Property | D64: =unit -> £ | E64: =KeyInputs!E114 -> 0 | F64: =KeyInputs!F114 -> 0 | G64: =KeyInputs!G114 -> 0 | H64: ='Outputs - BalanceSheet'!E15 -> 0 | I64: ='Outputs - BalanceSheet'!F15 -> 0 | J64: ='Outputs - BalanceSheet'!G15 -> 0 | K64: ='Outputs - BalanceSheet'!H15 -> 0 | L64: ='Outputs - BalanceSheet'!I15 -> 0 | N64: ='Outputs - Summary'!E65 -> 0 | O64: ='Outputs - Summary'!F65 -> 0 | P64: ='Outputs - Summary'!G65 -> 0 | Q64: ='Outputs - Summary'!H65 -> 0 | R64: ='Outputs - Summary'!I65 -> 0 | S64: ='Outputs - Summary'!J65 -> 0 | T64: ='Outputs - Summary'!K65 -> 0 | U64: ='Outputs - Summary'!L65 -> 0 | W64: =N64-E64 -> 0 | X64: =O64-F64 -> 0 | Y64: =P64-G64 -> 0 | Z64: =Q64-H64 -> 0 | AA64: =R64-I64 -> 0 | AB64: =S64-J64 -> 0 | AC64: =T64-K64 -> 0 | AD64: =U64-L64 -> 0 | AG64: =Capex!S93 -> 0 | AH64: =Capex!T93 -> 0 | AI64: =Capex!U93 -> 0 | AJ64: =Capex!V93 -> 0 | AK64: =Capex!W93 -> 0 | AL64: =Capex!X93 -> 0 | AM64: =Capex!Y93 -> 0 | AN64: =Capex!Z93 -> 0 | ... CF64: =Capex!BR93 -> 0
B65: =KeyInputs!C115 -> Vehicles | D65: =unit -> £ | E65: =KeyInputs!E115 -> 0 | F65: =KeyInputs!F115 -> 0 | G65: =KeyInputs!G115 -> 0 | H65: ='Outputs - BalanceSheet'!E16 -> 0 | I65: ='Outputs - BalanceSheet'!F16 -> 0 | J65: ='Outputs - BalanceSheet'!G16 -> 0 | K65: ='Outputs - BalanceSheet'!H16 -> 0 | L65: ='Outputs - BalanceSheet'!I16 -> 0 | N65: ='Outputs - Summary'!E66 -> 0 | O65: ='Outputs - Summary'!F66 -> 0 | P65: ='Outputs - Summary'!G66 -> 0 | Q65: ='Outputs - Summary'!H66 -> 0 | R65: ='Outputs - Summary'!I66 -> 0 | S65: ='Outputs - Summary'!J66 -> 0 | T65: ='Outputs - Summary'!K66 -> 0 | U65: ='Outputs - Summary'!L66 -> 0 | W65: =N65-E65 -> 0 | X65: =O65-F65 -> 0 | Y65: =P65-G65 -> 0 | Z65: =Q65-H65 -> 0 | AA65: =R65-I65 -> 0 | AB65: =S65-J65 -> 0 | AC65: =T65-K65 -> 0 | AD65: =U65-L65 -> 0 | AG65: =Capex!S103 -> 0 | AH65: =Capex!T103 -> 0 | AI65: =Capex!U103 -> 0 | AJ65: =Capex!V103 -> 0 | AK65: =Capex!W103 -> 0 | AL65: =Capex!X103 -> 0 | AM65: =Capex!Y103 -> 0 | AN65: =Capex!Z103 -> 0 | ... CF65: =Capex!BR103 -> 0
B66: =KeyInputs!C116 -> n/a | D66: =unit -> £ | E66: =KeyInputs!E116 -> 0 | F66: =KeyInputs!F116 -> 0 | G66: =KeyInputs!G116 -> 0 | H66: ='Outputs - BalanceSheet'!E17 -> 0 | I66: ='Outputs - BalanceSheet'!F17 -> 0 | J66: ='Outputs - BalanceSheet'!G17 -> 0 | K66: ='Outputs - BalanceSheet'!H17 -> 0 | L66: ='Outputs - BalanceSheet'!I17 -> 0 | N66: ='Outputs - Summary'!E67 -> 0 | O66: ='Outputs - Summary'!F67 -> 0 | P66: ='Outputs - Summary'!G67 -> 0 | Q66: ='Outputs - Summary'!H67 -> 0 | R66: ='Outputs - Summary'!I67 -> 0 | S66: ='Outputs - Summary'!J67 -> 0 | T66: ='Outputs - Summary'!K67 -> 0 | U66: ='Outputs - Summary'!L67 -> 0 | W66: =N66-E66 -> 0 | X66: =O66-F66 -> 0 | Y66: =P66-G66 -> 0 | Z66: =Q66-H66 -> 0 | AA66: =R66-I66 -> 0 | AB66: =S66-J66 -> 0 | AC66: =T66-K66 -> 0 | AD66: =U66-L66 -> 0 | AG66: =Capex!S113 -> 0 | AH66: =Capex!T113 -> 0 | AI66: =Capex!U113 -> 0 | AJ66: =Capex!V113 -> 0 | AK66: =Capex!W113 -> 0 | AL66: =Capex!X113 -> 0 | AM66: =Capex!Y113 -> 0 | AN66: =Capex!Z113 -> 0 | ... CF66: =Capex!BR113 -> 0
N67: ='Outputs - Summary'!E68 -> 0 | O67: ='Outputs - Summary'!F68 -> 0 | P67: ='Outputs - Summary'!G68 -> 0 | Q67: ='Outputs - Summary'!H68 -> 0 | R67: ='Outputs - Summary'!I68 -> 0 | S67: ='Outputs - Summary'!J68 -> 0 | T67: ='Outputs - Summary'!K68 -> 0 | U67: ='Outputs - Summary'!L68 -> 0 | W67: =N67-E67 -> 0 | X67: =O67-F67 -> 0 | Y67: =P67-G67 -> 0 | Z67: =Q67-H67 -> 0 | AA67: =R67-I67 -> 0 | AB67: =S67-J67 -> 0 | AC67: =T67-K67 -> 0 | AD67: =U67-L67 -> 0
B68: Trade debtors | D68: =unit -> £ | E68: =SUM(E69:E71) -> 0 | F68: =SUM(F69:F71) -> 0 | G68: =SUM(G69:G71) -> 0 | H68: =SUM(H69:H71) -> 0 | I68: =SUM(I69:I71) -> 0 | J68: =SUM(J69:J71) -> 0 | K68: =SUM(K69:K71) -> 0 | L68: =SUM(L69:L71) -> 0 | N68: ='Outputs - Summary'!E69 -> 0 | O68: ='Outputs - Summary'!F69 -> 0 | P68: ='Outputs - Summary'!G69 -> 0 | Q68: ='Outputs - Summary'!H69 -> 0 | R68: ='Outputs - Summary'!I69 -> 0 | S68: ='Outputs - Summary'!J69 -> 0 | T68: ='Outputs - Summary'!K69 -> 0 | U68: ='Outputs - Summary'!L69 -> 0 | W68: =N68-E68 -> 0 | X68: =O68-F68 -> 0 | Y68: =P68-G68 -> 0 | Z68: =Q68-H68 -> 0 | AA68: =R68-I68 -> 0 | AB68: =S68-J68 -> 0 | AC68: =T68-K68 -> 0 | AD68: =U68-L68 -> 0 | AG68: =SUM(AG69:AG71) -> 0 | AH68: =SUM(AH69:AH71) -> 0 | AI68: =SUM(AI69:AI71) -> 0 | AJ68: =SUM(AJ69:AJ71) -> 0 | AK68: =SUM(AK69:AK71) -> 0 | AL68: =SUM(AL69:AL71) -> 0 | AM68: =SUM(AM69:AM71) -> 0 | AN68: =SUM(AN69:AN71) -> 0 | ... CF68: =SUM(CF69:CF71) -> 0
B69: =KeyInputs!C119 -> Test | D69: =unit -> £ | E69: =KeyInputs!E119 -> 0 | F69: =KeyInputs!F119 -> 0 | G69: =KeyInputs!G119 -> 0 | H69: ='Outputs - BalanceSheet'!E20 -> 0 | I69: ='Outputs - BalanceSheet'!F20 -> 0 | J69: ='Outputs - BalanceSheet'!G20 -> 0 | K69: ='Outputs - BalanceSheet'!H20 -> 0 | L69: ='Outputs - BalanceSheet'!I20 -> 0 | N69: ='Outputs - Summary'!E70 -> 0 | O69: ='Outputs - Summary'!F70 -> 0 | P69: ='Outputs - Summary'!G70 -> 0 | Q69: ='Outputs - Summary'!H70 -> 0 | R69: ='Outputs - Summary'!I70 -> 0 | S69: ='Outputs - Summary'!J70 -> 0 | T69: ='Outputs - Summary'!K70 -> 0 | U69: ='Outputs - Summary'!L70 -> 0 | W69: =N69-E69 -> 0 | X69: =O69-F69 -> 0 | Y69: =P69-G69 -> 0 | Z69: =Q69-H69 -> 0 | AA69: =R69-I69 -> 0 | AB69: =S69-J69 -> 0 | AC69: =T69-K69 -> 0 | AD69: =U69-L69 -> 0 | AG69: =WorkingCapital!S57 -> 0 | AH69: =WorkingCapital!T57 -> 0 | AI69: =WorkingCapital!U57 -> 0 | AJ69: =WorkingCapital!V57 -> 0 | AK69: =WorkingCapital!W57 -> 0 | AL69: =WorkingCapital!X57 -> 0 | AM69: =WorkingCapital!Y57 -> 0 | AN69: =WorkingCapital!Z57 -> 0 | ... CF69: =WorkingCapital!BR57 -> 0
B70: =KeyInputs!C120 -> Insert Business Line2 | D70: =unit -> £ | E70: =KeyInputs!E120 -> 0 | F70: =KeyInputs!F120 -> 0 | G70: =KeyInputs!G120 -> 0 | H70: ='Outputs - BalanceSheet'!E21 -> 0 | I70: ='Outputs - BalanceSheet'!F21 -> 0 | J70: ='Outputs - BalanceSheet'!G21 -> 0 | K70: ='Outputs - BalanceSheet'!H21 -> 0 | L70: ='Outputs - BalanceSheet'!I21 -> 0 | N70: ='Outputs - Summary'!E71 -> 0 | O70: ='Outputs - Summary'!F71 -> 0 | P70: ='Outputs - Summary'!G71 -> 0 | Q70: ='Outputs - Summary'!H71 -> 0 | R70: ='Outputs - Summary'!I71 -> 0 | S70: ='Outputs - Summary'!J71 -> 0 | T70: ='Outputs - Summary'!K71 -> 0 | U70: ='Outputs - Summary'!L71 -> 0 | W70: =N70-E70 -> 0 | X70: =O70-F70 -> 0 | Y70: =P70-G70 -> 0 | Z70: =Q70-H70 -> 0 | AA70: =R70-I70 -> 0 | AB70: =S70-J70 -> 0 | AC70: =T70-K70 -> 0 | AD70: =U70-L70 -> 0 | AG70: =WorkingCapital!S68 -> 0 | AH70: =WorkingCapital!T68 -> 0 | AI70: =WorkingCapital!U68 -> 0 | AJ70: =WorkingCapital!V68 -> 0 | AK70: =WorkingCapital!W68 -> 0 | AL70: =WorkingCapital!X68 -> 0 | AM70: =WorkingCapital!Y68 -> 0 | AN70: =WorkingCapital!Z68 -> 0 | ... CF70: =WorkingCapital!BR68 -> 0
B71: =KeyInputs!C121 -> Insert Business Line3 | D71: =unit -> £ | E71: =KeyInputs!E121 -> 0 | F71: =KeyInputs!F121 -> 0 | G71: =KeyInputs!G121 -> 0 | H71: ='Outputs - BalanceSheet'!E22 -> 0 | I71: ='Outputs - BalanceSheet'!F22 -> 0 | J71: ='Outputs - BalanceSheet'!G22 -> 0 | K71: ='Outputs - BalanceSheet'!H22 -> 0 | L71: ='Outputs - BalanceSheet'!I22 -> 0 | N71: ='Outputs - Summary'!E72 -> 0 | O71: ='Outputs - Summary'!F72 -> 0 | P71: ='Outputs - Summary'!G72 -> 0 | Q71: ='Outputs - Summary'!H72 -> 0 | R71: ='Outputs - Summary'!I72 -> 0 | S71: ='Outputs - Summary'!J72 -> 0 | T71: ='Outputs - Summary'!K72 -> 0 | U71: ='Outputs - Summary'!L72 -> 0 | W71: =N71-E71 -> 0 | X71: =O71-F71 -> 0 | Y71: =P71-G71 -> 0 | Z71: =Q71-H71 -> 0 | AA71: =R71-I71 -> 0 | AB71: =S71-J71 -> 0 | AC71: =T71-K71 -> 0 | AD71: =U71-L71 -> 0 | AG71: =WorkingCapital!S79 -> 0 | AH71: =WorkingCapital!T79 -> 0 | AI71: =WorkingCapital!U79 -> 0 | AJ71: =WorkingCapital!V79 -> 0 | AK71: =WorkingCapital!W79 -> 0 | AL71: =WorkingCapital!X79 -> 0 | AM71: =WorkingCapital!Y79 -> 0 | AN71: =WorkingCapital!Z79 -> 0 | ... CF71: =WorkingCapital!BR79 -> 0
N72: ='Outputs - Summary'!E73 -> 0 | O72: ='Outputs - Summary'!F73 -> 0 | P72: ='Outputs - Summary'!G73 -> 0 | Q72: ='Outputs - Summary'!H73 -> 0 | R72: ='Outputs - Summary'!I73 -> 0 | S72: ='Outputs - Summary'!J73 -> 0 | T72: ='Outputs - Summary'!K73 -> 0 | U72: ='Outputs - Summary'!L73 -> 0 | W72: =N72-E72 -> 0 | X72: =O72-F72 -> 0 | Y72: =P72-G72 -> 0 | Z72: =Q72-H72 -> 0 | AA72: =R72-I72 -> 0 | AB72: =S72-J72 -> 0 | AC72: =T72-K72 -> 0 | AD72: =U72-L72 -> 0
B73: Stocks | D73: =unit -> £ | E73: =SUM(E74:E76) -> 0 | F73: =SUM(F74:F76) -> 0 | G73: =SUM(G74:G76) -> 0 | H73: =SUM(H74:H76) -> 0 | I73: =SUM(I74:I76) -> 0 | J73: =SUM(J74:J76) -> 0 | K73: =SUM(K74:K76) -> 0 | L73: =SUM(L74:L76) -> 0 | N73: ='Outputs - Summary'!E74 -> 0 | O73: ='Outputs - Summary'!F74 -> 0 | P73: ='Outputs - Summary'!G74 -> 0 | Q73: ='Outputs - Summary'!H74 -> 0 | R73: ='Outputs - Summary'!I74 -> 0 | S73: ='Outputs - Summary'!J74 -> 0 | T73: ='Outputs - Summary'!K74 -> 0 | U73: ='Outputs - Summary'!L74 -> 0 | W73: =N73-E73 -> 0 | X73: =O73-F73 -> 0 | Y73: =P73-G73 -> 0 | Z73: =Q73-H73 -> 0 | AA73: =R73-I73 -> 0 | AB73: =S73-J73 -> 0 | AC73: =T73-K73 -> 0 | AD73: =U73-L73 -> 0 | AG73: =SUM(AG74:AG76) -> 0 | AH73: =SUM(AH74:AH76) -> 0 | AI73: =SUM(AI74:AI76) -> 0 | AJ73: =SUM(AJ74:AJ76) -> 0 | AK73: =SUM(AK74:AK76) -> 0 | AL73: =SUM(AL74:AL76) -> 0 | AM73: =SUM(AM74:AM76) -> 0 | AN73: =SUM(AN74:AN76) -> 0 | ... CF73: =SUM(CF74:CF76) -> 0
B74: =B69 -> Test | D74: =unit -> £ | E74: =KeyInputs!E124 -> 0 | F74: =KeyInputs!F124 -> 0 | G74: =KeyInputs!G124 -> 0 | H74: ='Outputs - BalanceSheet'!E25 -> 0 | I74: ='Outputs - BalanceSheet'!F25 -> 0 | J74: ='Outputs - BalanceSheet'!G25 -> 0 | K74: ='Outputs - BalanceSheet'!H25 -> 0 | L74: ='Outputs - BalanceSheet'!I25 -> 0 | N74: ='Outputs - Summary'!E75 -> 0 | O74: ='Outputs - Summary'!F75 -> 0 | P74: ='Outputs - Summary'!G75 -> 0 | Q74: ='Outputs - Summary'!H75 -> 0 | R74: ='Outputs - Summary'!I75 -> 0 | S74: ='Outputs - Summary'!J75 -> 0 | T74: ='Outputs - Summary'!K75 -> 0 | U74: ='Outputs - Summary'!L75 -> 0 | W74: =N74-E74 -> 0 | X74: =O74-F74 -> 0 | Y74: =P74-G74 -> 0 | Z74: =Q74-H74 -> 0 | AA74: =R74-I74 -> 0 | AB74: =S74-J74 -> 0 | AC74: =T74-K74 -> 0 | AD74: =U74-L74 -> 0 | AG74: =WorkingCapital!S94 -> 0 | AH74: =WorkingCapital!T94 -> 0 | AI74: =WorkingCapital!U94 -> 0 | AJ74: =WorkingCapital!V94 -> 0 | AK74: =WorkingCapital!W94 -> 0 | AL74: =WorkingCapital!X94 -> 0 | AM74: =WorkingCapital!Y94 -> 0 | AN74: =WorkingCapital!Z94 -> 0 | ... CF74: =WorkingCapital!BR94 -> 0
B75: =B70 -> Insert Business Line2 | D75: =unit -> £ | E75: =KeyInputs!E125 -> 0 | F75: =KeyInputs!F125 -> 0 | G75: =KeyInputs!G125 -> 0 | H75: ='Outputs - BalanceSheet'!E26 -> 0 | I75: ='Outputs - BalanceSheet'!F26 -> 0 | J75: ='Outputs - BalanceSheet'!G26 -> 0 | K75: ='Outputs - BalanceSheet'!H26 -> 0 | L75: ='Outputs - BalanceSheet'!I26 -> 0 | N75: ='Outputs - Summary'!E76 -> 0 | O75: ='Outputs - Summary'!F76 -> 0 | P75: ='Outputs - Summary'!G76 -> 0 | Q75: ='Outputs - Summary'!H76 -> 0 | R75: ='Outputs - Summary'!I76 -> 0 | S75: ='Outputs - Summary'!J76 -> 0 | T75: ='Outputs - Summary'!K76 -> 0 | U75: ='Outputs - Summary'!L76 -> 0 | W75: =N75-E75 -> 0 | X75: =O75-F75 -> 0 | Y75: =P75-G75 -> 0 | Z75: =Q75-H75 -> 0 | AA75: =R75-I75 -> 0 | AB75: =S75-J75 -> 0 | AC75: =T75-K75 -> 0 | AD75: =U75-L75 -> 0 | AG75: =WorkingCapital!S112 -> 0 | AH75: =WorkingCapital!T112 -> 0 | AI75: =WorkingCapital!U112 -> 0 | AJ75: =WorkingCapital!V112 -> 0 | AK75: =WorkingCapital!W112 -> 0 | AL75: =WorkingCapital!X112 -> 0 | AM75: =WorkingCapital!Y112 -> 0 | AN75: =WorkingCapital!Z112 -> 0 | ... CF75: =WorkingCapital!BR112 -> 0
B76: =B71 -> Insert Business Line3 | D76: =unit -> £ | E76: =KeyInputs!E126 -> 0 | F76: =KeyInputs!F126 -> 0 | G76: =KeyInputs!G126 -> 0 | H76: ='Outputs - BalanceSheet'!E27 -> 0 | I76: ='Outputs - BalanceSheet'!F27 -> 0 | J76: ='Outputs - BalanceSheet'!G27 -> 0 | K76: ='Outputs - BalanceSheet'!H27 -> 0 | L76: ='Outputs - BalanceSheet'!I27 -> 0 | N76: ='Outputs - Summary'!E77 -> 0 | O76: ='Outputs - Summary'!F77 -> 0 | P76: ='Outputs - Summary'!G77 -> 0 | Q76: ='Outputs - Summary'!H77 -> 0 | R76: ='Outputs - Summary'!I77 -> 0 | S76: ='Outputs - Summary'!J77 -> 0 | T76: ='Outputs - Summary'!K77 -> 0 | U76: ='Outputs - Summary'!L77 -> 0 | W76: =N76-E76 -> 0 | X76: =O76-F76 -> 0 | Y76: =P76-G76 -> 0 | Z76: =Q76-H76 -> 0 | AA76: =R76-I76 -> 0 | AB76: =S76-J76 -> 0 | AC76: =T76-K76 -> 0 | AD76: =U76-L76 -> 0 | AG76: =WorkingCapital!S123 -> 0 | AH76: =WorkingCapital!T123 -> 0 | AI76: =WorkingCapital!U123 -> 0 | AJ76: =WorkingCapital!V123 -> 0 | AK76: =WorkingCapital!W123 -> 0 | AL76: =WorkingCapital!X123 -> 0 | AM76: =WorkingCapital!Y123 -> 0 | AN76: =WorkingCapital!Z123 -> 0 | ... CF76: =WorkingCapital!BR123 -> 0
N77: ='Outputs - Summary'!E78 -> 0 | O77: ='Outputs - Summary'!F78 -> 0 | P77: ='Outputs - Summary'!G78 -> 0 | Q77: ='Outputs - Summary'!H78 -> 0 | R77: ='Outputs - Summary'!I78 -> 0 | S77: ='Outputs - Summary'!J78 -> 0 | T77: ='Outputs - Summary'!K78 -> 0 | U77: ='Outputs - Summary'!L78 -> 0 | W77: =N77-E77 -> 0 | X77: =O77-F77 -> 0 | Y77: =P77-G77 -> 0 | Z77: =Q77-H77 -> 0 | AA77: =R77-I77 -> 0 | AB77: =S77-J77 -> 0 | AC77: =T77-K77 -> 0 | AD77: =U77-L77 -> 0
B78: Cash at bank | D78: =unit -> £ | E78: =KeyInputs!E128 -> 0 | F78: =KeyInputs!F128 -> 0 | G78: =KeyInputs!G128 -> 0 | H78: ='Outputs - BalanceSheet'!E29 -> 0 | I78: ='Outputs - BalanceSheet'!F29 -> 0 | J78: ='Outputs - BalanceSheet'!G29 -> 0 | K78: ='Outputs - BalanceSheet'!H29 -> 0 | L78: ='Outputs - BalanceSheet'!I29 -> 0 | N78: ='Outputs - Summary'!E79 -> 0 | O78: ='Outputs - Summary'!F79 -> 0 | P78: ='Outputs - Summary'!G79 -> 0 | Q78: ='Outputs - Summary'!H79 -> 0 | R78: ='Outputs - Summary'!I79 -> 0 | S78: ='Outputs - Summary'!J79 -> 0 | T78: ='Outputs - Summary'!K79 -> 0 | U78: ='Outputs - Summary'!L79 -> 0 | W78: =N78-E78 -> 0 | X78: =O78-F78 -> 0 | Y78: =P78-G78 -> 0 | Z78: =Q78-H78 -> 0 | AA78: =R78-I78 -> 0 | AB78: =S78-J78 -> 0 | AC78: =T78-K78 -> 0 | AD78: =U78-L78 -> 0 | AG78: =MAX('Outputs - Cashflow'!S$39,0) -> 0 | AH78: =MAX('Outputs - Cashflow'!T$39,0) -> 0 | AI78: =MAX('Outputs - Cashflow'!U$39,0) -> 0 | AJ78: =MAX('Outputs - Cashflow'!V$39,0) -> 0 | AK78: =MAX('Outputs - Cashflow'!W$39,0) -> 0 | AL78: =MAX('Outputs - Cashflow'!X$39,0) -> 0 | AM78: =MAX('Outputs - Cashflow'!Y$39,0) -> 0 | AN78: =MAX('Outputs - Cashflow'!Z$39,0) -> 0 | ... CF78: =MAX('Outputs - Cashflow'!BR$39,0) -> 0
B79: Total assets | E79: =SUM(E61:E78) -> 0 | F79: =SUM(F61:F78) -> 0 | G79: =SUM(G61:G78) -> 0 | H79: =SUM(H61:H78) -> 0 | I79: =SUM(I61:I78) -> 0 | J79: =SUM(J61:J78) -> 0 | K79: =SUM(K61:K78) -> 0 | L79: =SUM(L61:L78) -> 0 | N79: ='Outputs - Summary'!E80 -> 0 | O79: ='Outputs - Summary'!F80 -> 0 | P79: ='Outputs - Summary'!G80 -> 0 | Q79: ='Outputs - Summary'!H80 -> 0 | R79: ='Outputs - Summary'!I80 -> 0 | S79: ='Outputs - Summary'!J80 -> 0 | T79: ='Outputs - Summary'!K80 -> 0 | U79: ='Outputs - Summary'!L80 -> 0 | W79: =N79-E79 -> 0 | X79: =O79-F79 -> 0 | Y79: =P79-G79 -> 0 | Z79: =Q79-H79 -> 0 | AA79: =R79-I79 -> 0 | AB79: =S79-J79 -> 0 | AC79: =T79-K79 -> 0 | AD79: =U79-L79 -> 0
B81: Overdraft | D81: =unit -> £ | E81: =KeyInputs!E130 -> 0 | F81: =KeyInputs!F130 -> 0 | G81: =KeyInputs!G130 -> 0 | H81: ='Outputs - BalanceSheet'!E31 -> 0 | I81: ='Outputs - BalanceSheet'!F31 -> 0 | J81: ='Outputs - BalanceSheet'!G31 -> 0 | K81: ='Outputs - BalanceSheet'!H31 -> 0 | L81: ='Outputs - BalanceSheet'!I31 -> 0 | N81: ='Outputs - Summary'!E82 -> 0 | O81: ='Outputs - Summary'!F82 -> 0 | P81: ='Outputs - Summary'!G82 -> 0 | Q81: ='Outputs - Summary'!H82 -> 0 | R81: ='Outputs - Summary'!I82 -> 0 | S81: ='Outputs - Summary'!J82 -> 0 | T81: ='Outputs - Summary'!K82 -> 0 | U81: ='Outputs - Summary'!L82 -> 0 | W81: =N81-E81 -> 0 | X81: =O81-F81 -> 0 | Y81: =P81-G81 -> 0 | Z81: =Q81-H81 -> 0 | AA81: =R81-I81 -> 0 | AB81: =S81-J81 -> 0 | AC81: =T81-K81 -> 0 | AD81: =U81-L81 -> 0 | AG81: =MIN('Outputs - Cashflow'!S$39,0) -> 0 | AH81: =MIN('Outputs - Cashflow'!T$39,0) -> 0 | AI81: =MIN('Outputs - Cashflow'!U$39,0) -> 0 | AJ81: =MIN('Outputs - Cashflow'!V$39,0) -> 0 | AK81: =MIN('Outputs - Cashflow'!W$39,0) -> 0 | AL81: =MIN('Outputs - Cashflow'!X$39,0) -> 0 | AM81: =MIN('Outputs - Cashflow'!Y$39,0) -> 0 | AN81: =MIN('Outputs - Cashflow'!Z$39,0) -> 0 | ... CF81: =MIN('Outputs - Cashflow'!BR$39,0) -> 0
B82: Trade creditors | D82: =unit -> £ | E82: =KeyInputs!E131 -> 0 | F82: =KeyInputs!F131 -> 0 | G82: =KeyInputs!G131 -> 0 | H82: ='Outputs - BalanceSheet'!E32 -> 0 | I82: ='Outputs - BalanceSheet'!F32 -> 0 | J82: ='Outputs - BalanceSheet'!G32 -> 0 | K82: ='Outputs - BalanceSheet'!H32 -> 0 | L82: ='Outputs - BalanceSheet'!I32 -> 0 | N82: ='Outputs - Summary'!E83 -> 0 | O82: ='Outputs - Summary'!F83 -> 0 | P82: ='Outputs - Summary'!G83 -> 0 | Q82: ='Outputs - Summary'!H83 -> 0 | R82: ='Outputs - Summary'!I83 -> 0 | S82: ='Outputs - Summary'!J83 -> 0 | T82: ='Outputs - Summary'!K83 -> 0 | U82: ='Outputs - Summary'!L83 -> 0 | W82: =N82-E82 -> 0 | X82: =O82-F82 -> 0 | Y82: =P82-G82 -> 0 | Z82: =Q82-H82 -> 0 | AA82: =R82-I82 -> 0 | AB82: =S82-J82 -> 0 | AC82: =T82-K82 -> 0 | AD82: =U82-L82 -> 0 | AG82: =WorkingCapital!S$91 -> 0 | AH82: =WorkingCapital!T$91 -> 0 | AI82: =WorkingCapital!U$91 -> 0 | AJ82: =WorkingCapital!V$91 -> 0 | AK82: =WorkingCapital!W$91 -> 0 | AL82: =WorkingCapital!X$91 -> 0 | AM82: =WorkingCapital!Y$91 -> 0 | AN82: =WorkingCapital!Z$91 -> 0 | ... CF82: =WorkingCapital!BR$91 -> 0
B83: VAT | D83: =unit -> £ | E83: =KeyInputs!E132 -> 0 | F83: =KeyInputs!F132 -> 0 | G83: =KeyInputs!G132 -> 0 | H83: ='Outputs - BalanceSheet'!E33 -> 0 | I83: ='Outputs - BalanceSheet'!F33 -> 0 | J83: ='Outputs - BalanceSheet'!G33 -> 0 | K83: ='Outputs - BalanceSheet'!H33 -> 0 | L83: ='Outputs - BalanceSheet'!I33 -> 0 | N83: ='Outputs - Summary'!E84 -> 0 | O83: ='Outputs - Summary'!F84 -> 0 | P83: ='Outputs - Summary'!G84 -> 0 | Q83: ='Outputs - Summary'!H84 -> 0 | R83: ='Outputs - Summary'!I84 -> 0 | S83: ='Outputs - Summary'!J84 -> 0 | T83: ='Outputs - Summary'!K84 -> 0 | U83: ='Outputs - Summary'!L84 -> 0 | W83: =N83-E83 -> 0 | X83: =O83-F83 -> 0 | Y83: =P83-G83 -> 0 | Z83: =Q83-H83 -> 0 | AA83: =R83-I83 -> 0 | AB83: =S83-J83 -> 0 | AC83: =T83-K83 -> 0 | AD83: =U83-L83 -> 0 | AG83: =WorkingCapital!S$91 -> 0 | AH83: =WorkingCapital!T$91 -> 0 | AI83: =WorkingCapital!U$91 -> 0 | AJ83: =WorkingCapital!V$91 -> 0 | AK83: =WorkingCapital!W$91 -> 0 | AL83: =WorkingCapital!X$91 -> 0 | AM83: =WorkingCapital!Y$91 -> 0 | AN83: =WorkingCapital!Z$91 -> 0 | ... CF83: =WorkingCapital!BR$91 -> 0
B84: Interest on debt payable | D84: =unit -> £ | E84: =KeyInputs!E133 -> 0 | F84: =KeyInputs!F133 -> 0 | G84: =KeyInputs!G133 -> 0 | H84: ='Outputs - BalanceSheet'!E34 -> 0 | I84: ='Outputs - BalanceSheet'!F34 -> 0 | J84: ='Outputs - BalanceSheet'!G34 -> 0 | K84: ='Outputs - BalanceSheet'!H34 -> 0 | L84: ='Outputs - BalanceSheet'!I34 -> 0 | N84: ='Outputs - Summary'!E85 -> 0 | O84: ='Outputs - Summary'!F85 -> 0 | P84: ='Outputs - Summary'!G85 -> 0 | Q84: ='Outputs - Summary'!H85 -> 0 | R84: ='Outputs - Summary'!I85 -> 0 | S84: ='Outputs - Summary'!J85 -> 0 | T84: ='Outputs - Summary'!K85 -> 0 | U84: ='Outputs - Summary'!L85 -> 0 | W84: =N84-E84 -> 0 | X84: =O84-F84 -> 0 | Y84: =P84-G84 -> 0 | Z84: =Q84-H84 -> 0 | AA84: =R84-I84 -> 0 | AB84: =S84-J84 -> 0 | AC84: =T84-K84 -> 0 | AD84: =U84-L84 -> 0 | AG84: =DebtFinancing!S$24 -> 0 | AH84: =DebtFinancing!T$24 -> 0 | AI84: =DebtFinancing!U$24 -> 0 | AJ84: =DebtFinancing!V$24 -> 0 | AK84: =DebtFinancing!W$24 -> 0 | AL84: =DebtFinancing!X$24 -> 0 | AM84: =DebtFinancing!Y$24 -> 0 | AN84: =DebtFinancing!Z$24 -> 0 | ... CF84: =DebtFinancing!BR$24 -> 0
B85: Term debt | D85: =unit -> £ | E85: =KeyInputs!E134 -> 0 | F85: =KeyInputs!F134 -> 0 | G85: =KeyInputs!G134 -> 0 | H85: ='Outputs - BalanceSheet'!E35 -> 0 | I85: ='Outputs - BalanceSheet'!F35 -> 0 | J85: ='Outputs - BalanceSheet'!G35 -> 0 | K85: ='Outputs - BalanceSheet'!H35 -> 0 | L85: ='Outputs - BalanceSheet'!I35 -> 0 | N85: ='Outputs - Summary'!E86 -> 0 | O85: ='Outputs - Summary'!F86 -> 0 | P85: ='Outputs - Summary'!G86 -> 0 | Q85: ='Outputs - Summary'!H86 -> 0 | R85: ='Outputs - Summary'!I86 -> 0 | S85: ='Outputs - Summary'!J86 -> 0 | T85: ='Outputs - Summary'!K86 -> 0 | U85: ='Outputs - Summary'!L86 -> 0 | W85: =N85-E85 -> 0 | X85: =O85-F85 -> 0 | Y85: =P85-G85 -> 0 | Z85: =Q85-H85 -> 0 | AA85: =R85-I85 -> 0 | AB85: =S85-J85 -> 0 | AC85: =T85-K85 -> 0 | AD85: =U85-L85 -> 0 | AG85: =DebtFinancing!S$17 -> 0 | AH85: =DebtFinancing!T$17 -> 0 | AI85: =DebtFinancing!U$17 -> 0 | AJ85: =DebtFinancing!V$17 -> 0 | AK85: =DebtFinancing!W$17 -> 0 | AL85: =DebtFinancing!X$17 -> 0 | AM85: =DebtFinancing!Y$17 -> 0 | AN85: =DebtFinancing!Z$17 -> 0 | ... CF85: =DebtFinancing!BR$17 -> 0
B86: Current tax | D86: =unit -> £ | E86: =KeyInputs!E136 -> 0 | F86: =KeyInputs!F136 -> 0 | G86: =KeyInputs!G136 -> 0 | H86: ='Outputs - BalanceSheet'!E37 -> 0 | I86: ='Outputs - BalanceSheet'!F37 -> 0 | J86: ='Outputs - BalanceSheet'!G37 -> 0 | K86: ='Outputs - BalanceSheet'!H37 -> 0 | L86: ='Outputs - BalanceSheet'!I37 -> 0 | N86: ='Outputs - Summary'!E88 -> 0 | O86: ='Outputs - Summary'!F88 -> 0 | P86: ='Outputs - Summary'!G88 -> 0 | Q86: ='Outputs - Summary'!H88 -> 0 | R86: ='Outputs - Summary'!I88 -> 0 | S86: ='Outputs - Summary'!J88 -> 0 | T86: ='Outputs - Summary'!K88 -> 0 | U86: ='Outputs - Summary'!L88 -> 0 | W86: =N86-E86 -> 0 | X86: =O86-F86 -> 0 | Y86: =P86-G86 -> 0 | Z86: =Q86-H86 -> 0 | AA86: =R86-I86 -> 0 | AB86: =S86-J86 -> 0 | AC86: =T86-K86 -> 0 | AD86: =U86-L86 -> 0 | AG86: =TAX!S$44 -> 0 | AH86: =TAX!T$44 -> 0 | AI86: =TAX!U$44 -> 0 | AJ86: =TAX!V$44 -> 0 | AK86: =TAX!W$44 -> 0 | AL86: =TAX!X$44 -> 0 | AM86: =TAX!Y$44 -> 0 | AN86: =TAX!Z$44 -> 0 | ... CF86: =TAX!BR$44 -> 0
N87: ='Outputs - Summary'!E89 -> 0 | O87: ='Outputs - Summary'!F89 -> 0 | P87: ='Outputs - Summary'!G89 -> 0 | Q87: ='Outputs - Summary'!H89 -> 0 | R87: ='Outputs - Summary'!I89 -> 0 | S87: ='Outputs - Summary'!J89 -> 0 | T87: ='Outputs - Summary'!K89 -> 0 | U87: ='Outputs - Summary'!L89 -> 0 | W87: =N87-E87 -> 0 | X87: =O87-F87 -> 0 | Y87: =P87-G87 -> 0 | Z87: =Q87-H87 -> 0 | AA87: =R87-I87 -> 0 | AB87: =S87-J87 -> 0 | AC87: =T87-K87 -> 0 | AD87: =U87-L87 -> 0
B88: Net assets | D88: =unit -> £ | E88: =SUM(E61,E68,E73,E78,E81:E86) -> 0 | F88: =SUM(F61,F68,F73,F78,F81:F86) -> 0 | G88: =SUM(G61,G68,G73,G78,G81:G86) -> 0 | H88: =SUM(H61,H68,H73,H78,H81:H86) -> 0 | I88: =SUM(I61,I68,I73,I78,I81:I86) -> 0 | J88: =SUM(J61,J68,J73,J78,J81:J86) -> 0 | K88: =SUM(K61,K68,K73,K78,K81:K86) -> 0 | L88: =SUM(L61,L68,L73,L78,L81:L86) -> 0 | N88: ='Outputs - Summary'!E90 -> 0 | O88: ='Outputs - Summary'!F90 -> 0 | P88: ='Outputs - Summary'!G90 -> 0 | Q88: ='Outputs - Summary'!H90 -> 0 | R88: ='Outputs - Summary'!I90 -> 0 | S88: ='Outputs - Summary'!J90 -> 0 | T88: ='Outputs - Summary'!K90 -> 0 | U88: ='Outputs - Summary'!L90 -> 0 | W88: =N88-E88 -> 0 | X88: =O88-F88 -> 0 | Y88: =P88-G88 -> 0 | Z88: =Q88-H88 -> 0 | AA88: =R88-I88 -> 0 | AB88: =S88-J88 -> 0 | AC88: =T88-K88 -> 0 | AD88: =U88-L88 -> 0 | AG88: =SUM(AG61,AG68,AG73,AG78,AG81:AG86) -> 0 | AH88: =SUM(AH61,AH68,AH73,AH78,AH81:AH86) -> 0 | AI88: =SUM(AI61,AI68,AI73,AI78,AI81:AI86) -> 0 | AJ88: =SUM(AJ61,AJ68,AJ73,AJ78,AJ81:AJ86) -> 0 | AK88: =SUM(AK61,AK68,AK73,AK78,AK81:AK86) -> 0 | AL88: =SUM(AL61,AL68,AL73,AL78,AL81:AL86) -> 0 | AM88: =SUM(AM61,AM68,AM73,AM78,AM81:AM86) -> 0 | AN88: =SUM(AN61,AN68,AN73,AN78,AN81:AN86) -> 0 | ... CF88: =SUM(CF61,CF68,CF73,CF78,CF81:CF86) -> 0
B90: Share capital | D90: =unit -> £ | E90: =KeyInputs!E140 -> 0 | F90: =KeyInputs!F140 -> 0 | G90: =KeyInputs!G140 -> 0 | H90: ='Outputs - BalanceSheet'!E41 -> 0 | I90: ='Outputs - BalanceSheet'!F41 -> 0 | J90: ='Outputs - BalanceSheet'!G41 -> 0 | K90: ='Outputs - BalanceSheet'!H41 -> 0 | L90: ='Outputs - BalanceSheet'!I41 -> 0 | N90: ='Outputs - Summary'!E92 -> 0 | O90: ='Outputs - Summary'!F92 -> 0 | P90: ='Outputs - Summary'!G92 -> 0 | Q90: ='Outputs - Summary'!H92 -> 0 | R90: ='Outputs - Summary'!I92 -> 0 | S90: ='Outputs - Summary'!J92 -> 0 | T90: ='Outputs - Summary'!K92 -> 0 | U90: ='Outputs - Summary'!L92 -> 0 | W90: =N90-E90 -> 0 | X90: =O90-F90 -> 0 | Y90: =P90-G90 -> 0 | Z90: =Q90-H90 -> 0 | AA90: =R90-I90 -> 0 | AB90: =S90-J90 -> 0 | AC90: =T90-K90 -> 0 | AD90: =U90-L90 -> 0 | AG90: =AF90 -> 0 | AH90: =AG90 -> 0 | AI90: =AH90 -> 0 | AJ90: =AI90 -> 0 | AK90: =AJ90 -> 0 | AL90: =AK90 -> 0 | AM90: =AL90 -> 0 | AN90: =AM90 -> 0 | ... CF90: =CE90 -> 0
B91: P&L reserve | D91: =unit -> £ | E91: =KeyInputs!E141 -> 0 | F91: =KeyInputs!F141 -> 0 | G91: =KeyInputs!G141 -> 0 | H91: ='Outputs - BalanceSheet'!E42 -> 0 | I91: ='Outputs - BalanceSheet'!F42 -> 0 | J91: ='Outputs - BalanceSheet'!G42 -> 0 | K91: ='Outputs - BalanceSheet'!H42 -> 0 | L91: ='Outputs - BalanceSheet'!I42 -> 0 | N91: ='Outputs - Summary'!E93 -> 0 | O91: ='Outputs - Summary'!F93 -> 0 | P91: ='Outputs - Summary'!G93 -> 0 | Q91: ='Outputs - Summary'!H93 -> 0 | R91: ='Outputs - Summary'!I93 -> 0 | S91: ='Outputs - Summary'!J93 -> 0 | T91: ='Outputs - Summary'!K93 -> 0 | U91: ='Outputs - Summary'!L93 -> 0 | W91: =N91-E91 -> 0 | X91: =O91-F91 -> 0 | Y91: =P91-G91 -> 0 | Z91: =Q91-H91 -> 0 | AA91: =R91-I91 -> 0 | AB91: =S91-J91 -> 0 | AC91: =T91-K91 -> 0 | AD91: =U91-L91 -> 0 | AG91: ='Outputs - P&L'!S84 -> 0 | AH91: ='Outputs - P&L'!T84 -> 0 | AI91: ='Outputs - P&L'!U84 -> 0 | AJ91: ='Outputs - P&L'!V84 -> 0 | AK91: ='Outputs - P&L'!W84 -> 0 | AL91: ='Outputs - P&L'!X84 -> 0 | AM91: ='Outputs - P&L'!Y84 -> 0 | AN91: ='Outputs - P&L'!Z84 -> 0 | ... CF91: ='Outputs - P&L'!BR84 -> 0
B93: Shareholders' funds | D93: =unit -> £ | E93: =SUM(E90:E92) -> 0 | F93: =SUM(F90:F92) -> 0 | G93: =SUM(G90:G92) -> 0 | H93: =SUM(H90:H92) -> 0 | I93: =SUM(I90:I92) -> 0 | J93: =SUM(J90:J92) -> 0 | K93: =SUM(K90:K92) -> 0 | L93: =SUM(L90:L92) -> 0 | N93: ='Outputs - Summary'!E95 -> 0 | O93: ='Outputs - Summary'!F95 -> 0 | P93: ='Outputs - Summary'!G95 -> 0 | Q93: ='Outputs - Summary'!H95 -> 0 | R93: ='Outputs - Summary'!I95 -> 0 | S93: ='Outputs - Summary'!J95 -> 0 | T93: ='Outputs - Summary'!K95 -> 0 | U93: ='Outputs - Summary'!L95 -> 0 | W93: =N93-E93 -> 0 | X93: =O93-F93 -> 0 | Y93: =P93-G93 -> 0 | Z93: =Q93-H93 -> 0 | AA93: =R93-I93 -> 0 | AB93: =S93-J93 -> 0 | AC93: =T93-K93 -> 0 | AD93: =U93-L93 -> 0 | AG93: =SUM(AG90:AG92) -> 0 | AH93: =SUM(AH90:AH92) -> 0 | AI93: =SUM(AI90:AI92) -> 0 | AJ93: =SUM(AJ90:AJ92) -> 0 | AK93: =SUM(AK90:AK92) -> 0 | AL93: =SUM(AL90:AL92) -> 0 | AM93: =SUM(AM90:AM92) -> 0 | AN93: =SUM(AN90:AN92) -> 0 | ... CF93: =SUM(CF90:CF92) -> 0
A95: =Header1 -> 3 | B95: Cash Flow Statement
B97: Operating profit | D97: =unit -> £ | E97: =KeyInputs!E196 -> 0 | F97: =KeyInputs!F196 -> 0 | G97: =KeyInputs!G196 -> 0 | H97: ='Outputs - Cashflow'!E12 -> 0 | I97: ='Outputs - Cashflow'!F12 -> 0 | J97: ='Outputs - Cashflow'!G12 -> 0 | K97: ='Outputs - Cashflow'!H12 -> 0 | L97: ='Outputs - Cashflow'!I12 -> 0 | N97: ='Outputs - Summary'!E99 -> 0 | O97: ='Outputs - Summary'!F99 -> 0 | P97: ='Outputs - Summary'!G99 -> 0 | Q97: ='Outputs - Summary'!H99 -> 0 | R97: ='Outputs - Summary'!I99 -> 0 | S97: ='Outputs - Summary'!J99 -> 0 | T97: ='Outputs - Summary'!K99 -> 0 | U97: ='Outputs - Summary'!L99 -> 0 | W97: =N97-E97 -> 0 | X97: =O97-F97 -> 0 | Y97: =P97-G97 -> 0 | Z97: =Q97-H97 -> 0 | AA97: =R97-I97 -> 0 | AB97: =S97-J97 -> 0 | AC97: =T97-K97 -> 0 | AD97: =U97-L97 -> 0
B99: add back depreciation | D99: =unit -> £ | E99: =KeyInputs!E198 -> 0 | F99: =KeyInputs!F198 -> 0 | G99: =KeyInputs!G198 -> 0 | H99: ='Outputs - Cashflow'!E14 -> 0 | I99: ='Outputs - Cashflow'!F14 -> 0 | J99: ='Outputs - Cashflow'!G14 -> 0 | K99: ='Outputs - Cashflow'!H14 -> 0 | L99: ='Outputs - Cashflow'!I14 -> 0 | N99: ='Outputs - Summary'!E101 -> 0 | O99: ='Outputs - Summary'!F101 -> 0 | P99: ='Outputs - Summary'!G101 -> 0 | Q99: ='Outputs - Summary'!H101 -> 0 | R99: ='Outputs - Summary'!I101 -> 0 | S99: ='Outputs - Summary'!J101 -> 0 | T99: ='Outputs - Summary'!K101 -> 0 | U99: ='Outputs - Summary'!L101 -> 0 | W99: =N99-E99 -> 0 | X99: =O99-F99 -> 0 | Y99: =P99-G99 -> 0 | Z99: =Q99-H99 -> 0 | AA99: =R99-I99 -> 0 | AB99: =S99-J99 -> 0 | AC99: =T99-K99 -> 0 | AD99: =U99-L99 -> 0
B100: movement in trade debtors | D100: =unit -> £ | E100: =KeyInputs!E199 -> 0 | F100: =KeyInputs!F199 -> 0 | G100: =KeyInputs!G199 -> 0 | H100: ='Outputs - Cashflow'!E15 -> 0 | I100: ='Outputs - Cashflow'!F15 -> 0 | J100: ='Outputs - Cashflow'!G15 -> 0 | K100: ='Outputs - Cashflow'!H15 -> 0 | L100: ='Outputs - Cashflow'!I15 -> 0 | N100: ='Outputs - Summary'!E102 -> 0 | O100: ='Outputs - Summary'!F102 -> 0 | P100: ='Outputs - Summary'!G102 -> 0 | Q100: ='Outputs - Summary'!H102 -> 0 | R100: ='Outputs - Summary'!I102 -> 0 | S100: ='Outputs - Summary'!J102 -> 0 | T100: ='Outputs - Summary'!K102 -> 0 | U100: ='Outputs - Summary'!L102 -> 0 | W100: =N100-E100 -> 0 | X100: =O100-F100 -> 0 | Y100: =P100-G100 -> 0 | Z100: =Q100-H100 -> 0 | AA100: =R100-I100 -> 0 | AB100: =S100-J100 -> 0 | AC100: =T100-K100 -> 0 | AD100: =U100-L100 -> 0
B101: movement in stocks | D101: =unit -> £ | E101: =KeyInputs!E200 -> 0 | F101: =KeyInputs!F200 -> 0 | G101: =KeyInputs!G200 -> 0 | H101: ='Outputs - Cashflow'!E16 -> 0 | I101: ='Outputs - Cashflow'!F16 -> 0 | J101: ='Outputs - Cashflow'!G16 -> 0 | K101: ='Outputs - Cashflow'!H16 -> 0 | L101: ='Outputs - Cashflow'!I16 -> 0 | N101: ='Outputs - Summary'!E103 -> 0 | O101: ='Outputs - Summary'!F103 -> 0 | P101: ='Outputs - Summary'!G103 -> 0 | Q101: ='Outputs - Summary'!H103 -> 0 | R101: ='Outputs - Summary'!I103 -> 0 | S101: ='Outputs - Summary'!J103 -> 0 | T101: ='Outputs - Summary'!K103 -> 0 | U101: ='Outputs - Summary'!L103 -> 0 | W101: =N101-E101 -> 0 | X101: =O101-F101 -> 0 | Y101: =P101-G101 -> 0 | Z101: =Q101-H101 -> 0 | AA101: =R101-I101 -> 0 | AB101: =S101-J101 -> 0 | AC101: =T101-K101 -> 0 | AD101: =U101-L101 -> 0
B102: movement in trade creditors | D102: =unit -> £ | E102: =KeyInputs!E201 -> 0 | F102: =KeyInputs!F201 -> 0 | G102: =KeyInputs!G201 -> 0 | H102: ='Outputs - Cashflow'!E17 -> 0 | I102: ='Outputs - Cashflow'!F17 -> 0 | J102: ='Outputs - Cashflow'!G17 -> 0 | K102: ='Outputs - Cashflow'!H17 -> 0 | L102: ='Outputs - Cashflow'!I17 -> 0 | N102: ='Outputs - Summary'!E104 -> 0 | O102: ='Outputs - Summary'!F104 -> 0 | P102: ='Outputs - Summary'!G104 -> 0 | Q102: ='Outputs - Summary'!H104 -> 0 | R102: ='Outputs - Summary'!I104 -> 0 | S102: ='Outputs - Summary'!J104 -> 0 | T102: ='Outputs - Summary'!K104 -> 0 | U102: ='Outputs - Summary'!L104 -> 0 | W102: =N102-E102 -> 0 | X102: =O102-F102 -> 0 | Y102: =P102-G102 -> 0 | Z102: =Q102-H102 -> 0 | AA102: =R102-I102 -> 0 | AB102: =S102-J102 -> 0 | AC102: =T102-K102 -> 0 | AD102: =U102-L102 -> 0
B103: movement in VAT | D103: =unit -> £ | E103: =KeyInputs!E202 -> 0 | F103: =KeyInputs!F202 -> 0 | G103: =KeyInputs!G202 -> 0 | H103: ='Outputs - Cashflow'!E18 -> 0 | I103: ='Outputs - Cashflow'!F18 -> 0 | J103: ='Outputs - Cashflow'!G18 -> 0 | K103: ='Outputs - Cashflow'!H18 -> 0 | L103: ='Outputs - Cashflow'!I18 -> 0 | N103: ='Outputs - Summary'!E105 -> 0 | O103: ='Outputs - Summary'!F105 -> 0 | P103: ='Outputs - Summary'!G105 -> 0 | Q103: ='Outputs - Summary'!H105 -> 0 | R103: ='Outputs - Summary'!I105 -> 0 | S103: ='Outputs - Summary'!J105 -> 0 | T103: ='Outputs - Summary'!K105 -> 0 | U103: ='Outputs - Summary'!L105 -> 0 | W103: =N103-E103 -> 0 | X103: =O103-F103 -> 0 | Y103: =P103-G103 -> 0 | Z103: =Q103-H103 -> 0 | AA103: =R103-I103 -> 0 | AB103: =S103-J103 -> 0 | AC103: =T103-K103 -> 0 | AD103: =U103-L103 -> 0
B104: Operating cash flow | D104: =unit -> £ | E104: =SUM(E97:E103) -> 0 | F104: =SUM(F97:F103) -> 0 | G104: =SUM(G97:G103) -> 0 | H104: =SUM(H97:H103) -> 0 | I104: =SUM(I97:I103) -> 0 | J104: =SUM(J97:J103) -> 0 | K104: =SUM(K97:K103) -> 0 | L104: =SUM(L97:L103) -> 0 | N104: =SUM(N97:N103) -> 0 | O104: =SUM(O97:O103) -> 0 | P104: =SUM(P97:P103) -> 0 | Q104: =SUM(Q97:Q103) -> 0 | R104: =SUM(R97:R103) -> 0 | S104: =SUM(S97:S103) -> 0 | T104: =SUM(T97:T103) -> 0 | U104: =SUM(U97:U103) -> 0 | W104: =N104-E104 -> 0 | X104: =O104-F104 -> 0 | Y104: =P104-G104 -> 0 | Z104: =Q104-H104 -> 0 | AA104: =R104-I104 -> 0 | AB104: =S104-J104 -> 0 | AC104: =T104-K104 -> 0 | AD104: =U104-L104 -> 0
B106: Capital expenditure | D106: =unit -> £ | E106: =KeyInputs!E205 -> 0 | F106: =KeyInputs!F205 -> 0 | G106: =KeyInputs!G205 -> 0 | H106: ='Outputs - Cashflow'!E21 -> 0 | I106: ='Outputs - Cashflow'!F21 -> 0 | J106: ='Outputs - Cashflow'!G21 -> 0 | K106: ='Outputs - Cashflow'!H21 -> 0 | L106: ='Outputs - Cashflow'!I21 -> 0 | N106: ='Outputs - Summary'!E108 -> 0 | O106: ='Outputs - Summary'!F108 -> 0 | P106: ='Outputs - Summary'!G108 -> 0 | Q106: ='Outputs - Summary'!H108 -> 0 | R106: ='Outputs - Summary'!I108 -> 0 | S106: ='Outputs - Summary'!J108 -> 0 | T106: ='Outputs - Summary'!K108 -> 0 | U106: ='Outputs - Summary'!L108 -> 0 | W106: =N106-E106 -> 0 | X106: =O106-F106 -> 0 | Y106: =P106-G106 -> 0 | Z106: =Q106-H106 -> 0 | AA106: =R106-I106 -> 0 | AB106: =S106-J106 -> 0 | AC106: =T106-K106 -> 0 | AD106: =U106-L106 -> 0
B107: Proceeds of disposals | D107: =unit -> £ | E107: =KeyInputs!E206 -> 0 | F107: =KeyInputs!F206 -> 0 | G107: =KeyInputs!G206 -> 0 | H107: ='Outputs - Cashflow'!E22 -> 0 | I107: ='Outputs - Cashflow'!F22 -> 0 | J107: ='Outputs - Cashflow'!G22 -> 0 | K107: ='Outputs - Cashflow'!H22 -> 0 | L107: ='Outputs - Cashflow'!I22 -> 0 | N107: ='Outputs - Summary'!E109 -> 0 | O107: ='Outputs - Summary'!F109 -> 0 | P107: ='Outputs - Summary'!G109 -> 0 | Q107: ='Outputs - Summary'!H109 -> 0 | R107: ='Outputs - Summary'!I109 -> 0 | S107: ='Outputs - Summary'!J109 -> 0 | T107: ='Outputs - Summary'!K109 -> 0 | U107: ='Outputs - Summary'!L109 -> 0 | W107: =N107-E107 -> 0 | X107: =O107-F107 -> 0 | Y107: =P107-G107 -> 0 | Z107: =Q107-H107 -> 0 | AA107: =R107-I107 -> 0 | AB107: =S107-J107 -> 0 | AC107: =T107-K107 -> 0 | AD107: =U107-L107 -> 0
N108: ='Outputs - Summary'!E110 -> 0 | O108: ='Outputs - Summary'!F110 -> 0 | P108: ='Outputs - Summary'!G110 -> 0 | Q108: ='Outputs - Summary'!H110 -> 0 | R108: ='Outputs - Summary'!I110 -> 0 | S108: ='Outputs - Summary'!J110 -> 0 | T108: ='Outputs - Summary'!K110 -> 0 | U108: ='Outputs - Summary'!L110 -> 0 | W108: =N108-E108 -> 0 | X108: =O108-F108 -> 0 | Y108: =P108-G108 -> 0 | Z108: =Q108-H108 -> 0 | AA108: =R108-I108 -> 0 | AB108: =S108-J108 -> 0 | AC108: =T108-K108 -> 0 | AD108: =U108-L108 -> 0
B109: Grant received | D109: =unit -> £ | E109: =KeyInputs!E208 -> 0 | F109: =KeyInputs!F208 -> 0 | G109: =KeyInputs!G208 -> 0 | H109: ='Outputs - Cashflow'!E24 -> 0 | I109: ='Outputs - Cashflow'!F24 -> 0 | J109: ='Outputs - Cashflow'!G24 -> 0 | K109: ='Outputs - Cashflow'!H24 -> 0 | L109: ='Outputs - Cashflow'!I24 -> 0 | N109: ='Outputs - Summary'!E111 -> 0 | O109: ='Outputs - Summary'!F111 -> 0 | P109: ='Outputs - Summary'!G111 -> 0 | Q109: ='Outputs - Summary'!H111 -> 0 | R109: ='Outputs - Summary'!I111 -> 0 | S109: ='Outputs - Summary'!J111 -> 0 | T109: ='Outputs - Summary'!K111 -> 0 | U109: ='Outputs - Summary'!L111 -> 0 | W109: =N109-E109 -> 0 | X109: =O109-F109 -> 0 | Y109: =P109-G109 -> 0 | Z109: =Q109-H109 -> 0 | AA109: =R109-I109 -> 0 | AB109: =S109-J109 -> 0 | AC109: =T109-K109 -> 0 | AD109: =U109-L109 -> 0
N110: ='Outputs - Summary'!E112 -> 0 | O110: ='Outputs - Summary'!F112 -> 0 | P110: ='Outputs - Summary'!G112 -> 0 | Q110: ='Outputs - Summary'!H112 -> 0 | R110: ='Outputs - Summary'!I112 -> 0 | S110: ='Outputs - Summary'!J112 -> 0 | T110: ='Outputs - Summary'!K112 -> 0 | U110: ='Outputs - Summary'!L112 -> 0 | W110: =N110-E110 -> 0 | X110: =O110-F110 -> 0 | Y110: =P110-G110 -> 0 | Z110: =Q110-H110 -> 0 | AA110: =R110-I110 -> 0 | AB110: =S110-J110 -> 0 | AC110: =T110-K110 -> 0 | AD110: =U110-L110 -> 0
B111: Drawings on debt | D111: =unit -> £ | E111: =KeyInputs!E210 -> 0 | F111: =KeyInputs!F210 -> 0 | G111: =KeyInputs!G210 -> 0 | H111: ='Outputs - Cashflow'!E27 -> 0 | I111: ='Outputs - Cashflow'!F27 -> 0 | J111: ='Outputs - Cashflow'!G27 -> 0 | K111: ='Outputs - Cashflow'!H27 -> 0 | L111: ='Outputs - Cashflow'!I27 -> 0 | N111: ='Outputs - Summary'!E115 -> 0 | O111: ='Outputs - Summary'!F115 -> 0 | P111: ='Outputs - Summary'!G115 -> 0 | Q111: ='Outputs - Summary'!H115 -> 0 | R111: ='Outputs - Summary'!I115 -> 0 | S111: ='Outputs - Summary'!J115 -> 0 | T111: ='Outputs - Summary'!K115 -> 0 | U111: ='Outputs - Summary'!L115 -> 0 | W111: =N111-E111 -> 0 | X111: =O111-F111 -> 0 | Y111: =P111-G111 -> 0 | Z111: =Q111-H111 -> 0 | AA111: =R111-I111 -> 0 | AB111: =S111-J111 -> 0 | AC111: =T111-K111 -> 0 | AD111: =U111-L111 -> 0
B112: Repayments of debt | D112: =unit -> £ | E112: =KeyInputs!E211 -> 0 | F112: =KeyInputs!F211 -> 0 | G112: =KeyInputs!G211 -> 0 | H112: ='Outputs - Cashflow'!E28 -> 0 | I112: ='Outputs - Cashflow'!F28 -> 0 | J112: ='Outputs - Cashflow'!G28 -> 0 | K112: ='Outputs - Cashflow'!H28 -> 0 | L112: ='Outputs - Cashflow'!I28 -> 0 | N112: ='Outputs - Summary'!E116 -> 0 | O112: ='Outputs - Summary'!F116 -> 0 | P112: ='Outputs - Summary'!G116 -> 0 | Q112: ='Outputs - Summary'!H116 -> 0 | R112: ='Outputs - Summary'!I116 -> 0 | S112: ='Outputs - Summary'!J116 -> 0 | T112: ='Outputs - Summary'!K116 -> 0 | U112: ='Outputs - Summary'!L116 -> 0 | W112: =N112-E112 -> 0 | X112: =O112-F112 -> 0 | Y112: =P112-G112 -> 0 | Z112: =Q112-H112 -> 0 | AA112: =R112-I112 -> 0 | AB112: =S112-J112 -> 0 | AC112: =T112-K112 -> 0 | AD112: =U112-L112 -> 0
N113: ='Outputs - Summary'!E117 -> 0 | O113: ='Outputs - Summary'!F117 -> 0 | P113: ='Outputs - Summary'!G117 -> 0 | Q113: ='Outputs - Summary'!H117 -> 0 | R113: ='Outputs - Summary'!I117 -> 0 | S113: ='Outputs - Summary'!J117 -> 0 | T113: ='Outputs - Summary'!K117 -> 0 | U113: ='Outputs - Summary'!L117 -> 0 | W113: =N113-E113 -> 0 | X113: =O113-F113 -> 0 | Y113: =P113-G113 -> 0 | Z113: =Q113-H113 -> 0 | AA113: =R113-I113 -> 0 | AB113: =S113-J113 -> 0 | AC113: =T113-K113 -> 0 | AD113: =U113-L113 -> 0
B114: Interest on debt | D114: =unit -> £ | E114: =KeyInputs!E213 -> 0 | F114: =KeyInputs!F213 -> 0 | G114: =KeyInputs!G213 -> 0 | H114: ='Outputs - Cashflow'!E30 -> 0 | I114: ='Outputs - Cashflow'!F30 -> 0 | J114: ='Outputs - Cashflow'!G30 -> 0 | K114: ='Outputs - Cashflow'!H30 -> 0 | L114: ='Outputs - Cashflow'!I30 -> 0 | N114: ='Outputs - Summary'!E118 -> 0 | O114: ='Outputs - Summary'!F118 -> 0 | P114: ='Outputs - Summary'!G118 -> 0 | Q114: ='Outputs - Summary'!H118 -> 0 | R114: ='Outputs - Summary'!I118 -> 0 | S114: ='Outputs - Summary'!J118 -> 0 | T114: ='Outputs - Summary'!K118 -> 0 | U114: ='Outputs - Summary'!L118 -> 0 | W114: =N114-E114 -> 0 | X114: =O114-F114 -> 0 | Y114: =P114-G114 -> 0 | Z114: =Q114-H114 -> 0 | AA114: =R114-I114 -> 0 | AB114: =S114-J114 -> 0 | AC114: =T114-K114 -> 0 | AD114: =U114-L114 -> 0
N115: ='Outputs - Summary'!E119 -> 0 | O115: ='Outputs - Summary'!F119 -> 0 | P115: ='Outputs - Summary'!G119 -> 0 | Q115: ='Outputs - Summary'!H119 -> 0 | R115: ='Outputs - Summary'!I119 -> 0 | S115: ='Outputs - Summary'!J119 -> 0 | T115: ='Outputs - Summary'!K119 -> 0 | U115: ='Outputs - Summary'!L119 -> 0 | W115: =N115-E115 -> 0 | X115: =O115-F115 -> 0 | Y115: =P115-G115 -> 0 | Z115: =Q115-H115 -> 0 | AA115: =R115-I115 -> 0 | AB115: =S115-J115 -> 0 | AC115: =T115-K115 -> 0 | AD115: =U115-L115 -> 0
B116: Taxation | D116: =unit -> £ | E116: =KeyInputs!E215 -> 0 | F116: =KeyInputs!F215 -> 0 | G116: =KeyInputs!G215 -> 0 | H116: ='Outputs - Cashflow'!E32 -> 0 | I116: ='Outputs - Cashflow'!F32 -> 0 | J116: ='Outputs - Cashflow'!G32 -> 0 | K116: ='Outputs - Cashflow'!H32 -> 0 | L116: ='Outputs - Cashflow'!I32 -> 0 | N116: ='Outputs - Summary'!E120 -> 0 | O116: ='Outputs - Summary'!F120 -> 0 | P116: ='Outputs - Summary'!G120 -> 0 | Q116: ='Outputs - Summary'!H120 -> 0 | R116: ='Outputs - Summary'!I120 -> 0 | S116: ='Outputs - Summary'!J120 -> 0 | T116: ='Outputs - Summary'!K120 -> 0 | U116: ='Outputs - Summary'!L120 -> 0 | W116: =N116-E116 -> 0 | X116: =O116-F116 -> 0 | Y116: =P116-G116 -> 0 | Z116: =Q116-H116 -> 0 | AA116: =R116-I116 -> 0 | AB116: =S116-J116 -> 0 | AC116: =T116-K116 -> 0 | AD116: =U116-L116 -> 0
N117: ='Outputs - Summary'!E121 -> 0 | O117: ='Outputs - Summary'!F121 -> 0 | P117: ='Outputs - Summary'!G121 -> 0 | Q117: ='Outputs - Summary'!H121 -> 0 | R117: ='Outputs - Summary'!I121 -> 0 | S117: ='Outputs - Summary'!J121 -> 0 | T117: ='Outputs - Summary'!K121 -> 0 | U117: ='Outputs - Summary'!L121 -> 0 | W117: =N117-E117 -> 0 | X117: =O117-F117 -> 0 | Y117: =P117-G117 -> 0 | Z117: =Q117-H117 -> 0 | AA117: =R117-I117 -> 0 | AB117: =S117-J117 -> 0 | AC117: =T117-K117 -> 0 | AD117: =U117-L117 -> 0
B118: Dividends payable | D118: =unit -> £ | E118: =KeyInputs!E217 -> 0 | F118: =KeyInputs!F217 -> 0 | G118: =KeyInputs!G217 -> 0 | H118: ='Outputs - Cashflow'!E34 -> 0 | I118: ='Outputs - Cashflow'!F34 -> 0 | J118: ='Outputs - Cashflow'!G34 -> 0 | K118: ='Outputs - Cashflow'!H34 -> 0 | L118: ='Outputs - Cashflow'!I34 -> 0 | N118: ='Outputs - Summary'!E122 -> 0 | O118: ='Outputs - Summary'!F122 -> 0 | P118: ='Outputs - Summary'!G122 -> 0 | Q118: ='Outputs - Summary'!H122 -> 0 | R118: ='Outputs - Summary'!I122 -> 0 | S118: ='Outputs - Summary'!J122 -> 0 | T118: ='Outputs - Summary'!K122 -> 0 | U118: ='Outputs - Summary'!L122 -> 0 | W118: =N118-E118 -> 0 | X118: =O118-F118 -> 0 | Y118: =P118-G118 -> 0 | Z118: =Q118-H118 -> 0 | AA118: =R118-I118 -> 0 | AB118: =S118-J118 -> 0 | AC118: =T118-K118 -> 0 | AD118: =U118-L118 -> 0
N119: ='Outputs - Summary'!E123 -> 0 | O119: ='Outputs - Summary'!F123 -> 0 | P119: ='Outputs - Summary'!G123 -> 0 | Q119: ='Outputs - Summary'!H123 -> 0 | R119: ='Outputs - Summary'!I123 -> 0 | S119: ='Outputs - Summary'!J123 -> 0 | T119: ='Outputs - Summary'!K123 -> 0 | U119: ='Outputs - Summary'!L123 -> 0 | W119: =N119-E119 -> 0 | X119: =O119-F119 -> 0 | Y119: =P119-G119 -> 0 | Z119: =Q119-H119 -> 0 | AA119: =R119-I119 -> 0 | AB119: =S119-J119 -> 0 | AC119: =T119-K119 -> 0 | AD119: =U119-L119 -> 0
B120: Net cash flow | D120: =unit -> £ | E120: =SUM(E104:E119) -> 0 | F120: =SUM(F104:F119) -> 0 | G120: =SUM(G104:G119) -> 0 | H120: =SUM(H104:H119) -> 0 | I120: =SUM(I104:I119) -> 0 | J120: =SUM(J104:J119) -> 0 | K120: =SUM(K104:K119) -> 0 | L120: =SUM(L104:L119) -> 0 | N120: ='Outputs - Summary'!E124 -> 0 | O120: ='Outputs - Summary'!F124 -> 0 | P120: ='Outputs - Summary'!G124 -> 0 | Q120: ='Outputs - Summary'!H124 -> 0 | R120: ='Outputs - Summary'!I124 -> 0 | S120: ='Outputs - Summary'!J124 -> 0 | T120: ='Outputs - Summary'!K124 -> 0 | U120: ='Outputs - Summary'!L124 -> 0 | W120: =N120-E120 -> 0 | X120: =O120-F120 -> 0 | Y120: =P120-G120 -> 0 | Z120: =Q120-H120 -> 0 | AA120: =R120-I120 -> 0 | AB120: =S120-J120 -> 0 | AC120: =T120-K120 -> 0 | AD120: =U120-L120 -> 0
N121: ='Outputs - Summary'!E125 -> 0 | O121: ='Outputs - Summary'!F125 -> 0 | P121: ='Outputs - Summary'!G125 -> 0 | Q121: ='Outputs - Summary'!H125 -> 0 | R121: ='Outputs - Summary'!I125 -> 0 | S121: ='Outputs - Summary'!J125 -> 0 | T121: ='Outputs - Summary'!K125 -> 0 | U121: ='Outputs - Summary'!L125 -> 0
B122: Cash balance BF | D122: =unit -> £ | E122: =SUM(E106:E121) -> 0 | F122: =SUM(F106:F121) -> 0 | G122: =SUM(G106:G121) -> 0 | H122: ='Outputs - Cashflow'!E38 -> 0 | I122: ='Outputs - Cashflow'!F38 -> 0 | J122: ='Outputs - Cashflow'!G38 -> 0 | K122: ='Outputs - Cashflow'!H38 -> 0 | L122: ='Outputs - Cashflow'!I38 -> 0 | N122: ='Outputs - Summary'!E126 -> 0 | O122: ='Outputs - Summary'!F126 -> 0 | P122: ='Outputs - Summary'!G126 -> 0 | Q122: ='Outputs - Summary'!H126 -> 0 | R122: ='Outputs - Summary'!I126 -> 0 | S122: ='Outputs - Summary'!J126 -> 0 | T122: ='Outputs - Summary'!K126 -> 0 | U122: ='Outputs - Summary'!L126 -> 0
B123: Cash balance CF | D123: =unit -> £ | E123: =SUM(E120:E122) -> 0 | F123: =SUM(F120:F122) -> 0 | G123: =SUM(G120:G122) -> 0 | H123: =SUM(H120:H122) -> 0 | I123: =SUM(I120:I122) -> 0 | J123: =SUM(J120:J122) -> 0 | K123: =SUM(K120:K122) -> 0 | L123: =SUM(L120:L122) -> 0 | N123: ='Outputs - Summary'!E127 -> 0 | O123: ='Outputs - Summary'!F127 -> 0 | P123: ='Outputs - Summary'!G127 -> 0 | Q123: ='Outputs - Summary'!H127 -> 0 | R123: ='Outputs - Summary'!I127 -> 0 | S123: ='Outputs - Summary'!J127 -> 0 | T123: ='Outputs - Summary'!K127 -> 0 | U123: ='Outputs - Summary'!L127 -> 0
B124: Cash/Overdraft interest | E124: ='Outputs - Summary'!E128 -> 0 | F124: ='Outputs - Summary'!F128 -> 0 | G124: ='Outputs - Summary'!G128 -> 0 | H124: ='Outputs - Summary'!H128 -> 0 | I124: ='Outputs - Summary'!I128 -> 0 | J124: ='Outputs - Summary'!J128 -> 0 | K124: ='Outputs - Summary'!K128 -> 0 | L124: ='Outputs - Summary'!L128 -> 0
...

Sheet Key Ratios
A3: =IF(KeyInputs!$F$14=0,"Company Name",KeyInputs!$F$14) -> Company Name
A4: Ratios
D5: ='Outputs - Summary'!D5 -> Year | E5: ='Outputs - Summary'!E5 -> 2012 | F5: ='Outputs - Summary'!F5 -> 2013 | G5: ='Outputs - Summary'!G5 -> 2014 | H5: ='Outputs - Summary'!H5 -> 2015 | I5: ='Outputs - Summary'!I5 -> 2016 | J5: ='Outputs - Summary'!J5 -> 2017 | K5: ='Outputs - Summary'!K5 -> 2018 | L5: ='Outputs - Summary'!L5 -> 2019
D6: ='Outputs - Summary'!D6 -> Period number | E6: ='Outputs - Summary'!E6 -> -2 | F6: ='Outputs - Summary'!F6 -> -1 | G6: ='Outputs - Summary'!G6 -> 0 | H6: ='Outputs - Summary'!H6 -> 1 | I6: ='Outputs - Summary'!I6 -> 2 | J6: ='Outputs - Summary'!J6 -> 3 | K6: ='Outputs - Summary'!K6 -> 4 | L6: ='Outputs - Summary'!L6 -> 5
D7: ='Outputs - Summary'!D7 -> Period starts | E7: ='Outputs - Summary'!E7 -> 40909 | F7: ='Outputs - Summary'!F7 -> 41275 | G7: ='Outputs - Summary'!G7 -> 41640 | H7: ='Outputs - Summary'!H7 -> 42005 | I7: ='Outputs - Summary'!I7 -> 42370 | J7: ='Outputs - Summary'!J7 -> 42736 | K7: ='Outputs - Summary'!K7 -> 43101 | L7: ='Outputs - Summary'!L7 -> 43466
B8: =IF(Check!$C$12=0,"All checks are OK","There are "&Check!$C$12&" error/errors") -> All checks are OK | D8: ='Outputs - Summary'!D8 -> Period ends | E8: ='Outputs - Summary'!E8 -> 41274 | F8: ='Outputs - Summary'!F8 -> 41639 | G8: ='Outputs - Summary'!G8 -> 42004 | H8: ='Outputs - Summary'!H8 -> 42369 | I8: ='Outputs - Summary'!I8 -> 42735 | J8: ='Outputs - Summary'!J8 -> 43100 | K8: ='Outputs - Summary'!K8 -> 43465 | L8: ='Outputs - Summary'!L8 -> 43830
B10: Profit & Loss Account Ratios
B12: Gross Margin % | E12: ='Outputs - Summary'!E27/'Outputs - Summary'!E12 -> #DIV/0! | F12: ='Outputs - Summary'!F27/'Outputs - Summary'!F12 -> #DIV/0! | G12: ='Outputs - Summary'!G27/'Outputs - Summary'!G12 -> #DIV/0! | H12: ='Outputs - Summary'!H27/'Outputs - Summary'!H12 -> #DIV/0! | I12: ='Outputs - Summary'!I27/'Outputs - Summary'!I12 -> #DIV/0! | J12: ='Outputs - Summary'!J27/'Outputs - Summary'!J12 -> #DIV/0! | K12: ='Outputs - Summary'!K27/'Outputs - Summary'!K12 -> #DIV/0! | L12: ='Outputs - Summary'!L27/'Outputs - Summary'!L12 -> #DIV/0!
B13: Operating Margin % | E13: ='Outputs - Summary'!E32/'Outputs - Summary'!E12 -> #DIV/0! | F13: ='Outputs - Summary'!F32/'Outputs - Summary'!F12 -> #DIV/0! | G13: ='Outputs - Summary'!G32/'Outputs - Summary'!G12 -> #DIV/0! | H13: ='Outputs - Summary'!H32/'Outputs - Summary'!H12 -> #DIV/0! | I13: ='Outputs - Summary'!I32/'Outputs - Summary'!I12 -> #DIV/0! | J13: ='Outputs - Summary'!J32/'Outputs - Summary'!J12 -> #DIV/0! | K13: ='Outputs - Summary'!K32/'Outputs - Summary'!K12 -> #DIV/0! | L13: ='Outputs - Summary'!L32/'Outputs - Summary'!L12 -> #DIV/0!
B15: Sales/Direct Staff | E15: ='Outputs - Summary'!E22/'Outputs - Summary'!E12 -> #DIV/0! | F15: ='Outputs - Summary'!F22/'Outputs - Summary'!F12 -> #DIV/0! | G15: ='Outputs - Summary'!G22/'Outputs - Summary'!G12 -> #DIV/0! | H15: ='Outputs - Summary'!H22/'Outputs - Summary'!H12 -> #DIV/0! | I15: ='Outputs - Summary'!I22/'Outputs - Summary'!I12 -> #DIV/0! | J15: ='Outputs - Summary'!J22/'Outputs - Summary'!J12 -> #DIV/0! | K15: ='Outputs - Summary'!K22/'Outputs - Summary'!K12 -> #DIV/0! | L15: ='Outputs - Summary'!L22/'Outputs - Summary'!L12 -> #DIV/0!
B16: Sales/Variable Costs | E16: ='Outputs - Summary'!E17/'Outputs - Summary'!E12 -> #DIV/0! | F16: ='Outputs - Summary'!F17/'Outputs - Summary'!F12 -> #DIV/0! | G16: ='Outputs - Summary'!G17/'Outputs - Summary'!G12 -> #DIV/0! | H16: ='Outputs - Summary'!H17/'Outputs - Summary'!H12 -> #DIV/0! | I16: ='Outputs - Summary'!I17/'Outputs - Summary'!I12 -> #DIV/0! | J16: ='Outputs - Summary'!J17/'Outputs - Summary'!J12 -> #DIV/0! | K16: ='Outputs - Summary'!K17/'Outputs - Summary'!K12 -> #DIV/0! | L16: ='Outputs - Summary'!L17/'Outputs - Summary'!L12 -> #DIV/0!
B17: Sales/Central Satff | E17: ='Outputs - Summary'!E29/'Outputs - Summary'!E12 -> #DIV/0! | F17: ='Outputs - Summary'!F29/'Outputs - Summary'!F12 -> #DIV/0! | G17: ='Outputs - Summary'!G29/'Outputs - Summary'!G12 -> #DIV/0! | H17: ='Outputs - Summary'!H29/'Outputs - Summary'!H12 -> #DIV/0! | I17: ='Outputs - Summary'!I29/'Outputs - Summary'!I12 -> #DIV/0! | J17: ='Outputs - Summary'!J29/'Outputs - Summary'!J12 -> #DIV/0! | K17: ='Outputs - Summary'!K29/'Outputs - Summary'!K12 -> #DIV/0! | L17: ='Outputs - Summary'!L29/'Outputs - Summary'!L12 -> #DIV/0!
B18: Sales/Central Costs | E18: ='Outputs - Summary'!E30/'Outputs - Summary'!E12 -> #DIV/0! | F18: ='Outputs - Summary'!F30/'Outputs - Summary'!F12 -> #DIV/0! | G18: ='Outputs - Summary'!G30/'Outputs - Summary'!G12 -> #DIV/0! | H18: ='Outputs - Summary'!H30/'Outputs - Summary'!H12 -> #DIV/0! | I18: ='Outputs - Summary'!I30/'Outputs - Summary'!I12 -> #DIV/0! | J18: ='Outputs - Summary'!J30/'Outputs - Summary'!J12 -> #DIV/0! | K18: ='Outputs - Summary'!K30/'Outputs - Summary'!K12 -> #DIV/0! | L18: ='Outputs - Summary'!L30/'Outputs - Summary'!L12 -> #DIV/0!
B20: Growth KPIs
B21: Revenue growth | E21: na | F21: =('Outputs - Summary'!F12-'Outputs - Summary'!E12)/'Outputs - Summary'!E12 -> #DIV/0! | G21: =('Outputs - Summary'!G12-'Outputs - Summary'!F12)/'Outputs - Summary'!F12 -> #DIV/0! | H21: =('Outputs - Summary'!H12-'Outputs - Summary'!G12)/'Outputs - Summary'!G12 -> #DIV/0! | I21: =('Outputs - Summary'!I12-'Outputs - Summary'!H12)/'Outputs - Summary'!H12 -> #DIV/0! | J21: =('Outputs - Summary'!J12-'Outputs - Summary'!I12)/'Outputs - Summary'!I12 -> #DIV/0! | K21: =('Outputs - Summary'!K12-'Outputs - Summary'!J12)/'Outputs - Summary'!J12 -> #DIV/0! | L21: =('Outputs - Summary'!L12-'Outputs - Summary'!K12)/'Outputs - Summary'!K12 -> #DIV/0!
B22: Gross profit growth | E22: na | F22: =('Outputs - Summary'!F27-'Outputs - Summary'!E27)/'Outputs - Summary'!E27 -> #DIV/0! | G22: =('Outputs - Summary'!G27-'Outputs - Summary'!F27)/'Outputs - Summary'!F27 -> #DIV/0! | H22: =('Outputs - Summary'!H27-'Outputs - Summary'!G27)/'Outputs - Summary'!G27 -> #DIV/0! | I22: =('Outputs - Summary'!I27-'Outputs - Summary'!H27)/'Outputs - Summary'!H27 -> #DIV/0! | J22: =('Outputs - Summary'!J27-'Outputs - Summary'!I27)/'Outputs - Summary'!I27 -> #DIV/0! | K22: =('Outputs - Summary'!K27-'Outputs - Summary'!J27)/'Outputs - Summary'!J27 -> #DIV/0! | L22: =('Outputs - Summary'!L27-'Outputs - Summary'!K27)/'Outputs - Summary'!K27 -> #DIV/0!
B24: Balance Sheet Ratios
B26: Current Ratio | E26: =('Outputs - Summary'!E80/(SUM('Outputs - Summary'!E82:E88))) -> #DIV/0! | F26: =('Outputs - Summary'!F80/(SUM('Outputs - Summary'!F82:F88))) -> #DIV/0! | G26: =('Outputs - Summary'!G80/(SUM('Outputs - Summary'!G82:G88))) -> #DIV/0! | H26: =('Outputs - Summary'!H80/(SUM('Outputs - Summary'!H82:H88))) -> #DIV/0! | I26: =('Outputs - Summary'!I80/(SUM('Outputs - Summary'!I82:I88))) -> #DIV/0! | J26: =('Outputs - Summary'!J80/(SUM('Outputs - Summary'!J82:J88))) -> #DIV/0! | K26: =('Outputs - Summary'!K80/(SUM('Outputs - Summary'!K82:K88))) -> #DIV/0! | L26: =('Outputs - Summary'!L80/(SUM('Outputs - Summary'!L82:L88))) -> #DIV/0!
B27: Quick/Liquidity Ratio | E27: =('Outputs - Summary'!E79+'Outputs - Summary'!E69)/SUM('Outputs - Summary'!E82:E88) -> #DIV/0! | F27: =('Outputs - Summary'!F79+'Outputs - Summary'!F69)/SUM('Outputs - Summary'!F82:F88) -> #DIV/0! | G27: =('Outputs - Summary'!G79+'Outputs - Summary'!G69)/SUM('Outputs - Summary'!G82:G88) -> #DIV/0! | H27: =('Outputs - Summary'!H79+'Outputs - Summary'!H69)/SUM('Outputs - Summary'!H82:H88) -> #DIV/0! | I27: =('Outputs - Summary'!I79+'Outputs - Summary'!I69)/SUM('Outputs - Summary'!I82:I88) -> #DIV/0! | J27: =('Outputs - Summary'!J79+'Outputs - Summary'!J69)/SUM('Outputs - Summary'!J82:J88) -> #DIV/0! | K27: =('Outputs - Summary'!K79+'Outputs - Summary'!K69)/SUM('Outputs - Summary'!K82:K88) -> #DIV/0! | L27: =('Outputs - Summary'!L79+'Outputs - Summary'!L69)/SUM('Outputs - Summary'!L82:L88) -> #DIV/0!
B28: Cash Ratio | E28: ='Outputs - Summary'!E79/SUM('Outputs - Summary'!E82:E88) -> #DIV/0! | F28: ='Outputs - Summary'!F79/SUM('Outputs - Summary'!F82:F88) -> #DIV/0! | G28: ='Outputs - Summary'!G79/SUM('Outputs - Summary'!G82:G88) -> #DIV/0! | H28: ='Outputs - Summary'!H79/SUM('Outputs - Summary'!H82:H88) -> #DIV/0! | I28: ='Outputs - Summary'!I79/SUM('Outputs - Summary'!I82:I88) -> #DIV/0! | J28: ='Outputs - Summary'!J79/SUM('Outputs - Summary'!J82:J88) -> #DIV/0! | K28: ='Outputs - Summary'!K79/SUM('Outputs - Summary'!K82:K88) -> #DIV/0! | L28: ='Outputs - Summary'!L79/SUM('Outputs - Summary'!L82:L88) -> #DIV/0!
B29: Days Inventory Outstanding (DIO)
B30: Days Sales Outstanding (DSO)
B31: Days Payables Outstanding (DPO)
B32: Cash Conversion Ration
A34: End of sheet

Sheet KeyInputs
A3: =IF(KeyInputs!$F$14=0,"Company Name",KeyInputs!$F$14) -> Company Name
A4: General Model Assumptions
A5: Model Version 9 | D5: Year | E5: =F5-1 -> 2012 | F5: =G5-1 -> 2013 | G5: =H5-1 -> 2014 | H5: =F16 -> 2015 | I5: =H5+1 -> 2016 | J5: =I5+1 -> 2017 | K5: =J5+1 -> 2018 | L5: =K5+1 -> 2019 | N5: =$H$5 -> 2015 | O5: =$H$5 -> 2015 | P5: =$H$5 -> 2015 | Q5: =$H$5 -> 2015 | R5: =$H$5 -> 2015 | S5: =$H$5 -> 2015 | T5: =$H$5 -> 2015 | U5: =$H$5 -> 2015 | ... Y5: =$H$5 -> 2015 | Z5: =$I$5 -> 2016 | AA5: =$I$5 -> 2016 | AB5: =$I$5 -> 2016 | AC5: =$I$5 -> 2016 | AD5: =$I$5 -> 2016 | AE5: =$I$5 -> 2016 | AF5: =$I$5 -> 2016 | AG5: =$I$5 -> 2016 | ... AK5: =$I$5 -> 2016 | AL5: =$J$5 -> 2017 | AM5: =$J$5 -> 2017 | AN5: =$J$5 -> 2017 | AO5: =$J$5 -> 2017 | AP5: =$J$5 -> 2017 | AQ5: =$J$5 -> 2017 | AR5: =$J$5 -> 2017 | AS5: =$J$5 -> 2017 | ... AW5: =$J$5 -> 2017 | AX5: =$K$5 -> 2018 | AY5: =$K$5 -> 2018 | AZ5: =$K$5 -> 2018 | BA5: =$K$5 -> 2018 | BB5: =$K$5 -> 2018 | BC5: =$K$5 -> 2018 | BD5: =$K$5 -> 2018 | BE5: =$K$5 -> 2018 | ... BI5: =$K$5 -> 2018 | BJ5: =$L$5 -> 2019 | BK5: =$L$5 -> 2019 | BL5: =$L$5 -> 2019 | BM5: =$L$5 -> 2019 | BN5: =$L$5 -> 2019 | BO5: =$L$5 -> 2019 | BP5: =$L$5 -> 2019 | BQ5: =$L$5 -> 2019 | ... BU5: =$L$5 -> 2019
D6: Period number | E6: =F6-1 -> -2 | F6: =G6-1 -> -1 | G6: =H6-1 -> 0 | H6: 1 | I6: 2 | J6: 3 | K6: 4 | L6: 5 | N6: 1 | O6: 2 | P6: 3 | Q6: 4 | R6: 5 | S6: 6 | T6: 7 | U6: 8 | V6: 9 | W6: 10 | X6: 11 | Y6: 12 | Z6: 13 | AA6: 14 | AB6: 15 | AC6: 16 | AD6: 17 | AE6: 18 | AF6: 19 | AG6: 20 | AH6: 21 | AI6: 22 | AJ6: 23 | AK6: 24 | AL6: 25 | AM6: 26 | AN6: 27 | AO6: 28 | AP6: 29 | AQ6: 30 | AR6: 31 | AS6: 32 | AT6: 33 | AU6: 34 | AV6: 35 | AW6: 36 | AX6: 37 | AY6: 38 | AZ6: 39 | BA6: 40 | BB6: 41 | BC6: 42 | BD6: 43 | BE6: 44 | BF6: 45 | BG6: 46 | BH6: 47 | BI6: 48 | BJ6: 49 | BK6: 50 | BL6: 51 | BM6: 52 | BN6: 53 | BO6: 54 | BP6: 55 | BQ6: 56 | BR6: 57 | BS6: 58 | BT6: 59 | BU6: 60
D7: Period starts | E7: =EDATE(E8,-12)+1 -> 40909 | F7: =EDATE(F8,-12)+1 -> 41275 | G7: =EDATE(G8,-12)+1 -> 41640 | H7: =$F$17 -> 42005 | I7: =H8+1 -> 42370 | J7: =I8+1 -> 42736 | K7: =J8+1 -> 43101 | L7: =K8+1 -> 43466 | N7: =$F$17 -> 42005 | O7: =N8+1 -> 42036 | P7: =O8+1 -> 42064 | Q7: =P8+1 -> 42095 | R7: =Q8+1 -> 42125 | S7: =R8+1 -> 42156 | T7: =S8+1 -> 42186 | U7: =T8+1 -> 42217 | V7: =U8+1 -> 42248 | ... BU7: =BT8+1 -> 43800
B8: =IF(Check!$C$12=0,"All checks are OK","There are "&Check!$C$12&" error/errors") -> All checks are OK | D8: Period ends | E8: =F7-1 -> 41274 | F8: =G7-1 -> 41639 | G8: =H7-1 -> 42004 | H8: =EDATE(H7,12)-1 -> 42369 | I8: =EDATE(I7,12)-1 -> 42735 | J8: =EDATE(J7,12)-1 -> 43100 | K8: =EDATE(K7,12)-1 -> 43465 | L8: =EDATE(L7,12)-1 -> 43830 | N8: =EOMONTH(N7,0) -> 42035 | O8: =EOMONTH(O7,0) -> 42063 | P8: =EOMONTH(P7,0) -> 42094 | Q8: =EOMONTH(Q7,0) -> 42124 | R8: =EOMONTH(R7,0) -> 42155 | S8: =EOMONTH(S7,0) -> 42185 | T8: =EOMONTH(T7,0) -> 42216 | U8: =EOMONTH(U7,0) -> 42247 | ... BU8: =EOMONTH(BU7,0) -> 43830
A10: =Header1 -> 1 | B10: General inputs
B12: =Header2 -> 1.1 | C12: Forecast details
C14: Company Name
C16: Forecast start year | F16: 2015
C17: Forecast start date | F17: 42005
C19: Forecast period | F19: 3
C21: Business Line 1: | F21: Test
D22: Product Group 1 | F22: Insert Product Group 1
D23: Product Group 2 | F23: Insert Product Group 2
D24: Product Group 3 | F24: Insert Product Group 3
C26: Business Line 2: | F26: Insert Business Line2
D27: Product Group 4 | F27: Insert Product Group4
D28: Product Group 5 | F28: Insert Product Group5
D29: Product Group 6 | F29: Insert Product Group6
C31: Business Line 3: | F31: Insert Business Line3
D32: Product Group 7 | F32: Insert Product Group7
D33: Product Group 8 | F33: Insert Product Group8
D34: Product Group 9 | F34: Insert Product Group9
B36: =Header2 -> 1.2 | C36: General inputs
C38: Unit | F38: £
C40: Tolerance | F40: 0.01
B42: =Header2 -> 1.3 | C42: Working capital assumptions
C44: Average number of months credit given to customers
D45: =F21 -> Test | F45: 0 | G45: months' worth of revenue
D46: =F26 -> Insert Business Line2 | F46: 0 | G46: months' worth of revenue
D47: =F31 -> Insert Business Line3 | F47: 0 | G47: months' worth of revenue
C49: Average number of months credit received from suppliers | F49: 0 | G49: months' worth of total variable costs + central costs (non-staff)
C51: Average months stock kept at warehouse
D52: =F21 -> Test | F52: 0 | G52: months' worth of variable costs
D53: =F26 -> Insert Business Line2 | F53: 0 | G53: months' worth of variable costs
D54: =F31 -> Insert Business Line3 | F54: 0 | G54: months' worth of variable costs
C56: VAT payment | F56: 3 | G56: months
B58: =Header2 -> 1.4 | C58: Capital expenditure assumptions
F60: Type | G60: Reducing balance ratio
D61: Type 1 | F61: ICT equipement | G61: 3
D62: Type 2 | F62: F&F | G62: 5
D63: Type 3 | F63: Property | G63: 25
D64: Type 4 | F64: Vehicles | G64: 3
D65: Type 5 | F65: n/a | G65: 4
B68: =Header2 -> 1.5 | C68: Debt & overdraft financing
C70: Investment | F70: Existing loan | G70: Investment 1 | H70: Investment 2 | I70: Investment 3 | J70: Investment 4 | K70: Investment 5
C71: Drawdown | D71: Should be negative as recognition of liability | F71: na | G71: 0 | H71: 0 | I71: 0 | J71: 0 | K71: 0
C72: Drawdown date | D72: Must be first day of month | F72: =F17 -> 42005 | G72: 41365 | H72: 41456 | I72: 41821 | J72: 41821 | K72: 42186
C73: Debt term (years) | F73: 5 | G73: 2 | H73: 5 | I73: 5 | J73: 5 | K73: 5
C74: Repayment month | D74: Every 1, 2, 3, 4 or 6 months payment made | F74: 1 | G74: 1 | H74: 1 | I74: 1 | J74: 1 | K74: 1
C75: Interest payment month | D75: Every 1, 2, 3, 4 or 6 months payment made | F75: 1 | G75: 1 | H75: 1 | I75: 1 | J75: 1 | K75: 1
C76: Base rate | F76: 0.005 | G76: 0.005 | H76: 0.005 | I76: 0.005 | J76: 0.005 | K76: 0.005
C77: Rate above base rate | F77: 0.045 | G77: 0.03 | H77: 0.03 | I77: 0.03 | J77: 0.03 | K77: 0.03
C78: Interest rate % per annum | F78: =F77+F76 -> 0.05 | G78: =G77+G76 -> 0.035 | H78: =H77+H76 -> 0.035 | I78: =I77+I76 -> 0.035 | J78: =J77+J76 -> 0.035 | K78: =K77+K76 -> 0.035
C80: Overdraft interest rate | F80: 0
C81: Cash interest rate | F81: 0
B83: =Header2 -> 1.6 | C83: Grant income
C85: Investment | F85: Existing Grant | G85: Grant 1 | H85: Grant 2 | I85: Grant 3 | J85: Grant 4 | K85: Grant 5
C86: Drawdown | D86: Should be negative as recognition of liability | F86: na
C87: Drawdown date | D87: Must be first day of month | F87: =F17 -> 42005 | G87: 41395 | H87: 41548 | I87: 41456 | J87: 41974 | K87: 42186
C88: Grant term (years) | F88: 5 | G88: 5 | H88: 5 | I88: 5 | J88: 5 | K88: 5
B90: =Header2 -> 1.7 | C90: TAX inputs
C92: NI Employers' contribution | F92: 0.138 | G92: of gross salary
C94: Pension contribution | F94: 0 | G94: of gross salary
C96: Corporation tax rate | F96: 0.2 | G96: of profit before tax
C98: First corporate tax payment date | F98: 42094
C100: VAT rate | F100: 0.2
C101: VAT payment month | F101: 3
C103: Tax loss account | D103: =unit -> £ | F103: 0
A105: =Header1 -> 2 | B105: Actual balance sheet
C107: Year | E107: =$E$5 -> 2012 | F107: =$F$5 -> 2013 | G107: =$G$5 -> 2014
C108: Period starts | E108: =$E$7 -> 40909 | F108: =$F$7 -> 41275 | G108: =$G$7 -> 41640
C109: Period ends | E109: =$E$8 -> 41274 | F109: =$F$8 -> 41639 | G109: =$G$8 -> 42004
C111: Fixed assets | D111: =unit -> £ | E111: =SUM(E112:E116) -> 0 | F111: =SUM(F112:F116) -> 0 | G111: =SUM(G112:G116) -> 0
C112: =KeyInputs!F61 -> ICT equipement | D112: =unit -> £ | G112: 0
C113: =KeyInputs!F62 -> F&F | D113: =unit -> £ | G113: 0
C114: =KeyInputs!F63 -> Property | D114: =unit -> £ | G114: 0
C115: =KeyInputs!F64 -> Vehicles | D115: =unit -> £ | G115: 0
C116: =KeyInputs!F65 -> n/a | D116: =unit -> £ | G116: 0
C118: Trade debtors | D118: =unit -> £ | E118: =SUM(E119:E121) -> 0 | F118: =SUM(F119:F121) -> 0 | G118: =SUM(G119:G121) -> 0
C119: =WorkingCapital!C14 -> Test | D119: =unit -> £ | G119: 0
C120: =WorkingCapital!C25 -> Insert Business Line2 | D120: =unit -> £
C121: =WorkingCapital!C36 -> Insert Business Line3 | D121: =unit -> £ | G121: 0
C123: Stocks | D123: =unit -> £ | E123: =SUM(E124:E126) -> 0 | F123: =SUM(F124:F126) -> 0 | G123: =SUM(G124:G126) -> 0
C124: =WorkingCapital!C49 -> Test | D124: =unit -> £ | G124: 0
C125: =WorkingCapital!C60 -> Insert Business Line2 | D125: =unit -> £ | G125: 0
C126: =WorkingCapital!C71 -> Insert Business Line3 | D126: =unit -> £ | G126: 0
C128: Cash at bank | D128: =unit -> £ | F128: 0
C130: Overdraft | D130: =unit -> £ | F130: 0 | G130: 0
C131: Trade creditors | D131: =unit -> £
C132: VAT | D132: =unit -> £
C133: Interest on debt payable | D133: =unit -> £ | G133: 0
C134: Term debt | D134: =unit -> £ | G134: 0
C135: Grant deferred income | D135: =unit -> £ | G135: 0
C136: Current tax | D136: =unit -> £ | G136: 0
C138: Net assets | D138: =unit -> £ | E138: =SUM(E130:E137,E128,E123,E118,E111) -> 0 | F138: =SUM(F130:F137,F128,F123,F118,F111) -> 0 | G138: =SUM(G130:G137,G128,G123,G118,G111) -> 0
C140: Share capital | D140: =unit -> £
C141: P&L reserve | D141: =unit -> £
C143: Shareholders' funds | D143: =unit -> £ | E143: =SUM(E140:E142) -> 0 | F143: =SUM(F140:F142) -> 0 | G143: =SUM(G140:G142) -> 0
...

Sheet Inputs - Sensitivities
A3: =IF(KeyInputs!$F$14=0,"Company Name",KeyInputs!$F$14) -> Company Name
A4: Sensitivities
D5: =KeyInputs!D5 -> Year | E5: =KeyInputs!H5 -> 2015 | F5: =KeyInputs!I5 -> 2016 | G5: =KeyInputs!J5 -> 2017 | H5: =KeyInputs!K5 -> 2018 | I5: =KeyInputs!L5 -> 2019 | K5: =KeyInputs!N5 -> 2015 | L5: =KeyInputs!O5 -> 2015 | M5: =KeyInputs!P5 -> 2015 | N5: =KeyInputs!Q5 -> 2015 | O5: =KeyInputs!R5 -> 2015 | P5: =KeyInputs!S5 -> 2015 | Q5: =KeyInputs!T5 -> 2015 | R5: =KeyInputs!U5 -> 2015 | ... BR5: =KeyInputs!BU5 -> 2019
D6: =KeyInputs!D6 -> Period number | E6: =KeyInputs!H6 -> 1 | F6: =KeyInputs!I6 -> 2 | G6: =KeyInputs!J6 -> 3 | H6: =KeyInputs!K6 -> 4 | I6: =KeyInputs!L6 -> 5 | K6: =KeyInputs!N6 -> 1 | L6: =KeyInputs!O6 -> 2 | M6: =KeyInputs!P6 -> 3 | N6: =KeyInputs!Q6 -> 4 | O6: =KeyInputs!R6 -> 5 | P6: =KeyInputs!S6 -> 6 | Q6: =KeyInputs!T6 -> 7 | R6: =KeyInputs!U6 -> 8 | ... BR6: =KeyInputs!BU6 -> 60
D7: =KeyInputs!D7 -> Period starts | E7: =KeyInputs!H7 -> 42005 | F7: =KeyInputs!I7 -> 42370 | G7: =KeyInputs!J7 -> 42736 | H7: =KeyInputs!K7 -> 43101 | I7: =KeyInputs!L7 -> 43466 | K7: =KeyInputs!N7 -> 42005 | L7: =KeyInputs!O7 -> 42036 | M7: =KeyInputs!P7 -> 42064 | N7: =KeyInputs!Q7 -> 42095 | O7: =KeyInputs!R7 -> 42125 | P7: =KeyInputs!S7 -> 42156 | Q7: =KeyInputs!T7 -> 42186 | R7: =KeyInputs!U7 -> 42217 | ... BR7: =KeyInputs!BU7 -> 43800
B8: =IF(Check!$C$12=0,"All checks are OK","There are "&Check!$C$12&" error/errors") -> All checks are OK | D8: =KeyInputs!D8 -> Period ends | E8: =KeyInputs!H8 -> 42369 | F8: =KeyInputs!I8 -> 42735 | G8: =KeyInputs!J8 -> 43100 | H8: =KeyInputs!K8 -> 43465 | I8: =KeyInputs!L8 -> 43830 | K8: =KeyInputs!N8 -> 42035 | L8: =KeyInputs!O8 -> 42063 | M8: =KeyInputs!P8 -> 42094 | N8: =KeyInputs!Q8 -> 42124 | O8: =KeyInputs!R8 -> 42155 | P8: =KeyInputs!S8 -> 42185 | Q8: =KeyInputs!T8 -> 42216 | R8: =KeyInputs!U8 -> 42247 | ... BR8: =KeyInputs!BU8 -> 43830
A9: Sensitivity 1
B10: Product | C10: =Revenue!C35 -> Insert Product Group 1
B11: Variable | C11: Volume
B13: Scenario selected | C13: Base | E13: =SUMIF($K$5:$BR$5,E$5,$K13:$BR13) -> 0 | F13: =SUMIF($K$5:$BR$5,F$5,$K13:$BR13) -> 0 | G13: =SUMIF($K$5:$BR$5,G$5,$K13:$BR13) -> 0 | H13: =SUMIF($K$5:$BR$5,H$5,$K13:$BR13) -> 0 | I13: =SUMIF($K$5:$BR$5,I$5,$K13:$BR13) -> 0 | K13: =INDEX($K$15:$BR$17,MATCH($C$13,$B$15:$B$17,0),0) -> 0 | L13: =INDEX($K$15:$BR$17,MATCH($C$13,$B$15:$B$17,0),0) -> 0 | M13: =INDEX($K$15:$BR$17,MATCH($C$13,$B$15:$B$17,0),0) -> 0 | N13: =INDEX($K$15:$BR$17,MATCH($C$13,$B$15:$B$17,0),0) -> 0 | O13: =INDEX($K$15:$BR$17,MATCH($C$13,$B$15:$B$17,0),0) -> 0 | P13: =INDEX($K$15:$BR$17,MATCH($C$13,$B$15:$B$17,0),0) -> 0 | Q13: =INDEX($K$15:$BR$17,MATCH($C$13,$B$15:$B$17,0),0) -> 0 | R13: =INDEX($K$15:$BR$17,MATCH($C$13,$B$15:$B$17,0),0) -> 0 | ... BR13: =INDEX($K$15:$BR$17,MATCH($C$13,$B$15:$B$17,0),0) -> 0
B15: Upside | C15: 0.1 | E15: =SUMIF($K$5:$BR$5,E$5,$K15:$BR15) -> 0 | F15: =SUMIF($K$5:$BR$5,F$5,$K15:$BR15) -> 0 | G15: =SUMIF($K$5:$BR$5,G$5,$K15:$BR15) -> 0 | H15: =SUMIF($K$5:$BR$5,H$5,$K15:$BR15) -> 0 | I15: =SUMIF($K$5:$BR$5,I$5,$K15:$BR15) -> 0 | K15: =K16*(1+$C15) -> 0 | L15: =L16*(1+$C15) -> 0 | M15: =M16*(1+$C15) -> 0 | N15: =N16*(1+$C15) -> 0 | O15: =O16*(1+$C15) -> 0 | P15: =P16*(1+$C15) -> 0 | Q15: =Q16*(1+$C15) -> 0 | R15: =R16*(1+$C15) -> 0 | ... BR15: =BR16*(1+$C15) -> 0
B16: Base | C16: 0 | E16: =SUMIF($K$5:$BR$5,E$5,$K16:$BR16) -> 0 | F16: =SUMIF($K$5:$BR$5,F$5,$K16:$BR16) -> 0 | G16: =SUMIF($K$5:$BR$5,G$5,$K16:$BR16) -> 0 | H16: =SUMIF($K$5:$BR$5,H$5,$K16:$BR16) -> 0 | I16: =SUMIF($K$5:$BR$5,I$5,$K16:$BR16) -> 0
B17: Downside | C17: -0.1 | E17: =SUMIF($K$5:$BR$5,E$5,$K17:$BR17) -> 0 | F17: =SUMIF($K$5:$BR$5,F$5,$K17:$BR17) -> 0 | G17: =SUMIF($K$5:$BR$5,G$5,$K17:$BR17) -> 0 | H17: =SUMIF($K$5:$BR$5,H$5,$K17:$BR17) -> 0 | I17: =SUMIF($K$5:$BR$5,I$5,$K17:$BR17) -> 0 | K17: =K16*(1+$C17) -> 0 | L17: =L16*(1+$C17) -> 0 | M17: =M16*(1+$C17) -> 0 | N17: =N16*(1+$C17) -> 0 | O17: =O16*(1+$C17) -> 0 | P17: =P16*(1+$C17) -> 0 | Q17: =Q16*(1+$C17) -> 0 | R17: =R16*(1+$C17) -> 0 | ... BR17: =BR16*(1+$C17) -> 0
A19: Sensitivity 2
B20: Product | C20: =KeyInputs!F22 -> Insert Product Group 1
B21: Variable | C21: Product cost
B23: Scenario selected | C23: Base | E23: =SUMIF($K$5:$BR$5,E$5,$K23:$BR23) -> 0 | F23: =SUMIF($K$5:$BR$5,F$5,$K23:$BR23) -> 0 | G23: =SUMIF($K$5:$BR$5,G$5,$K23:$BR23) -> 0 | H23: =SUMIF($K$5:$BR$5,H$5,$K23:$BR23) -> 0 | I23: =SUMIF($K$5:$BR$5,I$5,$K23:$BR23) -> 0 | K23: =INDEX($K$25:$BR$27,MATCH($C$23,$B$25:$B$27,0),0) -> 0 | L23: =INDEX($K$25:$BR$27,MATCH($C$23,$B$25:$B$27,0),0) -> 0 | M23: =INDEX($K$25:$BR$27,MATCH($C$23,$B$25:$B$27,0),0) -> 0 | N23: =INDEX($K$25:$BR$27,MATCH($C$23,$B$25:$B$27,0),0) -> 0 | O23: =INDEX($K$25:$BR$27,MATCH($C$23,$B$25:$B$27,0),0) -> 0 | P23: =INDEX($K$25:$BR$27,MATCH($C$23,$B$25:$B$27,0),0) -> 0 | Q23: =INDEX($K$25:$BR$27,MATCH($C$23,$B$25:$B$27,0),0) -> 0 | R23: =INDEX($K$25:$BR$27,MATCH($C$23,$B$25:$B$27,0),0) -> 0 | ... BR23: =INDEX($K$25:$BR$27,MATCH($C$23,$B$25:$B$27,0),0) -> 0
B25: Upside | C25: 0.1 | E25: =SUMIF($K$5:$BR$5,E$5,$K25:$BR25) -> 0 | F25: =SUMIF($K$5:$BR$5,F$5,$K25:$BR25) -> 0 | G25: =SUMIF($K$5:$BR$5,G$5,$K25:$BR25) -> 0 | H25: =SUMIF($K$5:$BR$5,H$5,$K25:$BR25) -> 0 | I25: =SUMIF($K$5:$BR$5,I$5,$K25:$BR25) -> 0 | K25: =K26*(1+$C25) -> 0 | L25: =L26*(1+$C25) -> 0 | M25: =M26*(1+$C25) -> 0 | N25: =N26*(1+$C25) -> 0 | O25: =O26*(1+$C25) -> 0 | P25: =P26*(1+$C25) -> 0 | Q25: =Q26*(1+$C25) -> 0 | R25: =R26*(1+$C25) -> 0 | ... BR25: =BR26*(1+$C25) -> 0
B26: Base | C26: 0 | E26: =SUMIF($K$5:$BR$5,E$5,$K26:$BR26) -> 0 | F26: =SUMIF($K$5:$BR$5,F$5,$K26:$BR26) -> 0 | G26: =SUMIF($K$5:$BR$5,G$5,$K26:$BR26) -> 0 | H26: =SUMIF($K$5:$BR$5,H$5,$K26:$BR26) -> 0 | I26: =SUMIF($K$5:$BR$5,I$5,$K26:$BR26) -> 0
B27: Downside | C27: -0.1 | E27: =SUMIF($K$5:$BR$5,E$5,$K27:$BR27) -> 0 | F27: =SUMIF($K$5:$BR$5,F$5,$K27:$BR27) -> 0 | G27: =SUMIF($K$5:$BR$5,G$5,$K27:$BR27) -> 0 | H27: =SUMIF($K$5:$BR$5,H$5,$K27:$BR27) -> 0 | I27: =SUMIF($K$5:$BR$5,I$5,$K27:$BR27) -> 0 | K27: =K26*(1+$C27) -> 0 | L27: =L26*(1+$C27) -> 0 | M27: =M26*(1+$C27) -> 0 | N27: =N26*(1+$C27) -> 0 | O27: =O26*(1+$C27) -> 0 | P27: =P26*(1+$C27) -> 0 | Q27: =Q26*(1+$C27) -> 0 | R27: =R26*(1+$C27) -> 0 | ... BR27: =BR26*(1+$C27) -> 0
A29: Sensitivity 3
B30: Product | C30: Insert sensitivity
B31: Variable | C31: Insert variable
B33: Scenario selected | C33: Base | E33: =SUMIF($K$5:$BR$5,E$5,$K33:$BR33) -> 0 | F33: =SUMIF($K$5:$BR$5,F$5,$K33:$BR33) -> 0 | G33: =SUMIF($K$5:$BR$5,G$5,$K33:$BR33) -> 0 | H33: =SUMIF($K$5:$BR$5,H$5,$K33:$BR33) -> 0 | I33: =SUMIF($K$5:$BR$5,I$5,$K33:$BR33) -> 0 | K33: =INDEX($K$35:$BR$37,MATCH($C$33,$B$35:$B$37,0),0) -> 0 | L33: =INDEX($K$35:$BR$37,MATCH($C$33,$B$35:$B$37,0),0) -> 0 | M33: =INDEX($K$35:$BR$37,MATCH($C$33,$B$35:$B$37,0),0) -> 0 | N33: =INDEX($K$35:$BR$37,MATCH($C$33,$B$35:$B$37,0),0) -> 0 | O33: =INDEX($K$35:$BR$37,MATCH($C$33,$B$35:$B$37,0),0) -> 0 | P33: =INDEX($K$35:$BR$37,MATCH($C$33,$B$35:$B$37,0),0) -> 0 | Q33: =INDEX($K$35:$BR$37,MATCH($C$33,$B$35:$B$37,0),0) -> 0 | R33: =INDEX($K$35:$BR$37,MATCH($C$33,$B$35:$B$37,0),0) -> 0 | ... BR33: =INDEX($K$35:$BR$37,MATCH($C$33,$B$35:$B$37,0),0) -> 0
B35: Upside | C35: 0.1 | E35: =SUMIF($K$5:$BR$5,E$5,$K35:$BR35) -> 0 | F35: =SUMIF($K$5:$BR$5,F$5,$K35:$BR35) -> 0 | G35: =SUMIF($K$5:$BR$5,G$5,$K35:$BR35) -> 0 | H35: =SUMIF($K$5:$BR$5,H$5,$K35:$BR35) -> 0 | I35: =SUMIF($K$5:$BR$5,I$5,$K35:$BR35) -> 0 | K35: =K36*(1+$C35) -> 0 | L35: =L36*(1+$C35) -> 0 | M35: =M36*(1+$C35) -> 0 | N35: =N36*(1+$C35) -> 0 | O35: =O36*(1+$C35) -> 0 | P35: =P36*(1+$C35) -> 0 | Q35: =Q36*(1+$C35) -> 0 | R35: =R36*(1+$C35) -> 0 | ... BR35: =BR36*(1+$C35) -> 0
B36: Base | C36: 0 | E36: =SUMIF($K$5:$BR$5,E$5,$K36:$BR36) -> 0 | F36: =SUMIF($K$5:$BR$5,F$5,$K36:$BR36) -> 0 | G36: =SUMIF($K$5:$BR$5,G$5,$K36:$BR36) -> 0 | H36: =SUMIF($K$5:$BR$5,H$5,$K36:$BR36) -> 0 | I36: =SUMIF($K$5:$BR$5,I$5,$K36:$BR36) -> 0
B37: Downside | C37: -0.1 | E37: =SUMIF($K$5:$BR$5,E$5,$K37:$BR37) -> 0 | F37: =SUMIF($K$5:$BR$5,F$5,$K37:$BR37) -> 0 | G37: =SUMIF($K$5:$BR$5,G$5,$K37:$BR37) -> 0 | H37: =SUMIF($K$5:$BR$5,H$5,$K37:$BR37) -> 0 | I37: =SUMIF($K$5:$BR$5,I$5,$K37:$BR37) -> 0 | K37: =K36*(1+$C37) -> 0 | L37: =L36*(1+$C37) -> 0 | M37: =M36*(1+$C37) -> 0 | N37: =N36*(1+$C37) -> 0 | O37: =O36*(1+$C37) -> 0 | P37: =P36*(1+$C37) -> 0 | Q37: =Q36*(1+$C37) -> 0 | R37: =R36*(1+$C37) -> 0 | ... BR37: =BR36*(1+$C37) -> 0
A39: Sensitivity 4
B40: Product | C40: Insert sensitivity
B41: Variable | C41: Insert variable
B43: Scenario selected | C43: Base | E43: =SUMIF($K$5:$BR$5,E$5,$K43:$BR43) -> 0 | F43: =SUMIF($K$5:$BR$5,F$5,$K43:$BR43) -> 0 | G43: =SUMIF($K$5:$BR$5,G$5,$K43:$BR43) -> 0 | H43: =SUMIF($K$5:$BR$5,H$5,$K43:$BR43) -> 0 | I43: =SUMIF($K$5:$BR$5,I$5,$K43:$BR43) -> 0 | K43: =INDEX($K$45:$BR$47,MATCH($C$43,$B$45:$B$47,0),0) -> 0 | L43: =INDEX($K$45:$BR$47,MATCH($C$43,$B$45:$B$47,0),0) -> 0 | M43: =INDEX($K$45:$BR$47,MATCH($C$43,$B$45:$B$47,0),0) -> 0 | N43: =INDEX($K$45:$BR$47,MATCH($C$43,$B$45:$B$47,0),0) -> 0 | O43: =INDEX($K$45:$BR$47,MATCH($C$43,$B$45:$B$47,0),0) -> 0 | P43: =INDEX($K$45:$BR$47,MATCH($C$43,$B$45:$B$47,0),0) -> 0 | Q43: =INDEX($K$45:$BR$47,MATCH($C$43,$B$45:$B$47,0),0) -> 0 | R43: =INDEX($K$45:$BR$47,MATCH($C$43,$B$45:$B$47,0),0) -> 0 | ... BR43: =INDEX($K$45:$BR$47,MATCH($C$43,$B$45:$B$47,0),0) -> 0
B45: Upside | C45: 0.1 | E45: =SUMIF($K$5:$BR$5,E$5,$K45:$BR45) -> 0 | F45: =SUMIF($K$5:$BR$5,F$5,$K45:$BR45) -> 0 | G45: =SUMIF($K$5:$BR$5,G$5,$K45:$BR45) -> 0 | H45: =SUMIF($K$5:$BR$5,H$5,$K45:$BR45) -> 0 | I45: =SUMIF($K$5:$BR$5,I$5,$K45:$BR45) -> 0 | K45: =K46*(1+$C45) -> 0 | L45: =L46*(1+$C45) -> 0 | M45: =M46*(1+$C45) -> 0 | N45: =N46*(1+$C45) -> 0 | O45: =O46*(1+$C45) -> 0 | P45: =P46*(1+$C45) -> 0 | Q45: =Q46*(1+$C45) -> 0 | R45: =R46*(1+$C45) -> 0 | ... BR45: =BR46*(1+$C45) -> 0
B46: Base | C46: 0 | E46: =SUMIF($K$5:$BR$5,E$5,$K46:$BR46) -> 0 | F46: =SUMIF($K$5:$BR$5,F$5,$K46:$BR46) -> 0 | G46: =SUMIF($K$5:$BR$5,G$5,$K46:$BR46) -> 0 | H46: =SUMIF($K$5:$BR$5,H$5,$K46:$BR46) -> 0 | I46: =SUMIF($K$5:$BR$5,I$5,$K46:$BR46) -> 0
B47: Downside | C47: -0.1 | E47: =SUMIF($K$5:$BR$5,E$5,$K47:$BR47) -> 0 | F47: =SUMIF($K$5:$BR$5,F$5,$K47:$BR47) -> 0 | G47: =SUMIF($K$5:$BR$5,G$5,$K47:$BR47) -> 0 | H47: =SUMIF($K$5:$BR$5,H$5,$K47:$BR47) -> 0 | I47: =SUMIF($K$5:$BR$5,I$5,$K47:$BR47) -> 0 | K47: =K46*(1+$C47) -> 0 | L47: =L46*(1+$C47) -> 0 | M47: =M46*(1+$C47) -> 0 | N47: =N46*(1+$C47) -> 0 | O47: =O46*(1+$C47) -> 0 | P47: =P46*(1+$C47) -> 0 | Q47: =Q46*(1+$C47) -> 0 | R47: =R46*(1+$C47) -> 0 | ... BR47: =BR46*(1+$C47) -> 0
A49: Sensitivity 5
B50: Product | C50: Insert sensitivity
B51: Variable | C51: Insert variable
B53: Scenario selected | C53: Base | E53: =SUMIF($K$5:$BR$5,E$5,$K53:$BR53) -> 0 | F53: =SUMIF($K$5:$BR$5,F$5,$K53:$BR53) -> 0 | G53: =SUMIF($K$5:$BR$5,G$5,$K53:$BR53) -> 0 | H53: =SUMIF($K$5:$BR$5,H$5,$K53:$BR53) -> 0 | I53: =SUMIF($K$5:$BR$5,I$5,$K53:$BR53) -> 0 | K53: =INDEX($K$55:$BR$57,MATCH($C$53,$B$55:$B$57,0),0) -> 0 | L53: =INDEX($K$55:$BR$57,MATCH($C$53,$B$55:$B$57,0),0) -> 0 | M53: =INDEX($K$55:$BR$57,MATCH($C$53,$B$55:$B$57,0),0) -> 0 | N53: =INDEX($K$55:$BR$57,MATCH($C$53,$B$55:$B$57,0),0) -> 0 | O53: =INDEX($K$55:$BR$57,MATCH($C$53,$B$55:$B$57,0),0) -> 0 | P53: =INDEX($K$55:$BR$57,MATCH($C$53,$B$55:$B$57,0),0) -> 0 | Q53: =INDEX($K$55:$BR$57,MATCH($C$53,$B$55:$B$57,0),0) -> 0 | R53: =INDEX($K$55:$BR$57,MATCH($C$53,$B$55:$B$57,0),0) -> 0 | ... BR53: =INDEX($K$55:$BR$57,MATCH($C$53,$B$55:$B$57,0),0) -> 0
B55: Upside | C55: 0.1 | E55: =SUMIF($K$5:$BR$5,E$5,$K55:$BR55) -> 0 | F55: =SUMIF($K$5:$BR$5,F$5,$K55:$BR55) -> 0 | G55: =SUMIF($K$5:$BR$5,G$5,$K55:$BR55) -> 0 | H55: =SUMIF($K$5:$BR$5,H$5,$K55:$BR55) -> 0 | I55: =SUMIF($K$5:$BR$5,I$5,$K55:$BR55) -> 0 | K55: =K56*(1+$C55) -> 0 | L55: =L56*(1+$C55) -> 0 | M55: =M56*(1+$C55) -> 0 | N55: =N56*(1+$C55) -> 0 | O55: =O56*(1+$C55) -> 0 | P55: =P56*(1+$C55) -> 0 | Q55: =Q56*(1+$C55) -> 0 | R55: =R56*(1+$C55) -> 0 | ... BR55: =BR56*(1+$C55) -> 0
B56: Base | C56: 0 | E56: =SUMIF($K$5:$BR$5,E$5,$K56:$BR56) -> 0 | F56: =SUMIF($K$5:$BR$5,F$5,$K56:$BR56) -> 0 | G56: =SUMIF($K$5:$BR$5,G$5,$K56:$BR56) -> 0 | H56: =SUMIF($K$5:$BR$5,H$5,$K56:$BR56) -> 0 | I56: =SUMIF($K$5:$BR$5,I$5,$K56:$BR56) -> 0
B57: Downside | C57: -0.1 | E57: =SUMIF($K$5:$BR$5,E$5,$K57:$BR57) -> 0 | F57: =SUMIF($K$5:$BR$5,F$5,$K57:$BR57) -> 0 | G57: =SUMIF($K$5:$BR$5,G$5,$K57:$BR57) -> 0 | H57: =SUMIF($K$5:$BR$5,H$5,$K57:$BR57) -> 0 | I57: =SUMIF($K$5:$BR$5,I$5,$K57:$BR57) -> 0 | K57: =K56*(1+$C57) -> 0 | L57: =L56*(1+$C57) -> 0 | M57: =M56*(1+$C57) -> 0 | N57: =N56*(1+$C57) -> 0 | O57: =O56*(1+$C57) -> 0 | P57: =P56*(1+$C57) -> 0 | Q57: =Q56*(1+$C57) -> 0 | R57: =R56*(1+$C57) -> 0 | ... BR57: =BR56*(1+$C57) -> 0

Sheet Worksheet
B1: Jan
A2: Feb
A3: Mar
A4: Apr
A5: May
A6: Jun
A7: Jul
A8: Aug
A9: Sep
A10: Oct
A11: Nov | M11: `
A12: Dec
A14: Jan | B14: Feb | C14: Mar | D14: Apr | E14: May | F14: Jun | G14: Jul | H14: Aug | I14: Sep | J14: Oct | K14: Nov | L14: Dec | M14: Jan | N14: Feb | O14: Mar | P14: Apr | Q14: May | R14: Jun | S14: Jul | T14: Aug | U14: Sep | V14: Oct | W14: Nov | X14: Dec | Y14: Jan | Z14: Feb | AA14: Mar | AB14: Apr | AC14: May | AD14: Jun | AE14: Jul | AF14: Aug | AG14: Sep | AH14: Oct | AI14: Nov | AJ14: Dec | AK14: Jan | AL14: Feb | AM14: Mar | AN14: Apr | AO14: May | AP14: Jun | AQ14: Jul | AR14: Aug | AS14: Sep | AT14: Oct | AU14: Nov | AV14: Dec | AW14: Jan | AX14: Feb | AY14: Mar | AZ14: Apr | BA14: May | BB14: Jun | BC14: Jul | BD14: Aug | BE14: Sep | BF14: Oct | BG14: Nov | BH14: Dec
A15: 1 | B15: =A15+1 -> 2 | C15: =B15+1 -> 3 | D15: =C15+1 -> 4 | E15: =D15+1 -> 5 | F15: =E15+1 -> 6 | G15: =F15+1 -> 7 | H15: =G15+1 -> 8 | I15: =H15+1 -> 9 | ... BH15: =BG15+1 -> 60
A16: =ADDRESS(3,4) -> $D$3
A17: =OFFSET(A14,,HLOOKUP(KeyInputs!#REF!,A14:L15,2,FALSE)) -> #REF!

Sheet Prod Sales
A1: =KeyInputs!F14 -> 0
A2: Volume Sales Projections By Product Group
C4: =KeyInputs!F17 -> 42005 | P4: =KeyInputs!F17+1 -> 42006 | AC4: =KeyInputs!F17+2 -> 42007
C5: =KeyInputs!#REF! -> #REF! | D5: =OFFSET(Worksheet!$A$14,,(HLOOKUP(KeyInputs!#REF!,Worksheet!$A$14:$L$15,2,FALSE))) -> #REF! | E5: =OFFSET(Worksheet!$A$14,,(HLOOKUP(KeyInputs!#REF!,Worksheet!$A$14:$L$15,2,FALSE))+Worksheet!A15) -> #REF! | F5: =OFFSET(Worksheet!$A$14,,(HLOOKUP(KeyInputs!#REF!,Worksheet!$A$14:$L$15,2,FALSE))+Worksheet!B15) -> #REF! | G5: =OFFSET(Worksheet!$A$14,,(HLOOKUP(KeyInputs!#REF!,Worksheet!$A$14:$L$15,2,FALSE))+Worksheet!C15) -> #REF! | H5: =OFFSET(Worksheet!$A$14,,(HLOOKUP(KeyInputs!#REF!,Worksheet!$A$14:$L$15,2,FALSE))+Worksheet!D15) -> #REF! | I5: =OFFSET(Worksheet!$A$14,,(HLOOKUP(KeyInputs!#REF!,Worksheet!$A$14:$L$15,2,FALSE))+Worksheet!E15) -> #REF! | J5: =OFFSET(Worksheet!$A$14,,(HLOOKUP(KeyInputs!#REF!,Worksheet!$A$14:$L$15,2,FALSE))+Worksheet!F15) -> #REF! | K5: =OFFSET(Worksheet!$A$14,,(HLOOKUP(KeyInputs!#REF!,Worksheet!$A$14:$L$15,2,FALSE))+Worksheet!G15) -> #REF! | L5: =OFFSET(Worksheet!$A$14,,(HLOOKUP(KeyInputs!#REF!,Worksheet!$A$14:$L$15,2,FALSE))+Worksheet!H15) -> #REF! | ... N5: =OFFSET(Worksheet!$A$14,,(HLOOKUP(KeyInputs!#REF!,Worksheet!$A$14:$L$15,2,FALSE))+Worksheet!J15) -> #REF! | P5: =KeyInputs!#REF! -> #REF! | Q5: =OFFSET(Worksheet!$A$14,,(HLOOKUP(KeyInputs!#REF!,Worksheet!$A$14:$L$15,2,FALSE))) -> #REF! | R5: =OFFSET(Worksheet!$A$14,,(HLOOKUP(KeyInputs!#REF!,Worksheet!$A$14:$L$15,2,FALSE))+Worksheet!A15) -> #REF! | S5: =OFFSET(Worksheet!$A$14,,(HLOOKUP(KeyInputs!#REF!,Worksheet!$A$14:$L$15,2,FALSE))+Worksheet!B15) -> #REF! | T5: =OFFSET(Worksheet!$A$14,,(HLOOKUP(KeyInputs!#REF!,Worksheet!$A$14:$L$15,2,FALSE))+Worksheet!C15) -> #REF! | U5: =OFFSET(Worksheet!$A$14,,(HLOOKUP(KeyInputs!#REF!,Worksheet!$A$14:$L$15,2,FALSE))+Worksheet!D15) -> #REF! | V5: =OFFSET(Worksheet!$A$14,,(HLOOKUP(KeyInputs!#REF!,Worksheet!$A$14:$L$15,2,FALSE))+Worksheet!E15) -> #REF! | W5: =OFFSET(Worksheet!$A$14,,(HLOOKUP(KeyInputs!#REF!,Worksheet!$A$14:$L$15,2,FALSE))+Worksheet!F15) -> #REF! | X5: =OFFSET(Worksheet!$A$14,,(HLOOKUP(KeyInputs!#REF!,Worksheet!$A$14:$L$15,2,FALSE))+Worksheet!G15) -> #REF! | Y5: =OFFSET(Worksheet!$A$14,,(HLOOKUP(KeyInputs!#REF!,Worksheet!$A$14:$L$15,2,FALSE))+Worksheet!H15) -> #REF! | ... AA5: =OFFSET(Worksheet!$A$14,,(HLOOKUP(KeyInputs!#REF!,Worksheet!$A$14:$L$15,2,FALSE))+Worksheet!J15) -> #REF! | AC5: =KeyInputs!#REF! -> #REF! | AD5: =OFFSET(Worksheet!$A$14,,(HLOOKUP(KeyInputs!#REF!,Worksheet!$A$14:$L$15,2,FALSE))) -> #REF! | AE5: =OFFSET(Worksheet!$A$14,,(HLOOKUP(KeyInputs!#REF!,Worksheet!$A$14:$L$15,2,FALSE))+Worksheet!A15) -> #REF! | AF5: =OFFSET(Worksheet!$A$14,,(HLOOKUP(KeyInputs!#REF!,Worksheet!$A$14:$L$15,2,FALSE))+Worksheet!B15) -> #REF! | AG5: =OFFSET(Worksheet!$A$14,,(HLOOKUP(KeyInputs!#REF!,Worksheet!$A$14:$L$15,2,FALSE))+Worksheet!C15) -> #REF! | AH5: =OFFSET(Worksheet!$A$14,,(HLOOKUP(KeyInputs!#REF!,Worksheet!$A$14:$L$15,2,FALSE))+Worksheet!D15) -> #REF! | AI5: =OFFSET(Worksheet!$A$14,,(HLOOKUP(KeyInputs!#REF!,Worksheet!$A$14:$L$15,2,FALSE))+Worksheet!E15) -> #REF! | AJ5: =OFFSET(Worksheet!$A$14,,(HLOOKUP(KeyInputs!#REF!,Worksheet!$A$14:$L$15,2,FALSE))+Worksheet!F15) -> #REF! | AK5: =OFFSET(Worksheet!$A$14,,(HLOOKUP(KeyInputs!#REF!,Worksheet!$A$14:$L$15,2,FALSE))+Worksheet!G15) -> #REF! | AL5: =OFFSET(Worksheet!$A$14,,(HLOOKUP(KeyInputs!#REF!,Worksheet!$A$14:$L$15,2,FALSE))+Worksheet!H15) -> #REF! | ... AN5: =OFFSET(Worksheet!$A$14,,(HLOOKUP(KeyInputs!#REF!,Worksheet!$A$14:$L$15,2,FALSE))+Worksheet!J15) -> #REF!
A6: =KeyInputs!F21 -> Test
B7: =KeyInputs!F22 -> Insert Product Group 1 | C7: 11531.116 | D7: 11531.116 | E7: 11531.116 | F7: 14483.952 | G7: 14483.952 | H7: 14483.952 | I7: 20481.01 | J7: 24936.109 | K7: 28431.394 | L7: 35099.394 | M7: 47096.187 | N7: 34099.884 | P7: 34099.884 | Q7: 34099.884 | R7: 38613.638 | S7: 38613.638 | T7: 42429.823 | U7: 42429.823 | V7: 47009.244 | W7: 47009.244 | X7: 52504.55 | Y7: 52504.55 | Z7: 52504.55 | AA7: 52504.55
B8: =KeyInputs!F23 -> Insert Product Group 2
B9: =KeyInputs!F24 -> Insert Product Group 3
A11: =KeyInputs!F26 -> Insert Business Line2
B12: =KeyInputs!F27 -> Insert Product Group4
B13: =KeyInputs!F28 -> Insert Product Group5
B14: =KeyInputs!F29 -> Insert Product Group6
A16: =KeyInputs!F31 -> Insert Business Line3
B17: =KeyInputs!F32 -> Insert Product Group7
B18: =KeyInputs!F33 -> Insert Product Group8
B19: =KeyInputs!F34 -> Insert Product Group9
C21: =SUM(C7:C19) -> 11531.116 | D21: =SUM(D7:D19) -> 11531.116 | E21: =SUM(E7:E19) -> 11531.116 | F21: =SUM(F7:F19) -> 14483.952 | G21: =SUM(G7:G19) -> 14483.952 | H21: =SUM(H7:H19) -> 14483.952 | I21: =SUM(I7:I19) -> 20481.01 | J21: =SUM(J7:J19) -> 24936.109 | ... N21: =SUM(N7:N19) -> 34099.884 | P21: =SUM(P7:P19) -> 34099.884 | Q21: =SUM(Q7:Q19) -> 34099.884 | R21: =SUM(R7:R19) -> 38613.638 | S21: =SUM(S7:S19) -> 38613.638 | T21: =SUM(T7:T19) -> 42429.823 | U21: =SUM(U7:U19) -> 42429.823 | V21: =SUM(V7:V19) -> 47009.244 | W21: =SUM(W7:W19) -> 47009.244 | ... AA21: =SUM(AA7:AA19) -> 52504.55 | AC21: =SUM(AC7:AC19) -> 0 | AD21: =SUM(AD7:AD19) -> 0 | AE21: =SUM(AE7:AE19) -> 0 | AF21: =SUM(AF7:AF19) -> 0 | AG21: =SUM(AG7:AG19) -> 0 | AH21: =SUM(AH7:AH19) -> 0 | AI21: =SUM(AI7:AI19) -> 0 | AJ21: =SUM(AJ7:AJ19) -> 0 | ... AN21: =SUM(AN7:AN19) -> 0

Sheet Sales Assumptions
A1: =KeyInputs!F14 -> 0
A2: Sales Assumptions

Sheet Sales (UK)
A1: =KeyInputs!F14 -> 0
A2: Sales (UK)
C4: =KeyInputs!F17 -> 42005 | P4: =KeyInputs!F17+1 -> 42006 | AC4: =KeyInputs!F17+2 -> 42007
